{
  "type": "Feature",
  "properties": {
    "iso:country":"US",
    "sg:address":"11400 N Warren St",
    "sg:city":"Hayden",
    "sg:classifiers":[
        {
            "category":"Shopping",
            "subcategory":"Hobbies, Toys, & Games",
            "type":"Retail Goods"
        }
    ],
    "sg:phone":"+1 208 762 8166",
    "sg:postcode":"83835",
    "sg:province":"ID",
    "sg:tags":[
        "model",
        "supply"
    ],
    "wof:name":"TNT Rc Hobbies",
    "wof:placetype":"venue"
},
  "geometry": {"coordinates":[-116.791873,47.775896],"type":"Point"}
}