{
  "type": "Feature",
  "properties": {
    "iso:country":"US",
    "sg:address":"1270 W Cove Rd",
    "sg:city":"Viola",
    "sg:classifiers":[
        {
            "category":"Farming",
            "subcategory":"Farm & Veterinary Services",
            "type":"Manufacturing & Wholesale Goods"
        }
    ],
    "sg:phone":"+1 208 858 2103",
    "sg:postcode":"83872",
    "sg:province":"ID",
    "sg:tags":[
        "breeder",
        "livestock"
    ],
    "sg:website":"http://www.sheepskinsnyarn.com",
    "wof:name":"Jerrylee Farm",
    "wof:placetype":"venue"
},
  "geometry": {"coordinates":[-117.025582,46.902514],"type":"Point"}
}