{
  "type": "Feature",
  "properties": {
    "iso:country":"US",
    "sg:address":"850 Shoshone St W",
    "sg:city":"Twin Falls",
    "sg:classifiers":[
        {
            "category":"Food & Beverages",
            "subcategory":"Groceries & Convenience Stores",
            "type":"Retail Goods"
        }
    ],
    "sg:phone":"+1 208 733 8987",
    "sg:postcode":"83301",
    "sg:province":"ID",
    "sg:tags":[
        "grocer"
    ],
    "wof:name":"Swensen's Magic Markets Inc",
    "wof:placetype":"venue"
},
  "geometry": {"coordinates":[-114.478224,42.549899],"type":"Point"}
}