{
  "type": "Feature",
  "properties": {
    "addr:full":"3930 E 2000 N Sugar City ID 83448",
    "addr:housenumber":"3930",
    "addr:postcode":"83448",
    "addr:street":"E 2000 N",
    "iso:country":"US",
    "sg:address":"3930 E 2000 N",
    "sg:city":"Sugar City",
    "sg:phone":"+1 208 356 3178",
    "sg:postcode":"83448",
    "sg:province":"ID",
    "sg:tags":[
        "farm",
        "irish",
        "potato"
    ],
    "wof:name":"Wahoo Corp",
    "wof:placetype":"venue"
},
  "geometry": {"coordinates":[-111.69981199999999,43.854704],"type":"Point"}
}