{
  "type": "Feature",
  "properties": {
    "iso:country":"US",
    "sg:address":"201 E 50th St",
    "sg:city":"Boise",
    "sg:classifiers":[
        {
            "category":"Utilities",
            "subcategory":"Water",
            "type":"Services"
        }
    ],
    "sg:phone":"+1 208 472 2930",
    "sg:postcode":"83714",
    "sg:province":"ID",
    "sg:tags":[
        "company",
        "sewage"
    ],
    "wof:name":"Garden City Water Dept",
    "wof:placetype":"venue"
},
  "geometry": {"coordinates":[-116.266697,43.643095],"type":"Point"}
}