{
  "type": "Feature",
  "properties": {
    "iso:country":"US",
    "sg:address":"3359 N 5th W",
    "sg:city":"Idaho Falls",
    "sg:classifiers":[
        {
            "category":"Professional",
            "type":"Services"
        }
    ],
    "sg:phone":"+1 208 535 0755",
    "sg:postcode":"83401",
    "sg:province":"ID",
    "wof:name":"Melven J Haroldsen",
    "wof:placetype":"venue"
},
  "geometry": {"coordinates":[-112.043264,43.525597],"type":"Point"}
}