{
  "type": "Feature",
  "properties": {
    "iso:country":"US",
    "sg:address":"3210 N Government Way",
    "sg:city":"Coeur D Alene",
    "sg:classifiers":[
        {
            "category":"Banks & Credit Unions",
            "subcategory":"Bank",
            "type":"Services"
        }
    ],
    "sg:phone":"+1 208 667 3990",
    "sg:postcode":"83815",
    "sg:province":"ID",
    "sg:tags":[
        "business",
        "cashing",
        "institution",
        "banking",
        "depository",
        "check",
        "se"
    ],
    "wof:name":"First Choice Title Loan & Chck",
    "wof:placetype":"venue"
},
  "geometry": {"coordinates":[-116.786404,47.707239],"type":"Point"}
}