{
  "type": "Feature",
  "properties": {
    "addr:full":"1480 State Hwy 22 Howe ID 83244",
    "addr:housenumber":"1480",
    "addr:postcode":"83244",
    "addr:street":"State Hwy 22",
    "iso:country":"US",
    "sg:address":"1480 State Hwy 22",
    "sg:city":"Howe",
    "sg:classifiers":[
        {
            "category":"Farming",
            "subcategory":"Farm",
            "type":"Manufacturing & Wholesale Goods"
        }
    ],
    "sg:phone":"+1 208 767 3128",
    "sg:postcode":"83244",
    "sg:province":"ID",
    "wof:name":"Isham Farms",
    "wof:placetype":"venue"
},
  "geometry": {"coordinates":[-112.996019,43.783396],"type":"Point"}
}