{
  "type": "Feature",
  "properties": {
    "addr:full":"601 N Orchard St Boise ID 83706",
    "addr:housenumber":"601",
    "addr:postcode":"83706",
    "addr:street":"N Orchard St",
    "iso:country":"US",
    "sg:address":"601 N Orchard St",
    "sg:city":"Boise",
    "sg:classifiers":[
        {
            "category":"Home & Garden",
            "subcategory":"Furniture",
            "type":"Retail Goods"
        }
    ],
    "sg:phone":"+1 208 377 8454",
    "sg:postcode":"83706",
    "sg:province":"ID",
    "wof:name":"Bargain Station Furniture",
    "wof:placetype":"venue"
},
  "geometry": {"coordinates":[-116.243454,43.610707],"type":"Point"}
}