{
  "type": "Feature",
  "properties": {
    "iso:country":"US",
    "sg:address":"5140 E Seltice Way",
    "sg:city":"Post Falls",
    "sg:classifiers":[
        {
            "category":"Wholesale",
            "subcategory":"Office Equipment",
            "type":"Manufacturing & Wholesale Goods"
        }
    ],
    "sg:phone":"+1 208 773 1691",
    "sg:postcode":"83854",
    "sg:province":"ID",
    "sg:tags":[
        "machine",
        "duplicating",
        "copying"
    ],
    "wof:name":"H & H Business Systems Inc",
    "wof:placetype":"venue"
},
  "geometry": {"coordinates":[-116.881406,47.706132],"type":"Point"}
}