{
  "type": "Feature",
  "properties": {
    "iso:country":"US",
    "sg:address":"525 W 19th St",
    "sg:city":"Idaho Falls",
    "sg:classifiers":[
        {
            "category":"Building & Trades",
            "subcategory":"Electrical",
            "type":"Services"
        }
    ],
    "sg:phone":"+1 208 524 5611",
    "sg:postcode":"83402",
    "sg:province":"ID",
    "sg:tags":[
        "electric",
        "contractor"
    ],
    "wof:name":"Oakey Electric",
    "wof:placetype":"venue"
},
  "geometry": {"coordinates":[-112.043877,43.480922],"type":"Point"}
}