{
  "type": "Feature",
  "properties": {
    "iso:country":"US",
    "sg:address":"205 N Berkley St",
    "sg:city":"Council",
    "sg:classifiers":[
        {
            "category":"Health Services",
            "subcategory":"Hospital",
            "type":"Services"
        }
    ],
    "sg:phone":"+1 208 253 6850",
    "sg:postcode":"83612",
    "sg:province":"ID",
    "sg:tags":[
        "mental"
    ],
    "wof:name":"Adams County Behavioral Health",
    "wof:placetype":"venue"
},
  "geometry": {"coordinates":[-116.43040000000001,44.73184],"type":"Point"}
}