{
  "type": "Feature",
  "properties": {
    "iso:country":"US",
    "sg:address":"3202 N 4th St",
    "sg:city":"Coeur D Alene",
    "sg:classifiers":[
        {
            "category":"Shopping",
            "subcategory":"Florist",
            "type":"Retail Goods"
        }
    ],
    "sg:phone":"+1 208 667 7019",
    "sg:postcode":"83815",
    "sg:province":"ID",
    "wof:name":"Betty & Ev Floral",
    "wof:placetype":"venue"
},
  "geometry": {"coordinates":[-116.78094,47.705799],"type":"Point"}
}