{
  "type": "Feature",
  "properties": {
    "addr:full":"224 16th Ave N Nampa ID 83687",
    "addr:housenumber":"224",
    "addr:postcode":"83687",
    "addr:street":"16Th Ave N",
    "iso:country":"US",
    "sg:address":"224 16th Ave N",
    "sg:city":"Nampa",
    "sg:classifiers":[
        {
            "category":"Retail",
            "subcategory":"Auto Repair",
            "type":"Services"
        }
    ],
    "sg:phone":"+1 208 466 1965",
    "sg:postcode":"83687",
    "sg:province":"ID",
    "sg:tags":[
        "automotive"
    ],
    "wof:name":"A-1 Radiator & Muffler Shop",
    "wof:placetype":"venue"
},
  "geometry": {"coordinates":[-116.55117799999999,43.579271],"type":"Point"}
}