{
  "type": "Feature",
  "properties": {
    "iso:country":"US",
    "sg:address":"1404 E F St",
    "sg:city":"Moscow",
    "sg:classifiers":[
        {
            "category":"Real Estate",
            "subcategory":"Architect",
            "type":"Services"
        }
    ],
    "sg:phone":"+1 208 883 3276",
    "sg:postcode":"83843",
    "sg:province":"ID",
    "wof:name":"Full Circle Studios",
    "wof:placetype":"venue"
},
  "geometry": {"coordinates":[-116.982958,46.740379],"type":"Point"}
}