{
  "type": "Feature",
  "properties": {
    "iso:country":"US",
    "sg:address":"3134 S 1900 E",
    "sg:city":"Wendell",
    "sg:classifiers":[
        {
            "category":"Wholesale",
            "subcategory":"Farm Supplies",
            "type":"Manufacturing & Wholesale Goods"
        }
    ],
    "sg:phone":"+1 208 536 6185",
    "sg:postcode":"83355",
    "sg:province":"ID",
    "sg:tags":[
        "livestock"
    ],
    "wof:name":"Sherman Young Livestock",
    "wof:placetype":"venue"
},
  "geometry": {"coordinates":[-114.71386800000001,42.748751],"type":"Point"}
}