{
  "type": "Feature",
  "properties": {
    "iso:country":"US",
    "sg:address":"904 E White Ave",
    "sg:city":"Moscow",
    "sg:classifiers":[
        {
            "category":"Organizations",
            "subcategory":"Religious Organization",
            "type":"Services"
        }
    ],
    "sg:phone":"+1 208 882 9411",
    "sg:postcode":"83843",
    "sg:province":"ID",
    "sg:tags":[
        "church"
    ],
    "wof:name":"Kingdom Hall-Jehovah's Witness",
    "wof:placetype":"venue"
},
  "geometry": {"coordinates":[-116.987762,46.722866],"type":"Point"}
}