{
  "type": "Feature",
  "properties": {
    "iso:country":"US",
    "sg:address":"1301 E 17th St",
    "sg:city":"Idaho Falls",
    "sg:classifiers":[
        {
            "category":"Building & Trades",
            "subcategory":"Construction",
            "type":"Services"
        }
    ],
    "sg:phone":"+1 208 529 0700",
    "sg:postcode":"83404",
    "sg:province":"ID",
    "sg:tags":[
        "home",
        "builder"
    ],
    "wof:name":"Homestead Construction",
    "wof:placetype":"venue"
},
  "geometry": {"coordinates":[-112.01009,43.482559],"type":"Point"}
}