{
  "type": "Feature",
  "properties": {
    "iso:country":"US",
    "sg:address":"55734 State Hwy 97",
    "sg:city":"Saint Maries",
    "sg:phone":"+1 208 689 3078",
    "sg:postcode":"83861",
    "sg:province":"ID",
    "sg:tags":[
        "beef",
        "farm",
        "crop",
        "field",
        "cattle",
        "feedlot"
    ],
    "wof:name":"Tom Christensen",
    "wof:placetype":"venue"
},
  "geometry": {"coordinates":[-116.733143,47.436832],"type":"Point"}
}