{
  "type": "Feature",
  "properties": {
    "addr:full":"703 Warm Springs Rd Ketchum ID 83340",
    "addr:housenumber":"703",
    "addr:postcode":"83340",
    "addr:street":"Warm Springs Rd",
    "iso:country":"US",
    "sg:address":"703 Warm Springs Rd",
    "sg:city":"Ketchum",
    "sg:classifiers":[
        {
            "category":"Restaurant",
            "type":"Food & Drink"
        }
    ],
    "sg:phone":"+1 208 726 4213",
    "sg:postcode":"83340",
    "sg:province":"ID",
    "wof:name":"Mama Inez",
    "wof:placetype":"venue"
},
  "geometry": {"coordinates":[-114.36708299999999,43.682719],"type":"Point"}
}