{
  "type": "Feature",
  "properties": {
    "iso:country":"US",
    "sg:address":"703 Warm Springs Rd",
    "sg:city":"Ketchum",
    "sg:classifiers":[
        {
            "category":"Restaurant",
            "type":"Food & Drink"
        }
    ],
    "sg:phone":"+1 208 726 4213",
    "sg:postcode":"83340",
    "sg:province":"ID",
    "wof:name":"Mama Inez",
    "wof:placetype":"venue"
},
  "geometry": {"coordinates":[-114.367083,43.682719],"type":"Point"}
}