{
  "type": "Feature",
  "properties": {
    "iso:country":"US",
    "sg:address":"720 S Main St",
    "sg:city":"Bellevue",
    "sg:classifiers":[
        {
            "category":"Retail",
            "subcategory":"Auto Rental",
            "type":"Services"
        }
    ],
    "sg:phone":"+1 208 788 3224",
    "sg:postcode":"83313",
    "sg:province":"ID",
    "sg:tags":[
        "renting",
        "automobile"
    ],
    "wof:name":"Suv Auto Rental",
    "wof:placetype":"venue"
},
  "geometry": {"coordinates":[-114.310465,43.513123],"type":"Point"}
}