{
  "type": "Feature",
  "properties": {
    "addr:full":"104 E 46th St Boise ID 83714",
    "addr:housenumber":"104",
    "addr:postcode":"83714",
    "addr:street":"E 46Th St",
    "iso:country":"US",
    "sg:address":"104 E 46th St",
    "sg:city":"Boise",
    "sg:classifiers":[
        {
            "category":"Retail",
            "subcategory":"Auto Repair",
            "type":"Services"
        }
    ],
    "sg:phone":"+1 208 378 4500",
    "sg:postcode":"83714",
    "sg:province":"ID",
    "sg:tags":[
        "muffler",
        "exhaust",
        "system"
    ],
    "wof:name":"Ammerman's Custom Exhaust",
    "wof:placetype":"venue"
},
  "geometry": {"coordinates":[-116.25462899999999,43.639002],"type":"Point"}
}