{
  "type": "Feature",
  "properties": {
    "addr:full":"1336 W 4th St Weiser ID 83672",
    "addr:housenumber":"1336",
    "addr:postcode":"83672",
    "addr:street":"W 4Th St",
    "iso:country":"US",
    "sg:address":"1336 W 4th St",
    "sg:city":"Weiser",
    "sg:classifiers":[
        {
            "category":"Professional",
            "subcategory":"Lawyer & Legal Services",
            "type":"Services"
        }
    ],
    "sg:phone":"+1 208 549 0430",
    "sg:postcode":"83672",
    "sg:province":"ID",
    "wof:name":"J L Jones Prof Sus",
    "wof:placetype":"venue"
},
  "geometry": {"coordinates":[-116.974127,44.255451],"type":"Point"}
}