{
  "type": "Feature",
  "properties": {
    "iso:country":"US",
    "sg:address":"523 S Main St",
    "sg:city":"Troy",
    "sg:classifiers":[
        {
            "category":"Personal",
            "subcategory":"Beauty Salon",
            "type":"Services"
        }
    ],
    "sg:phone":"+1 208 835 4777",
    "sg:postcode":"83871",
    "sg:province":"ID",
    "wof:name":"Home Town Hair",
    "wof:placetype":"venue"
},
  "geometry": {"coordinates":[-116.767079,46.734364],"type":"Point"}
}