{
  "type": "Feature",
  "properties": {
    "addr:full":"6883 Overland Rd Boise ID 83709",
    "addr:housenumber":"6883",
    "addr:postcode":"83709",
    "addr:street":"Overland Rd",
    "iso:country":"US",
    "sg:address":"6883 Overland Rd",
    "sg:city":"Boise",
    "sg:classifiers":[
        {
            "category":"Shopping",
            "subcategory":"Department Store",
            "type":"Retail Goods"
        }
    ],
    "sg:phone":"+1 208 322 7585",
    "sg:postcode":"83709",
    "sg:province":"ID",
    "sg:tags":[
        "shop"
    ],
    "wof:name":"Only One Dollar",
    "wof:placetype":"venue"
},
  "geometry": {"coordinates":[-116.270691,43.59009],"type":"Point"}
}