{
  "type": "Feature",
  "properties": {
    "iso:country":"US",
    "sg:address":"3301 E Chicago St",
    "sg:city":"Caldwell",
    "sg:classifiers":[
        {
            "category":"Building & Trades",
            "subcategory":"Construction",
            "type":"Services"
        }
    ],
    "sg:phone":"+1 208 465 5993",
    "sg:postcode":"83605",
    "sg:province":"ID",
    "sg:tags":[
        "downspouts",
        "gutter"
    ],
    "wof:name":"Advanced Continuous Gutters",
    "wof:placetype":"venue"
},
  "geometry": {"coordinates":[-116.655923,43.650942],"type":"Point"}
}