{
  "type": "Feature",
  "properties": {
    "iso:country":"US",
    "sg:address":"695 N Shady Grove Way",
    "sg:city":"Kuna",
    "sg:classifiers":[
        {
            "category":"Building & Trades",
            "subcategory":"Construction",
            "type":"Services"
        }
    ],
    "sg:phone":"+1 208 922 5326",
    "sg:postcode":"83634",
    "sg:province":"ID",
    "sg:tags":[
        "residential",
        "remodel",
        "contractor"
    ],
    "wof:name":"L C Home Improvement",
    "wof:placetype":"venue"
},
  "geometry": {"coordinates":[-116.41138100000001,43.493679],"type":"Point"}
}