{
  "type": "Feature",
  "properties": {
    "addr:full":"2362 Blacktail Rd Cocolalla ID 83813",
    "addr:housenumber":"2362",
    "addr:postcode":"83813",
    "addr:street":"Blacktail Rd",
    "iso:country":"US",
    "sg:address":"2362 Blacktail Rd",
    "sg:city":"Cocolalla",
    "sg:classifiers":[
        {
            "category":"Retail",
            "subcategory":"Portrait Studio",
            "type":"Services"
        }
    ],
    "sg:phone":"+1 208 263 2874",
    "sg:postcode":"83813",
    "sg:province":"ID",
    "sg:tags":[
        "photographer"
    ],
    "wof:name":"Creative Impressions",
    "wof:placetype":"venue"
},
  "geometry": {"coordinates":[-116.594098,48.114931],"type":"Point"}
}