{
  "type": "Feature",
  "properties": {
    "iso:country":"US",
    "sg:address":"1405 Industrial Way",
    "sg:city":"Caldwell",
    "sg:classifiers":[
        {
            "category":"Wholesale",
            "subcategory":"Construction Materials",
            "type":"Manufacturing & Wholesale Goods"
        }
    ],
    "sg:phone":"+1 208 454 8702",
    "sg:postcode":"83605",
    "sg:province":"ID",
    "sg:tags":[
        "marble"
    ],
    "sg:website":"www.custommarble.cc",
    "wof:name":"Custom Marble & Solid Surfaces",
    "wof:placetype":"venue"
},
  "geometry": {"coordinates":[-116.655337,43.654196],"type":"Point"}
}