{
  "type": "Feature",
  "properties": {
    "iso:country":"US",
    "sg:address":"1375 E Braemere Rd",
    "sg:city":"Boise",
    "sg:classifiers":[
        {
            "category":"Real Estate",
            "subcategory":"Real Estate Operator",
            "type":"Services"
        }
    ],
    "sg:phone":"+1 208 343 3926",
    "sg:postcode":"83702",
    "sg:province":"ID",
    "sg:tags":[
        "property",
        "lessor"
    ],
    "wof:name":"Jay Hill",
    "wof:placetype":"venue"
},
  "geometry": {"coordinates":[-116.17433699999999,43.653194],"type":"Point"}
}