{
  "type": "Feature",
  "properties": {
    "addr:full":"130 E Maple St Shelley ID 83274",
    "addr:housenumber":"130",
    "addr:postcode":"83274",
    "addr:street":"E Maple St",
    "iso:country":"US",
    "sg:address":"130 E Maple St",
    "sg:city":"Shelley",
    "sg:classifiers":[
        {
            "category":"Banks & Credit Unions",
            "subcategory":"Bank",
            "type":"Services"
        }
    ],
    "sg:phone":"+1 208 357 0888",
    "sg:postcode":"83274",
    "sg:province":"ID",
    "sg:tags":[
        "cashing",
        "check"
    ],
    "wof:name":"Checks R Us",
    "wof:placetype":"venue"
},
  "geometry": {"coordinates":[-112.122428,43.383054],"type":"Point"}
}