{
  "type": "Feature",
  "properties": {
    "iso:country":"US",
    "sg:address":"950 Allumbaugh St",
    "sg:city":"Boise",
    "sg:classifiers":[
        {
            "category":"Real Estate",
            "subcategory":"Real Estate Operator",
            "type":"Services"
        }
    ],
    "sg:phone":"+1 208 323 2121",
    "sg:postcode":"83704",
    "sg:province":"ID",
    "sg:tags":[
        "apartment"
    ],
    "wof:name":"Deer Creek Apartments",
    "wof:placetype":"venue"
},
  "geometry": {"coordinates":[-116.26615200000001,43.613516],"type":"Point"}
}