{
  "type": "Feature",
  "properties": {
    "addr:full":"6833 el Paso St Bonners Ferry ID 83805",
    "addr:housenumber":"6833",
    "addr:postcode":"83805",
    "addr:street":"El Paso St",
    "iso:country":"US",
    "sg:address":"6833 el Paso St",
    "sg:city":"Bonners Ferry",
    "sg:classifiers":[
        {
            "category":"Health Services",
            "subcategory":"Doctor",
            "type":"Services"
        }
    ],
    "sg:phone":"+1 208 267 3773",
    "sg:postcode":"83805",
    "sg:province":"ID",
    "sg:tags":[
        "physician",
        "surgeon"
    ],
    "wof:name":"Sandpoint Pediatrics",
    "wof:placetype":"venue"
},
  "geometry": {"coordinates":[-116.316185,48.685936],"type":"Point"}
}