{
  "type": "Feature",
  "properties": {
    "addr:full":"2175 Centurion Pl Boise ID 83709",
    "addr:housenumber":"2175",
    "addr:postcode":"83709",
    "addr:street":"Centurion Pl",
    "iso:country":"US",
    "sg:address":"2175 Centurion Pl",
    "sg:city":"Boise",
    "sg:classifiers":[
        {
            "category":"Autos & Motor Vehicles",
            "subcategory":"Auto Supplies",
            "type":"Retail Goods"
        }
    ],
    "sg:phone":"+1 208 378 8183",
    "sg:postcode":"83709",
    "sg:province":"ID",
    "sg:tags":[
        "automobile",
        "parts"
    ],
    "wof:name":"Idaho Transmission Warehouse",
    "wof:placetype":"venue"
},
  "geometry": {"coordinates":[-116.27166,43.583879],"type":"Point"}
}