{
  "type": "Feature",
  "properties": {
    "iso:country":"US",
    "sg:address":"5983 W State St",
    "sg:city":"Boise",
    "sg:classifiers":[
        {
            "category":"Banks & Credit Unions",
            "subcategory":"Bank",
            "type":"Services"
        }
    ],
    "sg:phone":"+1 208 853 4100",
    "sg:postcode":"83703",
    "sg:province":"ID",
    "sg:tags":[
        "loan",
        "real estate"
    ],
    "wof:name":"Specialty Mortgage",
    "wof:placetype":"venue"
},
  "geometry": {"coordinates":[-116.263521,43.658553],"type":"Point"}
}