{
  "type": "Feature",
  "properties": {
    "iso:country":"US",
    "sg:address":"1755 N Westgate Dr",
    "sg:city":"Boise",
    "sg:classifiers":[
        {
            "category":"Banks & Credit Unions",
            "subcategory":"Bank",
            "type":"Services"
        }
    ],
    "sg:phone":"+1 208 375 0060",
    "sg:postcode":"83704",
    "sg:province":"ID",
    "sg:tags":[
        "loan"
    ],
    "wof:name":"Nationwide Mortgage Inc",
    "wof:placetype":"venue"
},
  "geometry": {"coordinates":[-116.2808,43.621185],"type":"Point"}
}