{
  "type": "Feature",
  "properties": {
    "iso:country":"US",
    "sg:address":"704 N Hwy 91",
    "sg:city":"Firth",
    "sg:classifiers":[
        {
            "category":"Wholesale",
            "subcategory":"Machinery & Supplies",
            "type":"Manufacturing & Wholesale Goods"
        }
    ],
    "sg:phone":"+1 208 346 6545",
    "sg:postcode":"83236",
    "sg:province":"ID",
    "sg:tags":[
        "equipment",
        "dairy"
    ],
    "wof:name":"Russ Dial Construction",
    "wof:placetype":"venue"
},
  "geometry": {"coordinates":[-112.18915,43.299923],"type":"Point"}
}