{
  "type": "Feature",
  "properties": {
    "iso:country":"US",
    "sg:address":"2035 Eagle Dr",
    "sg:city":"Ammon",
    "sg:classifiers":[
        {
            "category":"Recreation",
            "type":"Entertainment"
        }
    ],
    "sg:phone":"+1 208 552 6392",
    "sg:postcode":"83406",
    "sg:province":"ID",
    "sg:tags":[
        "psychic",
        "medium"
    ],
    "wof:name":"Sweet Serenity",
    "wof:placetype":"venue"
},
  "geometry": {"coordinates":[-111.980496,43.477774],"type":"Point"}
}