{
  "type": "Feature",
  "properties": {
    "iso:country":"US",
    "sg:address":"1716 Parkwood St",
    "sg:city":"Idaho Falls",
    "sg:classifiers":[
        {
            "category":"Health Services",
            "subcategory":"Health Practitioner",
            "type":"Services"
        }
    ],
    "sg:phone":"+1 208 524 2285",
    "sg:postcode":"83401",
    "sg:province":"ID",
    "wof:name":"Joann Hammond",
    "wof:placetype":"venue"
},
  "geometry": {"coordinates":[-112.00015399999999,43.490269],"type":"Point"}
}