{
  "type": "Feature",
  "properties": {
    "iso:country":"US",
    "sg:address":"3214 Acre Ln",
    "sg:city":"Boise",
    "sg:classifiers":[
        {
            "category":"Social Services",
            "subcategory":"Child Care",
            "type":"Services"
        }
    ],
    "sg:phone":"+1 208 376 7846",
    "sg:postcode":"83704",
    "sg:province":"ID",
    "sg:website":"www.sandcastleslc.com",
    "wof:name":"Sandcastles",
    "wof:placetype":"venue"
},
  "geometry": {"coordinates":[-116.27231399999999,43.635456],"type":"Point"}
}