{
  "type": "Feature",
  "properties": {
    "addr:full":"2105 12th Ave Rd Nampa ID 83686",
    "addr:housenumber":"2105",
    "addr:postcode":"83686",
    "addr:street":"12Th Ave Rd",
    "iso:country":"US",
    "sg:address":"2105 12th Ave Rd",
    "sg:city":"Nampa",
    "sg:classifiers":[
        {
            "category":"Health Services",
            "subcategory":"Nursing And Care Facility",
            "type":"Services"
        }
    ],
    "sg:phone":"+1 208 467 5721",
    "sg:postcode":"83686",
    "sg:province":"ID",
    "sg:tags":[
        "home",
        "convalescent"
    ],
    "wof:name":"Holly Nursing & Rehab",
    "wof:placetype":"venue"
},
  "geometry": {"coordinates":[-116.572866,43.54916],"type":"Point"}
}