{
  "type": "Feature",
  "properties": {
    "addr:full":"106 E Poplar Ave Coeur D Alene ID 83814",
    "addr:housenumber":"106",
    "addr:postcode":"83814",
    "addr:street":"E Poplar Ave",
    "iso:country":"US",
    "sg:address":"106 E Poplar Ave",
    "sg:city":"Coeur D Alene",
    "sg:classifiers":[
        {
            "category":"Building & Trades",
            "subcategory":"Construction",
            "type":"Services"
        }
    ],
    "sg:phone":"+1 208 667 5560",
    "sg:postcode":"83814",
    "sg:province":"ID",
    "sg:tags":[
        "general",
        "contractor"
    ],
    "sg:website":"www.ginnoconstruction.com",
    "wof:name":"Ginno Construction",
    "wof:placetype":"venue"
},
  "geometry": {"coordinates":[-116.78554800000001,47.692072],"type":"Point"}
}