{
  "type": "Feature",
  "properties": {
    "addr:full":"108 W 31st St Boise ID 83714",
    "addr:housenumber":"108",
    "addr:postcode":"83714",
    "addr:street":"W 31St St",
    "iso:country":"US",
    "sg:address":"108 W 31st St",
    "sg:city":"Boise",
    "sg:classifiers":[
        {
            "category":"Manufacturing",
            "subcategory":"Glass & Minerals",
            "type":"Manufacturing & Wholesale Goods"
        }
    ],
    "sg:phone":"+1 208 426 8775",
    "sg:postcode":"83714",
    "sg:province":"ID",
    "wof:name":"Technical Glass Svc Inc",
    "wof:placetype":"venue"
},
  "geometry": {"coordinates":[-116.237611,43.619815],"type":"Point"}
}