{
  "type": "Feature",
  "properties": {
    "iso:country":"US",
    "sg:address":"2054 Century Way",
    "sg:city":"Boise",
    "sg:classifiers":[
        {
            "category":"Building & Trades",
            "subcategory":"Construction",
            "type":"Services"
        }
    ],
    "sg:phone":"+1 208 322 2500",
    "sg:postcode":"83709",
    "sg:province":"ID",
    "sg:tags":[
        "roofing",
        "contractor"
    ],
    "wof:name":"Modern Roofing",
    "wof:placetype":"venue"
},
  "geometry": {"coordinates":[-116.272217,43.584064],"type":"Point"}
}