{
  "type": "Feature",
  "properties": {
    "iso:country":"US",
    "sg:address":"235 N Almon St",
    "sg:city":"Moscow",
    "sg:classifiers":[
        {
            "category":"Social Services",
            "subcategory":"Child Care",
            "type":"Services"
        }
    ],
    "sg:phone":"+1 208 882 8687",
    "sg:postcode":"83843",
    "sg:province":"ID",
    "wof:name":"Tots R Tops",
    "wof:placetype":"venue"
},
  "geometry": {"coordinates":[-117.00413500000001,46.735211],"type":"Point"}
}