{
  "type": "Feature",
  "properties": {
    "addr:full":"2113 Windancer Ct Nampa ID 83686",
    "addr:housenumber":"2113",
    "addr:postcode":"83686",
    "addr:street":"Windancer Ct",
    "iso:country":"US",
    "sg:address":"2113 Windancer Ct",
    "sg:city":"Nampa",
    "sg:classifiers":[
        {
            "category":"Professional",
            "subcategory":"Management & Consulting",
            "type":"Services"
        }
    ],
    "sg:phone":"+1 208 468 9775",
    "sg:postcode":"83686",
    "sg:province":"ID",
    "sg:tags":[
        "business"
    ],
    "wof:name":"Caffrey Consulting",
    "wof:placetype":"venue"
},
  "geometry": {"coordinates":[-116.585403,43.548682],"type":"Point"}
}