{
  "type": "Feature",
  "properties": {
    "addr:full":"147 S 1st W Rexburg ID 83440",
    "addr:housenumber":"147",
    "addr:postcode":"83440",
    "addr:street":"S 1St W",
    "iso:country":"US",
    "sg:address":"147 S 1st W",
    "sg:city":"Rexburg",
    "sg:classifiers":[
        {
            "category":"Shopping",
            "subcategory":"Bicycles & Sporting Goods",
            "type":"Retail Goods"
        }
    ],
    "sg:phone":"+1 208 356 6212",
    "sg:postcode":"83440",
    "sg:province":"ID",
    "sg:tags":[
        "equipment",
        "archery",
        "supply"
    ],
    "wof:name":"Brunson Electric Pro Archery",
    "wof:placetype":"venue"
},
  "geometry": {"coordinates":[-111.786632,43.822958],"type":"Point"}
}