{
  "type": "Feature",
  "properties": {
    "addr:full":"2203 University Dr Boise ID 83706",
    "addr:housenumber":"2203",
    "addr:postcode":"83706",
    "addr:street":"University Dr",
    "iso:country":"US",
    "sg:address":"2203 University Dr",
    "sg:city":"Boise",
    "sg:classifiers":[
        {
            "category":"Restaurant",
            "type":"Food & Drink"
        }
    ],
    "sg:phone":"+1 208 344 5905",
    "sg:postcode":"83706",
    "sg:province":"ID",
    "wof:name":"Shanghai",
    "wof:placetype":"venue"
},
  "geometry": {"coordinates":[-116.209484,43.604892],"type":"Point"}
}