{
  "type": "Feature",
  "properties": {
    "iso:country":"US",
    "sg:address":"1087 River St",
    "sg:city":"Boise",
    "sg:classifiers":[
        {
            "category":"Banks & Credit Unions",
            "subcategory":"Investment Brokerage",
            "type":"Services"
        }
    ],
    "sg:phone":"+1 208 338 6900",
    "sg:postcode":"83702",
    "sg:province":"ID",
    "sg:tags":[
        "security"
    ],
    "sg:website":"www.morganstanley.com",
    "wof:name":"Morgan Stanley",
    "wof:placetype":"venue"
},
  "geometry": {"coordinates":[-116.21114799999999,43.61179],"type":"Point"}
}