{
  "type": "Feature",
  "properties": {
    "addr:full":"218 W Cameron Ave Kellogg ID 83837",
    "addr:housenumber":"218",
    "addr:postcode":"83837",
    "addr:street":"W Cameron Ave",
    "iso:country":"US",
    "sg:address":"218 W Cameron Ave",
    "sg:city":"Kellogg",
    "sg:classifiers":[
        {
            "category":"Real Estate",
            "subcategory":"Real Estate Agent",
            "type":"Services"
        }
    ],
    "sg:phone":"+1 208 786 2241",
    "sg:postcode":"83837",
    "sg:province":"ID",
    "sg:tags":[
        "management"
    ],
    "wof:name":"Valley Investment Property Mgt",
    "wof:placetype":"venue"
},
  "geometry": {"coordinates":[-116.123721,47.541279],"type":"Point"}
}