{
  "type": "Feature",
  "properties": {
    "iso:country":"US",
    "sg:address":"1109 US Hwy 2",
    "sg:city":"Priest River",
    "sg:classifiers":[
        {
            "category":"Autos & Motor Vehicles",
            "subcategory":"Automobile Sales",
            "type":"Retail Goods"
        }
    ],
    "sg:phone":"+1 208 448 0447",
    "sg:postcode":"83856",
    "sg:province":"ID",
    "sg:tags":[
        "used"
    ],
    "wof:name":"Showroom Cars",
    "wof:placetype":"venue"
},
  "geometry": {"coordinates":[-116.92277199999999,48.180528],"type":"Point"}
}