{
  "type": "Feature",
  "properties": {
    "addr:full":"3787 County Line Rd Emmett ID 83617",
    "addr:housenumber":"3787",
    "addr:postcode":"83617",
    "addr:street":"County Line Rd",
    "iso:country":"US",
    "sg:address":"3787 County Line Rd",
    "sg:city":"Emmett",
    "sg:phone":"+1 208 365 4062",
    "sg:postcode":"83617",
    "sg:province":"ID",
    "sg:tags":[
        "equine",
        "beef",
        "farm",
        "crop",
        "field",
        "cattle"
    ],
    "wof:name":"Andy Kendall",
    "wof:placetype":"venue"
},
  "geometry": {"coordinates":[-116.712355,43.901607],"type":"Point"}
}