{
  "type": "Feature",
  "properties": {
    "iso:country":"US",
    "sg:address":"169 Warren Ave",
    "sg:city":"Pocatello",
    "sg:classifiers":[
        {
            "category":"Retail",
            "subcategory":"Auto Repair",
            "type":"Services"
        }
    ],
    "sg:phone":"+1 208 232 6391",
    "sg:postcode":"83201",
    "sg:province":"ID",
    "sg:tags":[
        "repairing",
        "automobile"
    ],
    "wof:name":"Stacy's Place",
    "wof:placetype":"venue"
},
  "geometry": {"coordinates":[-112.449093,42.877457],"type":"Point"}
}