{
  "type": "Feature",
  "properties": {
    "iso:country":"US",
    "sg:address":"1975 Belmont Ave",
    "sg:city":"Idaho Falls",
    "sg:classifiers":[
        {
            "category":"Shopping",
            "subcategory":"Beauty & Cosmetics",
            "type":"Retail Goods"
        }
    ],
    "sg:phone":"+1 208 529 1095",
    "sg:postcode":"83404",
    "sg:province":"ID",
    "sg:tags":[
        "merchandise"
    ],
    "wof:name":"Mary Kay Cosmetics",
    "wof:placetype":"venue"
},
  "geometry": {"coordinates":[-111.997378,43.480043],"type":"Point"}
}