{
  "type": "Feature",
  "properties": {
    "addr:full":"4811 Montour Rd Emmett ID 83617",
    "addr:housenumber":"4811",
    "addr:postcode":"83617",
    "addr:street":"Montour Rd",
    "iso:country":"US",
    "sg:address":"4811 Montour Rd",
    "sg:city":"Emmett",
    "sg:classifiers":[
        {
            "category":"Farming",
            "subcategory":"Farm",
            "type":"Manufacturing & Wholesale Goods"
        }
    ],
    "sg:phone":"+1 208 584 3383",
    "sg:postcode":"83617",
    "sg:province":"ID",
    "wof:name":"Volcanic Farms",
    "wof:placetype":"venue"
},
  "geometry": {"coordinates":[-116.338527,43.94099],"type":"Point"}
}