{
  "type": "Feature",
  "properties": {
    "iso:country":"US",
    "sg:address":"670 E 600 N",
    "sg:city":"Firth",
    "sg:classifiers":[
        {
            "category":"Farming",
            "subcategory":"Livestock Farm",
            "type":"Manufacturing & Wholesale Goods"
        }
    ],
    "sg:phone":"+1 208 346 6547",
    "sg:postcode":"83236",
    "sg:province":"ID",
    "sg:tags":[
        "beef",
        "feedlot",
        "cattle"
    ],
    "wof:name":"Dave Telford",
    "wof:placetype":"venue"
},
  "geometry": {"coordinates":[-112.165238,43.282613],"type":"Point"}
}