{
  "type": "Feature",
  "properties": {
    "iso:country":"US",
    "sg:address":"440 Washington Ave",
    "sg:city":"Pocatello",
    "sg:classifiers":[
        {
            "category":"Personal",
            "type":"Services"
        }
    ],
    "sg:phone":"+1 208 233 4004",
    "sg:postcode":"83201",
    "sg:province":"ID",
    "sg:tags":[
        "consultant",
        "program",
        "health",
        "fitness"
    ],
    "wof:name":"Garden Path",
    "wof:placetype":"venue"
},
  "geometry": {"coordinates":[-112.446444,42.883438],"type":"Point"}
}