{
  "type": "Feature",
  "properties": {
    "iso:country":"US",
    "sg:address":"20395 S Main St",
    "sg:city":"Carey",
    "sg:classifiers":[
        {
            "category":"Manufacturing",
            "subcategory":"Building Materials",
            "type":"Manufacturing & Wholesale Goods"
        }
    ],
    "sg:phone":"+1 208 823 4331",
    "sg:postcode":"83320",
    "sg:province":"ID",
    "wof:name":"Idaho Glulam & Mill Work",
    "wof:placetype":"venue"
},
  "geometry": {"coordinates":[-113.945795,43.294828],"type":"Point"}
}