{
  "type": "Feature",
  "properties": {
    "addr:full":"39 N 2nd E Soda Springs ID 83276",
    "addr:housenumber":"39",
    "addr:postcode":"83276",
    "addr:street":"N 2Nd E",
    "iso:country":"US",
    "sg:address":"39 N 2nd E",
    "sg:city":"Soda Springs",
    "sg:classifiers":[
        {
            "category":"Food & Beverages",
            "subcategory":"Groceries & Convenience Stores",
            "type":"Retail Goods"
        }
    ],
    "sg:phone":"+1 208 547 3177",
    "sg:postcode":"83276",
    "sg:province":"ID",
    "sg:tags":[
        "grocer"
    ],
    "sg:website":"www.lallatin.com",
    "wof:name":"Lallatin Food Town",
    "wof:placetype":"venue"
},
  "geometry": {"coordinates":[-111.597622,42.659215],"type":"Point"}
}