{
  "type": "Feature",
  "properties": {
    "iso:country":"US",
    "sg:address":"4546 Daphne St",
    "sg:city":"Meridian",
    "sg:classifiers":[
        {
            "category":"Building & Trades",
            "subcategory":"Plumbing",
            "type":"Services"
        }
    ],
    "sg:phone":"+1 208 884 8785",
    "sg:postcode":"83646",
    "sg:province":"ID",
    "sg:tags":[
        "plumbing",
        "contractor"
    ],
    "wof:name":"Pera's Plumbing Svc",
    "wof:placetype":"venue"
},
  "geometry": {"coordinates":[-116.44926700000001,43.650371],"type":"Point"}
}