{
  "type": "Feature",
  "properties": {
    "iso:country":"US",
    "sg:address":"77 E 100 N",
    "sg:city":"Blackfoot",
    "sg:classifiers":[
        {
            "category":"Farming",
            "subcategory":"Livestock Farm",
            "type":"Manufacturing & Wholesale Goods"
        }
    ],
    "sg:phone":"+1 208 785 6779",
    "sg:postcode":"83221",
    "sg:province":"ID",
    "sg:tags":[
        "feedlot",
        "hog",
        "or",
        "beef",
        "cattle"
    ],
    "wof:name":"Kris Wadsworth",
    "wof:placetype":"venue"
},
  "geometry": {"coordinates":[-112.28275,43.210716],"type":"Point"}
}