{
  "type": "Feature",
  "properties": {
    "addr:full":"8652 Wichita Dr Boise ID 83709",
    "addr:housenumber":"8652",
    "addr:postcode":"83709",
    "addr:street":"Wichita Dr",
    "iso:country":"US",
    "sg:address":"8652 Wichita Dr",
    "sg:city":"Boise",
    "sg:classifiers":[
        {
            "category":"Building & Trades",
            "subcategory":"Cleaning & Sanitation",
            "type":"Services"
        }
    ],
    "sg:phone":"+1 208 375 0001",
    "sg:postcode":"83709",
    "sg:province":"ID",
    "sg:tags":[
        "janitor"
    ],
    "wof:name":"Toby's Cleaning Svc",
    "wof:placetype":"venue"
},
  "geometry": {"coordinates":[-116.292468,43.586206],"type":"Point"}
}