{
  "type": "Feature",
  "properties": {
    "iso:country":"US",
    "sg:address":"480 W 17th St",
    "sg:city":"Idaho Falls",
    "sg:classifiers":[
        {
            "category":"Retail",
            "subcategory":"Auto Repair",
            "type":"Services"
        }
    ],
    "sg:phone":"+1 208 522 8129",
    "sg:postcode":"83402",
    "sg:province":"ID",
    "sg:tags":[
        "body",
        "vehicle"
    ],
    "wof:name":"Classic American Restoration",
    "wof:placetype":"venue"
},
  "geometry": {"coordinates":[-112.041974,43.482827],"type":"Point"}
}