{
  "type": "Feature",
  "properties": {
    "addr:full":"99 W Bridge St Blackfoot ID 83221",
    "addr:housenumber":"99",
    "addr:postcode":"83221",
    "addr:street":"W Bridge St",
    "iso:country":"US",
    "sg:address":"99 W Bridge St",
    "sg:city":"Blackfoot",
    "sg:classifiers":[
        {
            "category":"Shopping",
            "subcategory":"Florist",
            "type":"Retail Goods"
        }
    ],
    "sg:phone":"+1 208 785 2130",
    "sg:postcode":"83221",
    "sg:province":"ID",
    "wof:name":"May's Flowers & Music",
    "wof:placetype":"venue"
},
  "geometry": {"coordinates":[-112.344945,43.188717],"type":"Point"}
}