{
  "type": "Feature",
  "properties": {
    "iso:country":"US",
    "sg:address":"15 N 300 E",
    "sg:city":"Rupert",
    "sg:classifiers":[
        {
            "category":"Farming",
            "subcategory":"Farm & Veterinary Services",
            "type":"Manufacturing & Wholesale Goods"
        }
    ],
    "sg:phone":"+1 208 436 9323",
    "sg:postcode":"83350",
    "sg:province":"ID",
    "sg:tags":[
        "breeder",
        "livestock"
    ],
    "wof:name":"Magic Valley Gamebirds",
    "wof:placetype":"venue"
},
  "geometry": {"coordinates":[-113.60914699999999,42.623061],"type":"Point"}
}