{
  "type": "Feature",
  "properties": {
    "addr:full":"1102 Main St Riggins ID 83549",
    "addr:housenumber":"1102",
    "addr:postcode":"83549",
    "addr:street":"Main St",
    "iso:country":"US",
    "sg:address":"1102 Main St",
    "sg:city":"Riggins",
    "sg:classifiers":[
        {
            "category":"Organizations",
            "subcategory":"Religious Organization",
            "type":"Services"
        }
    ],
    "sg:phone":"+1 208 628 3844",
    "sg:postcode":"83549",
    "sg:province":"ID",
    "sg:tags":[
        "church"
    ],
    "wof:name":"Salmon River Community Church",
    "wof:placetype":"venue"
},
  "geometry": {"coordinates":[-116.312994,45.430022],"type":"Point"}
}