{
  "type": "Feature",
  "properties": {
    "iso:country":"US",
    "sg:address":"500 Sand Hollow Rd",
    "sg:city":"Caldwell",
    "sg:classifiers":[
        {
            "category":"Restaurant",
            "type":"Food & Drink"
        }
    ],
    "sg:phone":"+1 208 454 8686",
    "sg:postcode":"83607",
    "sg:province":"ID",
    "wof:name":"Sandhollow Country Cafe",
    "wof:placetype":"venue"
},
  "geometry": {"coordinates":[-116.748119,43.808457],"type":"Point"}
}