{
  "type": "Feature",
  "properties": {
    "iso:country":"US",
    "sg:address":"521 S Division Ave",
    "sg:city":"Sandpoint",
    "sg:classifiers":[
        {
            "category":"Shopping",
            "subcategory":"Books",
            "type":"Retail Goods"
        }
    ],
    "sg:phone":"+1 208 255 7919",
    "sg:postcode":"83864",
    "sg:province":"ID",
    "sg:tags":[
        "dealer"
    ],
    "wof:name":"Livewire Cafe Christian Books",
    "wof:placetype":"venue"
},
  "geometry": {"coordinates":[-116.567825,48.267624],"type":"Point"}
}