{
  "type": "Feature",
  "properties": {
    "iso:country":"US",
    "sg:address":"623 E Jamaica Ct",
    "sg:city":"Meridian",
    "sg:classifiers":[
        {
            "category":"Wholesale",
            "subcategory":"Machinery & Supplies",
            "type":"Manufacturing & Wholesale Goods"
        }
    ],
    "sg:phone":"+1 208 887 6577",
    "sg:postcode":"83642",
    "sg:province":"ID",
    "sg:tags":[
        "commercial",
        "fan"
    ],
    "wof:name":"Lancoe Industrial Inc",
    "wof:placetype":"venue"
},
  "geometry": {"coordinates":[-116.38624799999999,43.582478],"type":"Point"}
}