{
  "type": "Feature",
  "properties": {
    "iso:country":"US",
    "sg:address":"350 E Cedar St",
    "sg:city":"Pocatello",
    "sg:classifiers":[
        {
            "category":"Personal",
            "type":"Services"
        }
    ],
    "sg:phone":"+1 208 233 2610",
    "sg:postcode":"83201",
    "sg:province":"ID",
    "sg:tags":[
        "therapist",
        "massage"
    ],
    "wof:name":"Human Touch",
    "wof:placetype":"venue"
},
  "geometry": {"coordinates":[-112.450982,42.887856],"type":"Point"}
}