{
  "type": "Feature",
  "properties": {
    "iso:country":"US",
    "sg:address":"4041 W Riverbend Rd",
    "sg:city":"Post Falls",
    "sg:classifiers":[
        {
            "category":"Restaurant",
            "type":"Food & Drink"
        }
    ],
    "sg:phone":"+1 208 773 3086",
    "sg:postcode":"83854",
    "sg:province":"ID",
    "wof:name":"Cabin Restaurant",
    "wof:placetype":"venue"
},
  "geometry": {"coordinates":[-117.00331300000001,47.707394],"type":"Point"}
}