{
  "type": "Feature",
  "properties": {
    "iso:country":"US",
    "sg:address":"1480 Jefferson Ave",
    "sg:city":"Idaho Falls",
    "sg:classifiers":[
        {
            "category":"Organizations",
            "subcategory":"Religious Organization",
            "type":"Services"
        }
    ],
    "sg:phone":"+1 208 524 5534",
    "sg:postcode":"83402",
    "sg:province":"ID",
    "sg:tags":[
        "church"
    ],
    "wof:name":"Jehovah's Witnesses",
    "wof:placetype":"venue"
},
  "geometry": {"coordinates":[-112.043357,43.514863],"type":"Point"}
}