{
  "type": "Feature",
  "properties": {
    "iso:country":"US",
    "sg:address":"210 Triangle Dr",
    "sg:city":"Sandpoint",
    "sg:classifiers":[
        {
            "category":"Personal",
            "subcategory":"Beauty Salon",
            "type":"Services"
        }
    ],
    "sg:phone":"+1 208 263 6110",
    "sg:postcode":"83864",
    "sg:province":"ID",
    "wof:name":"New Agestyling Salon",
    "wof:placetype":"venue"
},
  "geometry": {"coordinates":[-116.54066899999999,48.30349],"type":"Point"}
}