{
  "type": "Feature",
  "properties": {
    "addr:full":"320 N 4th Ave Sandpoint ID 83864",
    "addr:housenumber":"320",
    "addr:postcode":"83864",
    "addr:street":"N 4Th Ave",
    "iso:country":"US",
    "sg:address":"320 N 4th Ave",
    "sg:city":"Sandpoint",
    "sg:classifiers":[
        {
            "category":"Banks & Credit Unions",
            "subcategory":"Bank",
            "type":"Services"
        }
    ],
    "sg:phone":"+1 208 255 4080",
    "sg:postcode":"83864",
    "sg:province":"ID",
    "sg:website":"www.wellsfargo.com",
    "wof:name":"Wells Fargo Bank",
    "wof:placetype":"venue"
},
  "geometry": {"coordinates":[-116.55175199999999,48.275284],"type":"Point"}
}