{
  "type": "Feature",
  "properties": {
    "iso:country":"US",
    "sg:address":"946 E 1450 N",
    "sg:city":"Shelley",
    "sg:classifiers":[
        {
            "category":"Farming",
            "subcategory":"Farm & Veterinary Services",
            "type":"Manufacturing & Wholesale Goods"
        }
    ],
    "sg:phone":"+1 208 357 3020",
    "sg:postcode":"83274",
    "sg:province":"ID",
    "wof:name":"Clinger Enterprises",
    "wof:placetype":"venue"
},
  "geometry": {"coordinates":[-112.091404,43.403094],"type":"Point"}
}