{
  "type": "Feature",
  "properties": {
    "iso:country":"US",
    "sg:address":"5103 Irving St",
    "sg:city":"Boise",
    "sg:classifiers":[
        {
            "category":"Wholesale",
            "subcategory":"Machinery & Supplies",
            "type":"Manufacturing & Wholesale Goods"
        }
    ],
    "sg:phone":"+1 208 375 1313",
    "sg:postcode":"83706",
    "sg:province":"ID",
    "sg:tags":[
        "tool"
    ],
    "wof:name":"K C Supply Co",
    "wof:placetype":"venue"
},
  "geometry": {"coordinates":[-116.245858,43.615164],"type":"Point"}
}