{
  "type": "Feature",
  "properties": {
    "iso:country":"US",
    "sg:address":"110 N 8th St",
    "sg:city":"Montpelier",
    "sg:classifiers":[
        {
            "category":"Insurance",
            "subcategory":"Insurance Agent",
            "type":"Services"
        }
    ],
    "sg:phone":"+1 208 847 1525",
    "sg:postcode":"83254",
    "sg:province":"ID",
    "wof:name":"Farmers Insurance & Financial",
    "wof:placetype":"venue"
},
  "geometry": {"coordinates":[-111.306788,42.318075],"type":"Point"}
}