{
  "type": "Feature",
  "properties": {
    "addr:full":"914 21st St Lewiston ID 83501",
    "addr:housenumber":"914",
    "addr:postcode":"83501",
    "addr:street":"21St St",
    "iso:country":"US",
    "sg:address":"914 21st St",
    "sg:city":"Lewiston",
    "sg:classifiers":[
        {
            "category":"Shopping",
            "subcategory":"Books",
            "type":"Retail Goods"
        }
    ],
    "sg:phone":"+1 208 743 7519",
    "sg:postcode":"83501",
    "sg:province":"ID",
    "sg:tags":[
        "dealer"
    ],
    "sg:website":"www.parable.com",
    "wof:name":"Christian Gift Ctr",
    "wof:placetype":"venue"
},
  "geometry": {"coordinates":[-117.00200100000001,46.411237],"type":"Point"}
}