{
  "type": "Feature",
  "properties": {
    "iso:country":"US",
    "sg:address":"301 S Main St",
    "sg:city":"Cascade",
    "sg:classifiers":[
        {
            "category":"Restaurant",
            "type":"Food & Drink"
        }
    ],
    "sg:phone":"+1 208 382 5498",
    "sg:postcode":"83611",
    "sg:province":"ID",
    "sg:tags":[
        "shop",
        "coffee"
    ],
    "wof:name":"Buzz City",
    "wof:placetype":"venue"
},
  "geometry": {"coordinates":[-116.040213,44.514238],"type":"Point"}
}