{
  "type": "Feature",
  "properties": {
    "addr:full":"5236 Chinden Blvd Boise ID 83714",
    "addr:housenumber":"5236",
    "addr:postcode":"83714",
    "addr:street":"Chinden Blvd",
    "iso:country":"US",
    "sg:address":"5236 Chinden Blvd",
    "sg:city":"Boise",
    "sg:classifiers":[
        {
            "category":"Manufacturing",
            "subcategory":"Tools & Machinery",
            "type":"Manufacturing & Wholesale Goods"
        }
    ],
    "sg:phone":"+1 208 323 8981",
    "sg:postcode":"83714",
    "sg:province":"ID",
    "sg:tags":[
        "optical"
    ],
    "wof:name":"Deshutes Optical Idaho",
    "wof:placetype":"venue"
},
  "geometry": {"coordinates":[-116.27051299999999,43.644342],"type":"Point"}
}