{
  "type": "Feature",
  "properties": {
    "iso:country":"US",
    "sg:address":"304 E Cameron Ave",
    "sg:city":"Kellogg",
    "sg:classifiers":[
        {
            "category":"Professional",
            "subcategory":"Accounting & Tax Preparation",
            "type":"Services"
        }
    ],
    "sg:phone":"+1 208 783 0304",
    "sg:postcode":"83837",
    "sg:province":"ID",
    "sg:tags":[
        "accountant"
    ],
    "wof:name":"Scott Beggs & Co",
    "wof:placetype":"venue"
},
  "geometry": {"coordinates":[-116.112928,47.536099],"type":"Point"}
}