{
  "type": "Feature",
  "properties": {
    "iso:country":"US",
    "sg:address":"1108 W Boise Ave",
    "sg:city":"Boise",
    "sg:classifiers":[
        {
            "category":"Insurance",
            "subcategory":"Insurance Agent",
            "type":"Services"
        }
    ],
    "sg:phone":"+1 208 343 8899",
    "sg:postcode":"83706",
    "sg:province":"ID",
    "wof:name":"Erstad & Co",
    "wof:placetype":"venue"
},
  "geometry": {"coordinates":[-116.19599599999999,43.592019],"type":"Point"}
}