{
  "type": "Feature",
  "properties": {
    "iso:country":"US",
    "sg:address":"980 Warm Springs Rd",
    "sg:city":"Ketchum",
    "sg:classifiers":[
        {
            "category":"Restaurant",
            "type":"Food & Drink"
        }
    ],
    "sg:phone":"+1 208 726 0709",
    "sg:postcode":"83340",
    "sg:province":"ID",
    "sg:tags":[
        "delicatessen"
    ],
    "wof:name":"Ketchum Food & Deli",
    "wof:placetype":"venue"
},
  "geometry": {"coordinates":[-114.45234499999999,43.666582],"type":"Point"}
}