{
  "type": "Feature",
  "properties": {
    "iso:country":"US",
    "sg:address":"1209 Main St",
    "sg:city":"Lewiston",
    "sg:classifiers":[
        {
            "category":"Shopping",
            "subcategory":"Used Merchandise",
            "type":"Retail Goods"
        }
    ],
    "sg:phone":"+1 208 750 1910",
    "sg:postcode":"83501",
    "sg:province":"ID",
    "sg:tags":[
        "antique",
        "furniture"
    ],
    "wof:name":"Bargain Hunter Mall",
    "wof:placetype":"venue"
},
  "geometry": {"coordinates":[-117.01747899999999,46.418794],"type":"Point"}
}