{
  "type": "Feature",
  "properties": {
    "iso:country":"US",
    "sg:address":"1365 N Orchard St",
    "sg:city":"Boise",
    "sg:classifiers":[
        {
            "category":"Real Estate",
            "subcategory":"Real Estate Agent",
            "type":"Services"
        }
    ],
    "sg:phone":"+1 208 377 1615",
    "sg:postcode":"83706",
    "sg:province":"ID",
    "sg:tags":[
        "appraiser"
    ],
    "sg:website":"www.northwestappraisal.com",
    "wof:name":"Northwest Appraisal Co",
    "wof:placetype":"venue"
},
  "geometry": {"coordinates":[-116.243359,43.615806],"type":"Point"}
}