{
  "type": "Feature",
  "properties": {
    "iso:country":"US",
    "sg:address":"1298 Twin Parks Dr",
    "sg:city":"Twin Falls",
    "sg:classifiers":[
        {
            "category":"Building & Trades",
            "subcategory":"Landscaping Services",
            "type":"Services"
        }
    ],
    "sg:phone":"+1 208 733 1491",
    "sg:postcode":"83301",
    "sg:province":"ID",
    "sg:tags":[
        "lawn",
        "maintenance",
        "grounds"
    ],
    "wof:name":"Idaho Lawn Svc",
    "wof:placetype":"venue"
},
  "geometry": {"coordinates":[-114.490326,42.585017],"type":"Point"}
}