{
  "type": "Feature",
  "properties": {
    "addr:full":"1073 Nearing Rd Moscow ID 83843",
    "addr:housenumber":"1073",
    "addr:postcode":"83843",
    "addr:street":"Nearing Rd",
    "iso:country":"US",
    "sg:address":"1073 Nearing Rd",
    "sg:city":"Moscow",
    "sg:classifiers":[
        {
            "category":"Professional",
            "subcategory":"Business Services",
            "type":"Services"
        }
    ],
    "sg:phone":"+1 208 883 3025",
    "sg:postcode":"83843",
    "sg:province":"ID",
    "sg:tags":[
        "consultant",
        "coach"
    ],
    "wof:name":"Griffiths Consulting",
    "wof:placetype":"venue"
},
  "geometry": {"coordinates":[-116.99154799999999,46.812237],"type":"Point"}
}