{
  "type": "Feature",
  "properties": {
    "iso:country":"US",
    "sg:address":"1033 Leadville Ave",
    "sg:city":"Boise",
    "sg:classifiers":[
        {
            "category":"Professional",
            "subcategory":"Advertising",
            "type":"Services"
        }
    ],
    "sg:phone":"+1 208 336 5099",
    "sg:postcode":"83706",
    "sg:province":"ID",
    "sg:tags":[
        "counselor"
    ],
    "wof:name":"B & B Marketing Group",
    "wof:placetype":"venue"
},
  "geometry": {"coordinates":[-116.19099799999999,43.600677],"type":"Point"}
}