{
  "type": "Feature",
  "properties": {
    "iso:country":"US",
    "sg:address":"111 S 27th St",
    "sg:city":"Boise",
    "sg:classifiers":[
        {
            "category":"Banks & Credit Unions",
            "subcategory":"Bank",
            "type":"Services"
        }
    ],
    "sg:phone":"+1 208 383 7851",
    "sg:postcode":"83702",
    "sg:province":"ID",
    "wof:name":"US Bank",
    "wof:placetype":"venue"
},
  "geometry": {"coordinates":[-116.22396999999999,43.620602],"type":"Point"}
}