{
  "type": "Feature",
  "properties": {
    "iso:country":"US",
    "sg:address":"1226 Colburn Culver Rd",
    "sg:city":"Sandpoint",
    "sg:classifiers":[
        {
            "category":"Farming",
            "subcategory":"Livestock Farm",
            "type":"Manufacturing & Wholesale Goods"
        }
    ],
    "sg:phone":"+1 208 263 3344",
    "sg:postcode":"83864",
    "sg:province":"ID",
    "sg:tags":[
        "equine"
    ],
    "wof:name":"Quad-L Ranch",
    "wof:placetype":"venue"
},
  "geometry": {"coordinates":[-116.504762,48.400291],"type":"Point"}
}