{
  "type": "Feature",
  "properties": {
    "iso:country":"US",
    "sg:address":"207 W Washington St",
    "sg:city":"Boise",
    "sg:classifiers":[
        {
            "category":"Banks & Credit Unions",
            "subcategory":"Bank",
            "type":"Services"
        }
    ],
    "sg:phone":"+1 208 389 4709",
    "sg:postcode":"83702",
    "sg:province":"ID",
    "sg:tags":[
        "loan",
        "real estate"
    ],
    "wof:name":"Columbia Mortgage Svc",
    "wof:placetype":"venue"
},
  "geometry": {"coordinates":[-116.19393100000001,43.616381],"type":"Point"}
}