{
  "type": "Feature",
  "properties": {
    "addr:full":"402 E 4th Ave Post Falls ID 83854",
    "addr:housenumber":"402",
    "addr:postcode":"83854",
    "addr:street":"E 4Th Ave",
    "iso:country":"US",
    "sg:address":"402 E 4th Ave",
    "sg:city":"Post Falls",
    "sg:classifiers":[
        {
            "category":"Organizations",
            "subcategory":"Religious Organization",
            "type":"Services"
        }
    ],
    "sg:phone":"+1 208 266 1170",
    "sg:postcode":"83854",
    "sg:province":"ID",
    "sg:tags":[
        "church"
    ],
    "wof:name":"River Valley Baptist Church",
    "wof:placetype":"venue"
},
  "geometry": {"coordinates":[-116.943432,47.710927],"type":"Point"}
}