{
  "type": "Feature",
  "properties": {
    "addr:full":"405 E Ave A Jerome ID 83338",
    "addr:housenumber":"405",
    "addr:postcode":"83338",
    "addr:street":"E Ave A",
    "iso:country":"US",
    "sg:address":"405 E Ave A",
    "sg:city":"Jerome",
    "sg:classifiers":[
        {
            "category":"Professional",
            "subcategory":"Advertising",
            "type":"Services"
        }
    ],
    "sg:phone":"+1 208 324 1491",
    "sg:postcode":"83338",
    "sg:province":"ID",
    "wof:name":"Intermountain Printing & Prmtn",
    "wof:placetype":"venue"
},
  "geometry": {"coordinates":[-114.513132,42.72308],"type":"Point"}
}