{
  "type": "Feature",
  "properties": {
    "addr:full":"1724 D St Rupert ID 83350",
    "addr:housenumber":"1724",
    "addr:postcode":"83350",
    "addr:street":"D St",
    "iso:country":"US",
    "sg:address":"1724 D St",
    "sg:city":"Rupert",
    "sg:classifiers":[
        {
            "category":"Real Estate",
            "subcategory":"Real Estate Operator",
            "type":"Services"
        }
    ],
    "sg:phone":"+1 208 436 0429",
    "sg:postcode":"83350",
    "sg:province":"ID",
    "sg:tags":[
        "building",
        "apartment"
    ],
    "wof:name":"Colonial Townhouse Apts",
    "wof:placetype":"venue"
},
  "geometry": {"coordinates":[-113.67270000000001,42.63002],"type":"Point"}
}