{
  "type": "Feature",
  "properties": {
    "addr:full":"12112 W Spring River St Boise ID 83709",
    "addr:housenumber":"12112",
    "addr:postcode":"83709",
    "addr:street":"W Spring River St",
    "iso:country":"US",
    "sg:address":"12112 W Spring River St",
    "sg:city":"Boise",
    "sg:classifiers":[
        {
            "category":"Building & Trades",
            "subcategory":"Landscaping Services",
            "type":"Services"
        }
    ],
    "sg:phone":"+1 208 321 0050",
    "sg:postcode":"83709",
    "sg:province":"ID",
    "wof:name":"Affordable Lawn Care",
    "wof:placetype":"venue"
},
  "geometry": {"coordinates":[-116.33171400000001,43.553456],"type":"Point"}
}