{
  "type": "Feature",
  "properties": {
    "iso:country":"US",
    "sg:address":"111 Broadway Ave",
    "sg:city":"Boise",
    "sg:classifiers":[
        {
            "category":"Retail",
            "subcategory":"Laundry & Dry Cleaning",
            "type":"Services"
        }
    ],
    "sg:phone":"+1 208 343 4323",
    "sg:postcode":"83702",
    "sg:province":"ID",
    "sg:tags":[
        "cleaners"
    ],
    "wof:name":"Cleaners Express",
    "wof:placetype":"venue"
},
  "geometry": {"coordinates":[-116.193222,43.610604],"type":"Point"}
}