{
  "type": "Feature",
  "properties": {
    "iso:country":"US",
    "sg:address":"1921 Uehlin Dr",
    "sg:city":"Payette",
    "sg:classifiers":[
        {
            "category":"Building & Trades",
            "subcategory":"Landscaping Services",
            "type":"Services"
        }
    ],
    "sg:phone":"+1 208 642 2660",
    "sg:postcode":"83661",
    "sg:province":"ID",
    "wof:name":"B An R Lawncare",
    "wof:placetype":"venue"
},
  "geometry": {"coordinates":[-116.918232,44.078418],"type":"Point"}
}