{
  "type": "Feature",
  "properties": {
    "iso:country":"US",
    "sg:address":"818 Main St",
    "sg:city":"Salmon",
    "sg:classifiers":[
        {
            "category":"Health Services",
            "subcategory":"Optometrist",
            "type":"Services"
        }
    ],
    "sg:phone":"+1 208 756 3600",
    "sg:postcode":"83467",
    "sg:province":"ID",
    "wof:name":"Slavin Eye Clinic",
    "wof:placetype":"venue"
},
  "geometry": {"coordinates":[-113.891037,45.174564],"type":"Point"}
}