{
  "type": "Feature",
  "properties": {
    "iso:country":"US",
    "sg:address":"3001 S Ten Mile Rd",
    "sg:city":"Meridian",
    "sg:classifiers":[
        {
            "category":"Building & Trades",
            "subcategory":"Construction",
            "type":"Services"
        }
    ],
    "sg:phone":"+1 208 888 6449",
    "sg:postcode":"83642",
    "sg:province":"ID",
    "sg:tags":[
        "general",
        "contractor"
    ],
    "wof:name":"Doug Larsen Construction Inc",
    "wof:placetype":"venue"
},
  "geometry": {"coordinates":[-116.433862,43.581051],"type":"Point"}
}