{
  "type": "Feature",
  "properties": {
    "iso:country":"US",
    "sg:address":"740 W Center St",
    "sg:city":"Pocatello",
    "sg:classifiers":[
        {
            "category":"Organizations",
            "subcategory":"Religious Organization",
            "type":"Services"
        }
    ],
    "sg:phone":"+1 208 233 8400",
    "sg:postcode":"83204",
    "sg:province":"ID",
    "sg:tags":[
        "church"
    ],
    "wof:name":"Rock Foursquare Church",
    "wof:placetype":"venue"
},
  "geometry": {"coordinates":[-112.454823,42.859572],"type":"Point"}
}