{
  "type": "Feature",
  "properties": {
    "iso:country":"US",
    "sg:address":"204 Earle St",
    "sg:city":"Mullan",
    "sg:classifiers":[
        {
            "category":"Personal",
            "subcategory":"Beauty Salon",
            "type":"Services"
        }
    ],
    "sg:phone":"+1 208 744 1127",
    "sg:postcode":"83846",
    "sg:province":"ID",
    "wof:name":"Silver Valley Hair Styling",
    "wof:placetype":"venue"
},
  "geometry": {"coordinates":[-115.799769,47.47054],"type":"Point"}
}