{
  "type": "Feature",
  "properties": {
    "addr:full":"2102 N 4th St Coeur D Alene ID 83814",
    "addr:housenumber":"2102",
    "addr:postcode":"83814",
    "addr:street":"N 4Th St Coeur D",
    "iso:country":"US",
    "sg:address":"2102 N 4th St",
    "sg:city":"Coeur D Alene",
    "sg:classifiers":[
        {
            "category":"Restaurant",
            "type":"Food & Drink"
        }
    ],
    "sg:menulink":"http://www.allmenus.com/id/coeur-dalene/120356-subway/menu/",
    "sg:phone":"+1 208 765 0594",
    "sg:postcode":"83814",
    "sg:province":"ID",
    "sg:tags":[
        "american",
        "sandwich"
    ],
    "wof:name":"Subway",
    "wof:placetype":"venue"
},
  "geometry": {"coordinates":[-116.78021200000001,47.696239],"type":"Point"}
}