{
  "type": "Feature",
  "properties": {
    "iso:country":"US",
    "sg:address":"3916 S Normandie Cir",
    "sg:city":"Boise",
    "sg:classifiers":[
        {
            "category":"Wholesale",
            "subcategory":"Auto Parts",
            "type":"Manufacturing & Wholesale Goods"
        }
    ],
    "sg:phone":"+1 208 376 1627",
    "sg:postcode":"83705",
    "sg:province":"ID",
    "sg:tags":[
        "automobile",
        "cleaning",
        "supply"
    ],
    "wof:name":"Hatch Car Beauty",
    "wof:placetype":"venue"
},
  "geometry": {"coordinates":[-116.230466,43.573738],"type":"Point"}
}