{
  "type": "Feature",
  "properties": {
    "iso:country":"US",
    "sg:address":"1590 E Polston Ave",
    "sg:city":"Post Falls",
    "sg:classifiers":[
        {
            "category":"Health Services",
            "subcategory":"Podiatrist",
            "type":"Services"
        }
    ],
    "sg:phone":"+1 208 777 9794",
    "sg:postcode":"83854",
    "sg:province":"ID",
    "wof:name":"Inland Northwest Foot & Ankle",
    "wof:placetype":"venue"
},
  "geometry": {"coordinates":[-116.926952,47.71462],"type":"Point"}
}