{
  "type": "Feature",
  "properties": {
    "iso:country":"US",
    "sg:address":"1651 W Hampton Ct",
    "sg:city":"Rathdrum",
    "sg:classifiers":[
        {
            "category":"Building & Trades",
            "subcategory":"Construction",
            "type":"Services"
        }
    ],
    "sg:phone":"+1 208 687 0536",
    "sg:postcode":"83858",
    "sg:province":"ID",
    "sg:tags":[
        "house"
    ],
    "wof:name":"Thompson Construction",
    "wof:placetype":"venue"
},
  "geometry": {"coordinates":[-116.81092200000001,47.832988],"type":"Point"}
}