{
  "type": "Feature",
  "properties": {
    "iso:country":"US",
    "sg:address":"4487 E 400 N",
    "sg:city":"Rigby",
    "sg:classifiers":[
        {
            "category":"Professional",
            "subcategory":"Computer Services",
            "type":"Services"
        }
    ],
    "sg:phone":"+1 208 538 5030",
    "sg:postcode":"83442",
    "sg:province":"ID",
    "sg:tags":[
        "datum"
    ],
    "wof:name":"D PS Ditigal Imprints",
    "wof:placetype":"venue"
},
  "geometry": {"coordinates":[-111.807463,43.6848],"type":"Point"}
}