{
  "type": "Feature",
  "properties": {
    "addr:full":"1061 1st Ave Deary ID 83823",
    "addr:housenumber":"1061",
    "addr:postcode":"83823",
    "addr:street":"1St Ave",
    "iso:country":"US",
    "sg:address":"1061 1st Ave",
    "sg:city":"Deary",
    "sg:classifiers":[
        {
            "category":"Building & Trades",
            "subcategory":"Construction",
            "type":"Services"
        }
    ],
    "sg:phone":"+1 208 877 1219",
    "sg:postcode":"83823",
    "sg:province":"ID",
    "sg:tags":[
        "general",
        "contractor"
    ],
    "wof:name":"C J Barton Construction Inc",
    "wof:placetype":"venue"
},
  "geometry": {"coordinates":[-116.565011,46.798221],"type":"Point"}
}