{
  "type": "Feature",
  "properties": {
    "iso:country":"US",
    "sg:address":"1050 Sunset Strip",
    "sg:city":"Mountain Home",
    "sg:classifiers":[
        {
            "category":"Retail",
            "subcategory":"Auto Repair",
            "type":"Services"
        }
    ],
    "sg:phone":"+1 208 587 7945",
    "sg:postcode":"83647",
    "sg:province":"ID",
    "sg:tags":[
        "repairing",
        "automobile"
    ],
    "wof:name":"Mouser Auto Repair",
    "wof:placetype":"venue"
},
  "geometry": {"coordinates":[-115.70355600000001,43.141389],"type":"Point"}
}