{
  "type": "Feature",
  "properties": {
    "addr:full":"4700 N Cloverdale Rd Boise ID 83713",
    "addr:housenumber":"4700",
    "addr:postcode":"83713",
    "addr:street":"N Cloverdale Rd",
    "iso:country":"US",
    "sg:address":"4700 N Cloverdale Rd",
    "sg:city":"Boise",
    "sg:classifiers":[
        {
            "category":"Banks & Credit Unions",
            "subcategory":"Investment Brokerage",
            "type":"Services"
        }
    ],
    "sg:phone":"+1 208 685 0444",
    "sg:postcode":"83713",
    "sg:province":"ID",
    "sg:tags":[
        "security"
    ],
    "wof:name":"Edward Jones Co",
    "wof:placetype":"venue"
},
  "geometry": {"coordinates":[-116.334379,43.648455],"type":"Point"}
}