{
  "type": "Feature",
  "properties": {
    "addr:full":"5366 Missoula Way Boise ID 83709",
    "addr:postcode":"5366;83709",
    "addr:street":"Missoula Way",
    "iso:country":"US",
    "sg:address":"5366 Missoula Way",
    "sg:city":"Boise",
    "sg:classifiers":[
        {
            "category":"Social Services",
            "type":"Services"
        }
    ],
    "sg:phone":"+1 208 377 2292",
    "sg:postcode":"83709",
    "sg:province":"ID",
    "sg:tags":[
        "counselor",
        "marriage",
        "family"
    ],
    "wof:name":"Keith Potter",
    "wof:placetype":"venue"
},
  "geometry": {"coordinates":[-116.29257699999999,43.556649],"type":"Point"}
}