{
  "type": "Feature",
  "properties": {
    "iso:country":"US",
    "sg:address":"118 N 7th St",
    "sg:city":"Coeur D Alene",
    "sg:classifiers":[
        {
            "category":"Insurance",
            "subcategory":"Insurance Agent",
            "type":"Services"
        }
    ],
    "sg:phone":"+1 208 676 8653",
    "sg:postcode":"83814",
    "sg:province":"ID",
    "wof:name":"Lamott Agency",
    "wof:placetype":"venue"
},
  "geometry": {"coordinates":[-116.776731,47.673647],"type":"Point"}
}