{
  "type": "Feature",
  "properties": {
    "iso:country":"US",
    "sg:address":"445 Joan Ave",
    "sg:city":"Idaho Falls",
    "sg:classifiers":[
        {
            "category":"Building & Trades",
            "subcategory":"Construction",
            "type":"Services"
        }
    ],
    "sg:phone":"+1 208 522 2894",
    "sg:postcode":"83401",
    "sg:province":"ID",
    "sg:tags":[
        "house"
    ],
    "wof:name":"Phoenix Construction Co LLC",
    "wof:placetype":"venue"
},
  "geometry": {"coordinates":[-111.99592,43.49875],"type":"Point"}
}