{
  "type": "Feature",
  "properties": {
    "iso:country":"US",
    "sg:address":"6896 Pheasant Dr",
    "sg:city":"Lava Hot Springs",
    "sg:classifiers":[
        {
            "category":"Retail",
            "subcategory":"Auto Repair",
            "type":"Services"
        }
    ],
    "sg:phone":"+1 208 776 9438",
    "sg:postcode":"83246",
    "sg:province":"ID",
    "sg:tags":[
        "contract",
        "mechanic"
    ],
    "wof:name":"Mark Evans",
    "wof:placetype":"venue"
},
  "geometry": {"coordinates":[-112.02175200000001,42.660711],"type":"Point"}
}