{
  "type": "Feature",
  "properties": {
    "iso:country":"US",
    "sg:address":"642 N 2000 E",
    "sg:city":"Saint Anthony",
    "sg:classifiers":[
        {
            "category":"Farming",
            "subcategory":"Farm",
            "type":"Manufacturing & Wholesale Goods"
        }
    ],
    "sg:phone":"+1 208 624 7056",
    "sg:postcode":"83445",
    "sg:province":"ID",
    "sg:tags":[
        "field",
        "grain",
        "cash",
        "crop",
        "general"
    ],
    "wof:name":"Frank Mackert",
    "wof:placetype":"venue"
},
  "geometry": {"coordinates":[-111.757778,43.977516],"type":"Point"}
}