{
  "type": "Feature",
  "properties": {
    "iso:country":"US",
    "sg:address":"415 N 3rd St",
    "sg:city":"Coeur D Alene",
    "sg:classifiers":[
        {
            "category":"Retail",
            "subcategory":"Auto Repair",
            "type":"Services"
        }
    ],
    "sg:phone":"+1 208 664 1402",
    "sg:postcode":"83814",
    "sg:province":"ID",
    "sg:tags":[
        "transmission"
    ],
    "wof:name":"AAMCO Transmissions",
    "wof:placetype":"venue"
},
  "geometry": {"coordinates":[-116.78262700000001,47.676273],"type":"Point"}
}