{
  "type": "Feature",
  "properties": {
    "iso:country":"US",
    "sg:address":"5901 Overland Rd",
    "sg:city":"Boise",
    "sg:classifiers":[
        {
            "category":"Shopping",
            "type":"Retail Goods"
        }
    ],
    "sg:phone":"+1 208 375 4229",
    "sg:postcode":"83709",
    "sg:province":"ID",
    "sg:tags":[
        "art",
        "gallery",
        "dealer"
    ],
    "wof:name":"Marv's Framing & Gallery",
    "wof:placetype":"venue"
},
  "geometry": {"coordinates":[-116.255878,43.58992],"type":"Point"}
}