{
  "type": "Feature",
  "properties": {
    "addr:full":"136 Thain Rd Lewiston ID 83501",
    "addr:housenumber":"136",
    "addr:postcode":"83501",
    "addr:street":"Thain Rd",
    "iso:country":"US",
    "sg:address":"136 Thain Rd",
    "sg:city":"Lewiston",
    "sg:classifiers":[
        {
            "category":"Banks & Credit Unions",
            "subcategory":"Bank",
            "type":"Services"
        }
    ],
    "sg:phone":"+1 208 746 7366",
    "sg:postcode":"83501",
    "sg:province":"ID",
    "wof:name":"Catholic Credit Union",
    "wof:placetype":"venue"
},
  "geometry": {"coordinates":[-116.988364,46.389031],"type":"Point"}
}