{
  "type": "Feature",
  "properties": {
    "iso:country":"US",
    "sg:address":"120 SE 7th St",
    "sg:city":"Grangeville",
    "sg:classifiers":[
        {
            "category":"Shopping",
            "subcategory":"Gifts & Souvenirs",
            "type":"Retail Goods"
        }
    ],
    "sg:phone":"+1 208 983 7771",
    "sg:postcode":"83530",
    "sg:province":"ID",
    "wof:name":"Camas Gifts",
    "wof:placetype":"venue"
},
  "geometry": {"coordinates":[-116.121751,45.919768],"type":"Point"}
}