{
  "type": "Feature",
  "properties": {
    "addr:full":"1924 Vista Ave Boise ID 83705",
    "addr:housenumber":"1924",
    "addr:postcode":"83705",
    "addr:street":"Vista Ave",
    "iso:country":"US",
    "sg:address":"1924 Vista Ave",
    "sg:city":"Boise",
    "sg:classifiers":[
        {
            "category":"Banks & Credit Unions",
            "subcategory":"Bank",
            "type":"Services"
        }
    ],
    "sg:phone":"+1 208 345 5626",
    "sg:postcode":"83705",
    "sg:province":"ID",
    "sg:tags":[
        "loan",
        "real estate"
    ],
    "wof:name":"Best Choice Mortgage",
    "wof:placetype":"venue"
},
  "geometry": {"coordinates":[-116.213579,43.585557],"type":"Point"}
}