{
  "type": "Feature",
  "properties": {
    "addr:full":"823 E Boyd Ave Coeur D Alene ID 83814",
    "addr:housenumber":"823",
    "addr:postcode":"83814",
    "addr:street":"E Boyd Ave",
    "iso:country":"US",
    "sg:address":"823 E Boyd Ave",
    "sg:city":"Coeur D Alene",
    "sg:classifiers":[
        {
            "category":"Building & Trades",
            "subcategory":"Construction",
            "type":"Services"
        }
    ],
    "sg:phone":"+1 208 660 3355",
    "sg:postcode":"83814",
    "sg:province":"ID",
    "sg:tags":[
        "concrete",
        "pumping"
    ],
    "wof:name":"Pilot Concrete Pumping",
    "wof:placetype":"venue"
},
  "geometry": {"coordinates":[-116.77506700000001,47.68191],"type":"Point"}
}