{
  "type": "Feature",
  "properties": {
    "iso:country":"US",
    "sg:address":"9087 Rim Rd",
    "sg:city":"Nampa",
    "sg:phone":"+1 208 467 7305",
    "sg:postcode":"83686",
    "sg:province":"ID",
    "sg:tags":[
        "farm",
        "field",
        "crop"
    ],
    "wof:name":"Roger Haylett",
    "wof:placetype":"venue"
},
  "geometry": {"coordinates":[-116.633128,43.510137],"type":"Point"}
}