{
  "type": "Feature",
  "properties": {
    "iso:country":"US",
    "sg:address":"33 Lakewood Ave",
    "sg:city":"Sagle",
    "sg:classifiers":[
        {
            "category":"Retail",
            "subcategory":"Repair Shop",
            "type":"Services"
        }
    ],
    "sg:phone":"+1 208 255 2060",
    "sg:postcode":"83860",
    "sg:province":"ID",
    "wof:name":"R&J Ignitor Service",
    "wof:placetype":"venue"
},
  "geometry": {"coordinates":[-116.538796,48.239225],"type":"Point"}
}