{
  "type": "Feature",
  "properties": {
    "addr:full":"324 W State St Eagle ID 83616",
    "addr:housenumber":"324",
    "addr:postcode":"83616",
    "addr:street":"W State St",
    "iso:country":"US",
    "sg:address":"324 W State St",
    "sg:city":"Eagle",
    "sg:classifiers":[
        {
            "category":"Organizations",
            "subcategory":"Community Association",
            "type":"Services"
        }
    ],
    "sg:phone":"+1 208 938 8410",
    "sg:postcode":"83616",
    "sg:province":"ID",
    "sg:tags":[
        "club"
    ],
    "wof:name":"Idaho Athletic Club",
    "wof:placetype":"venue"
},
  "geometry": {"coordinates":[-116.357118,43.695212],"type":"Point"}
}