{
  "type": "Feature",
  "properties": {
    "iso:country":"US",
    "sg:address":"3650 Mill Creek Rd",
    "sg:city":"Cambridge",
    "sg:phone":"+1 208 257 3595",
    "sg:postcode":"83610",
    "sg:province":"ID",
    "sg:tags":[
        "beef",
        "farm",
        "crop",
        "field",
        "cattle",
        "feedlot"
    ],
    "wof:name":"Gibson Artith",
    "wof:placetype":"venue"
},
  "geometry": {"coordinates":[-116.844205,44.67946],"type":"Point"}
}