{
  "type": "Feature",
  "properties": {
    "iso:country":"US",
    "sg:address":"621 Northstar Dr",
    "sg:city":"Hailey",
    "sg:classifiers":[
        {
            "category":"Personal",
            "subcategory":"Beauty Salon",
            "type":"Services"
        }
    ],
    "sg:phone":"+1 208 578 2214",
    "sg:postcode":"83333",
    "sg:province":"ID",
    "wof:name":"Radiance Skin Care Studio",
    "wof:placetype":"venue"
},
  "geometry": {"coordinates":[-114.322855,43.525083],"type":"Point"}
}