{
  "type": "Feature",
  "properties": {
    "iso:country":"US",
    "sg:address":"6341 N Bellecreek Ave",
    "sg:city":"Boise",
    "sg:classifiers":[
        {
            "category":"Professional",
            "subcategory":"Art Services",
            "type":"Services"
        }
    ],
    "sg:phone":"+1 208 342 6966",
    "sg:postcode":"83713",
    "sg:province":"ID",
    "sg:tags":[
        "photo",
        "photography",
        "commercial",
        "studio",
        "portrait"
    ],
    "wof:name":"Thunder Studio",
    "wof:placetype":"venue"
},
  "geometry": {"coordinates":[-116.35001099999999,43.662103],"type":"Point"}
}