{
  "type": "Feature",
  "properties": {
    "iso:country":"US",
    "sg:address":"2337 3rd Ave N",
    "sg:city":"Lewiston",
    "sg:classifiers":[
        {
            "category":"Building & Trades",
            "subcategory":"Construction",
            "type":"Services"
        }
    ],
    "sg:phone":"+1 208 746 4192",
    "sg:postcode":"83501",
    "sg:province":"ID",
    "sg:tags":[
        "water",
        "restoration",
        "damage"
    ],
    "sg:website":"www.kingservices.com",
    "wof:name":"King Services & Construction",
    "wof:placetype":"venue"
},
  "geometry": {"coordinates":[-116.99822399999999,46.423654],"type":"Point"}
}