{
  "type": "Feature",
  "properties": {
    "iso:country":"US",
    "sg:address":"4348 W Chinden Blvd",
    "sg:city":"Garden City",
    "sg:classifiers":[
        {
            "category":"Deli",
            "type":"Food & Drink"
        }
    ],
    "sg:menulink":"http://www.allmenus.com/id/boise-city/3575-cobbys-ii/menu/",
    "sg:phone":"+1 208 322 7401",
    "sg:postcode":"83714",
    "sg:province":"ID",
    "sg:tags":[
        "american"
    ],
    "wof:name":"Cobby's II",
    "wof:placetype":"venue"
},
  "geometry": {"coordinates":[-116.254002,43.633097],"type":"Point"}
}