{
  "type": "Feature",
  "properties": {
    "iso:country":"US",
    "sg:address":"130 26th St",
    "sg:city":"Lewiston",
    "sg:classifiers":[
        {
            "category":"Building & Trades",
            "subcategory":"Construction",
            "type":"Services"
        }
    ],
    "sg:phone":"+1 208 743 9179",
    "sg:postcode":"83501",
    "sg:province":"ID",
    "sg:tags":[
        "hanging",
        "contractor"
    ],
    "wof:name":"Andrews Painting Travis",
    "wof:placetype":"venue"
},
  "geometry": {"coordinates":[-116.994979,46.417517],"type":"Point"}
}