{
  "type": "Feature",
  "properties": {
    "addr:full":"68 French Gulch Rd Kingston ID 83839",
    "addr:housenumber":"68",
    "addr:postcode":"83839",
    "addr:street":"French Gulch Rd",
    "iso:country":"US",
    "sg:address":"68 French Gulch Rd",
    "sg:city":"Kingston",
    "sg:classifiers":[
        {
            "category":"Building & Trades",
            "subcategory":"Cleaning & Sanitation",
            "type":"Services"
        }
    ],
    "sg:phone":"+1 208 682 4092",
    "sg:postcode":"83839",
    "sg:province":"ID",
    "sg:tags":[
        "janitor"
    ],
    "wof:name":"Silver Valley Cleaning",
    "wof:placetype":"venue"
},
  "geometry": {"coordinates":[-116.275666,47.548005],"type":"Point"}
}