{
  "type": "Feature",
  "properties": {
    "iso:country":"US",
    "sg:address":"2125 3rd Ave N",
    "sg:city":"Lewiston",
    "sg:classifiers":[
        {
            "category":"Travel",
            "subcategory":"Hotels & Motels",
            "type":"Entertainment"
        }
    ],
    "sg:phone":"+1 208 746 5851",
    "sg:postcode":"83501",
    "sg:province":"ID",
    "wof:name":"Evergreen Motel",
    "wof:placetype":"venue"
},
  "geometry": {"coordinates":[-117.002763,46.423717],"type":"Point"}
}