{
  "type": "Feature",
  "properties": {
    "addr:full":"1 E State St Eagle ID 83616",
    "addr:housenumber":"1",
    "addr:postcode":"83616",
    "addr:street":"E State St",
    "iso:country":"US",
    "sg:address":"1 E State St",
    "sg:city":"Eagle",
    "sg:classifiers":[
        {
            "category":"Home & Garden",
            "subcategory":"Building Materials",
            "type":"Retail Goods"
        }
    ],
    "sg:phone":"+1 208 939 9396",
    "sg:postcode":"83616",
    "sg:province":"ID",
    "sg:tags":[
        "windows"
    ],
    "wof:name":"Idaho Window Sales-Hurd",
    "wof:placetype":"venue"
},
  "geometry": {"coordinates":[-116.354007,43.695266],"type":"Point"}
}