{
  "type": "Feature",
  "properties": {
    "addr:full":"2002 N Washington Ave Emmett ID 83617",
    "addr:housenumber":"2002",
    "addr:postcode":"83617",
    "addr:street":"N Washington Ave",
    "iso:country":"US",
    "sg:address":"2002 N Washington Ave",
    "sg:city":"Emmett",
    "sg:classifiers":[
        {
            "category":"Bars & Pubs",
            "type":"Food & Drink"
        }
    ],
    "sg:phone":"+1 208 365 9987",
    "sg:postcode":"83617",
    "sg:province":"ID",
    "wof:name":"T Bar J Saloon",
    "wof:placetype":"venue"
},
  "geometry": {"coordinates":[-116.502353,43.897274],"type":"Point"}
}