{
  "type": "Feature",
  "properties": {
    "iso:country":"US",
    "sg:address":"3299 Woodridge Dr",
    "sg:city":"Twin Falls",
    "sg:classifiers":[
        {
            "category":"Restaurant",
            "type":"Food & Drink"
        }
    ],
    "sg:phone":"+1 208 735 0921",
    "sg:postcode":"83301",
    "sg:province":"ID",
    "sg:tags":[
        "caterer"
    ],
    "sg:website":"www.homestyledirect.com",
    "wof:name":"Homestyle Direct",
    "wof:placetype":"venue"
},
  "geometry": {"coordinates":[-114.413785,42.565816],"type":"Point"}
}