{
  "type": "Feature",
  "properties": {
    "iso:country":"US",
    "sg:address":"390 Delbert Dr",
    "sg:city":"Idaho Falls",
    "sg:classifiers":[
        {
            "category":"Wholesale",
            "subcategory":"Medical Equipment & Supplies",
            "type":"Manufacturing & Wholesale Goods"
        },
        {
            "category":"Shopping",
            "type":"Retail Goods"
        }
    ],
    "sg:phone":"+1 208 552 6695",
    "sg:postcode":"83401",
    "sg:province":"ID",
    "sg:tags":[
        "home",
        "health",
        "care"
    ],
    "wof:name":"K D Enterprises",
    "wof:placetype":"venue"
},
  "geometry": {"coordinates":[-112.005433,43.494242],"type":"Point"}
}