{
  "type": "Feature",
  "properties": {
    "iso:country":"US",
    "sg:address":"1601 E Gilbert Ave",
    "sg:city":"Coeur D Alene",
    "sg:classifiers":[
        {
            "category":"Social Services",
            "subcategory":"Job Training",
            "type":"Services"
        }
    ],
    "sg:phone":"+1 208 667 9607",
    "sg:postcode":"83815",
    "sg:province":"ID",
    "sg:tags":[
        "rehabilitation"
    ],
    "wof:name":"Trinity Group Homes Inc",
    "wof:placetype":"venue"
},
  "geometry": {"coordinates":[-116.763683,47.702675],"type":"Point"}
}