{
  "type": "Feature",
  "properties": {
    "iso:country":"US",
    "sg:address":"2128 E 1850 S",
    "sg:city":"Gooding",
    "sg:classifiers":[
        {
            "category":"Building & Trades",
            "subcategory":"Construction",
            "type":"Services"
        }
    ],
    "sg:phone":"+1 208 934 4964",
    "sg:postcode":"83330",
    "sg:province":"ID",
    "sg:tags":[
        "house"
    ],
    "wof:name":"Ron Gill Const",
    "wof:placetype":"venue"
},
  "geometry": {"coordinates":[-114.66583199999999,42.93141],"type":"Point"}
}