{
  "type": "Feature",
  "properties": {
    "iso:country":"US",
    "sg:address":"2076 Century Way",
    "sg:city":"Boise",
    "sg:classifiers":[
        {
            "category":"Wholesale",
            "subcategory":"Machinery & Supplies",
            "type":"Manufacturing & Wholesale Goods"
        }
    ],
    "sg:phone":"+1 208 376 1365",
    "sg:postcode":"83709",
    "sg:province":"ID",
    "sg:tags":[
        "equipment",
        "welding"
    ],
    "wof:name":"Norco",
    "wof:placetype":"venue"
},
  "geometry": {"coordinates":[-116.272217,43.584064],"type":"Point"}
}