{
  "type": "Feature",
  "properties": {
    "iso:country":"US",
    "sg:address":"405 Main St",
    "sg:city":"Cottonwood",
    "sg:classifiers":[
        {
            "category":"Bars & Pubs",
            "type":"Food & Drink"
        }
    ],
    "sg:phone":"+1 208 962 3560",
    "sg:postcode":"83522",
    "sg:province":"ID",
    "sg:tags":[
        "lounge",
        "cocktail"
    ],
    "wof:name":"Royale Room",
    "wof:placetype":"venue"
},
  "geometry": {"coordinates":[-116.349944,46.048084],"type":"Point"}
}