{
  "type": "Feature",
  "properties": {
    "iso:country":"US",
    "sg:address":"14251 US Hwy 30",
    "sg:city":"Pocatello",
    "sg:classifiers":[
        {
            "category":"Building & Trades",
            "subcategory":"Construction",
            "type":"Services"
        }
    ],
    "sg:phone":"+1 208 478 9315",
    "sg:postcode":"83201",
    "sg:province":"ID",
    "sg:tags":[
        "painter"
    ],
    "wof:name":"American Painting & Sndblstng",
    "wof:placetype":"venue"
},
  "geometry": {"coordinates":[-112.503511,42.903327],"type":"Point"}
}