{
  "type": "Feature",
  "properties": {
    "iso:country":"US",
    "sg:address":"4500 Ginzel St",
    "sg:city":"Boise",
    "sg:classifiers":[
        {
            "category":"Professional",
            "subcategory":"Business Services",
            "type":"Services"
        }
    ],
    "sg:phone":"+1 208 342 5100",
    "sg:postcode":"83703",
    "sg:province":"ID",
    "sg:tags":[
        "decorating",
        "contractor"
    ],
    "wof:name":"Talking Balloon Event Decortrs",
    "wof:placetype":"venue"
},
  "geometry": {"coordinates":[-116.235161,43.65991],"type":"Point"}
}