{
  "type": "Feature",
  "properties": {
    "addr:full":"3650 N Government Way Coeur D Alene ID 83815",
    "addr:housenumber":"3650",
    "addr:postcode":"83815",
    "addr:street":"N Government Way",
    "iso:country":"US",
    "sg:address":"3650 N Government Way",
    "sg:city":"Coeur D Alene",
    "sg:classifiers":[
        {
            "category":"Social Services",
            "type":"Services"
        }
    ],
    "sg:phone":"+1 208 765 5085",
    "sg:postcode":"83815",
    "sg:province":"ID",
    "wof:name":"Coeur DAlene Counseling",
    "wof:placetype":"venue"
},
  "geometry": {"coordinates":[-116.786444,47.710962],"type":"Point"}
}