{
  "type": "Feature",
  "properties": {
    "iso:country":"US",
    "sg:address":"6479 N Fox Run Ave",
    "sg:city":"Meridian",
    "sg:classifiers":[
        {
            "category":"Building & Trades",
            "subcategory":"Construction",
            "type":"Services"
        }
    ],
    "sg:phone":"+1 208 898 9117",
    "sg:postcode":"83646",
    "sg:province":"ID",
    "sg:tags":[
        "maintenance",
        "contractor"
    ],
    "wof:name":"Foxtail Course Maintenance",
    "wof:placetype":"venue"
},
  "geometry": {"coordinates":[-116.402226,43.663877],"type":"Point"}
}