{
  "type": "Feature",
  "properties": {
    "addr:full":"2320 Orchard Rd Council ID 83612",
    "addr:housenumber":"2320",
    "addr:postcode":"83612",
    "addr:street":"Orchard Rd",
    "iso:country":"US",
    "sg:address":"2320 Orchard Rd",
    "sg:city":"Council",
    "sg:classifiers":[
        {
            "category":"Professional",
            "subcategory":"Research",
            "type":"Services"
        }
    ],
    "sg:phone":"+1 208 253 4612",
    "sg:postcode":"83612",
    "sg:province":"ID",
    "sg:tags":[
        "environmental",
        "ecological"
    ],
    "wof:name":"SEC Inc",
    "wof:placetype":"venue"
},
  "geometry": {"coordinates":[-116.42606499999999,44.752545],"type":"Point"}
}