{
  "type": "Feature",
  "properties": {
    "iso:country":"US",
    "sg:address":"225 N 9th St",
    "sg:city":"Boise",
    "sg:classifiers":[
        {
            "category":"Real Estate",
            "subcategory":"Real Estate Operator",
            "type":"Services"
        }
    ],
    "sg:phone":"+1 208 333 7000",
    "sg:postcode":"83702",
    "sg:province":"ID",
    "sg:tags":[
        "suite",
        "executive"
    ],
    "wof:name":"Christensen Corp",
    "wof:placetype":"venue"
},
  "geometry": {"coordinates":[-116.20338,43.617609],"type":"Point"}
}