{
  "type": "Feature",
  "properties": {
    "iso:country":"US",
    "sg:address":"439 W Main St",
    "sg:city":"St Anthony",
    "sg:classifiers":[
        {
            "category":"Freight",
            "type":"Transportation"
        }
    ],
    "sg:phone":"+1 208 624 4277",
    "sg:postcode":"83445",
    "sg:province":"ID",
    "sg:tags":[
        "operator",
        "hauling",
        "trucking"
    ],
    "wof:name":"M L Palmer Trucking",
    "wof:placetype":"venue"
},
  "geometry": {"coordinates":[-111.68862,43.966463],"type":"Point"}
}