{
  "type": "Feature",
  "properties": {
    "addr:full":"16429 McDermott Rd Nampa ID 83687",
    "addr:housenumber":"16429",
    "addr:postcode":"83687",
    "addr:street":"Mcdermott Rd",
    "iso:country":"US",
    "sg:address":"16429 McDermott Rd",
    "sg:city":"Nampa",
    "sg:classifiers":[
        {
            "category":"Building & Trades",
            "subcategory":"Construction",
            "type":"Services"
        }
    ],
    "sg:phone":"+1 208 466 2953",
    "sg:postcode":"83687",
    "sg:province":"ID",
    "sg:tags":[
        "excavating",
        "contractor"
    ],
    "wof:name":"Paul Construction",
    "wof:placetype":"venue"
},
  "geometry": {"coordinates":[-116.47368400000001,43.611866],"type":"Point"}
}