{
  "type": "Feature",
  "properties": {
    "addr:full":"2376 E Hwy 2 Oldtown ID 83822",
    "addr:housenumber":"2376",
    "addr:postcode":"83822",
    "addr:street":"E Hwy 2",
    "iso:country":"US",
    "sg:address":"2376 E Hwy 2",
    "sg:city":"Oldtown",
    "sg:classifiers":[
        {
            "category":"Government",
            "subcategory":"Office",
            "type":"Public Place"
        }
    ],
    "sg:phone":"+1 208 437 3133",
    "sg:postcode":"83822",
    "sg:province":"ID",
    "sg:tags":[
        "federal"
    ],
    "wof:name":"US Army Corps Of Engineers",
    "wof:placetype":"venue"
},
  "geometry": {"coordinates":[-116.993011,48.180549],"type":"Point"}
}