{
  "type": "Feature",
  "properties": {
    "iso:country":"US",
    "sg:address":"6260 E Commerce Loop",
    "sg:city":"Post Falls",
    "sg:classifiers":[
        {
            "category":"Retail",
            "subcategory":"Auto Repair",
            "type":"Services"
        }
    ],
    "sg:phone":"+1 208 667 9339",
    "sg:postcode":"83854",
    "sg:province":"ID",
    "sg:tags":[
        "repairing",
        "automobile"
    ],
    "wof:name":"Marks Automotive",
    "wof:placetype":"venue"
},
  "geometry": {"coordinates":[-116.868672,47.704398],"type":"Point"}
}