{
  "type": "Feature",
  "properties": {
    "addr:full":"10264 W Overland Rd Boise ID 83709",
    "addr:housenumber":"10264",
    "addr:postcode":"83709",
    "addr:street":"W Overland Rd",
    "iso:country":"US",
    "sg:address":"10264 W Overland Rd",
    "sg:city":"Boise",
    "sg:classifiers":[
        {
            "category":"Ice Cream",
            "type":"Food & Drink"
        }
    ],
    "sg:menulink":"http://www.allmenus.com/id/boise-city/172814-dairy-queen/menu/",
    "sg:phone":"+1 208 323 2658",
    "sg:postcode":"83709",
    "sg:province":"ID",
    "sg:tags":[
        "burger",
        "american"
    ],
    "wof:name":"Dairy Queen",
    "wof:placetype":"venue"
},
  "geometry": {"coordinates":[-116.310177,43.590847],"type":"Point"}
}