{
  "type": "Feature",
  "properties": {
    "addr:full":"5216 Kootenai St Boise ID 83705",
    "addr:housenumber":"5216",
    "addr:postcode":"83705",
    "addr:street":"Kootenai St",
    "iso:country":"US",
    "sg:address":"5216 Kootenai St",
    "sg:city":"Boise",
    "sg:classifiers":[
        {
            "category":"Professional",
            "subcategory":"Advertising",
            "type":"Services"
        }
    ],
    "sg:phone":"+1 208 387 2686",
    "sg:postcode":"83705",
    "sg:province":"ID",
    "sg:tags":[
        "counselor"
    ],
    "wof:name":"Aurora Advertising",
    "wof:placetype":"venue"
},
  "geometry": {"coordinates":[-116.245796,43.593494],"type":"Point"}
}