{
  "type": "Feature",
  "properties": {
    "addr:full":"1398 S Hwy 191 Rexburg ID 83440",
    "addr:housenumber":"1398",
    "addr:postcode":"83440",
    "addr:street":"S Hwy 191",
    "iso:country":"US",
    "sg:address":"1398 S Hwy 191",
    "sg:city":"Rexburg",
    "sg:classifiers":[
        {
            "category":"Bars & Pubs",
            "type":"Food & Drink"
        }
    ],
    "sg:phone":"+1 208 356 9861",
    "sg:postcode":"83440",
    "sg:province":"ID",
    "wof:name":"Miller's Hideaway Tavern",
    "wof:placetype":"venue"
},
  "geometry": {"coordinates":[-111.80647999999999,43.806535],"type":"Point"}
}