{
  "type": "Feature",
  "properties": {
    "iso:country":"US",
    "sg:address":"2058 Overland Ave",
    "sg:city":"Burley",
    "sg:classifiers":[
        {
            "category":"Professional",
            "subcategory":"Accounting & Tax Preparation",
            "type":"Services"
        }
    ],
    "sg:phone":"+1 208 878 9000",
    "sg:postcode":"83318",
    "sg:province":"ID",
    "sg:tags":[
        "accountant"
    ],
    "sg:website":"www.gpricecpa.com",
    "wof:name":"Garald Price & Assoc",
    "wof:placetype":"venue"
},
  "geometry": {"coordinates":[-113.793323,42.527401],"type":"Point"}
}