{
  "type": "Feature",
  "properties": {
    "iso:country":"US",
    "sg:address":"3560 Advent Gulch Rd",
    "sg:city":"Cambridge",
    "sg:classifiers":[
        {
            "category":"Farming",
            "subcategory":"Livestock Farm",
            "type":"Manufacturing & Wholesale Goods"
        }
    ],
    "sg:phone":"+1 208 257 3560",
    "sg:postcode":"83610",
    "sg:province":"ID",
    "sg:tags":[
        "ranch"
    ],
    "wof:name":"Showdown Ranch",
    "wof:placetype":"venue"
},
  "geometry": {"coordinates":[-116.798005,44.669016],"type":"Point"}
}