{
  "type": "Feature",
  "properties": {
    "addr:full":"2517 Main St Lewiston ID 83501",
    "addr:housenumber":"2517",
    "addr:postcode":"83501",
    "addr:street":"Main St",
    "iso:country":"US",
    "sg:address":"2517 Main St",
    "sg:city":"Lewiston",
    "sg:classifiers":[
        {
            "category":"Building & Trades",
            "subcategory":"Construction",
            "type":"Services"
        }
    ],
    "sg:phone":"+1 208 746 1351",
    "sg:postcode":"83501",
    "sg:province":"ID",
    "sg:tags":[
        "general",
        "contractor"
    ],
    "wof:name":"Kenaston Corp",
    "wof:placetype":"venue"
},
  "geometry": {"coordinates":[-116.995525,46.416091],"type":"Point"}
}