{
  "type": "Feature",
  "properties": {
    "addr:full":"1053 S Blvd Idaho Falls ID 83404",
    "addr:housenumber":"1053",
    "addr:postcode":"83404",
    "addr:street":"S Blvd",
    "iso:country":"US",
    "sg:address":"1053 S Blvd",
    "sg:city":"Idaho Falls",
    "sg:classifiers":[
        {
            "category":"Shopping",
            "type":"Retail Goods"
        }
    ],
    "sg:phone":"+1 208 529 2011",
    "sg:postcode":"83404",
    "sg:province":"ID",
    "sg:tags":[
        "ornamental",
        "nursery",
        "merchandise"
    ],
    "wof:name":"U-B Framed & Florals",
    "wof:placetype":"venue"
},
  "geometry": {"coordinates":[-112.033619,43.488495],"type":"Point"}
}