{
  "type": "Feature",
  "properties": {
    "iso:country":"US",
    "sg:address":"2020 N Lakewood Dr",
    "sg:city":"Coeur D Alene",
    "sg:classifiers":[
        {
            "category":"Banks & Credit Unions",
            "subcategory":"Investment Brokerage",
            "type":"Services"
        }
    ],
    "sg:phone":"+1 208 664 9294",
    "sg:postcode":"83814",
    "sg:province":"ID",
    "sg:tags":[
        "stock",
        "bond"
    ],
    "wof:name":"Edward Jones Co",
    "wof:placetype":"venue"
},
  "geometry": {"coordinates":[-116.801727,47.694655],"type":"Point"}
}