{
  "type": "Feature",
  "properties": {
    "addr:full":"20355 US Hwy 30 Buhl ID 83316",
    "addr:postcode":"20355;83316",
    "addr:street":"Us Hwy 30",
    "iso:country":"US",
    "sg:address":"20355 US Hwy 30",
    "sg:city":"Buhl",
    "sg:classifiers":[
        {
            "category":"Wholesale",
            "subcategory":"Machinery & Supplies",
            "type":"Manufacturing & Wholesale Goods"
        }
    ],
    "sg:phone":"+1 208 543 4342",
    "sg:postcode":"83316",
    "sg:province":"ID",
    "sg:tags":[
        "farm",
        "equipment"
    ],
    "wof:name":"Buhl Implement Co",
    "wof:placetype":"venue"
},
  "geometry": {"coordinates":[-114.731668,42.593458],"type":"Point"}
}