{
  "type": "Feature",
  "properties": {
    "addr:full":"6809 N 5600 E Preston ID 83263",
    "addr:housenumber":"6809;5600 e",
    "addr:postcode":"83263",
    "addr:street":"N",
    "iso:country":"US",
    "sg:address":"6809 N 5600 E",
    "sg:city":"Preston",
    "sg:classifiers":[
        {
            "category":"Retail",
            "subcategory":"Repair Shop",
            "type":"Services"
        }
    ],
    "sg:phone":"+1 208 852 0529",
    "sg:postcode":"83263",
    "sg:province":"ID",
    "sg:tags":[
        "welding"
    ],
    "wof:name":"S M Fabricating",
    "wof:placetype":"venue"
},
  "geometry": {"coordinates":[-111.747845,42.218591],"type":"Point"}
}