{
  "type": "Feature",
  "properties": {
    "iso:country":"US",
    "sg:address":"5900 Sweet Ola Hwy",
    "sg:city":"Sweet",
    "sg:classifiers":[
        {
            "category":"Building & Trades",
            "subcategory":"Construction",
            "type":"Services"
        }
    ],
    "sg:phone":"+1 208 584 3381",
    "sg:postcode":"83670",
    "sg:province":"ID",
    "sg:tags":[
        "light",
        "manufacturing"
    ],
    "wof:name":"Squaw Butte Construction Inc",
    "wof:placetype":"venue"
},
  "geometry": {"coordinates":[-116.33502300000001,43.947829],"type":"Point"}
}