{
  "type": "Feature",
  "properties": {
    "addr:full":"138 W Main St Rexburg ID 83440",
    "addr:housenumber":"138",
    "addr:postcode":"83440",
    "addr:street":"W Main St",
    "iso:country":"US",
    "sg:address":"138 W Main St",
    "sg:city":"Rexburg",
    "sg:classifiers":[
        {
            "category":"Restaurant",
            "type":"Food & Drink"
        },
        {
            "category":"Food & Beverages",
            "subcategory":"Fruits & Vegetables",
            "type":"Retail Goods"
        }
    ],
    "sg:menulink":"http://www.allmenus.com/id/thornton/135835-jamba-juice/menu/",
    "sg:phone":"+1 208 359 9617",
    "sg:postcode":"83440",
    "sg:province":"ID",
    "sg:tags":[
        "smoothy",
        "juice",
        "american"
    ],
    "wof:name":"Jamba Juice",
    "wof:placetype":"venue"
},
  "geometry": {"coordinates":[-111.787806,43.826064],"type":"Point"}
}