{
  "type": "Feature",
  "properties": {
    "iso:country":"US",
    "sg:address":"121 Broadway Ave S",
    "sg:city":"Buhl",
    "sg:classifiers":[
        {
            "category":"Retail",
            "subcategory":"Repair Shop",
            "type":"Services"
        }
    ],
    "sg:phone":"+1 208 543 2585",
    "sg:postcode":"83316",
    "sg:province":"ID",
    "wof:name":"Clock Shop",
    "wof:placetype":"venue"
},
  "geometry": {"coordinates":[-114.759567,42.59874],"type":"Point"}
}