{
  "type": "Feature",
  "properties": {
    "iso:country":"US",
    "sg:address":"116 S State St",
    "sg:city":"Preston",
    "sg:classifiers":[
        {
            "category":"Home & Garden",
            "subcategory":"Building Materials",
            "type":"Retail Goods"
        }
    ],
    "sg:phone":"+1 208 852 1202",
    "sg:postcode":"83263",
    "sg:province":"ID",
    "sg:tags":[
        "glass",
        "window",
        "plate"
    ],
    "wof:name":"Harris Collision Rpr & Glass",
    "wof:placetype":"venue"
},
  "geometry": {"coordinates":[-111.876693,42.093803],"type":"Point"}
}