{
  "type": "Feature",
  "properties": {
    "addr:full":"1578 S Timesquare Ln Boise ID 83709",
    "addr:housenumber":"1578",
    "addr:postcode":"83709",
    "addr:street":"S Timesquare Ln",
    "iso:country":"US",
    "sg:address":"1578 S Timesquare Ln",
    "sg:city":"Boise",
    "sg:classifiers":[
        {
            "category":"Professional",
            "subcategory":"Management & Consulting",
            "type":"Services"
        }
    ],
    "sg:phone":"+1 208 338 6586",
    "sg:postcode":"83709",
    "sg:province":"ID",
    "sg:tags":[
        "career",
        "transition"
    ],
    "wof:name":"Lee Hecht Harrison LLC",
    "wof:placetype":"venue"
},
  "geometry": {"coordinates":[-116.30117199999999,43.590719],"type":"Point"}
}