{
  "type": "Feature",
  "properties": {
    "addr:full":"921 N Main St Meridian ID 83647",
    "addr:housenumber":"921",
    "addr:postcode":"83647",
    "addr:street":"N Main St",
    "iso:country":"US",
    "sg:address":"921 N Main St",
    "sg:city":"Meridian",
    "sg:classifiers":[
        {
            "category":"Banks & Credit Unions",
            "subcategory":"Investment Brokerage",
            "type":"Services"
        }
    ],
    "sg:phone":"+1 208 888 9666",
    "sg:postcode":"83647",
    "sg:province":"ID",
    "sg:tags":[
        "funds",
        "mutual"
    ],
    "wof:name":"Edward Jones Co",
    "wof:placetype":"venue"
},
  "geometry": {"coordinates":[-115.70225499999999,43.13964],"type":"Point"}
}