{
  "type": "Feature",
  "properties": {
    "iso:country":"US",
    "sg:address":"2828 Airport Way",
    "sg:city":"Boise",
    "sg:classifiers":[
        {
            "category":"Restaurant",
            "type":"Food & Drink"
        }
    ],
    "sg:menulink":"http://www.allmenus.com/id/boise-city/212068-mcdonalds/menu/",
    "sg:postcode":"83705",
    "sg:province":"ID",
    "sg:tags":[
        "burger",
        "american"
    ],
    "wof:name":"McDonald's",
    "wof:placetype":"venue"
},
  "geometry": {"coordinates":[-116.216948,43.569712],"type":"Point"}
}