{
  "type": "Feature",
  "properties": {
    "iso:country":"US",
    "sg:address":"1291 N Salem Rd",
    "sg:city":"Rexburg",
    "sg:classifiers":[
        {
            "category":"Building & Trades",
            "subcategory":"Plumbing",
            "type":"Services"
        }
    ],
    "sg:phone":"+1 208 356 4111",
    "sg:postcode":"83440",
    "sg:province":"ID",
    "sg:tags":[
        "plumbing",
        "contractor"
    ],
    "wof:name":"Holley Plumbing & Heating",
    "wof:placetype":"venue"
},
  "geometry": {"coordinates":[-111.77812,43.844782],"type":"Point"}
}