{
  "type": "Feature",
  "properties": {
    "iso:country":"US",
    "sg:address":"6855 S 15th E",
    "sg:city":"Idaho Falls",
    "sg:classifiers":[
        {
            "category":"Sports & Exercise",
            "subcategory":"Race Track",
            "type":"Entertainment"
        }
    ],
    "sg:phone":"+1 208 529 0671",
    "sg:postcode":"83404",
    "sg:province":"ID",
    "wof:name":"Sandy Downs",
    "wof:placetype":"venue"
},
  "geometry": {"coordinates":[-112.003749,43.435074],"type":"Point"}
}