{
  "type": "Feature",
  "properties": {
    "addr:full":"5620 E Hill Rd Boise ID 83703",
    "addr:housenumber":"5620",
    "addr:postcode":"83703",
    "addr:street":"E Hill Rd",
    "iso:country":"US",
    "sg:address":"5620 E Hill Rd",
    "sg:city":"Boise",
    "sg:classifiers":[
        {
            "category":"Retail",
            "subcategory":"Repair Shop",
            "type":"Services"
        }
    ],
    "sg:phone":"+1 208 343 4440",
    "sg:postcode":"83703",
    "sg:province":"ID",
    "sg:tags":[
        "equipment",
        "establishment",
        "taxidermist"
    ],
    "wof:name":"Gene's Taxidermy",
    "wof:placetype":"venue"
},
  "geometry": {"coordinates":[-116.26328599999999,43.675877],"type":"Point"}
}