{
  "type": "Feature",
  "properties": {
    "iso:country":"US",
    "sg:address":"410 Old State Hwy",
    "sg:city":"Cascade",
    "sg:classifiers":[
        {
            "category":"Real Estate",
            "subcategory":"Real Estate Operator",
            "type":"Services"
        }
    ],
    "sg:phone":"+1 208 382 6201",
    "sg:postcode":"83611",
    "sg:province":"ID",
    "sg:tags":[
        "apartment"
    ],
    "wof:name":"Claremont Apartments",
    "wof:placetype":"venue"
},
  "geometry": {"coordinates":[-116.04899,44.517966],"type":"Point"}
}