{
  "type": "Feature",
  "properties": {
    "iso:country":"US",
    "sg:address":"11850 N Forest Rd",
    "sg:city":"Hayden",
    "sg:classifiers":[
        {
            "category":"Building & Trades",
            "subcategory":"Construction",
            "type":"Services"
        }
    ],
    "sg:phone":"+1 208 762 4142",
    "sg:postcode":"83835",
    "sg:province":"ID",
    "sg:tags":[
        "new",
        "remodel"
    ],
    "wof:name":"Mr Homework",
    "wof:placetype":"venue"
},
  "geometry": {"coordinates":[-116.784672,47.779542],"type":"Point"}
}