{
  "type": "Feature",
  "properties": {
    "iso:country":"US",
    "sg:address":"305 E Idaho Ave",
    "sg:city":"Homedale",
    "sg:classifiers":[
        {
            "category":"Restaurant",
            "type":"Food & Drink"
        }
    ],
    "sg:phone":"+1 208 337 4243",
    "sg:postcode":"83628",
    "sg:province":"ID",
    "wof:name":"Homedale Drive In",
    "wof:placetype":"venue"
},
  "geometry": {"coordinates":[-116.928978,43.617811],"type":"Point"}
}