{
  "type": "Feature",
  "properties": {
    "iso:country":"US",
    "sg:address":"343 Call Ave",
    "sg:city":"Idaho Falls",
    "sg:classifiers":[
        {
            "category":"Travel",
            "subcategory":"Hotels & Motels",
            "type":"Entertainment"
        }
    ],
    "sg:phone":"+1 208 525 9958",
    "sg:postcode":"83402",
    "sg:province":"ID",
    "sg:tags":[
        "operation"
    ],
    "wof:name":"Ross Hotel",
    "wof:placetype":"venue"
},
  "geometry": {"coordinates":[-112.070014,43.494701],"type":"Point"}
}