{
  "type": "Feature",
  "properties": {
    "addr:full":"66 2nd St S Nampa ID 83651",
    "addr:housenumber":"66",
    "addr:postcode":"83651",
    "addr:street":"2Nd St S",
    "iso:country":"US",
    "sg:address":"66 2nd St S",
    "sg:city":"Nampa",
    "sg:classifiers":[
        {
            "category":"Cinema",
            "subcategory":"Movie Rental",
            "type":"Entertainment"
        }
    ],
    "sg:phone":"+1 208 461 4144",
    "sg:postcode":"83651",
    "sg:province":"ID",
    "sg:tags":[
        "video",
        "game",
        "leasing"
    ],
    "wof:name":"Game Crazy",
    "wof:placetype":"venue"
},
  "geometry": {"coordinates":[-116.572497,43.58607],"type":"Point"}
}