{
  "type": "Feature",
  "properties": {
    "addr:full":"5285 Glenwood St Garden City ID 83714",
    "addr:housenumber":"5285",
    "addr:postcode":"83714",
    "addr:street":"Glenwood St",
    "iso:country":"US",
    "sg:address":"5285 Glenwood St",
    "sg:city":"Garden City",
    "sg:classifiers":[
        {
            "category":"Restaurant",
            "type":"Food & Drink"
        }
    ],
    "sg:menulink":"http://www.allmenus.com/id/boise-city/78922-pizza-hut/menu/",
    "sg:phone":"+1 208 322 5562",
    "sg:postcode":"83714",
    "sg:province":"ID",
    "sg:tags":[
        "american",
        "pizza"
    ],
    "wof:name":"Pizza Hut",
    "wof:placetype":"venue"
},
  "geometry": {"coordinates":[-116.27975000000001,43.65342],"type":"Point"}
}