{
  "type": "Feature",
  "properties": {
    "iso:country":"US",
    "sg:address":"2306 N Whitley Dr",
    "sg:city":"Fruitland",
    "sg:classifiers":[
        {
            "category":"Retail",
            "subcategory":"Auto Repair",
            "type":"Services"
        }
    ],
    "sg:phone":"+1 208 452 4774",
    "sg:postcode":"83619",
    "sg:province":"ID",
    "sg:tags":[
        "muffler",
        "exhaust",
        "system"
    ],
    "wof:name":"A-1 Speed-O-Motive Muffler Svc",
    "wof:placetype":"venue"
},
  "geometry": {"coordinates":[-116.923503,44.032088],"type":"Point"}
}