{
  "type": "Feature",
  "properties": {
    "iso:country":"US",
    "sg:address":"513 E 22nd Ave",
    "sg:city":"Post Falls",
    "sg:classifiers":[
        {
            "category":"Manufacturing",
            "subcategory":"Tools & Machinery",
            "type":"Manufacturing & Wholesale Goods"
        }
    ],
    "sg:phone":"+1 208 773 5164",
    "sg:postcode":"83854",
    "sg:province":"ID",
    "sg:tags":[
        "fire",
        "fighting"
    ],
    "wof:name":"Alexanders Company",
    "wof:placetype":"venue"
},
  "geometry": {"coordinates":[-116.942442,47.729478],"type":"Point"}
}