{
  "type": "Feature",
  "properties": {
    "iso:country":"US",
    "sg:address":"514 E Galloway St",
    "sg:city":"Weiser",
    "sg:classifiers":[
        {
            "category":"Professional",
            "subcategory":"Management & Consulting",
            "type":"Services"
        }
    ],
    "sg:phone":"+1 208 549 2219",
    "sg:postcode":"83672",
    "sg:province":"ID",
    "sg:tags":[
        "home",
        "demonstration"
    ],
    "wof:name":"Essence Of Romance By Heather",
    "wof:placetype":"venue"
},
  "geometry": {"coordinates":[-116.95987700000001,44.250338],"type":"Point"}
}