{
  "type": "Feature",
  "properties": {
    "iso:country":"US",
    "sg:address":"2500 W A St Ste 201",
    "sg:city":"Moscow",
    "sg:classifiers":[
        {
            "category":"Health Services",
            "subcategory":"Doctor",
            "type":"Services"
        }
    ],
    "sg:phone":"+1 208 883 2828",
    "sg:postcode":"83843",
    "sg:province":"ID",
    "sg:tags":[
        "physician",
        "pediatrics-orthopedic",
        "surgeons",
        "orthopedics",
        "surgeon",
        "surgery"
    ],
    "wof:name":"Jacobson, Charles A Md",
    "wof:placetype":"venue"
},
  "geometry": {"coordinates":[-117.020502,46.735282],"type":"Point"}
}