{
  "type": "Feature",
  "properties": {
    "iso:country":"US",
    "sg:address":"205 E 42nd St",
    "sg:city":"Boise",
    "sg:classifiers":[
        {
            "category":"Mining & Drilling",
            "type":"Manufacturing & Wholesale Goods"
        }
    ],
    "sg:phone":"+1 208 375 4990",
    "sg:postcode":"83714",
    "sg:province":"ID",
    "sg:tags":[
        "stone"
    ],
    "wof:name":"Mike's Stone Supply",
    "wof:placetype":"venue"
},
  "geometry": {"coordinates":[-116.247067,43.634471],"type":"Point"}
}