{
  "type": "Feature",
  "properties": {
    "addr:full":"85 S Cole Rd Boise ID 83709",
    "addr:housenumber":"85",
    "addr:postcode":"83709",
    "addr:street":"S Cole Rd",
    "iso:country":"US",
    "sg:address":"85 S Cole Rd",
    "sg:city":"Boise",
    "sg:classifiers":[
        {
            "category":"Insurance",
            "subcategory":"Insurance Agent",
            "type":"Services"
        }
    ],
    "sg:phone":"+1 208 327 9545",
    "sg:postcode":"83709",
    "sg:province":"ID",
    "wof:name":"Enhanced Benefit Svc",
    "wof:placetype":"venue"
},
  "geometry": {"coordinates":[-116.274272,43.6039],"type":"Point"}
}