{
  "type": "Feature",
  "properties": {
    "addr:full":"2320 Caldwell Blvd Nampa ID 83651",
    "addr:housenumber":"2320",
    "addr:postcode":"83651",
    "addr:street":"Caldwell Blvd",
    "iso:country":"US",
    "sg:address":"2320 Caldwell Blvd",
    "sg:city":"Nampa",
    "sg:classifiers":[
        {
            "category":"Professional",
            "subcategory":"Accounting & Tax Preparation",
            "type":"Services"
        }
    ],
    "sg:phone":"+1 208 467 3320",
    "sg:postcode":"83651",
    "sg:province":"ID",
    "sg:tags":[
        "return",
        "filing"
    ],
    "wof:name":"H & R Block Tax Svc",
    "wof:placetype":"venue"
},
  "geometry": {"coordinates":[-116.610562,43.61079],"type":"Point"}
}