{
  "type": "Feature",
  "properties": {
    "iso:country":"US",
    "sg:address":"159 S Main St",
    "sg:city":"Soda Springs",
    "sg:classifiers":[
        {
            "category":"Government",
            "subcategory":"Office",
            "type":"Public Place"
        }
    ],
    "sg:phone":"+1 208 547 2164",
    "sg:postcode":"83276",
    "sg:province":"ID",
    "wof:name":"Caribou County Data Processing",
    "wof:placetype":"venue"
},
  "geometry": {"coordinates":[-111.60363099999999,42.655576],"type":"Point"}
}