{
  "type": "Feature",
  "properties": {
    "addr:full":"487 State Hwy 34 Grace ID 83241",
    "addr:housenumber":"487",
    "addr:postcode":"83241",
    "addr:street":"State Hwy 34 Grace",
    "iso:country":"US",
    "sg:address":"487 State Hwy 34",
    "sg:city":"Grace",
    "sg:phone":"+1 208 425 3660",
    "sg:postcode":"83241",
    "sg:province":"ID",
    "sg:tags":[
        "farm",
        "wheat"
    ],
    "wof:name":"Paul Jenkins",
    "wof:placetype":"venue"
},
  "geometry": {"coordinates":[-111.73045999999999,42.580308],"type":"Point"}
}