{
  "type": "Feature",
  "properties": {
    "addr:full":"9118 W Black Eagle Dr Boise ID 83709",
    "addr:housenumber":"9118",
    "addr:postcode":"83709",
    "addr:street":"W Black Eagle Dr",
    "iso:country":"US",
    "sg:address":"9118 W Black Eagle Dr",
    "sg:city":"Boise",
    "sg:classifiers":[
        {
            "category":"Manufacturing",
            "subcategory":"Electronics",
            "type":"Manufacturing & Wholesale Goods"
        }
    ],
    "sg:phone":"+1 208 375 3666",
    "sg:postcode":"83709",
    "sg:province":"ID",
    "sg:tags":[
        "semiconductor",
        "devices"
    ],
    "wof:name":"KLA-Tencor Corp",
    "wof:placetype":"venue"
},
  "geometry": {"coordinates":[-116.29526799999999,43.592045],"type":"Point"}
}