{
  "type": "Feature",
  "properties": {
    "addr:full":"9780 W Milclay St Boise ID 83704",
    "addr:housenumber":"9780",
    "addr:postcode":"83704",
    "addr:street":"W Milclay St",
    "iso:country":"US",
    "sg:address":"9780 W Milclay St",
    "sg:city":"Boise",
    "sg:classifiers":[
        {
            "category":"Professional",
            "subcategory":"Lawyer & Legal Services",
            "type":"Services"
        }
    ],
    "sg:phone":"+1 208 321 7597",
    "sg:postcode":"83704",
    "sg:province":"ID",
    "wof:name":"J Tech Enterprises",
    "wof:placetype":"venue"
},
  "geometry": {"coordinates":[-116.303906,43.635759],"type":"Point"}
}