{
  "type": "Feature",
  "properties": {
    "iso:country":"US",
    "sg:address":"3409 Chinden Blvd",
    "sg:city":"Boise",
    "sg:classifiers":[
        {
            "category":"Personal",
            "subcategory":"Tattoo Parlor",
            "type":"Services"
        }
    ],
    "sg:phone":"+1 208 344 0804",
    "sg:postcode":"83714",
    "sg:province":"ID",
    "sg:tags":[
        "tattooing"
    ],
    "wof:name":"Garden City Tattoo",
    "wof:placetype":"venue"
},
  "geometry": {"coordinates":[-116.240186,43.62319],"type":"Point"}
}