{
  "type": "Feature",
  "properties": {
    "iso:country":"US",
    "sg:address":"229 Monteval Rd",
    "sg:city":"Careywood",
    "sg:classifiers":[
        {
            "category":"Retail",
            "subcategory":"Auto Repair",
            "type":"Services"
        }
    ],
    "sg:phone":"+1 208 683 3342",
    "sg:postcode":"83809",
    "sg:province":"ID",
    "sg:tags":[
        "automotive"
    ],
    "wof:name":"Mountainside Shop",
    "wof:placetype":"venue"
},
  "geometry": {"coordinates":[-116.558465,48.067713],"type":"Point"}
}