{
  "type": "Feature",
  "properties": {
    "addr:full":"215 E Hawaii Ave Nampa ID 83686",
    "addr:housenumber":"215",
    "addr:postcode":"83686",
    "addr:street":"E Hawaii Ave",
    "iso:country":"US",
    "sg:address":"215 E Hawaii Ave",
    "sg:city":"Nampa",
    "sg:classifiers":[
        {
            "category":"Health Services",
            "subcategory":"Doctor",
            "type":"Services"
        }
    ],
    "sg:phone":"+1 208 884 2909",
    "sg:postcode":"83686",
    "sg:province":"ID",
    "sg:tags":[
        "physician",
        "surgeon"
    ],
    "wof:name":"Tom Douthit MD",
    "wof:placetype":"venue"
},
  "geometry": {"coordinates":[-116.57017500000001,43.555044],"type":"Point"}
}