{
  "type": "Feature",
  "properties": {
    "iso:country":"US",
    "sg:address":"209 E Superior St",
    "sg:city":"Sandpoint",
    "sg:classifiers":[
        {
            "category":"Restaurant",
            "type":"Food & Drink"
        }
    ],
    "sg:phone":"+1 208 265 4075",
    "sg:postcode":"83864",
    "sg:province":"ID",
    "wof:name":"Edguapos",
    "wof:placetype":"venue"
},
  "geometry": {"coordinates":[-116.54746400000001,48.270879],"type":"Point"}
}