{
  "type": "Feature",
  "properties": {
    "iso:country":"US",
    "sg:address":"516 W Main St",
    "sg:city":"Jerome",
    "sg:classifiers":[
        {
            "category":"Building & Trades",
            "subcategory":"Construction",
            "type":"Services"
        }
    ],
    "sg:phone":"+1 208 324 8640",
    "sg:postcode":"83338",
    "sg:province":"ID",
    "sg:tags":[
        "contractor"
    ],
    "wof:name":"Franklin Building Truss Plant",
    "wof:placetype":"venue"
},
  "geometry": {"coordinates":[-114.526507,42.724228],"type":"Point"}
}