{
  "type": "Feature",
  "properties": {
    "addr:full":"18 Ranft Dr Idaho City ID 83631",
    "addr:housenumber":"18",
    "addr:postcode":"83631",
    "addr:street":"Ranft Dr",
    "iso:country":"US",
    "sg:address":"18 Ranft Dr",
    "sg:city":"Idaho City",
    "sg:classifiers":[
        {
            "category":"Shopping",
            "subcategory":"Hobbies, Toys, & Games",
            "type":"Retail Goods"
        }
    ],
    "sg:phone":"+1 208 392 6062",
    "sg:postcode":"83631",
    "sg:province":"ID",
    "sg:tags":[
        "craft"
    ],
    "wof:name":"Fireside Soap Works",
    "wof:placetype":"venue"
},
  "geometry": {"coordinates":[-115.96204899999999,43.914716],"type":"Point"}
}