{
  "type": "Feature",
  "properties": {
    "addr:full":"67 Center St Lava Hot Springs ID 83246",
    "addr:housenumber":"67",
    "addr:postcode":"83246",
    "addr:street":"Center St",
    "iso:country":"US",
    "sg:address":"67 Center St",
    "sg:city":"Lava Hot Springs",
    "sg:classifiers":[
        {
            "category":"Retail",
            "subcategory":"Auto Repair",
            "type":"Services"
        }
    ],
    "sg:phone":"+1 208 776 5837",
    "sg:postcode":"83246",
    "sg:province":"ID",
    "sg:tags":[
        "repairing",
        "automobile"
    ],
    "wof:name":"Shane's Service Station",
    "wof:placetype":"venue"
},
  "geometry": {"coordinates":[-112.012298,42.618796],"type":"Point"}
}