{
  "type": "Feature",
  "properties": {
    "iso:country":"US",
    "sg:address":"406 S 14th St",
    "sg:city":"Coeur D Alene",
    "sg:classifiers":[
        {
            "category":"Building & Trades",
            "subcategory":"Construction",
            "type":"Services"
        }
    ],
    "sg:phone":"+1 208 664 8672",
    "sg:postcode":"83814",
    "sg:province":"ID",
    "sg:tags":[
        "house"
    ],
    "wof:name":"American Commercial Builder",
    "wof:placetype":"venue"
},
  "geometry": {"coordinates":[-116.765823,47.670808],"type":"Point"}
}