{
  "type": "Feature",
  "properties": {
    "addr:full":"3305 Spiceland Dr Boise ID 83704",
    "addr:housenumber":"3305",
    "addr:postcode":"83704",
    "addr:street":"Spiceland Dr",
    "iso:country":"US",
    "sg:address":"3305 Spiceland Dr",
    "sg:city":"Boise",
    "sg:classifiers":[
        {
            "category":"Manufacturing",
            "subcategory":"Printing",
            "type":"Manufacturing & Wholesale Goods"
        }
    ],
    "sg:phone":"+1 208 322 1456",
    "sg:postcode":"83704",
    "sg:province":"ID",
    "sg:tags":[
        "publisher"
    ],
    "wof:name":"Spencer Books",
    "wof:placetype":"venue"
},
  "geometry": {"coordinates":[-116.30122900000001,43.635691],"type":"Point"}
}