{
  "type": "Feature",
  "properties": {
    "iso:country":"US",
    "sg:address":"827 Park Blvd",
    "sg:city":"Boise",
    "sg:classifiers":[
        {
            "category":"Professional",
            "subcategory":"Accounting & Tax Preparation",
            "type":"Services"
        }
    ],
    "sg:phone":"+1 208 336 1740",
    "sg:postcode":"83712",
    "sg:province":"ID",
    "sg:tags":[
        "accountant"
    ],
    "sg:website":"www.gtgcpa.com",
    "wof:name":"Gunther Tondrick & Goode",
    "wof:placetype":"venue"
},
  "geometry": {"coordinates":[-116.19000699999999,43.603605],"type":"Point"}
}