{
  "type": "Feature",
  "properties": {
    "addr:full":"2050 S Washington Ave Emmett ID 83617",
    "addr:housenumber":"2050",
    "addr:postcode":"83617",
    "addr:street":"S Washington Ave",
    "iso:country":"US",
    "sg:address":"2050 S Washington Ave",
    "sg:city":"Emmett",
    "sg:classifiers":[
        {
            "category":"Retail",
            "subcategory":"Auto Repair",
            "type":"Services"
        }
    ],
    "sg:phone":"+1 208 365 3216",
    "sg:postcode":"83617",
    "sg:province":"ID",
    "sg:tags":[
        "repairing",
        "automobile"
    ],
    "wof:name":"Ed's Automotive Repair",
    "wof:placetype":"venue"
},
  "geometry": {"coordinates":[-116.49988,43.860741],"type":"Point"}
}