{
  "type": "Feature",
  "properties": {
    "addr:full":"437 Wyoming St Gooding ID 83330",
    "addr:housenumber":"437",
    "addr:postcode":"83330",
    "addr:street":"Wyoming St",
    "iso:country":"US",
    "sg:address":"437 Wyoming St",
    "sg:city":"Gooding",
    "sg:classifiers":[
        {
            "category":"Building & Trades",
            "subcategory":"Cleaning & Sanitation",
            "type":"Services"
        }
    ],
    "sg:phone":"+1 208 423 4850",
    "sg:postcode":"83330",
    "sg:province":"ID",
    "sg:tags":[
        "maintenance"
    ],
    "wof:name":"Magic Valley Maid Service",
    "wof:placetype":"venue"
},
  "geometry": {"coordinates":[-114.70911599999999,42.941289],"type":"Point"}
}