{
  "type": "Feature",
  "properties": {
    "iso:country":"US",
    "sg:address":"627 N Dupont Ave",
    "sg:city":"Boise",
    "sg:classifiers":[
        {
            "category":"Shopping",
            "subcategory":"Bicycles & Sporting Goods",
            "type":"Retail Goods"
        }
    ],
    "sg:phone":"+1 208 658 8808",
    "sg:postcode":"83713",
    "sg:province":"ID",
    "sg:tags":[
        "equipment",
        "exercise"
    ],
    "wof:name":"Upper Limit Fitness",
    "wof:placetype":"venue"
},
  "geometry": {"coordinates":[-116.338043,43.609259],"type":"Point"}
}