{
  "type": "Feature",
  "properties": {
    "iso:country":"US",
    "sg:address":"1208 E Linden St",
    "sg:city":"Caldwell",
    "sg:classifiers":[
        {
            "category":"Organizations",
            "subcategory":"Non-profit Organization",
            "type":"Services"
        }
    ],
    "sg:phone":"+1 208 454 1744",
    "sg:postcode":"83605",
    "sg:province":"ID",
    "sg:tags":[
        "info",
        "addiction",
        "abuse",
        "treatment",
        "drug"
    ],
    "wof:name":"Linden House",
    "wof:placetype":"venue"
},
  "geometry": {"coordinates":[-116.68427200000001,43.647951],"type":"Point"}
}