{
  "type": "Feature",
  "properties": {
    "iso:country":"US",
    "sg:address":"122 W Simplot Blvd",
    "sg:city":"Caldwell",
    "sg:phone":"+1 208 459 0121",
    "sg:postcode":"83605",
    "sg:province":"ID",
    "sg:tags":[
        "oil"
    ],
    "wof:name":"Baird Oil",
    "wof:placetype":"venue"
},
  "geometry": {"coordinates":[-116.70279600000001,43.669618],"type":"Point"}
}