{
  "type": "Feature",
  "properties": {
    "iso:country":"US",
    "sg:address":"173 E Main St",
    "sg:city":"Rigby",
    "sg:classifiers":[
        {
            "category":"Sports & Exercise",
            "subcategory":"Gym",
            "type":"Entertainment"
        }
    ],
    "sg:phone":"+1 208 745 8073",
    "sg:postcode":"83442",
    "sg:province":"ID",
    "sg:tags":[
        "club",
        "health",
        "studio",
        "gymnasium"
    ],
    "wof:name":"Rigby Recreation Ctr",
    "wof:placetype":"venue"
},
  "geometry": {"coordinates":[-111.912763,43.672297],"type":"Point"}
}