{
  "type": "Feature",
  "properties": {
    "iso:country":"US",
    "sg:address":"218 S Main St",
    "sg:city":"Moscow",
    "sg:phone":"+1 208 882 1324",
    "sg:postcode":"83843",
    "sg:province":"ID",
    "sg:website":"http://www.sistersbrew.com",
    "wof:name":"Sisters' Brew Coffee House",
    "wof:placetype":"venue"
},
  "geometry": {"coordinates":[-117.001389,46.732888],"type":"Point"}
}