{
  "type": "Feature",
  "properties": {
    "addr:full":"6836 Glenwood St Boise ID 83714",
    "addr:housenumber":"6836",
    "addr:postcode":"83714",
    "addr:street":"Glenwood St",
    "iso:country":"US",
    "sg:address":"6836 Glenwood St",
    "sg:city":"Boise",
    "sg:classifiers":[
        {
            "category":"Banks & Credit Unions",
            "subcategory":"Investment Brokerage",
            "type":"Services"
        }
    ],
    "sg:phone":"+1 208 853 3800",
    "sg:postcode":"83714",
    "sg:province":"ID",
    "sg:tags":[
        "security"
    ],
    "wof:name":"Great Northern Financial",
    "wof:placetype":"venue"
},
  "geometry": {"coordinates":[-116.279253,43.664761],"type":"Point"}
}