{
  "type": "Feature",
  "properties": {
    "iso:country":"US",
    "sg:address":"1526 Overland Ave",
    "sg:city":"Burley",
    "sg:classifiers":[
        {
            "category":"Insurance",
            "subcategory":"Insurance Agent",
            "type":"Services"
        }
    ],
    "sg:phone":"+1 208 678 0420",
    "sg:postcode":"83318",
    "sg:province":"ID",
    "wof:name":"Financial Strategies",
    "wof:placetype":"venue"
},
  "geometry": {"coordinates":[-113.793322,42.533856],"type":"Point"}
}