{
  "type": "Feature",
  "properties": {
    "iso:country":"US",
    "sg:address":"6570 S Federal Way",
    "sg:city":"Boise",
    "sg:classifiers":[
        {
            "category":"Personal",
            "subcategory":"Beauty Salon",
            "type":"Services"
        }
    ],
    "sg:phone":"+1 208 333 8677",
    "sg:postcode":"83716",
    "sg:province":"ID",
    "wof:name":"Supercuts",
    "wof:placetype":"venue"
},
  "geometry": {"coordinates":[-116.15532,43.541214],"type":"Point"}
}