{
  "type": "Feature",
  "properties": {
    "iso:country":"US",
    "sg:address":"2108 Caldwell Blvd",
    "sg:city":"Nampa",
    "sg:classifiers":[
        {
            "category":"Shopping",
            "subcategory":"Jewelry",
            "type":"Retail Goods"
        }
    ],
    "sg:phone":"+1 208 461 0677",
    "sg:postcode":"83651",
    "sg:province":"ID",
    "sg:tags":[
        "jeweler"
    ],
    "wof:name":"LA Don's Fine Jewelry",
    "wof:placetype":"venue"
},
  "geometry": {"coordinates":[-116.604946,43.607139],"type":"Point"}
}