{
  "type": "Feature",
  "properties": {
    "iso:country":"US",
    "sg:address":"364 N Main St",
    "sg:city":"Moscow",
    "sg:classifiers":[
        {
            "category":"Restaurant",
            "type":"Food & Drink"
        }
    ],
    "sg:phone":"+1 208 882 0848",
    "sg:postcode":"83843",
    "sg:province":"ID",
    "wof:name":"Mark Iv Restaurant",
    "wof:placetype":"venue"
},
  "geometry": {"coordinates":[-117.001395,46.736979],"type":"Point"}
}