{
  "type": "Feature",
  "properties": {
    "iso:country":"US",
    "sg:address":"913 Warner Ave",
    "sg:city":"Lewiston",
    "sg:classifiers":[
        {
            "category":"Building & Trades",
            "subcategory":"Construction",
            "type":"Services"
        }
    ],
    "sg:phone":"+1 208 746 9379",
    "sg:postcode":"83501",
    "sg:province":"ID",
    "sg:tags":[
        "house"
    ],
    "wof:name":"Orchard Builders",
    "wof:placetype":"venue"
},
  "geometry": {"coordinates":[-116.982361,46.384035],"type":"Point"}
}