{
  "type": "Feature",
  "properties": {
    "iso:country":"US",
    "sg:address":"1236 Yellowstone Ave",
    "sg:city":"Pocatello",
    "sg:classifiers":[
        {
            "category":"Retail",
            "subcategory":"Car Wash",
            "type":"Services"
        }
    ],
    "sg:phone":"+1 208 238 9144",
    "sg:postcode":"83201",
    "sg:province":"ID",
    "sg:tags":[
        "polishing",
        "washing"
    ],
    "wof:name":"Pro-Clean Car Wash Of Idaho",
    "wof:placetype":"venue"
},
  "geometry": {"coordinates":[-112.451292,42.89651],"type":"Point"}
}