{
  "type": "Feature",
  "properties": {
    "addr:full":"480 E Orchard Ave Hayden Lake ID 83835",
    "addr:housenumber":"480",
    "addr:postcode":"83835",
    "addr:street":"E Orchard Ave",
    "iso:country":"US",
    "sg:address":"480 E Orchard Ave",
    "sg:city":"Hayden Lake",
    "sg:classifiers":[
        {
            "category":"Building & Trades",
            "subcategory":"Construction",
            "type":"Services"
        }
    ],
    "sg:phone":"+1 208 772 5357",
    "sg:postcode":"83835",
    "sg:province":"ID",
    "sg:tags":[
        "excavating",
        "contractor"
    ],
    "wof:name":"Ken Bettis Excavating",
    "wof:placetype":"venue"
},
  "geometry": {"coordinates":[-116.780575,47.755271],"type":"Point"}
}