{
  "type": "Feature",
  "properties": {
    "iso:country":"US",
    "sg:address":"8057 Emerald St",
    "sg:city":"Boise",
    "sg:classifiers":[
        {
            "category":"Shopping",
            "subcategory":"Bicycles & Sporting Goods",
            "type":"Retail Goods"
        }
    ],
    "sg:phone":"+1 208 322 4653",
    "sg:postcode":"83704",
    "sg:province":"ID",
    "sg:tags":[
        "equipment",
        "golf",
        "supply"
    ],
    "wof:name":"Wide World Of Golf & Tennis",
    "wof:placetype":"venue"
},
  "geometry": {"coordinates":[-116.282056,43.61139],"type":"Point"}
}