{
  "type": "Feature",
  "properties": {
    "addr:full":"5725 W Fairview Ave Boise ID 83706",
    "addr:housenumber":"5725",
    "addr:postcode":"83706",
    "addr:street":"W Fairview Ave",
    "iso:country":"US",
    "sg:address":"5725 W Fairview Ave",
    "sg:city":"Boise",
    "sg:classifiers":[
        {
            "category":"Shopping",
            "subcategory":"Crafts & Fabrics",
            "type":"Retail Goods"
        }
    ],
    "sg:phone":"+1 208 376 0087",
    "sg:postcode":"83706",
    "sg:province":"ID",
    "sg:tags":[
        "material",
        "quilting",
        "supply"
    ],
    "sg:website":"www.quiltcrossing.com",
    "wof:name":"Quilt Crossing",
    "wof:placetype":"venue"
},
  "geometry": {"coordinates":[-116.25326,43.618967],"type":"Point"}
}