{
  "type": "Feature",
  "properties": {
    "addr:full":"612 Dufur St Nampa ID 83686",
    "addr:housenumber":"612",
    "addr:postcode":"83686",
    "addr:street":"Dufur St",
    "iso:country":"US",
    "sg:address":"612 Dufur St",
    "sg:city":"Nampa",
    "sg:classifiers":[
        {
            "category":"Professional",
            "subcategory":"Business Services",
            "type":"Services"
        }
    ],
    "sg:phone":"+1 208 467 2004",
    "sg:postcode":"83686",
    "sg:province":"ID",
    "wof:name":"H A S Liquidating",
    "wof:placetype":"venue"
},
  "geometry": {"coordinates":[-116.548728,43.561612],"type":"Point"}
}