{
  "type": "Feature",
  "properties": {
    "iso:country":"US",
    "sg:address":"2000 Flandro Dr",
    "sg:city":"Pocatello",
    "sg:classifiers":[
        {
            "category":"Banks & Credit Unions",
            "subcategory":"Bank",
            "type":"Services"
        }
    ],
    "sg:phone":"+1 208 238 8378",
    "sg:postcode":"83202",
    "sg:province":"ID",
    "wof:name":"Citizens Community Bank",
    "wof:placetype":"venue"
},
  "geometry": {"coordinates":[-112.45082499999999,42.910664],"type":"Point"}
}