{
  "type": "Feature",
  "properties": {
    "iso:country":"US",
    "sg:address":"1535 W Franklin Rd",
    "sg:city":"Meridian",
    "sg:classifiers":[
        {
            "category":"Recreation",
            "type":"Entertainment"
        }
    ],
    "sg:phone":"+1 208 888 1855",
    "sg:postcode":"83642",
    "sg:province":"ID",
    "sg:tags":[
        "martial",
        "arts",
        "instruction"
    ],
    "wof:name":"Karate For Kids",
    "wof:placetype":"venue"
},
  "geometry": {"coordinates":[-116.412851,43.60469],"type":"Point"}
}