{
  "type": "Feature",
  "properties": {
    "addr:full":"713 N Main St Meridian ID 83647",
    "addr:housenumber":"713",
    "addr:postcode":"83647",
    "addr:street":"N Main St",
    "iso:country":"US",
    "sg:address":"713 N Main St",
    "sg:city":"Meridian",
    "sg:classifiers":[
        {
            "category":"Banks & Credit Unions",
            "subcategory":"Bank",
            "type":"Services"
        }
    ],
    "sg:phone":"+1 208 888 1447",
    "sg:postcode":"83647",
    "sg:province":"ID",
    "sg:tags":[
        "savings",
        "loan",
        "association"
    ],
    "wof:name":"Washington Federal Savings",
    "wof:placetype":"venue"
},
  "geometry": {"coordinates":[-115.700157,43.137025],"type":"Point"}
}