{
  "type": "Feature",
  "properties": {
    "iso:country":"US",
    "sg:address":"2478 E Poleline Ave",
    "sg:city":"Post Falls",
    "sg:classifiers":[
        {
            "category":"Education",
            "subcategory":"School",
            "type":"Public Place"
        }
    ],
    "sg:phone":"+1 208 773 8327",
    "sg:postcode":"83854",
    "sg:province":"ID",
    "sg:website":"www.pfsd.com",
    "wof:name":"Prairie View School",
    "wof:placetype":"venue"
},
  "geometry": {"coordinates":[-116.915122,47.730406],"type":"Point"}
}