{
  "type": "Feature",
  "properties": {
    "iso:country":"US",
    "sg:address":"10751 Overland Rd",
    "sg:city":"Boise",
    "sg:classifiers":[
        {
            "category":"Professional",
            "subcategory":"Accounting & Tax Preparation",
            "type":"Services"
        }
    ],
    "sg:phone":"+1 208 433 9722",
    "sg:postcode":"83709",
    "sg:province":"ID",
    "sg:tags":[
        "return",
        "filing"
    ],
    "wof:name":"Jackson Hewitt Tax Svc",
    "wof:placetype":"venue"
},
  "geometry": {"coordinates":[-116.315213,43.590217],"type":"Point"}
}