{
  "type": "Feature",
  "properties": {
    "addr:full":"701 N Main St Moscow ID 83843",
    "addr:housenumber":"701",
    "addr:postcode":"83843",
    "addr:street":"N Main St",
    "iso:country":"US",
    "sg:address":"701 N Main St",
    "sg:city":"Moscow",
    "sg:classifiers":[
        {
            "category":"Food & Beverages",
            "subcategory":"Bakery",
            "type":"Retail Goods"
        }
    ],
    "sg:phone":"+1 208 882 4618",
    "sg:postcode":"83843",
    "sg:province":"ID",
    "sg:tags":[
        "baker"
    ],
    "wof:name":"Wheatberries Bake Shop",
    "wof:placetype":"venue"
},
  "geometry": {"coordinates":[-117.00148799999999,46.74077],"type":"Point"}
}