{
  "type": "Feature",
  "properties": {
    "addr:full":"215 3rd Ave W Marsing ID 83639",
    "addr:housenumber":"215",
    "addr:postcode":"83639",
    "addr:street":"3Rd Ave W",
    "iso:country":"US",
    "sg:address":"215 3rd Ave W",
    "sg:city":"Marsing",
    "sg:classifiers":[
        {
            "category":"Organizations",
            "subcategory":"Religious Organization",
            "type":"Services"
        }
    ],
    "sg:phone":"+1 208 896 4333",
    "sg:postcode":"83639",
    "sg:province":"ID",
    "sg:tags":[
        "church"
    ],
    "wof:name":"Church Of Jesus Christ Of Lds",
    "wof:placetype":"venue"
},
  "geometry": {"coordinates":[-116.806264,43.543506],"type":"Point"}
}