{
  "type": "Feature",
  "properties": {
    "addr:full":"417 N Henry St Post Falls ID 83854",
    "addr:housenumber":"417",
    "addr:postcode":"83854",
    "addr:street":"N Henry St",
    "iso:country":"US",
    "sg:address":"417 N Henry St",
    "sg:city":"Post Falls",
    "sg:classifiers":[
        {
            "category":"Professional",
            "subcategory":"Accounting & Tax Preparation",
            "type":"Services"
        }
    ],
    "sg:phone":"+1 208 777 7221",
    "sg:postcode":"83854",
    "sg:province":"ID",
    "sg:tags":[
        "return",
        "filing"
    ],
    "wof:name":"Morrison Accounting Svc",
    "wof:placetype":"venue"
},
  "geometry": {"coordinates":[-116.943382,47.711917],"type":"Point"}
}