{
  "type": "Feature",
  "properties": {
    "iso:country":"US",
    "sg:address":"3939 Transport St",
    "sg:city":"Boise",
    "sg:classifiers":[
        {
            "category":"Wholesale",
            "subcategory":"Machinery & Supplies",
            "type":"Manufacturing & Wholesale Goods"
        }
    ],
    "sg:phone":"+1 208 344 1525",
    "sg:postcode":"83705",
    "sg:province":"ID",
    "sg:tags":[
        "engine"
    ],
    "wof:name":"Central Equipment Co",
    "wof:placetype":"venue"
},
  "geometry": {"coordinates":[-116.20261000000001,43.564505],"type":"Point"}
}