{
  "type": "Feature",
  "properties": {
    "addr:full":"1341 Filer Ave E Twin Falls ID 83301",
    "addr:housenumber":"1341",
    "addr:postcode":"83301",
    "addr:street":"Filer Ave E",
    "iso:country":"US",
    "sg:address":"1341 Filer Ave E",
    "sg:city":"Twin Falls",
    "sg:classifiers":[
        {
            "category":"Retail",
            "subcategory":"Photofinishing",
            "type":"Services"
        }
    ],
    "sg:phone":"+1 208 733 1559",
    "sg:postcode":"83301",
    "sg:province":"ID",
    "sg:tags":[
        "photo",
        "finishing"
    ],
    "wof:name":"Tom's 50-Minute Photo",
    "wof:placetype":"venue"
},
  "geometry": {"coordinates":[-114.457561,42.570482],"type":"Point"}
}