{
  "type": "Feature",
  "properties": {
    "addr:full":"224 22nd Ave S Nampa ID 83651",
    "addr:housenumber":"224",
    "addr:postcode":"83651",
    "addr:street":"22Nd Ave S",
    "iso:country":"US",
    "sg:address":"224 22nd Ave S",
    "sg:city":"Nampa",
    "sg:classifiers":[
        {
            "category":"Food & Beverages",
            "subcategory":"Groceries & Convenience Stores",
            "type":"Retail Goods"
        }
    ],
    "sg:phone":"+1 208 467 4251",
    "sg:postcode":"83651",
    "sg:province":"ID",
    "wof:name":"Jacksons Food Stores",
    "wof:placetype":"venue"
},
  "geometry": {"coordinates":[-116.550391,43.570691],"type":"Point"}
}