{
  "type": "Feature",
  "properties": {
    "iso:country":"US",
    "sg:address":"7566 Stirrup Ave",
    "sg:city":"Boise",
    "sg:classifiers":[
        {
            "category":"Building & Trades",
            "subcategory":"Construction",
            "type":"Services"
        }
    ],
    "sg:phone":"+1 208 362 9492",
    "sg:postcode":"83709",
    "sg:province":"ID",
    "sg:tags":[
        "designer",
        "dealer",
        "pool",
        "swimming"
    ],
    "wof:name":"Paradise Pool Construction",
    "wof:placetype":"venue"
},
  "geometry": {"coordinates":[-116.279656,43.54844],"type":"Point"}
}