{
  "type": "Feature",
  "properties": {
    "iso:country":"US",
    "sg:address":"569 S Park Ave",
    "sg:city":"Shelley",
    "sg:classifiers":[
        {
            "category":"Retail",
            "subcategory":"Auto Repair",
            "type":"Services"
        }
    ],
    "sg:phone":"+1 208 357 3642",
    "sg:postcode":"83274",
    "sg:province":"ID",
    "sg:tags":[
        "automotive"
    ],
    "wof:name":"Pro Brake Inc",
    "wof:placetype":"venue"
},
  "geometry": {"coordinates":[-112.123299,43.372846],"type":"Point"}
}