{
  "type": "Feature",
  "properties": {
    "iso:country":"US",
    "sg:address":"111 N 3800 E",
    "sg:city":"Rigby",
    "sg:classifiers":[
        {
            "category":"Professional",
            "subcategory":"Business Services",
            "type":"Services"
        }
    ],
    "sg:phone":"+1 208 745 8311",
    "sg:postcode":"83442",
    "sg:province":"ID",
    "wof:name":"L & K Enterprises LLC",
    "wof:placetype":"venue"
},
  "geometry": {"coordinates":[-111.94376699999999,43.641425],"type":"Point"}
}