{
  "type": "Feature",
  "properties": {
    "iso:country":"US",
    "sg:address":"1024 16th Ave",
    "sg:city":"Lewiston",
    "sg:classifiers":[
        {
            "category":"Home & Garden",
            "subcategory":"Carpets & Floor Coverings",
            "type":"Retail Goods"
        }
    ],
    "sg:phone":"+1 208 743 6806",
    "sg:postcode":"83501",
    "sg:province":"ID",
    "sg:tags":[
        "material"
    ],
    "wof:name":"Complete Floorcovering",
    "wof:placetype":"venue"
},
  "geometry": {"coordinates":[-117.018184,46.404073],"type":"Point"}
}