{
  "type": "Feature",
  "properties": {
    "iso:country":"US",
    "sg:address":"2275 N Yellowstone Hwy",
    "sg:city":"Idaho Falls",
    "sg:classifiers":[
        {
            "category":"Retail",
            "subcategory":"Auto Repair",
            "type":"Services"
        }
    ],
    "sg:phone":"+1 208 528 2882",
    "sg:postcode":"83401",
    "sg:province":"ID",
    "sg:tags":[
        "body",
        "automobile",
        "painting"
    ],
    "wof:name":"Sam's Auto Body",
    "wof:placetype":"venue"
},
  "geometry": {"coordinates":[-112.006012,43.516839],"type":"Point"}
}