{
  "type": "Feature",
  "properties": {
    "iso:country":"US",
    "sg:address":"1403 N 15th St",
    "sg:city":"Boise",
    "sg:classifiers":[
        {
            "category":"Building & Trades",
            "subcategory":"Landscaping Services",
            "type":"Services"
        }
    ],
    "sg:phone":"+1 208 345 8506",
    "sg:postcode":"83702",
    "sg:province":"ID",
    "wof:name":"D & H Lawn Service",
    "wof:placetype":"venue"
},
  "geometry": {"coordinates":[-116.205882,43.631087],"type":"Point"}
}