{
  "type": "Feature",
  "properties": {
    "addr:full":"7260 Hidden Valley Dr Boise ID 83709",
    "addr:housenumber":"7260",
    "addr:postcode":"83709",
    "addr:street":"Hidden Valley Dr",
    "iso:country":"US",
    "sg:address":"7260 Hidden Valley Dr",
    "sg:city":"Boise",
    "sg:classifiers":[
        {
            "category":"Professional",
            "subcategory":"Art Services",
            "type":"Services"
        }
    ],
    "sg:phone":"+1 208 362 2282",
    "sg:postcode":"83709",
    "sg:province":"ID",
    "sg:tags":[
        "commercial",
        "design"
    ],
    "wof:name":"Casey Enterprises",
    "wof:placetype":"venue"
},
  "geometry": {"coordinates":[-116.333433,43.537114],"type":"Point"}
}