{
  "type": "Feature",
  "properties": {
    "iso:country":"US",
    "sg:address":"1510 Pocatello Creek Rd",
    "sg:city":"Pocatello",
    "sg:classifiers":[
        {
            "category":"Autos & Motor Vehicles",
            "subcategory":"Fuel & Gas Station",
            "type":"Retail Goods"
        }
    ],
    "sg:phone":"+1 208 233 7257",
    "sg:postcode":"83201",
    "sg:province":"ID",
    "sg:tags":[
        "station"
    ],
    "wof:name":"Pocatello Creek Self Service",
    "wof:placetype":"venue"
},
  "geometry": {"coordinates":[-112.433347,42.898578],"type":"Point"}
}