{
  "type": "Feature",
  "properties": {
    "iso:country":"US",
    "sg:address":"2030 S Washington Ave",
    "sg:city":"Emmett",
    "sg:classifiers":[
        {
            "category":"Government",
            "subcategory":"Office",
            "type":"Public Place"
        }
    ],
    "sg:phone":"+1 208 364 7780",
    "sg:postcode":"83617",
    "sg:province":"ID",
    "sg:tags":[
        "state",
        "inspection"
    ],
    "wof:name":"Commerce & Labor Dept",
    "wof:placetype":"venue"
},
  "geometry": {"coordinates":[-116.499881,43.860532],"type":"Point"}
}