{
  "type": "Feature",
  "properties": {
    "iso:country":"US",
    "sg:address":"911 Shoup St",
    "sg:city":"Salmon",
    "sg:classifiers":[
        {
            "category":"Real Estate",
            "subcategory":"Real Estate Agent",
            "type":"Services"
        }
    ],
    "sg:phone":"+1 208 756 6310",
    "sg:postcode":"83467",
    "sg:province":"ID",
    "sg:tags":[
        "appraiser"
    ],
    "wof:name":"Brent T Barry Appraisal Svc",
    "wof:placetype":"venue"
},
  "geometry": {"coordinates":[-113.889634,45.174858],"type":"Point"}
}