{
  "type": "Feature",
  "properties": {
    "iso:country":"US",
    "sg:address":"1420 Lincoln Way",
    "sg:city":"Coeur D Alene",
    "sg:classifiers":[
        {
            "category":"Professional",
            "subcategory":"Accounting & Tax Preparation",
            "type":"Services"
        }
    ],
    "sg:phone":"+1 208 664 3157",
    "sg:postcode":"83814",
    "sg:province":"ID",
    "sg:tags":[
        "accountant"
    ],
    "wof:name":"Ralph Nelson CPA",
    "wof:placetype":"venue"
},
  "geometry": {"coordinates":[-116.791667,47.688279],"type":"Point"}
}