{
  "type": "Feature",
  "properties": {
    "iso:country":"US",
    "sg:address":"111 Broadway Ave",
    "sg:city":"Boise",
    "sg:classifiers":[
        {
            "category":"Cafe",
            "type":"Food & Drink"
        }
    ],
    "sg:menulink":"http://www.allmenus.com/id/boise-city/27198-aladdin-sports-cafe/menu/",
    "sg:phone":"+1 208 368 0880",
    "sg:postcode":"83702",
    "sg:province":"ID",
    "sg:tags":[
        "egyptian"
    ],
    "wof:name":"Aladdin Sports Cafe",
    "wof:placetype":"venue"
},
  "geometry": {"coordinates":[-116.193262,43.610443],"type":"Point"}
}