{
  "type": "Feature",
  "properties": {
    "iso:country":"US",
    "sg:address":"8050 Northview St",
    "sg:city":"Boise",
    "sg:classifiers":[
        {
            "category":"Health Services",
            "subcategory":"Hospital",
            "type":"Services"
        }
    ],
    "sg:phone":"+1 208 327 0504",
    "sg:postcode":"83704",
    "sg:province":"ID",
    "sg:tags":[
        "mental"
    ],
    "wof:name":"Sunhealth Behavioral System",
    "wof:placetype":"venue"
},
  "geometry": {"coordinates":[-116.283621,43.6267],"type":"Point"}
}