{
  "type": "Feature",
  "properties": {
    "iso:country":"US",
    "sg:address":"74 Grays Lake Rd",
    "sg:city":"Wayan",
    "sg:classifiers":[
        {
            "category":"Government",
            "subcategory":"Office",
            "type":"Public Place"
        }
    ],
    "sg:phone":"+1 208 574 2757",
    "sg:postcode":"83285",
    "sg:province":"ID",
    "sg:tags":[
        "federal"
    ],
    "wof:name":"US Fish & Wildlife Svc",
    "wof:placetype":"venue"
},
  "geometry": {"coordinates":[-111.378362,43.031096],"type":"Point"}
}