{
  "type": "Feature",
  "properties": {
    "iso:country":"US",
    "sg:address":"418 W Linden St",
    "sg:city":"Caldwell",
    "sg:classifiers":[
        {
            "category":"Retail",
            "subcategory":"Laundry & Dry Cleaning",
            "type":"Services"
        }
    ],
    "sg:phone":"+1 208 454 0275",
    "sg:postcode":"83605",
    "sg:province":"ID",
    "wof:name":"Action Carpet Cleaning",
    "wof:placetype":"venue"
},
  "geometry": {"coordinates":[-116.701466,43.648038],"type":"Point"}
}