{
  "type": "Feature",
  "properties": {
    "iso:country":"US",
    "sg:address":"1034 Main St",
    "sg:city":"Lewiston",
    "sg:classifiers":[
        {
            "category":"Organizations",
            "subcategory":"Labor Organization",
            "type":"Services"
        }
    ],
    "sg:phone":"+1 208 743 2591",
    "sg:postcode":"83501",
    "sg:province":"ID",
    "wof:name":"Teamsters Local 690",
    "wof:placetype":"venue"
},
  "geometry": {"coordinates":[-117.02022700000001,46.419186],"type":"Point"}
}