{
  "type": "Feature",
  "properties": {
    "iso:country":"US",
    "sg:address":"100 E Idaho St",
    "sg:city":"Boise",
    "sg:classifiers":[
        {
            "category":"Health Services",
            "subcategory":"Doctor",
            "type":"Services"
        }
    ],
    "sg:phone":"+1 208 381 7310",
    "sg:postcode":"83712",
    "sg:province":"ID",
    "sg:tags":[
        "physician",
        "surgeon"
    ],
    "wof:name":"Idaho Pediatric Gastroentrlgy",
    "wof:placetype":"venue"
},
  "geometry": {"coordinates":[-116.193245,43.611523],"type":"Point"}
}