{
  "type": "Feature",
  "properties": {
    "iso:country":"US",
    "sg:address":"933 S 3rd W St",
    "sg:city":"Grace",
    "sg:classifiers":[
        {
            "category":"Professional",
            "type":"Services"
        }
    ],
    "sg:phone":"+1 208 425 9121",
    "sg:postcode":"83241",
    "sg:province":"ID",
    "sg:tags":[
        "establishment"
    ],
    "wof:name":"C To C Inc",
    "wof:placetype":"venue"
},
  "geometry": {"coordinates":[-111.734032,42.567865],"type":"Point"}
}