{
  "type": "Feature",
  "properties": {
    "iso:country":"US",
    "sg:address":"508 Marble St",
    "sg:city":"Kimberly",
    "sg:classifiers":[
        {
            "category":"Building & Trades",
            "subcategory":"Cleaning & Sanitation",
            "type":"Services"
        }
    ],
    "sg:phone":"+1 208 543 5721",
    "sg:postcode":"83341",
    "sg:province":"ID",
    "sg:tags":[
        "maintenance"
    ],
    "wof:name":"Western Building Maintenance",
    "wof:placetype":"venue"
},
  "geometry": {"coordinates":[-114.371578,42.525053],"type":"Point"}
}