{
  "type": "Feature",
  "properties": {
    "iso:country":"US",
    "sg:address":"6205 Overland Rd",
    "sg:city":"Boise",
    "sg:classifiers":[
        {
            "category":"Professional",
            "subcategory":"Printing & Photocopies",
            "type":"Services"
        }
    ],
    "sg:phone":"+1 208 376 7360",
    "sg:postcode":"83709",
    "sg:province":"ID",
    "sg:tags":[
        "duplicating",
        "copying"
    ],
    "sg:website":"www.blueprintspecialties.com",
    "wof:name":"Capitol Copy & Print",
    "wof:placetype":"venue"
},
  "geometry": {"coordinates":[-116.258437,43.589881],"type":"Point"}
}