{
  "type": "Feature",
  "properties": {
    "iso:country":"US",
    "sg:address":"11734 Peconic Dr",
    "sg:city":"Boise",
    "sg:classifiers":[
        {
            "category":"Professional",
            "subcategory":"Accounting & Tax Preparation",
            "type":"Services"
        }
    ],
    "sg:phone":"+1 208 362 9204",
    "sg:postcode":"83709",
    "sg:province":"ID",
    "wof:name":"Prudhomme Accounting",
    "wof:placetype":"venue"
},
  "geometry": {"coordinates":[-116.329077,43.576847],"type":"Point"}
}