{
  "type": "Feature",
  "properties": {
    "iso:country":"US",
    "sg:address":"48 N 1st E",
    "sg:city":"Rexburg",
    "sg:classifiers":[
        {
            "category":"Home & Garden",
            "subcategory":"Building Materials",
            "type":"Retail Goods"
        }
    ],
    "sg:phone":"+1 208 356 0773",
    "sg:postcode":"83440",
    "sg:province":"ID",
    "sg:tags":[
        "paint"
    ],
    "wof:name":"Columbia Paint & Coatings",
    "wof:placetype":"venue"
},
  "geometry": {"coordinates":[-111.78088099999999,43.826104],"type":"Point"}
}