{
  "type": "Feature",
  "properties": {
    "iso:country":"US",
    "sg:address":"1 W Market Ave",
    "sg:city":"Kellogg",
    "sg:classifiers":[
        {
            "category":"Organizations",
            "subcategory":"Religious Organization",
            "type":"Services"
        }
    ],
    "sg:phone":"+1 208 784 6641",
    "sg:postcode":"83837",
    "sg:province":"ID",
    "sg:tags":[
        "church"
    ],
    "wof:name":"Emmanual Episcopal Church",
    "wof:placetype":"venue"
},
  "geometry": {"coordinates":[-116.121406,47.533735],"type":"Point"}
}