{
  "type": "Feature",
  "properties": {
    "addr:full":"623 S Main St Ste 5 Moscow ID 83843",
    "addr:housenumber":"623",
    "addr:postcode":"83843",
    "addr:street":"S Main St Ste 5",
    "iso:country":"US",
    "sg:address":"623 S Main St Ste 5",
    "sg:city":"Moscow",
    "sg:classifiers":[
        {
            "category":"Health Services",
            "subcategory":"Doctor",
            "type":"Services"
        }
    ],
    "sg:phone":"+1 208 882 2011",
    "sg:postcode":"83843",
    "sg:province":"ID",
    "sg:tags":[
        "physician",
        "family",
        "practice",
        "surgeons",
        "medicine"
    ],
    "wof:name":"Md Richard Howe",
    "wof:placetype":"venue"
},
  "geometry": {"coordinates":[-117.00135899999999,46.729871],"type":"Point"}
}