{
  "type": "Feature",
  "properties": {
    "addr:full":"1415 Albion Ave Burley ID 83318",
    "addr:housenumber":"1415",
    "addr:postcode":"83318",
    "addr:street":"Albion Ave",
    "iso:country":"US",
    "sg:address":"1415 Albion Ave",
    "sg:city":"Burley",
    "sg:classifiers":[
        {
            "category":"Government",
            "subcategory":"Police Station",
            "type":"Public Place"
        }
    ],
    "sg:phone":"+1 208 878 1002",
    "sg:postcode":"83318",
    "sg:province":"ID",
    "sg:tags":[
        "sheriff"
    ],
    "wof:name":"Cassia County Criminal Section",
    "wof:placetype":"venue"
},
  "geometry": {"coordinates":[-113.791849,42.534389],"type":"Point"}
}