{
  "type": "Feature",
  "properties": {
    "iso:country":"US",
    "sg:address":"526 N Dupont Ave",
    "sg:city":"Boise",
    "sg:classifiers":[
        {
            "category":"Wholesale",
            "subcategory":"Hardware",
            "type":"Manufacturing & Wholesale Goods"
        }
    ],
    "sg:phone":"+1 208 323 1838",
    "sg:postcode":"83713",
    "sg:province":"ID",
    "sg:tags":[
        "parts",
        "refrigerating"
    ],
    "wof:name":"Thermal Supply Inc",
    "wof:placetype":"venue"
},
  "geometry": {"coordinates":[-116.33789299999999,43.610349],"type":"Point"}
}