{
  "type": "Feature",
  "properties": {
    "iso:country":"US",
    "sg:address":"2100 Genesee-Juliaetta Rd",
    "sg:city":"Genesee",
    "sg:classifiers":[
        {
            "category":"Farming",
            "subcategory":"Livestock Farm",
            "type":"Manufacturing & Wholesale Goods"
        }
    ],
    "sg:phone":"+1 208 285 1597",
    "sg:postcode":"83832",
    "sg:province":"ID",
    "sg:tags":[
        "animal",
        "general"
    ],
    "wof:name":"Nelson Ranch",
    "wof:placetype":"venue"
},
  "geometry": {"coordinates":[-116.912977,46.549587],"type":"Point"}
}