{
  "type": "Feature",
  "properties": {
    "iso:country":"US",
    "sg:address":"6156 Happy Valley Rd",
    "sg:city":"Kuna",
    "sg:phone":"+1 208 466 6871",
    "sg:postcode":"83634",
    "sg:province":"ID",
    "sg:tags":[
        "farm",
        "field",
        "grain",
        "cash",
        "crop"
    ],
    "wof:name":"L W Welch",
    "wof:placetype":"venue"
},
  "geometry": {"coordinates":[-116.513296,43.463174],"type":"Point"}
}