{
  "type": "Feature",
  "properties": {
    "iso:country":"US",
    "sg:address":"2300 W 17th S",
    "sg:city":"Idaho Falls",
    "sg:classifiers":[
        {
            "category":"Professional",
            "type":"Services"
        }
    ],
    "sg:phone":"+1 208 552 2392",
    "sg:postcode":"83402",
    "sg:province":"ID",
    "sg:tags":[
        "establishment"
    ],
    "wof:name":"Natalie's Attic",
    "wof:placetype":"venue"
},
  "geometry": {"coordinates":[-112.077416,43.482336],"type":"Point"}
}