{
  "type": "Feature",
  "properties": {
    "iso:country":"US",
    "sg:address":"1275 Mercury Ave",
    "sg:city":"Idaho Falls",
    "sg:classifiers":[
        {
            "category":"Wholesale",
            "subcategory":"Vending Machines",
            "type":"Manufacturing & Wholesale Goods"
        }
    ],
    "sg:phone":"+1 208 522 3170",
    "sg:postcode":"83402",
    "sg:province":"ID",
    "wof:name":"Service Vending Co",
    "wof:placetype":"venue"
},
  "geometry": {"coordinates":[-112.053737,43.503966],"type":"Point"}
}