{
  "type": "Feature",
  "properties": {
    "iso:country":"US",
    "sg:address":"3310 Gekeler Ln",
    "sg:city":"Boise",
    "sg:classifiers":[
        {
            "category":"Food & Beverages",
            "subcategory":"Groceries & Convenience Stores",
            "type":"Retail Goods"
        }
    ],
    "sg:phone":"+1 208 344 8568",
    "sg:postcode":"83706",
    "sg:province":"ID",
    "sg:tags":[
        "grocer"
    ],
    "wof:name":"M & W Markets",
    "wof:placetype":"venue"
},
  "geometry": {"coordinates":[-116.183409,43.572389],"type":"Point"}
}