{
  "type": "Feature",
  "properties": {
    "addr:full":"556 4th Ave W Twin Falls ID 83301",
    "addr:housenumber":"556",
    "addr:postcode":"83301",
    "addr:street":"4Th Ave W",
    "iso:country":"US",
    "sg:address":"556 4th Ave W",
    "sg:city":"Twin Falls",
    "sg:classifiers":[
        {
            "category":"Autos & Motor Vehicles",
            "subcategory":"Auto Supplies",
            "type":"Retail Goods"
        }
    ],
    "sg:phone":"+1 208 733 3077",
    "sg:postcode":"83301",
    "sg:province":"ID",
    "sg:tags":[
        "tire"
    ],
    "sg:website":"www.okautosystems.com",
    "wof:name":"O K Auto Systems Inc",
    "wof:placetype":"venue"
},
  "geometry": {"coordinates":[-114.478326,42.557787],"type":"Point"}
}