{
  "type": "Feature",
  "properties": {
    "addr:full":"110 Tibbetts Dr Sandpoint ID 83864",
    "addr:housenumber":"110",
    "addr:postcode":"83864",
    "addr:street":"Tibbetts Dr",
    "iso:country":"US",
    "sg:address":"110 Tibbetts Dr",
    "sg:city":"Sandpoint",
    "sg:classifiers":[
        {
            "category":"Personal",
            "subcategory":"Tanning Parlor",
            "type":"Services"
        }
    ],
    "sg:phone":"+1 208 263 5484",
    "sg:postcode":"83864",
    "sg:province":"ID",
    "sg:tags":[
        "salon"
    ],
    "wof:name":"Sunrise Tans",
    "wof:placetype":"venue"
},
  "geometry": {"coordinates":[-116.548089,48.297602],"type":"Point"}
}