{
  "type": "Feature",
  "properties": {
    "iso:country":"US",
    "sg:address":"147 N Bridge St",
    "sg:city":"St Anthony",
    "sg:classifiers":[
        {
            "category":"Retail",
            "subcategory":"Auto Repair",
            "type":"Services"
        }
    ],
    "sg:phone":"+1 208 624 4422",
    "sg:postcode":"83445",
    "sg:province":"ID",
    "sg:tags":[
        "automobile",
        "lubrication"
    ],
    "wof:name":"Lube Bay",
    "wof:placetype":"venue"
},
  "geometry": {"coordinates":[-111.682559,43.967841],"type":"Point"}
}