{
  "type": "Feature",
  "properties": {
    "iso:country":"US",
    "sg:address":"1008 N 3rd St",
    "sg:city":"Mccall",
    "sg:classifiers":[
        {
            "category":"Real Estate",
            "subcategory":"Real Estate Operator",
            "type":"Services"
        }
    ],
    "sg:phone":"+1 208 634 7766",
    "sg:postcode":"83638",
    "sg:province":"ID",
    "sg:tags":[
        "condominium"
    ],
    "sg:website":"www.accommodationservices.com",
    "wof:name":"Accommodation Services",
    "wof:placetype":"venue"
},
  "geometry": {"coordinates":[-116.09797,44.910285],"type":"Point"}
}