{
  "type": "Feature",
  "properties": {
    "iso:country":"US",
    "sg:address":"3923 Cassia St",
    "sg:city":"Boise",
    "sg:classifiers":[
        {
            "category":"Personal",
            "type":"Services"
        }
    ],
    "sg:phone":"+1 208 336 4126",
    "sg:postcode":"83705",
    "sg:province":"ID",
    "wof:name":"Rocky Farrens",
    "wof:placetype":"venue"
},
  "geometry": {"coordinates":[-116.232281,43.596975],"type":"Point"}
}