{
  "type": "Feature",
  "properties": {
    "iso:country":"US",
    "sg:address":"243 E 23rd Dr",
    "sg:city":"Burley",
    "sg:classifiers":[
        {
            "category":"Shopping",
            "subcategory":"Beauty & Cosmetics",
            "type":"Retail Goods"
        }
    ],
    "sg:phone":"+1 208 678 8587",
    "sg:postcode":"83318",
    "sg:province":"ID",
    "sg:tags":[
        "merchandise"
    ],
    "wof:name":"Avon Ind Sales-Carol Barksdale",
    "wof:placetype":"venue"
},
  "geometry": {"coordinates":[-113.79025,42.523998],"type":"Point"}
}