{
  "type": "Feature",
  "properties": {
    "addr:full":"111 S Kimball Ave Caldwell ID 83605",
    "addr:housenumber":"111",
    "addr:postcode":"83605",
    "addr:street":"S Kimball Ave",
    "iso:country":"US",
    "sg:address":"111 S Kimball Ave",
    "sg:city":"Caldwell",
    "sg:classifiers":[
        {
            "category":"Retail",
            "subcategory":"Animal Services",
            "type":"Services"
        }
    ],
    "sg:phone":"+1 208 402 0038",
    "sg:postcode":"83605",
    "sg:province":"ID",
    "sg:tags":[
        "pet",
        "grooming",
        "washing"
    ],
    "wof:name":"Clipper Time Grooming",
    "wof:placetype":"venue"
},
  "geometry": {"coordinates":[-116.686555,43.666679],"type":"Point"}
}