{
  "type": "Feature",
  "properties": {
    "addr:full":"1866 E Chisholm Dr Nampa ID 83687",
    "addr:housenumber":"1866",
    "addr:postcode":"83687",
    "addr:street":"E Chisholm Dr",
    "iso:country":"US",
    "sg:address":"1866 E Chisholm Dr",
    "sg:city":"Nampa",
    "sg:classifiers":[
        {
            "category":"Communications",
            "subcategory":"Film & Video Production",
            "type":"Services"
        }
    ],
    "sg:phone":"+1 208 467 3301",
    "sg:postcode":"83687",
    "sg:province":"ID",
    "sg:tags":[
        "taping"
    ],
    "sg:website":"www.6onyourside.com",
    "wof:name":"KIVI",
    "wof:placetype":"venue"
},
  "geometry": {"coordinates":[-116.549252,43.599039],"type":"Point"}
}