{
  "type": "Feature",
  "properties": {
    "iso:country":"US",
    "sg:address":"11598 Santa Barbara Dr",
    "sg:city":"Boise",
    "sg:classifiers":[
        {
            "category":"Building & Trades",
            "subcategory":"Construction",
            "type":"Services"
        }
    ],
    "sg:phone":"+1 208 362 5147",
    "sg:postcode":"83709",
    "sg:province":"ID",
    "sg:tags":[
        "contractor"
    ],
    "wof:name":"Home Interiors",
    "wof:placetype":"venue"
},
  "geometry": {"coordinates":[-116.32652,43.539664],"type":"Point"}
}