{
  "type": "Feature",
  "properties": {
    "iso:country":"US",
    "sg:address":"4800 W Fairview Ave",
    "sg:city":"Boise",
    "sg:classifiers":[
        {
            "category":"Professional",
            "subcategory":"Accounting & Tax Preparation",
            "type":"Services"
        }
    ],
    "sg:phone":"+1 208 287 2494",
    "sg:postcode":"83706",
    "sg:province":"ID",
    "sg:tags":[
        "billing"
    ],
    "sg:website":"www.crowneone.com",
    "wof:name":"Crowne One Network Inc",
    "wof:placetype":"venue"
},
  "geometry": {"coordinates":[-116.242246,43.618992],"type":"Point"}
}