{
  "type": "Feature",
  "properties": {
    "addr:full":"2199 W Ironwood Center Dr Coeur D Alene ID 83814",
    "addr:housenumber":"2199",
    "addr:postcode":"83814",
    "addr:street":"W Ironwood Center Dr",
    "iso:country":"US",
    "sg:address":"2199 W Ironwood Center Dr",
    "sg:city":"Coeur D Alene",
    "sg:classifiers":[
        {
            "category":"Health Services",
            "subcategory":"Doctor",
            "type":"Services"
        }
    ],
    "sg:phone":"+1 208 666 0448",
    "sg:postcode":"83814",
    "sg:province":"ID",
    "sg:tags":[
        "physician",
        "surgeon"
    ],
    "wof:name":"North Idaho Mental Health",
    "wof:placetype":"venue"
},
  "geometry": {"coordinates":[-116.796586,47.697692],"type":"Point"}
}