{
  "type": "Feature",
  "properties": {
    "iso:country":"US",
    "sg:address":"2106 E Linden St",
    "sg:city":"Caldwell",
    "sg:classifiers":[
        {
            "category":"Organizations",
            "subcategory":"Religious Organization",
            "type":"Services"
        }
    ],
    "sg:phone":"+1 208 459 2451",
    "sg:postcode":"83605",
    "sg:province":"ID",
    "sg:tags":[
        "church"
    ],
    "wof:name":"Caldwell Seventh-Day Adventist",
    "wof:placetype":"venue"
},
  "geometry": {"coordinates":[-116.671815,43.64805],"type":"Point"}
}