{
  "type": "Feature",
  "properties": {
    "iso:country":"US",
    "sg:address":"824 E Wallace Ave",
    "sg:city":"Coeur D Alene",
    "sg:classifiers":[
        {
            "category":"Recreation",
            "type":"Entertainment"
        }
    ],
    "sg:phone":"+1 208 667 3054",
    "sg:postcode":"83814",
    "sg:province":"ID",
    "wof:name":"Hands of Healing Massage",
    "wof:placetype":"venue"
},
  "geometry": {"coordinates":[-116.775047,47.676579],"type":"Point"}
}