{
  "type": "Feature",
  "properties": {
    "iso:country":"US",
    "sg:address":"1472 State Hwy 41",
    "sg:city":"Rathdrum",
    "sg:classifiers":[
        {
            "category":"Wholesale",
            "subcategory":"Machinery & Supplies",
            "type":"Manufacturing & Wholesale Goods"
        }
    ],
    "sg:phone":"+1 208 687 1732",
    "sg:postcode":"83858",
    "sg:province":"ID",
    "sg:tags":[
        "dry wall",
        "contractor"
    ],
    "wof:name":"GTS Drywall Supply/Sepia",
    "wof:placetype":"venue"
},
  "geometry": {"coordinates":[-116.893902,47.805077],"type":"Point"}
}