{
  "type": "Feature",
  "properties": {
    "addr:full":"2500 N Fry St Boise ID 83704",
    "addr:housenumber":"2500",
    "addr:postcode":"83704",
    "addr:street":"N Fry St",
    "iso:country":"US",
    "sg:address":"2500 N Fry St",
    "sg:city":"Boise",
    "sg:classifiers":[
        {
            "category":"Professional",
            "subcategory":"Business Services",
            "type":"Services"
        }
    ],
    "sg:phone":"+1 208 323 1641",
    "sg:postcode":"83704",
    "sg:province":"ID",
    "wof:name":"Ortho-Remotes L L C",
    "wof:placetype":"venue"
},
  "geometry": {"coordinates":[-116.26572400000001,43.628906],"type":"Point"}
}