{
  "type": "Feature",
  "properties": {
    "iso:country":"US",
    "sg:address":"7109 Overland Rd",
    "sg:city":"Boise",
    "sg:classifiers":[
        {
            "category":"Shopping",
            "subcategory":"Florist",
            "type":"Retail Goods"
        }
    ],
    "sg:phone":"+1 208 322 3500",
    "sg:postcode":"83709",
    "sg:province":"ID",
    "sg:website":"www.jmichaelsflorist.com",
    "wof:name":"J Michaels Florist Wines",
    "wof:placetype":"venue"
},
  "geometry": {"coordinates":[-116.268422,43.590034],"type":"Point"}
}