{
  "type": "Feature",
  "properties": {
    "addr:full":"5306 Chinden Blvd Boise ID 83714",
    "addr:housenumber":"5306",
    "addr:postcode":"83714",
    "addr:street":"Chinden Blvd",
    "iso:country":"US",
    "sg:address":"5306 Chinden Blvd",
    "sg:city":"Boise",
    "sg:classifiers":[
        {
            "category":"Autos & Motor Vehicles",
            "subcategory":"Auto Supplies",
            "type":"Retail Goods"
        }
    ],
    "sg:phone":"+1 208 322 0567",
    "sg:postcode":"83714",
    "sg:province":"ID",
    "sg:tags":[
        "tire"
    ],
    "wof:name":"Bruneel Tire Factory",
    "wof:placetype":"venue"
},
  "geometry": {"coordinates":[-116.27255599999999,43.645417],"type":"Point"}
}