{
  "type": "Feature",
  "properties": {
    "iso:country":"US",
    "sg:address":"510 S 14th St",
    "sg:city":"Boise",
    "sg:classifiers":[
        {
            "category":"Social Services",
            "type":"Services"
        }
    ],
    "sg:phone":"+1 208 426 8018",
    "sg:postcode":"83702",
    "sg:province":"ID",
    "sg:tags":[
        "counselor",
        "marriage",
        "family"
    ],
    "wof:name":"Adolescent & Family Therapy",
    "wof:placetype":"venue"
},
  "geometry": {"coordinates":[-116.215347,43.616043],"type":"Point"}
}