{
  "type": "Feature",
  "properties": {
    "iso:country":"US",
    "sg:address":"4261 E Stonebridge Dr",
    "sg:city":"Meridian",
    "sg:classifiers":[
        {
            "category":"Building & Trades",
            "subcategory":"Landscaping Services",
            "type":"Services"
        }
    ],
    "sg:phone":"+1 208 376 6146",
    "sg:postcode":"83642",
    "sg:province":"ID",
    "wof:name":"Action Lawn Care",
    "wof:placetype":"venue"
},
  "geometry": {"coordinates":[-116.341452,43.614674],"type":"Point"}
}