{
  "type": "Feature",
  "properties": {
    "addr:full":"712 SW 4th St Fruitland ID 83619",
    "addr:housenumber":"712",
    "addr:postcode":"83619",
    "addr:street":"Sw 4Th St",
    "iso:country":"US",
    "sg:address":"712 SW 4th St",
    "sg:city":"Fruitland",
    "sg:classifiers":[
        {
            "category":"Building & Trades",
            "subcategory":"Construction",
            "type":"Services"
        }
    ],
    "sg:phone":"+1 208 452 7899",
    "sg:postcode":"83619",
    "sg:province":"ID",
    "sg:tags":[
        "marking",
        "maintenance",
        "parking"
    ],
    "wof:name":"Guardian Management Co",
    "wof:placetype":"venue"
},
  "geometry": {"coordinates":[-116.92364499999999,44.007771],"type":"Point"}
}