{
  "type": "Feature",
  "properties": {
    "iso:country":"US",
    "sg:address":"611 Randolph St",
    "sg:city":"Melba",
    "sg:classifiers":[
        {
            "category":"Education",
            "subcategory":"School",
            "type":"Public Place"
        }
    ],
    "sg:phone":"+1 208 495 1103",
    "sg:postcode":"83641",
    "sg:province":"ID",
    "sg:website":"www.melbaschools.org",
    "wof:name":"Melba School Dist/Trans Dept",
    "wof:placetype":"venue"
},
  "geometry": {"coordinates":[-116.528619,43.385646],"type":"Point"}
}