{
  "type": "Feature",
  "properties": {
    "addr:full":"410 W Neider Ave Coeur D Alene ID 83815",
    "addr:housenumber":"410",
    "addr:postcode":"83815",
    "addr:street":"W Neider Ave",
    "iso:country":"US",
    "sg:address":"410 W Neider Ave",
    "sg:city":"Coeur D Alene",
    "sg:classifiers":[
        {
            "category":"Food & Beverages",
            "subcategory":"Groceries & Convenience Stores",
            "type":"Retail Goods"
        }
    ],
    "sg:phone":"+1 208 664 0771",
    "sg:postcode":"83815",
    "sg:province":"ID",
    "sg:tags":[
        "grocer"
    ],
    "sg:website":"www.mytidymans.com",
    "wof:name":"Tidyman's Inc",
    "wof:placetype":"venue"
},
  "geometry": {"coordinates":[-116.79428,47.707158],"type":"Point"}
}