{
  "type": "Feature",
  "properties": {
    "addr:full":"803 E Iona Rd Idaho Falls ID 83401",
    "addr:housenumber":"803",
    "addr:postcode":"83401",
    "addr:street":"E Iona Rd",
    "iso:country":"US",
    "sg:address":"803 E Iona Rd",
    "sg:city":"Idaho Falls",
    "sg:classifiers":[
        {
            "category":"Recreation",
            "subcategory":"Marina",
            "type":"Entertainment"
        }
    ],
    "sg:phone":"+1 208 522 8097",
    "sg:postcode":"83401",
    "sg:province":"ID",
    "sg:tags":[
        "repairing",
        "boat"
    ],
    "wof:name":"Anchor Boat Works",
    "wof:placetype":"venue"
},
  "geometry": {"coordinates":[-112.016946,43.525967],"type":"Point"}
}