{
  "type": "Feature",
  "properties": {
    "addr:full":"5219 Chinden Blvd Boise ID 83714",
    "addr:housenumber":"5219",
    "addr:postcode":"83714",
    "addr:street":"Chinden Blvd",
    "iso:country":"US",
    "sg:address":"5219 Chinden Blvd",
    "sg:city":"Boise",
    "sg:classifiers":[
        {
            "category":"Retail",
            "subcategory":"Auto Repair",
            "type":"Services"
        }
    ],
    "sg:phone":"+1 208 376 5301",
    "sg:postcode":"83714",
    "sg:province":"ID",
    "sg:tags":[
        "repairing",
        "automobile"
    ],
    "wof:name":"Access Auto Repair",
    "wof:placetype":"venue"
},
  "geometry": {"coordinates":[-116.27068800000001,43.644286],"type":"Point"}
}