{
  "type": "Feature",
  "properties": {
    "iso:country":"US",
    "sg:address":"300 W Coeur D'Alene Lake Dr",
    "sg:city":"Coeur D Alene",
    "sg:classifiers":[
        {
            "category":"Restaurant",
            "type":"Food & Drink"
        }
    ],
    "sg:phone":"+1 208 664 6236",
    "sg:postcode":"83814",
    "sg:province":"ID",
    "wof:name":"Eduardo's Lounge",
    "wof:placetype":"venue"
},
  "geometry": {"coordinates":[-116.751924,47.668807],"type":"Point"}
}