{
  "type": "Feature",
  "properties": {
    "iso:country":"US",
    "sg:address":"499 S Main St",
    "sg:city":"Meridian",
    "sg:classifiers":[
        {
            "category":"Restaurant",
            "type":"Food & Drink"
        }
    ],
    "sg:menulink":"http://www.allmenus.com/id/boise-city/75567-round-table-pizza/menu/",
    "sg:phone":"+1 208 887 1100",
    "sg:postcode":"83642",
    "sg:province":"ID",
    "sg:tags":[
        "american",
        "pizza"
    ],
    "wof:name":"Round Table Pizza",
    "wof:placetype":"venue"
},
  "geometry": {"coordinates":[-116.39170300000001,43.600432],"type":"Point"}
}