{
  "type": "Feature",
  "properties": {
    "iso:country":"US",
    "sg:address":"510 Broadway Ave S",
    "sg:city":"Buhl",
    "sg:classifiers":[
        {
            "category":"Travel",
            "subcategory":"Hotels & Motels",
            "type":"Entertainment"
        }
    ],
    "sg:phone":"+1 208 543 8814",
    "sg:postcode":"83316",
    "sg:province":"ID",
    "wof:name":"Oregon Trail Motel",
    "wof:placetype":"venue"
},
  "geometry": {"coordinates":[-114.754768,42.595389],"type":"Point"}
}