{
  "type": "Feature",
  "properties": {
    "iso:country":"US",
    "sg:address":"13 N Fairview St",
    "sg:city":"Nampa",
    "sg:classifiers":[
        {
            "category":"Retail",
            "subcategory":"Auto Repair",
            "type":"Services"
        }
    ],
    "sg:phone":"+1 208 466 8113",
    "sg:postcode":"83651",
    "sg:province":"ID",
    "sg:tags":[
        "automotive"
    ],
    "wof:name":"Jims Labor Service",
    "wof:placetype":"venue"
},
  "geometry": {"coordinates":[-116.57556200000001,43.579215],"type":"Point"}
}