{
  "type": "Feature",
  "properties": {
    "iso:country":"US",
    "sg:address":"13377 W Persimmon St",
    "sg:city":"Boise",
    "sg:classifiers":[
        {
            "category":"Building & Trades",
            "subcategory":"Construction",
            "type":"Services"
        }
    ],
    "sg:phone":"+1 208 939 1178",
    "sg:postcode":"83713",
    "sg:province":"ID",
    "sg:tags":[
        "hanging",
        "contractor"
    ],
    "wof:name":"Igo Outdoors",
    "wof:placetype":"venue"
},
  "geometry": {"coordinates":[-116.349925,43.647772],"type":"Point"}
}