{
  "type": "Feature",
  "properties": {
    "iso:country":"US",
    "sg:address":"7104 Sunnybrook Dr",
    "sg:city":"Boise",
    "sg:classifiers":[
        {
            "category":"Real Estate",
            "subcategory":"Real Estate Operator",
            "type":"Services"
        }
    ],
    "sg:phone":"+1 208 322 5349",
    "sg:postcode":"83709",
    "sg:province":"ID",
    "sg:tags":[
        "property",
        "lessor"
    ],
    "wof:name":"William Dunham",
    "wof:placetype":"venue"
},
  "geometry": {"coordinates":[-116.269333,43.591133],"type":"Point"}
}