{
  "type": "Feature",
  "properties": {
    "iso:country":"US",
    "sg:address":"721 Grant St",
    "sg:city":"Caldwell",
    "sg:classifiers":[
        {
            "category":"Personal",
            "subcategory":"Beauty Salon",
            "type":"Services"
        }
    ],
    "sg:phone":"+1 208 459 6111",
    "sg:postcode":"83605",
    "sg:province":"ID",
    "wof:name":"Stylist",
    "wof:placetype":"venue"
},
  "geometry": {"coordinates":[-116.693376,43.661812],"type":"Point"}
}