{
  "type": "Feature",
  "properties": {
    "iso:country":"US",
    "sg:address":"3084 Triumph Ln",
    "sg:city":"Boise",
    "sg:classifiers":[
        {
            "category":"Home & Garden",
            "subcategory":"Household Appliances",
            "type":"Retail Goods"
        }
    ],
    "sg:phone":"+1 208 344 8717",
    "sg:postcode":"83705",
    "sg:province":"ID",
    "wof:name":"Heartful Promotions",
    "wof:placetype":"venue"
},
  "geometry": {"coordinates":[-116.200619,43.574755],"type":"Point"}
}