{
  "type": "Feature",
  "properties": {
    "iso:country":"US",
    "sg:address":"810 N Henry St",
    "sg:city":"Post Falls",
    "sg:classifiers":[
        {
            "category":"Health Services",
            "subcategory":"Clinic",
            "type":"Services"
        }
    ],
    "sg:phone":"+1 208 773 2297",
    "sg:postcode":"83854",
    "sg:province":"ID",
    "wof:name":"Life Energetics",
    "wof:placetype":"venue"
},
  "geometry": {"coordinates":[-116.94336300000001,47.716862],"type":"Point"}
}