{
  "type": "Feature",
  "properties": {
    "iso:country":"US",
    "sg:address":"1203 Kenyon Rd",
    "sg:city":"Twin Falls",
    "sg:classifiers":[
        {
            "category":"Building & Trades",
            "subcategory":"Construction",
            "type":"Services"
        }
    ],
    "sg:phone":"+1 208 733 3869",
    "sg:postcode":"83301",
    "sg:province":"ID",
    "sg:tags":[
        "contractor"
    ],
    "wof:name":"Schmechel Dry Wall",
    "wof:placetype":"venue"
},
  "geometry": {"coordinates":[-114.494119,42.531531],"type":"Point"}
}