{
  "type": "Feature",
  "properties": {
    "addr:full":"1915 N 16th St Boise ID 83702",
    "addr:housenumber":"1915",
    "addr:postcode":"83702",
    "addr:street":"N 16Th St",
    "iso:country":"US",
    "sg:address":"1915 N 16th St",
    "sg:city":"Boise",
    "sg:classifiers":[
        {
            "category":"Professional",
            "subcategory":"Management & Consulting",
            "type":"Services"
        }
    ],
    "sg:phone":"+1 208 433 0686",
    "sg:postcode":"83702",
    "sg:province":"ID",
    "sg:tags":[
        "coaching"
    ],
    "wof:name":"Sage Project  The",
    "wof:placetype":"venue"
},
  "geometry": {"coordinates":[-116.207093,43.636259],"type":"Point"}
}