{
  "type": "Feature",
  "properties": {
    "iso:country":"US",
    "sg:address":"6633 Whitley Dr",
    "sg:city":"Fruitland",
    "sg:classifiers":[
        {
            "category":"Farming",
            "subcategory":"Farm & Veterinary Services",
            "type":"Manufacturing & Wholesale Goods"
        }
    ],
    "sg:phone":"+1 208 452 3201",
    "sg:postcode":"83619",
    "sg:province":"ID",
    "sg:tags":[
        "preparation",
        "crop",
        "for",
        "market"
    ],
    "wof:name":"Henggeler Bros Inc",
    "wof:placetype":"venue"
},
  "geometry": {"coordinates":[-116.924105,43.985706],"type":"Point"}
}