{
  "type": "Feature",
  "properties": {
    "iso:country":"US",
    "sg:address":"507 S Main St",
    "sg:city":"Hailey",
    "sg:classifiers":[
        {
            "category":"Shopping",
            "subcategory":"Computers & Home Electronics",
            "type":"Retail Goods"
        }
    ],
    "sg:phone":"+1 208 788 9747",
    "sg:postcode":"83333",
    "sg:province":"ID",
    "sg:tags":[
        "equipment",
        "electronic",
        "supply"
    ],
    "wof:name":"Radio Shack",
    "wof:placetype":"venue"
},
  "geometry": {"coordinates":[-114.312359,43.515776],"type":"Point"}
}