{
  "type": "Feature",
  "properties": {
    "iso:country":"US",
    "sg:address":"9045 Irving St",
    "sg:city":"Boise",
    "sg:classifiers":[
        {
            "category":"Social Services",
            "subcategory":"Child Care",
            "type":"Services"
        }
    ],
    "sg:phone":"+1 208 322 1077",
    "sg:postcode":"83704",
    "sg:province":"ID",
    "wof:name":"Today's Child Unique Child Cr",
    "wof:placetype":"venue"
},
  "geometry": {"coordinates":[-116.29537999999999,43.615694],"type":"Point"}
}