{
  "type": "Feature",
  "properties": {
    "addr:full":"504 King St Cottonwood ID 83522",
    "addr:housenumber":"504",
    "addr:postcode":"83522",
    "addr:street":"King St",
    "iso:country":"US",
    "sg:address":"504 King St",
    "sg:city":"Cottonwood",
    "sg:classifiers":[
        {
            "category":"Sports & Exercise",
            "subcategory":"Bowling",
            "type":"Entertainment"
        }
    ],
    "sg:phone":"+1 208 962 5595",
    "sg:postcode":"83522",
    "sg:province":"ID",
    "sg:tags":[
        "center"
    ],
    "wof:name":"Cottonwood Bowl",
    "wof:placetype":"venue"
},
  "geometry": {"coordinates":[-116.349734,46.049588],"type":"Point"}
}