{
  "type": "Feature",
  "properties": {
    "addr:full":"113 McKinley Ave Kellogg ID 83837",
    "addr:housenumber":"113",
    "addr:postcode":"83837",
    "addr:street":"Mckinley Ave",
    "iso:country":"US",
    "sg:address":"113 McKinley Ave",
    "sg:city":"Kellogg",
    "sg:classifiers":[
        {
            "category":"Restaurant",
            "type":"Food & Drink"
        }
    ],
    "sg:phone":"+1 208 783 0547",
    "sg:postcode":"83837",
    "sg:province":"ID",
    "wof:name":"Silver Star Restaurant",
    "wof:placetype":"venue"
},
  "geometry": {"coordinates":[-116.12424799999999,47.535544],"type":"Point"}
}