{
  "type": "Feature",
  "properties": {
    "iso:country":"US",
    "sg:address":"113 McKinley Ave",
    "sg:city":"Kellogg",
    "sg:classifiers":[
        {
            "category":"Restaurant",
            "type":"Food & Drink"
        }
    ],
    "sg:phone":"+1 208 783 0547",
    "sg:postcode":"83837",
    "sg:province":"ID",
    "wof:name":"Silver Star Restaurant",
    "wof:placetype":"venue"
},
  "geometry": {"coordinates":[-116.124248,47.535544],"type":"Point"}
}