{
  "type": "Feature",
  "properties": {
    "iso:country":"US",
    "sg:address":"8251 S Mundt Rd",
    "sg:city":"Coeur D Alene",
    "sg:classifiers":[
        {
            "category":"Building & Trades",
            "subcategory":"Construction",
            "type":"Services"
        }
    ],
    "sg:phone":"+1 208 667 6049",
    "sg:postcode":"83814",
    "sg:province":"ID",
    "sg:tags":[
        "steel",
        "erection",
        "structural"
    ],
    "wof:name":"Mundt Enterprises",
    "wof:placetype":"venue"
},
  "geometry": {"coordinates":[-116.88178600000001,47.599554],"type":"Point"}
}