{
  "type": "Feature",
  "properties": {
    "addr:full":"501 S Main St Meridian ID 83628",
    "addr:housenumber":"501",
    "addr:postcode":"83628",
    "addr:street":"S Main St",
    "iso:country":"US",
    "sg:address":"501 S Main St",
    "sg:city":"Meridian",
    "sg:classifiers":[
        {
            "category":"Restaurant",
            "type":"Food & Drink"
        }
    ],
    "sg:phone":"+1 208 898 9470",
    "sg:postcode":"83628",
    "sg:province":"ID",
    "wof:name":"Muggsy's",
    "wof:placetype":"venue"
},
  "geometry": {"coordinates":[-116.932793,43.610613],"type":"Point"}
}