{
  "type": "Feature",
  "properties": {
    "iso:country":"US",
    "sg:address":"114 W A St",
    "sg:city":"Shoshone",
    "sg:classifiers":[
        {
            "category":"Home & Garden",
            "subcategory":"Garden Supply",
            "type":"Retail Goods"
        }
    ],
    "sg:phone":"+1 208 886 2628",
    "sg:postcode":"83352",
    "sg:province":"ID",
    "sg:tags":[
        "lawn",
        "mower"
    ],
    "sg:website":"www.outdoorpower.com",
    "wof:name":"Outdoor Power",
    "wof:placetype":"venue"
},
  "geometry": {"coordinates":[-114.408446,42.935025],"type":"Point"}
}