{
  "type": "Feature",
  "properties": {
    "addr:full":"2298 Forest Vale Dr Twin Falls ID 83301",
    "addr:housenumber":"2298",
    "addr:postcode":"83301",
    "addr:street":"Forest Vale Dr",
    "iso:country":"US",
    "sg:address":"2298 Forest Vale Dr",
    "sg:city":"Twin Falls",
    "sg:classifiers":[
        {
            "category":"Shopping",
            "type":"Retail Goods"
        }
    ],
    "sg:phone":"+1 208 734 9256",
    "sg:postcode":"83301",
    "sg:province":"ID",
    "sg:tags":[
        "cosmetic",
        "perfume"
    ],
    "wof:name":"Avon Products",
    "wof:placetype":"venue"
},
  "geometry": {"coordinates":[-114.439458,42.568065],"type":"Point"}
}