{
  "type": "Feature",
  "properties": {
    "iso:country":"US",
    "sg:address":"3232 Elder St",
    "sg:city":"Boise",
    "sg:classifiers":[
        {
            "category":"Government",
            "subcategory":"Office",
            "type":"Public Place"
        }
    ],
    "sg:phone":"+1 208 334 6626",
    "sg:postcode":"83705",
    "sg:province":"ID",
    "sg:tags":[
        "state",
        "inspection"
    ],
    "wof:name":"Facility Standards Bureau",
    "wof:placetype":"venue"
},
  "geometry": {"coordinates":[-116.222486,43.573552],"type":"Point"}
}