{
  "type": "Feature",
  "properties": {
    "iso:country":"US",
    "sg:address":"2198 W King Rd",
    "sg:city":"Kuna",
    "sg:classifiers":[
        {
            "category":"Manufacturing",
            "subcategory":"Retail Goods",
            "type":"Manufacturing & Wholesale Goods"
        }
    ],
    "sg:phone":"+1 208 922 4811",
    "sg:postcode":"83634",
    "sg:province":"ID",
    "sg:tags":[
        "product",
        "mfg"
    ],
    "wof:name":"Lazy 9 Trailer Mfg LTD Co",
    "wof:placetype":"venue"
},
  "geometry": {"coordinates":[-116.44066,43.473835],"type":"Point"}
}