{
  "type": "Feature",
  "properties": {
    "iso:country":"US",
    "sg:address":"469 Main St",
    "sg:city":"Boise",
    "sg:classifiers":[
        {
            "category":"Communications",
            "subcategory":"Film & Video Production",
            "type":"Services"
        }
    ],
    "sg:phone":"+1 208 336 4162",
    "sg:postcode":"83702",
    "sg:province":"ID",
    "sg:tags":[
        "motion",
        "picture"
    ],
    "wof:name":"Laughling Dog Productions",
    "wof:placetype":"venue"
},
  "geometry": {"coordinates":[-116.199403,43.613361],"type":"Point"}
}