{
  "type": "Feature",
  "properties": {
    "addr:full":"210 S 2nd St W Soda Springs ID 83276",
    "addr:housenumber":"210",
    "addr:postcode":"83276",
    "addr:street":"S 2Nd St",
    "iso:country":"US",
    "sg:address":"210 S 2nd St W",
    "sg:city":"Soda Springs",
    "sg:classifiers":[
        {
            "category":"Farming",
            "subcategory":"Farm",
            "type":"Manufacturing & Wholesale Goods"
        }
    ],
    "sg:phone":"+1 208 547 4178",
    "sg:postcode":"83276",
    "sg:province":"ID",
    "sg:tags":[
        "crop",
        "general"
    ],
    "wof:name":"Fraser Family Farm LLC",
    "wof:placetype":"venue"
},
  "geometry": {"coordinates":[-111.609937,42.654212],"type":"Point"}
}