{
  "type": "Feature",
  "properties": {
    "iso:country":"US",
    "sg:address":"74 E Miles Ave",
    "sg:city":"Hayden Lake",
    "sg:classifiers":[
        {
            "category":"Building & Trades",
            "subcategory":"Construction",
            "type":"Services"
        }
    ],
    "sg:phone":"+1 208 772 5018",
    "sg:postcode":"83835",
    "sg:province":"ID",
    "sg:tags":[
        "general",
        "contractor"
    ],
    "wof:name":"Rosenberger Construction",
    "wof:placetype":"venue"
},
  "geometry": {"coordinates":[-116.783811,47.766225],"type":"Point"}
}