{
  "type": "Feature",
  "properties": {
    "iso:country":"US",
    "sg:address":"305 Main St",
    "sg:city":"Deary",
    "sg:classifiers":[
        {
            "category":"Personal",
            "subcategory":"Beauty Salon",
            "type":"Services"
        }
    ],
    "sg:phone":"+1 208 877 7025",
    "sg:postcode":"83823",
    "sg:province":"ID",
    "wof:name":"Hi-Lite Beauty Salon",
    "wof:placetype":"venue"
},
  "geometry": {"coordinates":[-116.560845,46.799457],"type":"Point"}
}