{
  "type": "Feature",
  "properties": {
    "addr:full":"1200 Anderson Corner Rd Parma ID 83660",
    "addr:housenumber":"1200",
    "addr:postcode":"83660",
    "addr:street":"Anderson Corner Rd",
    "iso:country":"US",
    "sg:address":"1200 Anderson Corner Rd",
    "sg:city":"Parma",
    "sg:classifiers":[
        {
            "category":"Farming",
            "subcategory":"Nursery",
            "type":"Manufacturing & Wholesale Goods"
        }
    ],
    "sg:phone":"+1 208 674 4000",
    "sg:postcode":"83660",
    "sg:province":"ID",
    "sg:tags":[
        "grower",
        "nursery-wholesale"
    ],
    "sg:website":"http://www.nunhemsusa.com",
    "wof:name":"Nunhems Usa Inc",
    "wof:placetype":"venue"
},
  "geometry": {"coordinates":[-116.94663199999999,43.872959],"type":"Point"}
}