{
  "type": "Feature",
  "properties": {
    "addr:full":"4 W Cameron Ave Kellogg ID 83837",
    "addr:housenumber":"4",
    "addr:postcode":"83837",
    "addr:street":"W Cameron Ave",
    "iso:country":"US",
    "sg:address":"4 W Cameron Ave",
    "sg:city":"Kellogg",
    "sg:classifiers":[
        {
            "category":"Retail",
            "subcategory":"Veterinary Services",
            "type":"Services"
        }
    ],
    "sg:phone":"+1 208 784 1381",
    "sg:postcode":"83837",
    "sg:province":"ID",
    "sg:tags":[
        "hospital",
        "animal"
    ],
    "wof:name":"Kellogg Animal Hospital",
    "wof:placetype":"venue"
},
  "geometry": {"coordinates":[-116.119035,47.538358],"type":"Point"}
}