{
  "type": "Feature",
  "properties": {
    "iso:country":"US",
    "sg:address":"12 E Little Ave",
    "sg:city":"Driggs",
    "sg:classifiers":[
        {
            "category":"Shopping",
            "subcategory":"Bicycles & Sporting Goods",
            "type":"Retail Goods"
        }
    ],
    "sg:phone":"+1 208 354 2828",
    "sg:postcode":"83422",
    "sg:province":"ID",
    "sg:tags":[
        "snowboard"
    ],
    "sg:website":"www.yost.com",
    "wof:name":"Yostmark Mountain Equipment",
    "wof:placetype":"venue"
},
  "geometry": {"coordinates":[-111.110941,43.723026],"type":"Point"}
}