{
  "type": "Feature",
  "properties": {
    "addr:full":"675 Jackson St Twin Falls ID 83301",
    "addr:housenumber":"675",
    "addr:postcode":"83301",
    "addr:street":"Jackson St",
    "iso:country":"US",
    "sg:address":"675 Jackson St",
    "sg:city":"Twin Falls",
    "sg:classifiers":[
        {
            "category":"Professional",
            "subcategory":"Detective & Security Services",
            "type":"Services"
        }
    ],
    "sg:phone":"+1 208 737 9528",
    "sg:postcode":"83301",
    "sg:province":"ID",
    "sg:tags":[
        "car"
    ],
    "wof:name":"Owens Investigation",
    "wof:placetype":"venue"
},
  "geometry": {"coordinates":[-114.472633,42.573076],"type":"Point"}
}