{
  "type": "Feature",
  "properties": {
    "iso:country":"US",
    "sg:address":"401 N 8th St",
    "sg:city":"Parma",
    "sg:classifiers":[
        {
            "category":"Social Services",
            "subcategory":"Adult Care",
            "type":"Services"
        }
    ],
    "sg:phone":"+1 208 722 5496",
    "sg:postcode":"83660",
    "sg:province":"ID",
    "sg:tags":[
        "residential"
    ],
    "wof:name":"In Parma Living Center",
    "wof:placetype":"venue"
},
  "geometry": {"coordinates":[-116.937183,43.784686],"type":"Point"}
}