{
  "type": "Feature",
  "properties": {
    "iso:country":"US",
    "sg:address":"109 N Arthur Ave",
    "sg:city":"Pocatello",
    "sg:classifiers":[
        {
            "category":"Social Services",
            "type":"Services"
        }
    ],
    "sg:phone":"+1 208 234 4673",
    "sg:postcode":"83204",
    "sg:province":"ID",
    "sg:tags":[
        "counselor",
        "marriage",
        "family"
    ],
    "wof:name":"Hope Tree Inc",
    "wof:placetype":"venue"
},
  "geometry": {"coordinates":[-112.452506,42.862107],"type":"Point"}
}