{
  "type": "Feature",
  "properties": {
    "addr:full":"816 4th St S Nampa ID 83651",
    "addr:housenumber":"816",
    "addr:postcode":"83651",
    "addr:street":"4Th St S",
    "iso:country":"US",
    "sg:address":"816 4th St S",
    "sg:city":"Nampa",
    "sg:classifiers":[
        {
            "category":"Personal",
            "subcategory":"Beauty Salon",
            "type":"Services"
        }
    ],
    "sg:phone":"+1 208 442 8438",
    "sg:postcode":"83651",
    "sg:province":"ID",
    "wof:name":"House Of Beauty",
    "wof:placetype":"venue"
},
  "geometry": {"coordinates":[-116.566754,43.579312],"type":"Point"}
}