{
  "type": "Feature",
  "properties": {
    "iso:country":"US",
    "sg:address":"74 N 400 W",
    "sg:city":"Blackfoot",
    "sg:classifiers":[
        {
            "category":"Building & Trades",
            "subcategory":"Electrical",
            "type":"Services"
        }
    ],
    "sg:phone":"+1 208 785 2363",
    "sg:postcode":"83221",
    "sg:province":"ID",
    "sg:tags":[
        "electric",
        "contractor"
    ],
    "wof:name":"Davis Electric Co",
    "wof:placetype":"venue"
},
  "geometry": {"coordinates":[-112.375901,43.209958],"type":"Point"}
}