{
  "type": "Feature",
  "properties": {
    "iso:country":"US",
    "sg:address":"2716 Addison Ave E",
    "sg:city":"Twin Falls",
    "sg:classifiers":[
        {
            "category":"Professional",
            "subcategory":"Accounting & Tax Preparation",
            "type":"Services"
        }
    ],
    "sg:phone":"+1 208 736 8297",
    "sg:postcode":"83301",
    "sg:province":"ID",
    "sg:tags":[
        "return",
        "filing"
    ],
    "wof:name":"Magic Valley Tax & Bookkeeping",
    "wof:placetype":"venue"
},
  "geometry": {"coordinates":[-114.426781,42.562799],"type":"Point"}
}