{
  "type": "Feature",
  "properties": {
    "iso:country":"US",
    "sg:address":"1879 Arlington Dr",
    "sg:city":"Pocatello",
    "sg:classifiers":[
        {
            "category":"Professional",
            "subcategory":"Business Services",
            "type":"Services"
        }
    ],
    "sg:phone":"+1 208 233 8045",
    "sg:postcode":"83204",
    "sg:province":"ID",
    "sg:tags":[
        "embroidery"
    ],
    "sg:website":"www.tejacadv.com",
    "wof:name":"Rocky Mountain Designs",
    "wof:placetype":"venue"
},
  "geometry": {"coordinates":[-112.423857,42.814111],"type":"Point"}
}