{
  "type": "Feature",
  "properties": {
    "iso:country":"US",
    "sg:address":"1555 N 1200 E",
    "sg:city":"Terreton",
    "sg:classifiers":[
        {
            "category":"Wholesale",
            "subcategory":"Farm Supplies",
            "type":"Manufacturing & Wholesale Goods"
        }
    ],
    "sg:phone":"+1 208 663 4415",
    "sg:postcode":"83450",
    "sg:province":"ID",
    "sg:tags":[
        "feed"
    ],
    "wof:name":"Sebs Feed & Supply",
    "wof:placetype":"venue"
},
  "geometry": {"coordinates":[-112.456022,43.847837],"type":"Point"}
}