{
  "type": "Feature",
  "properties": {
    "iso:country":"US",
    "sg:address":"595 E 42nd St",
    "sg:city":"Boise",
    "sg:classifiers":[
        {
            "category":"Wholesale",
            "subcategory":"Office Equipment",
            "type":"Manufacturing & Wholesale Goods"
        }
    ],
    "sg:phone":"+1 208 376 6900",
    "sg:postcode":"83714",
    "sg:province":"ID",
    "sg:tags":[
        "machine",
        "duplicating",
        "copying"
    ],
    "wof:name":"DPI",
    "wof:placetype":"venue"
},
  "geometry": {"coordinates":[-116.24553,43.635135],"type":"Point"}
}