{
  "type": "Feature",
  "properties": {
    "iso:country":"US",
    "sg:address":"11 E Hooper Ave",
    "sg:city":"Soda Springs",
    "sg:classifiers":[
        {
            "category":"Organizations",
            "subcategory":"Religious Organization",
            "type":"Services"
        }
    ],
    "sg:phone":"+1 208 547 1870",
    "sg:postcode":"83276",
    "sg:province":"ID",
    "sg:tags":[
        "church"
    ],
    "wof:name":"Hope Lutheran Church",
    "wof:placetype":"venue"
},
  "geometry": {"coordinates":[-111.603379,42.659072],"type":"Point"}
}