{
  "type": "Feature",
  "properties": {
    "iso:country":"US",
    "sg:address":"412 Burrell Ave",
    "sg:city":"Lewiston",
    "sg:classifiers":[
        {
            "category":"Professional",
            "type":"Services"
        }
    ],
    "sg:phone":"+1 208 743 3841",
    "sg:postcode":"83501",
    "sg:province":"ID",
    "sg:tags":[
        "agency",
        "government"
    ],
    "wof:name":"National Weather Svc",
    "wof:placetype":"venue"
},
  "geometry": {"coordinates":[-117.00882,46.377005],"type":"Point"}
}