{
  "type": "Feature",
  "properties": {
    "iso:country":"US",
    "sg:address":"2480 N Bullock Ave",
    "sg:city":"Meridian",
    "sg:classifiers":[
        {
            "category":"Building & Trades",
            "subcategory":"Construction",
            "type":"Services"
        }
    ],
    "sg:phone":"+1 208 887 1884",
    "sg:postcode":"83646",
    "sg:province":"ID",
    "sg:tags":[
        "house"
    ],
    "wof:name":"Creekside Custom Homes Inc",
    "wof:placetype":"venue"
},
  "geometry": {"coordinates":[-116.362845,43.627629],"type":"Point"}
}