{
  "type": "Feature",
  "properties": {
    "iso:country":"US",
    "sg:address":"2549 E Iona Rd",
    "sg:city":"Idaho Falls",
    "sg:classifiers":[
        {
            "category":"Social Services",
            "subcategory":"Child Care",
            "type":"Services"
        }
    ],
    "sg:phone":"+1 208 522 4054",
    "sg:postcode":"83401",
    "sg:province":"ID",
    "sg:tags":[
        "day"
    ],
    "wof:name":"Home Away From Home Day Care",
    "wof:placetype":"venue"
},
  "geometry": {"coordinates":[-111.98314499999999,43.525929],"type":"Point"}
}