{
  "type": "Feature",
  "properties": {
    "iso:country":"US",
    "sg:address":"8250 Lola Ln",
    "sg:city":"Nampa",
    "sg:classifiers":[
        {
            "category":"Insurance",
            "subcategory":"Insurance Agent",
            "type":"Services"
        }
    ],
    "sg:phone":"+1 208 467 2480",
    "sg:postcode":"83686",
    "sg:province":"ID",
    "wof:name":"Beneficial Financial Group",
    "wof:placetype":"venue"
},
  "geometry": {"coordinates":[-116.558543,43.466669],"type":"Point"}
}