{
  "type": "Feature",
  "properties": {
    "iso:country":"US",
    "sg:address":"8638 Overland Rd",
    "sg:city":"Boise",
    "sg:classifiers":[
        {
            "category":"Shopping",
            "subcategory":"Florist",
            "type":"Retail Goods"
        }
    ],
    "sg:phone":"+1 208 322 4438",
    "sg:postcode":"83709",
    "sg:province":"ID",
    "wof:name":"Balloons & Bears",
    "wof:placetype":"venue"
},
  "geometry": {"coordinates":[-116.288776,43.590333],"type":"Point"}
}