{
  "type": "Feature",
  "properties": {
    "iso:country":"US",
    "sg:address":"417 Main St",
    "sg:city":"Filer",
    "sg:classifiers":[
        {
            "category":"Manufacturing",
            "subcategory":"Tools & Machinery",
            "type":"Manufacturing & Wholesale Goods"
        }
    ],
    "sg:phone":"+1 208 326 3566",
    "sg:postcode":"83328",
    "sg:province":"ID",
    "sg:tags":[
        "machine",
        "shop"
    ],
    "wof:name":"Wayment Manufacturing Inc",
    "wof:placetype":"venue"
},
  "geometry": {"coordinates":[-114.610437,42.570123],"type":"Point"}
}