{
  "type": "Feature",
  "properties": {
    "iso:country":"US",
    "sg:address":"611 E Mullan Ave",
    "sg:city":"Osburn",
    "sg:classifiers":[
        {
            "category":"Building & Trades",
            "subcategory":"Plumbing",
            "type":"Services"
        }
    ],
    "sg:phone":"+1 208 753 2503",
    "sg:postcode":"83849",
    "sg:province":"ID",
    "sg:tags":[
        "plumbing",
        "contractor"
    ],
    "wof:name":"Bell Plumbing & Heating",
    "wof:placetype":"venue"
},
  "geometry": {"coordinates":[-115.995728,47.504336],"type":"Point"}
}