{
  "type": "Feature",
  "properties": {
    "iso:country":"US",
    "sg:address":"101 E Appleway Ave",
    "sg:city":"Coeur D Alene",
    "sg:classifiers":[
        {
            "category":"Wholesale",
            "subcategory":"Sporting Goods",
            "type":"Manufacturing & Wholesale Goods"
        }
    ],
    "sg:phone":"+1 208 667 2250",
    "sg:postcode":"83814",
    "sg:province":"ID",
    "sg:tags":[
        "paint",
        "game",
        "ball"
    ],
    "wof:name":"Virtual Assault Paintball",
    "wof:placetype":"venue"
},
  "geometry": {"coordinates":[-116.78526,47.700734],"type":"Point"}
}