{
  "type": "Feature",
  "properties": {
    "addr:full":"1508 Northwest Blvd Coeur D Alene ID 83814",
    "addr:housenumber":"1508",
    "addr:postcode":"83814",
    "addr:street":"Northwest Blvd",
    "iso:country":"US",
    "sg:address":"1508 Northwest Blvd",
    "sg:city":"Coeur D Alene",
    "sg:classifiers":[
        {
            "category":"Real Estate",
            "subcategory":"Real Estate Agent",
            "type":"Services"
        }
    ],
    "sg:phone":"+1 208 667 9595",
    "sg:postcode":"83814",
    "sg:province":"ID",
    "wof:name":"Help U Sell List For Less",
    "wof:placetype":"venue"
},
  "geometry": {"coordinates":[-116.797601,47.687865],"type":"Point"}
}