{
  "type": "Feature",
  "properties": {
    "iso:country":"US",
    "sg:address":"817 N Meridian Rd",
    "sg:city":"Meridian",
    "sg:classifiers":[
        {
            "category":"Retail",
            "subcategory":"Repair Shop",
            "type":"Services"
        }
    ],
    "sg:phone":"+1 208 887 0815",
    "sg:postcode":"83642",
    "sg:province":"ID",
    "sg:tags":[
        "clocks",
        "parts"
    ],
    "wof:name":"Ye Olde Clock Shoppe Inc",
    "wof:placetype":"venue"
},
  "geometry": {"coordinates":[-116.393612,43.611185],"type":"Point"}
}