{
  "type": "Feature",
  "properties": {
    "addr:full":"2982 E Dagger Falls Dr Eagle ID 83616",
    "addr:housenumber":"2982",
    "addr:postcode":"83616",
    "addr:street":"E Dagger Falls Dr",
    "iso:country":"US",
    "sg:address":"2982 E Dagger Falls Dr",
    "sg:city":"Eagle",
    "sg:classifiers":[
        {
            "category":"Professional",
            "type":"Services"
        }
    ],
    "sg:phone":"+1 208 761 6265",
    "sg:postcode":"83616",
    "sg:province":"ID",
    "wof:name":"American Biohazard Service",
    "wof:placetype":"venue"
},
  "geometry": {"coordinates":[-116.316772,43.70962],"type":"Point"}
}