{
  "type": "Feature",
  "properties": {
    "addr:full":"447 N Kuna-Meridian Rd Kuna ID 83634",
    "addr:housenumber":"447",
    "addr:postcode":"83634",
    "addr:street":"N Kuna-Meridian Rd",
    "iso:country":"US",
    "sg:address":"447 N Kuna-Meridian Rd",
    "sg:city":"Kuna",
    "sg:classifiers":[
        {
            "category":"Retail",
            "subcategory":"Repair Shop",
            "type":"Services"
        }
    ],
    "sg:phone":"+1 208 922 4468",
    "sg:postcode":"83634",
    "sg:province":"ID",
    "wof:name":"Jay S Classics",
    "wof:placetype":"venue"
},
  "geometry": {"coordinates":[-116.393913,43.493487],"type":"Point"}
}