{
  "type": "Feature",
  "properties": {
    "iso:country":"US",
    "sg:address":"960 W Palouse River Dr",
    "sg:city":"Moscow",
    "sg:classifiers":[
        {
            "category":"Place Of Worship",
            "subcategory":"Church",
            "type":"Public Place"
        },
        {
            "category":"Place Of Worship",
            "type":"Public Place"
        }
    ],
    "sg:phone":"+1 208 883 0661",
    "sg:postcode":"83843",
    "sg:province":"ID",
    "sg:tags":[
        "churches-interdenominational",
        "churches-non-denominational",
        "churches-various",
        "denomination"
    ],
    "sg:website":"http://www.bridgebible.org",
    "wof:name":"Bridge Bible Fellowship",
    "wof:placetype":"venue"
},
  "geometry": {"coordinates":[-117.013052,46.7146],"type":"Point"}
}