{
  "type": "Feature",
  "properties": {
    "iso:country":"US",
    "sg:address":"1555 E 1500 N",
    "sg:city":"Hamer",
    "sg:phone":"+1 208 663 4412",
    "sg:postcode":"83425",
    "sg:province":"ID",
    "sg:tags":[
        "farm",
        "field",
        "crop"
    ],
    "wof:name":"Paul Gunderson",
    "wof:placetype":"venue"
},
  "geometry": {"coordinates":[-112.384227,43.841473],"type":"Point"}
}