{
  "type": "Feature",
  "properties": {
    "iso:country":"US",
    "sg:address":"106 S Scott St",
    "sg:city":"Post Falls",
    "sg:classifiers":[
        {
            "category":"Retail",
            "subcategory":"Auto Repair",
            "type":"Services"
        }
    ],
    "sg:phone":"+1 208 773 8673",
    "sg:postcode":"83854",
    "sg:province":"ID",
    "sg:tags":[
        "automotive"
    ],
    "wof:name":"Lake City Electric",
    "wof:placetype":"venue"
},
  "geometry": {"coordinates":[-116.92034200000001,47.705425],"type":"Point"}
}