{
  "type": "Feature",
  "properties": {
    "iso:country":"US",
    "sg:address":"995 Shoup Ave",
    "sg:city":"Idaho Falls",
    "sg:classifiers":[
        {
            "category":"Food & Beverages",
            "subcategory":"Fruits & Vegetables",
            "type":"Retail Goods"
        }
    ],
    "sg:phone":"+1 208 528 9811",
    "sg:postcode":"83402",
    "sg:province":"ID",
    "sg:tags":[
        "produce"
    ],
    "wof:name":"Fresh Produce",
    "wof:placetype":"venue"
},
  "geometry": {"coordinates":[-112.036311,43.496574],"type":"Point"}
}