{
  "type": "Feature",
  "properties": {
    "addr:full":"1400 N Holmes Ave Idaho Falls ID 83401",
    "addr:housenumber":"1400",
    "addr:postcode":"83401",
    "addr:street":"N Holmes Ave",
    "iso:country":"US",
    "sg:address":"1400 N Holmes Ave",
    "sg:city":"Idaho Falls",
    "sg:classifiers":[
        {
            "category":"Autos & Motor Vehicles",
            "subcategory":"Automobile Sales",
            "type":"Retail Goods"
        }
    ],
    "sg:phone":"+1 208 522 6030",
    "sg:postcode":"83401",
    "sg:province":"ID",
    "sg:tags":[
        "car",
        "dealer"
    ],
    "wof:name":"Wackeril Auto Ctr",
    "wof:placetype":"venue"
},
  "geometry": {"coordinates":[-112.023847,43.511314],"type":"Point"}
}