{
  "type": "Feature",
  "properties": {
    "iso:country":"US",
    "sg:address":"25 E Fairview Ave",
    "sg:city":"Meridian",
    "sg:classifiers":[
        {
            "category":"Professional",
            "type":"Services"
        }
    ],
    "sg:phone":"+1 208 895 0767",
    "sg:postcode":"83642",
    "sg:province":"ID",
    "sg:tags":[
        "establishment"
    ],
    "wof:name":"Koval Marketing",
    "wof:placetype":"venue"
},
  "geometry": {"coordinates":[-116.39195599999999,43.619092],"type":"Point"}
}