{
  "type": "Feature",
  "properties": {
    "addr:full":"3901 Rose Hill St Boise ID 83705",
    "addr:housenumber":"3901",
    "addr:postcode":"83705",
    "addr:street":"Rose Hill St",
    "iso:country":"US",
    "sg:address":"3901 Rose Hill St",
    "sg:city":"Boise",
    "sg:classifiers":[
        {
            "category":"Restaurant",
            "type":"Food & Drink"
        }
    ],
    "sg:phone":"+1 208 367 1314",
    "sg:postcode":"83705",
    "sg:province":"ID",
    "sg:tags":[
        "caterer"
    ],
    "wof:name":"Sushi On The Spot",
    "wof:placetype":"venue"
},
  "geometry": {"coordinates":[-116.229242,43.600615],"type":"Point"}
}