{
  "type": "Feature",
  "properties": {
    "addr:full":"9490 Fairview Ave Boise ID 83704",
    "addr:housenumber":"9490",
    "addr:postcode":"83704",
    "addr:street":"Fairview Ave",
    "iso:country":"US",
    "sg:address":"9490 Fairview Ave",
    "sg:city":"Boise",
    "sg:classifiers":[
        {
            "category":"Health Services",
            "subcategory":"Clinic",
            "type":"Services"
        }
    ],
    "sg:phone":"+1 208 322 7061",
    "sg:postcode":"83704",
    "sg:province":"ID",
    "sg:tags":[
        "home"
    ],
    "wof:name":"First Choice Home Care",
    "wof:placetype":"venue"
},
  "geometry": {"coordinates":[-116.300579,43.619536],"type":"Point"}
}