{
  "type": "Feature",
  "properties": {
    "iso:country":"US",
    "sg:address":"1303 NW 16th St",
    "sg:city":"Fruitland",
    "sg:classifiers":[
        {
            "category":"Real Estate",
            "subcategory":"Real Estate Agent",
            "type":"Services"
        }
    ],
    "sg:phone":"+1 208 452 4334",
    "sg:postcode":"83619",
    "sg:province":"ID",
    "sg:website":"www.remax.com",
    "wof:name":"Re/Max Tri-Cities",
    "wof:placetype":"venue"
},
  "geometry": {"coordinates":[-116.93097299999999,44.025485],"type":"Point"}
}