{
  "type": "Feature",
  "properties": {
    "addr:full":"601 Packard Ave Pocatello ID 83201",
    "addr:housenumber":"601",
    "addr:postcode":"83201",
    "addr:street":"Packard Ave",
    "iso:country":"US",
    "sg:address":"601 Packard Ave",
    "sg:city":"Pocatello",
    "sg:classifiers":[
        {
            "category":"Professional",
            "subcategory":"Secretarial Services",
            "type":"Services"
        }
    ],
    "sg:phone":"+1 208 233 0889",
    "sg:postcode":"83201",
    "sg:province":"ID",
    "sg:tags":[
        "reporting"
    ],
    "wof:name":"Rapid Resumes",
    "wof:placetype":"venue"
},
  "geometry": {"coordinates":[-112.460025,42.887778],"type":"Point"}
}