{
  "type": "Feature",
  "properties": {
    "iso:country":"US",
    "sg:address":"5 Arena Rd",
    "sg:city":"Garden Valley",
    "sg:classifiers":[
        {
            "category":"Professional",
            "subcategory":"Advertising",
            "type":"Services"
        }
    ],
    "sg:phone":"+1 208 462 3130",
    "sg:postcode":"83622",
    "sg:province":"ID",
    "sg:tags":[
        "counselor"
    ],
    "wof:name":"Satellite Direct",
    "wof:placetype":"venue"
},
  "geometry": {"coordinates":[-115.954424,44.172121],"type":"Point"}
}