{
  "type": "Feature",
  "properties": {
    "iso:country":"US",
    "sg:address":"2180 Dora Ln",
    "sg:city":"Boise",
    "sg:classifiers":[
        {
            "category":"Building & Trades",
            "subcategory":"Construction",
            "type":"Services"
        }
    ],
    "sg:phone":"+1 208 367 9207",
    "sg:postcode":"83702",
    "sg:province":"ID",
    "sg:tags":[
        "general",
        "contractor"
    ],
    "wof:name":"Idaho Contractor Referral",
    "wof:placetype":"venue"
},
  "geometry": {"coordinates":[-116.215211,43.63952],"type":"Point"}
}