{
  "type": "Feature",
  "properties": {
    "addr:full":"2378 Mill Creek Rd Council ID 83612",
    "addr:housenumber":"2378",
    "addr:postcode":"83612",
    "addr:street":"Mill Creek Rd",
    "iso:country":"US",
    "sg:address":"2378 Mill Creek Rd",
    "sg:city":"Council",
    "sg:classifiers":[
        {
            "category":"Freight",
            "type":"Transportation"
        }
    ],
    "sg:phone":"+1 208 253 4420",
    "sg:postcode":"83612",
    "sg:province":"ID",
    "sg:tags":[
        "excavation",
        "trucking"
    ],
    "wof:name":"Hileman Trucking Inc",
    "wof:placetype":"venue"
},
  "geometry": {"coordinates":[-116.414584,44.763507],"type":"Point"}
}