{
  "type": "Feature",
  "properties": {
    "iso:country":"US",
    "sg:address":"3592 Park Ln",
    "sg:city":"American Falls",
    "sg:classifiers":[
        {
            "category":"Recreation",
            "type":"Entertainment"
        }
    ],
    "sg:phone":"+1 208 548 2672",
    "sg:postcode":"83211",
    "sg:province":"ID",
    "sg:tags":[
        "parks"
    ],
    "wof:name":"Massacre Rocks State Park",
    "wof:placetype":"venue"
},
  "geometry": {"coordinates":[-112.986555,42.676908],"type":"Point"}
}