{
  "type": "Feature",
  "properties": {
    "iso:country":"US",
    "sg:address":"22 College Ave",
    "sg:city":"Rexburg",
    "sg:classifiers":[
        {
            "category":"Communications",
            "type":"Services"
        }
    ],
    "sg:phone":"+1 208 656 9700",
    "sg:postcode":"83440",
    "sg:province":"ID",
    "wof:name":"Point Communication",
    "wof:placetype":"venue"
},
  "geometry": {"coordinates":[-111.782473,43.825558],"type":"Point"}
}