{
  "type": "Feature",
  "properties": {
    "iso:country":"US",
    "sg:address":"1261 Wilson Ave",
    "sg:city":"Pocatello",
    "sg:classifiers":[
        {
            "category":"Home & Garden",
            "subcategory":"Furniture",
            "type":"Retail Goods"
        }
    ],
    "sg:phone":"+1 208 237 9090",
    "sg:postcode":"83201",
    "sg:province":"ID",
    "sg:tags":[
        "builder",
        "custom"
    ],
    "wof:name":"Real Wood Custom Furniture LLP",
    "wof:placetype":"venue"
},
  "geometry": {"coordinates":[-112.45359000000001,42.895925],"type":"Point"}
}