{
  "type": "Feature",
  "properties": {
    "addr:full":"650 S 5th Ave Pocatello ID 83201",
    "addr:housenumber":"650",
    "addr:postcode":"83201",
    "addr:street":"S 5Th Ave",
    "iso:country":"US",
    "sg:address":"650 S 5th Ave",
    "sg:city":"Pocatello",
    "sg:classifiers":[
        {
            "category":"Manufacturing",
            "subcategory":"Printing",
            "type":"Manufacturing & Wholesale Goods"
        }
    ],
    "sg:phone":"+1 208 232 6646",
    "sg:postcode":"83201",
    "sg:province":"ID",
    "sg:tags":[
        "printer"
    ],
    "sg:website":"www.kinkos.com",
    "wof:name":"Fed Ex Kinko's Ofc & Print Ctr",
    "wof:placetype":"venue"
},
  "geometry": {"coordinates":[-112.438667,42.862462],"type":"Point"}
}