{
  "type": "Feature",
  "properties": {
    "iso:country":"US",
    "sg:address":"2021 W Norcrest Dr",
    "sg:city":"Boise",
    "sg:classifiers":[
        {
            "category":"Wholesale",
            "subcategory":"Vending Machines",
            "type":"Manufacturing & Wholesale Goods"
        }
    ],
    "sg:phone":"+1 208 343 0342",
    "sg:postcode":"83705",
    "sg:province":"ID",
    "sg:tags":[
        "operator"
    ],
    "wof:name":"Draks Enterprises",
    "wof:placetype":"venue"
},
  "geometry": {"coordinates":[-116.206323,43.577783],"type":"Point"}
}