{
  "type": "Feature",
  "properties": {
    "iso:country":"US",
    "sg:address":"5500 Emerald St",
    "sg:city":"Boise",
    "sg:classifiers":[
        {
            "category":"Social Services",
            "type":"Services"
        }
    ],
    "sg:phone":"+1 208 322 8112",
    "sg:postcode":"83706",
    "sg:province":"ID",
    "sg:tags":[
        "counselor",
        "marriage",
        "family"
    ],
    "sg:website":"www.gracecounseling.com",
    "wof:name":"Grace Counseling",
    "wof:placetype":"venue"
},
  "geometry": {"coordinates":[-116.249622,43.611701],"type":"Point"}
}