{
  "type": "Feature",
  "properties": {
    "addr:full":"1124 Burrell Ave Lewiston ID 83501",
    "addr:housenumber":"1124",
    "addr:postcode":"83501",
    "addr:street":"Burrell Ave",
    "iso:country":"US",
    "sg:address":"1124 Burrell Ave",
    "sg:city":"Lewiston",
    "sg:classifiers":[
        {
            "category":"Real Estate",
            "subcategory":"Real Estate Operator",
            "type":"Services"
        }
    ],
    "sg:phone":"+1 208 743 0185",
    "sg:postcode":"83501",
    "sg:province":"ID",
    "sg:tags":[
        "apartment"
    ],
    "wof:name":"Burrell Street Station",
    "wof:placetype":"venue"
},
  "geometry": {"coordinates":[-116.973339,46.376587],"type":"Point"}
}