{
  "type": "Feature",
  "properties": {
    "iso:country":"US",
    "sg:address":"783 W Idaho St",
    "sg:city":"Boise",
    "sg:classifiers":[
        {
            "category":"Personal",
            "subcategory":"Beauty Salon",
            "type":"Services"
        }
    ],
    "sg:phone":"+1 208 429 1800",
    "sg:postcode":"83702",
    "sg:province":"ID",
    "wof:name":"Crimson Mist",
    "wof:placetype":"venue"
},
  "geometry": {"coordinates":[-116.20207499999999,43.615831],"type":"Point"}
}