{
  "type": "Feature",
  "properties": {
    "addr:full":"1350 Parkway Dr Blackfoot ID 83221",
    "addr:housenumber":"1350",
    "addr:postcode":"83221",
    "addr:street":"Parkway Dr",
    "iso:country":"US",
    "sg:address":"1350 Parkway Dr",
    "sg:city":"Blackfoot",
    "sg:classifiers":[
        {
            "category":"Restaurant",
            "type":"Food & Drink"
        }
    ],
    "sg:phone":"+1 208 785 6330",
    "sg:postcode":"83221",
    "sg:province":"ID",
    "wof:name":"Pizza Hut",
    "wof:placetype":"venue"
},
  "geometry": {"coordinates":[-112.36058300000001,43.195424],"type":"Point"}
}