{
  "type": "Feature",
  "properties": {
    "iso:country":"US",
    "sg:address":"1916 N Lakewood Dr",
    "sg:city":"Coeur D Alene",
    "sg:classifiers":[
        {
            "category":"Organizations",
            "subcategory":"Non-profit Organization",
            "type":"Services"
        }
    ],
    "sg:phone":"+1 208 667 4628",
    "sg:postcode":"83814",
    "sg:province":"ID",
    "wof:name":"Lake City Senior Ctr",
    "wof:placetype":"venue"
},
  "geometry": {"coordinates":[-116.80300699999999,47.693789],"type":"Point"}
}