{
  "type": "Feature",
  "properties": {
    "addr:full":"4180 Hatchery Rd Eagle ID 83616",
    "addr:housenumber":"4180",
    "addr:postcode":"83616",
    "addr:street":"Hatchery Rd",
    "iso:country":"US",
    "sg:address":"4180 Hatchery Rd",
    "sg:city":"Eagle",
    "sg:classifiers":[
        {
            "category":"Shopping",
            "subcategory":"Hobbies, Toys, & Games",
            "type":"Retail Goods"
        }
    ],
    "sg:phone":"+1 208 939 6798",
    "sg:postcode":"83616",
    "sg:province":"ID",
    "wof:name":"Wood Elf Toys",
    "wof:placetype":"venue"
},
  "geometry": {"coordinates":[-116.404448,43.684827],"type":"Point"}
}