{
  "type": "Feature",
  "properties": {
    "iso:country":"US",
    "sg:address":"6629 Ustick Rd",
    "sg:city":"Boise",
    "sg:classifiers":[
        {
            "category":"Organizations",
            "subcategory":"Religious Organization",
            "type":"Services"
        }
    ],
    "sg:phone":"+1 208 323 0197",
    "sg:postcode":"83704",
    "sg:province":"ID",
    "sg:tags":[
        "pentecostal",
        "church"
    ],
    "wof:name":"Boise Worship Center",
    "wof:placetype":"venue"
},
  "geometry": {"coordinates":[-116.266035,43.633753],"type":"Point"}
}