{
  "type": "Feature",
  "properties": {
    "iso:country":"US",
    "sg:address":"1020 Michigan St",
    "sg:city":"Sandpoint",
    "sg:classifiers":[
        {
            "category":"Government",
            "subcategory":"Office",
            "type":"Public Place"
        }
    ],
    "sg:phone":"+1 208 263 5159",
    "sg:postcode":"83864",
    "sg:province":"ID",
    "wof:name":"Panhandle Home Health Agency",
    "wof:placetype":"venue"
},
  "geometry": {"coordinates":[-116.56219900000001,48.269458],"type":"Point"}
}