{
  "type": "Feature",
  "properties": {
    "iso:country":"US",
    "sg:address":"8439 W Idaho Blvd",
    "sg:city":"Letha",
    "sg:classifiers":[
        {
            "category":"Freight",
            "type":"Transportation"
        }
    ],
    "sg:phone":"+1 208 365 2616",
    "sg:postcode":"83636",
    "sg:province":"ID",
    "sg:tags":[
        "livestock",
        "hauling"
    ],
    "wof:name":"Weekes Trucking Inc",
    "wof:placetype":"venue"
},
  "geometry": {"coordinates":[-116.651193,43.894413],"type":"Point"}
}