{
  "type": "Feature",
  "properties": {
    "iso:country":"US",
    "sg:address":"17008 W Rice Ave",
    "sg:city":"Hauser",
    "sg:classifiers":[
        {
            "category":"Utilities",
            "subcategory":"Electric",
            "type":"Services"
        },
        {
            "category":"Building & Trades",
            "subcategory":"Electrical",
            "type":"Services"
        }
    ],
    "sg:phone":"+1 208 773 3275",
    "sg:postcode":"83854",
    "sg:province":"ID",
    "sg:tags":[
        "supplies-repair",
        "industrial",
        "electrician",
        "equipment",
        "equipment-repair",
        "contractors-commercial",
        "electronic"
    ],
    "wof:name":"Chet's Electric",
    "wof:placetype":"venue"
},
  "geometry": {"coordinates":[-117.015698,47.763455],"type":"Point"}
}