{
  "type": "Feature",
  "properties": {
    "iso:country":"US",
    "sg:address":"658 Overland Ave",
    "sg:city":"Burley",
    "sg:classifiers":[
        {
            "category":"Insurance",
            "subcategory":"Insurance Agent",
            "type":"Services"
        }
    ],
    "sg:phone":"+1 208 878 1399",
    "sg:postcode":"83318",
    "sg:province":"ID",
    "wof:name":"Progressive Insurance Co",
    "wof:placetype":"venue"
},
  "geometry": {"coordinates":[-113.793324,42.545087],"type":"Point"}
}