{
  "type": "Feature",
  "properties": {
    "iso:country":"US",
    "sg:address":"2530 W 1600 S",
    "sg:city":"Aberdeen",
    "sg:classifiers":[
        {
            "category":"Building & Trades",
            "subcategory":"Construction",
            "type":"Services"
        }
    ],
    "sg:phone":"+1 208 397 4039",
    "sg:postcode":"83210",
    "sg:province":"ID",
    "sg:tags":[
        "hanging",
        "contractor"
    ],
    "wof:name":"Barelas Painting",
    "wof:placetype":"venue"
},
  "geometry": {"coordinates":[-112.797795,42.965815],"type":"Point"}
}