{
  "type": "Feature",
  "properties": {
    "iso:country":"US",
    "sg:address":"7659 S Marsh Creek Rd",
    "sg:city":"Mc Cammon",
    "sg:classifiers":[
        {
            "category":"Professional",
            "subcategory":"Business Services",
            "type":"Services"
        }
    ],
    "sg:phone":"+1 208 254 3532",
    "sg:postcode":"83250",
    "sg:province":"ID",
    "wof:name":"J & TT Enterprises LLC",
    "wof:placetype":"venue"
},
  "geometry": {"coordinates":[-112.232084,42.65096],"type":"Point"}
}