{
  "type": "Feature",
  "properties": {
    "iso:country":"US",
    "sg:address":"17785 Mink Rd",
    "sg:city":"Caldwell",
    "sg:classifiers":[
        {
            "category":"Farming",
            "subcategory":"Farm",
            "type":"Manufacturing & Wholesale Goods"
        }
    ],
    "sg:phone":"+1 208 459 4647",
    "sg:postcode":"83607",
    "sg:province":"ID",
    "sg:tags":[
        "crop",
        "general"
    ],
    "wof:name":"Peterson Farm",
    "wof:placetype":"venue"
},
  "geometry": {"coordinates":[-116.748342,43.71279],"type":"Point"}
}