{
  "type": "Feature",
  "properties": {
    "addr:full":"525 Steelhead Way Boise ID 83704",
    "addr:housenumber":"525",
    "addr:postcode":"83704",
    "addr:street":"Steelhead Way",
    "iso:country":"US",
    "sg:address":"525 Steelhead Way",
    "sg:city":"Boise",
    "sg:classifiers":[
        {
            "category":"Wholesale",
            "subcategory":"Hardware",
            "type":"Manufacturing & Wholesale Goods"
        }
    ],
    "sg:phone":"+1 208 377 1600",
    "sg:postcode":"83704",
    "sg:province":"ID",
    "sg:tags":[
        "air",
        "parts",
        "conditioning",
        "supply"
    ],
    "wof:name":"Johnstone Supply",
    "wof:placetype":"venue"
},
  "geometry": {"coordinates":[-116.290389,43.609113],"type":"Point"}
}