{
  "type": "Feature",
  "properties": {
    "iso:country":"US",
    "sg:address":"7249 Potomac Dr",
    "sg:city":"Boise",
    "sg:classifiers":[
        {
            "category":"Building & Trades",
            "subcategory":"Construction",
            "type":"Services"
        }
    ],
    "sg:phone":"+1 208 345 4232",
    "sg:postcode":"83704",
    "sg:province":"ID",
    "sg:tags":[
        "repairing",
        "remodeling",
        "contractor"
    ],
    "wof:name":"Crossroads Construction",
    "wof:placetype":"venue"
},
  "geometry": {"coordinates":[-116.272603,43.611053],"type":"Point"}
}