{
  "type": "Feature",
  "properties": {
    "iso:country":"US",
    "sg:address":"6336 W Contractors St",
    "sg:city":"Boise",
    "sg:classifiers":[
        {
            "category":"Building & Trades",
            "subcategory":"Construction",
            "type":"Services"
        }
    ],
    "sg:phone":"+1 208 562 6300",
    "sg:postcode":"83709",
    "sg:province":"ID",
    "sg:tags":[
        "fire",
        "restoration",
        "damage"
    ],
    "wof:name":"Rapid Response Inc",
    "wof:placetype":"venue"
},
  "geometry": {"coordinates":[-116.26209799999999,43.569203],"type":"Point"}
}