{
  "type": "Feature",
  "properties": {
    "addr:full":"1019 W Bridge St Blackfoot ID 83221",
    "addr:housenumber":"1019",
    "addr:postcode":"83221",
    "addr:street":"W Bridge St",
    "iso:country":"US",
    "sg:address":"1019 W Bridge St",
    "sg:city":"Blackfoot",
    "sg:classifiers":[
        {
            "category":"Professional",
            "subcategory":"Business Services",
            "type":"Services"
        }
    ],
    "sg:phone":"+1 208 785 0161",
    "sg:postcode":"83221",
    "sg:province":"ID",
    "sg:tags":[
        "reservation",
        "motel",
        "hotel"
    ],
    "wof:name":"Sunset Motel",
    "wof:placetype":"venue"
},
  "geometry": {"coordinates":[-112.358148,43.193078],"type":"Point"}
}