{
  "type": "Feature",
  "properties": {
    "addr:full":"204 E Superior St Sandpoint ID 83864",
    "addr:housenumber":"204",
    "addr:postcode":"83864",
    "addr:street":"E Superior St",
    "iso:country":"US",
    "sg:address":"204 E Superior St",
    "sg:city":"Sandpoint",
    "sg:classifiers":[
        {
            "category":"Health Services",
            "subcategory":"Medical Lab",
            "type":"Services"
        }
    ],
    "sg:phone":"+1 208 255 5577",
    "sg:postcode":"83864",
    "sg:province":"ID",
    "wof:name":"Sandpoint Denture Clinic",
    "wof:placetype":"venue"
},
  "geometry": {"coordinates":[-116.54761999999999,48.270761],"type":"Point"}
}