{
  "type": "Feature",
  "properties": {
    "addr:full":"1704 N 12th St Boise ID 83702",
    "addr:housenumber":"1704",
    "addr:postcode":"83702",
    "addr:street":"N 12Th St",
    "iso:country":"US",
    "sg:address":"1704 N 12th St",
    "sg:city":"Boise",
    "sg:classifiers":[
        {
            "category":"Professional",
            "subcategory":"Management & Consulting",
            "type":"Services"
        }
    ],
    "sg:phone":"+1 208 343 1022",
    "sg:postcode":"83702",
    "sg:province":"ID",
    "wof:name":"Waterworks Consulting Inc",
    "wof:placetype":"venue"
},
  "geometry": {"coordinates":[-116.202129,43.631927],"type":"Point"}
}