{
  "type": "Feature",
  "properties": {
    "iso:country":"US",
    "sg:address":"250 Beechwood Dr",
    "sg:city":"Boise",
    "sg:classifiers":[
        {
            "category":"Real Estate",
            "subcategory":"Developer",
            "type":"Services"
        }
    ],
    "sg:phone":"+1 208 375 6666",
    "sg:postcode":"83709",
    "sg:province":"ID",
    "wof:name":"Dennis M Baker & Assoc",
    "wof:placetype":"venue"
},
  "geometry": {"coordinates":[-116.272413,43.604114],"type":"Point"}
}