{
  "type": "Feature",
  "properties": {
    "iso:country":"US",
    "sg:address":"6745 N 5600 E",
    "sg:city":"Preston",
    "sg:phone":"+1 208 852 2141",
    "sg:postcode":"83263",
    "sg:province":"ID",
    "sg:tags":[
        "farm",
        "field",
        "crop"
    ],
    "wof:name":"Jim Call",
    "wof:placetype":"venue"
},
  "geometry": {"coordinates":[-111.74876399999999,42.220769],"type":"Point"}
}