{
  "type": "Feature",
  "properties": {
    "iso:country":"US",
    "sg:address":"387 Heyburn Ave W",
    "sg:city":"Twin Falls",
    "sg:classifiers":[
        {
            "category":"Real Estate",
            "subcategory":"Real Estate Agent",
            "type":"Services"
        }
    ],
    "sg:phone":"+1 208 733 1406",
    "sg:postcode":"83301",
    "sg:province":"ID",
    "sg:tags":[
        "appraiser"
    ],
    "wof:name":"Bauer Appraisals",
    "wof:placetype":"venue"
},
  "geometry": {"coordinates":[-114.486605,42.567188],"type":"Point"}
}