{
  "type": "Feature",
  "properties": {
    "iso:country":"US",
    "sg:address":"419 Miller St",
    "sg:city":"Lewiston",
    "sg:classifiers":[
        {
            "category":"Real Estate",
            "subcategory":"Real Estate Operator",
            "type":"Services"
        }
    ],
    "sg:phone":"+1 208 746 8137",
    "sg:postcode":"83501",
    "sg:province":"ID",
    "sg:tags":[
        "apartment"
    ],
    "wof:name":"Millcreek Apartments",
    "wof:placetype":"venue"
},
  "geometry": {"coordinates":[-117.017304,46.415277],"type":"Point"}
}