{
  "type": "Feature",
  "properties": {
    "addr:full":"508 S 5th St Boise ID 83702",
    "addr:housenumber":"508",
    "addr:postcode":"83702",
    "addr:street":"S 5Th St",
    "iso:country":"US",
    "sg:address":"508 S 5th St",
    "sg:city":"Boise",
    "sg:classifiers":[
        {
            "category":"Personal",
            "subcategory":"Beauty Salon",
            "type":"Services"
        }
    ],
    "sg:phone":"+1 208 336 8200",
    "sg:postcode":"83702",
    "sg:province":"ID",
    "sg:website":"http://www.hairartbymaria.vpweb.com/",
    "wof:name":"Olivers",
    "wof:placetype":"venue"
},
  "geometry": {"coordinates":[-116.202878,43.610708],"type":"Point"}
}