{
  "type": "Feature",
  "properties": {
    "addr:full":"128 5th St Wilder ID 83676",
    "addr:housenumber":"128",
    "addr:postcode":"83676",
    "addr:street":"5Th St",
    "iso:country":"US",
    "sg:address":"128 5th St",
    "sg:city":"Wilder",
    "sg:classifiers":[
        {
            "category":"Food & Beverages",
            "subcategory":"Groceries & Convenience Stores",
            "type":"Retail Goods"
        }
    ],
    "sg:phone":"+1 208 482 6299",
    "sg:postcode":"83676",
    "sg:province":"ID",
    "sg:tags":[
        "grocer"
    ],
    "wof:name":"Jackson's Food",
    "wof:placetype":"venue"
},
  "geometry": {"coordinates":[-116.9119,43.672866],"type":"Point"}
}