{
  "type": "Feature",
  "properties": {
    "iso:country":"US",
    "sg:address":"514 S 4th Ave",
    "sg:city":"Sandpoint",
    "sg:classifiers":[
        {
            "category":"Building & Trades",
            "subcategory":"Construction",
            "type":"Services"
        }
    ],
    "sg:phone":"+1 208 263 5485",
    "sg:postcode":"83864",
    "sg:province":"ID",
    "sg:tags":[
        "concrete",
        "contractor"
    ],
    "wof:name":"Pucci & Sons Concrete",
    "wof:placetype":"venue"
},
  "geometry": {"coordinates":[-116.55145400000001,48.267397],"type":"Point"}
}