{
  "type": "Feature",
  "properties": {
    "iso:country":"US",
    "sg:address":"2021 Cleveland Blvd",
    "sg:city":"Caldwell",
    "sg:classifiers":[
        {
            "category":"Professional",
            "subcategory":"Lawyer & Legal Services",
            "type":"Services"
        }
    ],
    "sg:phone":"+1 208 459 9690",
    "sg:postcode":"83605",
    "sg:province":"ID",
    "sg:tags":[
        "attorney",
        "practice"
    ],
    "wof:name":"Bublitz Law PC",
    "wof:placetype":"venue"
},
  "geometry": {"coordinates":[-116.677008,43.655584],"type":"Point"}
}