{
  "type": "Feature",
  "properties": {
    "iso:country":"US",
    "sg:address":"773 Bear Rd",
    "sg:city":"Priest River",
    "sg:classifiers":[
        {
            "category":"Building & Trades",
            "subcategory":"Construction",
            "type":"Services"
        }
    ],
    "sg:phone":"+1 208 265 5157",
    "sg:postcode":"83856",
    "sg:province":"ID",
    "sg:tags":[
        "house"
    ],
    "wof:name":"Western Construction",
    "wof:placetype":"venue"
},
  "geometry": {"coordinates":[-116.92137200000001,48.271326],"type":"Point"}
}