{
  "type": "Feature",
  "properties": {
    "addr:full":"360 W State St Eagle ID 83616",
    "addr:housenumber":"360",
    "addr:postcode":"83616",
    "addr:street":"W State St",
    "iso:country":"US",
    "sg:address":"360 W State St",
    "sg:city":"Eagle",
    "sg:classifiers":[
        {
            "category":"Social Services",
            "subcategory":"Adult Care",
            "type":"Services"
        }
    ],
    "sg:phone":"+1 208 395 1750",
    "sg:postcode":"83616",
    "sg:province":"ID",
    "sg:tags":[
        "home",
        "residential"
    ],
    "wof:name":"Emmeritus Corp",
    "wof:placetype":"venue"
},
  "geometry": {"coordinates":[-116.357575,43.695204],"type":"Point"}
}