{
  "type": "Feature",
  "properties": {
    "iso:country":"US",
    "sg:address":"21500 Middleton Rd",
    "sg:city":"Caldwell",
    "sg:classifiers":[
        {
            "category":"Building & Trades",
            "subcategory":"Construction",
            "type":"Services"
        }
    ],
    "sg:phone":"+1 208 459 3420",
    "sg:postcode":"83605",
    "sg:province":"ID",
    "sg:tags":[
        "excavating",
        "contractor"
    ],
    "wof:name":"King Excavation",
    "wof:placetype":"venue"
},
  "geometry": {"coordinates":[-116.613186,43.681608],"type":"Point"}
}