{
  "type": "Feature",
  "properties": {
    "addr:full":"1004 Gooby Rd Sandpoint ID 83864",
    "addr:housenumber":"1004",
    "addr:postcode":"83864",
    "addr:street":"Gooby Rd",
    "iso:country":"US",
    "sg:address":"1004 Gooby Rd",
    "sg:city":"Sandpoint",
    "sg:classifiers":[
        {
            "category":"Professional",
            "subcategory":"Business Services",
            "type":"Services"
        }
    ],
    "sg:phone":"+1 208 255 7016",
    "sg:postcode":"83864",
    "sg:province":"ID",
    "wof:name":"Smith Construction",
    "wof:placetype":"venue"
},
  "geometry": {"coordinates":[-116.59613899999999,48.294717],"type":"Point"}
}