{
  "type": "Feature",
  "properties": {
    "iso:country":"US",
    "sg:address":"200 W Hanley Ave",
    "sg:city":"Coeur D Alene",
    "sg:classifiers":[
        {
            "category":"Shopping",
            "subcategory":"Gifts & Souvenirs",
            "type":"Retail Goods"
        }
    ],
    "sg:phone":"+1 208 762 7617",
    "sg:postcode":"83815",
    "sg:province":"ID",
    "sg:tags":[
        "shop"
    ],
    "wof:name":"Legends Eight",
    "wof:placetype":"venue"
},
  "geometry": {"coordinates":[-116.788417,47.729844],"type":"Point"}
}