{
  "type": "Feature",
  "properties": {
    "addr:full":"13579 N Marble Dr Pocatello ID 83202",
    "addr:housenumber":"13579",
    "addr:postcode":"83202",
    "addr:street":"N Marble Dr",
    "iso:country":"US",
    "sg:address":"13579 N Marble Dr",
    "sg:city":"Pocatello",
    "sg:classifiers":[
        {
            "category":"Building & Trades",
            "subcategory":"Construction",
            "type":"Services"
        }
    ],
    "sg:phone":"+1 208 237 5766",
    "sg:postcode":"83202",
    "sg:province":"ID",
    "sg:tags":[
        "house"
    ],
    "wof:name":"Woodland Homes",
    "wof:placetype":"venue"
},
  "geometry": {"coordinates":[-112.443016,42.95953],"type":"Point"}
}