{
  "type": "Feature",
  "properties": {
    "iso:country":"US",
    "sg:address":"502 4th Ave W",
    "sg:city":"Twin Falls",
    "sg:classifiers":[
        {
            "category":"Home & Garden",
            "subcategory":"Hardware",
            "type":"Retail Goods"
        }
    ],
    "sg:phone":"+1 208 734 8336",
    "sg:postcode":"83301",
    "sg:province":"ID",
    "sg:website":"www.aaascreen.com",
    "wof:name":"AAA Screen Window & Door",
    "wof:placetype":"venue"
},
  "geometry": {"coordinates":[-114.478829,42.558275],"type":"Point"}
}