{
  "type": "Feature",
  "properties": {
    "iso:country":"US",
    "sg:address":"547 N 4th Ave",
    "sg:city":"Pocatello",
    "sg:classifiers":[
        {
            "category":"Autos & Motor Vehicles",
            "subcategory":"Automobile Sales",
            "type":"Retail Goods"
        }
    ],
    "sg:phone":"+1 208 478 8100",
    "sg:postcode":"83201",
    "sg:province":"ID",
    "sg:tags":[
        "car",
        "dealer"
    ],
    "wof:name":"Creekside Auto",
    "wof:placetype":"venue"
},
  "geometry": {"coordinates":[-112.448654,42.869274],"type":"Point"}
}