{
  "type": "Feature",
  "properties": {
    "iso:country":"US",
    "sg:address":"128 W Mission Ave",
    "sg:city":"Kellogg",
    "sg:classifiers":[
        {
            "category":"Shopping",
            "type":"Retail Goods"
        }
    ],
    "sg:phone":"+1 208 786 4202",
    "sg:postcode":"83837",
    "sg:province":"ID",
    "sg:tags":[
        "picture",
        "frame"
    ],
    "wof:name":"Beth's Framing Shop & Gallery",
    "wof:placetype":"venue"
},
  "geometry": {"coordinates":[-116.11953,47.54176],"type":"Point"}
}