{
  "type": "Feature",
  "properties": {
    "iso:country":"US",
    "sg:address":"250 N 5th Ave",
    "sg:city":"Pocatello",
    "sg:classifiers":[
        {
            "category":"Professional",
            "subcategory":"Accounting & Tax Preparation",
            "type":"Services"
        }
    ],
    "sg:phone":"+1 208 478 9789",
    "sg:postcode":"83201",
    "sg:province":"ID",
    "sg:tags":[
        "accountant"
    ],
    "wof:name":"Padgett Business Svc",
    "wof:placetype":"venue"
},
  "geometry": {"coordinates":[-112.444903,42.867725],"type":"Point"}
}