{
  "type": "Feature",
  "properties": {
    "iso:country":"US",
    "sg:address":"1428 W Hill Rd",
    "sg:city":"Boise",
    "sg:classifiers":[
        {
            "category":"Home & Garden",
            "subcategory":"Carpets & Floor Coverings",
            "type":"Retail Goods"
        }
    ],
    "sg:phone":"+1 208 344 3163",
    "sg:postcode":"83702",
    "sg:province":"ID",
    "sg:tags":[
        "firm",
        "design",
        "interior",
        "mi",
        "furniture"
    ],
    "wof:name":"Lucille Taylor Interiors",
    "wof:placetype":"venue"
},
  "geometry": {"coordinates":[-116.205816,43.639038],"type":"Point"}
}