{
  "type": "Feature",
  "properties": {
    "addr:full":"755 N 600 E Firth ID 83236",
    "addr:housenumber":"755",
    "addr:postcode":"83236",
    "addr:street":"N 600 E",
    "iso:country":"US",
    "sg:address":"755 N 600 E",
    "sg:city":"Firth",
    "sg:classifiers":[
        {
            "category":"Building & Trades",
            "subcategory":"Construction",
            "type":"Services"
        }
    ],
    "sg:phone":"+1 208 346 6694",
    "sg:postcode":"83236",
    "sg:province":"ID",
    "sg:tags":[
        "laying",
        "carpet"
    ],
    "wof:name":"Lane Smith",
    "wof:placetype":"venue"
},
  "geometry": {"coordinates":[-112.17833899999999,43.304292],"type":"Point"}
}