{
  "type": "Feature",
  "properties": {
    "addr:full":"700 S Lincoln Ave Jerome ID 83338",
    "addr:housenumber":"700",
    "addr:postcode":"83338",
    "addr:street":"S Lincoln Ave",
    "iso:country":"US",
    "sg:address":"700 S Lincoln Ave",
    "sg:city":"Jerome",
    "sg:classifiers":[
        {
            "category":"Real Estate",
            "subcategory":"Real Estate Agent",
            "type":"Services"
        }
    ],
    "sg:phone":"+1 208 324 3354",
    "sg:postcode":"83338",
    "sg:province":"ID",
    "sg:website":"www.canyonsiderealty.com",
    "wof:name":"Canyonside Realty Inc",
    "wof:placetype":"venue"
},
  "geometry": {"coordinates":[-114.518428,42.717839],"type":"Point"}
}