{
  "type": "Feature",
  "properties": {
    "addr:full":"3838 E Menan Lorenzo Hwy Rigby ID 83442",
    "addr:housenumber":"3838",
    "addr:postcode":"83442",
    "addr:street":"E Menan Lorenzo Hwy",
    "iso:country":"US",
    "sg:address":"3838 E Menan Lorenzo Hwy",
    "sg:city":"Rigby",
    "sg:classifiers":[
        {
            "category":"Personal",
            "subcategory":"Beauty Salon",
            "type":"Services"
        }
    ],
    "sg:phone":"+1 208 745 6553",
    "sg:postcode":"83442",
    "sg:province":"ID",
    "sg:tags":[
        "shop"
    ],
    "wof:name":"Clarenes Little Beauty Shop",
    "wof:placetype":"venue"
},
  "geometry": {"coordinates":[-111.93597,43.728109],"type":"Point"}
}