{
  "type": "Feature",
  "properties": {
    "iso:country":"US",
    "sg:address":"2318 Addison Ave E",
    "sg:city":"Twin Falls",
    "sg:classifiers":[
        {
            "category":"Food & Beverages",
            "subcategory":"Groceries & Convenience Stores",
            "type":"Retail Goods"
        }
    ],
    "sg:phone":"+1 208 734 0293",
    "sg:postcode":"83301",
    "sg:province":"ID",
    "sg:tags":[
        "grocer"
    ],
    "wof:name":"Grocery Outlet",
    "wof:placetype":"venue"
},
  "geometry": {"coordinates":[-114.43735,42.562962],"type":"Point"}
}