{
  "type": "Feature",
  "properties": {
    "iso:country":"US",
    "sg:address":"1480 E Lincoln Rd",
    "sg:city":"Idaho Falls",
    "sg:classifiers":[
        {
            "category":"Utilities",
            "subcategory":"Cable",
            "type":"Services"
        }
    ],
    "sg:phone":"+1 208 523 4567",
    "sg:postcode":"83401",
    "sg:province":"ID",
    "sg:tags":[
        "television"
    ],
    "wof:name":"Cable One Inc",
    "wof:placetype":"venue"
},
  "geometry": {"coordinates":[-112.00251299999999,43.511132],"type":"Point"}
}