{
  "type": "Feature",
  "properties": {
    "iso:country":"US",
    "sg:address":"204 S Main St",
    "sg:city":"Moscow",
    "sg:classifiers":[
        {
            "category":"Real Estate",
            "subcategory":"Real Estate Agent",
            "type":"Services"
        }
    ],
    "sg:phone":"+1 208 882 9500",
    "sg:postcode":"83843",
    "sg:province":"ID",
    "sg:website":"www.moscowrealestate.com",
    "wof:name":"Bennett & Assoc Real Estate",
    "wof:placetype":"venue"
},
  "geometry": {"coordinates":[-117.001278,46.732369],"type":"Point"}
}