{
  "type": "Feature",
  "properties": {
    "iso:country":"US",
    "sg:address":"1333 S Pioneer Rd",
    "sg:city":"Idaho Falls",
    "sg:classifiers":[
        {
            "category":"Freight",
            "type":"Transportation"
        }
    ],
    "sg:phone":"+1 208 523 7867",
    "sg:postcode":"83402",
    "sg:province":"ID",
    "sg:tags":[
        "commercial",
        "storage"
    ],
    "wof:name":"Access Controlled Storage",
    "wof:placetype":"venue"
},
  "geometry": {"coordinates":[-112.063278,43.484066],"type":"Point"}
}