{
  "type": "Feature",
  "properties": {
    "addr:full":"581 E Provident Dr Boise ID 83706",
    "addr:housenumber":"581",
    "addr:postcode":"83706",
    "addr:street":"E Provident Dr",
    "iso:country":"US",
    "sg:address":"581 E Provident Dr",
    "sg:city":"Boise",
    "sg:classifiers":[
        {
            "category":"Professional",
            "subcategory":"Management & Consulting",
            "type":"Services"
        }
    ],
    "sg:phone":"+1 208 343 7021",
    "sg:postcode":"83706",
    "sg:province":"ID",
    "sg:tags":[
        "business"
    ],
    "wof:name":"Kyes Consulting",
    "wof:placetype":"venue"
},
  "geometry": {"coordinates":[-116.17800800000001,43.587134],"type":"Point"}
}