{
  "type": "Feature",
  "properties": {
    "addr:full":"24010 Notus Rd Caldwell ID 83607",
    "addr:postcode":"24010;83607",
    "addr:street":"Notus Rd",
    "iso:country":"US",
    "sg:address":"24010 Notus Rd",
    "sg:city":"Caldwell",
    "sg:classifiers":[
        {
            "category":"Freight",
            "type":"Transportation"
        }
    ],
    "sg:phone":"+1 208 454 8239",
    "sg:postcode":"83607",
    "sg:province":"ID",
    "sg:tags":[
        "livestock",
        "hauling"
    ],
    "wof:name":"Cheney Transportation",
    "wof:placetype":"venue"
},
  "geometry": {"coordinates":[-116.797825,43.720192],"type":"Point"}
}