{
  "type": "Feature",
  "properties": {
    "iso:country":"US",
    "sg:address":"5027 Yellowstone Ave",
    "sg:city":"Pocatello",
    "sg:classifiers":[
        {
            "category":"Home & Garden",
            "subcategory":"Building Materials",
            "type":"Retail Goods"
        }
    ],
    "sg:phone":"+1 208 237 6544",
    "sg:postcode":"83202",
    "sg:province":"ID",
    "sg:tags":[
        "glass",
        "leaded"
    ],
    "wof:name":"Yellowstone Stained Glass",
    "wof:placetype":"venue"
},
  "geometry": {"coordinates":[-112.466495,42.925797],"type":"Point"}
}