{
  "type": "Feature",
  "properties": {
    "addr:full":"906 Broadway St Pocatello ID 83204",
    "addr:housenumber":"906",
    "addr:postcode":"83204",
    "addr:street":"Broadway St",
    "iso:country":"US",
    "sg:address":"906 Broadway St",
    "sg:city":"Pocatello",
    "sg:classifiers":[
        {
            "category":"Professional",
            "subcategory":"Business Services",
            "type":"Services"
        }
    ],
    "sg:phone":"+1 208 234 2901",
    "sg:postcode":"83204",
    "sg:province":"ID",
    "wof:name":"Donald Fodor",
    "wof:placetype":"venue"
},
  "geometry": {"coordinates":[-112.400864,42.834797],"type":"Point"}
}