{
  "type": "Feature",
  "properties": {
    "iso:country":"US",
    "sg:address":"4333 E 300 N",
    "sg:city":"Rigby",
    "sg:classifiers":[
        {
            "category":"Building & Trades",
            "subcategory":"Construction",
            "type":"Services"
        }
    ],
    "sg:phone":"+1 208 745 7764",
    "sg:postcode":"83442",
    "sg:province":"ID",
    "sg:tags":[
        "excavation",
        "contractor"
    ],
    "wof:name":"Clark Larry L Excavation",
    "wof:placetype":"venue"
},
  "geometry": {"coordinates":[-111.838407,43.670314],"type":"Point"}
}