{
  "type": "Feature",
  "properties": {
    "addr:full":"736 2nd Ave N Twin Falls ID 83301",
    "addr:housenumber":"736",
    "addr:postcode":"83301",
    "addr:street":"2Nd Ave N",
    "iso:country":"US",
    "sg:address":"736 2nd Ave N",
    "sg:city":"Twin Falls",
    "sg:classifiers":[
        {
            "category":"Shopping",
            "type":"Retail Goods"
        }
    ],
    "sg:phone":"+1 208 734 3444",
    "sg:postcode":"83301",
    "sg:province":"ID",
    "sg:tags":[
        "candle"
    ],
    "wof:name":"All About Brides",
    "wof:placetype":"venue"
},
  "geometry": {"coordinates":[-114.477282,42.562472],"type":"Point"}
}