{
  "type": "Feature",
  "properties": {
    "iso:country":"US",
    "sg:address":"10237 Walker St",
    "sg:city":"Hayden",
    "sg:classifiers":[
        {
            "category":"Building & Trades",
            "subcategory":"Construction",
            "type":"Services"
        }
    ],
    "sg:phone":"+1 208 762 0294",
    "sg:postcode":"83835",
    "sg:province":"ID",
    "sg:tags":[
        "carpentry",
        "contractor"
    ],
    "wof:name":"A Cut Above",
    "wof:placetype":"venue"
},
  "geometry": {"coordinates":[-116.774576,47.765949],"type":"Point"}
}