{
  "type": "Feature",
  "properties": {
    "addr:full":"9179 W State St Boise ID 83714",
    "addr:housenumber":"9179",
    "addr:postcode":"83714",
    "addr:street":"W State St",
    "iso:country":"US",
    "sg:address":"9179 W State St",
    "sg:city":"Boise",
    "sg:classifiers":[
        {
            "category":"Real Estate",
            "subcategory":"Architect",
            "type":"Services"
        }
    ],
    "sg:phone":"+1 208 853 0911",
    "sg:postcode":"83714",
    "sg:province":"ID",
    "wof:name":"Teal Architects",
    "wof:placetype":"venue"
},
  "geometry": {"coordinates":[-116.298863,43.677263],"type":"Point"}
}