{
  "type": "Feature",
  "properties": {
    "addr:full":"800 E Citation Ct Boise ID 83716",
    "addr:housenumber":"800",
    "addr:postcode":"83716",
    "addr:street":"E Citation Ct",
    "iso:country":"US",
    "sg:address":"800 E Citation Ct",
    "sg:city":"Boise",
    "sg:classifiers":[
        {
            "category":"Manufacturing",
            "subcategory":"Tools & Machinery",
            "type":"Manufacturing & Wholesale Goods"
        }
    ],
    "sg:phone":"+1 208 331 0505",
    "sg:postcode":"83716",
    "sg:province":"ID",
    "sg:tags":[
        "analytical",
        "instrument",
        "mfg"
    ],
    "wof:name":"Particle Measuring Systems",
    "wof:placetype":"venue"
},
  "geometry": {"coordinates":[-116.171161,43.54483],"type":"Point"}
}