{
  "type": "Feature",
  "properties": {
    "iso:country":"US",
    "sg:address":"11152 W State St",
    "sg:city":"Star",
    "sg:classifiers":[
        {
            "category":"Professional",
            "subcategory":"Accounting & Tax Preparation",
            "type":"Services"
        }
    ],
    "sg:phone":"+1 208 286 9914",
    "sg:postcode":"83669",
    "sg:province":"ID",
    "sg:tags":[
        "bookkeeping",
        "general"
    ],
    "wof:name":"Accounting & Tax Svc LLC",
    "wof:placetype":"venue"
},
  "geometry": {"coordinates":[-116.492621,43.69208],"type":"Point"}
}