{
  "type": "Feature",
  "properties": {
    "iso:country":"US",
    "sg:address":"6473 Madison St",
    "sg:city":"Bonners Ferry",
    "sg:classifiers":[
        {
            "category":"Retail",
            "subcategory":"Repair Shop",
            "type":"Services"
        }
    ],
    "sg:phone":"+1 208 267 5541",
    "sg:postcode":"83805",
    "sg:province":"ID",
    "sg:tags":[
        "electrical"
    ],
    "wof:name":"Kootenai Country Inc",
    "wof:placetype":"venue"
},
  "geometry": {"coordinates":[-116.31350399999999,48.691484],"type":"Point"}
}