{
  "type": "Feature",
  "properties": {
    "addr:full":"1121 21st St Lewiston ID 83501",
    "addr:housenumber":"1121",
    "addr:postcode":"83501",
    "addr:street":"21St St",
    "iso:country":"US",
    "sg:address":"1121 21st St",
    "sg:city":"Lewiston",
    "sg:classifiers":[
        {
            "category":"Cinema",
            "subcategory":"Movie Rental",
            "type":"Entertainment"
        }
    ],
    "sg:phone":"+1 208 798 8267",
    "sg:postcode":"83501",
    "sg:province":"ID",
    "sg:tags":[
        "leasing",
        "video",
        "disc",
        "tape"
    ],
    "wof:name":"Blockbuster Video",
    "wof:placetype":"venue"
},
  "geometry": {"coordinates":[-117.00187,46.409124],"type":"Point"}
}