{
  "type": "Feature",
  "properties": {
    "iso:country":"US",
    "sg:address":"635 Brent St",
    "sg:city":"Pocatello",
    "sg:classifiers":[
        {
            "category":"Real Estate",
            "subcategory":"Real Estate Agent",
            "type":"Services"
        }
    ],
    "sg:phone":"+1 208 637 2078",
    "sg:postcode":"83201",
    "sg:province":"ID",
    "wof:name":"Pepperidge Management Company",
    "wof:placetype":"venue"
},
  "geometry": {"coordinates":[-112.421836,42.919153],"type":"Point"}
}