{
  "type": "Feature",
  "properties": {
    "iso:country":"US",
    "sg:address":"4501 S Federal Way",
    "sg:city":"Boise",
    "sg:classifiers":[
        {
            "category":"Home & Garden",
            "subcategory":"Furniture",
            "type":"Retail Goods"
        }
    ],
    "sg:phone":"+1 208 368 7878",
    "sg:postcode":"83716",
    "sg:province":"ID",
    "sg:tags":[
        "cabinet"
    ],
    "wof:name":"Creative Woods Inc-Canac",
    "wof:placetype":"venue"
},
  "geometry": {"coordinates":[-116.17161400000001,43.562757],"type":"Point"}
}