{
  "type": "Feature",
  "properties": {
    "iso:country":"US",
    "sg:address":"508 W Center St",
    "sg:city":"Pocatello",
    "sg:classifiers":[
        {
            "category":"Retail",
            "subcategory":"Auto Repair",
            "type":"Services"
        }
    ],
    "sg:phone":"+1 208 478 1375",
    "sg:postcode":"83204",
    "sg:province":"ID",
    "sg:tags":[
        "repairing",
        "automobile"
    ],
    "wof:name":"Custom Auto Repair",
    "wof:placetype":"venue"
},
  "geometry": {"coordinates":[-112.45324599999999,42.860543],"type":"Point"}
}