{
  "type": "Feature",
  "properties": {
    "addr:full":"339 State St Weiser ID 83672",
    "addr:housenumber":"339",
    "addr:postcode":"83672",
    "addr:street":"State St",
    "iso:country":"US",
    "sg:address":"339 State St",
    "sg:city":"Weiser",
    "sg:classifiers":[
        {
            "category":"Personal",
            "subcategory":"Beauty Salon",
            "type":"Services"
        }
    ],
    "sg:phone":"+1 208 549 4800",
    "sg:postcode":"83672",
    "sg:province":"ID",
    "wof:name":"American Beauty",
    "wof:placetype":"venue"
},
  "geometry": {"coordinates":[-116.970522,44.245229],"type":"Point"}
}