{
  "type": "Feature",
  "properties": {
    "addr:full":"148 N 2nd St Eagle ID 83616",
    "addr:housenumber":"148",
    "addr:postcode":"83616",
    "addr:street":"N 2Nd St",
    "iso:country":"US",
    "sg:address":"148 N 2nd St",
    "sg:city":"Eagle",
    "sg:classifiers":[
        {
            "category":"Social Services",
            "subcategory":"Child Care",
            "type":"Services"
        }
    ],
    "sg:phone":"+1 208 939 1145",
    "sg:postcode":"83616",
    "sg:province":"ID",
    "sg:tags":[
        "kindergarten",
        "academic",
        "school"
    ],
    "wof:name":"Idaho Children's Academy",
    "wof:placetype":"venue"
},
  "geometry": {"coordinates":[-116.35118300000001,43.695993],"type":"Point"}
}