{
  "type": "Feature",
  "properties": {
    "iso:country":"US",
    "sg:address":"875 Jones Dr",
    "sg:city":"Pocatello",
    "sg:classifiers":[
        {
            "category":"Real Estate",
            "subcategory":"Real Estate Agent",
            "type":"Services"
        }
    ],
    "sg:phone":"+1 208 237 8945",
    "sg:postcode":"83201",
    "sg:province":"ID",
    "sg:tags":[
        "agency",
        "rental"
    ],
    "wof:name":"Thiemann Rentals",
    "wof:placetype":"venue"
},
  "geometry": {"coordinates":[-112.4697,42.892497],"type":"Point"}
}