{
  "type": "Feature",
  "properties": {
    "iso:country":"US",
    "sg:address":"720 W Idaho St",
    "sg:city":"Boise",
    "sg:classifiers":[
        {
            "category":"Professional",
            "subcategory":"Management & Consulting",
            "type":"Services"
        }
    ],
    "sg:phone":"+1 208 342 7342",
    "sg:postcode":"83702",
    "sg:province":"ID",
    "wof:name":"Management North West",
    "wof:placetype":"venue"
},
  "geometry": {"coordinates":[-116.202527,43.616332],"type":"Point"}
}