{
  "type": "Feature",
  "properties": {
    "addr:full":"676 Shoup Ave W Twin Falls ID 83301",
    "addr:housenumber":"676",
    "addr:postcode":"83301",
    "addr:street":"Shoup Ave W",
    "iso:country":"US",
    "sg:address":"676 Shoup Ave W",
    "sg:city":"Twin Falls",
    "sg:classifiers":[
        {
            "category":"Government",
            "subcategory":"Office",
            "type":"Public Place"
        }
    ],
    "sg:phone":"+1 208 732 0947",
    "sg:postcode":"83301",
    "sg:province":"ID",
    "sg:tags":[
        "federal",
        "affairs",
        "govt",
        "admin"
    ],
    "wof:name":"Us Veterans Affairs Dept",
    "wof:placetype":"venue"
},
  "geometry": {"coordinates":[-114.49413,42.565912],"type":"Point"}
}