{
  "type": "Feature",
  "properties": {
    "iso:country":"US",
    "sg:address":"11567 Lake Shore Dr",
    "sg:city":"Nampa",
    "sg:classifiers":[
        {
            "category":"Building & Trades",
            "subcategory":"Construction",
            "type":"Services"
        }
    ],
    "sg:phone":"+1 208 323 7275",
    "sg:postcode":"83686",
    "sg:province":"ID",
    "sg:tags":[
        "boring",
        "drilling",
        "contractor"
    ],
    "wof:name":"Accurbore Inc",
    "wof:placetype":"venue"
},
  "geometry": {"coordinates":[-116.61959899999999,43.517471],"type":"Point"}
}