{
  "type": "Feature",
  "properties": {
    "iso:country":"US",
    "sg:address":"119 N Commercial Ave",
    "sg:city":"Emmett",
    "sg:classifiers":[
        {
            "category":"Railroad",
            "type":"Transportation"
        }
    ],
    "sg:phone":"+1 208 365 6353",
    "sg:postcode":"83617",
    "sg:province":"ID",
    "sg:website":"www.rgpc.com",
    "wof:name":"Idaho Northern & Pacific Rr",
    "wof:placetype":"venue"
},
  "geometry": {"coordinates":[-116.501474,43.876029],"type":"Point"}
}