{
  "type": "Feature",
  "properties": {
    "addr:full":"2030 US Hwy 30 Fruitland ID 83619",
    "addr:housenumber":"2030",
    "addr:postcode":"83619",
    "addr:street":"Us Hwy 30",
    "iso:country":"US",
    "sg:address":"2030 US Hwy 30",
    "sg:city":"Fruitland",
    "sg:classifiers":[
        {
            "category":"Professional",
            "type":"Services"
        }
    ],
    "sg:phone":"+1 208 452 6585",
    "sg:postcode":"83619",
    "sg:province":"ID",
    "sg:tags":[
        "establishment"
    ],
    "wof:name":"Rocky Mountain Restoration",
    "wof:placetype":"venue"
},
  "geometry": {"coordinates":[-116.900509,43.974613],"type":"Point"}
}