{
  "type": "Feature",
  "properties": {
    "iso:country":"US",
    "sg:address":"872 Fairway Dr",
    "sg:city":"Twin Falls",
    "sg:classifiers":[
        {
            "category":"Retail",
            "subcategory":"Laundry & Dry Cleaning",
            "type":"Services"
        }
    ],
    "sg:phone":"+1 208 733 3914",
    "sg:postcode":"83301",
    "sg:province":"ID",
    "sg:tags":[
        "garment",
        "agent"
    ],
    "wof:name":"Tuck It Away Storage",
    "wof:placetype":"venue"
},
  "geometry": {"coordinates":[-114.46118300000001,42.571621],"type":"Point"}
}