{
  "type": "Feature",
  "properties": {
    "addr:full":"280 W Judicial St Blackfoot ID 83221",
    "addr:housenumber":"280",
    "addr:postcode":"83221",
    "addr:street":"W Judicial St",
    "iso:country":"US",
    "sg:address":"280 W Judicial St",
    "sg:city":"Blackfoot",
    "sg:classifiers":[
        {
            "category":"Banks & Credit Unions",
            "subcategory":"Bank",
            "type":"Services"
        }
    ],
    "sg:phone":"+1 208 785 6843",
    "sg:postcode":"83221",
    "sg:province":"ID",
    "sg:website":"www.bankofcommerce.org",
    "wof:name":"Bank Of Commerce",
    "wof:placetype":"venue"
},
  "geometry": {"coordinates":[-112.347976,43.189288],"type":"Point"}
}