{
  "type": "Feature",
  "properties": {
    "iso:country":"US",
    "sg:address":"150 N 8th St",
    "sg:city":"Boise",
    "sg:classifiers":[
        {
            "category":"Bars & Pubs",
            "type":"Food & Drink"
        }
    ],
    "sg:phone":"+1 208 336 1313",
    "sg:postcode":"83702",
    "sg:province":"ID",
    "sg:tags":[
        "club",
        "night"
    ],
    "wof:name":"Balcony Club",
    "wof:placetype":"venue"
},
  "geometry": {"coordinates":[-116.202955,43.615959],"type":"Point"}
}