{
  "type": "Feature",
  "properties": {
    "addr:full":"3119 Commercial Way Caldwell ID 83605",
    "addr:housenumber":"3119",
    "addr:postcode":"83605",
    "addr:street":"Commercial Way",
    "iso:country":"US",
    "sg:address":"3119 Commercial Way",
    "sg:city":"Caldwell",
    "sg:classifiers":[
        {
            "category":"Health Services",
            "subcategory":"Hospital",
            "type":"Services"
        }
    ],
    "sg:phone":"+1 208 453 2033",
    "sg:postcode":"83605",
    "sg:province":"ID",
    "sg:tags":[
        "specialty"
    ],
    "wof:name":"St Alphonsus Regional Med Ctr",
    "wof:placetype":"venue"
},
  "geometry": {"coordinates":[-116.658552,43.659275],"type":"Point"}
}