{
  "type": "Feature",
  "properties": {
    "addr:full":"866 W Hayden Ave Hayden ID 83835",
    "addr:housenumber":"866",
    "addr:postcode":"83835",
    "addr:street":"W Hayden Ave",
    "iso:country":"US",
    "sg:address":"866 W Hayden Ave",
    "sg:city":"Hayden",
    "sg:classifiers":[
        {
            "category":"Professional",
            "subcategory":"Accounting & Tax Preparation",
            "type":"Services"
        }
    ],
    "sg:phone":"+1 208 762 9737",
    "sg:postcode":"83835",
    "sg:province":"ID",
    "sg:tags":[
        "accountant"
    ],
    "wof:name":"William T Baker CPA",
    "wof:placetype":"venue"
},
  "geometry": {"coordinates":[-116.79828999999999,47.758949],"type":"Point"}
}