{
  "type": "Feature",
  "properties": {
    "addr:full":"1385 N Garden St Boise ID 83706",
    "addr:housenumber":"1385",
    "addr:postcode":"83706",
    "addr:street":"N Garden St",
    "iso:country":"US",
    "sg:address":"1385 N Garden St",
    "sg:city":"Boise",
    "sg:classifiers":[
        {
            "category":"Professional",
            "subcategory":"Business Services",
            "type":"Services"
        }
    ],
    "sg:phone":"+1 208 378 4409",
    "sg:postcode":"83706",
    "sg:province":"ID",
    "wof:name":"Uehling Design",
    "wof:placetype":"venue"
},
  "geometry": {"coordinates":[-116.238553,43.616251],"type":"Point"}
}