{
  "type": "Feature",
  "properties": {
    "addr:full":"117 S 9th Ave Caldwell ID 83605",
    "addr:housenumber":"117",
    "addr:postcode":"83605",
    "addr:street":"S 9Th Ave",
    "iso:country":"US",
    "sg:address":"117 S 9th Ave",
    "sg:city":"Caldwell",
    "sg:classifiers":[
        {
            "category":"Social Services",
            "type":"Services"
        }
    ],
    "sg:phone":"+1 208 454 3825",
    "sg:postcode":"83605",
    "sg:province":"ID",
    "sg:tags":[
        "counselor",
        "marriage",
        "family"
    ],
    "wof:name":"Carol Collins PHD",
    "wof:placetype":"venue"
},
  "geometry": {"coordinates":[-116.68615,43.665411],"type":"Point"}
}