{
  "type": "Feature",
  "properties": {
    "addr:full":"150 N Capitol Blvd Boise ID 83702",
    "addr:housenumber":"150",
    "addr:postcode":"83702",
    "addr:street":"N Capitol Blvd",
    "iso:country":"US",
    "sg:address":"150 N Capitol Blvd",
    "sg:city":"Boise",
    "sg:classifiers":[
        {
            "category":"Government",
            "subcategory":"Office",
            "type":"Public Place"
        }
    ],
    "sg:phone":"+1 208 384 3755",
    "sg:postcode":"83702",
    "sg:province":"ID",
    "sg:tags":[
        "village"
    ],
    "wof:name":"City",
    "wof:placetype":"venue"
},
  "geometry": {"coordinates":[-116.201779,43.615362],"type":"Point"}
}