{
  "type": "Feature",
  "properties": {
    "iso:country":"US",
    "sg:address":"4460 Andco Dr",
    "sg:city":"Idaho Falls",
    "sg:classifiers":[
        {
            "category":"Autos & Motor Vehicles",
            "subcategory":"Automobile Sales",
            "type":"Retail Goods"
        }
    ],
    "sg:phone":"+1 208 528 0004",
    "sg:postcode":"83402",
    "sg:province":"ID",
    "sg:tags":[
        "truck"
    ],
    "wof:name":"Idaho Falls Peterbilt",
    "wof:placetype":"venue"
},
  "geometry": {"coordinates":[-112.117654,43.439407],"type":"Point"}
}