{
  "type": "Feature",
  "properties": {
    "addr:full":"3998 Ginger Creek Dr Meridian ID 83642",
    "addr:housenumber":"3998",
    "addr:postcode":"83642",
    "addr:street":"Ginger Creek Dr",
    "iso:country":"US",
    "sg:address":"3998 Ginger Creek Dr",
    "sg:city":"Meridian",
    "sg:classifiers":[
        {
            "category":"Real Estate",
            "subcategory":"Real Estate Agent",
            "type":"Services"
        }
    ],
    "sg:phone":"+1 208 323 1576",
    "sg:postcode":"83642",
    "sg:province":"ID",
    "wof:name":"Steven & Ling Chi",
    "wof:placetype":"venue"
},
  "geometry": {"coordinates":[-116.34361,43.640486],"type":"Point"}
}