{
  "type": "Feature",
  "properties": {
    "addr:full":"413 W Jefferson St Boise ID 83702",
    "addr:housenumber":"413",
    "addr:postcode":"83702",
    "addr:street":"W Jefferson St",
    "iso:country":"US",
    "sg:address":"413 W Jefferson St",
    "sg:city":"Boise",
    "sg:classifiers":[
        {
            "category":"Professional",
            "subcategory":"Lawyer & Legal Services",
            "type":"Services"
        }
    ],
    "sg:phone":"+1 208 336 1433",
    "sg:postcode":"83702",
    "sg:province":"ID",
    "sg:tags":[
        "attorney"
    ],
    "wof:name":"Matthews Law Office",
    "wof:placetype":"venue"
},
  "geometry": {"coordinates":[-116.197686,43.615996],"type":"Point"}
}