{
  "type": "Feature",
  "properties": {
    "iso:country":"US",
    "sg:address":"955 Wells St",
    "sg:city":"Meridian",
    "sg:phone":"+1 208 888 4767",
    "sg:postcode":"83642",
    "sg:province":"ID",
    "sg:tags":[
        "farm",
        "corn",
        "soybean"
    ],
    "wof:name":"Robert L Middleton",
    "wof:placetype":"venue"
},
  "geometry": {"coordinates":[-116.362442,43.596527],"type":"Point"}
}