{
  "type": "Feature",
  "properties": {
    "iso:country":"US",
    "sg:address":"7806 Desert Ave",
    "sg:city":"Boise",
    "sg:classifiers":[
        {
            "category":"Building & Trades",
            "subcategory":"Construction",
            "type":"Services"
        }
    ],
    "sg:phone":"+1 208 362 4459",
    "sg:postcode":"83709",
    "sg:province":"ID",
    "sg:tags":[
        "carpentry",
        "contractor"
    ],
    "wof:name":"Bob Cormier Woodworking",
    "wof:placetype":"venue"
},
  "geometry": {"coordinates":[-116.28158500000001,43.554026],"type":"Point"}
}