{
  "type": "Feature",
  "properties": {
    "addr:full":"450 Thain Rd Lewiston ID 83501",
    "addr:housenumber":"450",
    "addr:postcode":"83501",
    "addr:street":"Thain Rd",
    "iso:country":"US",
    "sg:address":"450 Thain Rd",
    "sg:city":"Lewiston",
    "sg:classifiers":[
        {
            "category":"Insurance",
            "subcategory":"Insurance Agent",
            "type":"Services"
        }
    ],
    "sg:phone":"+1 208 746 9771",
    "sg:postcode":"83501",
    "sg:province":"ID",
    "wof:name":"Don Solom Insurance Svc",
    "wof:placetype":"venue"
},
  "geometry": {"coordinates":[-116.972432,46.377828],"type":"Point"}
}