{
  "type": "Feature",
  "properties": {
    "addr:full":"1604 W Orchard Ave Nampa ID 83651",
    "addr:housenumber":"1604",
    "addr:postcode":"83651",
    "addr:street":"W Orchard Ave",
    "iso:country":"US",
    "sg:address":"1604 W Orchard Ave",
    "sg:city":"Nampa",
    "sg:classifiers":[
        {
            "category":"Government",
            "subcategory":"Office",
            "type":"Public Place"
        }
    ],
    "sg:phone":"+1 208 442 2558",
    "sg:postcode":"83651",
    "sg:province":"ID",
    "sg:tags":[
        "consultant"
    ],
    "wof:name":"Deanna L Combs",
    "wof:placetype":"venue"
},
  "geometry": {"coordinates":[-116.60059200000001,43.590433],"type":"Point"}
}