{
  "type": "Feature",
  "properties": {
    "addr:full":"3312 N Lakeharbor Ln Boise ID 83703",
    "addr:housenumber":"3312",
    "addr:postcode":"83703",
    "addr:street":"N Lakeharbor Ln",
    "iso:country":"US",
    "sg:address":"3312 N Lakeharbor Ln",
    "sg:city":"Boise",
    "sg:classifiers":[
        {
            "category":"Professional",
            "subcategory":"Accounting & Tax Preparation",
            "type":"Services"
        }
    ],
    "sg:phone":"+1 208 854 0846",
    "sg:postcode":"83703",
    "sg:province":"ID",
    "wof:name":"Therapist Solutions",
    "wof:placetype":"venue"
},
  "geometry": {"coordinates":[-116.250562,43.650765],"type":"Point"}
}