{
  "type": "Feature",
  "properties": {
    "iso:country":"US",
    "sg:address":"5700 E Franklin Rd",
    "sg:city":"Nampa",
    "sg:classifiers":[
        {
            "category":"Professional",
            "subcategory":"Business Services",
            "type":"Services"
        },
        {
            "category":"Travel",
            "subcategory":"Hotels & Motels",
            "type":"Entertainment"
        }
    ],
    "sg:phone":"+1 208 442 0036",
    "sg:postcode":"83687",
    "sg:province":"ID",
    "sg:tags":[
        "operation",
        "convention",
        "meeting",
        "facility"
    ],
    "wof:name":"Hampton Inn",
    "wof:placetype":"venue"
},
  "geometry": {"coordinates":[-116.508577,43.605118],"type":"Point"}
}