{
  "type": "Feature",
  "properties": {
    "addr:full":"1514 Falcon Dr Idaho Falls ID 83406",
    "addr:housenumber":"1514",
    "addr:postcode":"83406",
    "addr:street":"Falcon Dr",
    "iso:country":"US",
    "sg:address":"1514 Falcon Dr",
    "sg:city":"Idaho Falls",
    "sg:classifiers":[
        {
            "category":"Personal",
            "subcategory":"Beauty Salon",
            "type":"Services"
        }
    ],
    "sg:phone":"+1 208 552 1263",
    "sg:postcode":"83406",
    "sg:province":"ID",
    "sg:tags":[
        "shop"
    ],
    "wof:name":"Roxannas Hair Design",
    "wof:placetype":"venue"
},
  "geometry": {"coordinates":[-111.981478,43.483947],"type":"Point"}
}