{
  "type": "Feature",
  "properties": {
    "iso:country":"US",
    "sg:address":"1110 N Cole Rd",
    "sg:city":"Boise",
    "sg:classifiers":[
        {
            "category":"Health Services",
            "subcategory":"Health Practitioner",
            "type":"Services"
        }
    ],
    "sg:phone":"+1 208 336 0000",
    "sg:postcode":"83704",
    "sg:province":"ID",
    "sg:tags":[
        "acupuncture"
    ],
    "wof:name":"C C Wilcher Acupuncture",
    "wof:placetype":"venue"
},
  "geometry": {"coordinates":[-116.274105,43.616349],"type":"Point"}
}