{
  "type": "Feature",
  "properties": {
    "iso:country":"US",
    "sg:address":"215 N Main St",
    "sg:city":"Hailey",
    "sg:classifiers":[
        {
            "category":"Insurance",
            "subcategory":"Insurance Agent",
            "type":"Services"
        }
    ],
    "sg:phone":"+1 208 788 3255",
    "sg:postcode":"83333",
    "sg:province":"ID",
    "wof:name":"Harrison Insurance",
    "wof:placetype":"venue"
},
  "geometry": {"coordinates":[-114.316841,43.521378],"type":"Point"}
}