{
  "type": "Feature",
  "properties": {
    "addr:full":"1317 N Oak Creek Way Meridian ID 83642",
    "addr:housenumber":"1317",
    "addr:postcode":"83642",
    "addr:street":"N Oak Creek Way",
    "iso:country":"US",
    "sg:address":"1317 N Oak Creek Way",
    "sg:city":"Meridian",
    "sg:classifiers":[
        {
            "category":"Utilities",
            "subcategory":"Telephone",
            "type":"Services"
        }
    ],
    "sg:phone":"+1 208 884 0043",
    "sg:postcode":"83642",
    "sg:province":"ID",
    "sg:tags":[
        "host",
        "internet"
    ],
    "wof:name":"Scrapnetworkcom Inc",
    "wof:placetype":"venue"
},
  "geometry": {"coordinates":[-116.43621400000001,43.616654],"type":"Point"}
}