{
  "type": "Feature",
  "properties": {
    "iso:country":"US",
    "sg:address":"300 N 6th St",
    "sg:city":"Boise",
    "sg:classifiers":[
        {
            "category":"Professional",
            "subcategory":"Art Services",
            "type":"Services"
        }
    ],
    "sg:phone":"+1 208 336 8891",
    "sg:postcode":"83702",
    "sg:province":"ID",
    "sg:tags":[
        "graphic",
        "designer"
    ],
    "wof:name":"Blam Design LLC",
    "wof:placetype":"venue"
},
  "geometry": {"coordinates":[-116.198922,43.616727],"type":"Point"}
}