{
  "type": "Feature",
  "properties": {
    "addr:full":"2048 Hwy 93 N North Fork ID 83466",
    "addr:housenumber":"2048",
    "addr:postcode":"83466",
    "addr:street":"Hwy 93 N",
    "iso:country":"US",
    "sg:address":"2048 Hwy 93 N",
    "sg:city":"North Fork",
    "sg:classifiers":[
        {
            "category":"Government",
            "subcategory":"Post Office",
            "type":"Public Place"
        }
    ],
    "sg:phone":"+1 208 865 2556",
    "sg:postcode":"83466",
    "sg:province":"ID",
    "wof:name":"US Post Office",
    "wof:placetype":"venue"
},
  "geometry": {"coordinates":[-113.99481400000001,45.406659],"type":"Point"}
}