{
  "type": "Feature",
  "properties": {
    "iso:country":"US",
    "sg:address":"907 NW 2nd St",
    "sg:city":"Fruitland",
    "sg:classifiers":[
        {
            "category":"Retail",
            "subcategory":"Laundry & Dry Cleaning",
            "type":"Services"
        },
        {
            "category":"Building & Trades",
            "subcategory":"Cleaning & Sanitation",
            "type":"Services"
        }
    ],
    "sg:phone":"+1 208 452 6270",
    "sg:postcode":"83619",
    "sg:province":"ID",
    "sg:tags":[
        "cleaner",
        "carpet",
        "rug",
        "janitorial"
    ],
    "wof:name":"Bev & Les Quality Cleaners",
    "wof:placetype":"venue"
},
  "geometry": {"coordinates":[-116.92635,44.012473],"type":"Point"}
}