{
  "type": "Feature",
  "properties": {
    "addr:full":"10032 W State St Boise ID 83714",
    "addr:housenumber":"10032",
    "addr:postcode":"83714",
    "addr:street":"W State St",
    "iso:country":"US",
    "sg:address":"10032 W State St",
    "sg:city":"Boise",
    "sg:classifiers":[
        {
            "category":"Retail",
            "subcategory":"Repair Shop",
            "type":"Services"
        }
    ],
    "sg:phone":"+1 208 888 0338",
    "sg:postcode":"83714",
    "sg:province":"ID",
    "sg:tags":[
        "appliance"
    ],
    "wof:name":"Action Appliance",
    "wof:placetype":"venue"
},
  "geometry": {"coordinates":[-116.307596,43.6805],"type":"Point"}
}