{
  "type": "Feature",
  "properties": {
    "addr:full":"2007 Birch Ave Lewiston ID 83501",
    "addr:housenumber":"2007",
    "addr:postcode":"83501",
    "addr:street":"Birch Ave",
    "iso:country":"US",
    "sg:address":"2007 Birch Ave",
    "sg:city":"Lewiston",
    "sg:classifiers":[
        {
            "category":"Professional",
            "subcategory":"Management & Consulting",
            "type":"Services"
        }
    ],
    "sg:phone":"+1 208 746 9810",
    "sg:postcode":"83501",
    "sg:province":"ID",
    "wof:name":"United Heritage Financial Svcs",
    "wof:placetype":"venue"
},
  "geometry": {"coordinates":[-116.928038,46.367911],"type":"Point"}
}