{
  "type": "Feature",
  "properties": {
    "addr:full":"6633 S Federal Way Boise ID 83705",
    "addr:housenumber":"6633",
    "addr:postcode":"83705",
    "addr:street":"S Federal Way",
    "iso:country":"US",
    "sg:address":"6633 S Federal Way",
    "sg:city":"Boise",
    "sg:classifiers":[
        {
            "category":"Retail",
            "subcategory":"Auto Repair",
            "type":"Services"
        }
    ],
    "sg:phone":"+1 208 367 0800",
    "sg:postcode":"83705",
    "sg:province":"ID",
    "sg:tags":[
        "wrecker"
    ],
    "wof:name":"Valley View Towing",
    "wof:placetype":"venue"
},
  "geometry": {"coordinates":[-116.155649,43.542586],"type":"Point"}
}