{
  "type": "Feature",
  "properties": {
    "addr:full":"703 S Canal St Coeur D Alene ID 83814",
    "addr:housenumber":"703",
    "addr:postcode":"83814",
    "addr:street":"S Canal St Coeur D",
    "iso:country":"US",
    "sg:address":"703 S Canal St",
    "sg:city":"Coeur D Alene",
    "sg:classifiers":[
        {
            "category":"Professional",
            "type":"Services"
        }
    ],
    "sg:phone":"+1 208 765 0331",
    "sg:postcode":"83814",
    "sg:province":"ID",
    "wof:name":"Pn Inc",
    "wof:placetype":"venue"
},
  "geometry": {"coordinates":[-116.808021,47.688048],"type":"Point"}
}