{
  "type": "Feature",
  "properties": {
    "iso:country":"US",
    "sg:address":"462 N University Ave",
    "sg:city":"Blackfoot",
    "sg:classifiers":[
        {
            "category":"Organizations",
            "subcategory":"Religious Organization",
            "type":"Services"
        }
    ],
    "sg:phone":"+1 208 785 4562",
    "sg:postcode":"83221",
    "sg:province":"ID",
    "wof:name":"Spiritual Assembly of Bah",
    "wof:placetype":"venue"
},
  "geometry": {"coordinates":[-112.338365,43.189928],"type":"Point"}
}