{
  "type": "Feature",
  "properties": {
    "iso:country":"US",
    "sg:address":"1700 W Pullman Rd",
    "sg:city":"Moscow",
    "sg:classifiers":[
        {
            "category":"Food & Beverages",
            "subcategory":"Groceries & Convenience Stores",
            "type":"Retail Goods"
        }
    ],
    "sg:phone":"+1 208 883 8335",
    "sg:postcode":"83843",
    "sg:province":"ID",
    "sg:tags":[
        "grocer"
    ],
    "wof:name":"Winco Foods",
    "wof:placetype":"venue"
},
  "geometry": {"coordinates":[-117.02458799999999,46.732603],"type":"Point"}
}