{
  "type": "Feature",
  "properties": {
    "iso:country":"US",
    "sg:address":"590 Gifford Ave",
    "sg:city":"American Falls",
    "sg:classifiers":[
        {
            "category":"Health Services",
            "subcategory":"Doctor",
            "type":"Services"
        }
    ],
    "sg:phone":"+1 208 226 5147",
    "sg:postcode":"83211",
    "sg:province":"ID",
    "sg:tags":[
        "physician",
        "surgeon"
    ],
    "wof:name":"Doctors Clinic-American Falls",
    "wof:placetype":"venue"
},
  "geometry": {"coordinates":[-112.849132,42.782075],"type":"Point"}
}