{
  "type": "Feature",
  "properties": {
    "addr:full":"1234 E County Rd Pocatello ID 83204",
    "addr:housenumber":"1234",
    "addr:postcode":"83204",
    "addr:street":"E County Rd",
    "iso:country":"US",
    "sg:address":"1234 E County Rd",
    "sg:city":"Pocatello",
    "sg:classifiers":[
        {
            "category":"Professional",
            "subcategory":"Research",
            "type":"Services"
        }
    ],
    "sg:phone":"+1 208 478 2471",
    "sg:postcode":"83204",
    "sg:province":"ID",
    "sg:tags":[
        "environmental",
        "ecological"
    ],
    "wof:name":"Envirocon",
    "wof:placetype":"venue"
},
  "geometry": {"coordinates":[-112.542704,42.908184],"type":"Point"}
}