{
  "type": "Feature",
  "properties": {
    "addr:full":"4500 Alma Ln Nampa ID 83686",
    "addr:housenumber":"4500",
    "addr:postcode":"83686",
    "addr:street":"Alma Ln",
    "iso:country":"US",
    "sg:address":"4500 Alma Ln",
    "sg:city":"Nampa",
    "sg:classifiers":[
        {
            "category":"Building & Trades",
            "subcategory":"Construction",
            "type":"Services"
        }
    ],
    "sg:phone":"+1 208 467 2788",
    "sg:postcode":"83686",
    "sg:province":"ID",
    "sg:tags":[
        "floor",
        "laying",
        "contractor"
    ],
    "wof:name":"Schuler Alternatives",
    "wof:placetype":"venue"
},
  "geometry": {"coordinates":[-116.516172,43.524147],"type":"Point"}
}