{
  "type": "Feature",
  "properties": {
    "addr:full":"3828 E 12 N Rigby ID 83442",
    "addr:housenumber":"3828;12 n",
    "addr:postcode":"83442",
    "addr:street":"E",
    "iso:country":"US",
    "sg:address":"3828 E 12 N",
    "sg:city":"Rigby",
    "sg:classifiers":[
        {
            "category":"Professional",
            "type":"Services"
        }
    ],
    "sg:phone":"+1 208 745 7450",
    "sg:postcode":"83442",
    "sg:province":"ID",
    "wof:name":"EZ Contract Services PA Inc",
    "wof:placetype":"venue"
},
  "geometry": {"coordinates":[-111.937848,43.627802],"type":"Point"}
}