{
  "type": "Feature",
  "properties": {
    "addr:full":"306 S Kimball Ave Caldwell ID 83605",
    "addr:housenumber":"306",
    "addr:postcode":"83605",
    "addr:street":"S Kimball Ave",
    "iso:country":"US",
    "sg:address":"306 S Kimball Ave",
    "sg:city":"Caldwell",
    "sg:classifiers":[
        {
            "category":"Autos & Motor Vehicles",
            "subcategory":"Automobile Sales",
            "type":"Retail Goods"
        }
    ],
    "sg:phone":"+1 208 455 2773",
    "sg:postcode":"83605",
    "sg:province":"ID",
    "sg:tags":[
        "car",
        "dealer"
    ],
    "wof:name":"J Z Auto",
    "wof:placetype":"venue"
},
  "geometry": {"coordinates":[-116.689002,43.664958],"type":"Point"}
}