{
  "type": "Feature",
  "properties": {
    "iso:country":"US",
    "sg:address":"319 S Locust St",
    "sg:city":"Nampa",
    "sg:classifiers":[
        {
            "category":"Wholesale",
            "subcategory":"Hardware",
            "type":"Manufacturing & Wholesale Goods"
        }
    ],
    "sg:phone":"+1 208 467 7161",
    "sg:postcode":"83686",
    "sg:province":"ID",
    "sg:tags":[
        "refrigerating"
    ],
    "wof:name":"A-C Heating & Refrigeration",
    "wof:placetype":"venue"
},
  "geometry": {"coordinates":[-116.568679,43.566386],"type":"Point"}
}