{
  "type": "Feature",
  "properties": {
    "addr:full":"445 Marjacq Ave Idaho Falls ID 83401",
    "addr:housenumber":"445",
    "addr:postcode":"83401",
    "addr:street":"Marjacq Ave",
    "iso:country":"US",
    "sg:address":"445 Marjacq Ave",
    "sg:city":"Idaho Falls",
    "sg:classifiers":[
        {
            "category":"Personal",
            "type":"Services"
        }
    ],
    "sg:phone":"+1 208 528 0148",
    "sg:postcode":"83401",
    "sg:province":"ID",
    "sg:tags":[
        "therapist",
        "massage"
    ],
    "wof:name":"A Touch Of Peace",
    "wof:placetype":"venue"
},
  "geometry": {"coordinates":[-112.017318,43.493854],"type":"Point"}
}