{
  "type": "Feature",
  "properties": {
    "addr:full":"133 S 2nd Ave Pocatello ID 83201",
    "addr:housenumber":"133",
    "addr:postcode":"83201",
    "addr:street":"S 2Nd Ave",
    "iso:country":"US",
    "sg:address":"133 S 2nd Ave",
    "sg:city":"Pocatello",
    "sg:classifiers":[
        {
            "category":"Building & Trades",
            "subcategory":"Plumbing",
            "type":"Services"
        }
    ],
    "sg:phone":"+1 208 233 6626",
    "sg:postcode":"83201",
    "sg:province":"ID",
    "sg:tags":[
        "conditioning",
        "air",
        "system",
        "contractor"
    ],
    "wof:name":"RCH Svc",
    "wof:placetype":"venue"
},
  "geometry": {"coordinates":[-112.445983,42.864072],"type":"Point"}
}