{
  "type": "Feature",
  "properties": {
    "iso:country":"US",
    "sg:address":"6059 Corporal Ln",
    "sg:city":"Boise",
    "sg:classifiers":[
        {
            "category":"Building & Trades",
            "subcategory":"Cleaning & Sanitation",
            "type":"Services"
        }
    ],
    "sg:phone":"+1 208 322 9441",
    "sg:postcode":"83704",
    "sg:province":"ID",
    "sg:tags":[
        "janitor"
    ],
    "wof:name":"CNV Cleaning Svc",
    "wof:placetype":"venue"
},
  "geometry": {"coordinates":[-116.257486,43.60842],"type":"Point"}
}