{
  "type": "Feature",
  "properties": {
    "iso:country":"US",
    "sg:address":"11307 N Government Way",
    "sg:city":"Hayden",
    "sg:classifiers":[
        {
            "category":"Building & Trades",
            "subcategory":"Construction",
            "type":"Services"
        }
    ],
    "sg:phone":"+1 208 762 4311",
    "sg:postcode":"83835",
    "sg:province":"ID",
    "sg:tags":[
        "maker",
        "cabinet"
    ],
    "wof:name":"Rose Woodworks",
    "wof:placetype":"venue"
},
  "geometry": {"coordinates":[-116.786462,47.775552],"type":"Point"}
}