{
  "type": "Feature",
  "properties": {
    "addr:full":"745 W Main St Saint Anthony ID 83445",
    "addr:housenumber":"745",
    "addr:postcode":"83445",
    "addr:street":"W Main St",
    "iso:country":"US",
    "sg:address":"745 W Main St",
    "sg:city":"Saint Anthony",
    "sg:classifiers":[
        {
            "category":"Retail",
            "subcategory":"Auto Repair",
            "type":"Services"
        }
    ],
    "sg:phone":"+1 208 624 3707",
    "sg:postcode":"83445",
    "sg:province":"ID",
    "sg:tags":[
        "automotive"
    ],
    "wof:name":"L&D Enterprises",
    "wof:placetype":"venue"
},
  "geometry": {"coordinates":[-111.692441,43.96648],"type":"Point"}
}