{
  "type": "Feature",
  "properties": {
    "addr:full":"13560 W Elmspring St Boise ID 83713",
    "addr:housenumber":"13560",
    "addr:postcode":"83713",
    "addr:street":"W Elmspring St",
    "iso:country":"US",
    "sg:address":"13560 W Elmspring St",
    "sg:city":"Boise",
    "sg:classifiers":[
        {
            "category":"Insurance",
            "subcategory":"Insurance Agent",
            "type":"Services"
        }
    ],
    "sg:phone":"+1 208 939 7575",
    "sg:postcode":"83713",
    "sg:province":"ID",
    "wof:name":"Farmers Insurance Group",
    "wof:placetype":"venue"
},
  "geometry": {"coordinates":[-116.351468,43.656179],"type":"Point"}
}