{
  "type": "Feature",
  "properties": {
    "addr:full":"804 N Lincoln St Post Falls ID 83854",
    "addr:housenumber":"804",
    "addr:postcode":"83854",
    "addr:street":"N Lincoln St",
    "iso:country":"US",
    "sg:address":"804 N Lincoln St",
    "sg:city":"Post Falls",
    "sg:classifiers":[
        {
            "category":"Personal",
            "subcategory":"Beauty Salon",
            "type":"Services"
        }
    ],
    "sg:phone":"+1 208 773 7167",
    "sg:postcode":"83854",
    "sg:province":"ID",
    "wof:name":"Quesnell's Cuts",
    "wof:placetype":"venue"
},
  "geometry": {"coordinates":[-116.94026700000001,47.716926],"type":"Point"}
}