{
  "type": "Feature",
  "properties": {
    "iso:country":"US",
    "sg:address":"22 N Latah St",
    "sg:city":"Boise",
    "sg:classifiers":[
        {
            "category":"Shopping",
            "subcategory":"Clothing, Apparel, & Fashions",
            "type":"Retail Goods"
        }
    ],
    "sg:phone":"+1 208 338 0593",
    "sg:postcode":"83706",
    "sg:province":"ID",
    "sg:tags":[
        "alteration"
    ],
    "wof:name":"Theresa's Custom Sewing",
    "wof:placetype":"venue"
},
  "geometry": {"coordinates":[-116.228458,43.604509],"type":"Point"}
}