{
  "type": "Feature",
  "properties": {
    "iso:country":"US",
    "sg:address":"10154 Arnold Rd",
    "sg:city":"Boise",
    "sg:classifiers":[
        {
            "category":"Building & Trades",
            "subcategory":"Construction",
            "type":"Services"
        }
    ],
    "sg:phone":"+1 208 939 8474",
    "sg:postcode":"83714",
    "sg:province":"ID",
    "sg:tags":[
        "contractor"
    ],
    "wof:name":"R & L Framing",
    "wof:placetype":"venue"
},
  "geometry": {"coordinates":[-116.308139,43.687716],"type":"Point"}
}