{
  "type": "Feature",
  "properties": {
    "addr:full":"101 E Best Ave Coeur D Alene ID 83814",
    "addr:housenumber":"101",
    "addr:postcode":"83814",
    "addr:street":"E Best Ave",
    "iso:country":"US",
    "sg:address":"101 E Best Ave",
    "sg:city":"Coeur D Alene",
    "sg:classifiers":[
        {
            "category":"Building & Trades",
            "subcategory":"Equipment Rental",
            "type":"Services"
        }
    ],
    "sg:phone":"+1 208 676 1699",
    "sg:postcode":"83814",
    "sg:province":"ID",
    "sg:tags":[
        "yard"
    ],
    "wof:name":"Rent-A-Center",
    "wof:placetype":"venue"
},
  "geometry": {"coordinates":[-116.78525999999999,47.700734],"type":"Point"}
}