{
  "type": "Feature",
  "properties": {
    "addr:full":"1804 Penninger Cir Boise ID 83709",
    "addr:housenumber":"1804",
    "addr:postcode":"83709",
    "addr:street":"Penninger Cir",
    "iso:country":"US",
    "sg:address":"1804 Penninger Cir",
    "sg:city":"Boise",
    "sg:classifiers":[
        {
            "category":"Professional",
            "type":"Services"
        }
    ],
    "sg:phone":"+1 208 377 3993",
    "sg:postcode":"83709",
    "sg:province":"ID",
    "sg:tags":[
        "establishment"
    ],
    "wof:name":"A Spectrum Specialties",
    "wof:placetype":"venue"
},
  "geometry": {"coordinates":[-116.283192,43.587811],"type":"Point"}
}