{
  "type": "Feature",
  "properties": {
    "iso:country":"US",
    "sg:address":"22689 Farmway Rd",
    "sg:city":"Caldwell",
    "sg:classifiers":[
        {
            "category":"Building & Trades",
            "subcategory":"Construction",
            "type":"Services"
        }
    ],
    "sg:phone":"+1 208 454 5659",
    "sg:postcode":"83607",
    "sg:province":"ID",
    "sg:tags":[
        "floor",
        "laying",
        "contractor"
    ],
    "wof:name":"Buddy Yuen",
    "wof:placetype":"venue"
},
  "geometry": {"coordinates":[-116.71314,43.700852],"type":"Point"}
}