{
  "type": "Feature",
  "properties": {
    "iso:country":"US",
    "sg:address":"511 Van Dreff St",
    "sg:city":"Salmon",
    "sg:classifiers":[
        {
            "category":"Personal",
            "subcategory":"Beauty Salon",
            "type":"Services"
        }
    ],
    "sg:phone":"+1 208 756 8200",
    "sg:postcode":"83467",
    "sg:province":"ID",
    "sg:tags":[
        "shop",
        "manicuring"
    ],
    "wof:name":"Terry's Touch",
    "wof:placetype":"venue"
},
  "geometry": {"coordinates":[-113.895263,45.174934],"type":"Point"}
}