{
  "type": "Feature",
  "properties": {
    "addr:full":"12970 US Hwy 12 Orofino ID 83544",
    "addr:housenumber":"12970",
    "addr:postcode":"83544",
    "addr:street":"Us Hwy 12",
    "iso:country":"US",
    "sg:address":"12970 US Hwy 12",
    "sg:city":"Orofino",
    "sg:classifiers":[
        {
            "category":"Shopping",
            "subcategory":"Department Store",
            "type":"Retail Goods"
        }
    ],
    "sg:phone":"+1 208 476 7510",
    "sg:postcode":"83544",
    "sg:province":"ID",
    "wof:name":"King's Of Orofino",
    "wof:placetype":"venue"
},
  "geometry": {"coordinates":[-116.31907099999999,46.499239],"type":"Point"}
}