{
  "type": "Feature",
  "properties": {
    "addr:full":"4300 W Riverbend Ave Post Falls ID 83854",
    "addr:housenumber":"4300",
    "addr:postcode":"83854",
    "addr:street":"W Riverbend Ave",
    "iso:country":"US",
    "sg:address":"4300 W Riverbend Ave",
    "sg:city":"Post Falls",
    "sg:classifiers":[
        {
            "category":"Shopping",
            "subcategory":"Optical Goods",
            "type":"Retail Goods"
        }
    ],
    "sg:phone":"+1 208 773 0360",
    "sg:postcode":"83854",
    "sg:province":"ID",
    "sg:tags":[
        "sun",
        "goggles",
        "sunglasses"
    ],
    "sg:website":"www.sunglasshut.com",
    "wof:name":"Sunglass Hut",
    "wof:placetype":"venue"
},
  "geometry": {"coordinates":[-117.00725799999999,47.705655],"type":"Point"}
}