{
  "type": "Feature",
  "properties": {
    "addr:full":"4155 Yellowstone Ave Pocatello ID 83202",
    "addr:housenumber":"4155",
    "addr:postcode":"83202",
    "addr:street":"Yellowstone Ave",
    "iso:country":"US",
    "sg:address":"4155 Yellowstone Ave",
    "sg:city":"Pocatello",
    "sg:classifiers":[
        {
            "category":"Restaurant",
            "type":"Food & Drink"
        }
    ],
    "sg:menulink":"http://www.allmenus.com/id/pocatello/120388-subway/menu/",
    "sg:phone":"+1 208 237 6634",
    "sg:postcode":"83202",
    "sg:province":"ID",
    "sg:tags":[
        "american",
        "sandwich"
    ],
    "wof:name":"Subway",
    "wof:placetype":"venue"
},
  "geometry": {"coordinates":[-112.466317,42.90905],"type":"Point"}
}