{
  "type": "Feature",
  "properties": {
    "addr:full":"333 N Woodruff Ave Idaho Falls ID 83401",
    "addr:housenumber":"333",
    "addr:postcode":"83401",
    "addr:street":"N Woodruff Ave",
    "iso:country":"US",
    "sg:address":"333 N Woodruff Ave",
    "sg:city":"Idaho Falls",
    "sg:classifiers":[
        {
            "category":"Food & Beverages",
            "subcategory":"Groceries & Convenience Stores",
            "type":"Retail Goods"
        }
    ],
    "sg:phone":"+1 208 552 0821",
    "sg:postcode":"83401",
    "sg:province":"ID",
    "sg:tags":[
        "grocer"
    ],
    "wof:name":"Winco Foods",
    "wof:placetype":"venue"
},
  "geometry": {"coordinates":[-111.999197,43.498718],"type":"Point"}
}