{
  "type": "Feature",
  "properties": {
    "iso:country":"US",
    "sg:address":"1180 Wild Phlox Way",
    "sg:city":"Boise",
    "sg:classifiers":[
        {
            "category":"Professional",
            "subcategory":"Business Services",
            "type":"Services"
        }
    ],
    "sg:phone":"+1 208 376 6212",
    "sg:postcode":"83709",
    "sg:province":"ID",
    "wof:name":"Barbara L Stjohn",
    "wof:placetype":"venue"
},
  "geometry": {"coordinates":[-116.276515,43.595149],"type":"Point"}
}