{
  "type": "Feature",
  "properties": {
    "iso:country":"US",
    "sg:address":"2537 W State St Ste 200",
    "sg:city":"Boise",
    "sg:classifiers":[
        {
            "category":"Social Services",
            "subcategory":"Child Care",
            "type":"Services"
        },
        {
            "category":"Professional",
            "type":"Services"
        },
        {
            "category":"Professional",
            "subcategory":"Lawyer & Legal Services",
            "type":"Services"
        }
    ],
    "sg:phone":"+1 208 577 6717",
    "sg:postcode":"83702",
    "sg:province":"ID",
    "sg:tags":[
        "arbitration",
        "attorney",
        "law",
        "business",
        "family",
        "compensation",
        "personal",
        "practice",
        "worker",
        "damage",
        "immigration",
        "property",
        "benefit",
        "accident",
        "adoption",
        "employee",
        "injury",
        "consumer",
        "insurance",
        "mediation"
    ],
    "sg:website":"http://www.bradylawoffice.com",
    "wof:name":"Brady Law Chartered",
    "wof:placetype":"venue"
},
  "geometry": {"coordinates":[-116.221113,43.630452],"type":"Point"}
}