{
  "type": "Feature",
  "properties": {
    "iso:country":"US",
    "sg:address":"9845 W Secretariat Ct",
    "sg:city":"Boise",
    "sg:classifiers":[
        {
            "category":"Insurance",
            "subcategory":"Insurance Agent",
            "type":"Services"
        }
    ],
    "sg:phone":"+1 208 373 0943",
    "sg:postcode":"83704",
    "sg:province":"ID",
    "wof:name":"Hirai Group LLC",
    "wof:placetype":"venue"
},
  "geometry": {"coordinates":[-116.304956,43.645659],"type":"Point"}
}