{
  "type": "Feature",
  "properties": {
    "iso:country":"US",
    "sg:address":"1150 Lowell Dr",
    "sg:city":"Idaho Falls",
    "sg:classifiers":[
        {
            "category":"Personal",
            "subcategory":"Beauty Salon",
            "type":"Services"
        }
    ],
    "sg:phone":"+1 208 524 1596",
    "sg:postcode":"83402",
    "sg:province":"ID",
    "wof:name":"Place To Be",
    "wof:placetype":"venue"
},
  "geometry": {"coordinates":[-112.09241900000001,43.486914],"type":"Point"}
}