{
  "type": "Feature",
  "properties": {
    "iso:country":"US",
    "sg:address":"7901 S Chisum Way",
    "sg:city":"Meridian",
    "sg:classifiers":[
        {
            "category":"Building & Trades",
            "subcategory":"Construction",
            "type":"Services"
        }
    ],
    "sg:phone":"+1 208 895 8673",
    "sg:postcode":"83642",
    "sg:province":"ID",
    "sg:tags":[
        "contractor"
    ],
    "wof:name":"Sargent Tile Works LLC",
    "wof:placetype":"venue"
},
  "geometry": {"coordinates":[-116.42196800000001,43.534318],"type":"Point"}
}