{
  "type": "Feature",
  "properties": {
    "iso:country":"US",
    "sg:address":"2220 E Star Ln",
    "sg:city":"Meridian",
    "sg:classifiers":[
        {
            "category":"Building & Trades",
            "subcategory":"Landscaping Services",
            "type":"Services"
        }
    ],
    "sg:phone":"+1 208 887 9652",
    "sg:postcode":"83642",
    "sg:province":"ID",
    "sg:tags":[
        "landscape",
        "contractor"
    ],
    "wof:name":"LA Casse Landscaping Inc",
    "wof:placetype":"venue"
},
  "geometry": {"coordinates":[-116.369113,43.64389],"type":"Point"}
}