{
  "type": "Feature",
  "properties": {
    "iso:country":"US",
    "sg:address":"925 N Main St",
    "sg:city":"Meridian",
    "sg:classifiers":[
        {
            "category":"Insurance",
            "subcategory":"Insurance Agent",
            "type":"Services"
        },
        {
            "category":"Insurance",
            "subcategory":"Hazard Insurance",
            "type":"Services"
        },
        {
            "category":"Insurance",
            "subcategory":"Health Insurance",
            "type":"Services"
        },
        {
            "category":"Insurance",
            "subcategory":"Life Insurance",
            "type":"Services"
        }
    ],
    "sg:phone":"+1 208 629 0861",
    "sg:postcode":"83642",
    "sg:province":"ID",
    "sg:tags":[
        "business",
        "auto",
        "commercial",
        "disability",
        "compensation",
        "worker"
    ],
    "sg:website":"http://www.aaillc.com",
    "wof:name":"All American Insurance LLC",
    "wof:placetype":"venue"
},
  "geometry": {"coordinates":[-116.391577,43.612182],"type":"Point"}
}