{
  "type": "Feature",
  "properties": {
    "iso:country":"US",
    "sg:address":"3383 Anchor Ln",
    "sg:city":"Twin Falls",
    "sg:classifiers":[
        {
            "category":"Real Estate",
            "subcategory":"Architect",
            "type":"Services"
        }
    ],
    "sg:phone":"+1 208 733 2493",
    "sg:postcode":"83301",
    "sg:province":"ID",
    "sg:tags":[
        "architectural"
    ],
    "wof:name":"Archeion Design Built",
    "wof:placetype":"venue"
},
  "geometry": {"coordinates":[-114.44424100000001,42.490363],"type":"Point"}
}