{
  "type": "Feature",
  "properties": {
    "iso:country":"US",
    "sg:address":"125 Maple St",
    "sg:city":"Kamiah",
    "sg:classifiers":[
        {
            "category":"Social Services",
            "type":"Services"
        }
    ],
    "sg:phone":"+1 208 935 0244",
    "sg:postcode":"83536",
    "sg:province":"ID",
    "wof:name":"Senior Services",
    "wof:placetype":"venue"
},
  "geometry": {"coordinates":[-116.03060600000001,46.23069],"type":"Point"}
}