{
  "type": "Feature",
  "properties": {
    "addr:full":"851 S 5th Ave Pocatello ID 83201",
    "addr:housenumber":"851",
    "addr:postcode":"83201",
    "addr:street":"S 5Th Ave",
    "iso:country":"US",
    "sg:address":"851 S 5th Ave",
    "sg:city":"Pocatello",
    "sg:classifiers":[
        {
            "category":"Restaurant",
            "type":"Food & Drink"
        }
    ],
    "sg:menulink":"http://www.allmenus.com/id/pocatello/224250-elmers-restaurant/menu/",
    "sg:phone":"+1 208 232 9114",
    "sg:postcode":"83201",
    "sg:province":"ID",
    "sg:tags":[
        "wrap",
        "burger",
        "american",
        "sandwich",
        "steakhouse"
    ],
    "wof:name":"Elmer's Restaurant",
    "wof:placetype":"venue"
},
  "geometry": {"coordinates":[-112.436942,42.860939],"type":"Point"}
}