{
  "type": "Feature",
  "properties": {
    "iso:country":"US",
    "sg:address":"845 Evergreen Rd",
    "sg:city":"Sagle",
    "sg:classifiers":[
        {
            "category":"Professional",
            "subcategory":"Business Services",
            "type":"Services"
        }
    ],
    "sg:phone":"+1 208 255 5700",
    "sg:postcode":"83860",
    "sg:province":"ID",
    "wof:name":"Scott Gilbert Ltd Partnership",
    "wof:placetype":"venue"
},
  "geometry": {"coordinates":[-116.711302,48.209309],"type":"Point"}
}