{
  "type": "Feature",
  "properties": {
    "iso:country":"US",
    "sg:address":"5120 W Cherry Ln",
    "sg:city":"Meridian",
    "sg:classifiers":[
        {
            "category":"Real Estate",
            "subcategory":"Real Estate Operator",
            "type":"Services"
        }
    ],
    "sg:phone":"+1 208 888 5979",
    "sg:postcode":"83642",
    "sg:province":"ID",
    "sg:tags":[
        "property",
        "lessor"
    ],
    "wof:name":"Steven P Cady Inc",
    "wof:placetype":"venue"
},
  "geometry": {"coordinates":[-116.45757,43.619474],"type":"Point"}
}