{
  "type": "Feature",
  "properties": {
    "addr:full":"4150 W King Rd Kuna ID 83634",
    "addr:housenumber":"4150",
    "addr:postcode":"83634",
    "addr:street":"W King Rd",
    "iso:country":"US",
    "sg:address":"4150 W King Rd",
    "sg:city":"Kuna",
    "sg:classifiers":[
        {
            "category":"Professional",
            "subcategory":"Computer Services",
            "type":"Services"
        }
    ],
    "sg:phone":"+1 208 922 3400",
    "sg:postcode":"83634",
    "sg:province":"ID",
    "wof:name":"Classic Computer Svc",
    "wof:placetype":"venue"
},
  "geometry": {"coordinates":[-116.4622,43.473817],"type":"Point"}
}