{
  "type": "Feature",
  "properties": {
    "addr:full":"300 N 16th St Payette ID 83661",
    "addr:housenumber":"300",
    "addr:postcode":"83661",
    "addr:street":"N 16Th St",
    "iso:country":"US",
    "sg:address":"300 N 16th St",
    "sg:city":"Payette",
    "sg:classifiers":[
        {
            "category":"Manufacturing",
            "subcategory":"Metals",
            "type":"Manufacturing & Wholesale Goods"
        }
    ],
    "sg:phone":"+1 208 642 4148",
    "sg:postcode":"83661",
    "sg:province":"ID",
    "sg:tags":[
        "gates"
    ],
    "wof:name":"Superior Lift Gates Inc",
    "wof:placetype":"venue"
},
  "geometry": {"coordinates":[-116.92314,44.080031],"type":"Point"}
}