{
  "type": "Feature",
  "properties": {
    "iso:country":"US",
    "sg:address":"828 S Washington St Ste A",
    "sg:city":"Moscow",
    "sg:classifiers":[
        {
            "category":"Professional",
            "subcategory":"Accounting & Tax Preparation",
            "type":"Services"
        }
    ],
    "sg:phone":"+1 208 883 3167",
    "sg:postcode":"83843",
    "sg:province":"ID",
    "sg:tags":[
        "payroll",
        "return",
        "accountants-certified",
        "preparation-business",
        "public"
    ],
    "sg:website":"http://www.accountant-city.com/MCKETTA",
    "wof:name":"Judi Mcketta Cpa",
    "wof:placetype":"venue"
},
  "geometry": {"coordinates":[-116.999999,46.727789],"type":"Point"}
}