{
  "type": "Feature",
  "properties": {
    "addr:full":"9436 Linfield Dr Boise ID 83704",
    "addr:housenumber":"9436",
    "addr:postcode":"83704",
    "addr:street":"Linfield Dr",
    "iso:country":"US",
    "sg:address":"9436 Linfield Dr",
    "sg:city":"Boise",
    "sg:classifiers":[
        {
            "category":"Shopping",
            "subcategory":"Crafts & Fabrics",
            "type":"Retail Goods"
        }
    ],
    "sg:phone":"+1 208 375 2288",
    "sg:postcode":"83704",
    "sg:province":"ID",
    "sg:tags":[
        "sewing"
    ],
    "wof:name":"Cindys Sewing",
    "wof:placetype":"venue"
},
  "geometry": {"coordinates":[-116.30136400000001,43.64442],"type":"Point"}
}