{
  "type": "Feature",
  "properties": {
    "iso:country":"US",
    "sg:address":"3002 Cemetery Rd",
    "sg:city":"Cambridge",
    "sg:classifiers":[
        {
            "category":"Farming",
            "subcategory":"Nursery",
            "type":"Manufacturing & Wholesale Goods"
        }
    ],
    "sg:phone":"+1 208 257 3960",
    "sg:postcode":"83610",
    "sg:province":"ID",
    "sg:tags":[
        "ornamental"
    ],
    "wof:name":"Quail Run Nursery",
    "wof:placetype":"venue"
},
  "geometry": {"coordinates":[-116.67359,44.585601],"type":"Point"}
}