{
  "type": "Feature",
  "properties": {
    "iso:country":"US",
    "sg:address":"2136 S Owl Ridge Ave",
    "sg:city":"Boise",
    "sg:classifiers":[
        {
            "category":"Building & Trades",
            "subcategory":"Equipment Rental",
            "type":"Services"
        }
    ],
    "sg:phone":"+1 208 376 9305",
    "sg:postcode":"83709",
    "sg:province":"ID",
    "sg:tags":[
        "aircraft",
        "leasing",
        "charter"
    ],
    "wof:name":"Bair Air Inc",
    "wof:placetype":"venue"
},
  "geometry": {"coordinates":[-116.322547,43.583523],"type":"Point"}
}