{
  "type": "Feature",
  "properties": {
    "iso:country":"US",
    "sg:address":"1805 W Overland Rd",
    "sg:city":"Boise",
    "sg:classifiers":[
        {
            "category":"Health Services",
            "subcategory":"Chiropractor",
            "type":"Services"
        }
    ],
    "sg:phone":"+1 208 336 4040",
    "sg:postcode":"83705",
    "sg:province":"ID",
    "wof:name":"Vista Chiropractic Clinic",
    "wof:placetype":"venue"
},
  "geometry": {"coordinates":[-116.20544,43.589775],"type":"Point"}
}