{
  "type": "Feature",
  "properties": {
    "iso:country":"US",
    "sg:address":"2089 N Holmes Ave",
    "sg:city":"Idaho Falls",
    "sg:classifiers":[
        {
            "category":"Home & Garden",
            "subcategory":"Building Materials",
            "type":"Retail Goods"
        }
    ],
    "sg:phone":"+1 208 522 3999",
    "sg:postcode":"83401",
    "sg:province":"ID",
    "sg:tags":[
        "glass",
        "window",
        "plate"
    ],
    "wof:name":"Colvin's Glass Inc",
    "wof:placetype":"venue"
},
  "geometry": {"coordinates":[-112.023708,43.51475],"type":"Point"}
}