{
  "type": "Feature",
  "properties": {
    "addr:full":"14207 US Hwy 30 Pocatello ID 83201",
    "addr:housenumber":"14207",
    "addr:postcode":"83201",
    "addr:street":"Us Hwy 30",
    "iso:country":"US",
    "sg:address":"14207 US Hwy 30",
    "sg:city":"Pocatello",
    "sg:classifiers":[
        {
            "category":"Autos & Motor Vehicles",
            "subcategory":"Recreational Vehicle Sales",
            "type":"Retail Goods"
        }
    ],
    "sg:phone":"+1 208 233 6330",
    "sg:postcode":"83201",
    "sg:province":"ID",
    "wof:name":"Park-A-Way Rv",
    "wof:placetype":"venue"
},
  "geometry": {"coordinates":[-112.503511,42.903327],"type":"Point"}
}