{
  "type": "Feature",
  "properties": {
    "iso:country":"US",
    "sg:address":"342 E 3rd St",
    "sg:city":"Meridian",
    "sg:classifiers":[
        {
            "category":"Manufacturing",
            "subcategory":"Furniture",
            "type":"Manufacturing & Wholesale Goods"
        }
    ],
    "sg:phone":"+1 208 884 0761",
    "sg:postcode":"83642",
    "sg:province":"ID",
    "sg:tags":[
        "household",
        "wood",
        "mfg"
    ],
    "wof:name":"Dead Wood Works",
    "wof:placetype":"venue"
},
  "geometry": {"coordinates":[-116.388706,43.606497],"type":"Point"}
}