{
  "type": "Feature",
  "properties": {
    "addr:full":"835 Blue Lakes Blvd S Twin Falls ID 83301",
    "addr:housenumber":"835",
    "addr:postcode":"83301",
    "addr:street":"Blue Lakes Blvd S Twin",
    "iso:country":"US",
    "sg:address":"835 Blue Lakes Blvd S",
    "sg:city":"Twin Falls",
    "sg:classifiers":[
        {
            "category":"Organizations",
            "subcategory":"Religious Organization",
            "type":"Services"
        }
    ],
    "sg:phone":"+1 208 735 2249",
    "sg:postcode":"83301",
    "sg:province":"ID",
    "sg:tags":[
        "church"
    ],
    "wof:name":"Centro De Oracion Y Alabanza",
    "wof:placetype":"venue"
},
  "geometry": {"coordinates":[-114.46007400000001,42.535859],"type":"Point"}
}