{
  "type": "Feature",
  "properties": {
    "iso:country":"US",
    "sg:address":"522 Main St",
    "sg:city":"Ashton",
    "sg:classifiers":[
        {
            "category":"Social Services",
            "type":"Services"
        }
    ],
    "sg:phone":"+1 208 652 3594",
    "sg:postcode":"83420",
    "sg:province":"ID",
    "sg:tags":[
        "senior",
        "citizen"
    ],
    "wof:name":"Ashton Senior Citizens",
    "wof:placetype":"venue"
},
  "geometry": {"coordinates":[-111.44811900000001,44.071397],"type":"Point"}
}