{
  "type": "Feature",
  "properties": {
    "iso:country":"US",
    "sg:address":"243 W Roseberry Rd",
    "sg:city":"Donnelly",
    "sg:phone":"+1 208 325 8631",
    "sg:postcode":"83638",
    "sg:province":"ID",
    "sg:tags":[
        "gas"
    ],
    "wof:name":"V-1 Propane",
    "wof:placetype":"venue"
},
  "geometry": {"coordinates":[-116.091172,44.73114],"type":"Point"}
}