{
  "type": "Feature",
  "properties": {
    "addr:full":"4565 Victorian Way Idaho Falls ID 83404",
    "addr:housenumber":"4565",
    "addr:postcode":"83404",
    "addr:street":"Victorian Way",
    "iso:country":"US",
    "sg:address":"4565 Victorian Way",
    "sg:city":"Idaho Falls",
    "sg:classifiers":[
        {
            "category":"Restaurant",
            "type":"Food & Drink"
        }
    ],
    "sg:phone":"+1 208 529 3368",
    "sg:postcode":"83404",
    "sg:province":"ID",
    "wof:name":"J & C Enterprises",
    "wof:placetype":"venue"
},
  "geometry": {"coordinates":[-112.034098,43.456673],"type":"Point"}
}