{
  "type": "Feature",
  "properties": {
    "addr:full":"2128 8th Ave Lewiston ID 83501",
    "addr:housenumber":"2128",
    "addr:postcode":"83501",
    "addr:street":"8Th Ave",
    "iso:country":"US",
    "sg:address":"2128 8th Ave",
    "sg:city":"Lewiston",
    "sg:classifiers":[
        {
            "category":"Travel",
            "subcategory":"Hotels & Motels",
            "type":"Entertainment"
        }
    ],
    "sg:phone":"+1 800 424 6423",
    "sg:postcode":"83501",
    "sg:province":"ID",
    "sg:website":"http://www.comfortinn.com/hotel-lewiston-idaho-ID606?promo=yplocal",
    "wof:name":"Comfort Inn Lewiston",
    "wof:placetype":"venue"
},
  "geometry": {"coordinates":[-117.001518,46.412554],"type":"Point"}
}