{
  "type": "Feature",
  "properties": {
    "addr:full":"1201 6th Ave S Payette ID 83661",
    "addr:housenumber":"1201",
    "addr:postcode":"83661",
    "addr:street":"6Th Ave S",
    "iso:country":"US",
    "sg:address":"1201 6th Ave S",
    "sg:city":"Payette",
    "sg:classifiers":[
        {
            "category":"Home & Garden",
            "subcategory":"Building Materials",
            "type":"Retail Goods"
        }
    ],
    "sg:phone":"+1 208 642 2464",
    "sg:postcode":"83661",
    "sg:province":"ID",
    "sg:tags":[
        "equipment"
    ],
    "wof:name":"Furrers Glass & Paint",
    "wof:placetype":"venue"
},
  "geometry": {"coordinates":[-116.92818699999999,44.067675],"type":"Point"}
}