{
  "type": "Feature",
  "properties": {
    "iso:country":"US",
    "sg:address":"80 Butler Dr",
    "sg:city":"Saint Maries",
    "sg:classifiers":[
        {
            "category":"Manufacturing",
            "subcategory":"Lumber",
            "type":"Manufacturing & Wholesale Goods"
        }
    ],
    "sg:phone":"+1 208 245 3209",
    "sg:postcode":"83861",
    "sg:province":"ID",
    "sg:tags":[
        "logging"
    ],
    "wof:name":"Harry D Dimico",
    "wof:placetype":"venue"
},
  "geometry": {"coordinates":[-116.603673,47.335618],"type":"Point"}
}