{
  "type": "Feature",
  "properties": {
    "iso:country":"US",
    "sg:address":"112 3rd St S",
    "sg:city":"Nampa",
    "sg:classifiers":[
        {
            "category":"Bars & Pubs",
            "type":"Food & Drink"
        },
        {
            "category":"Restaurant",
            "type":"Food & Drink"
        },
        {
            "category":"Bars & Pubs",
            "subcategory":"Lounge",
            "type":"Food & Drink"
        }
    ],
    "sg:phone":"+1 208 466 4006",
    "sg:postcode":"83651",
    "sg:province":"ID",
    "sg:tags":[
        "style",
        "cocktail",
        "family"
    ],
    "wof:name":"Generations Restaurant",
    "wof:placetype":"venue"
},
  "geometry": {"coordinates":[-116.57321899999999,43.58509],"type":"Point"}
}