{
  "type": "Feature",
  "properties": {
    "iso:country":"US",
    "sg:address":"614 N 15th St",
    "sg:city":"Coeur D Alene",
    "sg:classifiers":[
        {
            "category":"Professional",
            "subcategory":"Business Services",
            "type":"Services"
        }
    ],
    "sg:phone":"+1 208 667 5844",
    "sg:postcode":"83814",
    "sg:province":"ID",
    "sg:tags":[
        "drafting"
    ],
    "wof:name":"Stevan Joseph Drafting & Dsgn",
    "wof:placetype":"venue"
},
  "geometry": {"coordinates":[-116.764683,47.678231],"type":"Point"}
}