{
  "type": "Feature",
  "properties": {
    "iso:country":"US",
    "sg:address":"3200 N Lakeharbor Ln",
    "sg:city":"Boise",
    "sg:classifiers":[
        {
            "category":"Personal",
            "subcategory":"Beauty Salon",
            "type":"Services"
        }
    ],
    "sg:phone":"+1 208 342 3843",
    "sg:postcode":"83703",
    "sg:province":"ID",
    "wof:name":"Silver Lake Salon",
    "wof:placetype":"venue"
},
  "geometry": {"coordinates":[-116.251167,43.650272],"type":"Point"}
}