{
  "type": "Feature",
  "properties": {
    "addr:full":"1131 Selkirk Rd Sandpoint ID 83864",
    "addr:housenumber":"1131",
    "addr:postcode":"83864",
    "addr:street":"Selkirk Rd",
    "iso:country":"US",
    "sg:address":"1131 Selkirk Rd",
    "sg:city":"Sandpoint",
    "sg:classifiers":[
        {
            "category":"Professional",
            "type":"Services"
        }
    ],
    "sg:phone":"+1 208 263 1198",
    "sg:postcode":"83864",
    "sg:province":"ID",
    "wof:name":"Remmetter Inc",
    "wof:placetype":"venue"
},
  "geometry": {"coordinates":[-116.47250699999999,48.372465],"type":"Point"}
}