{
  "type": "Feature",
  "properties": {
    "iso:country":"US",
    "sg:address":"1401 N Whitley Dr",
    "sg:city":"Fruitland",
    "sg:classifiers":[
        {
            "category":"Banks & Credit Unions",
            "subcategory":"Bank",
            "type":"Services"
        }
    ],
    "sg:phone":"+1 208 452 5750",
    "sg:postcode":"83619",
    "sg:province":"ID",
    "sg:tags":[
        "loan",
        "real estate"
    ],
    "wof:name":"Executive Home Loans",
    "wof:placetype":"venue"
},
  "geometry": {"coordinates":[-116.92364999999999,44.023107],"type":"Point"}
}