{
  "type": "Feature",
  "properties": {
    "iso:country":"US",
    "sg:address":"296 Lomax St",
    "sg:city":"Idaho Falls",
    "sg:classifiers":[
        {
            "category":"Home & Garden",
            "subcategory":"Building Materials",
            "type":"Retail Goods"
        }
    ],
    "sg:phone":"+1 208 522 6550",
    "sg:postcode":"83401",
    "sg:province":"ID",
    "sg:tags":[
        "glass",
        "window",
        "plate"
    ],
    "sg:website":"www.valleyglass.com",
    "wof:name":"Valley Glass Co",
    "wof:placetype":"venue"
},
  "geometry": {"coordinates":[-112.031114,43.497824],"type":"Point"}
}