{
  "type": "Feature",
  "properties": {
    "iso:country":"US",
    "sg:address":"1410 S Blaine St",
    "sg:city":"Moscow",
    "sg:classifiers":[
        {
            "category":"Shopping",
            "subcategory":"Department Store",
            "type":"Retail Goods"
        }
    ],
    "sg:phone":"+1 208 882 8095",
    "sg:postcode":"83843",
    "sg:province":"ID",
    "wof:name":"Sears Roebuck & Co",
    "wof:placetype":"venue"
},
  "geometry": {"coordinates":[-116.985529,46.721836],"type":"Point"}
}