{
  "type": "Feature",
  "properties": {
    "addr:full":"703 Dogwood St Pocatello ID 83201",
    "addr:housenumber":"703",
    "addr:postcode":"83201",
    "addr:street":"Dogwood St",
    "iso:country":"US",
    "sg:address":"703 Dogwood St",
    "sg:city":"Pocatello",
    "sg:classifiers":[
        {
            "category":"Personal",
            "subcategory":"Beauty Salon",
            "type":"Services"
        }
    ],
    "sg:phone":"+1 208 232 1984",
    "sg:postcode":"83201",
    "sg:province":"ID",
    "sg:tags":[
        "shop"
    ],
    "wof:name":"Mary's House Of Style",
    "wof:placetype":"venue"
},
  "geometry": {"coordinates":[-112.46610699999999,42.884602],"type":"Point"}
}