{
  "type": "Feature",
  "properties": {
    "iso:country":"US",
    "sg:address":"11500 Fairview Ave",
    "sg:city":"Boise",
    "sg:classifiers":[
        {
            "category":"Home & Garden",
            "subcategory":"Garden Supply",
            "type":"Retail Goods"
        }
    ],
    "sg:phone":"+1 208 376 3322",
    "sg:postcode":"83713",
    "sg:province":"ID",
    "sg:tags":[
        "nurseryman"
    ],
    "wof:name":"Garden Center West Inc",
    "wof:placetype":"venue"
},
  "geometry": {"coordinates":[-116.32936599999999,43.619429],"type":"Point"}
}