{
  "type": "Feature",
  "properties": {
    "iso:country":"US",
    "sg:address":"252 W Main St",
    "sg:city":"Jerome",
    "sg:classifiers":[
        {
            "category":"Retail",
            "subcategory":"Auto Repair",
            "type":"Services"
        }
    ],
    "sg:phone":"+1 208 324 2572",
    "sg:postcode":"83338",
    "sg:province":"ID",
    "sg:tags":[
        "repairing",
        "automobile"
    ],
    "wof:name":"Jerome Wheel & Auto Svc",
    "wof:placetype":"venue"
},
  "geometry": {"coordinates":[-114.520973,42.724238],"type":"Point"}
}