{
  "type": "Feature",
  "properties": {
    "addr:full":"215 W Maple St Pocatello ID 83201",
    "addr:housenumber":"215",
    "addr:postcode":"83201",
    "addr:street":"W Maple St",
    "iso:country":"US",
    "sg:address":"215 W Maple St",
    "sg:city":"Pocatello",
    "sg:classifiers":[
        {
            "category":"Home & Garden",
            "subcategory":"Building Materials",
            "type":"Retail Goods"
        }
    ],
    "sg:phone":"+1 208 233 2172",
    "sg:postcode":"83201",
    "sg:province":"ID",
    "sg:tags":[
        "glass",
        "window",
        "plate"
    ],
    "wof:name":"Speedy Glass",
    "wof:placetype":"venue"
},
  "geometry": {"coordinates":[-112.453146,42.88047],"type":"Point"}
}