{
  "type": "Feature",
  "properties": {
    "iso:country":"US",
    "sg:address":"2063 W Jayton Dr",
    "sg:city":"Meridian",
    "sg:classifiers":[
        {
            "category":"Professional",
            "subcategory":"Computer Services",
            "type":"Services"
        }
    ],
    "sg:phone":"+1 208 887 8606",
    "sg:postcode":"83642",
    "sg:province":"ID",
    "sg:tags":[
        "programing",
        "custom"
    ],
    "wof:name":"Ridgeline Web Design",
    "wof:placetype":"venue"
},
  "geometry": {"coordinates":[-116.420103,43.611387],"type":"Point"}
}