{
  "type": "Feature",
  "properties": {
    "iso:country":"US",
    "sg:address":"10917 N Yellowstone Hwy",
    "sg:city":"Ucon",
    "sg:classifiers":[
        {
            "category":"Retail",
            "subcategory":"Auto Repair",
            "type":"Services"
        }
    ],
    "sg:phone":"+1 208 522 2035",
    "sg:postcode":"83454",
    "sg:province":"ID",
    "sg:tags":[
        "repairing",
        "automobile"
    ],
    "wof:name":"S A Hill Garage",
    "wof:placetype":"venue"
},
  "geometry": {"coordinates":[-111.963774,43.594431],"type":"Point"}
}