{
  "type": "Feature",
  "properties": {
    "addr:full":"1205 W Bannock St Boise ID 83702",
    "addr:housenumber":"1205",
    "addr:postcode":"83702",
    "addr:street":"W Bannock St",
    "iso:country":"US",
    "sg:address":"1205 W Bannock St",
    "sg:city":"Boise",
    "sg:classifiers":[
        {
            "category":"Retail",
            "subcategory":"Funeral Services",
            "type":"Services"
        }
    ],
    "sg:phone":"+1 208 343 6493",
    "sg:postcode":"83702",
    "sg:province":"ID",
    "sg:tags":[
        "director"
    ],
    "sg:website":"www.summersfuneral.com",
    "wof:name":"Summers Funeral Home",
    "wof:placetype":"venue"
},
  "geometry": {"coordinates":[-116.207904,43.620052],"type":"Point"}
}