{
  "type": "Feature",
  "properties": {
    "addr:full":"252 N 2nd Ave Pocatello ID 83201",
    "addr:housenumber":"252",
    "addr:postcode":"83201",
    "addr:street":"N 2Nd Ave",
    "iso:country":"US",
    "sg:address":"252 N 2nd Ave",
    "sg:city":"Pocatello",
    "sg:classifiers":[
        {
            "category":"Retail",
            "subcategory":"Auto Repair",
            "type":"Services"
        }
    ],
    "sg:phone":"+1 208 232 7365",
    "sg:postcode":"83201",
    "sg:province":"ID",
    "sg:tags":[
        "repairing",
        "automobile"
    ],
    "wof:name":"Frank's Repair Svc Inc",
    "wof:placetype":"venue"
},
  "geometry": {"coordinates":[-112.447953,42.865786],"type":"Point"}
}