{
  "type": "Feature",
  "properties": {
    "addr:full":"3457 E 650 N Menan ID 83434",
    "addr:housenumber":"3457",
    "addr:postcode":"83434",
    "addr:street":"E 650 N",
    "iso:country":"US",
    "sg:address":"3457 E 650 N",
    "sg:city":"Menan",
    "sg:classifiers":[
        {
            "category":"Real Estate",
            "subcategory":"Real Estate Agent",
            "type":"Services"
        }
    ],
    "sg:phone":"+1 208 200 9955",
    "sg:postcode":"83434",
    "sg:province":"ID",
    "sg:tags":[
        "management"
    ],
    "wof:name":"Aspen Property Maintenance",
    "wof:placetype":"venue"
},
  "geometry": {"coordinates":[-112.01095599999999,43.720649],"type":"Point"}
}