{
  "type": "Feature",
  "properties": {
    "addr:full":"246 Roosevelt St American Falls ID 83211",
    "addr:housenumber":"246",
    "addr:postcode":"83211",
    "addr:street":"Roosevelt St",
    "iso:country":"US",
    "sg:address":"246 Roosevelt St",
    "sg:city":"American Falls",
    "sg:classifiers":[
        {
            "category":"Farming",
            "subcategory":"Livestock Farm",
            "type":"Manufacturing & Wholesale Goods"
        }
    ],
    "sg:phone":"+1 208 226 2611",
    "sg:postcode":"83211",
    "sg:province":"ID",
    "sg:tags":[
        "ranch"
    ],
    "wof:name":"Bowler Ranches Inc",
    "wof:placetype":"venue"
},
  "geometry": {"coordinates":[-112.85431,42.78314],"type":"Point"}
}