{
  "type": "Feature",
  "properties": {
    "addr:full":"3174 N 3375 E Kimberly ID 83341",
    "addr:housenumber":"3174;3375 e",
    "addr:postcode":"83341",
    "addr:street":"N",
    "iso:country":"US",
    "sg:address":"3174 N 3375 E",
    "sg:city":"Kimberly",
    "sg:classifiers":[
        {
            "category":"Building & Trades",
            "subcategory":"Construction",
            "type":"Services"
        }
    ],
    "sg:phone":"+1 208 539 2231",
    "sg:postcode":"83341",
    "sg:province":"ID",
    "sg:tags":[
        "painter"
    ],
    "wof:name":"Larry Lattin Painting",
    "wof:placetype":"venue"
},
  "geometry": {"coordinates":[-114.388386,42.459335],"type":"Point"}
}