{
  "type": "Feature",
  "properties": {
    "iso:country":"US",
    "sg:address":"1428 G St",
    "sg:city":"Lewiston",
    "sg:classifiers":[
        {
            "category":"Insurance",
            "subcategory":"Title Insurance",
            "type":"Services"
        }
    ],
    "sg:phone":"+1 208 746 2323",
    "sg:postcode":"83501",
    "sg:province":"ID",
    "sg:website":"www.firstam.com",
    "wof:name":"First American Title Ins Co",
    "wof:placetype":"venue"
},
  "geometry": {"coordinates":[-117.013316,46.416601],"type":"Point"}
}