{
  "type": "Feature",
  "properties": {
    "iso:country":"US",
    "sg:address":"705 W Hwy 39",
    "sg:city":"Blackfoot",
    "sg:classifiers":[
        {
            "category":"Retail",
            "subcategory":"Auto Repair",
            "type":"Services"
        }
    ],
    "sg:phone":"+1 208 684 4376",
    "sg:postcode":"83221",
    "sg:province":"ID",
    "sg:tags":[
        "repairing",
        "automobile"
    ],
    "wof:name":"Countryside Auto Care",
    "wof:placetype":"venue"
},
  "geometry": {"coordinates":[-112.440033,43.196723],"type":"Point"}
}