{
  "type": "Feature",
  "properties": {
    "iso:country":"US",
    "sg:address":"2728 11th Ave",
    "sg:city":"Lewiston",
    "sg:classifiers":[
        {
            "category":"Taxi",
            "type":"Transportation"
        }
    ],
    "sg:phone":"+1 208 743 3222",
    "sg:postcode":"83501",
    "sg:province":"ID",
    "sg:tags":[
        "taxicab",
        "airport"
    ],
    "wof:name":"Aaa Ride Cab",
    "wof:placetype":"venue"
},
  "geometry": {"coordinates":[-116.993601,46.40934],"type":"Point"}
}