{
  "type": "Feature",
  "properties": {
    "iso:country":"US",
    "sg:address":"24 Heinrich Ln",
    "sg:city":"Mccall",
    "sg:classifiers":[
        {
            "category":"Freight",
            "type":"Transportation"
        }
    ],
    "sg:phone":"+1 208 630 4074",
    "sg:postcode":"83638",
    "sg:province":"ID",
    "sg:tags":[
        "local",
        "hauling",
        "trucking"
    ],
    "wof:name":"CTW Trucking Inc",
    "wof:placetype":"venue"
},
  "geometry": {"coordinates":[-116.09358400000001,44.847075],"type":"Point"}
}