{
  "type": "Feature",
  "properties": {
    "addr:full":"8303 Caswell St Boise ID 83714",
    "addr:housenumber":"8303",
    "addr:postcode":"83714",
    "addr:street":"Caswell St",
    "iso:country":"US",
    "sg:address":"8303 Caswell St",
    "sg:city":"Boise",
    "sg:classifiers":[
        {
            "category":"Manufacturing",
            "subcategory":"Chemicals & Compounds",
            "type":"Manufacturing & Wholesale Goods"
        },
        {
            "category":"Personal",
            "subcategory":"Beauty Salon",
            "type":"Services"
        }
    ],
    "sg:phone":"+1 208 853 1415",
    "sg:postcode":"83714",
    "sg:province":"ID",
    "sg:tags":[
        "mfg"
    ],
    "wof:name":"Sawtooth Wax Products Inc",
    "wof:placetype":"venue"
},
  "geometry": {"coordinates":[-116.28908300000001,43.679089],"type":"Point"}
}