{
  "type": "Feature",
  "properties": {
    "iso:country":"US",
    "sg:address":"1400 S Blaine St",
    "sg:city":"Moscow",
    "sg:classifiers":[
        {
            "category":"Restaurant",
            "type":"Food & Drink"
        }
    ],
    "sg:menulink":"http://www.allmenus.com/id/moscow/198414-kfc---kentucky-fried-chicken/menu/",
    "sg:phone":"+1 208 882 8363",
    "sg:postcode":"83843",
    "sg:province":"ID",
    "sg:tags":[
        "american",
        "chicken"
    ],
    "wof:name":"KFC - Kentucky Fried Chicken",
    "wof:placetype":"venue"
},
  "geometry": {"coordinates":[-116.98564,46.721638],"type":"Point"}
}