{
  "type": "Feature",
  "properties": {
    "iso:country":"US",
    "sg:address":"2320 Galey St",
    "sg:city":"Meridian",
    "sg:classifiers":[
        {
            "category":"Health Services",
            "subcategory":"Chiropractor",
            "type":"Services"
        }
    ],
    "sg:phone":"+1 208 461 8200",
    "sg:postcode":"83672",
    "sg:province":"ID",
    "wof:name":"Adam Austin Chiropractic",
    "wof:placetype":"venue"
},
  "geometry": {"coordinates":[-116.981334,44.26427],"type":"Point"}
}