{
  "type": "Feature",
  "properties": {
    "addr:full":"890 Oxford Dr Idaho Falls ID 83401",
    "addr:housenumber":"890",
    "addr:postcode":"83401",
    "addr:street":"Oxford Dr",
    "iso:country":"US",
    "sg:address":"890 Oxford Dr",
    "sg:city":"Idaho Falls",
    "sg:classifiers":[
        {
            "category":"Health Services",
            "subcategory":"Doctor",
            "type":"Services"
        }
    ],
    "sg:phone":"+1 208 523 3060",
    "sg:postcode":"83401",
    "sg:province":"ID",
    "sg:tags":[
        "physician",
        "surgeon"
    ],
    "wof:name":"Medical Center For Children",
    "wof:placetype":"venue"
},
  "geometry": {"coordinates":[-112.006815,43.490403],"type":"Point"}
}