{
  "type": "Feature",
  "properties": {
    "iso:country":"US",
    "sg:address":"1247 E Fairview Ave",
    "sg:city":"Meridian",
    "sg:classifiers":[
        {
            "category":"Retail",
            "subcategory":"Laundry & Dry Cleaning",
            "type":"Services"
        }
    ],
    "sg:phone":"+1 208 884 2066",
    "sg:postcode":"83642",
    "sg:province":"ID",
    "sg:tags":[
        "cleaners",
        "rug",
        "carpet"
    ],
    "wof:name":"Centennial Carpet & Upholstery",
    "wof:placetype":"venue"
},
  "geometry": {"coordinates":[-116.37927999999999,43.619393],"type":"Point"}
}