{
  "type": "Feature",
  "properties": {
    "iso:country":"US",
    "sg:address":"682 N 2858 E",
    "sg:city":"Roberts",
    "sg:classifiers":[
        {
            "category":"Education",
            "subcategory":"School",
            "type":"Public Place"
        }
    ],
    "sg:phone":"+1 208 228 3111",
    "sg:postcode":"83444",
    "sg:province":"ID",
    "sg:website":"www.d251.k12.id.us",
    "wof:name":"Roberts Elementary School",
    "wof:placetype":"venue"
},
  "geometry": {"coordinates":[-112.130835,43.723951],"type":"Point"}
}