{
  "type": "Feature",
  "properties": {
    "addr:full":"2302 Bogus Basin Rd Boise ID 83702",
    "addr:housenumber":"2302",
    "addr:postcode":"83702",
    "addr:street":"Bogus Basin Rd",
    "iso:country":"US",
    "sg:address":"2302 Bogus Basin Rd",
    "sg:city":"Boise",
    "sg:classifiers":[
        {
            "category":"Insurance",
            "subcategory":"Insurance Agent",
            "type":"Services"
        }
    ],
    "sg:phone":"+1 208 344 6900",
    "sg:postcode":"83702",
    "sg:province":"ID",
    "wof:name":"State Farm Insurance",
    "wof:placetype":"venue"
},
  "geometry": {"coordinates":[-116.208202,43.641036],"type":"Point"}
}