{
  "type": "Feature",
  "properties": {
    "addr:full":"840 Park Ave Idaho Falls ID 83402",
    "addr:housenumber":"840",
    "addr:postcode":"83402",
    "addr:street":"Park Ave",
    "iso:country":"US",
    "sg:address":"840 Park Ave",
    "sg:city":"Idaho Falls",
    "sg:classifiers":[
        {
            "category":"Social Services",
            "type":"Services"
        }
    ],
    "sg:phone":"+1 208 552 5575",
    "sg:postcode":"83402",
    "sg:province":"ID",
    "sg:tags":[
        "shelter",
        "homeless"
    ],
    "wof:name":"City Of Refuge",
    "wof:placetype":"venue"
},
  "geometry": {"coordinates":[-112.03794000000001,43.496158],"type":"Point"}
}