{
  "type": "Feature",
  "properties": {
    "addr:full":"6438 Supply Way Boise ID 83716",
    "addr:postcode":"83716",
    "addr:street":"Way",
    "iso:country":"US",
    "sg:address":"6438 Supply Way",
    "sg:city":"Boise",
    "sg:classifiers":[
        {
            "category":"Retail",
            "subcategory":"Auto Repair",
            "type":"Services"
        }
    ],
    "sg:phone":"+1 208 368 0461",
    "sg:postcode":"83716",
    "sg:province":"ID",
    "sg:tags":[
        "automobile",
        "co",
        "drive",
        "transporter"
    ],
    "sg:website":"www.whitecloudauto.com",
    "wof:name":"White Cloud Auto Transport Inc",
    "wof:placetype":"venue"
},
  "geometry": {"coordinates":[-116.180874,43.539671],"type":"Point"}
}