{
  "type": "Feature",
  "properties": {
    "addr:full":"2517 N Pioneer Ridge Dr Post Falls ID 83854",
    "addr:housenumber":"2517",
    "addr:postcode":"83854",
    "addr:street":"N Pioneer Ridge Dr",
    "iso:country":"US",
    "sg:address":"2517 N Pioneer Ridge Dr",
    "sg:city":"Post Falls",
    "sg:classifiers":[
        {
            "category":"Professional",
            "subcategory":"Computer Services",
            "type":"Services"
        }
    ],
    "sg:phone":"+1 208 773 9622",
    "sg:postcode":"83854",
    "sg:province":"ID",
    "sg:tags":[
        "datum",
        "internet"
    ],
    "wof:name":"Dot Com Enterprises",
    "wof:placetype":"venue"
},
  "geometry": {"coordinates":[-116.95211500000001,47.732002],"type":"Point"}
}