{
  "type": "Feature",
  "properties": {
    "iso:country":"US",
    "sg:address":"502 Tyhee Ave",
    "sg:city":"American Falls",
    "sg:classifiers":[
        {
            "category":"Government",
            "subcategory":"Office",
            "type":"Public Place"
        }
    ],
    "sg:phone":"+1 208 226 5186",
    "sg:postcode":"83211",
    "sg:province":"ID",
    "sg:tags":[
        "state",
        "resource"
    ],
    "wof:name":"Health & Welfare Dept",
    "wof:placetype":"venue"
},
  "geometry": {"coordinates":[-112.851838,42.784623],"type":"Point"}
}