{
  "type": "Feature",
  "properties": {
    "iso:country":"US",
    "sg:address":"1502 W Karcher Rd",
    "sg:city":"Nampa",
    "sg:classifiers":[
        {
            "category":"Autos & Motor Vehicles",
            "subcategory":"Automobile Sales",
            "type":"Retail Goods"
        }
    ],
    "sg:phone":"+1 208 463 1048",
    "sg:postcode":"83651",
    "sg:province":"ID",
    "sg:tags":[
        "truck"
    ],
    "wof:name":"Don Freeman Equipment",
    "wof:placetype":"venue"
},
  "geometry": {"coordinates":[-116.600149,43.605062],"type":"Point"}
}