{
  "type": "Feature",
  "properties": {
    "iso:country":"US",
    "sg:address":"515 S 4th E",
    "sg:city":"Preston",
    "sg:classifiers":[
        {
            "category":"Social Services",
            "subcategory":"Child Care",
            "type":"Services"
        }
    ],
    "sg:phone":"+1 208 852 3012",
    "sg:postcode":"83263",
    "sg:province":"ID",
    "sg:tags":[
        "kindergarten",
        "academic",
        "school"
    ],
    "wof:name":"Head Start-Preston Ctr",
    "wof:placetype":"venue"
},
  "geometry": {"coordinates":[-111.86678999999999,42.086769],"type":"Point"}
}