{
  "type": "Feature",
  "properties": {
    "iso:country":"US",
    "sg:address":"206 Courthouse Dr",
    "sg:city":"Salmon",
    "sg:classifiers":[
        {
            "category":"Government",
            "subcategory":"Office",
            "type":"Public Place"
        }
    ],
    "sg:phone":"+1 208 756 6441",
    "sg:postcode":"83467",
    "sg:province":"ID",
    "sg:tags":[
        "county",
        "program"
    ],
    "wof:name":"Lemhi County Solid Waste",
    "wof:placetype":"venue"
},
  "geometry": {"coordinates":[-113.90109200000001,45.17889],"type":"Point"}
}