{
  "type": "Feature",
  "properties": {
    "iso:country":"US",
    "sg:address":"1777 Gekeler Ln",
    "sg:city":"Boise",
    "sg:classifiers":[
        {
            "category":"Real Estate",
            "subcategory":"Real Estate Agent",
            "type":"Services"
        }
    ],
    "sg:phone":"+1 208 342 0035",
    "sg:postcode":"83706",
    "sg:province":"ID",
    "wof:name":"Garrett Properties",
    "wof:placetype":"venue"
},
  "geometry": {"coordinates":[-116.182197,43.592994],"type":"Point"}
}