{
  "type": "Feature",
  "properties": {
    "addr:full":"1206 Huckleberry Ave Sandpoint ID 83864",
    "addr:housenumber":"1206",
    "addr:postcode":"83864",
    "addr:street":"Huckleberry Ave",
    "iso:country":"US",
    "sg:address":"1206 Huckleberry Ave",
    "sg:city":"Sandpoint",
    "sg:classifiers":[
        {
            "category":"Shopping",
            "subcategory":"Crafts & Fabrics",
            "type":"Retail Goods"
        }
    ],
    "sg:phone":"+1 208 263 8326",
    "sg:postcode":"83864",
    "sg:province":"ID",
    "sg:tags":[
        "sewing"
    ],
    "wof:name":"Alisaras Needlecraft",
    "wof:placetype":"venue"
},
  "geometry": {"coordinates":[-116.56979699999999,48.284501],"type":"Point"}
}