{
  "type": "Feature",
  "properties": {
    "addr:full":"104 S Warpath St Salmon ID 83467",
    "addr:housenumber":"104",
    "addr:postcode":"83467",
    "addr:street":"S Warpath St",
    "iso:country":"US",
    "sg:address":"104 S Warpath St",
    "sg:city":"Salmon",
    "sg:classifiers":[
        {
            "category":"Real Estate",
            "subcategory":"Surveying",
            "type":"Services"
        }
    ],
    "sg:phone":"+1 208 756 3070",
    "sg:postcode":"83467",
    "sg:province":"ID",
    "sg:tags":[
        "surveyor"
    ],
    "wof:name":"Wade Surveying",
    "wof:placetype":"venue"
},
  "geometry": {"coordinates":[-113.88402000000001,45.171744],"type":"Point"}
}