{
  "type": "Feature",
  "properties": {
    "addr:full":"317 Happy Day Blvd Caldwell ID 83607",
    "addr:housenumber":"317",
    "addr:postcode":"83607",
    "addr:street":"Happy Day Blvd",
    "iso:country":"US",
    "sg:address":"317 Happy Day Blvd",
    "sg:city":"Caldwell",
    "sg:classifiers":[
        {
            "category":"Organizations",
            "subcategory":"Professional Association",
            "type":"Services"
        }
    ],
    "sg:phone":"+1 208 454 1652",
    "sg:postcode":"83607",
    "sg:province":"ID",
    "wof:name":"Idaho Migrant Council",
    "wof:placetype":"venue"
},
  "geometry": {"coordinates":[-116.63340700000001,43.627693],"type":"Point"}
}