{
  "type": "Feature",
  "properties": {
    "iso:country":"US",
    "sg:address":"16 Rocky Spring Rd",
    "sg:city":"Boise",
    "sg:classifiers":[
        {
            "category":"Building & Trades",
            "subcategory":"Construction",
            "type":"Services"
        }
    ],
    "sg:phone":"+1 208 345 2156",
    "sg:postcode":"83716",
    "sg:province":"ID",
    "sg:tags":[
        "hanging",
        "contractor"
    ],
    "wof:name":"J & L Painting LLC",
    "wof:placetype":"venue"
},
  "geometry": {"coordinates":[-116.04120899999999,43.668945],"type":"Point"}
}