{
  "type": "Feature",
  "properties": {
    "addr:full":"255 N 2100 W Malad City ID 83252",
    "addr:housenumber":"255",
    "addr:postcode":"83252",
    "addr:street":"N 2100 W Malad",
    "iso:country":"US",
    "sg:address":"255 N 2100 W",
    "sg:city":"Malad City",
    "sg:classifiers":[
        {
            "category":"Professional",
            "type":"Services"
        }
    ],
    "sg:phone":"+1 208 766 5323",
    "sg:postcode":"83252",
    "sg:province":"ID",
    "wof:name":"Sierra Wind Dancer Art",
    "wof:placetype":"venue"
},
  "geometry": {"coordinates":[-112.286958,42.187104],"type":"Point"}
}