{
  "type": "Feature",
  "properties": {
    "iso:country":"US",
    "sg:address":"110 Addison Ave",
    "sg:city":"Twin Falls",
    "sg:classifiers":[
        {
            "category":"Restaurant",
            "type":"Food & Drink"
        }
    ],
    "sg:menulink":"http://www.allmenus.com/id/twin-falls/212119-mcdonalds/menu/",
    "sg:postcode":"83301",
    "sg:province":"ID",
    "sg:tags":[
        "burger",
        "american"
    ],
    "wof:name":"McDonald's",
    "wof:placetype":"venue"
},
  "geometry": {"coordinates":[-114.479676,42.563076],"type":"Point"}
}