{
  "type": "Feature",
  "properties": {
    "iso:country":"US",
    "sg:address":"3055 S Shortleaf Ave",
    "sg:city":"Boise",
    "sg:classifiers":[
        {
            "category":"Professional",
            "subcategory":"Management & Consulting",
            "type":"Services"
        }
    ],
    "sg:phone":"+1 208 338 5226",
    "sg:postcode":"83716",
    "sg:province":"ID",
    "sg:tags":[
        "business"
    ],
    "wof:name":"At Consulting",
    "wof:placetype":"venue"
},
  "geometry": {"coordinates":[-116.123567,43.573778],"type":"Point"}
}