{
  "type": "Feature",
  "properties": {
    "iso:country":"US",
    "sg:address":"81 N Shilling Ave",
    "sg:city":"Blackfoot",
    "sg:classifiers":[
        {
            "category":"Restaurant",
            "type":"Food & Drink"
        }
    ],
    "sg:phone":"+1 208 785 3606",
    "sg:postcode":"83221",
    "sg:province":"ID",
    "wof:name":"Shilling House",
    "wof:placetype":"venue"
},
  "geometry": {"coordinates":[-112.342832,43.187705],"type":"Point"}
}