{
  "type": "Feature",
  "properties": {
    "iso:country":"US",
    "sg:address":"4618 W State St",
    "sg:city":"Boise",
    "sg:classifiers":[
        {
            "category":"Shopping",
            "subcategory":"Department Store",
            "type":"Retail Goods"
        }
    ],
    "sg:phone":"+1 208 344 9042",
    "sg:postcode":"83703",
    "sg:province":"ID",
    "sg:tags":[
        "shop"
    ],
    "wof:name":"Thursday",
    "wof:placetype":"venue"
},
  "geometry": {"coordinates":[-116.24830900000001,43.649355],"type":"Point"}
}