{
  "type": "Feature",
  "properties": {
    "iso:country":"US",
    "sg:address":"3111 N Wright Rd",
    "sg:city":"Idaho Falls",
    "sg:classifiers":[
        {
            "category":"Building & Trades",
            "subcategory":"Construction",
            "type":"Services"
        }
    ],
    "sg:phone":"+1 208 523 3202",
    "sg:postcode":"83401",
    "sg:province":"ID",
    "sg:tags":[
        "general",
        "contractor"
    ],
    "wof:name":"Taylor Construction",
    "wof:placetype":"venue"
},
  "geometry": {"coordinates":[-112.01751899999999,43.52331],"type":"Point"}
}