{
  "type": "Feature",
  "properties": {
    "addr:full":"2519 Iowa Ave Caldwell ID 83605",
    "addr:housenumber":"2519",
    "addr:postcode":"83605",
    "addr:street":"Iowa Ave",
    "iso:country":"US",
    "sg:address":"2519 Iowa Ave",
    "sg:city":"Caldwell",
    "sg:classifiers":[
        {
            "category":"Retail",
            "subcategory":"Animal Services",
            "type":"Services"
        }
    ],
    "sg:phone":"+1 208 459 0794",
    "sg:postcode":"83605",
    "sg:province":"ID",
    "wof:name":"All Creatures Great & Small",
    "wof:placetype":"venue"
},
  "geometry": {"coordinates":[-116.679151,43.647903],"type":"Point"}
}