{
  "type": "Feature",
  "properties": {
    "addr:full":"13895 Nounan Rd Soda Springs ID 83276",
    "addr:housenumber":"13895",
    "addr:postcode":"83276",
    "addr:street":"Nounan Rd",
    "iso:country":"US",
    "sg:address":"13895 Nounan Rd",
    "sg:city":"Soda Springs",
    "sg:classifiers":[
        {
            "category":"Shopping",
            "subcategory":"Catalog Store",
            "type":"Retail Goods"
        }
    ],
    "sg:phone":"+1 208 547 3885",
    "sg:postcode":"83276",
    "sg:province":"ID",
    "sg:tags":[
        "house",
        "mail",
        "telephone",
        "communications"
    ],
    "wof:name":"Quick Start",
    "wof:placetype":"venue"
},
  "geometry": {"coordinates":[-111.51931399999999,42.583269],"type":"Point"}
}