{
  "type": "Feature",
  "properties": {
    "iso:country":"US",
    "sg:address":"1435 Desmet Rd",
    "sg:city":"Desmet",
    "sg:classifiers":[
        {
            "category":"Place Of Worship",
            "type":"Public Place"
        }
    ],
    "sg:phone":"+1 208 274 2241",
    "sg:postcode":"83824",
    "sg:province":"ID",
    "sg:tags":[
        "church"
    ],
    "wof:name":"Church Of Grail",
    "wof:placetype":"venue"
},
  "geometry": {"coordinates":[-116.969185,47.14888],"type":"Point"}
}