{
  "type": "Feature",
  "properties": {
    "addr:full":"10468 Chicken Dinner Rd Caldwell ID 83607",
    "addr:housenumber":"10468",
    "addr:postcode":"83607",
    "addr:street":"Chicken Dinner Rd",
    "iso:country":"US",
    "sg:address":"10468 Chicken Dinner Rd",
    "sg:city":"Caldwell",
    "sg:classifiers":[
        {
            "category":"Restaurant",
            "type":"Food & Drink"
        }
    ],
    "sg:phone":"+1 208 459 7754",
    "sg:postcode":"83607",
    "sg:province":"ID",
    "sg:tags":[
        "eating"
    ],
    "wof:name":"Chicken Dinner Arena Inc",
    "wof:placetype":"venue"
},
  "geometry": {"coordinates":[-116.772201,43.517306],"type":"Point"}
}