{
  "type": "Feature",
  "properties": {
    "iso:country":"US",
    "sg:address":"2127 SE 3rd Way",
    "sg:city":"Meridian",
    "sg:classifiers":[
        {
            "category":"Autos & Motor Vehicles",
            "subcategory":"Fuel & Gas Station",
            "type":"Retail Goods"
        }
    ],
    "sg:phone":"+1 208 412 3384",
    "sg:postcode":"83642",
    "sg:province":"ID",
    "wof:name":"Color Fill Inc",
    "wof:placetype":"venue"
},
  "geometry": {"coordinates":[-116.388115,43.584488],"type":"Point"}
}