{
  "type": "Feature",
  "properties": {
    "iso:country":"US",
    "sg:address":"1107 S 5th Ave",
    "sg:city":"Pocatello",
    "sg:classifiers":[
        {
            "category":"Food & Beverages",
            "subcategory":"Groceries & Convenience Stores",
            "type":"Retail Goods"
        }
    ],
    "sg:phone":"+1 208 232 0330",
    "sg:postcode":"83201",
    "sg:province":"ID",
    "wof:name":"Jackson's Food",
    "wof:placetype":"venue"
},
  "geometry": {"coordinates":[-112.434057,42.858237],"type":"Point"}
}