{
  "type": "Feature",
  "properties": {
    "iso:country":"US",
    "sg:address":"1008 S Park Ave W",
    "sg:city":"Twin Falls",
    "sg:classifiers":[
        {
            "category":"Shopping",
            "subcategory":"Department Store",
            "type":"Retail Goods"
        }
    ],
    "sg:phone":"+1 208 543 5402",
    "sg:postcode":"83301",
    "sg:province":"ID",
    "sg:tags":[
        "shop"
    ],
    "wof:name":"One Dollar Buys",
    "wof:placetype":"venue"
},
  "geometry": {"coordinates":[-114.50050899999999,42.549861],"type":"Point"}
}