{
  "type": "Feature",
  "properties": {
    "iso:country":"US",
    "sg:address":"701 Jackson Ave",
    "sg:city":"Priest River",
    "sg:classifiers":[
        {
            "category":"Organizations",
            "subcategory":"Religious Organization",
            "type":"Services"
        }
    ],
    "sg:phone":"+1 208 448 1861",
    "sg:postcode":"83856",
    "sg:province":"ID",
    "sg:tags":[
        "church"
    ],
    "wof:name":"Living Hope Methodist Church",
    "wof:placetype":"venue"
},
  "geometry": {"coordinates":[-116.914466,48.181948],"type":"Point"}
}