{
  "type": "Feature",
  "properties": {
    "iso:country":"US",
    "sg:address":"9421 Desert Ave",
    "sg:city":"Boise",
    "sg:classifiers":[
        {
            "category":"Banks & Credit Unions",
            "subcategory":"Investment Brokerage",
            "type":"Services"
        }
    ],
    "sg:phone":"+1 208 362 5545",
    "sg:postcode":"83709",
    "sg:province":"ID",
    "sg:tags":[
        "advisory"
    ],
    "wof:name":"Dream Makers",
    "wof:placetype":"venue"
},
  "geometry": {"coordinates":[-116.300376,43.553747],"type":"Point"}
}