{
  "type": "Feature",
  "properties": {
    "iso:country":"US",
    "sg:address":"72 S 200 W",
    "sg:city":"Burley",
    "sg:classifiers":[
        {
            "category":"Building & Trades",
            "subcategory":"Electrical",
            "type":"Services"
        }
    ],
    "sg:phone":"+1 208 678 9655",
    "sg:postcode":"83318",
    "sg:province":"ID",
    "sg:tags":[
        "electric",
        "contractor"
    ],
    "wof:name":"Harris Refrigeration Heating",
    "wof:placetype":"venue"
},
  "geometry": {"coordinates":[-113.83318800000001,42.522538],"type":"Point"}
}