{
  "type": "Feature",
  "properties": {
    "addr:full":"30 S Maple St Blackfoot ID 83221",
    "addr:housenumber":"30",
    "addr:postcode":"83221",
    "addr:street":"S Maple St",
    "iso:country":"US",
    "sg:address":"30 S Maple St",
    "sg:city":"Blackfoot",
    "sg:classifiers":[
        {
            "category":"Retail",
            "subcategory":"Car Wash",
            "type":"Services"
        }
    ],
    "sg:phone":"+1 208 785 4450",
    "sg:postcode":"83221",
    "sg:province":"ID",
    "sg:tags":[
        "automobile",
        "detail",
        "clean"
    ],
    "wof:name":"Cortez Auto Detail",
    "wof:placetype":"venue"
},
  "geometry": {"coordinates":[-112.348156,43.190287],"type":"Point"}
}