{
  "type": "Feature",
  "properties": {
    "iso:country":"US",
    "sg:address":"400 Benjamin Ln",
    "sg:city":"Boise",
    "sg:classifiers":[
        {
            "category":"Real Estate",
            "subcategory":"Real Estate Agent",
            "type":"Services"
        }
    ],
    "sg:phone":"+1 208 322 9237",
    "sg:postcode":"83704",
    "sg:province":"ID",
    "wof:name":"Peterson Properties LP",
    "wof:placetype":"venue"
},
  "geometry": {"coordinates":[-116.288078,43.610142],"type":"Point"}
}