{
  "type": "Feature",
  "properties": {
    "addr:full":"3713 Garrity Blvd Nampa ID 83687",
    "addr:housenumber":"3713",
    "addr:postcode":"83687",
    "addr:street":"Garrity Blvd",
    "iso:country":"US",
    "sg:address":"3713 Garrity Blvd",
    "sg:city":"Nampa",
    "sg:classifiers":[
        {
            "category":"Retail",
            "subcategory":"Repair Shop",
            "type":"Services"
        }
    ],
    "sg:phone":"+1 208 466 7875",
    "sg:postcode":"83687",
    "sg:province":"ID",
    "sg:tags":[
        "tractor"
    ],
    "wof:name":"Burks Tractor Co Inc",
    "wof:placetype":"venue"
},
  "geometry": {"coordinates":[-116.525766,43.590619],"type":"Point"}
}