{
  "type": "Feature",
  "properties": {
    "iso:country":"US",
    "sg:address":"8350 S Jardine Ln",
    "sg:city":"Meridian",
    "sg:classifiers":[
        {
            "category":"Autos & Motor Vehicles",
            "subcategory":"Motorcycle Sales",
            "type":"Retail Goods"
        }
    ],
    "sg:phone":"+1 208 887 6460",
    "sg:postcode":"83642",
    "sg:province":"ID",
    "sg:tags":[
        "scooter"
    ],
    "wof:name":"Race & Trail Products",
    "wof:placetype":"venue"
},
  "geometry": {"coordinates":[-116.384091,43.531533],"type":"Point"}
}