{
  "type": "Feature",
  "properties": {
    "addr:full":"401 River St Wallace ID 83873",
    "addr:housenumber":"401",
    "addr:postcode":"83873",
    "addr:street":"River St",
    "iso:country":"US",
    "sg:address":"401 River St",
    "sg:city":"Wallace",
    "sg:classifiers":[
        {
            "category":"Education",
            "subcategory":"School",
            "type":"Public Place"
        }
    ],
    "sg:phone":"+1 208 752 3305",
    "sg:postcode":"83873",
    "sg:province":"ID",
    "wof:name":"Silver Valley Schl To Work Off",
    "wof:placetype":"venue"
},
  "geometry": {"coordinates":[-115.926991,47.474042],"type":"Point"}
}