{
  "type": "Feature",
  "properties": {
    "addr:full":"1609 12th Ave Rd Nampa ID 83686",
    "addr:housenumber":"1609",
    "addr:postcode":"83686",
    "addr:street":"12Th Ave Rd",
    "iso:country":"US",
    "sg:address":"1609 12th Ave Rd",
    "sg:city":"Nampa",
    "sg:classifiers":[
        {
            "category":"Health Services",
            "subcategory":"Doctor",
            "type":"Services"
        }
    ],
    "sg:phone":"+1 208 467 5259",
    "sg:postcode":"83686",
    "sg:province":"ID",
    "sg:tags":[
        "dentist"
    ],
    "wof:name":"Nampa-Caldwell Orthodontics",
    "wof:placetype":"venue"
},
  "geometry": {"coordinates":[-116.572963,43.553404],"type":"Point"}
}