{
  "type": "Feature",
  "properties": {
    "iso:country":"US",
    "sg:address":"1620 W Broadway St",
    "sg:city":"Idaho Falls",
    "sg:classifiers":[
        {
            "category":"Shopping",
            "subcategory":"Florist",
            "type":"Retail Goods"
        }
    ],
    "sg:phone":"+1 208 522 1483",
    "sg:postcode":"83402",
    "sg:province":"ID",
    "wof:name":"City Floral Shop",
    "wof:placetype":"venue"
},
  "geometry": {"coordinates":[-112.063668,43.49686],"type":"Point"}
}