{
  "type": "Feature",
  "properties": {
    "iso:country":"US",
    "sg:address":"4055 Professional Way",
    "sg:city":"Idaho Falls",
    "sg:classifiers":[
        {
            "category":"Shopping",
            "subcategory":"Computers & Home Electronics",
            "type":"Retail Goods"
        }
    ],
    "sg:phone":"+1 208 528 0205",
    "sg:postcode":"83402",
    "sg:province":"ID",
    "sg:tags":[
        "equipment",
        "satellite",
        "system"
    ],
    "wof:name":"Star West Satellite",
    "wof:placetype":"venue"
},
  "geometry": {"coordinates":[-112.059774,43.461122],"type":"Point"}
}