{
  "type": "Feature",
  "properties": {
    "iso:country":"US",
    "sg:address":"475 Yellowstone Ave",
    "sg:city":"Pocatello",
    "sg:classifiers":[
        {
            "category":"Personal",
            "type":"Services"
        }
    ],
    "sg:phone":"+1 208 478 1700",
    "sg:postcode":"83201",
    "sg:province":"ID",
    "sg:tags":[
        "bankruptcy"
    ],
    "wof:name":"Bankruptcy Petition Preparer",
    "wof:placetype":"venue"
},
  "geometry": {"coordinates":[-112.451522,42.882811],"type":"Point"}
}