{
  "type": "Feature",
  "properties": {
    "addr:full":"4272 N Waterloo Ave Boise ID 83713",
    "addr:housenumber":"4272",
    "addr:postcode":"83713",
    "addr:street":"N Waterloo Ave",
    "iso:country":"US",
    "sg:address":"4272 N Waterloo Ave",
    "sg:city":"Boise",
    "sg:classifiers":[
        {
            "category":"Professional",
            "subcategory":"Business Services",
            "type":"Services"
        }
    ],
    "sg:phone":"+1 208 938 0623",
    "sg:postcode":"83713",
    "sg:province":"ID",
    "sg:tags":[
        "appraiser"
    ],
    "wof:name":"Kelly Temple Residential Appsl",
    "wof:placetype":"venue"
},
  "geometry": {"coordinates":[-116.34604899999999,43.641231],"type":"Point"}
}