{
  "type": "Feature",
  "properties": {
    "iso:country":"US",
    "sg:address":"980 S Lincoln Ave",
    "sg:city":"Jerome",
    "sg:classifiers":[
        {
            "category":"Banks & Credit Unions",
            "subcategory":"Bank",
            "type":"Services"
        }
    ],
    "sg:phone":"+1 208 324 5200",
    "sg:postcode":"83338",
    "sg:province":"ID",
    "sg:website":"www.dlevans.com",
    "wof:name":"D L Evans Bank",
    "wof:placetype":"venue"
},
  "geometry": {"coordinates":[-114.518327,42.715981],"type":"Point"}
}