{
  "type": "Feature",
  "properties": {
    "addr:full":"1673 Shoreline Dr Boise ID 83702",
    "addr:housenumber":"1673",
    "addr:postcode":"83702",
    "addr:street":"Shoreline Dr",
    "iso:country":"US",
    "sg:address":"1673 Shoreline Dr",
    "sg:city":"Boise",
    "sg:classifiers":[
        {
            "category":"Health Services",
            "subcategory":"Doctor",
            "type":"Services"
        }
    ],
    "sg:phone":"+1 208 429 8311",
    "sg:postcode":"83702",
    "sg:province":"ID",
    "sg:tags":[
        "physician",
        "surgeon"
    ],
    "wof:name":"St Alphonsus Med Group Shrln",
    "wof:placetype":"venue"
},
  "geometry": {"coordinates":[-116.22192200000001,43.617448],"type":"Point"}
}