{
  "type": "Feature",
  "properties": {
    "iso:country":"US",
    "sg:address":"4029 N Government Way",
    "sg:city":"Coeur D Alene",
    "sg:classifiers":[
        {
            "category":"Shopping",
            "subcategory":"Used Merchandise",
            "type":"Retail Goods"
        }
    ],
    "sg:phone":"+1 208 765 4689",
    "sg:postcode":"83815",
    "sg:province":"ID",
    "sg:tags":[
        "pawnbroker"
    ],
    "wof:name":"Shooter's Supply Gun & Loan",
    "wof:placetype":"venue"
},
  "geometry": {"coordinates":[-116.786726,47.715109],"type":"Point"}
}