{
  "type": "Feature",
  "properties": {
    "iso:country":"US",
    "sg:address":"190 E 2nd N",
    "sg:city":"Mountain Home",
    "sg:classifiers":[
        {
            "category":"Restaurant",
            "type":"Food & Drink"
        }
    ],
    "sg:phone":"+1 208 587 0885",
    "sg:postcode":"83647",
    "sg:province":"ID",
    "wof:name":"Dilly Deli",
    "wof:placetype":"venue"
},
  "geometry": {"coordinates":[-115.694767,43.131551],"type":"Point"}
}