{
  "type": "Feature",
  "properties": {
    "iso:country":"US",
    "sg:address":"477 Shoup Ave",
    "sg:city":"Idaho Falls",
    "sg:classifiers":[
        {
            "category":"Personal",
            "type":"Services"
        }
    ],
    "sg:phone":"+1 208 552 0505",
    "sg:postcode":"83402",
    "sg:province":"ID",
    "sg:tags":[
        "therapist",
        "massage"
    ],
    "wof:name":"Arapahoe Counseling & Massage",
    "wof:placetype":"venue"
},
  "geometry": {"coordinates":[-112.039427,43.492448],"type":"Point"}
}