{
  "type": "Feature",
  "properties": {
    "iso:country":"US",
    "sg:address":"401 Maurice St N",
    "sg:city":"Twin Falls",
    "sg:classifiers":[
        {
            "category":"Organizations",
            "subcategory":"Religious Organization",
            "type":"Services"
        }
    ],
    "sg:phone":"+1 208 733 3446",
    "sg:postcode":"83301",
    "sg:province":"ID",
    "wof:name":"L D S Employment Office",
    "wof:placetype":"venue"
},
  "geometry": {"coordinates":[-114.452922,42.569358],"type":"Point"}
}