{
  "type": "Feature",
  "properties": {
    "addr:full":"275 Sunrise Dr Moscow ID 83843",
    "addr:housenumber":"275",
    "addr:postcode":"83843",
    "addr:street":"Sunrise Dr",
    "iso:country":"US",
    "sg:address":"275 Sunrise Dr",
    "sg:city":"Moscow",
    "sg:classifiers":[
        {
            "category":"Structure",
            "subcategory":"Office Building",
            "type":"Public Place"
        }
    ],
    "sg:phone":"+1 208 882 8737",
    "sg:postcode":"83843",
    "sg:province":"ID",
    "sg:tags":[
        "park"
    ],
    "wof:name":"Saddle Ridge Properties",
    "wof:placetype":"venue"
},
  "geometry": {"coordinates":[-116.975219,46.735028],"type":"Point"}
}