{
  "type": "Feature",
  "properties": {
    "addr:full":"649 Golf Course Rd Jerome ID 83338",
    "addr:housenumber":"649",
    "addr:postcode":"83338",
    "addr:street":"Golf Course Rd",
    "iso:country":"US",
    "sg:address":"649 Golf Course Rd",
    "sg:city":"Jerome",
    "sg:classifiers":[
        {
            "category":"Restaurant",
            "type":"Food & Drink"
        }
    ],
    "sg:phone":"+1 208 324 5081",
    "sg:postcode":"83338",
    "sg:province":"ID",
    "sg:tags":[
        "eating"
    ],
    "wof:name":"T Box Restaurant & Lounge",
    "wof:placetype":"venue"
},
  "geometry": {"coordinates":[-114.50794,42.637021],"type":"Point"}
}