{
  "type": "Feature",
  "properties": {
    "addr:full":"524 Bank St Wallace ID 83873",
    "addr:housenumber":"524",
    "addr:postcode":"83873",
    "addr:street":"Bank St",
    "iso:country":"US",
    "sg:address":"524 Bank St",
    "sg:city":"Wallace",
    "sg:classifiers":[
        {
            "category":"Shopping",
            "subcategory":"Hobbies, Toys, & Games",
            "type":"Retail Goods"
        }
    ],
    "sg:phone":"+1 208 556 7081",
    "sg:postcode":"83873",
    "sg:province":"ID",
    "sg:tags":[
        "shop",
        "rock"
    ],
    "wof:name":"Silver Capital Arts",
    "wof:placetype":"venue"
},
  "geometry": {"coordinates":[-115.92508599999999,47.471531],"type":"Point"}
}