{
  "type": "Feature",
  "properties": {
    "iso:country":"US",
    "sg:address":"1023 Yellowstone Ave",
    "sg:city":"Pocatello",
    "sg:classifiers":[
        {
            "category":"Banks & Credit Unions",
            "subcategory":"Bank",
            "type":"Services"
        }
    ],
    "sg:phone":"+1 208 234 1918",
    "sg:postcode":"83201",
    "sg:province":"ID",
    "sg:tags":[
        "loan"
    ],
    "wof:name":"Check N Loan",
    "wof:placetype":"venue"
},
  "geometry": {"coordinates":[-112.45143,42.891467],"type":"Point"}
}