{
  "type": "Feature",
  "properties": {
    "iso:country":"US",
    "sg:address":"1255 E Main St",
    "sg:city":"Burley",
    "sg:classifiers":[
        {
            "category":"Wholesale",
            "subcategory":"Machinery & Supplies",
            "type":"Manufacturing & Wholesale Goods"
        }
    ],
    "sg:phone":"+1 208 678 2488",
    "sg:postcode":"83318",
    "sg:province":"ID",
    "sg:tags":[
        "equipment"
    ],
    "wof:name":"Mountain Meadow Sales",
    "wof:placetype":"venue"
},
  "geometry": {"coordinates":[-113.773781,42.537123],"type":"Point"}
}