{
  "type": "Feature",
  "properties": {
    "iso:country":"US",
    "sg:address":"125 S Curtis Rd",
    "sg:city":"Boise",
    "sg:classifiers":[
        {
            "category":"Personal",
            "subcategory":"Shoe Repair & Shine",
            "type":"Services"
        }
    ],
    "sg:phone":"+1 208 343 4242",
    "sg:postcode":"83705",
    "sg:province":"ID",
    "sg:tags":[
        "repairing",
        "boot"
    ],
    "wof:name":"Rosendahl Foot & Shoe Svc",
    "wof:placetype":"venue"
},
  "geometry": {"coordinates":[-116.25381299999999,43.601442],"type":"Point"}
}