{
  "type": "Feature",
  "properties": {
    "iso:country":"US",
    "sg:address":"1230 E 4100 N",
    "sg:city":"Buhl",
    "sg:phone":"+1 208 543 5096",
    "sg:postcode":"83316",
    "sg:province":"ID",
    "sg:tags":[
        "beef",
        "farm",
        "corn",
        "crop",
        "field",
        "cattle",
        "feedlot"
    ],
    "wof:name":"Owen Shriver",
    "wof:placetype":"venue"
},
  "geometry": {"coordinates":[-114.80528200000001,42.593322],"type":"Point"}
}