{
  "type": "Feature",
  "properties": {
    "addr:full":"5304 W State St Boise ID 83703",
    "addr:housenumber":"5304",
    "addr:postcode":"83703",
    "addr:street":"W State St",
    "iso:country":"US",
    "sg:address":"5304 W State St",
    "sg:city":"Boise",
    "sg:classifiers":[
        {
            "category":"Shopping",
            "subcategory":"Florist",
            "type":"Retail Goods"
        }
    ],
    "sg:phone":"+1 208 853 3232",
    "sg:postcode":"83703",
    "sg:province":"ID",
    "sg:website":"www.clufffloral.com",
    "wof:name":"Cluff Floral",
    "wof:placetype":"venue"
},
  "geometry": {"coordinates":[-116.25636,43.654517],"type":"Point"}
}