{
  "type": "Feature",
  "properties": {
    "iso:country":"US",
    "sg:address":"5059 Yellowstone Ave",
    "sg:city":"Chubbuck",
    "sg:classifiers":[
        {
            "category":"Food & Beverages",
            "subcategory":"Groceries & Convenience Stores",
            "type":"Retail Goods"
        }
    ],
    "sg:phone":"+1 208 237 5971",
    "sg:postcode":"83202",
    "sg:province":"ID",
    "wof:name":"Jackson's Food",
    "wof:placetype":"venue"
},
  "geometry": {"coordinates":[-112.466493,42.925601],"type":"Point"}
}