{
  "type": "Feature",
  "properties": {
    "iso:country":"US",
    "sg:address":"3075 Dairy Rd",
    "sg:city":"Weippe",
    "sg:classifiers":[
        {
            "category":"Building & Trades",
            "subcategory":"Construction",
            "type":"Services"
        }
    ],
    "sg:phone":"+1 208 435 0163",
    "sg:postcode":"83553",
    "sg:province":"ID",
    "sg:tags":[
        "hanging",
        "contractor"
    ],
    "wof:name":"Vanburen Painting",
    "wof:placetype":"venue"
},
  "geometry": {"coordinates":[-115.920329,46.339021],"type":"Point"}
}