{
  "type": "Feature",
  "properties": {
    "iso:country":"US",
    "sg:address":"6806 S Eisenman Rd",
    "sg:city":"Boise",
    "sg:classifiers":[
        {
            "category":"Shopping",
            "subcategory":"Department Store",
            "type":"Retail Goods"
        }
    ],
    "sg:phone":"+1 208 331 5000",
    "sg:postcode":"83716",
    "sg:province":"ID",
    "wof:name":"Boise Factory Outlet",
    "wof:placetype":"venue"
},
  "geometry": {"coordinates":[-116.164936,43.54162],"type":"Point"}
}