{
  "type": "Feature",
  "properties": {
    "iso:country":"US",
    "sg:address":"1605 G St",
    "sg:city":"Rupert",
    "sg:classifiers":[
        {
            "category":"Building & Trades",
            "subcategory":"Electrical",
            "type":"Services"
        }
    ],
    "sg:phone":"+1 208 436 4469",
    "sg:postcode":"83350",
    "sg:province":"ID",
    "sg:tags":[
        "electric",
        "contractor"
    ],
    "wof:name":"Dalry Electric Inc",
    "wof:placetype":"venue"
},
  "geometry": {"coordinates":[-113.67649,42.628661],"type":"Point"}
}