{
  "type": "Feature",
  "properties": {
    "iso:country":"US",
    "sg:address":"2880 Highway 95 S",
    "sg:city":"Moscow",
    "sg:classifiers":[
        {
            "category":"Personal",
            "subcategory":"Beauty Salon",
            "type":"Services"
        }
    ],
    "sg:phone":"+1 208 883 9775",
    "sg:postcode":"83843",
    "sg:province":"ID",
    "sg:tags":[
        "hair",
        "stylist"
    ],
    "wof:name":"Hair By Maria",
    "wof:placetype":"venue"
},
  "geometry": {"coordinates":[-117.004891,46.709374],"type":"Point"}
}