{
  "type": "Feature",
  "properties": {
    "iso:country":"US",
    "sg:address":"914 E Mullan Ave",
    "sg:city":"Coeur D Alene",
    "sg:classifiers":[
        {
            "category":"Building & Trades",
            "subcategory":"Landscaping Services",
            "type":"Services"
        }
    ],
    "sg:phone":"+1 208 667 1415",
    "sg:postcode":"83814",
    "sg:province":"ID",
    "sg:tags":[
        "landscape",
        "contractor"
    ],
    "wof:name":"Wes's Landscaping & Mntnc",
    "wof:placetype":"venue"
},
  "geometry": {"coordinates":[-116.77378899999999,47.671615],"type":"Point"}
}