{
  "type": "Feature",
  "properties": {
    "iso:country":"US",
    "sg:address":"1284 S Hwy 34",
    "sg:city":"Preston",
    "sg:classifiers":[
        {
            "category":"Manufacturing",
            "subcategory":"Textiles",
            "type":"Manufacturing & Wholesale Goods"
        }
    ],
    "sg:phone":"+1 208 852 3405",
    "sg:postcode":"83263",
    "sg:province":"ID",
    "sg:tags":[
        "product",
        "mfg"
    ],
    "wof:name":"Bevs Cottage",
    "wof:placetype":"venue"
},
  "geometry": {"coordinates":[-111.876672,42.073892],"type":"Point"}
}