{
  "type": "Feature",
  "properties": {
    "addr:full":"2908 Garrity Blvd Nampa ID 83687",
    "addr:housenumber":"2908",
    "addr:postcode":"83687",
    "addr:street":"Garrity Blvd",
    "iso:country":"US",
    "sg:address":"2908 Garrity Blvd",
    "sg:city":"Nampa",
    "sg:classifiers":[
        {
            "category":"Shopping",
            "subcategory":"Hobbies, Toys, & Games",
            "type":"Retail Goods"
        }
    ],
    "sg:phone":"+1 208 466 8173",
    "sg:postcode":"83687",
    "sg:province":"ID",
    "sg:tags":[
        "craft",
        "supply"
    ],
    "wof:name":"Hobby Center Inc",
    "wof:placetype":"venue"
},
  "geometry": {"coordinates":[-116.533069,43.587236],"type":"Point"}
}