{
  "type": "Feature",
  "properties": {
    "addr:full":"1915 N Elder St Nampa ID 83687",
    "addr:housenumber":"1915",
    "addr:postcode":"83687",
    "addr:street":"N Elder St",
    "iso:country":"US",
    "sg:address":"1915 N Elder St",
    "sg:city":"Nampa",
    "sg:classifiers":[
        {
            "category":"Home & Garden",
            "subcategory":"Furniture",
            "type":"Retail Goods"
        }
    ],
    "sg:phone":"+1 208 442 7112",
    "sg:postcode":"83687",
    "sg:province":"ID",
    "sg:tags":[
        "cabinet"
    ],
    "wof:name":"European Cabinetry & Millwk",
    "wof:placetype":"venue"
},
  "geometry": {"coordinates":[-116.559348,43.603999],"type":"Point"}
}