{
  "type": "Feature",
  "properties": {
    "addr:full":"348 Garfield St Idaho Falls ID 83401",
    "addr:housenumber":"348",
    "addr:postcode":"83401",
    "addr:street":"Garfield St",
    "iso:country":"US",
    "sg:address":"348 Garfield St",
    "sg:city":"Idaho Falls",
    "sg:classifiers":[
        {
            "category":"Home & Garden",
            "subcategory":"Building Materials",
            "type":"Retail Goods"
        }
    ],
    "sg:phone":"+1 208 547 3672",
    "sg:postcode":"83401",
    "sg:province":"ID",
    "sg:tags":[
        "glass",
        "window",
        "plate"
    ],
    "wof:name":"Diamond Glass",
    "wof:placetype":"venue"
},
  "geometry": {"coordinates":[-112.02775200000001,43.500413],"type":"Point"}
}