{
  "type": "Feature",
  "properties": {
    "iso:country":"US",
    "sg:address":"2120 Missman Rd",
    "sg:city":"Council",
    "sg:classifiers":[
        {
            "category":"Building & Trades",
            "subcategory":"Construction",
            "type":"Services"
        }
    ],
    "sg:phone":"+1 208 253 4622",
    "sg:postcode":"83612",
    "sg:province":"ID",
    "sg:tags":[
        "general",
        "contractor"
    ],
    "wof:name":"Testa Construction",
    "wof:placetype":"venue"
},
  "geometry": {"coordinates":[-116.422697,44.749312],"type":"Point"}
}