{
  "type": "Feature",
  "properties": {
    "iso:country":"US",
    "sg:address":"5507 el Gato Ln",
    "sg:city":"Meridian",
    "sg:classifiers":[
        {
            "category":"Building & Trades",
            "subcategory":"Plumbing",
            "type":"Services"
        }
    ],
    "sg:phone":"+1 208 888 1973",
    "sg:postcode":"83642",
    "sg:province":"ID",
    "sg:tags":[
        "plumbing",
        "contractor"
    ],
    "wof:name":"Pond's Plumbing & Heating Svc",
    "wof:placetype":"venue"
},
  "geometry": {"coordinates":[-116.46148599999999,43.613845],"type":"Point"}
}