{
  "type": "Feature",
  "properties": {
    "addr:full":"3553 Hansen Ave Boise ID 83703",
    "addr:housenumber":"3553",
    "addr:postcode":"83703",
    "addr:street":"Hansen Ave",
    "iso:country":"US",
    "sg:address":"3553 Hansen Ave",
    "sg:city":"Boise",
    "sg:classifiers":[
        {
            "category":"Shopping",
            "subcategory":"Stationery & Office Supplies",
            "type":"Retail Goods"
        }
    ],
    "sg:phone":"+1 208 343 3505",
    "sg:postcode":"83703",
    "sg:province":"ID",
    "wof:name":"Custom Office Resource",
    "wof:placetype":"venue"
},
  "geometry": {"coordinates":[-116.230153,43.64533],"type":"Point"}
}