{
  "type": "Feature",
  "properties": {
    "addr:full":"2650 S Orchard St Boise ID 83705",
    "addr:housenumber":"2650",
    "addr:postcode":"83705",
    "addr:street":"S Orchard St",
    "iso:country":"US",
    "sg:address":"2650 S Orchard St",
    "sg:city":"Boise",
    "sg:classifiers":[
        {
            "category":"Autos & Motor Vehicles",
            "subcategory":"Automobile Sales",
            "type":"Retail Goods"
        }
    ],
    "sg:phone":"+1 208 384 0717",
    "sg:postcode":"83705",
    "sg:province":"ID",
    "sg:tags":[
        "car",
        "dealer"
    ],
    "sg:website":"www.hertzboise.com",
    "wof:name":"Hertz Car Sales",
    "wof:placetype":"venue"
},
  "geometry": {"coordinates":[-116.24354700000001,43.578116],"type":"Point"}
}