{
  "type": "Feature",
  "properties": {
    "iso:country":"US",
    "sg:address":"1245 W Snoqualmie Ave",
    "sg:city":"Post Falls",
    "sg:classifiers":[
        {
            "category":"Autos & Motor Vehicles",
            "subcategory":"Motorcycle Sales",
            "type":"Retail Goods"
        }
    ],
    "sg:phone":"+1 208 773 6634",
    "sg:postcode":"83854",
    "sg:province":"ID",
    "sg:tags":[
        "all",
        "terrain"
    ],
    "wof:name":"Monster Quad & Cycle Supply",
    "wof:placetype":"venue"
},
  "geometry": {"coordinates":[-116.96432799999999,47.728257],"type":"Point"}
}