{
  "type": "Feature",
  "properties": {
    "addr:full":"9762 Deer Flat Rd Nampa ID 83686",
    "addr:housenumber":"9762",
    "addr:postcode":"83686",
    "addr:street":"Deer Flat Rd",
    "iso:country":"US",
    "sg:address":"9762 Deer Flat Rd",
    "sg:city":"Nampa",
    "sg:classifiers":[
        {
            "category":"Farming",
            "subcategory":"Farm",
            "type":"Manufacturing & Wholesale Goods"
        }
    ],
    "sg:phone":"+1 208 466 4775",
    "sg:postcode":"83686",
    "sg:province":"ID",
    "sg:tags":[
        "crop",
        "general"
    ],
    "wof:name":"Krajnik Farm",
    "wof:placetype":"venue"
},
  "geometry": {"coordinates":[-116.59291399999999,43.502968],"type":"Point"}
}