{
  "type": "Feature",
  "properties": {
    "iso:country":"US",
    "sg:address":"18404 W Paddlewheel Ln",
    "sg:city":"Hauser",
    "sg:classifiers":[
        {
            "category":"Wholesale",
            "subcategory":"Toys & Hobbies",
            "type":"Manufacturing & Wholesale Goods"
        }
    ],
    "sg:phone":"+1 208 773 7016",
    "sg:postcode":"83854",
    "sg:province":"ID",
    "sg:tags":[
        "wholesaler"
    ],
    "wof:name":"Tops Interprises",
    "wof:placetype":"venue"
},
  "geometry": {"coordinates":[-117.033936,47.782864],"type":"Point"}
}