{
  "type": "Feature",
  "properties": {
    "addr:full":"127 W 5th St N Burley ID 83318",
    "addr:housenumber":"127",
    "addr:postcode":"83318",
    "addr:street":"W 5Th St N",
    "iso:country":"US",
    "sg:address":"127 W 5th St N",
    "sg:city":"Burley",
    "sg:classifiers":[
        {
            "category":"Professional",
            "subcategory":"Business Services",
            "type":"Services"
        }
    ],
    "sg:phone":"+1 208 678 3332",
    "sg:postcode":"83318",
    "sg:province":"ID",
    "wof:name":"Industrial Commission Idaho",
    "wof:placetype":"venue"
},
  "geometry": {"coordinates":[-113.794302,42.561389],"type":"Point"}
}