{
  "type": "Feature",
  "properties": {
    "iso:country":"US",
    "sg:address":"715 17th Ave S",
    "sg:city":"Nampa",
    "sg:classifiers":[
        {
            "category":"Building & Trades",
            "subcategory":"Construction",
            "type":"Services"
        }
    ],
    "sg:phone":"+1 208 466 7267",
    "sg:postcode":"83651",
    "sg:province":"ID",
    "sg:tags":[
        "specializing",
        "home",
        "builder",
        "operative",
        "family"
    ],
    "wof:name":"Ray Bright",
    "wof:placetype":"venue"
},
  "geometry": {"coordinates":[-116.56057300000001,43.570602],"type":"Point"}
}