{
  "type": "Feature",
  "properties": {
    "iso:country":"US",
    "sg:address":"4636 E Ririe Hwy",
    "sg:city":"Idaho Falls",
    "sg:classifiers":[
        {
            "category":"Building & Trades",
            "subcategory":"Construction",
            "type":"Services"
        }
    ],
    "sg:phone":"+1 208 523 9411",
    "sg:postcode":"83401",
    "sg:province":"ID",
    "sg:tags":[
        "excavation",
        "foundation"
    ],
    "wof:name":"Seek Excavating Company",
    "wof:placetype":"venue"
},
  "geometry": {"coordinates":[-111.939379,43.555995],"type":"Point"}
}