{
  "type": "Feature",
  "properties": {
    "iso:country":"US",
    "sg:address":"840 N 2nd E",
    "sg:city":"Rexburg",
    "sg:classifiers":[
        {
            "category":"Shopping",
            "subcategory":"Clothing, Apparel, & Fashions",
            "type":"Retail Goods"
        }
    ],
    "sg:phone":"+1 208 356 6005",
    "sg:postcode":"83440",
    "sg:province":"ID",
    "sg:tags":[
        "western"
    ],
    "wof:name":"Curt's Corral",
    "wof:placetype":"venue"
},
  "geometry": {"coordinates":[-111.77801,43.840282],"type":"Point"}
}