{
  "type": "Feature",
  "properties": {
    "iso:country":"US",
    "sg:address":"120 State Hwy 81",
    "sg:city":"Burley",
    "sg:classifiers":[
        {
            "category":"Home & Garden",
            "subcategory":"Garden Supply",
            "type":"Retail Goods"
        }
    ],
    "sg:phone":"+1 208 678 0405",
    "sg:postcode":"83318",
    "sg:province":"ID",
    "sg:tags":[
        "nurseryman"
    ],
    "wof:name":"Sunrise Nursery & Landscape",
    "wof:placetype":"venue"
},
  "geometry": {"coordinates":[-113.763515,42.531297],"type":"Point"}
}