{
  "type": "Feature",
  "properties": {
    "iso:country":"US",
    "sg:address":"213 Woodvine St",
    "sg:city":"Boise",
    "sg:classifiers":[
        {
            "category":"Wholesale",
            "subcategory":"Metals & Minerals",
            "type":"Manufacturing & Wholesale Goods"
        }
    ],
    "sg:phone":"+1 208 344 4207",
    "sg:postcode":"83706",
    "sg:province":"ID",
    "sg:tags":[
        "center"
    ],
    "wof:name":"Cools Cutom Paints",
    "wof:placetype":"venue"
},
  "geometry": {"coordinates":[-116.179215,43.582067],"type":"Point"}
}