{
  "type": "Feature",
  "properties": {
    "addr:full":"858 W 100 S Blackfoot ID 83221",
    "addr:housenumber":"858",
    "addr:postcode":"83221",
    "addr:street":"W 100 S",
    "iso:country":"US",
    "sg:address":"858 W 100 S",
    "sg:city":"Blackfoot",
    "sg:classifiers":[
        {
            "category":"Building & Trades",
            "subcategory":"Construction",
            "type":"Services"
        }
    ],
    "sg:phone":"+1 208 684 3333",
    "sg:postcode":"83221",
    "sg:province":"ID",
    "sg:tags":[
        "excavation",
        "contractor"
    ],
    "wof:name":"Andersons Construction",
    "wof:placetype":"venue"
},
  "geometry": {"coordinates":[-112.471996,43.182439],"type":"Point"}
}