{
  "type": "Feature",
  "properties": {
    "iso:country":"US",
    "sg:address":"1345 Hiline Rd",
    "sg:city":"Pocatello",
    "sg:classifiers":[
        {
            "category":"Organizations",
            "subcategory":"Religious Organization",
            "type":"Services"
        }
    ],
    "sg:phone":"+1 208 237 6711",
    "sg:postcode":"83201",
    "sg:province":"ID",
    "wof:name":"Family Worship CN",
    "wof:placetype":"venue"
},
  "geometry": {"coordinates":[-112.446617,42.899849],"type":"Point"}
}