{
  "type": "Feature",
  "properties": {
    "iso:country":"US",
    "sg:address":"209 E Railroad Ave",
    "sg:city":"Post Falls",
    "sg:classifiers":[
        {
            "category":"Organizations",
            "subcategory":"Community Association",
            "type":"Services"
        }
    ],
    "sg:phone":"+1 208 773 2923",
    "sg:postcode":"83854",
    "sg:province":"ID",
    "sg:tags":[
        "fraternal"
    ],
    "wof:name":"Fraternal Order Of Eagles",
    "wof:placetype":"venue"
},
  "geometry": {"coordinates":[-116.94646400000001,47.710033],"type":"Point"}
}