{
  "type": "Feature",
  "properties": {
    "iso:country":"US",
    "sg:address":"6097 S Greensferry Rd",
    "sg:city":"Coeur D Alene",
    "sg:classifiers":[
        {
            "category":"Retail",
            "subcategory":"Repair Shop",
            "type":"Services"
        }
    ],
    "sg:phone":"+1 208 667 6194",
    "sg:postcode":"83814",
    "sg:province":"ID",
    "wof:name":"Cougar Taxidermy",
    "wof:placetype":"venue"
},
  "geometry": {"coordinates":[-116.906109,47.656188],"type":"Point"}
}