{
  "type": "Feature",
  "properties": {
    "iso:country":"US",
    "sg:address":"4663 Ustick Rd",
    "sg:city":"Nampa",
    "sg:phone":"+1 208 466 0599",
    "sg:postcode":"83687",
    "sg:province":"ID",
    "sg:tags":[
        "farm",
        "field",
        "crop"
    ],
    "wof:name":"Grant Bastian",
    "wof:placetype":"venue"
},
  "geometry": {"coordinates":[-116.48847600000001,43.634078],"type":"Point"}
}