{
  "type": "Feature",
  "properties": {
    "addr:full":"459 Gullane Cir Idaho Falls ID 83401",
    "addr:housenumber":"459",
    "addr:postcode":"83401",
    "addr:street":"Gullane Cir",
    "iso:country":"US",
    "sg:address":"459 Gullane Cir",
    "sg:city":"Idaho Falls",
    "sg:classifiers":[
        {
            "category":"Building & Trades",
            "subcategory":"Landscaping Services",
            "type":"Services"
        }
    ],
    "sg:phone":"+1 208 529 5970",
    "sg:postcode":"83401",
    "sg:province":"ID",
    "sg:tags":[
        "tree"
    ],
    "wof:name":"Roberts & Sons Tree Svc",
    "wof:placetype":"venue"
},
  "geometry": {"coordinates":[-112.042131,43.542941],"type":"Point"}
}