{
  "type": "Feature",
  "properties": {
    "iso:country":"US",
    "sg:address":"402 E Jefferson St",
    "sg:city":"Boise",
    "sg:classifiers":[
        {
            "category":"Personal",
            "subcategory":"Beauty Salon",
            "type":"Services"
        }
    ],
    "sg:phone":"+1 208 338 1717",
    "sg:postcode":"83712",
    "sg:province":"ID",
    "wof:name":"Adorn Me Salon",
    "wof:placetype":"venue"
},
  "geometry": {"coordinates":[-116.188848,43.611696],"type":"Point"}
}