{
  "type": "Feature",
  "properties": {
    "iso:country":"US",
    "sg:address":"2315 8th St",
    "sg:city":"Lewiston",
    "sg:classifiers":[
        {
            "category":"Shopping",
            "subcategory":"Pharmacy",
            "type":"Retail Goods"
        }
    ],
    "sg:phone":"+1 208 750 1444",
    "sg:postcode":"83501",
    "sg:province":"ID",
    "wof:name":"Owl Pharmacies",
    "wof:placetype":"venue"
},
  "geometry": {"coordinates":[-117.02140199999999,46.396936],"type":"Point"}
}