{
  "type": "Feature",
  "properties": {
    "iso:country":"US",
    "sg:address":"1420 N Eagle Creek Way",
    "sg:city":"Eagle",
    "sg:classifiers":[
        {
            "category":"Retail",
            "subcategory":"Portrait Studio",
            "type":"Services"
        }
    ],
    "sg:phone":"+1 208 938 1533",
    "sg:postcode":"83616",
    "sg:province":"ID",
    "sg:tags":[
        "photo"
    ],
    "wof:name":"Photography By Chris",
    "wof:placetype":"venue"
},
  "geometry": {"coordinates":[-116.317988,43.70923],"type":"Point"}
}