{
  "type": "Feature",
  "properties": {
    "iso:country":"US",
    "sg:address":"13029 Delayne Rd",
    "sg:city":"Donnelly",
    "sg:classifiers":[
        {
            "category":"Retail",
            "subcategory":"Repair Shop",
            "type":"Services"
        }
    ],
    "sg:phone":"+1 208 325 8836",
    "sg:postcode":"83615",
    "sg:province":"ID",
    "sg:tags":[
        "upholsterer"
    ],
    "wof:name":"P & B Upholstery",
    "wof:placetype":"venue"
},
  "geometry": {"coordinates":[-116.09464699999999,44.715716],"type":"Point"}
}