{
  "type": "Feature",
  "properties": {
    "iso:country":"US",
    "sg:address":"415 E Parkcenter Blvd",
    "sg:city":"Boise",
    "sg:classifiers":[
        {
            "category":"Restaurant",
            "type":"Food & Drink"
        }
    ],
    "sg:phone":"+1 208 429 0011",
    "sg:postcode":"83706",
    "sg:province":"ID",
    "sg:tags":[
        "pizza",
        "italian"
    ],
    "wof:name":"Smokey Mountain Pizza & Pasta",
    "wof:placetype":"venue"
},
  "geometry": {"coordinates":[-116.177879,43.596149],"type":"Point"}
}