{
  "type": "Feature",
  "properties": {
    "iso:country":"US",
    "sg:address":"512 2nd Ave N",
    "sg:city":"Twin Falls",
    "sg:classifiers":[
        {
            "category":"Retail",
            "subcategory":"Repair Shop",
            "type":"Services"
        }
    ],
    "sg:phone":"+1 208 733 1980",
    "sg:postcode":"83301",
    "sg:province":"ID",
    "sg:tags":[
        "equipment",
        "telephone",
        "system"
    ],
    "wof:name":"Dad's Telephone Sales & Svc",
    "wof:placetype":"venue"
},
  "geometry": {"coordinates":[-114.474994,42.560896],"type":"Point"}
}