{
  "type": "Feature",
  "properties": {
    "iso:country":"US",
    "sg:address":"4200 N Pennfield Pl",
    "sg:city":"Boise",
    "sg:classifiers":[
        {
            "category":"Shopping",
            "subcategory":"Clothing, Apparel, & Fashions",
            "type":"Retail Goods"
        }
    ],
    "sg:phone":"+1 208 378 4543",
    "sg:postcode":"83713",
    "sg:province":"ID",
    "sg:tags":[
        "infant",
        "wear"
    ],
    "wof:name":"Kiddy Kottage",
    "wof:placetype":"venue"
},
  "geometry": {"coordinates":[-116.32218399999999,43.643684],"type":"Point"}
}