{
  "type": "Feature",
  "properties": {
    "iso:country":"US",
    "sg:address":"502 E Clark St",
    "sg:city":"Paul",
    "sg:classifiers":[
        {
            "category":"Building & Trades",
            "subcategory":"Plumbing",
            "type":"Services"
        }
    ],
    "sg:phone":"+1 208 438 8396",
    "sg:postcode":"83347",
    "sg:province":"ID",
    "sg:tags":[
        "plumbing",
        "contractor"
    ],
    "wof:name":"M Catmull Plumbing & Heating",
    "wof:placetype":"venue"
},
  "geometry": {"coordinates":[-113.777135,42.606815],"type":"Point"}
}