{
  "type": "Feature",
  "properties": {
    "addr:full":"2017 3rd Ave N Lewiston ID 83501",
    "addr:housenumber":"2017",
    "addr:postcode":"83501",
    "addr:street":"3Rd Ave N",
    "iso:country":"US",
    "sg:address":"2017 3rd Ave N",
    "sg:city":"Lewiston",
    "sg:classifiers":[
        {
            "category":"Building & Trades",
            "subcategory":"Plumbing",
            "type":"Services"
        }
    ],
    "sg:phone":"+1 208 750 0496",
    "sg:postcode":"83501",
    "sg:province":"ID",
    "sg:tags":[
        "mechanical",
        "contractor"
    ],
    "wof:name":"R & M Mechanical",
    "wof:placetype":"venue"
},
  "geometry": {"coordinates":[-117.003991,46.423728],"type":"Point"}
}