{
  "type": "Feature",
  "properties": {
    "iso:country":"US",
    "sg:address":"6936 N 15th St",
    "sg:city":"Coeur D Alene",
    "sg:classifiers":[
        {
            "category":"Building & Trades",
            "subcategory":"Construction",
            "type":"Services"
        }
    ],
    "sg:phone":"+1 208 762 1497",
    "sg:postcode":"83815",
    "sg:province":"ID",
    "sg:tags":[
        "hanging",
        "contractor"
    ],
    "wof:name":"Inland Painting",
    "wof:placetype":"venue"
},
  "geometry": {"coordinates":[-116.76509299999999,47.735923],"type":"Point"}
}