{
  "type": "Feature",
  "properties": {
    "iso:country":"US",
    "sg:address":"5803 Cleveland Blvd",
    "sg:city":"Caldwell",
    "sg:classifiers":[
        {
            "category":"Autos & Motor Vehicles",
            "subcategory":"Automobile Sales",
            "type":"Retail Goods"
        }
    ],
    "sg:phone":"+1 208 947 6000",
    "sg:postcode":"83607",
    "sg:province":"ID",
    "sg:tags":[
        "car",
        "dealer"
    ],
    "sg:website":"www.lmidaho.com",
    "wof:name":"Caldwell Auto Mall",
    "wof:placetype":"venue"
},
  "geometry": {"coordinates":[-116.633912,43.62656],"type":"Point"}
}