{
  "type": "Feature",
  "properties": {
    "iso:country":"US",
    "sg:address":"2731 Klamath Ln",
    "sg:city":"Nampa",
    "sg:classifiers":[
        {
            "category":"Professional",
            "type":"Services"
        }
    ],
    "sg:phone":"+1 208 461 9359",
    "sg:postcode":"83686",
    "sg:province":"ID",
    "wof:name":"Earl T Vancampen Seattle",
    "wof:placetype":"venue"
},
  "geometry": {"coordinates":[-116.535295,43.542191],"type":"Point"}
}