{
  "type": "Feature",
  "properties": {
    "iso:country":"US",
    "sg:address":"228 Holly St",
    "sg:city":"Nampa",
    "sg:classifiers":[
        {
            "category":"Health Services",
            "subcategory":"Chiropractor",
            "type":"Services"
        }
    ],
    "sg:phone":"+1 208 467 5759",
    "sg:postcode":"83686",
    "sg:province":"ID",
    "wof:name":"Chiropractic Center",
    "wof:placetype":"venue"
},
  "geometry": {"coordinates":[-116.564234,43.567316],"type":"Point"}
}