{
  "type": "Feature",
  "properties": {
    "addr:full":"216 N 9th St St Maries ID 83861",
    "addr:housenumber":"216",
    "addr:postcode":"83861",
    "addr:street":"N 9Th St St",
    "iso:country":"US",
    "sg:address":"216 N 9th St",
    "sg:city":"St Maries",
    "sg:classifiers":[
        {
            "category":"Education",
            "subcategory":"School",
            "type":"Public Place"
        }
    ],
    "sg:phone":"+1 208 245 2274",
    "sg:postcode":"83861",
    "sg:province":"ID",
    "wof:name":"St Maries Seventh Day",
    "wof:placetype":"venue"
},
  "geometry": {"coordinates":[-116.568826,47.317574],"type":"Point"}
}