{
  "type": "Feature",
  "properties": {
    "addr:full":"160 Johnson Ave Orofino ID 83544",
    "addr:housenumber":"160",
    "addr:postcode":"83544",
    "addr:street":"Johnson Ave",
    "iso:country":"US",
    "sg:address":"160 Johnson Ave",
    "sg:city":"Orofino",
    "sg:classifiers":[
        {
            "category":"Shopping",
            "subcategory":"Discount & Variety Stores",
            "type":"Retail Goods"
        }
    ],
    "sg:phone":"+1 208 476 7284",
    "sg:postcode":"83544",
    "sg:province":"ID",
    "wof:name":"Fergie's Variety",
    "wof:placetype":"venue"
},
  "geometry": {"coordinates":[-116.25379700000001,46.479586],"type":"Point"}
}