{
  "type": "Feature",
  "properties": {
    "iso:country":"US",
    "sg:address":"190 E State St",
    "sg:city":"Eagle",
    "sg:classifiers":[
        {
            "category":"Restaurant",
            "type":"Food & Drink"
        }
    ],
    "sg:phone":"+1 208 939 2500",
    "sg:postcode":"83616",
    "sg:province":"ID",
    "sg:tags":[
        "eating"
    ],
    "wof:name":"Davinci's",
    "wof:placetype":"venue"
},
  "geometry": {"coordinates":[-116.35171,43.695258],"type":"Point"}
}