{
  "type": "Feature",
  "properties": {
    "iso:country":"US",
    "sg:address":"1003 W Fort St",
    "sg:city":"Boise",
    "sg:classifiers":[
        {
            "category":"Real Estate",
            "subcategory":"Real Estate Agent",
            "type":"Services"
        }
    ],
    "sg:phone":"+1 208 363 7000",
    "sg:postcode":"83702",
    "sg:province":"ID",
    "sg:tags":[
        "investment"
    ],
    "wof:name":"Sperry Van Ness",
    "wof:placetype":"venue"
},
  "geometry": {"coordinates":[-116.201166,43.623454],"type":"Point"}
}