{
  "type": "Feature",
  "properties": {
    "addr:full":"520 S 9th St Boise ID 83702",
    "addr:housenumber":"520",
    "addr:postcode":"83702",
    "addr:street":"S 9Th St",
    "iso:country":"US",
    "sg:address":"520 S 9th St",
    "sg:city":"Boise",
    "sg:classifiers":[
        {
            "category":"Arts & Performance",
            "subcategory":"Theater",
            "type":"Entertainment"
        }
    ],
    "sg:phone":"+1 208 429 9908",
    "sg:postcode":"83702",
    "sg:province":"ID",
    "sg:website":"www.idahoshakespeare.org",
    "wof:name":"Idaho Shakespeare Festival",
    "wof:placetype":"venue"
},
  "geometry": {"coordinates":[-116.208268,43.61236],"type":"Point"}
}