{
  "type": "Feature",
  "properties": {
    "iso:country":"US",
    "sg:address":"6003 Overland Rd",
    "sg:city":"Boise",
    "sg:classifiers":[
        {
            "category":"Social Services",
            "type":"Services"
        }
    ],
    "sg:phone":"+1 208 331 8300",
    "sg:postcode":"83709",
    "sg:province":"ID",
    "wof:name":"Riverside Ctr For Chldren Fmly",
    "wof:placetype":"venue"
},
  "geometry": {"coordinates":[-116.256882,43.589937],"type":"Point"}
}