{
  "type": "Feature",
  "properties": {
    "iso:country":"US",
    "sg:address":"3507 E Lewis Ln",
    "sg:city":"Nampa",
    "sg:classifiers":[
        {
            "category":"Real Estate",
            "subcategory":"Real Estate Agent",
            "type":"Services"
        }
    ],
    "sg:phone":"+1 208 463 9304",
    "sg:postcode":"83686",
    "sg:province":"ID",
    "sg:tags":[
        "inspection"
    ],
    "wof:name":"Treasure Valley Maintenance",
    "wof:placetype":"venue"
},
  "geometry": {"coordinates":[-116.528548,43.517271],"type":"Point"}
}