{
  "type": "Feature",
  "properties": {
    "addr:full":"14032 State Hwy 55 Mccall ID 83638",
    "addr:housenumber":"14032",
    "addr:postcode":"83638",
    "addr:street":"State Hwy 55",
    "iso:country":"US",
    "sg:address":"14032 State Hwy 55",
    "sg:city":"Mccall",
    "sg:classifiers":[
        {
            "category":"Retail",
            "subcategory":"Auto Repair",
            "type":"Services"
        }
    ],
    "sg:phone":"+1 208 634 5383",
    "sg:postcode":"83638",
    "sg:province":"ID",
    "sg:tags":[
        "repairing",
        "automobile"
    ],
    "wof:name":"Alpine Automotive Parts",
    "wof:placetype":"venue"
},
  "geometry": {"coordinates":[-116.090704,44.858432],"type":"Point"}
}