{
  "type": "Feature",
  "properties": {
    "addr:full":"7024 Overland Rd Boise ID 83709",
    "addr:housenumber":"7024",
    "addr:postcode":"83709",
    "addr:street":"Overland Rd",
    "iso:country":"US",
    "sg:address":"7024 Overland Rd",
    "sg:city":"Boise",
    "sg:classifiers":[
        {
            "category":"Retail",
            "subcategory":"Auto Repair",
            "type":"Services"
        }
    ],
    "sg:phone":"+1 208 327 9900",
    "sg:postcode":"83709",
    "sg:province":"ID",
    "sg:tags":[
        "transmission"
    ],
    "wof:name":"Economy Transmission Svc",
    "wof:placetype":"venue"
},
  "geometry": {"coordinates":[-116.269272,43.590205],"type":"Point"}
}