{
  "type": "Feature",
  "properties": {
    "addr:full":"5118 N Sawyer Ave Boise ID 83714",
    "addr:housenumber":"5118",
    "addr:postcode":"83714",
    "addr:street":"N Sawyer Ave",
    "iso:country":"US",
    "sg:address":"5118 N Sawyer Ave",
    "sg:city":"Boise",
    "sg:classifiers":[
        {
            "category":"Wholesale",
            "subcategory":"Machinery & Supplies",
            "type":"Manufacturing & Wholesale Goods"
        }
    ],
    "sg:phone":"+1 208 377 9555",
    "sg:postcode":"83714",
    "sg:province":"ID",
    "sg:tags":[
        "cleaners",
        "vacuum"
    ],
    "sg:website":"www.pro-team.com",
    "wof:name":"Pro-Team Inc",
    "wof:placetype":"venue"
},
  "geometry": {"coordinates":[-116.266858,43.64498],"type":"Point"}
}