{
  "type": "Feature",
  "properties": {
    "iso:country":"US",
    "sg:address":"1720 N Woodruff Ave",
    "sg:city":"Idaho Falls",
    "sg:classifiers":[
        {
            "category":"Wholesale",
            "subcategory":"Office Equipment",
            "type":"Manufacturing & Wholesale Goods"
        }
    ],
    "sg:phone":"+1 208 232 9446",
    "sg:postcode":"83401",
    "sg:province":"ID",
    "sg:tags":[
        "machine",
        "duplicating",
        "copying"
    ],
    "sg:website":"www.fentonsofficesolutions.com",
    "wof:name":"Fenton's Office Solutions",
    "wof:placetype":"venue"
},
  "geometry": {"coordinates":[-112.000646,43.511548],"type":"Point"}
}