{
  "type": "Feature",
  "properties": {
    "iso:country":"US",
    "sg:address":"2373 E 214 N",
    "sg:city":"Saint Anthony",
    "sg:phone":"+1 208 458 4420",
    "sg:postcode":"83445",
    "sg:province":"ID",
    "sg:tags":[
        "irish",
        "wheat",
        "potato",
        "farm",
        "crop",
        "field"
    ],
    "wof:name":"Reed Ashcraft Farms",
    "wof:placetype":"venue"
},
  "geometry": {"coordinates":[-111.68082099999999,43.914446],"type":"Point"}
}