{
  "type": "Feature",
  "properties": {
    "iso:country":"US",
    "sg:address":"341 N 2nd E",
    "sg:city":"Soda Springs",
    "sg:classifiers":[
        {
            "category":"Travel",
            "subcategory":"Hotels & Motels",
            "type":"Entertainment"
        }
    ],
    "sg:phone":"+1 208 547 4351",
    "sg:postcode":"83276",
    "sg:province":"ID",
    "wof:name":"Lake View Motel & Trailer Park",
    "wof:placetype":"venue"
},
  "geometry": {"coordinates":[-111.597286,42.666975],"type":"Point"}
}