{
  "type": "Feature",
  "properties": {
    "iso:country":"US",
    "sg:address":"605 Williams Rd",
    "sg:city":"Emmett",
    "sg:classifiers":[
        {
            "category":"Building & Trades",
            "subcategory":"Construction",
            "type":"Services"
        }
    ],
    "sg:phone":"+1 208 365 9447",
    "sg:postcode":"83617",
    "sg:province":"ID",
    "sg:tags":[
        "contractor"
    ],
    "wof:name":"Canaday Roofing",
    "wof:placetype":"venue"
},
  "geometry": {"coordinates":[-116.505558,43.871394],"type":"Point"}
}