{
  "type": "Feature",
  "properties": {
    "addr:full":"350 N Milwaukee St Boise ID 83704",
    "addr:housenumber":"350",
    "addr:postcode":"83704",
    "addr:street":"N Milwaukee St",
    "iso:country":"US",
    "sg:address":"350 N Milwaukee St",
    "sg:city":"Boise",
    "sg:classifiers":[
        {
            "category":"Travel",
            "subcategory":"Travel Agent",
            "type":"Entertainment"
        }
    ],
    "sg:phone":"+1 208 375 6800",
    "sg:postcode":"83704",
    "sg:province":"ID",
    "sg:tags":[
        "cruise"
    ],
    "wof:name":"Global Travel",
    "wof:placetype":"venue"
},
  "geometry": {"coordinates":[-116.28222,43.607228],"type":"Point"}
}