{
  "type": "Feature",
  "properties": {
    "addr:full":"221 11th Ave N Nampa ID 83687",
    "addr:housenumber":"221",
    "addr:postcode":"83687",
    "addr:street":"11Th Ave N",
    "iso:country":"US",
    "sg:address":"221 11th Ave N",
    "sg:city":"Nampa",
    "sg:classifiers":[
        {
            "category":"Shopping",
            "subcategory":"Department Store",
            "type":"Retail Goods"
        }
    ],
    "sg:phone":"+1 208 466 5390",
    "sg:postcode":"83687",
    "sg:province":"ID",
    "sg:tags":[
        "shop"
    ],
    "wof:name":"Plaza Del Calzado",
    "wof:placetype":"venue"
},
  "geometry": {"coordinates":[-116.556687,43.582854],"type":"Point"}
}