{
  "type": "Feature",
  "properties": {
    "addr:full":"900 Sandy Glen Ln Burley ID 83318",
    "addr:housenumber":"900",
    "addr:postcode":"83318",
    "addr:street":"Sandy Glen Ln",
    "iso:country":"US",
    "sg:address":"900 Sandy Glen Ln",
    "sg:city":"Burley",
    "sg:classifiers":[
        {
            "category":"Personal",
            "subcategory":"Beauty Salon",
            "type":"Services"
        }
    ],
    "sg:phone":"+1 208 678 9004",
    "sg:postcode":"83318",
    "sg:province":"ID",
    "sg:tags":[
        "shop"
    ],
    "wof:name":"Salon 900",
    "wof:placetype":"venue"
},
  "geometry": {"coordinates":[-113.782462,42.509548],"type":"Point"}
}