{
  "type": "Feature",
  "properties": {
    "addr:full":"400 Broadway Ave S Buhl ID 83316",
    "addr:housenumber":"400",
    "addr:postcode":"83316",
    "addr:street":"Broadway Ave S",
    "iso:country":"US",
    "sg:address":"400 Broadway Ave S",
    "sg:city":"Buhl",
    "sg:classifiers":[
        {
            "category":"Retail",
            "subcategory":"Auto Repair",
            "type":"Services"
        }
    ],
    "sg:phone":"+1 208 543 4624",
    "sg:postcode":"83316",
    "sg:province":"ID",
    "sg:tags":[
        "repairing",
        "automobile"
    ],
    "wof:name":"Geska's Broadway Automotive",
    "wof:placetype":"venue"
},
  "geometry": {"coordinates":[-114.75608200000001,42.596389],"type":"Point"}
}