{
  "type": "Feature",
  "properties": {
    "iso:country":"US",
    "sg:address":"2976 E State St",
    "sg:city":"Eagle",
    "sg:classifiers":[
        {
            "category":"Personal",
            "subcategory":"Beauty Salon",
            "type":"Services"
        }
    ],
    "sg:phone":"+1 208 938 9690",
    "sg:postcode":"83616",
    "sg:province":"ID",
    "wof:name":"Fantastic Sams",
    "wof:placetype":"venue"
},
  "geometry": {"coordinates":[-116.315637,43.683355],"type":"Point"}
}