{
  "type": "Feature",
  "properties": {
    "addr:full":"1780 E Schneidmiller Ave Post Falls ID 83854",
    "addr:housenumber":"1780",
    "addr:postcode":"83854",
    "addr:street":"E Schneidmiller Ave",
    "iso:country":"US",
    "sg:address":"1780 E Schneidmiller Ave",
    "sg:city":"Post Falls",
    "sg:classifiers":[
        {
            "category":"Restaurant",
            "type":"Food & Drink"
        }
    ],
    "sg:phone":"+1 208 457 8500",
    "sg:postcode":"83854",
    "sg:province":"ID",
    "sg:tags":[
        "eating"
    ],
    "sg:website":"www.wingersdiner.com",
    "wof:name":"Winger's Diner",
    "wof:placetype":"venue"
},
  "geometry": {"coordinates":[-116.92011100000001,47.712067],"type":"Point"}
}