{
  "type": "Feature",
  "properties": {
    "iso:country":"US",
    "sg:address":"624 Main St",
    "sg:city":"Gooding",
    "sg:classifiers":[
        {
            "category":"Government",
            "subcategory":"Police Station",
            "type":"Public Place"
        }
    ],
    "sg:phone":"+1 208 934 4421",
    "sg:postcode":"83330",
    "sg:province":"ID",
    "sg:tags":[
        "sheriff"
    ],
    "wof:name":"Gooding County Sheriff",
    "wof:placetype":"venue"
},
  "geometry": {"coordinates":[-114.712788,42.939322],"type":"Point"}
}