{
  "type": "Feature",
  "properties": {
    "iso:country":"US",
    "sg:address":"318 N Woodruff Ave",
    "sg:city":"Idaho Falls",
    "sg:classifiers":[
        {
            "category":"Food & Beverages",
            "subcategory":"Specialty",
            "type":"Retail Goods"
        }
    ],
    "sg:phone":"+1 208 524 0061",
    "sg:postcode":"83401",
    "sg:province":"ID",
    "sg:tags":[
        "tea",
        "coffee"
    ],
    "wof:name":"Moxie Java",
    "wof:placetype":"venue"
},
  "geometry": {"coordinates":[-111.998987,43.496818],"type":"Point"}
}