{
  "type": "Feature",
  "properties": {
    "iso:country":"US",
    "sg:address":"220 E Lewis St",
    "sg:city":"Pocatello",
    "sg:classifiers":[
        {
            "category":"Building & Trades",
            "subcategory":"Construction",
            "type":"Services"
        }
    ],
    "sg:phone":"+1 208 232 6877",
    "sg:postcode":"83201",
    "sg:province":"ID",
    "sg:tags":[
        "railroad",
        "contractor"
    ],
    "wof:name":"Crew Shuttle Svc Inc",
    "wof:placetype":"venue"
},
  "geometry": {"coordinates":[-112.445923,42.863797],"type":"Point"}
}