{
  "type": "Feature",
  "properties": {
    "iso:country":"US",
    "sg:address":"602 S Washington Ave",
    "sg:city":"Emmett",
    "sg:classifiers":[
        {
            "category":"Insurance",
            "subcategory":"Insurance Agent",
            "type":"Services"
        }
    ],
    "sg:phone":"+1 208 365 2160",
    "sg:postcode":"83617",
    "sg:province":"ID",
    "wof:name":"Jensen-Leavitt Insurance",
    "wof:placetype":"venue"
},
  "geometry": {"coordinates":[-116.49993600000001,43.870879],"type":"Point"}
}