{
  "type": "Feature",
  "properties": {
    "iso:country":"US",
    "sg:address":"2216 S Latah St",
    "sg:city":"Boise",
    "sg:classifiers":[
        {
            "category":"Retail",
            "subcategory":"Repair Shop",
            "type":"Services"
        }
    ],
    "sg:phone":"+1 208 342 7499",
    "sg:postcode":"83705",
    "sg:province":"ID",
    "wof:name":"No No Cleaning",
    "wof:placetype":"venue"
},
  "geometry": {"coordinates":[-116.2285,43.581147],"type":"Point"}
}