{
  "type": "Feature",
  "properties": {
    "iso:country":"US",
    "sg:address":"530 W 20th St",
    "sg:city":"Idaho Falls",
    "sg:classifiers":[
        {
            "category":"Wholesale",
            "subcategory":"Meat",
            "type":"Manufacturing & Wholesale Goods"
        }
    ],
    "sg:phone":"+1 208 522 4804",
    "sg:postcode":"83402",
    "sg:province":"ID",
    "sg:tags":[
        "product"
    ],
    "wof:name":"Great Western Frozen Food Inc",
    "wof:placetype":"venue"
},
  "geometry": {"coordinates":[-112.045299,43.480185],"type":"Point"}
}