{
  "type": "Feature",
  "properties": {
    "iso:country":"US",
    "sg:address":"704 E 4th Ave",
    "sg:city":"Post Falls",
    "sg:classifiers":[
        {
            "category":"Manufacturing",
            "subcategory":"Building Materials",
            "type":"Manufacturing & Wholesale Goods"
        }
    ],
    "sg:phone":"+1 208 773 4511",
    "sg:postcode":"83854",
    "sg:province":"ID",
    "sg:tags":[
        "plywood",
        "veneer"
    ],
    "sg:website":"www.idahoveneer.com",
    "wof:name":"Idaho Veneer Co",
    "wof:placetype":"venue"
},
  "geometry": {"coordinates":[-116.93821699999999,47.711082],"type":"Point"}
}