{
  "type": "Feature",
  "properties": {
    "addr:full":"554 Steelhead Way Boise ID 83704",
    "addr:housenumber":"554",
    "addr:postcode":"83704",
    "addr:street":"Steelhead Way",
    "iso:country":"US",
    "sg:address":"554 Steelhead Way",
    "sg:city":"Boise",
    "sg:classifiers":[
        {
            "category":"Shopping",
            "subcategory":"Computers & Home Electronics",
            "type":"Retail Goods"
        }
    ],
    "sg:phone":"+1 208 376 7312",
    "sg:postcode":"83704",
    "sg:province":"ID",
    "sg:tags":[
        "software"
    ],
    "wof:name":"Nexus Solutions Group",
    "wof:placetype":"venue"
},
  "geometry": {"coordinates":[-116.290239,43.60891],"type":"Point"}
}