{
  "type": "Feature",
  "properties": {
    "addr:full":"805 S 18th E Mountain Home ID 83647",
    "addr:housenumber":"805",
    "addr:postcode":"83647",
    "addr:street":"S 18Th E",
    "iso:country":"US",
    "sg:address":"805 S 18th E",
    "sg:city":"Mountain Home",
    "sg:classifiers":[
        {
            "category":"Building & Trades",
            "subcategory":"Construction",
            "type":"Services"
        }
    ],
    "sg:phone":"+1 208 587 3423",
    "sg:postcode":"83647",
    "sg:province":"ID",
    "sg:tags":[
        "general",
        "contractor"
    ],
    "wof:name":"C 2 Construction Inc",
    "wof:placetype":"venue"
},
  "geometry": {"coordinates":[-115.67756199999999,43.125136],"type":"Point"}
}