{
  "type": "Feature",
  "properties": {
    "iso:country":"US",
    "sg:address":"24034 Batt Corner Rd",
    "sg:city":"Parma",
    "sg:classifiers":[
        {
            "category":"Real Estate",
            "subcategory":"Real Estate Operator",
            "type":"Services"
        }
    ],
    "sg:phone":"+1 208 482 7397",
    "sg:postcode":"83660",
    "sg:province":"ID",
    "sg:tags":[
        "apartment"
    ],
    "wof:name":"Pocatello Properties",
    "wof:placetype":"venue"
},
  "geometry": {"coordinates":[-116.921708,43.719888],"type":"Point"}
}