{
  "type": "Feature",
  "properties": {
    "iso:country":"US",
    "sg:address":"1110 Albeni Rd",
    "sg:city":"Priest River",
    "sg:classifiers":[
        {
            "category":"Restaurant",
            "type":"Food & Drink"
        }
    ],
    "sg:phone":"+1 208 448 2490",
    "sg:postcode":"83856",
    "sg:province":"ID",
    "wof:name":"Burger Express",
    "wof:placetype":"venue"
},
  "geometry": {"coordinates":[-116.922766,48.180528],"type":"Point"}
}