{
  "type": "Feature",
  "properties": {
    "iso:country":"US",
    "sg:address":"10269 Roan Meadows Dr",
    "sg:city":"Boise",
    "sg:classifiers":[
        {
            "category":"Home & Garden",
            "subcategory":"Building Materials",
            "type":"Retail Goods"
        }
    ],
    "sg:phone":"+1 208 362 1177",
    "sg:postcode":"83709",
    "sg:province":"ID",
    "sg:tags":[
        "door"
    ],
    "wof:name":"Morgan Door Co Treasure Valley",
    "wof:placetype":"venue"
},
  "geometry": {"coordinates":[-116.30910799999999,43.572875],"type":"Point"}
}