{
  "type": "Feature",
  "properties": {
    "iso:country":"US",
    "sg:address":"945 Pancheri Dr",
    "sg:city":"Idaho Falls",
    "sg:classifiers":[
        {
            "category":"Wholesale",
            "subcategory":"Machinery & Supplies",
            "type":"Manufacturing & Wholesale Goods"
        }
    ],
    "sg:phone":"+1 208 523 5500",
    "sg:postcode":"83402",
    "sg:province":"ID",
    "sg:tags":[
        "equipment",
        "irrigation",
        "system"
    ],
    "wof:name":"Pipeco",
    "wof:placetype":"venue"
},
  "geometry": {"coordinates":[-112.04939400000001,43.485526],"type":"Point"}
}