{
  "type": "Feature",
  "properties": {
    "addr:full":"400 Floyde St Mccall ID 83638",
    "addr:housenumber":"400",
    "addr:postcode":"83638",
    "addr:street":"Floyde St",
    "iso:country":"US",
    "sg:address":"400 Floyde St",
    "sg:city":"Mccall",
    "sg:classifiers":[
        {
            "category":"Building & Trades",
            "subcategory":"Construction",
            "type":"Services"
        }
    ],
    "sg:phone":"+1 208 634 2022",
    "sg:postcode":"83638",
    "sg:province":"ID",
    "sg:tags":[
        "general",
        "contractor"
    ],
    "wof:name":"Darling & Son's Construction",
    "wof:placetype":"venue"
},
  "geometry": {"coordinates":[-116.09675,44.901399],"type":"Point"}
}