{
  "type": "Feature",
  "properties": {
    "iso:country":"US",
    "sg:address":"1137 N Scrivner Pl",
    "sg:city":"Meridian",
    "sg:classifiers":[
        {
            "category":"Building & Trades",
            "subcategory":"Landscaping Services",
            "type":"Services"
        }
    ],
    "sg:phone":"+1 208 898 0430",
    "sg:postcode":"83642",
    "sg:province":"ID",
    "sg:tags":[
        "lawn",
        "maintenance",
        "grounds"
    ],
    "wof:name":"EZ Landscape & Maintenance",
    "wof:placetype":"venue"
},
  "geometry": {"coordinates":[-116.375438,43.614615],"type":"Point"}
}