{
  "type": "Feature",
  "properties": {
    "addr:full":"1202 Meadowbrook Ln Pocatello ID 83201",
    "addr:housenumber":"1202",
    "addr:postcode":"83201",
    "addr:street":"Meadowbrook Ln",
    "iso:country":"US",
    "sg:address":"1202 Meadowbrook Ln",
    "sg:city":"Pocatello",
    "sg:classifiers":[
        {
            "category":"Retail",
            "subcategory":"Repair Shop",
            "type":"Services"
        }
    ],
    "sg:phone":"+1 208 233 0424",
    "sg:postcode":"83201",
    "sg:province":"ID",
    "wof:name":"Dans Design Custom Framing",
    "wof:placetype":"venue"
},
  "geometry": {"coordinates":[-112.444729,42.896286],"type":"Point"}
}