{
  "type": "Feature",
  "properties": {
    "iso:country":"US",
    "sg:address":"700 W Main St",
    "sg:city":"Grangeville",
    "sg:classifiers":[
        {
            "category":"Travel",
            "subcategory":"Hotels & Motels",
            "type":"Entertainment"
        }
    ],
    "sg:phone":"+1 208 983 2500",
    "sg:postcode":"83530",
    "sg:province":"ID",
    "sg:website":"www.montysmotel.com",
    "wof:name":"Monty's Motel",
    "wof:placetype":"venue"
},
  "geometry": {"coordinates":[-116.128292,45.926798],"type":"Point"}
}