{
  "type": "Feature",
  "properties": {
    "addr:full":"902 W 720 N Shoshone ID 83352",
    "addr:housenumber":"902",
    "addr:postcode":"83352",
    "addr:street":"W 720 N",
    "iso:country":"US",
    "sg:address":"902 W 720 N",
    "sg:city":"Shoshone",
    "sg:classifiers":[
        {
            "category":"Building & Trades",
            "subcategory":"Cleaning & Sanitation",
            "type":"Services"
        }
    ],
    "sg:phone":"+1 208 886 7529",
    "sg:postcode":"83352",
    "sg:province":"ID",
    "sg:tags":[
        "maintenance"
    ],
    "wof:name":"Tinas Cleaning Service",
    "wof:placetype":"venue"
},
  "geometry": {"coordinates":[-114.584862,43.04013],"type":"Point"}
}