{
  "type": "Feature",
  "properties": {
    "iso:country":"US",
    "sg:address":"1945 Washington Ave",
    "sg:city":"St Maries",
    "sg:classifiers":[
        {
            "category":"Freight",
            "type":"Transportation"
        }
    ],
    "sg:phone":"+1 208 245 0156",
    "sg:postcode":"83861",
    "sg:province":"ID",
    "sg:tags":[
        "operator",
        "local",
        "trucking"
    ],
    "wof:name":"Greg M Stancil Trucking LLC",
    "wof:placetype":"venue"
},
  "geometry": {"coordinates":[-116.581054,47.312926],"type":"Point"}
}