{
  "type": "Feature",
  "properties": {
    "addr:full":"1621 Calico Cir Pocatello ID 83201",
    "addr:housenumber":"1621",
    "addr:postcode":"83201",
    "addr:street":"Calico Cir",
    "iso:country":"US",
    "sg:address":"1621 Calico Cir",
    "sg:city":"Pocatello",
    "sg:classifiers":[
        {
            "category":"Manufacturing",
            "subcategory":"Paper Products",
            "type":"Manufacturing & Wholesale Goods"
        }
    ],
    "sg:phone":"+1 208 237 8689",
    "sg:postcode":"83201",
    "sg:province":"ID",
    "sg:tags":[
        "box",
        "fiber",
        "mfg"
    ],
    "wof:name":"Hells Canyon Custom Fly Boxes",
    "wof:placetype":"venue"
},
  "geometry": {"coordinates":[-112.434338,42.905112],"type":"Point"}
}