{
  "type": "Feature",
  "properties": {
    "addr:full":"1230 Caldwell Blvd Nampa ID 83651",
    "addr:housenumber":"1230",
    "addr:postcode":"83651",
    "addr:street":"Caldwell Blvd",
    "iso:country":"US",
    "sg:address":"1230 Caldwell Blvd",
    "sg:city":"Nampa",
    "sg:classifiers":[
        {
            "category":"Personal",
            "subcategory":"Beauty Salon",
            "type":"Services"
        }
    ],
    "sg:phone":"+1 208 461 2203",
    "sg:postcode":"83651",
    "sg:province":"ID",
    "wof:name":"Fantastic Sam's",
    "wof:placetype":"venue"
},
  "geometry": {"coordinates":[-116.595538,43.600583],"type":"Point"}
}