{
  "type": "Feature",
  "properties": {
    "iso:country":"US",
    "sg:address":"312 S Astro Ave",
    "sg:city":"Star",
    "sg:classifiers":[
        {
            "category":"Wholesale",
            "subcategory":"Electrical",
            "type":"Manufacturing & Wholesale Goods"
        }
    ],
    "sg:phone":"+1 208 286 0160",
    "sg:postcode":"83669",
    "sg:province":"ID",
    "sg:tags":[
        "equipment"
    ],
    "wof:name":"Alarm Star",
    "wof:placetype":"venue"
},
  "geometry": {"coordinates":[-116.484729,43.689573],"type":"Point"}
}