{
  "type": "Feature",
  "properties": {
    "addr:full":"612 W North St Grangeville ID 83530",
    "addr:housenumber":"612",
    "addr:postcode":"83530",
    "addr:street":"W North St",
    "iso:country":"US",
    "sg:address":"612 W North St",
    "sg:city":"Grangeville",
    "sg:classifiers":[
        {
            "category":"Insurance",
            "subcategory":"Insurance Agent",
            "type":"Services"
        }
    ],
    "sg:phone":"+1 208 983 2215",
    "sg:postcode":"83530",
    "sg:province":"ID",
    "wof:name":"State Farm Insurance",
    "wof:placetype":"venue"
},
  "geometry": {"coordinates":[-116.126769,45.927468],"type":"Point"}
}