{
  "type": "Feature",
  "properties": {
    "iso:country":"US",
    "sg:address":"21120 US Hwy 30",
    "sg:city":"Filer",
    "sg:classifiers":[
        {
            "category":"Wholesale",
            "subcategory":"Farm Supplies",
            "type":"Manufacturing & Wholesale Goods"
        }
    ],
    "sg:phone":"+1 208 326 4321",
    "sg:postcode":"83328",
    "sg:province":"ID",
    "sg:tags":[
        "bulb",
        "seed"
    ],
    "wof:name":"Seminis Vegetable Seeds",
    "wof:placetype":"venue"
},
  "geometry": {"coordinates":[-114.591431,42.563767],"type":"Point"}
}