{
  "type": "Feature",
  "properties": {
    "addr:full":"211 Teena St Boise ID 83714",
    "addr:housenumber":"211",
    "addr:postcode":"83714",
    "addr:street":"Teena St",
    "iso:country":"US",
    "sg:address":"211 Teena St",
    "sg:city":"Boise",
    "sg:classifiers":[
        {
            "category":"Taxi",
            "type":"Transportation"
        }
    ],
    "sg:phone":"+1 208 866 5601",
    "sg:postcode":"83714",
    "sg:province":"ID",
    "sg:tags":[
        "taxicab"
    ],
    "wof:name":"Green & White Taxi",
    "wof:placetype":"venue"
},
  "geometry": {"coordinates":[-116.250624,43.635352],"type":"Point"}
}