{
  "type": "Feature",
  "properties": {
    "iso:country":"US",
    "sg:address":"314 S Robinson Blvd",
    "sg:city":"Nampa",
    "sg:classifiers":[
        {
            "category":"Manufacturing",
            "subcategory":"Metals",
            "type":"Manufacturing & Wholesale Goods"
        }
    ],
    "sg:phone":"+1 208 467 1801",
    "sg:postcode":"83687",
    "sg:province":"ID",
    "sg:tags":[
        "fabrication",
        "structural"
    ],
    "wof:name":"Tri City Transportation",
    "wof:placetype":"venue"
},
  "geometry": {"coordinates":[-116.49365,43.567931],"type":"Point"}
}