{
  "type": "Feature",
  "properties": {
    "addr:full":"300 Mission St Mccall ID 83638",
    "addr:housenumber":"300",
    "addr:postcode":"83638",
    "addr:street":"Mission St",
    "iso:country":"US",
    "sg:address":"300 Mission St",
    "sg:city":"Mccall",
    "sg:classifiers":[
        {
            "category":"Travel",
            "subcategory":"Campground",
            "type":"Entertainment"
        }
    ],
    "sg:phone":"+1 208 634 5598",
    "sg:postcode":"83638",
    "sg:province":"ID",
    "sg:tags":[
        "camp"
    ],
    "wof:name":"Camp Pinewood",
    "wof:placetype":"venue"
},
  "geometry": {"coordinates":[-116.105059,44.893919],"type":"Point"}
}