{
  "type": "Feature",
  "properties": {
    "addr:full":"10483 W Shadow Rock St Boise ID 83714",
    "addr:housenumber":"10483",
    "addr:postcode":"83714",
    "addr:street":"W Shadow Rock St",
    "iso:country":"US",
    "sg:address":"10483 W Shadow Rock St",
    "sg:city":"Boise",
    "sg:classifiers":[
        {
            "category":"Professional",
            "subcategory":"Computer Services",
            "type":"Services"
        }
    ],
    "sg:phone":"+1 208 938 3544",
    "sg:postcode":"83714",
    "sg:province":"ID",
    "sg:tags":[
        "related",
        "programing",
        "custom"
    ],
    "wof:name":"Intergrated Internet Solutions",
    "wof:placetype":"venue"
},
  "geometry": {"coordinates":[-116.31180500000001,43.697675],"type":"Point"}
}