{
  "type": "Feature",
  "properties": {
    "addr:full":"101 E Hooper Ave Soda Springs ID 83276",
    "addr:housenumber":"101",
    "addr:postcode":"83276",
    "addr:street":"E Hooper Ave",
    "iso:country":"US",
    "sg:address":"101 E Hooper Ave",
    "sg:city":"Soda Springs",
    "sg:classifiers":[
        {
            "category":"Wholesale",
            "subcategory":"Electrical",
            "type":"Manufacturing & Wholesale Goods"
        }
    ],
    "sg:phone":"+1 208 547 4444",
    "sg:postcode":"83276",
    "sg:province":"ID",
    "sg:tags":[
        "communication",
        "radio",
        "system"
    ],
    "wof:name":"R & L Communications",
    "wof:placetype":"venue"
},
  "geometry": {"coordinates":[-111.599148,42.658984],"type":"Point"}
}