{
  "type": "Feature",
  "properties": {
    "iso:country":"US",
    "sg:address":"1133 Albion Ave",
    "sg:city":"Burley",
    "sg:classifiers":[
        {
            "category":"Building & Trades",
            "subcategory":"Electrical",
            "type":"Services"
        }
    ],
    "sg:phone":"+1 208 678 4071",
    "sg:postcode":"83318",
    "sg:province":"ID",
    "sg:tags":[
        "electric",
        "contractor"
    ],
    "sg:website":"www.larryselectricandheating.com",
    "wof:name":"Larry's Electric & Heating",
    "wof:placetype":"venue"
},
  "geometry": {"coordinates":[-113.791837,42.538975],"type":"Point"}
}