{
  "type": "Feature",
  "properties": {
    "addr:full":"3402 Cleveland Blvd Caldwell ID 83605",
    "addr:housenumber":"3402",
    "addr:postcode":"83605",
    "addr:street":"Cleveland Blvd",
    "iso:country":"US",
    "sg:address":"3402 Cleveland Blvd",
    "sg:city":"Caldwell",
    "sg:classifiers":[
        {
            "category":"Retail",
            "subcategory":"Auto Repair",
            "type":"Services"
        }
    ],
    "sg:phone":"+1 208 454 8705",
    "sg:postcode":"83605",
    "sg:province":"ID",
    "sg:tags":[
        "wheel",
        "automotive",
        "axle",
        "alignment"
    ],
    "wof:name":"Canyon County Certified Align",
    "wof:placetype":"venue"
},
  "geometry": {"coordinates":[-116.662114,43.645121],"type":"Point"}
}