{
  "type": "Feature",
  "properties": {
    "iso:country":"US",
    "sg:address":"2037 N Yellowstone Hwy",
    "sg:city":"Idaho Falls",
    "sg:classifiers":[
        {
            "category":"Shopping",
            "type":"Retail Goods"
        }
    ],
    "sg:phone":"+1 208 523 8800",
    "sg:postcode":"83401",
    "sg:province":"ID",
    "sg:tags":[
        "art",
        "gallery",
        "dealer"
    ],
    "wof:name":"Wild West Design",
    "wof:placetype":"venue"
},
  "geometry": {"coordinates":[-112.00961,43.514772],"type":"Point"}
}