{
  "type": "Feature",
  "properties": {
    "iso:country":"US",
    "sg:address":"3521 N 1100 E",
    "sg:city":"Buhl",
    "sg:classifiers":[
        {
            "category":"Building & Trades",
            "subcategory":"Construction",
            "type":"Services"
        }
    ],
    "sg:phone":"+1 208 537 9130",
    "sg:postcode":"83316",
    "sg:province":"ID",
    "sg:tags":[
        "well",
        "drilling"
    ],
    "wof:name":"Bishop Well Drilling Inc",
    "wof:placetype":"venue"
},
  "geometry": {"coordinates":[-114.82944500000001,42.505987],"type":"Point"}
}