{
  "type": "Feature",
  "properties": {
    "iso:country":"US",
    "sg:address":"1800 Garrett Way",
    "sg:city":"Pocatello",
    "sg:classifiers":[
        {
            "category":"Wholesale",
            "subcategory":"Farm Supplies",
            "type":"Manufacturing & Wholesale Goods"
        }
    ],
    "sg:phone":"+1 208 233 0308",
    "sg:postcode":"83201",
    "sg:province":"ID",
    "sg:website":"www.calranch.com",
    "wof:name":"CAL Stores",
    "wof:placetype":"venue"
},
  "geometry": {"coordinates":[-112.458325,42.876383],"type":"Point"}
}