{
  "type": "Feature",
  "properties": {
    "addr:full":"820 Blue Lakes Blvd N Twin Falls ID 83301",
    "addr:housenumber":"820",
    "addr:postcode":"83301",
    "addr:street":"Blue Lakes Blvd N",
    "iso:country":"US",
    "sg:address":"820 Blue Lakes Blvd N",
    "sg:city":"Twin Falls",
    "sg:classifiers":[
        {
            "category":"Restaurant",
            "type":"Food & Drink"
        }
    ],
    "sg:menulink":"http://www.allmenus.com/id/twin-falls/87366-little-caesars-pizza/menu/",
    "sg:phone":"+1 208 733 7756",
    "sg:postcode":"83301",
    "sg:province":"ID",
    "sg:tags":[
        "american",
        "pizza"
    ],
    "wof:name":"Little Caesar's Pizza",
    "wof:placetype":"venue"
},
  "geometry": {"coordinates":[-114.46036700000001,42.576306],"type":"Point"}
}