{
  "type": "Feature",
  "properties": {
    "addr:full":"3095 N Lakeharbor Ln Boise ID 83703",
    "addr:housenumber":"3095",
    "addr:postcode":"83703",
    "addr:street":"N Lakeharbor Ln",
    "iso:country":"US",
    "sg:address":"3095 N Lakeharbor Ln",
    "sg:city":"Boise",
    "sg:classifiers":[
        {
            "category":"Restaurant",
            "type":"Food & Drink"
        }
    ],
    "sg:phone":"+1 208 853 9800",
    "sg:postcode":"83703",
    "sg:province":"ID",
    "sg:tags":[
        "eating"
    ],
    "wof:name":"Eddie's Diner",
    "wof:placetype":"venue"
},
  "geometry": {"coordinates":[-116.25372,43.652094],"type":"Point"}
}