{
  "type": "Feature",
  "properties": {
    "iso:country":"US",
    "sg:address":"17355 S Bull Run Rd",
    "sg:city":"Cataldo",
    "sg:classifiers":[
        {
            "category":"Building & Trades",
            "subcategory":"Construction",
            "type":"Services"
        }
    ],
    "sg:phone":"+1 208 682 3258",
    "sg:postcode":"83810",
    "sg:province":"ID",
    "sg:tags":[
        "road",
        "contractor"
    ],
    "wof:name":"RDS Excavation",
    "wof:placetype":"venue"
},
  "geometry": {"coordinates":[-116.471574,47.52364],"type":"Point"}
}