{
  "type": "Feature",
  "properties": {
    "addr:full":"980 W Central Rd Emmett ID 83617",
    "addr:housenumber":"980",
    "addr:postcode":"83617",
    "addr:street":"W Central Rd",
    "iso:country":"US",
    "sg:address":"980 W Central Rd",
    "sg:city":"Emmett",
    "sg:classifiers":[
        {
            "category":"Organizations",
            "subcategory":"Religious Organization",
            "type":"Services"
        }
    ],
    "sg:phone":"+1 208 365 3841",
    "sg:postcode":"83617",
    "sg:province":"ID",
    "sg:tags":[
        "church"
    ],
    "wof:name":"Church Of Jesus Christ Of Lds",
    "wof:placetype":"venue"
},
  "geometry": {"coordinates":[-116.511577,43.900862],"type":"Point"}
}