{
  "type": "Feature",
  "properties": {
    "iso:country":"US",
    "sg:address":"1400 Harden Rd",
    "sg:city":"Moscow",
    "sg:classifiers":[
        {
            "category":"Personal",
            "type":"Services"
        }
    ],
    "sg:phone":"+1 208 882 0709",
    "sg:postcode":"83843",
    "sg:province":"ID",
    "sg:tags":[
        "therapist",
        "massage"
    ],
    "wof:name":"Kristie Harden",
    "wof:placetype":"venue"
},
  "geometry": {"coordinates":[-117.012111,46.748074],"type":"Point"}
}