{
  "type": "Feature",
  "properties": {
    "iso:country":"US",
    "sg:address":"578 W Ranch Ct",
    "sg:city":"Rathdrum",
    "sg:classifiers":[
        {
            "category":"Banks & Credit Unions",
            "subcategory":"Bank",
            "type":"Services"
        }
    ],
    "sg:phone":"+1 208 687 1132",
    "sg:postcode":"83858",
    "sg:province":"ID",
    "sg:tags":[
        "mortgage"
    ],
    "wof:name":"Mortgage Services",
    "wof:placetype":"venue"
},
  "geometry": {"coordinates":[-116.788984,47.826433],"type":"Point"}
}