{
  "type": "Feature",
  "properties": {
    "iso:country":"US",
    "sg:address":"4107 Cleveland Blvd",
    "sg:city":"Caldwell",
    "sg:classifiers":[
        {
            "category":"Autos & Motor Vehicles",
            "subcategory":"Automobile Sales",
            "type":"Retail Goods"
        }
    ],
    "sg:phone":"+1 208 455 2888",
    "sg:postcode":"83605",
    "sg:province":"ID",
    "sg:tags":[
        "new",
        "car"
    ],
    "wof:name":"4 Bs Auto Sales",
    "wof:placetype":"venue"
},
  "geometry": {"coordinates":[-116.655461,43.640916],"type":"Point"}
}