{
  "type": "Feature",
  "properties": {
    "iso:country":"US",
    "sg:address":"419 D St",
    "sg:city":"Idaho Falls",
    "sg:classifiers":[
        {
            "category":"Manufacturing",
            "subcategory":"Metals",
            "type":"Manufacturing & Wholesale Goods"
        }
    ],
    "sg:phone":"+1 208 542 2848",
    "sg:postcode":"83402",
    "sg:province":"ID",
    "sg:tags":[
        "steel"
    ],
    "wof:name":"Continental Steel Inc",
    "wof:placetype":"venue"
},
  "geometry": {"coordinates":[-112.039793,43.495576],"type":"Point"}
}