{
  "type": "Feature",
  "properties": {
    "iso:country":"US",
    "sg:address":"5423 Yellowstone Ave",
    "sg:city":"Pocatello",
    "sg:classifiers":[
        {
            "category":"Social Services",
            "subcategory":"Child Care",
            "type":"Services"
        }
    ],
    "sg:phone":"+1 208 237 9192",
    "sg:postcode":"83202",
    "sg:province":"ID",
    "wof:name":"Tot Spot",
    "wof:placetype":"venue"
},
  "geometry": {"coordinates":[-112.466576,42.932208],"type":"Point"}
}