{
  "type": "Feature",
  "properties": {
    "iso:country":"US",
    "sg:address":"2900 N Government Way",
    "sg:city":"Coeur D Alene",
    "sg:classifiers":[
        {
            "category":"Shopping",
            "subcategory":"Clothing, Apparel, & Fashions",
            "type":"Retail Goods"
        }
    ],
    "sg:phone":"+1 208 651 1027",
    "sg:postcode":"83815",
    "sg:province":"ID",
    "wof:name":"Concepcione",
    "wof:placetype":"venue"
},
  "geometry": {"coordinates":[-116.786337,47.703467],"type":"Point"}
}