{
  "type": "Feature",
  "properties": {
    "addr:full":"225 N 5th St Boise ID 83702",
    "addr:housenumber":"225",
    "addr:postcode":"83702",
    "addr:street":"N 5Th St",
    "iso:country":"US",
    "sg:address":"225 N 5th St",
    "sg:city":"Boise",
    "sg:classifiers":[
        {
            "category":"Shopping",
            "subcategory":"Used Merchandise",
            "type":"Retail Goods"
        }
    ],
    "sg:phone":"+1 208 344 4589",
    "sg:postcode":"83702",
    "sg:province":"ID",
    "sg:tags":[
        "clothing"
    ],
    "wof:name":"Lux Fashion Lounge",
    "wof:placetype":"venue"
},
  "geometry": {"coordinates":[-116.198673,43.615222],"type":"Point"}
}