{
  "type": "Feature",
  "properties": {
    "addr:full":"106 S Saint Charles St Salmon ID 83467",
    "addr:housenumber":"106",
    "addr:postcode":"83467",
    "addr:street":"S Saint Charles St",
    "iso:country":"US",
    "sg:address":"106 S Saint Charles St",
    "sg:city":"Salmon",
    "sg:classifiers":[
        {
            "category":"Personal",
            "subcategory":"Beauty Salon",
            "type":"Services"
        }
    ],
    "sg:phone":"+1 208 756 6311",
    "sg:postcode":"83467",
    "sg:province":"ID",
    "wof:name":"Sensations Salon",
    "wof:placetype":"venue"
},
  "geometry": {"coordinates":[-113.89549,45.176165],"type":"Point"}
}