{
  "type": "Feature",
  "properties": {
    "addr:full":"809 N Orchard St Boise ID 83706",
    "addr:housenumber":"809",
    "addr:postcode":"83706",
    "addr:street":"N Orchard St",
    "iso:country":"US",
    "sg:address":"809 N Orchard St",
    "sg:city":"Boise",
    "sg:classifiers":[
        {
            "category":"Real Estate",
            "subcategory":"Real Estate Agent",
            "type":"Services"
        }
    ],
    "sg:phone":"+1 208 939 5175",
    "sg:postcode":"83706",
    "sg:province":"ID",
    "sg:tags":[
        "appraiser"
    ],
    "wof:name":"Roger M Ritter",
    "wof:placetype":"venue"
},
  "geometry": {"coordinates":[-116.243521,43.612439],"type":"Point"}
}