{
  "type": "Feature",
  "properties": {
    "iso:country":"US",
    "sg:address":"1151 E Ashford St",
    "sg:city":"Meridian",
    "sg:classifiers":[
        {
            "category":"Home & Garden",
            "subcategory":"Building Materials",
            "type":"Retail Goods"
        }
    ],
    "sg:phone":"+1 208 888 9955",
    "sg:postcode":"83642",
    "sg:province":"ID",
    "sg:tags":[
        "screen",
        "window"
    ],
    "wof:name":"Screens 4 Less",
    "wof:placetype":"venue"
},
  "geometry": {"coordinates":[-116.380931,43.613835],"type":"Point"}
}