{
  "type": "Feature",
  "properties": {
    "iso:country":"US",
    "sg:address":"149 Anderson Creek Rd",
    "sg:city":"Garden Valley",
    "sg:classifiers":[
        {
            "category":"Farming",
            "subcategory":"Livestock Farm",
            "type":"Manufacturing & Wholesale Goods"
        }
    ],
    "sg:phone":"+1 208 462 3797",
    "sg:postcode":"83622",
    "sg:province":"ID",
    "sg:tags":[
        "beef",
        "feedlot",
        "cattle"
    ],
    "wof:name":"Doug Youren",
    "wof:placetype":"venue"
},
  "geometry": {"coordinates":[-115.965566,44.113788],"type":"Point"}
}