{
  "type": "Feature",
  "properties": {
    "addr:full":"3580 N Cloverdale Rd Boise ID 83713",
    "addr:housenumber":"3580",
    "addr:postcode":"83713",
    "addr:street":"N Cloverdale Rd",
    "iso:country":"US",
    "sg:address":"3580 N Cloverdale Rd",
    "sg:city":"Boise",
    "sg:classifiers":[
        {
            "category":"Organizations",
            "subcategory":"Religious Organization",
            "type":"Services"
        }
    ],
    "sg:phone":"+1 208 375 4219",
    "sg:postcode":"83713",
    "sg:province":"ID",
    "sg:tags":[
        "church"
    ],
    "sg:website":"www.cloverdaleurc.net",
    "wof:name":"Cloverdale United Reformed",
    "wof:placetype":"venue"
},
  "geometry": {"coordinates":[-116.334266,43.637008],"type":"Point"}
}