{
  "type": "Feature",
  "properties": {
    "addr:full":"10 E Main St Rexburg ID 83440",
    "addr:housenumber":"10",
    "addr:postcode":"83440",
    "addr:street":"E Main St",
    "iso:country":"US",
    "sg:address":"10 E Main St",
    "sg:city":"Rexburg",
    "sg:classifiers":[
        {
            "category":"Restaurant",
            "type":"Food & Drink"
        }
    ],
    "sg:phone":"+1 208 356 4009",
    "sg:postcode":"83440",
    "sg:province":"ID",
    "wof:name":"Old Mesquite Grill",
    "wof:placetype":"venue"
},
  "geometry": {"coordinates":[-111.783618,43.825985],"type":"Point"}
}