{
  "type": "Feature",
  "properties": {
    "iso:country":"US",
    "sg:address":"606 N Corbin Rd",
    "sg:city":"Post Falls",
    "sg:classifiers":[
        {
            "category":"Building & Trades",
            "subcategory":"Construction",
            "type":"Services"
        }
    ],
    "sg:phone":"+1 208 773 7466",
    "sg:postcode":"83854",
    "sg:province":"ID",
    "sg:tags":[
        "excavation",
        "contractor"
    ],
    "wof:name":"Archies Enterprises",
    "wof:placetype":"venue"
},
  "geometry": {"coordinates":[-116.990879,47.71349],"type":"Point"}
}