{
  "type": "Feature",
  "properties": {
    "addr:full":"9811 Bigwood Dr Boise ID 83709",
    "addr:housenumber":"9811",
    "addr:postcode":"83709",
    "addr:street":"Bigwood Dr",
    "iso:country":"US",
    "sg:address":"9811 Bigwood Dr",
    "sg:city":"Boise",
    "sg:classifiers":[
        {
            "category":"Professional",
            "subcategory":"Business Services",
            "type":"Services"
        }
    ],
    "sg:phone":"+1 208 362 0746",
    "sg:postcode":"83709",
    "sg:province":"ID",
    "wof:name":"Buckley Auction Service",
    "wof:placetype":"venue"
},
  "geometry": {"coordinates":[-116.30466699999999,43.534671],"type":"Point"}
}