{
  "type": "Feature",
  "properties": {
    "iso:country":"US",
    "sg:address":"9811 Bigwood Dr",
    "sg:city":"Boise",
    "sg:classifiers":[
        {
            "category":"Professional",
            "subcategory":"Business Services",
            "type":"Services"
        }
    ],
    "sg:phone":"+1 208 362 0746",
    "sg:postcode":"83709",
    "sg:province":"ID",
    "wof:name":"Buckley Auction Service",
    "wof:placetype":"venue"
},
  "geometry": {"coordinates":[-116.304667,43.534671],"type":"Point"}
}