{
  "type": "Feature",
  "properties": {
    "iso:country":"US",
    "sg:address":"33964 N Main Ave",
    "sg:city":"Bayview",
    "sg:classifiers":[
        {
            "category":"Communications",
            "subcategory":"News Services",
            "type":"Services"
        }
    ],
    "sg:phone":"+1 208 683 2321",
    "sg:postcode":"83803",
    "sg:province":"ID",
    "wof:name":"Neport News Ship Building",
    "wof:placetype":"venue"
},
  "geometry": {"coordinates":[-116.56018,47.980279],"type":"Point"}
}