{
  "type": "Feature",
  "properties": {
    "addr:full":"580 W Clark St Pocatello ID 83204",
    "addr:housenumber":"580",
    "addr:postcode":"83204",
    "addr:street":"W Clark St",
    "iso:country":"US",
    "sg:address":"580 W Clark St",
    "sg:city":"Pocatello",
    "sg:classifiers":[
        {
            "category":"Real Estate",
            "subcategory":"Real Estate Operator",
            "type":"Services"
        }
    ],
    "sg:phone":"+1 208 233 8898",
    "sg:postcode":"83204",
    "sg:province":"ID",
    "sg:tags":[
        "apartment"
    ],
    "wof:name":"Rosewood Apartments",
    "wof:placetype":"venue"
},
  "geometry": {"coordinates":[-112.45383200000001,42.861518],"type":"Point"}
}