{
  "type": "Feature",
  "properties": {
    "iso:country":"US",
    "sg:address":"1118 F St",
    "sg:city":"Lewiston",
    "sg:classifiers":[
        {
            "category":"Government",
            "subcategory":"Office",
            "type":"Public Place"
        }
    ],
    "sg:phone":"+1 208 799 5035",
    "sg:postcode":"83501",
    "sg:province":"ID",
    "sg:tags":[
        "government-state"
    ],
    "sg:website":"http://www.tax.idaho.gov",
    "wof:name":"State of Idaho Lewiston-State Office Building",
    "wof:placetype":"venue"
},
  "geometry": {"coordinates":[-117.01937700000001,46.418274],"type":"Point"}
}