{
  "type": "Feature",
  "properties": {
    "iso:country":"US",
    "sg:address":"5616 E Powerline Rd",
    "sg:city":"Nampa",
    "sg:classifiers":[
        {
            "category":"Manufacturing",
            "subcategory":"Metals",
            "type":"Manufacturing & Wholesale Goods"
        }
    ],
    "sg:phone":"+1 208 466 1224",
    "sg:postcode":"83687",
    "sg:province":"ID",
    "sg:tags":[
        "pipe",
        "bending",
        "tube",
        "precision"
    ],
    "wof:name":"Titus Manufacturing",
    "wof:placetype":"venue"
},
  "geometry": {"coordinates":[-116.50176,43.576041],"type":"Point"}
}