{
  "type": "Feature",
  "properties": {
    "iso:country":"US",
    "sg:address":"450 Falls Ave W",
    "sg:city":"Twin Falls",
    "sg:classifiers":[
        {
            "category":"Professional",
            "subcategory":"Lawyer & Legal Services",
            "type":"Services"
        }
    ],
    "sg:phone":"+1 208 734 5682",
    "sg:postcode":"83301",
    "sg:province":"ID",
    "sg:tags":[
        "attorney"
    ],
    "wof:name":"Taylor Law Offices",
    "wof:placetype":"venue"
},
  "geometry": {"coordinates":[-114.48662,42.578119],"type":"Point"}
}