{
  "type": "Feature",
  "properties": {
    "addr:full":"373 W Hwy 39 Blackfoot ID 83221",
    "addr:housenumber":"373",
    "addr:postcode":"83221",
    "addr:street":"W Hwy 39",
    "iso:country":"US",
    "sg:address":"373 W Hwy 39",
    "sg:city":"Blackfoot",
    "sg:classifiers":[
        {
            "category":"Health Services",
            "subcategory":"Clinic",
            "type":"Services"
        }
    ],
    "sg:phone":"+1 208 785 2499",
    "sg:postcode":"83221",
    "sg:province":"ID",
    "sg:tags":[
        "home"
    ],
    "wof:name":"Community & Residential Svc",
    "wof:placetype":"venue"
},
  "geometry": {"coordinates":[-112.37341499999999,43.198842],"type":"Point"}
}