{
  "type": "Feature",
  "properties": {
    "iso:country":"US",
    "sg:address":"154 N 3600 E",
    "sg:city":"Rigby",
    "sg:classifiers":[
        {
            "category":"Personal",
            "subcategory":"Beauty Salon",
            "type":"Services"
        }
    ],
    "sg:phone":"+1 208 754 4724",
    "sg:postcode":"83442",
    "sg:province":"ID",
    "sg:tags":[
        "shop"
    ],
    "wof:name":"Rones Country Cuts",
    "wof:placetype":"venue"
},
  "geometry": {"coordinates":[-111.983328,43.653904],"type":"Point"}
}