{
  "type": "Feature",
  "properties": {
    "addr:full":"1847 Idaho St Lewiston ID 83501",
    "addr:housenumber":"1847",
    "addr:postcode":"83501",
    "addr:street":"Idaho St",
    "iso:country":"US",
    "sg:address":"1847 Idaho St",
    "sg:city":"Lewiston",
    "sg:classifiers":[
        {
            "category":"Wholesale",
            "subcategory":"Groceries",
            "type":"Manufacturing & Wholesale Goods"
        }
    ],
    "sg:phone":"+1 208 743 9489",
    "sg:postcode":"83501",
    "sg:province":"ID",
    "sg:tags":[
        "grocer"
    ],
    "wof:name":"URM Cash & Carry",
    "wof:placetype":"venue"
},
  "geometry": {"coordinates":[-117.005949,46.414638],"type":"Point"}
}