{
  "type": "Feature",
  "properties": {
    "iso:country":"US",
    "sg:address":"623 1st St",
    "sg:city":"Idaho Falls",
    "sg:classifiers":[
        {
            "category":"Manufacturing",
            "subcategory":"Printing",
            "type":"Manufacturing & Wholesale Goods"
        }
    ],
    "sg:phone":"+1 208 529 3658",
    "sg:postcode":"83401",
    "sg:province":"ID",
    "sg:tags":[
        "engraver",
        "wood"
    ],
    "wof:name":"Brooks Trophy Cottage",
    "wof:placetype":"venue"
},
  "geometry": {"coordinates":[-112.02095199999999,43.497045],"type":"Point"}
}