{
  "type": "Feature",
  "properties": {
    "iso:country":"US",
    "sg:address":"802 Front St",
    "sg:city":"Mccammon",
    "sg:classifiers":[
        {
            "category":"Government",
            "subcategory":"Office",
            "type":"Public Place"
        }
    ],
    "sg:phone":"+1 208 254 3200",
    "sg:postcode":"83250",
    "sg:province":"ID",
    "sg:tags":[
        "village"
    ],
    "wof:name":"Mc Cammon City Office",
    "wof:placetype":"venue"
},
  "geometry": {"coordinates":[-112.190172,42.648287],"type":"Point"}
}