{
  "type": "Feature",
  "properties": {
    "iso:country":"US",
    "sg:address":"2338 Overland Ave",
    "sg:city":"Burley",
    "sg:classifiers":[
        {
            "category":"Home & Garden",
            "subcategory":"Furniture",
            "type":"Retail Goods"
        }
    ],
    "sg:phone":"+1 208 678 5975",
    "sg:postcode":"83318",
    "sg:province":"ID",
    "wof:name":"Fine Furniture",
    "wof:placetype":"venue"
},
  "geometry": {"coordinates":[-113.793318,42.523979],"type":"Point"}
}