{
  "type": "Feature",
  "properties": {
    "addr:full":"440 E Center St Pocatello ID 83201",
    "addr:housenumber":"440",
    "addr:postcode":"83201",
    "addr:street":"E Center St",
    "iso:country":"US",
    "sg:address":"440 E Center St",
    "sg:city":"Pocatello",
    "sg:classifiers":[
        {
            "category":"Shopping",
            "subcategory":"Computers & Home Electronics",
            "type":"Retail Goods"
        }
    ],
    "sg:phone":"+1 208 232 9022",
    "sg:postcode":"83201",
    "sg:province":"ID",
    "sg:tags":[
        "equipment",
        "dealer"
    ],
    "sg:website":"www.dats.com",
    "wof:name":"Data Solutions",
    "wof:placetype":"venue"
},
  "geometry": {"coordinates":[-112.445446,42.86537],"type":"Point"}
}