{
  "type": "Feature",
  "properties": {
    "addr:full":"5677 Bethel St Boise ID 83706",
    "addr:housenumber":"5677",
    "addr:postcode":"83706",
    "addr:street":"Bethel St",
    "iso:country":"US",
    "sg:address":"5677 Bethel St",
    "sg:city":"Boise",
    "sg:classifiers":[
        {
            "category":"Professional",
            "subcategory":"Detective & Security Services",
            "type":"Services"
        }
    ],
    "sg:phone":"+1 208 377 8866",
    "sg:postcode":"83706",
    "sg:province":"ID",
    "sg:tags":[
        "car",
        "armored"
    ],
    "wof:name":"Loomis Fargo & Co",
    "wof:placetype":"venue"
},
  "geometry": {"coordinates":[-116.24974899999999,43.606119],"type":"Point"}
}