{
  "type": "Feature",
  "properties": {
    "addr:full":"2539 Channing Way Idaho Falls ID 83404",
    "addr:housenumber":"2539",
    "addr:postcode":"83404",
    "addr:street":"Channing Way",
    "iso:country":"US",
    "sg:address":"2539 Channing Way",
    "sg:city":"Idaho Falls",
    "sg:classifiers":[
        {
            "category":"Insurance",
            "subcategory":"Insurance Agent",
            "type":"Services"
        }
    ],
    "sg:phone":"+1 208 522 6800",
    "sg:postcode":"83404",
    "sg:province":"ID",
    "wof:name":"Allstate Insurance",
    "wof:placetype":"venue"
},
  "geometry": {"coordinates":[-111.990549,43.47436],"type":"Point"}
}