{
  "type": "Feature",
  "properties": {
    "iso:country":"US",
    "sg:address":"5606 State Hwy 45",
    "sg:city":"Nampa",
    "sg:classifiers":[
        {
            "category":"Banks & Credit Unions",
            "subcategory":"Bank",
            "type":"Services"
        }
    ],
    "sg:phone":"+1 208 466 3453",
    "sg:postcode":"83686",
    "sg:province":"ID",
    "sg:tags":[
        "financing"
    ],
    "wof:name":"Emerald Funding Resources",
    "wof:placetype":"venue"
},
  "geometry": {"coordinates":[-116.573216,43.457257],"type":"Point"}
}