{
  "type": "Feature",
  "properties": {
    "addr:full":"288 Van Buren St Twin Falls ID 83301",
    "addr:housenumber":"288",
    "addr:postcode":"83301",
    "addr:street":"Van Buren St",
    "iso:country":"US",
    "sg:address":"288 Van Buren St",
    "sg:city":"Twin Falls",
    "sg:classifiers":[
        {
            "category":"Professional",
            "subcategory":"Detective & Security Services",
            "type":"Services"
        }
    ],
    "sg:phone":"+1 208 737 9528",
    "sg:postcode":"83301",
    "sg:province":"ID",
    "sg:tags":[
        "investigator"
    ],
    "wof:name":"Owens Investigation",
    "wof:placetype":"venue"
},
  "geometry": {"coordinates":[-114.4713,42.565144],"type":"Point"}
}