{
  "type": "Feature",
  "properties": {
    "iso:country":"US",
    "sg:address":"75 S 1st W",
    "sg:city":"Rexburg",
    "sg:classifiers":[
        {
            "category":"Real Estate",
            "subcategory":"Real Estate Operator",
            "type":"Services"
        }
    ],
    "sg:phone":"+1 208 359 1985",
    "sg:postcode":"83440",
    "sg:province":"ID",
    "sg:tags":[
        "apartment"
    ],
    "wof:name":"Lajolla Apartments",
    "wof:placetype":"venue"
},
  "geometry": {"coordinates":[-111.78661200000001,43.824468],"type":"Point"}
}