{
  "type": "Feature",
  "properties": {
    "iso:country":"US",
    "sg:address":"220 N 1st Ave",
    "sg:city":"Sandpoint",
    "sg:classifiers":[
        {
            "category":"Personal",
            "subcategory":"Beauty Salon",
            "type":"Services"
        }
    ],
    "sg:phone":"+1 208 255 5220",
    "sg:postcode":"83864",
    "sg:province":"ID",
    "sg:tags":[
        "shop"
    ],
    "wof:name":"Nail Nails Nails",
    "wof:placetype":"venue"
},
  "geometry": {"coordinates":[-116.547696,48.274587],"type":"Point"}
}