{
  "type": "Feature",
  "properties": {
    "addr:full":"3021 W State St Boise ID 83703",
    "addr:housenumber":"3021",
    "addr:postcode":"83703",
    "addr:street":"W State St",
    "iso:country":"US",
    "sg:address":"3021 W State St",
    "sg:city":"Boise",
    "sg:classifiers":[
        {
            "category":"Shopping",
            "type":"Retail Goods"
        }
    ],
    "sg:phone":"+1 208 338 3828",
    "sg:postcode":"83703",
    "sg:province":"ID",
    "sg:tags":[
        "cards",
        "sport",
        "baseball",
        "memorabilia"
    ],
    "wof:name":"Jerry's Rookie Shop",
    "wof:placetype":"venue"
},
  "geometry": {"coordinates":[-116.22718399999999,43.634595],"type":"Point"}
}