{
  "type": "Feature",
  "properties": {
    "iso:country":"US",
    "sg:address":"1160 Torino Ave",
    "sg:city":"Meridian",
    "sg:classifiers":[
        {
            "category":"Freight",
            "type":"Transportation"
        }
    ],
    "sg:phone":"+1 208 846 8917",
    "sg:postcode":"83642",
    "sg:province":"ID",
    "sg:tags":[
        "operator",
        "local",
        "trucking"
    ],
    "wof:name":"Melvin Enterprises Inc",
    "wof:placetype":"venue"
},
  "geometry": {"coordinates":[-116.372557,43.595544],"type":"Point"}
}