{
  "type": "Feature",
  "properties": {
    "iso:country":"US",
    "sg:address":"15 E Cameron Ave",
    "sg:city":"Kellogg",
    "sg:classifiers":[
        {
            "category":"Autos & Motor Vehicles",
            "subcategory":"Auto Supplies",
            "type":"Retail Goods"
        }
    ],
    "sg:phone":"+1 208 783 1105",
    "sg:postcode":"83837",
    "sg:province":"ID",
    "sg:tags":[
        "tire"
    ],
    "sg:website":"www.lesschwab.com",
    "wof:name":"Les Schwab Tire Ctr",
    "wof:placetype":"venue"
},
  "geometry": {"coordinates":[-116.118111,47.537826],"type":"Point"}
}