{
  "type": "Feature",
  "properties": {
    "addr:full":"132 S Shilling Ave Blackfoot ID 83221",
    "addr:housenumber":"132",
    "addr:postcode":"83221",
    "addr:street":"S Shilling Ave",
    "iso:country":"US",
    "sg:address":"132 S Shilling Ave",
    "sg:city":"Blackfoot",
    "sg:classifiers":[
        {
            "category":"Education",
            "subcategory":"College",
            "type":"Public Place"
        }
    ],
    "sg:phone":"+1 208 785 8060",
    "sg:postcode":"83221",
    "sg:province":"ID",
    "sg:tags":[
        "executive"
    ],
    "wof:name":"Bingham County Coop Extenion",
    "wof:placetype":"venue"
},
  "geometry": {"coordinates":[-112.343857,43.18656],"type":"Point"}
}