{
  "type": "Feature",
  "properties": {
    "addr:full":"115 N Clark St Rigby ID 83442",
    "addr:housenumber":"115",
    "addr:postcode":"83442",
    "addr:street":"N Clark St",
    "iso:country":"US",
    "sg:address":"115 N Clark St",
    "sg:city":"Rigby",
    "sg:classifiers":[
        {
            "category":"Real Estate",
            "subcategory":"Real Estate Services",
            "type":"Services"
        }
    ],
    "sg:phone":"+1 208 745 1090",
    "sg:postcode":"83442",
    "sg:province":"ID",
    "sg:tags":[
        "company",
        "title"
    ],
    "wof:name":"Ameri Title",
    "wof:placetype":"venue"
},
  "geometry": {"coordinates":[-111.911996,43.672298],"type":"Point"}
}