{
  "type": "Feature",
  "properties": {
    "iso:country":"US",
    "sg:address":"119 N 9th St",
    "sg:city":"Boise",
    "sg:classifiers":[
        {
            "category":"Banks & Credit Unions",
            "subcategory":"Bank",
            "type":"Services"
        }
    ],
    "sg:phone":"+1 208 393 2120",
    "sg:postcode":"83702",
    "sg:province":"ID",
    "sg:website":"www.wellsfargo.com",
    "wof:name":"Wells Fargo Bank",
    "wof:placetype":"venue"
},
  "geometry": {"coordinates":[-116.204082,43.616891],"type":"Point"}
}