{
  "type": "Feature",
  "properties": {
    "addr:full":"6554 Cougar Ridge Dr Lewiston ID 83501",
    "addr:housenumber":"6554",
    "addr:postcode":"83501",
    "addr:street":"Cougar Ridge Dr",
    "iso:country":"US",
    "sg:address":"6554 Cougar Ridge Dr",
    "sg:city":"Lewiston",
    "sg:classifiers":[
        {
            "category":"Restaurant",
            "type":"Food & Drink"
        }
    ],
    "sg:phone":"+1 208 798 8824",
    "sg:postcode":"83501",
    "sg:province":"ID",
    "wof:name":"Barchetta Carrozzeria",
    "wof:placetype":"venue"
},
  "geometry": {"coordinates":[-116.93712499999999,46.408678],"type":"Point"}
}