{
  "type": "Feature",
  "properties": {
    "iso:country":"US",
    "sg:address":"600 W Dalton Ave",
    "sg:city":"Coeur D Alene",
    "sg:classifiers":[
        {
            "category":"Manufacturing",
            "subcategory":"Tools & Machinery",
            "type":"Manufacturing & Wholesale Goods"
        }
    ],
    "sg:phone":"+1 208 667 8093",
    "sg:postcode":"83815",
    "sg:province":"ID",
    "sg:tags":[
        "water",
        "equipment",
        "works",
        "supply"
    ],
    "wof:name":"FNW/Ferguson",
    "wof:placetype":"venue"
},
  "geometry": {"coordinates":[-116.795031,47.722657],"type":"Point"}
}