{
  "type": "Feature",
  "properties": {
    "addr:full":"16 Emmett Hwy Emmett ID 83616",
    "addr:housenumber":"16",
    "addr:postcode":"83616",
    "addr:street":"Emmett Hwy",
    "iso:country":"US",
    "sg:address":"16 Emmett Hwy",
    "sg:city":"Emmett",
    "sg:classifiers":[
        {
            "category":"Real Estate",
            "subcategory":"Real Estate Agent",
            "type":"Services"
        }
    ],
    "sg:phone":"+1 208 365 0693",
    "sg:postcode":"83616",
    "sg:province":"ID",
    "sg:website":"www.emmett1.com",
    "wof:name":"Emmett 1 Real Estate",
    "wof:placetype":"venue"
},
  "geometry": {"coordinates":[-116.458247,43.706463],"type":"Point"}
}