{
  "type": "Feature",
  "properties": {
    "iso:country":"US",
    "sg:address":"706 S Main St",
    "sg:city":"Hailey",
    "sg:classifiers":[
        {
            "category":"Health Services",
            "subcategory":"Doctor",
            "type":"Services"
        }
    ],
    "sg:phone":"+1 208 788 3434",
    "sg:postcode":"83333",
    "sg:province":"ID",
    "sg:tags":[
        "clinic"
    ],
    "wof:name":"Hailey Medical Clinic",
    "wof:placetype":"venue"
},
  "geometry": {"coordinates":[-114.311001,43.513874],"type":"Point"}
}