{
  "type": "Feature",
  "properties": {
    "iso:country":"US",
    "sg:address":"1425 N Holmes Ave",
    "sg:city":"Idaho Falls",
    "sg:classifiers":[
        {
            "category":"Home & Garden",
            "subcategory":"Building Materials",
            "type":"Retail Goods"
        }
    ],
    "sg:phone":"+1 208 522 5571",
    "sg:postcode":"83401",
    "sg:province":"ID",
    "sg:website":"www.bmcwest.com",
    "wof:name":"BMC West Building Materials",
    "wof:placetype":"venue"
},
  "geometry": {"coordinates":[-112.02399699999999,43.511082],"type":"Point"}
}