{
  "type": "Feature",
  "properties": {
    "addr:full":"824 E Center St Pocatello ID 83201",
    "addr:housenumber":"824",
    "addr:postcode":"83201",
    "addr:street":"E Center St",
    "iso:country":"US",
    "sg:address":"824 E Center St",
    "sg:city":"Pocatello",
    "sg:classifiers":[
        {
            "category":"Real Estate",
            "subcategory":"Real Estate Agent",
            "type":"Services"
        }
    ],
    "sg:phone":"+1 208 234 1776",
    "sg:postcode":"83201",
    "sg:province":"ID",
    "wof:name":"Gate City Gmac",
    "wof:placetype":"venue"
},
  "geometry": {"coordinates":[-112.441198,42.868057],"type":"Point"}
}