{
  "type": "Feature",
  "properties": {
    "iso:country":"US",
    "sg:address":"3355 N Five Mile Rd",
    "sg:city":"Boise",
    "sg:classifiers":[
        {
            "category":"Professional",
            "subcategory":"Advertising",
            "type":"Services"
        }
    ],
    "sg:phone":"+1 208 377 4913",
    "sg:postcode":"83713",
    "sg:province":"ID",
    "sg:tags":[
        "mail"
    ],
    "wof:name":"Mailbox Merchants",
    "wof:placetype":"venue"
},
  "geometry": {"coordinates":[-116.31441700000001,43.634239],"type":"Point"}
}