{
  "type": "Feature",
  "properties": {
    "addr:full":"115 W A St Shoshone ID 83352",
    "addr:housenumber":"115",
    "addr:postcode":"83352",
    "addr:street":"W A St",
    "iso:country":"US",
    "sg:address":"115 W A St",
    "sg:city":"Shoshone",
    "sg:classifiers":[
        {
            "category":"Government",
            "subcategory":"Office",
            "type":"Public Place"
        }
    ],
    "sg:phone":"+1 208 886 7672",
    "sg:postcode":"83352",
    "sg:province":"ID",
    "wof:name":"Lincoln County Juvenile Prbtn",
    "wof:placetype":"venue"
},
  "geometry": {"coordinates":[-114.408509,42.934889],"type":"Point"}
}