{
  "type": "Feature",
  "properties": {
    "iso:country":"US",
    "sg:address":"4828 Yellowstone Ave",
    "sg:city":"Pocatello",
    "sg:classifiers":[
        {
            "category":"Bars & Pubs",
            "type":"Food & Drink"
        }
    ],
    "sg:phone":"+1 208 237 9950",
    "sg:postcode":"83202",
    "sg:province":"ID",
    "sg:tags":[
        "club",
        "night"
    ],
    "wof:name":"Bobby Jo's Five Mile Inn",
    "wof:placetype":"venue"
},
  "geometry": {"coordinates":[-112.466272,42.92089],"type":"Point"}
}