{
  "type": "Feature",
  "properties": {
    "iso:country":"US",
    "sg:address":"158 Blake St N",
    "sg:city":"Twin Falls",
    "sg:classifiers":[
        {
            "category":"Social Services",
            "subcategory":"Job Training",
            "type":"Services"
        }
    ],
    "sg:phone":"+1 208 734 1370",
    "sg:postcode":"83301",
    "sg:province":"ID",
    "sg:tags":[
        "retardation",
        "disabled",
        "mental",
        "dev"
    ],
    "wof:name":"Clearwater Care Ctr",
    "wof:placetype":"venue"
},
  "geometry": {"coordinates":[-114.48479,42.563704],"type":"Point"}
}