{
  "type": "Feature",
  "properties": {
    "iso:country":"US",
    "sg:address":"24515 Boehner Rd",
    "sg:city":"Wilder",
    "sg:classifiers":[
        {
            "category":"Real Estate",
            "subcategory":"Real Estate Operator",
            "type":"Services"
        }
    ],
    "sg:phone":"+1 208 482 7542",
    "sg:postcode":"83676",
    "sg:province":"ID",
    "sg:tags":[
        "property",
        "lessor"
    ],
    "wof:name":"Bucy Farms",
    "wof:placetype":"venue"
},
  "geometry": {"coordinates":[-116.872754,43.639671],"type":"Point"}
}