{
  "type": "Feature",
  "properties": {
    "iso:country":"US",
    "sg:address":"520 S Meridian Rd",
    "sg:city":"Meridian",
    "sg:classifiers":[
        {
            "category":"Professional",
            "subcategory":"Management & Consulting",
            "type":"Services"
        }
    ],
    "sg:phone":"+1 208 846 9600",
    "sg:postcode":"83642",
    "sg:province":"ID",
    "sg:tags":[
        "construction"
    ],
    "wof:name":"Mc Cabe Properties",
    "wof:placetype":"venue"
},
  "geometry": {"coordinates":[-116.393569,43.600538],"type":"Point"}
}