{
  "type": "Feature",
  "properties": {
    "iso:country":"US",
    "sg:address":"1607 Davis Ave",
    "sg:city":"Mccall",
    "sg:classifiers":[
        {
            "category":"Building & Trades",
            "subcategory":"Construction",
            "type":"Services"
        }
    ],
    "sg:phone":"+1 208 634 3740",
    "sg:postcode":"83638",
    "sg:province":"ID",
    "sg:tags":[
        "designer",
        "dealer",
        "pool",
        "swimming"
    ],
    "wof:name":"Central Idaho Pool & Spa",
    "wof:placetype":"venue"
},
  "geometry": {"coordinates":[-116.090409,44.91837],"type":"Point"}
}