{
  "type": "Feature",
  "properties": {
    "addr:full":"39 E 1st North St Paris ID 83261",
    "addr:housenumber":"39",
    "addr:postcode":"83261",
    "addr:street":"E 1St North St",
    "iso:country":"US",
    "sg:address":"39 E 1st North St",
    "sg:city":"Paris",
    "sg:classifiers":[
        {
            "category":"Travel",
            "subcategory":"Travel Agent",
            "type":"Entertainment"
        }
    ],
    "sg:phone":"+1 208 847 5358",
    "sg:postcode":"83261",
    "sg:province":"ID",
    "sg:tags":[
        "agency",
        "bureau"
    ],
    "wof:name":"Global Travel",
    "wof:placetype":"venue"
},
  "geometry": {"coordinates":[-111.400244,42.229122],"type":"Point"}
}