{
  "type": "Feature",
  "properties": {
    "addr:full":"1024 N 4th St Coeur D Alene ID 83814",
    "addr:housenumber":"1024",
    "addr:postcode":"83814",
    "addr:street":"N 4Th St Coeur D",
    "iso:country":"US",
    "sg:address":"1024 N 4th St",
    "sg:city":"Coeur D Alene",
    "sg:classifiers":[
        {
            "category":"Autos & Motor Vehicles",
            "subcategory":"Auto Supplies",
            "type":"Retail Goods"
        }
    ],
    "sg:phone":"+1 208 664 3713",
    "sg:postcode":"83814",
    "sg:province":"ID",
    "sg:tags":[
        "automobile",
        "stereo",
        "radio"
    ],
    "wof:name":"J & D Stereo",
    "wof:placetype":"venue"
},
  "geometry": {"coordinates":[-116.780681,47.683957],"type":"Point"}
}