{
  "type": "Feature",
  "properties": {
    "addr:full":"2423 Oakley Ave Twin Falls ID 83301",
    "addr:housenumber":"2423",
    "addr:postcode":"83301",
    "addr:street":"Oakley Ave",
    "iso:country":"US",
    "sg:address":"2423 Oakley Ave",
    "sg:city":"Twin Falls",
    "sg:classifiers":[
        {
            "category":"Building & Trades",
            "subcategory":"Construction",
            "type":"Services"
        }
    ],
    "sg:phone":"+1 208 655 4342",
    "sg:postcode":"83301",
    "sg:province":"ID",
    "sg:tags":[
        "contractor"
    ],
    "wof:name":"Reliable Roofing",
    "wof:placetype":"venue"
},
  "geometry": {"coordinates":[-114.578256,42.352471],"type":"Point"}
}