{
  "type": "Feature",
  "properties": {
    "iso:country":"US",
    "sg:address":"2716 S Colorado Ave",
    "sg:city":"Caldwell",
    "sg:classifiers":[
        {
            "category":"Building & Trades",
            "subcategory":"Plumbing",
            "type":"Services"
        }
    ],
    "sg:phone":"+1 208 453 2135",
    "sg:postcode":"83605",
    "sg:province":"ID",
    "sg:tags":[
        "heating",
        "contractor"
    ],
    "wof:name":"Hardy Brothers Heating",
    "wof:placetype":"venue"
},
  "geometry": {"coordinates":[-116.682002,43.646086],"type":"Point"}
}