{
  "type": "Feature",
  "properties": {
    "iso:country":"US",
    "sg:address":"1191 E Airport Rd",
    "sg:city":"Blackfoot",
    "sg:classifiers":[
        {
            "category":"Food & Beverages",
            "subcategory":"Specialty",
            "type":"Retail Goods"
        }
    ],
    "sg:phone":"+1 208 785 3628",
    "sg:postcode":"83221",
    "sg:province":"ID",
    "sg:tags":[
        "health",
        "diet"
    ],
    "sg:website":"www.dstoddy.com",
    "wof:name":"D & S Svc",
    "wof:placetype":"venue"
},
  "geometry": {"coordinates":[-112.33942999999999,43.207375],"type":"Point"}
}