{
  "type": "Feature",
  "properties": {
    "iso:country":"US",
    "sg:address":"1129 Main St",
    "sg:city":"Buhl",
    "sg:classifiers":[
        {
            "category":"Retail",
            "subcategory":"Auto Repair",
            "type":"Services"
        }
    ],
    "sg:phone":"+1 208 543 8000",
    "sg:postcode":"83316",
    "sg:province":"ID",
    "sg:tags":[
        "repairing",
        "automobile"
    ],
    "wof:name":"Tune Tech-N-Muffler",
    "wof:placetype":"venue"
},
  "geometry": {"coordinates":[-114.760756,42.598029],"type":"Point"}
}