{
  "type": "Feature",
  "properties": {
    "addr:full":"407 Leadville Ave Ketchum ID 83340",
    "addr:housenumber":"407",
    "addr:postcode":"83340",
    "addr:street":"Leadville Ave",
    "iso:country":"US",
    "sg:address":"407 Leadville Ave",
    "sg:city":"Ketchum",
    "sg:classifiers":[
        {
            "category":"Insurance",
            "subcategory":"Insurance Agent",
            "type":"Services"
        }
    ],
    "sg:phone":"+1 208 726 9213",
    "sg:postcode":"83340",
    "sg:province":"ID",
    "wof:name":"Farmers Insurance Group",
    "wof:placetype":"venue"
},
  "geometry": {"coordinates":[-114.35982300000001,43.678633],"type":"Point"}
}