{
  "type": "Feature",
  "properties": {
    "iso:country":"US",
    "sg:address":"1685 E 500 N",
    "sg:city":"St Anthony",
    "sg:classifiers":[
        {
            "category":"Travel",
            "subcategory":"Campground",
            "type":"Entertainment"
        }
    ],
    "sg:phone":"+1 208 624 3275",
    "sg:postcode":"83445",
    "sg:province":"ID",
    "sg:tags":[
        "recreational",
        "parks",
        "vehicle"
    ],
    "wof:name":"Desert Oasis Rv Park",
    "wof:placetype":"venue"
},
  "geometry": {"coordinates":[-111.82187399999999,43.95624],"type":"Point"}
}