{
  "type": "Feature",
  "properties": {
    "iso:country":"US",
    "sg:address":"36 E Pine Ave",
    "sg:city":"Meridian",
    "sg:classifiers":[
        {
            "category":"Real Estate",
            "subcategory":"Developer",
            "type":"Services"
        }
    ],
    "sg:phone":"+1 208 895 8858",
    "sg:postcode":"83642",
    "sg:province":"ID",
    "wof:name":"Heartland Development",
    "wof:placetype":"venue"
},
  "geometry": {"coordinates":[-116.392081,43.612024],"type":"Point"}
}