{
  "type": "Feature",
  "properties": {
    "addr:full":"4024 W Loxton Loop Coeur D Alene ID 83815",
    "addr:housenumber":"4024",
    "addr:postcode":"83815",
    "addr:street":"W Loxton Loop",
    "iso:country":"US",
    "sg:address":"4024 W Loxton Loop",
    "sg:city":"Coeur D Alene",
    "sg:classifiers":[
        {
            "category":"Real Estate",
            "subcategory":"Real Estate Agent",
            "type":"Services"
        }
    ],
    "sg:phone":"+1 208 762 0786",
    "sg:postcode":"83815",
    "sg:province":"ID",
    "sg:tags":[
        "inspection"
    ],
    "wof:name":"America's Home Inspection Svc",
    "wof:placetype":"venue"
},
  "geometry": {"coordinates":[-116.830726,47.741853],"type":"Point"}
}