{
  "type": "Feature",
  "properties": {
    "iso:country":"US",
    "sg:address":"426 Main Ave S",
    "sg:city":"Twin Falls",
    "sg:classifiers":[
        {
            "category":"Organizations",
            "subcategory":"Non-profit Organization",
            "type":"Services"
        }
    ],
    "sg:phone":"+1 208 735 1126",
    "sg:postcode":"83301",
    "sg:province":"ID",
    "wof:name":"Success By 6",
    "wof:placetype":"venue"
},
  "geometry": {"coordinates":[-114.46615300000001,42.552872],"type":"Point"}
}