{
  "type": "Feature",
  "properties": {
    "iso:country":"US",
    "sg:address":"622 Center St W",
    "sg:city":"Kimberly",
    "sg:classifiers":[
        {
            "category":"Freight",
            "type":"Transportation"
        }
    ],
    "sg:phone":"+1 208 423 5977",
    "sg:postcode":"83341",
    "sg:province":"ID",
    "sg:tags":[
        "operator",
        "local",
        "trucking"
    ],
    "wof:name":"Atkinson Custom Hauling",
    "wof:placetype":"venue"
},
  "geometry": {"coordinates":[-114.372016,42.533736],"type":"Point"}
}