{
  "type": "Feature",
  "properties": {
    "iso:country":"US",
    "sg:address":"406 South St",
    "sg:city":"Parma",
    "sg:classifiers":[
        {
            "category":"Government",
            "subcategory":"Office",
            "type":"Public Place"
        }
    ],
    "sg:phone":"+1 208 722 6088",
    "sg:postcode":"83660",
    "sg:province":"ID",
    "sg:tags":[
        "village"
    ],
    "wof:name":"Parma City Shop",
    "wof:placetype":"venue"
},
  "geometry": {"coordinates":[-116.942069,43.781492],"type":"Point"}
}