{
  "type": "Feature",
  "properties": {
    "addr:full":"23141 Upper Pleasant Ridge Rd Wilder ID 83676",
    "addr:housenumber":"23141",
    "addr:postcode":"83676",
    "addr:street":"Upper Pleasant Ridge Rd",
    "iso:country":"US",
    "sg:address":"23141 Upper Pleasant Ridge Rd",
    "sg:city":"Wilder",
    "sg:classifiers":[
        {
            "category":"Building & Trades",
            "subcategory":"Construction",
            "type":"Services"
        }
    ],
    "sg:phone":"+1 208 459 4114",
    "sg:postcode":"83676",
    "sg:province":"ID",
    "sg:tags":[
        "house"
    ],
    "wof:name":"Bk Construction",
    "wof:placetype":"venue"
},
  "geometry": {"coordinates":[-116.854786,43.647115],"type":"Point"}
}