{
  "type": "Feature",
  "properties": {
    "iso:country":"US",
    "sg:address":"2390 American Legion Blvd",
    "sg:city":"Mountain Home",
    "sg:classifiers":[
        {
            "category":"Manufacturing",
            "subcategory":"Printing",
            "type":"Manufacturing & Wholesale Goods"
        }
    ],
    "sg:phone":"+1 208 587 9011",
    "sg:postcode":"83647",
    "sg:province":"ID",
    "sg:tags":[
        "printer"
    ],
    "wof:name":"First Class Inc",
    "wof:placetype":"venue"
},
  "geometry": {"coordinates":[-115.670542,43.133948],"type":"Point"}
}