{
  "type": "Feature",
  "properties": {
    "iso:country":"US",
    "sg:address":"2504 N Snow Goose Way",
    "sg:city":"Meridian",
    "sg:classifiers":[
        {
            "category":"Banks & Credit Unions",
            "subcategory":"Bank",
            "type":"Services"
        }
    ],
    "sg:phone":"+1 208 898 9015",
    "sg:postcode":"83646",
    "sg:province":"ID",
    "sg:tags":[
        "loan",
        "real estate"
    ],
    "wof:name":"Idahome Loans",
    "wof:placetype":"venue"
},
  "geometry": {"coordinates":[-116.381243,43.62752],"type":"Point"}
}