{
  "type": "Feature",
  "properties": {
    "iso:country":"US",
    "sg:address":"840 Main St",
    "sg:city":"Lewiston",
    "sg:classifiers":[
        {
            "category":"Communications",
            "subcategory":"Film & Video Production",
            "type":"Services"
        }
    ],
    "sg:phone":"+1 208 743 5855",
    "sg:postcode":"83501",
    "sg:province":"ID",
    "sg:tags":[
        "taping"
    ],
    "wof:name":"Digital Barn Productions",
    "wof:placetype":"venue"
},
  "geometry": {"coordinates":[-117.02240399999999,46.41981],"type":"Point"}
}