{
  "type": "Feature",
  "properties": {
    "addr:full":"10475 Missouri Ave Nampa ID 83686",
    "addr:housenumber":"10475",
    "addr:postcode":"83686",
    "addr:street":"Missouri Ave",
    "iso:country":"US",
    "sg:address":"10475 Missouri Ave",
    "sg:city":"Nampa",
    "sg:phone":"+1 208 466 3895",
    "sg:postcode":"83686",
    "sg:province":"ID",
    "sg:tags":[
        "fee",
        "beef",
        "farm",
        "cash",
        "crop",
        "field",
        "grain",
        "cattle"
    ],
    "wof:name":"Sayers Elbern",
    "wof:placetype":"venue"
},
  "geometry": {"coordinates":[-116.601957,43.488307],"type":"Point"}
}