{
  "type": "Feature",
  "properties": {
    "addr:full":"320 N Orchard St Boise ID 83706",
    "addr:housenumber":"320",
    "addr:postcode":"83706",
    "addr:street":"N Orchard St",
    "iso:country":"US",
    "sg:address":"320 N Orchard St",
    "sg:city":"Boise",
    "sg:classifiers":[
        {
            "category":"Health Services",
            "subcategory":"Medical Lab",
            "type":"Services"
        }
    ],
    "sg:phone":"+1 208 323 7790",
    "sg:postcode":"83706",
    "sg:province":"ID",
    "wof:name":"Public Denture Ctr",
    "wof:placetype":"venue"
},
  "geometry": {"coordinates":[-116.243388,43.607629],"type":"Point"}
}