{
  "type": "Feature",
  "properties": {
    "iso:country":"US",
    "sg:address":"120 Thain Rd",
    "sg:city":"Lewiston",
    "sg:classifiers":[
        {
            "category":"Shopping",
            "subcategory":"Bicycles & Sporting Goods",
            "type":"Retail Goods"
        }
    ],
    "sg:phone":"+1 208 746 5307",
    "sg:postcode":"83501",
    "sg:province":"ID",
    "wof:name":"Tri-State Outfitters",
    "wof:placetype":"venue"
},
  "geometry": {"coordinates":[-116.98958500000001,46.390001],"type":"Point"}
}