{
  "type": "Feature",
  "properties": {
    "iso:country":"US",
    "sg:address":"12329 E Frontage Rd",
    "sg:city":"Coeur D Alene",
    "sg:classifiers":[
        {
            "category":"Travel",
            "subcategory":"Campground",
            "type":"Entertainment"
        }
    ],
    "sg:phone":"+1 208 664 2812",
    "sg:postcode":"83814",
    "sg:province":"ID",
    "wof:name":"Wolf Lodge Campground",
    "wof:placetype":"venue"
},
  "geometry": {"coordinates":[-116.630455,47.627252],"type":"Point"}
}