{
  "type": "Feature",
  "properties": {
    "iso:country":"US",
    "sg:address":"1590 Yellowstone Ave",
    "sg:city":"Pocatello",
    "sg:classifiers":[
        {
            "category":"Banks & Credit Unions",
            "subcategory":"Bank",
            "type":"Services"
        }
    ],
    "sg:phone":"+1 208 233 6176",
    "sg:postcode":"83201",
    "sg:province":"ID",
    "sg:website":"www.zionsbank.com",
    "wof:name":"Zions Bank",
    "wof:placetype":"venue"
},
  "geometry": {"coordinates":[-112.451191,42.90413],"type":"Point"}
}