{
  "type": "Feature",
  "properties": {
    "addr:full":"1590 Yellowstone Ave Pocatello ID 83201",
    "addr:housenumber":"1590",
    "addr:postcode":"83201",
    "addr:street":"Yellowstone Ave",
    "iso:country":"US",
    "sg:address":"1590 Yellowstone Ave",
    "sg:city":"Pocatello",
    "sg:classifiers":[
        {
            "category":"Banks & Credit Unions",
            "subcategory":"Bank",
            "type":"Services"
        }
    ],
    "sg:phone":"+1 208 233 6176",
    "sg:postcode":"83201",
    "sg:province":"ID",
    "sg:website":"www.zionsbank.com",
    "wof:name":"Zions Bank",
    "wof:placetype":"venue"
},
  "geometry": {"coordinates":[-112.45119099999999,42.90413],"type":"Point"}
}