{
  "type": "Feature",
  "properties": {
    "iso:country":"US",
    "sg:address":"737 S Capital Ave",
    "sg:city":"Idaho Falls",
    "sg:classifiers":[
        {
            "category":"Wholesale",
            "subcategory":"Meat",
            "type":"Manufacturing & Wholesale Goods"
        }
    ],
    "sg:phone":"+1 208 227 9013",
    "sg:postcode":"83402",
    "sg:province":"ID",
    "sg:tags":[
        "product"
    ],
    "wof:name":"Enter Mountain Natural",
    "wof:placetype":"venue"
},
  "geometry": {"coordinates":[-112.04653500000001,43.485934],"type":"Point"}
}