{
  "type": "Feature",
  "properties": {
    "iso:country":"US",
    "sg:address":"209 E Ada Ave",
    "sg:city":"Meridian",
    "sg:classifiers":[
        {
            "category":"Shopping",
            "subcategory":"Discount & Variety Stores",
            "type":"Retail Goods"
        }
    ],
    "sg:phone":"+1 208 362 7123",
    "sg:postcode":"83642",
    "sg:province":"ID",
    "sg:tags":[
        "merchandise",
        "general"
    ],
    "wof:name":"Lumin-Essence",
    "wof:placetype":"venue"
},
  "geometry": {"coordinates":[-116.388836,43.606911],"type":"Point"}
}