{
  "type": "Feature",
  "properties": {
    "iso:country":"US",
    "sg:address":"780 Cleveland St",
    "sg:city":"Idaho Falls",
    "sg:classifiers":[
        {
            "category":"Manufacturing",
            "subcategory":"Printing",
            "type":"Manufacturing & Wholesale Goods"
        }
    ],
    "sg:phone":"+1 208 523 1839",
    "sg:postcode":"83401",
    "sg:province":"ID",
    "sg:tags":[
        "commercial"
    ],
    "wof:name":"Lyle F Hansen Printing",
    "wof:placetype":"venue"
},
  "geometry": {"coordinates":[-112.017413,43.499545],"type":"Point"}
}