{
  "type": "Feature",
  "properties": {
    "addr:full":"5116 Emerald St Boise ID 83706",
    "addr:housenumber":"5116",
    "addr:postcode":"83706",
    "addr:street":"Emerald St",
    "iso:country":"US",
    "sg:address":"5116 Emerald St",
    "sg:city":"Boise",
    "sg:classifiers":[
        {
            "category":"Shopping",
            "subcategory":"Gifts & Souvenirs",
            "type":"Retail Goods"
        }
    ],
    "sg:phone":"+1 208 939 2925",
    "sg:postcode":"83706",
    "sg:province":"ID",
    "sg:tags":[
        "party",
        "supply"
    ],
    "wof:name":"Diamond Rental",
    "wof:placetype":"venue"
},
  "geometry": {"coordinates":[-116.244811,43.611689],"type":"Point"}
}