{
  "type": "Feature",
  "properties": {
    "addr:full":"1980 Denell Way Boise ID 83709",
    "addr:housenumber":"1980",
    "addr:postcode":"83709",
    "addr:street":"Denell Way",
    "iso:country":"US",
    "sg:address":"1980 Denell Way",
    "sg:city":"Boise",
    "sg:classifiers":[
        {
            "category":"Building & Trades",
            "subcategory":"Construction",
            "type":"Services"
        }
    ],
    "sg:phone":"+1 208 322 8849",
    "sg:postcode":"83709",
    "sg:province":"ID",
    "sg:tags":[
        "dry wall",
        "contractor"
    ],
    "wof:name":"Jds Inc",
    "wof:placetype":"venue"
},
  "geometry": {"coordinates":[-116.310148,43.586169],"type":"Point"}
}