{
  "type": "Feature",
  "properties": {
    "iso:country":"US",
    "sg:address":"1612 W Jefferson St",
    "sg:city":"Boise",
    "sg:classifiers":[
        {
            "category":"Health Services",
            "subcategory":"Health Practitioner",
            "type":"Services"
        }
    ],
    "sg:phone":"+1 208 338 0405",
    "sg:postcode":"83702",
    "sg:province":"ID",
    "sg:tags":[
        "physician"
    ],
    "wof:name":"Shelby Entner",
    "wof:placetype":"venue"
},
  "geometry": {"coordinates":[-116.21173,43.623263],"type":"Point"}
}