{
  "type": "Feature",
  "properties": {
    "iso:country":"US",
    "sg:address":"350 G St",
    "sg:city":"Idaho Falls",
    "sg:classifiers":[
        {
            "category":"Education",
            "subcategory":"School",
            "type":"Public Place"
        }
    ],
    "sg:phone":"+1 208 522 6236",
    "sg:postcode":"83402",
    "sg:province":"ID",
    "wof:name":"Castillito MHS",
    "wof:placetype":"venue"
},
  "geometry": {"coordinates":[-112.03674,43.497217],"type":"Point"}
}