{
  "type": "Feature",
  "properties": {
    "addr:full":"47 S 100 W Jerome ID 83338",
    "addr:housenumber":"47;100",
    "addr:postcode":"83338",
    "addr:street":"S;W Jerome",
    "iso:country":"US",
    "sg:address":"47 S 100 W",
    "sg:city":"Jerome",
    "sg:classifiers":[
        {
            "category":"Shopping",
            "subcategory":"Discount & Variety Stores",
            "type":"Retail Goods"
        }
    ],
    "sg:phone":"+1 208 324 3030",
    "sg:postcode":"83338",
    "sg:province":"ID",
    "sg:tags":[
        "merchandise",
        "general"
    ],
    "wof:name":"J & N Sales",
    "wof:placetype":"venue"
},
  "geometry": {"coordinates":[-114.537978,42.71644],"type":"Point"}
}