{
  "type": "Feature",
  "properties": {
    "addr:full":"4951 N Mitchell St Boise ID 83704",
    "addr:housenumber":"4951",
    "addr:postcode":"83704",
    "addr:street":"N Mitchell St",
    "iso:country":"US",
    "sg:address":"4951 N Mitchell St",
    "sg:city":"Boise",
    "sg:classifiers":[
        {
            "category":"Organizations",
            "subcategory":"Religious Organization",
            "type":"Services"
        }
    ],
    "sg:phone":"+1 208 375 9618",
    "sg:postcode":"83704",
    "sg:province":"ID",
    "wof:name":"Family History Center",
    "wof:placetype":"venue"
},
  "geometry": {"coordinates":[-116.30422799999999,43.650055],"type":"Point"}
}