{
  "type": "Feature",
  "properties": {
    "iso:country":"US",
    "sg:address":"23751 Hoskins Rd",
    "sg:city":"Homedale",
    "sg:classifiers":[
        {
            "category":"Professional",
            "type":"Services"
        }
    ],
    "sg:phone":"+1 208 337 5325",
    "sg:postcode":"83676",
    "sg:province":"ID",
    "sg:tags":[
        "establishment"
    ],
    "wof:name":"GMO Livestock Product",
    "wof:placetype":"venue"
},
  "geometry": {"coordinates":[-116.86646500000001,43.603139],"type":"Point"}
}