{
  "type": "Feature",
  "properties": {
    "addr:full":"9133 W Highland Dr Coeur D Alene ID 83814",
    "addr:housenumber":"9133",
    "addr:postcode":"83814",
    "addr:street":"W Highland Dr",
    "iso:country":"US",
    "sg:address":"9133 W Highland Dr",
    "sg:city":"Coeur D Alene",
    "sg:classifiers":[
        {
            "category":"Banks & Credit Unions",
            "subcategory":"Investment Brokerage",
            "type":"Services"
        }
    ],
    "sg:phone":"+1 208 777 8006",
    "sg:postcode":"83814",
    "sg:province":"ID",
    "wof:name":"Highland Financial",
    "wof:placetype":"venue"
},
  "geometry": {"coordinates":[-116.90966899999999,47.689898],"type":"Point"}
}