{
  "type": "Feature",
  "properties": {
    "iso:country":"US",
    "sg:address":"118 E 37th St",
    "sg:city":"Boise",
    "sg:classifiers":[
        {
            "category":"Professional",
            "subcategory":"Testing Lab",
            "type":"Services"
        }
    ],
    "sg:phone":"+1 208 331 2566",
    "sg:postcode":"83714",
    "sg:province":"ID",
    "sg:tags":[
        "laboratory"
    ],
    "wof:name":"Alpha Testing Labs",
    "wof:placetype":"venue"
},
  "geometry": {"coordinates":[-116.241084,43.626212],"type":"Point"}
}