{
  "type": "Feature",
  "properties": {
    "addr:full":"651 Saratoga Dr Twin Falls ID 83301",
    "addr:housenumber":"651",
    "addr:postcode":"83301",
    "addr:street":"Saratoga Dr",
    "iso:country":"US",
    "sg:address":"651 Saratoga Dr",
    "sg:city":"Twin Falls",
    "sg:classifiers":[
        {
            "category":"Real Estate",
            "subcategory":"Real Estate Operator",
            "type":"Services"
        }
    ],
    "sg:phone":"+1 208 735 1600",
    "sg:postcode":"83301",
    "sg:province":"ID",
    "sg:tags":[
        "apartment"
    ],
    "wof:name":"Saratoga Apartments",
    "wof:placetype":"venue"
},
  "geometry": {"coordinates":[-114.49342300000001,42.573589],"type":"Point"}
}