{
  "type": "Feature",
  "properties": {
    "iso:country":"US",
    "sg:address":"832 Blue Lakes Blvd N",
    "sg:city":"Twin Falls",
    "sg:classifiers":[
        {
            "category":"Personal",
            "subcategory":"Beauty Salon",
            "type":"Services"
        }
    ],
    "sg:phone":"+1 208 733 2321",
    "sg:postcode":"83301",
    "sg:province":"ID",
    "wof:name":"Studio One Hair",
    "wof:placetype":"venue"
},
  "geometry": {"coordinates":[-114.460298,42.576004],"type":"Point"}
}