{
  "type": "Feature",
  "properties": {
    "addr:full":"253 Harrison St American Falls ID 83211",
    "addr:housenumber":"253",
    "addr:postcode":"83211",
    "addr:street":"Harrison St",
    "iso:country":"US",
    "sg:address":"253 Harrison St",
    "sg:city":"American Falls",
    "sg:classifiers":[
        {
            "category":"Shopping",
            "subcategory":"Department Store",
            "type":"Retail Goods"
        }
    ],
    "sg:phone":"+1 208 226 7800",
    "sg:postcode":"83211",
    "sg:province":"ID",
    "sg:tags":[
        "shop"
    ],
    "wof:name":"Family Dollar Store",
    "wof:placetype":"venue"
},
  "geometry": {"coordinates":[-112.852903,42.785068],"type":"Point"}
}