{
  "type": "Feature",
  "properties": {
    "iso:country":"US",
    "sg:address":"830 Blue Lakes Blvd N",
    "sg:city":"Twin Falls",
    "sg:classifiers":[
        {
            "category":"Shopping",
            "subcategory":"Gifts & Souvenirs",
            "type":"Retail Goods"
        }
    ],
    "sg:phone":"+1 208 733 9971",
    "sg:postcode":"83301",
    "sg:province":"ID",
    "sg:tags":[
        "shop"
    ],
    "wof:name":"Black Sheep Gallery",
    "wof:placetype":"venue"
},
  "geometry": {"coordinates":[-114.460221,42.576046],"type":"Point"}
}