{
  "type": "Feature",
  "properties": {
    "iso:country":"US",
    "sg:address":"3085 Backhand Dr",
    "sg:city":"Idaho Falls",
    "sg:classifiers":[
        {
            "category":"Manufacturing",
            "subcategory":"Printing",
            "type":"Manufacturing & Wholesale Goods"
        }
    ],
    "sg:phone":"+1 208 528 8505",
    "sg:postcode":"83406",
    "sg:province":"ID",
    "sg:tags":[
        "lithographic",
        "commercial"
    ],
    "wof:name":"Imprinters",
    "wof:placetype":"venue"
},
  "geometry": {"coordinates":[-111.97341,43.493181],"type":"Point"}
}