{
  "type": "Feature",
  "properties": {
    "iso:country":"US",
    "sg:address":"3557 E Overland Rd",
    "sg:city":"Meridian",
    "sg:classifiers":[
        {
            "category":"Professional",
            "subcategory":"Engineering",
            "type":"Services"
        }
    ],
    "sg:phone":"+1 208 884 0306",
    "sg:postcode":"83642",
    "sg:province":"ID",
    "sg:tags":[
        "engineer"
    ],
    "sg:website":"www.sunrise-eng.com",
    "wof:name":"Sunrise Engineering Inc",
    "wof:placetype":"venue"
},
  "geometry": {"coordinates":[-116.349366,43.590303],"type":"Point"}
}