{
  "type": "Feature",
  "properties": {
    "iso:country":"US",
    "sg:address":"65 S Broadway St",
    "sg:city":"Blackfoot",
    "sg:classifiers":[
        {
            "category":"Food & Beverages",
            "subcategory":"Specialty",
            "type":"Retail Goods"
        }
    ],
    "sg:phone":"+1 208 785 5130",
    "sg:postcode":"83221",
    "sg:province":"ID",
    "sg:tags":[
        "health",
        "diet"
    ],
    "wof:name":"Stow-A-Way Health Foods",
    "wof:placetype":"venue"
},
  "geometry": {"coordinates":[-112.346532,43.188987],"type":"Point"}
}