{
  "type": "Feature",
  "properties": {
    "iso:country":"US",
    "sg:address":"24873 N Corbin Hill Rd",
    "sg:city":"Athol",
    "sg:classifiers":[
        {
            "category":"Professional",
            "type":"Services"
        }
    ],
    "sg:phone":"+1 208 683 9227",
    "sg:postcode":"83801",
    "sg:province":"ID",
    "wof:name":"Ideal-Imaging",
    "wof:placetype":"venue"
},
  "geometry": {"coordinates":[-116.720996,47.884609],"type":"Point"}
}