{
  "type": "Feature",
  "properties": {
    "iso:country":"US",
    "sg:address":"71 S Main St",
    "sg:city":"Soda Springs",
    "sg:classifiers":[
        {
            "category":"Bars & Pubs",
            "type":"Food & Drink"
        }
    ],
    "sg:phone":"+1 208 547 4726",
    "sg:postcode":"83276",
    "sg:province":"ID",
    "wof:name":"Mom & Dad's",
    "wof:placetype":"venue"
},
  "geometry": {"coordinates":[-111.60360300000001,42.657502],"type":"Point"}
}