{
  "type": "Feature",
  "properties": {
    "iso:country":"US",
    "sg:address":"520 E Coeur D Alene Ave",
    "sg:city":"Coeur D Alene",
    "sg:classifiers":[
        {
            "category":"Manufacturing",
            "subcategory":"Printing",
            "type":"Manufacturing & Wholesale Goods"
        }
    ],
    "sg:phone":"+1 208 667 8973",
    "sg:postcode":"83814",
    "sg:province":"ID",
    "sg:tags":[
        "typesetting"
    ],
    "wof:name":"Digitype Inc",
    "wof:placetype":"venue"
},
  "geometry": {"coordinates":[-116.779464,47.675016],"type":"Point"}
}