{
  "type": "Feature",
  "properties": {
    "addr:full":"380 N Capital Ave Idaho Falls ID 83402",
    "addr:housenumber":"380",
    "addr:postcode":"83402",
    "addr:street":"N Capital Ave",
    "iso:country":"US",
    "sg:address":"380 N Capital Ave",
    "sg:city":"Idaho Falls",
    "sg:classifiers":[
        {
            "category":"Professional",
            "subcategory":"Business Services",
            "type":"Services"
        }
    ],
    "sg:phone":"+1 208 589 8621",
    "sg:postcode":"83402",
    "sg:province":"ID",
    "wof:name":"Paisley Group Inc",
    "wof:placetype":"venue"
},
  "geometry": {"coordinates":[-112.042237,43.492334],"type":"Point"}
}