{
  "type": "Feature",
  "properties": {
    "iso:country":"US",
    "sg:address":"280 E Bridge St",
    "sg:city":"Midvale",
    "sg:classifiers":[
        {
            "category":"Organizations",
            "subcategory":"Religious Organization",
            "type":"Services"
        }
    ],
    "sg:phone":"+1 208 355 2242",
    "sg:postcode":"83645",
    "sg:province":"ID",
    "sg:tags":[
        "church"
    ],
    "wof:name":"Baptist Church",
    "wof:placetype":"venue"
},
  "geometry": {"coordinates":[-116.73017,44.47073],"type":"Point"}
}