{
  "type": "Feature",
  "properties": {
    "iso:country":"US",
    "sg:address":"715 Clarence Dr",
    "sg:city":"Idaho Falls",
    "sg:classifiers":[
        {
            "category":"Shopping",
            "subcategory":"Music",
            "type":"Retail Goods"
        }
    ],
    "sg:phone":"+1 208 542 2927",
    "sg:postcode":"83402",
    "sg:province":"ID",
    "sg:tags":[
        "compact",
        "record",
        "disc",
        "tape"
    ],
    "wof:name":"Lost & Found Records",
    "wof:placetype":"venue"
},
  "geometry": {"coordinates":[-112.09192899999999,43.501188],"type":"Point"}
}