{
  "type": "Feature",
  "properties": {
    "iso:country":"US",
    "sg:address":"105 Main St",
    "sg:city":"Sandpoint",
    "sg:classifiers":[
        {
            "category":"Arena",
            "subcategory":"Sports Club",
            "type":"Entertainment"
        }
    ],
    "sg:phone":"+1 208 263 9116",
    "sg:postcode":"83864",
    "sg:province":"ID",
    "sg:tags":[
        "soccer"
    ],
    "wof:name":"Sandpoint Soccer Assn",
    "wof:placetype":"venue"
},
  "geometry": {"coordinates":[-116.548728,48.274893],"type":"Point"}
}