{
  "type": "Feature",
  "properties": {
    "addr:full":"7352 N Government Way Dalton Gardens ID 83815",
    "addr:housenumber":"7352",
    "addr:postcode":"83815",
    "addr:street":"N Government Way Dalton Gardens",
    "iso:country":"US",
    "sg:address":"7352 N Government Way",
    "sg:city":"Dalton Gardens",
    "sg:classifiers":[
        {
            "category":"Education",
            "subcategory":"Dance Studio",
            "type":"Public Place"
        }
    ],
    "sg:phone":"+1 208 772 8351",
    "sg:postcode":"83815",
    "sg:province":"ID",
    "sg:tags":[
        "instruction",
        "dancing"
    ],
    "wof:name":"Moxie Tap & Theatre Arts",
    "wof:placetype":"venue"
},
  "geometry": {"coordinates":[-116.786653,47.738807],"type":"Point"}
}