{
  "type": "Feature",
  "properties": {
    "addr:full":"1105 8th St Rupert ID 83350",
    "addr:housenumber":"1105",
    "addr:postcode":"83350",
    "addr:street":"8Th St",
    "iso:country":"US",
    "sg:address":"1105 8th St",
    "sg:city":"Rupert",
    "sg:classifiers":[
        {
            "category":"Organizations",
            "subcategory":"Religious Organization",
            "type":"Services"
        }
    ],
    "sg:phone":"+1 208 436 8976",
    "sg:postcode":"83350",
    "sg:province":"ID",
    "sg:tags":[
        "church"
    ],
    "wof:name":"Lutheran Trinity Church",
    "wof:placetype":"venue"
},
  "geometry": {"coordinates":[-113.684118,42.619577],"type":"Point"}
}