{
  "type": "Feature",
  "properties": {
    "addr:full":"501 Main Ave St Maries ID 83861",
    "addr:housenumber":"501",
    "addr:postcode":"83861",
    "addr:street":"Main Ave St",
    "iso:country":"US",
    "sg:address":"501 Main Ave",
    "sg:city":"St Maries",
    "sg:classifiers":[
        {
            "category":"Food & Beverages",
            "subcategory":"Liquor & Beverages",
            "type":"Retail Goods"
        }
    ],
    "sg:phone":"+1 208 245 3123",
    "sg:postcode":"83861",
    "sg:province":"ID",
    "wof:name":"Idaho State Liquor Store 327",
    "wof:placetype":"venue"
},
  "geometry": {"coordinates":[-116.565715,47.31625],"type":"Point"}
}