{
  "type": "Feature",
  "properties": {
    "iso:country":"US",
    "sg:address":"582 E Boise Ave",
    "sg:city":"Boise",
    "sg:classifiers":[
        {
            "category":"Professional",
            "subcategory":"Business Services",
            "type":"Services"
        }
    ],
    "sg:phone":"+1 208 389 1457",
    "sg:postcode":"83706",
    "sg:province":"ID",
    "sg:tags":[
        "broker",
        "merchandise"
    ],
    "wof:name":"Fa Enterprises Inc",
    "wof:placetype":"venue"
},
  "geometry": {"coordinates":[-116.17374700000001,43.578687],"type":"Point"}
}