{
  "type": "Feature",
  "properties": {
    "iso:country":"US",
    "sg:address":"101 N Boyer Ave",
    "sg:city":"Sandpoint",
    "sg:classifiers":[
        {
            "category":"Social Services",
            "type":"Services"
        }
    ],
    "sg:phone":"+1 208 265 8706",
    "sg:postcode":"83864",
    "sg:province":"ID",
    "sg:tags":[
        "counseling"
    ],
    "wof:name":"Maranatha Counseling",
    "wof:placetype":"venue"
},
  "geometry": {"coordinates":[-116.557041,48.27401],"type":"Point"}
}