{
  "type": "Feature",
  "properties": {
    "iso:country":"US",
    "sg:address":"7615 W Kerry Dr",
    "sg:city":"Boise",
    "sg:classifiers":[
        {
            "category":"Building & Trades",
            "subcategory":"Construction",
            "type":"Services"
        }
    ],
    "sg:phone":"+1 208 853 4839",
    "sg:postcode":"83714",
    "sg:province":"ID",
    "sg:tags":[
        "residential"
    ],
    "wof:name":"MB West Corp",
    "wof:placetype":"venue"
},
  "geometry": {"coordinates":[-116.281362,43.6741],"type":"Point"}
}