{
  "type": "Feature",
  "properties": {
    "addr:full":"15742 Riverside Rd Caldwell ID 83607",
    "addr:housenumber":"15742",
    "addr:postcode":"83607",
    "addr:street":"Riverside Rd",
    "iso:country":"US",
    "sg:address":"15742 Riverside Rd",
    "sg:city":"Caldwell",
    "sg:classifiers":[
        {
            "category":"Retail",
            "subcategory":"Animal Services",
            "type":"Services"
        }
    ],
    "sg:phone":"+1 208 455 2364",
    "sg:postcode":"83607",
    "sg:province":"ID",
    "sg:tags":[
        "pet",
        "grooming",
        "washing"
    ],
    "wof:name":"Affordable Dog Grooming",
    "wof:placetype":"venue"
},
  "geometry": {"coordinates":[-116.722825,43.59935],"type":"Point"}
}