{
  "type": "Feature",
  "properties": {
    "addr:full":"1019 S Progress Ave Meridian ID 83642",
    "addr:housenumber":"1019",
    "addr:postcode":"83642",
    "addr:street":"S Progress Ave",
    "iso:country":"US",
    "sg:address":"1019 S Progress Ave",
    "sg:city":"Meridian",
    "sg:classifiers":[
        {
            "category":"Travel",
            "subcategory":"Hotels & Motels",
            "type":"Entertainment"
        }
    ],
    "sg:phone":"+1 208 887 7888",
    "sg:postcode":"83642",
    "sg:province":"ID",
    "wof:name":"Best Western Inn",
    "wof:placetype":"venue"
},
  "geometry": {"coordinates":[-116.391965,43.594962],"type":"Point"}
}