{
  "type": "Feature",
  "properties": {
    "addr:full":"400 E Linden St Caldwell ID 83605",
    "addr:housenumber":"400",
    "addr:postcode":"83605",
    "addr:street":"E Linden St",
    "iso:country":"US",
    "sg:address":"400 E Linden St",
    "sg:city":"Caldwell",
    "sg:classifiers":[
        {
            "category":"Education",
            "subcategory":"School",
            "type":"Public Place"
        }
    ],
    "sg:phone":"+1 208 455 3313",
    "sg:postcode":"83605",
    "sg:province":"ID",
    "wof:name":"Woodrow Wilson School",
    "wof:placetype":"venue"
},
  "geometry": {"coordinates":[-116.694056,43.647888],"type":"Point"}
}