{
  "type": "Feature",
  "properties": {
    "addr:full":"1512 N Government Way Coeur D Alene ID 83814",
    "addr:housenumber":"1512",
    "addr:postcode":"83814",
    "addr:street":"N Government Way",
    "iso:country":"US",
    "sg:address":"1512 N Government Way",
    "sg:city":"Coeur D Alene",
    "sg:classifiers":[
        {
            "category":"Retail",
            "subcategory":"Laundry & Dry Cleaning",
            "type":"Services"
        }
    ],
    "sg:phone":"+1 208 667 7837",
    "sg:postcode":"83814",
    "sg:province":"ID",
    "sg:tags":[
        "cleaners",
        "rug",
        "carpet"
    ],
    "wof:name":"Carpet Pro",
    "wof:placetype":"venue"
},
  "geometry": {"coordinates":[-116.786085,47.689773],"type":"Point"}
}