{
  "type": "Feature",
  "properties": {
    "iso:country":"US",
    "sg:address":"4662 Henry St",
    "sg:city":"Boise",
    "sg:classifiers":[
        {
            "category":"Building & Trades",
            "subcategory":"Construction",
            "type":"Services"
        }
    ],
    "sg:phone":"+1 208 362 7227",
    "sg:postcode":"83709",
    "sg:province":"ID",
    "sg:tags":[
        "general",
        "contractor"
    ],
    "wof:name":"Schmidt Construction Co Inc",
    "wof:placetype":"venue"
},
  "geometry": {"coordinates":[-116.256867,43.562182],"type":"Point"}
}