{
  "type": "Feature",
  "properties": {
    "iso:country":"US",
    "sg:address":"31801 Mann Ln",
    "sg:city":"Parma",
    "sg:classifiers":[
        {
            "category":"Farming",
            "subcategory":"Livestock Farm",
            "type":"Manufacturing & Wholesale Goods"
        }
    ],
    "sg:phone":"+1 208 722 6343",
    "sg:postcode":"83660",
    "sg:province":"ID",
    "sg:tags":[
        "beef",
        "feedlot",
        "cattle"
    ],
    "wof:name":"M & M Feedlot",
    "wof:placetype":"venue"
},
  "geometry": {"coordinates":[-117.000353,43.8364],"type":"Point"}
}