{
  "type": "Feature",
  "properties": {
    "addr:full":"809 N Whitley Dr Fruitland ID 83619",
    "addr:housenumber":"809",
    "addr:postcode":"83619",
    "addr:street":"N Whitley Dr",
    "iso:country":"US",
    "sg:address":"809 N Whitley Dr",
    "sg:city":"Fruitland",
    "sg:classifiers":[
        {
            "category":"Professional",
            "subcategory":"Management & Consulting",
            "type":"Services"
        }
    ],
    "sg:phone":"+1 208 452 3277",
    "sg:postcode":"83619",
    "sg:province":"ID",
    "sg:tags":[
        "business"
    ],
    "wof:name":"Dave Haidle Consulting",
    "wof:placetype":"venue"
},
  "geometry": {"coordinates":[-116.923794,44.018176],"type":"Point"}
}