{
  "type": "Feature",
  "properties": {
    "addr:full":"2248 W Ironwood Center Dr Coeur D Alene ID 83814",
    "addr:housenumber":"2248",
    "addr:postcode":"83814",
    "addr:street":"W Ironwood Center Dr",
    "iso:country":"US",
    "sg:address":"2248 W Ironwood Center Dr",
    "sg:city":"Coeur D Alene",
    "sg:classifiers":[
        {
            "category":"Professional",
            "subcategory":"Accounting & Tax Preparation",
            "type":"Services"
        }
    ],
    "sg:phone":"+1 208 664 1484",
    "sg:postcode":"83814",
    "sg:province":"ID",
    "sg:tags":[
        "accountant"
    ],
    "wof:name":"Robert J Blessing CPA",
    "wof:placetype":"venue"
},
  "geometry": {"coordinates":[-116.796442,47.697208],"type":"Point"}
}