{
  "type": "Feature",
  "properties": {
    "addr:full":"1 Quail Ln Boise ID 83716",
    "addr:housenumber":"1",
    "addr:postcode":"83716",
    "addr:street":"Quail Ln",
    "iso:country":"US",
    "sg:address":"1 Quail Ln",
    "sg:city":"Boise",
    "sg:classifiers":[
        {
            "category":"Building & Trades",
            "subcategory":"Construction",
            "type":"Services"
        }
    ],
    "sg:phone":"+1 208 343 2695",
    "sg:postcode":"83716",
    "sg:province":"ID",
    "sg:tags":[
        "contractor"
    ],
    "wof:name":"H & H Homes",
    "wof:placetype":"venue"
},
  "geometry": {"coordinates":[-115.98380899999999,43.666934],"type":"Point"}
}