{
  "type": "Feature",
  "properties": {
    "addr:full":"2815 Good St Boise ID 83703",
    "addr:housenumber":"2815",
    "addr:postcode":"83703",
    "addr:street":"Good St",
    "iso:country":"US",
    "sg:address":"2815 Good St",
    "sg:city":"Boise",
    "sg:classifiers":[
        {
            "category":"Building & Trades",
            "subcategory":"Cleaning & Sanitation",
            "type":"Services"
        }
    ],
    "sg:phone":"+1 208 440 4040",
    "sg:postcode":"83703",
    "sg:province":"ID",
    "sg:tags":[
        "house"
    ],
    "wof:name":"Ladybug Cleaners",
    "wof:placetype":"venue"
},
  "geometry": {"coordinates":[-116.22441600000001,43.639906],"type":"Point"}
}