{
  "type": "Feature",
  "properties": {
    "addr:full":"479 Emerald Ave Blackfoot ID 83221",
    "addr:housenumber":"479",
    "addr:postcode":"83221",
    "addr:street":"Emerald Ave",
    "iso:country":"US",
    "sg:address":"479 Emerald Ave",
    "sg:city":"Blackfoot",
    "sg:classifiers":[
        {
            "category":"Shopping",
            "type":"Retail Goods"
        }
    ],
    "sg:phone":"+1 208 785 6291",
    "sg:postcode":"83221",
    "sg:province":"ID",
    "sg:tags":[
        "art",
        "gallery",
        "dealer"
    ],
    "wof:name":"Rocky Mountain Publishing",
    "wof:placetype":"venue"
},
  "geometry": {"coordinates":[-112.324673,43.20849],"type":"Point"}
}