{
  "type": "Feature",
  "properties": {
    "iso:country":"US",
    "sg:address":"600 W Prairie Ave",
    "sg:city":"Coeur D Alene",
    "sg:classifiers":[
        {
            "category":"Government",
            "subcategory":"Office",
            "type":"Public Place"
        }
    ],
    "sg:phone":"+1 208 772 1261",
    "sg:postcode":"83815",
    "sg:province":"ID",
    "sg:tags":[
        "state",
        "program"
    ],
    "wof:name":"Motor Vehicle Investigator",
    "wof:placetype":"venue"
},
  "geometry": {"coordinates":[-116.79496899999999,47.744372],"type":"Point"}
}