{
  "type": "Feature",
  "properties": {
    "iso:country":"US",
    "sg:address":"3423 Crystal Creek Rd",
    "sg:city":"Pocatello",
    "sg:classifiers":[
        {
            "category":"Freight",
            "type":"Transportation"
        }
    ],
    "sg:phone":"+1 208 335 2153",
    "sg:postcode":"83204",
    "sg:province":"ID",
    "sg:tags":[
        "line"
    ],
    "wof:name":"Swim Transportation",
    "wof:placetype":"venue"
},
  "geometry": {"coordinates":[-112.527731,42.700169],"type":"Point"}
}