{
  "type": "Feature",
  "properties": {
    "iso:country":"US",
    "sg:address":"10 Round Up Cir",
    "sg:city":"Boise",
    "sg:classifiers":[
        {
            "category":"Professional",
            "subcategory":"Employment Agencies",
            "type":"Services"
        }
    ],
    "sg:phone":"+1 208 433 9609",
    "sg:postcode":"83716",
    "sg:province":"ID",
    "sg:tags":[
        "driving"
    ],
    "wof:name":"Tester Jeaunelle",
    "wof:placetype":"venue"
},
  "geometry": {"coordinates":[-115.932412,43.71378],"type":"Point"}
}