{
  "type": "Feature",
  "properties": {
    "iso:country":"US",
    "sg:address":"1401 W Shoreline Dr",
    "sg:city":"Boise",
    "sg:classifiers":[
        {
            "category":"Recreation",
            "subcategory":"Campground",
            "type":"Entertainment"
        }
    ],
    "sg:phone":"+1 208 345 8351",
    "sg:postcode":"83702",
    "sg:province":"ID",
    "sg:tags":[
        "recreational",
        "park",
        "vehicle"
    ],
    "wof:name":"Eagles Nest Resort",
    "wof:placetype":"venue"
},
  "geometry": {"coordinates":[-116.218948,43.614792],"type":"Point"}
}