{
  "type": "Feature",
  "properties": {
    "iso:country":"US",
    "sg:address":"7190 Barrister Dr",
    "sg:city":"Boise",
    "sg:classifiers":[
        {
            "category":"Government",
            "subcategory":"Office",
            "type":"Public Place"
        }
    ],
    "sg:phone":"+1 208 377 6520",
    "sg:postcode":"83704",
    "sg:province":"ID",
    "sg:tags":[
        "village"
    ],
    "sg:website":"www.itd.idaho.gov/dmv",
    "wof:name":"Boise Automobile Registration",
    "wof:placetype":"venue"
},
  "geometry": {"coordinates":[-116.266536,43.606553],"type":"Point"}
}