{
  "type": "Feature",
  "properties": {
    "addr:full":"1434 Ripon Ave Lewiston ID 83501",
    "addr:housenumber":"1434",
    "addr:postcode":"83501",
    "addr:street":"Ripon Ave",
    "iso:country":"US",
    "sg:address":"1434 Ripon Ave",
    "sg:city":"Lewiston",
    "sg:classifiers":[
        {
            "category":"Organizations",
            "subcategory":"Religious Organization",
            "type":"Services"
        }
    ],
    "sg:phone":"+1 208 746 6530",
    "sg:postcode":"83501",
    "sg:province":"ID",
    "sg:tags":[
        "church"
    ],
    "wof:name":"Jehovah's Witnesses",
    "wof:placetype":"venue"
},
  "geometry": {"coordinates":[-116.9564,46.365736],"type":"Point"}
}