{
  "type": "Feature",
  "properties": {
    "iso:country":"US",
    "sg:address":"1181 N Milwaukee St",
    "sg:city":"Boise",
    "sg:classifiers":[
        {
            "category":"Restaurant",
            "type":"Food & Drink"
        }
    ],
    "sg:phone":"+1 208 323 4400",
    "sg:postcode":"83704",
    "sg:province":"ID",
    "wof:name":"Good Times Drive Thru Burgers",
    "wof:placetype":"venue"
},
  "geometry": {"coordinates":[-116.28424,43.615051],"type":"Point"}
}