{
  "type": "Feature",
  "properties": {
    "iso:country":"US",
    "sg:address":"1880 N Aronmink Way",
    "sg:city":"Meridian",
    "sg:classifiers":[
        {
            "category":"Building & Trades",
            "subcategory":"Construction",
            "type":"Services"
        }
    ],
    "sg:phone":"+1 208 884 0722",
    "sg:postcode":"83646",
    "sg:province":"ID",
    "sg:tags":[
        "hanging",
        "contractor"
    ],
    "wof:name":"Gb Painting",
    "wof:placetype":"venue"
},
  "geometry": {"coordinates":[-116.434602,43.622074],"type":"Point"}
}