{
  "type": "Feature",
  "properties": {
    "iso:country":"US",
    "sg:address":"629 Palmetto Dr",
    "sg:city":"Eagle",
    "sg:classifiers":[
        {
            "category":"Building & Trades",
            "subcategory":"Cleaning & Sanitation",
            "type":"Services"
        }
    ],
    "sg:phone":"+1 208 323 8457",
    "sg:postcode":"83616",
    "sg:province":"ID",
    "sg:tags":[
        "maintenance"
    ],
    "wof:name":"Janitorman LLC",
    "wof:placetype":"venue"
},
  "geometry": {"coordinates":[-116.344517,43.701076],"type":"Point"}
}