{
  "type": "Feature",
  "properties": {
    "iso:country":"US",
    "sg:address":"835 Kootenai Cut Off Rd",
    "sg:city":"Ponderay",
    "sg:classifiers":[
        {
            "category":"Real Estate",
            "subcategory":"Real Estate Operator",
            "type":"Services"
        }
    ],
    "sg:phone":"+1 208 265 0788",
    "sg:postcode":"83864",
    "sg:province":"ID",
    "sg:tags":[
        "apartment"
    ],
    "wof:name":"Mt Baldy Apartments",
    "wof:placetype":"venue"
},
  "geometry": {"coordinates":[-116.536813,48.309192],"type":"Point"}
}