{
  "type": "Feature",
  "properties": {
    "iso:country":"US",
    "sg:address":"4813 Lake Front Pl",
    "sg:city":"Boise",
    "sg:classifiers":[
        {
            "category":"Real Estate",
            "subcategory":"Architect",
            "type":"Services"
        }
    ],
    "sg:phone":"+1 208 389 1200",
    "sg:postcode":"83714",
    "sg:province":"ID",
    "wof:name":"Armstrong Architects",
    "wof:placetype":"venue"
},
  "geometry": {"coordinates":[-116.294571,43.666081],"type":"Point"}
}