{
  "type": "Feature",
  "properties": {
    "iso:country":"US",
    "sg:address":"18 S Main St",
    "sg:city":"Payette",
    "sg:classifiers":[
        {
            "category":"Restaurant",
            "type":"Food & Drink"
        }
    ],
    "sg:menulink":"http://www.allmenus.com/id/payette/120350-subway/menu/",
    "sg:phone":"+1 208 642 1080",
    "sg:postcode":"83661",
    "sg:province":"ID",
    "sg:tags":[
        "american",
        "sandwich"
    ],
    "wof:name":"Subway",
    "wof:placetype":"venue"
},
  "geometry": {"coordinates":[-116.935174,44.074739],"type":"Point"}
}