{
  "type": "Feature",
  "properties": {
    "iso:country":"US",
    "sg:address":"17770 W Bison Trl",
    "sg:city":"Post Falls",
    "sg:classifiers":[
        {
            "category":"Professional",
            "subcategory":"Management & Consulting",
            "type":"Services"
        }
    ],
    "sg:phone":"+1 208 777 9076",
    "sg:postcode":"83854",
    "sg:province":"ID",
    "wof:name":"Access Solutions Inc",
    "wof:placetype":"venue"
},
  "geometry": {"coordinates":[-117.023465,47.667538],"type":"Point"}
}