{
  "type": "Feature",
  "properties": {
    "addr:full":"923 Craven Ave Buhl ID 83316",
    "addr:housenumber":"923",
    "addr:postcode":"83316",
    "addr:street":"Craven Ave",
    "iso:country":"US",
    "sg:address":"923 Craven Ave",
    "sg:city":"Buhl",
    "sg:classifiers":[
        {
            "category":"Freight",
            "type":"Transportation"
        }
    ],
    "sg:phone":"+1 208 543 8070",
    "sg:postcode":"83316",
    "sg:province":"ID",
    "sg:tags":[
        "operator",
        "local",
        "trucking"
    ],
    "wof:name":"Wayne Stahlecker Trucking",
    "wof:placetype":"venue"
},
  "geometry": {"coordinates":[-114.753427,42.585888],"type":"Point"}
}