{
  "type": "Feature",
  "properties": {
    "iso:country":"US",
    "sg:address":"3007 Deeg Rd",
    "sg:city":"American Falls",
    "sg:phone":"+1 208 226 7103",
    "sg:postcode":"83211",
    "sg:province":"ID",
    "sg:tags":[
        "farm",
        "wheat"
    ],
    "wof:name":"Deeg Farms",
    "wof:placetype":"venue"
},
  "geometry": {"coordinates":[-112.89525999999999,42.661116],"type":"Point"}
}