{
  "type": "Feature",
  "properties": {
    "iso:country":"US",
    "sg:address":"486 W 1st Ave",
    "sg:city":"Glenns Ferry",
    "sg:classifiers":[
        {
            "category":"Health Services",
            "subcategory":"Doctor",
            "type":"Services"
        }
    ],
    "sg:phone":"+1 208 366 7416",
    "sg:postcode":"83623",
    "sg:province":"ID",
    "sg:tags":[
        "physician",
        "surgeon"
    ],
    "wof:name":"Glenns Ferry Health Ctr",
    "wof:placetype":"venue"
},
  "geometry": {"coordinates":[-115.304362,42.953667],"type":"Point"}
}