{
  "type": "Feature",
  "properties": {
    "iso:country":"US",
    "sg:address":"30 W Bridge St",
    "sg:city":"Blackfoot",
    "sg:classifiers":[
        {
            "category":"Shopping",
            "subcategory":"Bicycles & Sporting Goods",
            "type":"Retail Goods"
        }
    ],
    "sg:phone":"+1 208 785 0232",
    "sg:postcode":"83221",
    "sg:province":"ID",
    "sg:tags":[
        "gun",
        "gunsmith"
    ],
    "wof:name":"A To Z Antiques & Sports",
    "wof:placetype":"venue"
},
  "geometry": {"coordinates":[-112.34581900000001,43.18916],"type":"Point"}
}