{
  "type": "Feature",
  "properties": {
    "iso:country":"US",
    "sg:address":"1337 Enterprise St",
    "sg:city":"Idaho Falls",
    "sg:classifiers":[
        {
            "category":"Wholesale",
            "subcategory":"Medical Equipment & Supplies",
            "type":"Manufacturing & Wholesale Goods"
        }
    ],
    "sg:phone":"+1 208 552 7400",
    "sg:postcode":"83402",
    "sg:province":"ID",
    "sg:tags":[
        "hospital"
    ],
    "wof:name":"Hill-Rom Co",
    "wof:placetype":"venue"
},
  "geometry": {"coordinates":[-112.060211,43.465568],"type":"Point"}
}