{
  "type": "Feature",
  "properties": {
    "iso:country":"US",
    "sg:address":"875 E Parkcenter Blvd",
    "sg:city":"Boise",
    "sg:classifiers":[
        {
            "category":"Banks & Credit Unions",
            "subcategory":"Bank",
            "type":"Services"
        }
    ],
    "sg:phone":"+1 208 334 7237",
    "sg:postcode":"83706",
    "sg:province":"ID",
    "wof:name":"Key Bank",
    "wof:placetype":"venue"
},
  "geometry": {"coordinates":[-116.17796199999999,43.593065],"type":"Point"}
}