{
  "type": "Feature",
  "properties": {
    "iso:country":"US",
    "sg:address":"1410 Air Base Rd",
    "sg:city":"Mountain Home",
    "sg:classifiers":[
        {
            "category":"Shopping",
            "subcategory":"Used Merchandise",
            "type":"Retail Goods"
        }
    ],
    "sg:phone":"+1 208 587 8858",
    "sg:postcode":"83647",
    "sg:province":"ID",
    "sg:tags":[
        "pawnbroker"
    ],
    "wof:name":"Mountain Sports & Pawnbrokers",
    "wof:placetype":"venue"
},
  "geometry": {"coordinates":[-115.67758000000001,43.126612],"type":"Point"}
}