{
  "type": "Feature",
  "properties": {
    "iso:country":"US",
    "sg:address":"119 N 1st Ave",
    "sg:city":"Sandpoint",
    "sg:classifiers":[
        {
            "category":"Shopping",
            "subcategory":"Hobbies, Toys, & Games",
            "type":"Retail Goods"
        }
    ],
    "sg:phone":"+1 208 263 4700",
    "sg:postcode":"83864",
    "sg:province":"ID",
    "sg:tags":[
        "equipment",
        "ceramic",
        "supply"
    ],
    "wof:name":"Curb A Yard",
    "wof:placetype":"venue"
},
  "geometry": {"coordinates":[-116.547753,48.273861],"type":"Point"}
}