{
  "type": "Feature",
  "properties": {
    "addr:full":"6017 Franklin Rd Boise ID 83709",
    "addr:housenumber":"6017",
    "addr:postcode":"83709",
    "addr:street":"Franklin Rd",
    "iso:country":"US",
    "sg:address":"6017 Franklin Rd",
    "sg:city":"Boise",
    "sg:classifiers":[
        {
            "category":"Home & Garden",
            "subcategory":"Home Furnishings",
            "type":"Retail Goods"
        }
    ],
    "sg:phone":"+1 208 424 1300",
    "sg:postcode":"83709",
    "sg:province":"ID",
    "sg:tags":[
        "fireplace"
    ],
    "wof:name":"Hardrock Fireplaces & Gallery",
    "wof:placetype":"venue"
},
  "geometry": {"coordinates":[-116.257103,43.603399],"type":"Point"}
}