{
  "type": "Feature",
  "properties": {
    "addr:full":"4709 W Camas St Boise ID 83705",
    "addr:housenumber":"4709",
    "addr:postcode":"83705",
    "addr:street":"W Camas St",
    "iso:country":"US",
    "sg:address":"4709 W Camas St",
    "sg:city":"Boise",
    "sg:classifiers":[
        {
            "category":"Social Services",
            "type":"Services"
        }
    ],
    "sg:phone":"+1 208 344 9187",
    "sg:postcode":"83705",
    "sg:province":"ID",
    "sg:tags":[
        "youth",
        "organization",
        "center"
    ],
    "sg:website":"www.head-start.net",
    "wof:name":"Friends Of Children & Family",
    "wof:placetype":"venue"
},
  "geometry": {"coordinates":[-116.240334,43.595183],"type":"Point"}
}