{
  "type": "Feature",
  "properties": {
    "iso:country":"US",
    "sg:address":"1435 N Main St",
    "sg:city":"Pocatello",
    "sg:classifiers":[
        {
            "category":"Sports & Exercise",
            "subcategory":"Gym",
            "type":"Entertainment"
        }
    ],
    "sg:phone":"+1 208 234 4177",
    "sg:postcode":"83204",
    "sg:province":"ID",
    "sg:tags":[
        "club",
        "health",
        "studio",
        "gymnasium"
    ],
    "wof:name":"Boxersize Fitness & Tanning",
    "wof:placetype":"venue"
},
  "geometry": {"coordinates":[-112.462788,42.87244],"type":"Point"}
}