{
  "type": "Feature",
  "properties": {
    "addr:full":"123 W Main St Emmett ID 83617",
    "addr:housenumber":"123",
    "addr:postcode":"83617",
    "addr:street":"W Main St",
    "iso:country":"US",
    "sg:address":"123 W Main St",
    "sg:city":"Emmett",
    "sg:classifiers":[
        {
            "category":"Professional",
            "subcategory":"Management & Consulting",
            "type":"Services"
        }
    ],
    "sg:phone":"+1 208 398 8142",
    "sg:postcode":"83617",
    "sg:province":"ID",
    "sg:tags":[
        "personnel",
        "consultant"
    ],
    "wof:name":"Martin & Assoc Staffing",
    "wof:placetype":"venue"
},
  "geometry": {"coordinates":[-116.500259,43.875547],"type":"Point"}
}