{
  "type": "Feature",
  "properties": {
    "iso:country":"US",
    "sg:address":"1003 N Orchard St",
    "sg:city":"Boise",
    "sg:classifiers":[
        {
            "category":"Health Services",
            "subcategory":"Chiropractor",
            "type":"Services"
        }
    ],
    "sg:phone":"+1 208 376 3113",
    "sg:postcode":"83706",
    "sg:province":"ID",
    "wof:name":"Energetic Chiropractic",
    "wof:placetype":"venue"
},
  "geometry": {"coordinates":[-116.243528,43.614109],"type":"Point"}
}