{
  "type": "Feature",
  "properties": {
    "iso:country":"US",
    "sg:address":"3456 E 17th St",
    "sg:city":"Ammon",
    "sg:classifiers":[
        {
            "category":"Professional",
            "subcategory":"Advertising",
            "type":"Services"
        }
    ],
    "sg:phone":"+1 208 523 7331",
    "sg:postcode":"83406",
    "sg:province":"ID",
    "sg:tags":[
        "guide"
    ],
    "wof:name":"Yellow Book",
    "wof:placetype":"venue"
},
  "geometry": {"coordinates":[-111.965692,43.481778],"type":"Point"}
}