{
  "type": "Feature",
  "properties": {
    "iso:country":"US",
    "sg:address":"116 W Greenhurst Rd",
    "sg:city":"Nampa",
    "sg:classifiers":[
        {
            "category":"Real Estate",
            "subcategory":"Real Estate Operator",
            "type":"Services"
        }
    ],
    "sg:phone":"+1 208 463 1826",
    "sg:postcode":"83686",
    "sg:province":"ID",
    "sg:tags":[
        "apartment"
    ],
    "wof:name":"Greenwood Apartments",
    "wof:placetype":"venue"
},
  "geometry": {"coordinates":[-116.572919,43.547168],"type":"Point"}
}