{
  "type": "Feature",
  "properties": {
    "iso:country":"US",
    "sg:address":"1520 W State St",
    "sg:city":"Boise",
    "sg:classifiers":[
        {
            "category":"Professional",
            "subcategory":"Research",
            "type":"Services"
        }
    ],
    "sg:phone":"+1 208 947 1235",
    "sg:postcode":"83702",
    "sg:province":"ID",
    "sg:tags":[
        "medical"
    ],
    "wof:name":"Sonora Clinical Research",
    "wof:placetype":"venue"
},
  "geometry": {"coordinates":[-116.209749,43.623389],"type":"Point"}
}