{
  "type": "Feature",
  "properties": {
    "iso:country":"US",
    "sg:address":"743 E 3400 N",
    "sg:city":"Castleford",
    "sg:phone":"+1 208 537 6647",
    "sg:postcode":"83321",
    "sg:province":"ID",
    "sg:tags":[
        "wheat",
        "farm",
        "corn",
        "cash",
        "crop",
        "field",
        "grain"
    ],
    "wof:name":"Don Graybeal",
    "wof:placetype":"venue"
},
  "geometry": {"coordinates":[-114.899292,42.49158],"type":"Point"}
}