{
  "type": "Feature",
  "properties": {
    "addr:full":"511 Americana Blvd Boise ID 83702",
    "addr:housenumber":"511",
    "addr:postcode":"83702",
    "addr:street":"Americana Blvd",
    "iso:country":"US",
    "sg:address":"511 Americana Blvd",
    "sg:city":"Boise",
    "sg:classifiers":[
        {
            "category":"Retail",
            "subcategory":"Auto Repair",
            "type":"Services"
        }
    ],
    "sg:phone":"+1 208 345 9444",
    "sg:postcode":"83702",
    "sg:province":"ID",
    "sg:tags":[
        "repairing",
        "automobile"
    ],
    "wof:name":"Motorsports Northwest",
    "wof:placetype":"venue"
},
  "geometry": {"coordinates":[-116.215751,43.618474],"type":"Point"}
}