{
  "type": "Feature",
  "properties": {
    "iso:country":"US",
    "sg:address":"14516 W Lacey Rd",
    "sg:city":"Pocatello",
    "sg:classifiers":[
        {
            "category":"Professional",
            "subcategory":"Business Services",
            "type":"Services"
        }
    ],
    "sg:phone":"+1 208 637 0235",
    "sg:postcode":"83202",
    "sg:province":"ID",
    "wof:name":"Dave & Kim McClung Enterprises",
    "wof:placetype":"venue"
},
  "geometry": {"coordinates":[-112.506694,42.940456],"type":"Point"}
}