{
  "type": "Feature",
  "properties": {
    "addr:full":"5199 N Quail Summit Way Boise ID 83703",
    "addr:housenumber":"5199",
    "addr:postcode":"83703",
    "addr:street":"N Quail Summit Way",
    "iso:country":"US",
    "sg:address":"5199 N Quail Summit Way",
    "sg:city":"Boise",
    "sg:classifiers":[
        {
            "category":"Professional",
            "subcategory":"Management & Consulting",
            "type":"Services"
        }
    ],
    "sg:phone":"+1 208 336 5110",
    "sg:postcode":"83703",
    "sg:province":"ID",
    "sg:tags":[
        "business"
    ],
    "wof:name":"Boise Business Consulting Inc",
    "wof:placetype":"venue"
},
  "geometry": {"coordinates":[-116.23698,43.666621],"type":"Point"}
}