{
  "type": "Feature",
  "properties": {
    "iso:country":"US",
    "sg:address":"425 Garfield St",
    "sg:city":"Idaho Falls",
    "sg:classifiers":[
        {
            "category":"Professional",
            "subcategory":"Detective & Security Services",
            "type":"Services"
        }
    ],
    "sg:phone":"+1 208 529 9481",
    "sg:postcode":"83401",
    "sg:province":"ID",
    "sg:tags":[
        "car",
        "armored"
    ],
    "wof:name":"Hammon Services Corp",
    "wof:placetype":"venue"
},
  "geometry": {"coordinates":[-112.025741,43.500565],"type":"Point"}
}