{
  "type": "Feature",
  "properties": {
    "addr:full":"1501 Little Bear Ridge Rd Troy ID 83871",
    "addr:housenumber":"1501",
    "addr:postcode":"83871",
    "addr:street":"Little Bear Ridge Rd",
    "iso:country":"US",
    "sg:address":"1501 Little Bear Ridge Rd",
    "sg:city":"Troy",
    "sg:classifiers":[
        {
            "category":"Farming",
            "subcategory":"Farm",
            "type":"Manufacturing & Wholesale Goods"
        }
    ],
    "sg:phone":"+1 208 835 2817",
    "sg:postcode":"83871",
    "sg:province":"ID",
    "wof:name":"Renfrow Bros",
    "wof:placetype":"venue"
},
  "geometry": {"coordinates":[-116.676789,46.675922],"type":"Point"}
}