{
  "type": "Feature",
  "properties": {
    "iso:country":"US",
    "sg:address":"1254 W Crenshaw St",
    "sg:city":"Kuna",
    "sg:classifiers":[
        {
            "category":"Professional",
            "subcategory":"Business Services",
            "type":"Services"
        }
    ],
    "sg:phone":"+1 208 922 9493",
    "sg:postcode":"83634",
    "sg:province":"ID",
    "wof:name":"Kcjb Inc",
    "wof:placetype":"venue"
},
  "geometry": {"coordinates":[-116.42926300000001,43.505438],"type":"Point"}
}