{
  "type": "Feature",
  "properties": {
    "iso:country":"US",
    "sg:address":"415 Farnsworth Way",
    "sg:city":"Rigby",
    "sg:classifiers":[
        {
            "category":"Retail",
            "subcategory":"Portrait Studio",
            "type":"Services"
        }
    ],
    "sg:phone":"+1 208 745 8518",
    "sg:postcode":"83442",
    "sg:province":"ID",
    "sg:tags":[
        "photographer"
    ],
    "wof:name":"Hammon Photography",
    "wof:placetype":"venue"
},
  "geometry": {"coordinates":[-111.907451,43.678977],"type":"Point"}
}