{
  "type": "Feature",
  "properties": {
    "addr:full":"2147 Albion Ave Burley ID 83318",
    "addr:housenumber":"2147",
    "addr:postcode":"83318",
    "addr:street":"Albion Ave",
    "iso:country":"US",
    "sg:address":"2147 Albion Ave",
    "sg:city":"Burley",
    "sg:classifiers":[
        {
            "category":"Sports & Exercise",
            "subcategory":"Gym",
            "type":"Entertainment"
        }
    ],
    "sg:phone":"+1 208 678 2754",
    "sg:postcode":"83318",
    "sg:province":"ID",
    "sg:tags":[
        "club",
        "health",
        "studio",
        "gymnasium"
    ],
    "wof:name":"Curves For Women",
    "wof:placetype":"venue"
},
  "geometry": {"coordinates":[-113.792028,42.526151],"type":"Point"}
}