{
  "type": "Feature",
  "properties": {
    "addr:full":"621 E Croy St Hailey ID 83333",
    "addr:housenumber":"621",
    "addr:postcode":"83333",
    "addr:street":"E Croy St",
    "iso:country":"US",
    "sg:address":"621 E Croy St",
    "sg:city":"Hailey",
    "sg:classifiers":[
        {
            "category":"Building & Trades",
            "subcategory":"Landscaping Services",
            "type":"Services"
        }
    ],
    "sg:phone":"+1 208 788 7579",
    "sg:postcode":"83333",
    "sg:province":"ID",
    "sg:tags":[
        "lawn",
        "maintenance",
        "grounds"
    ],
    "wof:name":"Fairway Lawns",
    "wof:placetype":"venue"
},
  "geometry": {"coordinates":[-114.306676,43.52196],"type":"Point"}
}