{
  "type": "Feature",
  "properties": {
    "iso:country":"US",
    "sg:address":"405 N Main St",
    "sg:city":"Mountain Home",
    "sg:phone":"+1 208 587 3272",
    "sg:postcode":"83647",
    "sg:province":"ID",
    "sg:tags":[
        "petroleum"
    ],
    "wof:name":"Brico of Idaho Inc",
    "wof:placetype":"venue"
},
  "geometry": {"coordinates":[-115.697104,43.134062],"type":"Point"}
}