{
  "type": "Feature",
  "properties": {
    "iso:country":"US",
    "sg:address":"4990 Valenty Rd",
    "sg:city":"Pocatello",
    "sg:classifiers":[
        {
            "category":"Manufacturing",
            "subcategory":"Food",
            "type":"Manufacturing & Wholesale Goods"
        }
    ],
    "sg:phone":"+1 208 238 0920",
    "sg:postcode":"83202",
    "sg:province":"ID",
    "sg:tags":[
        "coffee",
        "mfg"
    ],
    "wof:name":"Boyd Coffee Company",
    "wof:placetype":"venue"
},
  "geometry": {"coordinates":[-112.46469399999999,42.922489],"type":"Point"}
}