{
  "type": "Feature",
  "properties": {
    "iso:country":"US",
    "sg:address":"724 1st St S",
    "sg:city":"Nampa",
    "sg:classifiers":[
        {
            "category":"Bars & Pubs",
            "type":"Food & Drink"
        }
    ],
    "sg:phone":"+1 208 467 1507",
    "sg:postcode":"83651",
    "sg:province":"ID",
    "sg:tags":[
        "lounge",
        "cocktail"
    ],
    "wof:name":"Monkey Business",
    "wof:placetype":"venue"
},
  "geometry": {"coordinates":[-116.564788,43.582275],"type":"Point"}
}