{
  "type": "Feature",
  "properties": {
    "iso:country":"US",
    "sg:address":"1954 N Yellowstone Hwy",
    "sg:city":"Idaho Falls",
    "sg:classifiers":[
        {
            "category":"Shopping",
            "type":"Retail Goods"
        }
    ],
    "sg:phone":"+1 208 529 1999",
    "sg:postcode":"83401",
    "sg:province":"ID",
    "sg:tags":[
        "pet",
        "shop"
    ],
    "wof:name":"Peaches Pets Feed & Supply",
    "wof:placetype":"venue"
},
  "geometry": {"coordinates":[-112.011724,43.513561],"type":"Point"}
}