{
  "type": "Feature",
  "properties": {
    "iso:country":"US",
    "sg:address":"1180 Blue Lakes Blvd N",
    "sg:city":"Twin Falls",
    "sg:classifiers":[
        {
            "category":"Professional",
            "subcategory":"Computer Services",
            "type":"Services"
        }
    ],
    "sg:phone":"+1 208 734 1300",
    "sg:postcode":"83301",
    "sg:province":"ID",
    "sg:tags":[
        "internet"
    ],
    "wof:name":"Cyber Center",
    "wof:placetype":"venue"
},
  "geometry": {"coordinates":[-114.460247,42.58351],"type":"Point"}
}