{
  "type": "Feature",
  "properties": {
    "addr:full":"313 D St Lewiston ID 83501",
    "addr:housenumber":"313",
    "addr:postcode":"83501",
    "addr:street":"D St",
    "iso:country":"US",
    "sg:address":"313 D St",
    "sg:city":"Lewiston",
    "sg:classifiers":[
        {
            "category":"Government",
            "subcategory":"Police Station",
            "type":"Public Place"
        }
    ],
    "sg:phone":"+1 208 799 5020",
    "sg:postcode":"83501",
    "sg:province":"ID",
    "sg:tags":[
        "state"
    ],
    "wof:name":"Idaho State Police Invstgtn",
    "wof:placetype":"venue"
},
  "geometry": {"coordinates":[-117.029315,46.422014],"type":"Point"}
}