{
  "type": "Feature",
  "properties": {
    "iso:country":"US",
    "sg:address":"1620 N 8th E",
    "sg:city":"Mountain Home",
    "sg:classifiers":[
        {
            "category":"Professional",
            "type":"Services"
        }
    ],
    "sg:phone":"+1 208 587 8182",
    "sg:postcode":"83647",
    "sg:province":"ID",
    "sg:tags":[
        "establishment"
    ],
    "wof:name":"Ulti Mates",
    "wof:placetype":"venue"
},
  "geometry": {"coordinates":[-115.690437,43.149667],"type":"Point"}
}