{
  "type": "Feature",
  "properties": {
    "iso:country":"US",
    "sg:address":"7528 Stage Coach Rd",
    "sg:city":"Melba",
    "sg:classifiers":[
        {
            "category":"Professional",
            "subcategory":"Business Services",
            "type":"Services"
        }
    ],
    "sg:phone":"+1 208 495 2289",
    "sg:postcode":"83641",
    "sg:province":"ID",
    "wof:name":"Bonnie J Burns",
    "wof:placetype":"venue"
},
  "geometry": {"coordinates":[-116.544223,43.444727],"type":"Point"}
}