{
  "type": "Feature",
  "properties": {
    "iso:country":"US",
    "sg:address":"1070 Yellowstone Ave",
    "sg:city":"Pocatello",
    "sg:classifiers":[
        {
            "category":"Retail",
            "subcategory":"Auto Repair",
            "type":"Services"
        }
    ],
    "sg:phone":"+1 208 232 4774",
    "sg:postcode":"83201",
    "sg:province":"ID",
    "sg:tags":[
        "body",
        "automobile",
        "painting"
    ],
    "wof:name":"Prestige Annex",
    "wof:placetype":"venue"
},
  "geometry": {"coordinates":[-112.451368,42.893013],"type":"Point"}
}