{
  "type": "Feature",
  "properties": {
    "iso:country":"US",
    "sg:address":"3653 E 3600 N",
    "sg:city":"Kimberly",
    "sg:classifiers":[
        {
            "category":"Farming",
            "subcategory":"Livestock Farm",
            "type":"Manufacturing & Wholesale Goods"
        }
    ],
    "sg:phone":"+1 208 423 4527",
    "sg:postcode":"83341",
    "sg:province":"ID",
    "sg:tags":[
        "ranch"
    ],
    "wof:name":"White Gold Dairy LLC",
    "wof:placetype":"venue"
},
  "geometry": {"coordinates":[-114.33484900000001,42.518983],"type":"Point"}
}