{
  "type": "Feature",
  "properties": {
    "addr:full":"4757 Cascade Rd Emmett ID 83617",
    "addr:housenumber":"4757",
    "addr:postcode":"83617",
    "addr:street":"Cascade Rd",
    "iso:country":"US",
    "sg:address":"4757 Cascade Rd",
    "sg:city":"Emmett",
    "sg:classifiers":[
        {
            "category":"Building & Trades",
            "subcategory":"Construction",
            "type":"Services"
        }
    ],
    "sg:phone":"+1 208 365 6250",
    "sg:postcode":"83617",
    "sg:province":"ID",
    "sg:tags":[
        "excavation",
        "contractor"
    ],
    "wof:name":"Pulley Construction",
    "wof:placetype":"venue"
},
  "geometry": {"coordinates":[-116.551501,43.868292],"type":"Point"}
}