{
  "type": "Feature",
  "properties": {
    "iso:country":"US",
    "sg:address":"440 E Corporate Dr",
    "sg:city":"Meridian",
    "sg:classifiers":[
        {
            "category":"Real Estate",
            "subcategory":"Architect",
            "type":"Services"
        }
    ],
    "sg:phone":"+1 208 895 0700",
    "sg:postcode":"83642",
    "sg:province":"ID",
    "wof:name":"Ruby Edwards Architecture & De",
    "wof:placetype":"venue"
},
  "geometry": {"coordinates":[-116.388058,43.598992],"type":"Point"}
}