{
  "type": "Feature",
  "properties": {
    "addr:full":"209 Apache Dr Hailey ID 83333",
    "addr:housenumber":"209",
    "addr:postcode":"83333",
    "addr:street":"Apache Dr",
    "iso:country":"US",
    "sg:address":"209 Apache Dr",
    "sg:city":"Hailey",
    "sg:classifiers":[
        {
            "category":"Building & Trades",
            "subcategory":"Construction",
            "type":"Services"
        }
    ],
    "sg:phone":"+1 208 788 2607",
    "sg:postcode":"83333",
    "sg:province":"ID",
    "sg:tags":[
        "woodworker"
    ],
    "wof:name":"Northwest Door & Mill",
    "wof:placetype":"venue"
},
  "geometry": {"coordinates":[-114.29606200000001,43.569817],"type":"Point"}
}