{
  "type": "Feature",
  "properties": {
    "iso:country":"US",
    "sg:address":"2870 Juniper Dr",
    "sg:city":"Lewiston",
    "sg:classifiers":[
        {
            "category":"Social Services",
            "subcategory":"Adult Care",
            "type":"Services"
        }
    ],
    "sg:phone":"+1 208 746 2800",
    "sg:postcode":"83501",
    "sg:province":"ID",
    "sg:tags":[
        "home",
        "residential"
    ],
    "wof:name":"Royal Plaza Retirement & Care",
    "wof:placetype":"venue"
},
  "geometry": {"coordinates":[-116.991198,46.396053],"type":"Point"}
}