{
  "type": "Feature",
  "properties": {
    "addr:full":"107 W Main St Craigmont ID 83523",
    "addr:housenumber":"107",
    "addr:postcode":"83523",
    "addr:street":"W Main St",
    "iso:country":"US",
    "sg:address":"107 W Main St",
    "sg:city":"Craigmont",
    "sg:classifiers":[
        {
            "category":"Sports & Exercise",
            "subcategory":"Bowling",
            "type":"Entertainment"
        }
    ],
    "sg:phone":"+1 208 924 6649",
    "sg:postcode":"83523",
    "sg:province":"ID",
    "sg:tags":[
        "center"
    ],
    "wof:name":"Prairie Imperial Bowl",
    "wof:placetype":"venue"
},
  "geometry": {"coordinates":[-116.476142,46.240691],"type":"Point"}
}