{
  "type": "Feature",
  "properties": {
    "addr:full":"208 Main St Cottonwood ID 83522",
    "addr:housenumber":"208",
    "addr:postcode":"83522",
    "addr:street":"Main St",
    "iso:country":"US",
    "sg:address":"208 Main St",
    "sg:city":"Cottonwood",
    "sg:classifiers":[
        {
            "category":"Autos & Motor Vehicles",
            "subcategory":"Automobile Sales",
            "type":"Retail Goods"
        }
    ],
    "sg:phone":"+1 208 962 7120",
    "sg:postcode":"83522",
    "sg:province":"ID",
    "sg:tags":[
        "car",
        "dealer"
    ],
    "wof:name":"L & L Auto Sales",
    "wof:placetype":"venue"
},
  "geometry": {"coordinates":[-116.34410699999999,46.045239],"type":"Point"}
}