{
  "type": "Feature",
  "properties": {
    "iso:country":"US",
    "sg:address":"3200 Chinden Blvd",
    "sg:city":"Boise",
    "sg:classifiers":[
        {
            "category":"Autos & Motor Vehicles",
            "subcategory":"Automobile Sales",
            "type":"Retail Goods"
        }
    ],
    "sg:phone":"+1 208 336 8230",
    "sg:postcode":"83714",
    "sg:province":"ID",
    "sg:tags":[
        "car",
        "dealer"
    ],
    "wof:name":"Dale's Auto Sales",
    "wof:placetype":"venue"
},
  "geometry": {"coordinates":[-116.238298,43.621956],"type":"Point"}
}