{
  "type": "Feature",
  "properties": {
    "iso:country":"US",
    "sg:address":"3407 E Pinehill Dr",
    "sg:city":"Coeur D Alene",
    "sg:classifiers":[
        {
            "category":"Travel",
            "subcategory":"Travel Agent",
            "type":"Entertainment"
        }
    ],
    "sg:phone":"+1 208 666 9640",
    "sg:postcode":"83815",
    "sg:province":"ID",
    "sg:tags":[
        "agency",
        "bureau"
    ],
    "wof:name":"Destinations Unlimited Tours",
    "wof:placetype":"venue"
},
  "geometry": {"coordinates":[-116.756005,47.708653],"type":"Point"}
}