{
  "type": "Feature",
  "properties": {
    "iso:country":"US",
    "sg:address":"9116 Sunflower Ln",
    "sg:city":"Boise",
    "sg:classifiers":[
        {
            "category":"Building & Trades",
            "subcategory":"Construction",
            "type":"Services"
        }
    ],
    "sg:phone":"+1 208 376 0862",
    "sg:postcode":"83704",
    "sg:province":"ID",
    "sg:tags":[
        "contractor"
    ],
    "wof:name":"Pioneer Drywall",
    "wof:placetype":"venue"
},
  "geometry": {"coordinates":[-116.295262,43.624944],"type":"Point"}
}