{
  "type": "Feature",
  "properties": {
    "addr:full":"4545 Pinto Dr Boise ID 83709",
    "addr:housenumber":"4545",
    "addr:postcode":"83709",
    "addr:street":"Pinto Dr",
    "iso:country":"US",
    "sg:address":"4545 Pinto Dr",
    "sg:city":"Boise",
    "sg:classifiers":[
        {
            "category":"Building & Trades",
            "subcategory":"Construction",
            "type":"Services"
        }
    ],
    "sg:phone":"+1 208 362 9817",
    "sg:postcode":"83709",
    "sg:province":"ID",
    "sg:tags":[
        "grading",
        "contractor"
    ],
    "wof:name":"Justin Rubelt Inc",
    "wof:placetype":"venue"
},
  "geometry": {"coordinates":[-116.31682499999999,43.562069],"type":"Point"}
}