{
  "type": "Feature",
  "properties": {
    "iso:country":"US",
    "sg:address":"1880 E 8th N",
    "sg:city":"Mountain Home",
    "sg:classifiers":[
        {
            "category":"Sports & Exercise",
            "subcategory":"Golf",
            "type":"Entertainment"
        }
    ],
    "sg:phone":"+1 208 587 3293",
    "sg:postcode":"83647",
    "sg:province":"ID",
    "sg:tags":[
        "course"
    ],
    "wof:name":"Mountain Home Golf Course",
    "wof:placetype":"venue"
},
  "geometry": {"coordinates":[-115.674892,43.137597],"type":"Point"}
}