{
  "type": "Feature",
  "properties": {
    "addr:full":"3350 S 15th E Idaho Falls ID 83404",
    "addr:housenumber":"3350",
    "addr:postcode":"83404",
    "addr:street":"S 15Th E",
    "iso:country":"US",
    "sg:address":"3350 S 15th E",
    "sg:city":"Idaho Falls",
    "sg:classifiers":[
        {
            "category":"Health Services",
            "subcategory":"Doctor",
            "type":"Services"
        }
    ],
    "sg:phone":"+1 208 522 5376",
    "sg:postcode":"83404",
    "sg:province":"ID",
    "sg:tags":[
        "dentist"
    ],
    "wof:name":"Gary J Nelson Dmd",
    "wof:placetype":"venue"
},
  "geometry": {"coordinates":[-112.004154,43.468071],"type":"Point"}
}