{
  "type": "Feature",
  "properties": {
    "iso:country":"US",
    "sg:address":"513 Garfield St",
    "sg:city":"Boise",
    "sg:classifiers":[
        {
            "category":"Professional",
            "subcategory":"Computer Services",
            "type":"Services"
        }
    ],
    "sg:phone":"+1 208 395 3136",
    "sg:postcode":"83706",
    "sg:province":"ID",
    "wof:name":"Rob McConnel",
    "wof:placetype":"venue"
},
  "geometry": {"coordinates":[-116.18775599999999,43.589791],"type":"Point"}
}