{
  "type": "Feature",
  "properties": {
    "iso:country":"US",
    "sg:address":"1800 W Overland Rd",
    "sg:city":"Boise",
    "sg:classifiers":[
        {
            "category":"Professional",
            "subcategory":"Engineering",
            "type":"Services"
        }
    ],
    "sg:phone":"+1 208 344 9700",
    "sg:postcode":"83705",
    "sg:province":"ID",
    "sg:tags":[
        "engineer"
    ],
    "sg:website":"www.briggsengineering.com",
    "wof:name":"Briggs Engineering Inc",
    "wof:placetype":"venue"
},
  "geometry": {"coordinates":[-116.205478,43.58985],"type":"Point"}
}