{
  "type": "Feature",
  "properties": {
    "addr:full":"450 E Day St Pocatello ID 83201",
    "addr:housenumber":"450",
    "addr:postcode":"83201",
    "addr:street":"E Day St",
    "iso:country":"US",
    "sg:address":"450 E Day St",
    "sg:city":"Pocatello",
    "sg:classifiers":[
        {
            "category":"Shopping",
            "type":"Retail Goods"
        }
    ],
    "sg:phone":"+1 208 478 6554",
    "sg:postcode":"83201",
    "sg:province":"ID",
    "sg:tags":[
        "wheel",
        "chair",
        "scooter"
    ],
    "wof:name":"Advanced Mobility",
    "wof:placetype":"venue"
},
  "geometry": {"coordinates":[-112.45653,42.875168],"type":"Point"}
}