{
  "type": "Feature",
  "properties": {
    "iso:country":"US",
    "sg:address":"2130 W Franklin Rd",
    "sg:city":"Meridian",
    "sg:classifiers":[
        {
            "category":"Utilities",
            "subcategory":"Refuse",
            "type":"Services"
        }
    ],
    "sg:phone":"+1 208 888 3999",
    "sg:postcode":"83642",
    "sg:province":"ID",
    "sg:tags":[
        "garbage",
        "collection"
    ],
    "wof:name":"Sanitary Service Co",
    "wof:placetype":"venue"
},
  "geometry": {"coordinates":[-116.419201,43.604797],"type":"Point"}
}