{
  "type": "Feature",
  "properties": {
    "iso:country":"US",
    "sg:address":"129 Willow Ave W",
    "sg:city":"Fairfield",
    "sg:classifiers":[
        {
            "category":"Social Services",
            "subcategory":"Adult Care",
            "type":"Services"
        }
    ],
    "sg:phone":"+1 208 764 2226",
    "sg:postcode":"83327",
    "sg:province":"ID",
    "sg:tags":[
        "organization",
        "senior",
        "citizen"
    ],
    "wof:name":"Camas County Senior Citizen",
    "wof:placetype":"venue"
},
  "geometry": {"coordinates":[-114.793582,43.345564],"type":"Point"}
}