{
  "type": "Feature",
  "properties": {
    "iso:country":"US",
    "sg:address":"1053 Camelot Dr",
    "sg:city":"Boise",
    "sg:classifiers":[
        {
            "category":"Professional",
            "subcategory":"Business Services",
            "type":"Services"
        }
    ],
    "sg:phone":"+1 208 377 1384",
    "sg:postcode":"83704",
    "sg:province":"ID",
    "wof:name":"A&A Appraisals & Estate Sales",
    "wof:placetype":"venue"
},
  "geometry": {"coordinates":[-116.27133499999999,43.615945],"type":"Point"}
}