{
  "type": "Feature",
  "properties": {
    "iso:country":"US",
    "sg:address":"20 E Idaho Ave",
    "sg:city":"Homedale",
    "sg:classifiers":[
        {
            "category":"Manufacturing",
            "subcategory":"Printing",
            "type":"Manufacturing & Wholesale Goods"
        }
    ],
    "sg:phone":"+1 208 337 4866",
    "sg:postcode":"83628",
    "sg:province":"ID",
    "sg:tags":[
        "printer"
    ],
    "wof:name":"Owyhee Publishing Co Inc",
    "wof:placetype":"venue"
},
  "geometry": {"coordinates":[-116.932718,43.617662],"type":"Point"}
}