{
  "type": "Feature",
  "properties": {
    "addr:full":"421 N Cole Rd Boise ID 83704",
    "addr:housenumber":"421",
    "addr:postcode":"83704",
    "addr:street":"N Cole Rd",
    "iso:country":"US",
    "sg:address":"421 N Cole Rd",
    "sg:city":"Boise",
    "sg:classifiers":[
        {
            "category":"Banks & Credit Unions",
            "subcategory":"Bank",
            "type":"Services"
        }
    ],
    "sg:phone":"+1 208 323 8700",
    "sg:postcode":"83704",
    "sg:province":"ID",
    "wof:name":"Bank Of America",
    "wof:placetype":"venue"
},
  "geometry": {"coordinates":[-116.274045,43.608064],"type":"Point"}
}