{
  "type": "Feature",
  "properties": {
    "iso:country":"US",
    "sg:address":"570 Wedge Way",
    "sg:city":"Pocatello",
    "sg:classifiers":[
        {
            "category":"Professional",
            "subcategory":"Advertising",
            "type":"Services"
        }
    ],
    "sg:phone":"+1 208 478 8298",
    "sg:postcode":"83204",
    "sg:province":"ID",
    "sg:tags":[
        "distribution"
    ],
    "wof:name":"F Squared",
    "wof:placetype":"venue"
},
  "geometry": {"coordinates":[-112.393178,42.810569],"type":"Point"}
}