{
  "type": "Feature",
  "properties": {
    "iso:country":"US",
    "sg:address":"215 E Franklin Rd",
    "sg:city":"Meridian",
    "sg:classifiers":[
        {
            "category":"Organizations",
            "subcategory":"Professional Association",
            "type":"Services"
        }
    ],
    "sg:phone":"+1 208 888 2817",
    "sg:postcode":"83642",
    "sg:province":"ID",
    "sg:tags":[
        "chambers",
        "commerce"
    ],
    "wof:name":"Meridian Chamber Of Commerce",
    "wof:placetype":"venue"
},
  "geometry": {"coordinates":[-116.39107199999999,43.604615],"type":"Point"}
}