{
  "type": "Feature",
  "properties": {
    "iso:country":"US",
    "sg:address":"5235 S Ten Mile Rd",
    "sg:city":"Meridian",
    "sg:phone":"+1 208 888 3615",
    "sg:postcode":"83642",
    "sg:province":"ID",
    "sg:tags":[
        "farm",
        "field",
        "crop"
    ],
    "wof:name":"Willard Payne",
    "wof:placetype":"venue"
},
  "geometry": {"coordinates":[-116.433863,43.55753],"type":"Point"}
}