{
  "type": "Feature",
  "properties": {
    "iso:country":"US",
    "sg:address":"221 W 37th St",
    "sg:city":"Boise",
    "sg:classifiers":[
        {
            "category":"Shopping",
            "subcategory":"Computers & Home Electronics",
            "type":"Retail Goods"
        }
    ],
    "sg:phone":"+1 208 658 1100",
    "sg:postcode":"83714",
    "sg:province":"ID",
    "wof:name":"P C Recyclers",
    "wof:placetype":"venue"
},
  "geometry": {"coordinates":[-116.24433999999999,43.623916],"type":"Point"}
}