{
  "type": "Feature",
  "properties": {
    "addr:full":"170 S Spud Aly Shelley ID 83274",
    "addr:housenumber":"170",
    "addr:postcode":"83274",
    "addr:street":"S Spud Aly",
    "iso:country":"US",
    "sg:address":"170 S Spud Aly",
    "sg:city":"Shelley",
    "sg:classifiers":[
        {
            "category":"Building & Trades",
            "subcategory":"Construction",
            "type":"Services"
        }
    ],
    "sg:phone":"+1 208 357 7975",
    "sg:postcode":"83274",
    "sg:province":"ID",
    "sg:tags":[
        "acoustical",
        "contractor"
    ],
    "wof:name":"Shelley Acoustics",
    "wof:placetype":"venue"
},
  "geometry": {"coordinates":[-112.123214,43.380214],"type":"Point"}
}