{
  "type": "Feature",
  "properties": {
    "iso:country":"US",
    "sg:address":"10883 N Yellowstone Hwy",
    "sg:city":"Ucon",
    "sg:classifiers":[
        {
            "category":"Retail",
            "subcategory":"Auto Repair",
            "type":"Services"
        }
    ],
    "sg:phone":"+1 208 529 5564",
    "sg:postcode":"83454",
    "sg:province":"ID",
    "sg:tags":[
        "repairing",
        "automobile",
        "radiator"
    ],
    "wof:name":"Holst Radiator Repair",
    "wof:placetype":"venue"
},
  "geometry": {"coordinates":[-111.963885,43.593412],"type":"Point"}
}