{
  "type": "Feature",
  "properties": {
    "addr:full":"108 W 33rd St Boise ID 83714",
    "addr:housenumber":"108",
    "addr:postcode":"83714",
    "addr:street":"W 33Rd St",
    "iso:country":"US",
    "sg:address":"108 W 33rd St",
    "sg:city":"Boise",
    "sg:classifiers":[
        {
            "category":"Autos & Motor Vehicles",
            "subcategory":"Auto Supplies",
            "type":"Retail Goods"
        }
    ],
    "sg:phone":"+1 208 323 8403",
    "sg:postcode":"83714",
    "sg:province":"ID",
    "sg:tags":[
        "automobile",
        "parts"
    ],
    "wof:name":"Radiators Inc Of Idaho",
    "wof:placetype":"venue"
},
  "geometry": {"coordinates":[-116.239501,43.621158],"type":"Point"}
}