{
  "type": "Feature",
  "properties": {
    "iso:country":"US",
    "sg:address":"720 S Deakin St",
    "sg:city":"Moscow",
    "sg:classifiers":[
        {
            "category":"Organizations",
            "subcategory":"Community Association",
            "type":"Services"
        }
    ],
    "sg:phone":"+1 208 885 3558",
    "sg:postcode":"83843",
    "sg:province":"ID",
    "sg:tags":[
        "sorority",
        "fraternity"
    ],
    "wof:name":"Alpha Gamma Rho",
    "wof:placetype":"venue"
},
  "geometry": {"coordinates":[-117.007203,46.728023],"type":"Point"}
}