{
  "type": "Feature",
  "properties": {
    "addr:full":"2142 Broadway Ave Boise ID 83706",
    "addr:housenumber":"2142",
    "addr:postcode":"83706",
    "addr:street":"Broadway Ave",
    "iso:country":"US",
    "sg:address":"2142 Broadway Ave",
    "sg:city":"Boise",
    "sg:classifiers":[
        {
            "category":"Professional",
            "subcategory":"Accounting & Tax Preparation",
            "type":"Services"
        }
    ],
    "sg:phone":"+1 208 345 9762",
    "sg:postcode":"83706",
    "sg:province":"ID",
    "sg:tags":[
        "communication",
        "return",
        "telegraph"
    ],
    "wof:name":"H & R Block",
    "wof:placetype":"venue"
},
  "geometry": {"coordinates":[-116.193566,43.585479],"type":"Point"}
}