{
  "type": "Feature",
  "properties": {
    "iso:country":"US",
    "sg:address":"330 Orchard Ave",
    "sg:city":"Rexburg",
    "sg:classifiers":[
        {
            "category":"Personal",
            "subcategory":"Beauty Salon",
            "type":"Services"
        }
    ],
    "sg:phone":"+1 208 356 6608",
    "sg:postcode":"83440",
    "sg:province":"ID",
    "wof:name":"Shear Pleasure",
    "wof:placetype":"venue"
},
  "geometry": {"coordinates":[-111.791158,43.819237],"type":"Point"}
}