{
  "type": "Feature",
  "properties": {
    "iso:country":"US",
    "sg:address":"212 Deere St",
    "sg:city":"Twin Falls",
    "sg:classifiers":[
        {
            "category":"Social Services",
            "subcategory":"Job Training",
            "type":"Services"
        }
    ],
    "sg:phone":"+1 208 736 0990",
    "sg:postcode":"83301",
    "sg:province":"ID",
    "sg:tags":[
        "rehabilitation"
    ],
    "wof:name":"Omega Service Coordination",
    "wof:placetype":"venue"
},
  "geometry": {"coordinates":[-114.427294,42.548152],"type":"Point"}
}