{
  "type": "Feature",
  "properties": {
    "iso:country":"US",
    "sg:address":"1605 W Karcher Rd",
    "sg:city":"Nampa",
    "sg:classifiers":[
        {
            "category":"Retail",
            "subcategory":"Auto Repair",
            "type":"Services"
        }
    ],
    "sg:phone":"+1 208 466 7233",
    "sg:postcode":"83651",
    "sg:province":"ID",
    "sg:tags":[
        "automobile",
        "top",
        "upholstery"
    ],
    "wof:name":"Jim's Auto & Boat Upholstery",
    "wof:placetype":"venue"
},
  "geometry": {"coordinates":[-116.600899,43.604909],"type":"Point"}
}