{
  "type": "Feature",
  "properties": {
    "iso:country":"US",
    "sg:address":"5307 Lockwood Way",
    "sg:city":"Caldwell",
    "sg:classifiers":[
        {
            "category":"Building & Trades",
            "subcategory":"Construction",
            "type":"Services"
        }
    ],
    "sg:phone":"+1 208 454 2026",
    "sg:postcode":"83607",
    "sg:province":"ID",
    "sg:tags":[
        "general",
        "contractor"
    ],
    "wof:name":"KGL Construction",
    "wof:placetype":"venue"
},
  "geometry": {"coordinates":[-116.684756,43.623815],"type":"Point"}
}