{
  "type": "Feature",
  "properties": {
    "addr:full":"5307 Lockwood Way Caldwell ID 83607",
    "addr:housenumber":"5307",
    "addr:postcode":"83607",
    "addr:street":"Lockwood Way",
    "iso:country":"US",
    "sg:address":"5307 Lockwood Way",
    "sg:city":"Caldwell",
    "sg:classifiers":[
        {
            "category":"Building & Trades",
            "subcategory":"Construction",
            "type":"Services"
        }
    ],
    "sg:phone":"+1 208 454 2026",
    "sg:postcode":"83607",
    "sg:province":"ID",
    "sg:tags":[
        "general",
        "contractor"
    ],
    "wof:name":"KGL Construction",
    "wof:placetype":"venue"
},
  "geometry": {"coordinates":[-116.68475599999999,43.623815],"type":"Point"}
}