{
  "type": "Feature",
  "properties": {
    "iso:country":"US",
    "sg:address":"11070 Camas St",
    "sg:city":"Boise",
    "sg:classifiers":[
        {
            "category":"Building & Trades",
            "subcategory":"Construction",
            "type":"Services"
        }
    ],
    "sg:phone":"+1 208 376 7691",
    "sg:postcode":"83709",
    "sg:province":"ID",
    "sg:tags":[
        "grade",
        "final",
        "contractor"
    ],
    "wof:name":"Mastalskis Skid-Steer Service",
    "wof:placetype":"venue"
},
  "geometry": {"coordinates":[-116.319909,43.596465],"type":"Point"}
}