{
  "type": "Feature",
  "properties": {
    "addr:full":"648 Grays Lake Rd Wayan ID 83285",
    "addr:housenumber":"648",
    "addr:postcode":"83285",
    "addr:street":"Grays Lake Rd",
    "iso:country":"US",
    "sg:address":"648 Grays Lake Rd",
    "sg:city":"Wayan",
    "sg:classifiers":[
        {
            "category":"Farming",
            "subcategory":"Livestock Farm",
            "type":"Manufacturing & Wholesale Goods"
        }
    ],
    "sg:phone":"+1 208 574 2495",
    "sg:postcode":"83285",
    "sg:province":"ID",
    "sg:tags":[
        "feedlot",
        "field",
        "crop",
        "beef",
        "cattle"
    ],
    "wof:name":"Reed Humphreys",
    "wof:placetype":"venue"
},
  "geometry": {"coordinates":[-111.38644499999999,43.105212],"type":"Point"}
}