{
  "type": "Feature",
  "properties": {
    "iso:country":"US",
    "sg:address":"11875 W Manitoba Ct",
    "sg:city":"Post Falls",
    "sg:classifiers":[
        {
            "category":"Recreation",
            "type":"Entertainment"
        }
    ],
    "sg:phone":"+1 208 777 7958",
    "sg:postcode":"83854",
    "sg:province":"ID",
    "sg:tags":[
        "stable"
    ],
    "wof:name":"Prairie Stables",
    "wof:placetype":"venue"
},
  "geometry": {"coordinates":[-116.940275,47.766974],"type":"Point"}
}