{
  "type": "Feature",
  "properties": {
    "iso:country":"US",
    "sg:address":"2281 Overland Ave",
    "sg:city":"Burley",
    "sg:classifiers":[
        {
            "category":"Banks & Credit Unions",
            "subcategory":"Bank",
            "type":"Services"
        }
    ],
    "sg:phone":"+1 208 678 6000",
    "sg:postcode":"83318",
    "sg:province":"ID",
    "sg:website":"www.dlevans.com",
    "wof:name":"D L Evans Bank",
    "wof:placetype":"venue"
},
  "geometry": {"coordinates":[-113.793171,42.524701],"type":"Point"}
}