{
  "type": "Feature",
  "properties": {
    "iso:country":"US",
    "sg:address":"328 N Main St",
    "sg:city":"Moscow",
    "sg:classifiers":[
        {
            "category":"Retail",
            "subcategory":"Veterinary Services",
            "type":"Services"
        }
    ],
    "sg:phone":"+1 208 883 4349",
    "sg:postcode":"83843",
    "sg:province":"ID",
    "sg:tags":[
        "veterinarian"
    ],
    "wof:name":"Animal Care Ctr",
    "wof:placetype":"venue"
},
  "geometry": {"coordinates":[-117.001389,46.736488],"type":"Point"}
}