{
  "type": "Feature",
  "properties": {
    "iso:country":"US",
    "sg:address":"104 E 6th St",
    "sg:city":"Moscow",
    "sg:classifiers":[
        {
            "category":"Insurance",
            "subcategory":"Insurance Agent",
            "type":"Services"
        }
    ],
    "sg:phone":"+1 208 882 6776",
    "sg:postcode":"83843",
    "sg:province":"ID",
    "wof:name":"John Harrell Ins Financial Svc",
    "wof:placetype":"venue"
},
  "geometry": {"coordinates":[-116.999991,46.730242],"type":"Point"}
}