{
  "type": "Feature",
  "properties": {
    "iso:country":"US",
    "sg:address":"4700 W State St",
    "sg:city":"Boise",
    "sg:classifiers":[
        {
            "category":"Autos & Motor Vehicles",
            "subcategory":"Auto Supplies",
            "type":"Retail Goods"
        }
    ],
    "sg:phone":"+1 208 336 2563",
    "sg:postcode":"83703",
    "sg:province":"ID",
    "sg:tags":[
        "automobile",
        "parts"
    ],
    "wof:name":"Autozone",
    "wof:placetype":"venue"
},
  "geometry": {"coordinates":[-116.24746399999999,43.648534],"type":"Point"}
}