{
  "type": "Feature",
  "properties": {
    "iso:country":"US",
    "sg:address":"1100 Meadowbrook Ln",
    "sg:city":"Nampa",
    "sg:classifiers":[
        {
            "category":"Building & Trades",
            "subcategory":"Construction",
            "type":"Services"
        }
    ],
    "sg:phone":"+1 208 465 2004",
    "sg:postcode":"83686",
    "sg:province":"ID",
    "sg:tags":[
        "repairing",
        "remodeling",
        "contractor"
    ],
    "wof:name":"3 Co",
    "wof:placetype":"venue"
},
  "geometry": {"coordinates":[-116.562586,43.535533],"type":"Point"}
}