{
  "type": "Feature",
  "properties": {
    "iso:country":"US",
    "sg:address":"104 N Main St",
    "sg:city":"Moscow",
    "sg:classifiers":[
        {
            "category":"Professional",
            "subcategory":"Business Services",
            "type":"Services"
        }
    ],
    "sg:phone":"+1 208 883 4309",
    "sg:postcode":"83843",
    "sg:province":"ID",
    "wof:name":"Geographic Mapping Consultants",
    "wof:placetype":"venue"
},
  "geometry": {"coordinates":[-117.001296,46.733708],"type":"Point"}
}