{
  "type": "Feature",
  "properties": {
    "iso:country":"US",
    "sg:address":"1823 Blue Lakes Blvd N",
    "sg:city":"Twin Falls",
    "sg:classifiers":[
        {
            "category":"Bakery",
            "type":"Food & Drink"
        }
    ],
    "sg:menulink":"http://www.allmenus.com/id/twin-falls/100039-golden-corral/menu/",
    "sg:phone":"+1 208 735 1820",
    "sg:postcode":"83301",
    "sg:province":"ID",
    "sg:tags":[
        "american",
        "pastry"
    ],
    "wof:name":"Golden Corral",
    "wof:placetype":"venue"
},
  "geometry": {"coordinates":[-114.459003,42.594293],"type":"Point"}
}