{
  "type": "Feature",
  "properties": {
    "addr:full":"415 E Anderson St Idaho Falls ID 83401",
    "addr:housenumber":"415",
    "addr:postcode":"83401",
    "addr:street":"E Anderson St",
    "iso:country":"US",
    "sg:address":"415 E Anderson St",
    "sg:city":"Idaho Falls",
    "sg:classifiers":[
        {
            "category":"Food & Beverages",
            "subcategory":"Groceries & Convenience Stores",
            "type":"Retail Goods"
        }
    ],
    "sg:phone":"+1 208 524 1092",
    "sg:postcode":"83401",
    "sg:province":"ID",
    "wof:name":"Speedi Mart",
    "wof:placetype":"venue"
},
  "geometry": {"coordinates":[-112.026506,43.511378],"type":"Point"}
}