{
  "type": "Feature",
  "properties": {
    "iso:country":"US",
    "sg:address":"416 S Main St",
    "sg:city":"Hailey",
    "sg:classifiers":[
        {
            "category":"Personal",
            "subcategory":"Beauty Salon",
            "type":"Services"
        }
    ],
    "sg:phone":"+1 208 788 8518",
    "sg:postcode":"83320",
    "sg:province":"ID",
    "wof:name":"Bataille Zsa Salon",
    "wof:placetype":"venue"
},
  "geometry": {"coordinates":[-114.31304,43.516633],"type":"Point"}
}