{
  "type": "Feature",
  "properties": {
    "iso:country":"US",
    "sg:address":"620 S Elder St",
    "sg:city":"Nampa",
    "sg:classifiers":[
        {
            "category":"Shopping",
            "subcategory":"Gifts & Souvenirs",
            "type":"Retail Goods"
        }
    ],
    "sg:phone":"+1 208 465 7659",
    "sg:postcode":"83686",
    "sg:province":"ID",
    "sg:tags":[
        "basket"
    ],
    "wof:name":"Leones Special Occasions",
    "wof:placetype":"venue"
},
  "geometry": {"coordinates":[-116.560057,43.563217],"type":"Point"}
}