{
  "type": "Feature",
  "properties": {
    "addr:full":"8459 N 55th E Idaho Falls ID 83401",
    "addr:housenumber":"8459",
    "addr:postcode":"83401",
    "addr:street":"N 55Th E",
    "iso:country":"US",
    "sg:address":"8459 N 55th E",
    "sg:city":"Idaho Falls",
    "sg:classifiers":[
        {
            "category":"Building & Trades",
            "subcategory":"Construction",
            "type":"Services"
        }
    ],
    "sg:phone":"+1 208 535 0714",
    "sg:postcode":"83401",
    "sg:province":"ID",
    "sg:tags":[
        "general",
        "contractor"
    ],
    "wof:name":"J & D Enterprises",
    "wof:placetype":"venue"
},
  "geometry": {"coordinates":[-111.924119,43.57242],"type":"Point"}
}