{
  "type": "Feature",
  "properties": {
    "iso:country":"US",
    "sg:address":"112 Broadway Ave N",
    "sg:city":"Buhl",
    "sg:classifiers":[
        {
            "category":"Professional",
            "subcategory":"Accounting & Tax Preparation",
            "type":"Services"
        }
    ],
    "sg:phone":"+1 208 543 6550",
    "sg:postcode":"83316",
    "sg:province":"ID",
    "sg:tags":[
        "accountant"
    ],
    "wof:name":"D Monte Davis",
    "wof:placetype":"venue"
},
  "geometry": {"coordinates":[-114.760761,42.599835],"type":"Point"}
}