{
  "type": "Feature",
  "properties": {
    "addr:full":"11217 Barden Tower Dr Boise ID 83709",
    "addr:postcode":"11217;83709",
    "addr:street":"Tower Dr",
    "iso:country":"US",
    "sg:address":"11217 Barden Tower Dr",
    "sg:city":"Boise",
    "sg:classifiers":[
        {
            "category":"Social Services",
            "subcategory":"Adult Care",
            "type":"Services"
        }
    ],
    "sg:phone":"+1 208 376 7782",
    "sg:postcode":"83709",
    "sg:province":"ID",
    "sg:tags":[
        "home",
        "residential"
    ],
    "wof:name":"Happer Kamper",
    "wof:placetype":"venue"
},
  "geometry": {"coordinates":[-116.32265099999999,43.599483],"type":"Point"}
}