{
  "type": "Feature",
  "properties": {
    "iso:country":"US",
    "sg:address":"4317 Wagonwheel Cir",
    "sg:city":"Ammon",
    "sg:classifiers":[
        {
            "category":"Autos & Motor Vehicles",
            "subcategory":"Automobile Sales",
            "type":"Retail Goods"
        }
    ],
    "sg:phone":"+1 208 522 9200",
    "sg:postcode":"83401",
    "sg:province":"ID",
    "sg:tags":[
        "car",
        "dealer"
    ],
    "wof:name":"State Auto Sales",
    "wof:placetype":"venue"
},
  "geometry": {"coordinates":[-111.948254,43.466914],"type":"Point"}
}