{
  "type": "Feature",
  "properties": {
    "addr:full":"1017 Ripon Ave Lewiston ID 83501",
    "addr:housenumber":"1017",
    "addr:postcode":"83501",
    "addr:street":"Ripon Ave",
    "iso:country":"US",
    "sg:address":"1017 Ripon Ave",
    "sg:city":"Lewiston",
    "sg:classifiers":[
        {
            "category":"Building & Trades",
            "subcategory":"Landscaping Services",
            "type":"Services"
        }
    ],
    "sg:phone":"+1 208 798 9115",
    "sg:postcode":"83501",
    "sg:province":"ID",
    "sg:tags":[
        "designer",
        "landscape"
    ],
    "wof:name":"KAS Enterprises",
    "wof:placetype":"venue"
},
  "geometry": {"coordinates":[-116.979849,46.365941],"type":"Point"}
}