{
  "type": "Feature",
  "properties": {
    "addr:full":"110 Scout Ln Boise ID 83702",
    "addr:housenumber":"110",
    "addr:postcode":"83702",
    "addr:street":"Scout Ln",
    "iso:country":"US",
    "sg:address":"110 Scout Ln",
    "sg:city":"Boise",
    "sg:classifiers":[
        {
            "category":"Recreation",
            "type":"Entertainment"
        }
    ],
    "sg:phone":"+1 208 384 4256",
    "sg:postcode":"83702",
    "sg:province":"ID",
    "sg:tags":[
        "center"
    ],
    "wof:name":"Boise City Recreation Office",
    "wof:placetype":"venue"
},
  "geometry": {"coordinates":[-116.187359,43.615956],"type":"Point"}
}