{
  "type": "Feature",
  "properties": {
    "addr:full":"288 N Ridge Ave Idaho Falls ID 83402",
    "addr:housenumber":"288",
    "addr:postcode":"83402",
    "addr:street":"N Ridge Ave",
    "iso:country":"US",
    "sg:address":"288 N Ridge Ave",
    "sg:city":"Idaho Falls",
    "sg:classifiers":[
        {
            "category":"Social Services",
            "type":"Services"
        }
    ],
    "sg:phone":"+1 208 529 6696",
    "sg:postcode":"83402",
    "sg:province":"ID",
    "sg:tags":[
        "organization",
        "welfare"
    ],
    "sg:website":"www.youthranch.org",
    "wof:name":"Harbor House",
    "wof:placetype":"venue"
},
  "geometry": {"coordinates":[-112.03596,43.489456],"type":"Point"}
}