{
  "type": "Feature",
  "properties": {
    "addr:full":"2708 S River Rd St Anthony ID 83445",
    "addr:housenumber":"2708",
    "addr:postcode":"83445",
    "addr:street":"S River Rd",
    "iso:country":"US",
    "sg:address":"2708 S River Rd",
    "sg:city":"St Anthony",
    "sg:classifiers":[
        {
            "category":"Retail",
            "subcategory":"Laundry & Dry Cleaning",
            "type":"Services"
        }
    ],
    "sg:phone":"+1 208 624 7426",
    "sg:postcode":"83445",
    "sg:province":"ID",
    "wof:name":"Turner Laundry",
    "wof:placetype":"venue"
},
  "geometry": {"coordinates":[-111.61647600000001,43.98377],"type":"Point"}
}