{
  "type": "Feature",
  "properties": {
    "addr:full":"2416 12th Ave Rd Nampa ID 83686",
    "addr:housenumber":"2416",
    "addr:postcode":"83686",
    "addr:street":"12Th Ave Rd",
    "iso:country":"US",
    "sg:address":"2416 12th Ave Rd",
    "sg:city":"Nampa",
    "sg:classifiers":[
        {
            "category":"Banks & Credit Unions",
            "subcategory":"Bank",
            "type":"Services"
        }
    ],
    "sg:phone":"+1 208 463 1314",
    "sg:postcode":"83686",
    "sg:province":"ID",
    "sg:tags":[
        "cashing",
        "check"
    ],
    "wof:name":"Singers Insta-Cash Inc",
    "wof:placetype":"venue"
},
  "geometry": {"coordinates":[-116.572599,43.545934],"type":"Point"}
}