{
  "type": "Feature",
  "properties": {
    "addr:full":"1879 E Prairieview Dr Post Falls ID 83854",
    "addr:housenumber":"1879",
    "addr:postcode":"83854",
    "addr:street":"E Prairieview Dr",
    "iso:country":"US",
    "sg:address":"1879 E Prairieview Dr",
    "sg:city":"Post Falls",
    "sg:classifiers":[
        {
            "category":"Building & Trades",
            "subcategory":"Cleaning & Sanitation",
            "type":"Services"
        }
    ],
    "sg:phone":"+1 208 777 1563",
    "sg:postcode":"83854",
    "sg:province":"ID",
    "sg:tags":[
        "maintenance"
    ],
    "wof:name":"Vickis Cleaning Service",
    "wof:placetype":"venue"
},
  "geometry": {"coordinates":[-116.919127,47.726269],"type":"Point"}
}