{
  "type": "Feature",
  "properties": {
    "iso:country":"US",
    "sg:address":"5210 Cleveland Blvd",
    "sg:city":"Caldwell",
    "sg:classifiers":[
        {
            "category":"Cinema",
            "subcategory":"Movie Rental",
            "type":"Entertainment"
        }
    ],
    "sg:phone":"+1 208 455 8777",
    "sg:postcode":"83607",
    "sg:province":"ID",
    "sg:tags":[
        "video",
        "game",
        "leasing"
    ],
    "wof:name":"Game Crazy",
    "wof:placetype":"venue"
},
  "geometry": {"coordinates":[-116.64117299999999,43.631034],"type":"Point"}
}