{
  "type": "Feature",
  "properties": {
    "iso:country":"US",
    "sg:address":"1280 S Woodruff Ave",
    "sg:city":"Idaho Falls",
    "sg:classifiers":[
        {
            "category":"Insurance",
            "subcategory":"Insurance Agent",
            "type":"Services"
        }
    ],
    "sg:phone":"+1 208 524 5129",
    "sg:postcode":"83404",
    "sg:province":"ID",
    "wof:name":"Allstate Insurance",
    "wof:placetype":"venue"
},
  "geometry": {"coordinates":[-111.999269,43.486083],"type":"Point"}
}