{
  "type": "Feature",
  "properties": {
    "iso:country":"US",
    "sg:address":"227 Melbourne Dr",
    "sg:city":"Idaho Falls",
    "sg:classifiers":[
        {
            "category":"Real Estate",
            "subcategory":"Real Estate Operator",
            "type":"Services"
        }
    ],
    "sg:phone":"+1 208 523 0987",
    "sg:postcode":"83401",
    "sg:province":"ID",
    "sg:tags":[
        "building",
        "nonresidential"
    ],
    "wof:name":"Absolute Management & Ren",
    "wof:placetype":"venue"
},
  "geometry": {"coordinates":[-111.990983,43.495758],"type":"Point"}
}