{
  "type": "Feature",
  "properties": {
    "addr:full":"702 N 4th St Coeur D Alene ID 83814",
    "addr:housenumber":"702",
    "addr:postcode":"83814",
    "addr:street":"N 4Th St Coeur D",
    "iso:country":"US",
    "sg:address":"702 N 4th St",
    "sg:city":"Coeur D Alene",
    "sg:classifiers":[
        {
            "category":"Insurance",
            "subcategory":"Insurance Agent",
            "type":"Services"
        }
    ],
    "sg:phone":"+1 208 667 7844",
    "sg:postcode":"83814",
    "sg:province":"ID",
    "wof:name":"New York Life",
    "wof:placetype":"venue"
},
  "geometry": {"coordinates":[-116.780866,47.679385],"type":"Point"}
}