{
  "type": "Feature",
  "properties": {
    "addr:full":"2715 N 15th E Idaho Falls ID 83401",
    "addr:housenumber":"2715",
    "addr:postcode":"83401",
    "addr:street":"N 15Th E",
    "iso:country":"US",
    "sg:address":"2715 N 15th E",
    "sg:city":"Idaho Falls",
    "sg:classifiers":[
        {
            "category":"Autos & Motor Vehicles",
            "subcategory":"Automobile Sales",
            "type":"Retail Goods"
        }
    ],
    "sg:phone":"+1 208 523 4187",
    "sg:postcode":"83401",
    "sg:province":"ID",
    "sg:tags":[
        "wrecker"
    ],
    "wof:name":"All Star Auto Of Idaho Inc",
    "wof:placetype":"venue"
},
  "geometry": {"coordinates":[-112.003787,43.521144],"type":"Point"}
}