{
  "type": "Feature",
  "properties": {
    "addr:full":"516 Oak St Sandpoint ID 83864",
    "addr:housenumber":"516",
    "addr:postcode":"83864",
    "addr:street":"Oak St",
    "iso:country":"US",
    "sg:address":"516 Oak St",
    "sg:city":"Sandpoint",
    "sg:classifiers":[
        {
            "category":"Shopping",
            "subcategory":"Crafts & Fabrics",
            "type":"Retail Goods"
        }
    ],
    "sg:phone":"+1 208 263 9646",
    "sg:postcode":"83864",
    "sg:province":"ID",
    "sg:tags":[
        "shop"
    ],
    "wof:name":"Adele's Sewing Ctr",
    "wof:placetype":"venue"
},
  "geometry": {"coordinates":[-116.553586,48.275137],"type":"Point"}
}