{
  "type": "Feature",
  "properties": {
    "iso:country":"US",
    "sg:address":"117 S Adams St",
    "sg:city":"Jerome",
    "sg:classifiers":[
        {
            "category":"Professional",
            "subcategory":"Lawyer & Legal Services",
            "type":"Services"
        }
    ],
    "sg:phone":"+1 208 324 2303",
    "sg:postcode":"83338",
    "sg:province":"ID",
    "sg:tags":[
        "attorney"
    ],
    "wof:name":"Fredericksen Williams Meservy",
    "wof:placetype":"venue"
},
  "geometry": {"coordinates":[-114.516768,42.723928],"type":"Point"}
}