{
  "type": "Feature",
  "properties": {
    "addr:full":"102 N 3rd St Mccall ID 83638",
    "addr:housenumber":"102",
    "addr:postcode":"83638",
    "addr:street":"N 3Rd St",
    "iso:country":"US",
    "sg:address":"102 N 3rd St",
    "sg:city":"Mccall",
    "sg:classifiers":[
        {
            "category":"Real Estate",
            "subcategory":"Real Estate Agent",
            "type":"Services"
        }
    ],
    "sg:phone":"+1 208 634 3399",
    "sg:postcode":"83638",
    "sg:province":"ID",
    "wof:name":"Holland Realty Inc",
    "wof:placetype":"venue"
},
  "geometry": {"coordinates":[-116.096597,44.897763],"type":"Point"}
}