{
  "type": "Feature",
  "properties": {
    "iso:country":"US",
    "sg:address":"3616 N Sherwood Dr",
    "sg:city":"Coeur D Alene",
    "sg:classifiers":[
        {
            "category":"Building & Trades",
            "subcategory":"Construction",
            "type":"Services"
        }
    ],
    "sg:phone":"+1 208 765 4974",
    "sg:postcode":"83815",
    "sg:province":"ID",
    "sg:tags":[
        "home",
        "builder"
    ],
    "wof:name":"Briarwood Homes",
    "wof:placetype":"venue"
},
  "geometry": {"coordinates":[-116.831577,47.710494],"type":"Point"}
}