{
  "type": "Feature",
  "properties": {
    "addr:full":"9601 Scorpio St Boise ID 83709",
    "addr:housenumber":"9601",
    "addr:postcode":"83709",
    "addr:street":"Scorpio St",
    "iso:country":"US",
    "sg:address":"9601 Scorpio St",
    "sg:city":"Boise",
    "sg:classifiers":[
        {
            "category":"Professional",
            "subcategory":"Business Services",
            "type":"Services"
        }
    ],
    "sg:phone":"+1 208 362 6115",
    "sg:postcode":"83709",
    "sg:province":"ID",
    "wof:name":"Finished Visions",
    "wof:placetype":"venue"
},
  "geometry": {"coordinates":[-116.301698,43.56535],"type":"Point"}
}