{
  "type": "Feature",
  "properties": {
    "addr:full":"5872 N Government Way Dalton Gardens ID 83815",
    "addr:housenumber":"5872",
    "addr:postcode":"83815",
    "addr:street":"N Government Way Dalton Gardens",
    "iso:country":"US",
    "sg:address":"5872 N Government Way",
    "sg:city":"Dalton Gardens",
    "sg:classifiers":[
        {
            "category":"Shopping",
            "subcategory":"Musical Instruments",
            "type":"Retail Goods"
        }
    ],
    "sg:phone":"+1 208 762 5251",
    "sg:postcode":"83815",
    "sg:province":"ID",
    "wof:name":"Avatar Speakers",
    "wof:placetype":"venue"
},
  "geometry": {"coordinates":[-116.786635,47.726147],"type":"Point"}
}