{
  "type": "Feature",
  "properties": {
    "iso:country":"US",
    "sg:address":"554 Silver Beach Dr",
    "sg:city":"Jerome",
    "sg:classifiers":[
        {
            "category":"Freight",
            "type":"Transportation"
        }
    ],
    "sg:phone":"+1 208 324 0603",
    "sg:postcode":"83338",
    "sg:province":"ID",
    "sg:tags":[
        "operator",
        "trucking"
    ],
    "wof:name":"R Jae Dispatch",
    "wof:placetype":"venue"
},
  "geometry": {"coordinates":[-114.47745,42.64375],"type":"Point"}
}