{
  "type": "Feature",
  "properties": {
    "iso:country":"US",
    "sg:address":"17060 Goose Ln",
    "sg:city":"Caldwell",
    "sg:classifiers":[
        {
            "category":"Banks & Credit Unions",
            "subcategory":"Financial Services",
            "type":"Services"
        }
    ],
    "sg:phone":"+1 208 459 6874",
    "sg:postcode":"83607",
    "sg:province":"ID",
    "sg:tags":[
        "company",
        "holding"
    ],
    "wof:name":"Delta Development LLC",
    "wof:placetype":"venue"
},
  "geometry": {"coordinates":[-116.735359,43.564595],"type":"Point"}
}