{
  "type": "Feature",
  "properties": {
    "addr:full":"1952 Addison Ave E Twin Falls ID 83301",
    "addr:housenumber":"1952",
    "addr:postcode":"83301",
    "addr:street":"Addison Ave E",
    "iso:country":"US",
    "sg:address":"1952 Addison Ave E",
    "sg:city":"Twin Falls",
    "sg:classifiers":[
        {
            "category":"Shopping",
            "subcategory":"Used Merchandise",
            "type":"Retail Goods"
        }
    ],
    "sg:phone":"+1 208 734 9500",
    "sg:postcode":"83301",
    "sg:province":"ID",
    "sg:tags":[
        "personal"
    ],
    "wof:name":"Vintage Point",
    "wof:placetype":"venue"
},
  "geometry": {"coordinates":[-114.446664,42.563096],"type":"Point"}
}