{
  "type": "Feature",
  "properties": {
    "iso:country":"US",
    "sg:address":"365 Yellowstone Ave",
    "sg:city":"Pocatello",
    "sg:classifiers":[
        {
            "category":"Professional",
            "subcategory":"Credit Reporting & Collection",
            "type":"Services"
        }
    ],
    "sg:phone":"+1 208 232 1731",
    "sg:postcode":"83201",
    "sg:province":"ID",
    "sg:tags":[
        "agency"
    ],
    "wof:name":"Action Collection Svc Inc",
    "wof:placetype":"venue"
},
  "geometry": {"coordinates":[-112.451522,42.881176],"type":"Point"}
}