{
  "type": "Feature",
  "properties": {
    "addr:full":"176 Main St Victor ID 83455",
    "addr:housenumber":"176",
    "addr:postcode":"83455",
    "addr:street":"Main St",
    "iso:country":"US",
    "sg:address":"176 Main St",
    "sg:city":"Victor",
    "sg:classifiers":[
        {
            "category":"Home & Garden",
            "subcategory":"Furniture",
            "type":"Retail Goods"
        }
    ],
    "sg:phone":"+1 208 787 4567",
    "sg:postcode":"83455",
    "sg:province":"ID",
    "sg:tags":[
        "cabinet"
    ],
    "wof:name":"Intermountain Building Prod",
    "wof:placetype":"venue"
},
  "geometry": {"coordinates":[-111.111321,43.599706],"type":"Point"}
}