{
  "type": "Feature",
  "properties": {
    "addr:full":"1440 Kimberly Rd Twin Falls ID 83301",
    "addr:housenumber":"1440",
    "addr:postcode":"83301",
    "addr:street":"Kimberly Rd",
    "iso:country":"US",
    "sg:address":"1440 Kimberly Rd",
    "sg:city":"Twin Falls",
    "sg:classifiers":[
        {
            "category":"Wholesale",
            "subcategory":"Machinery & Supplies",
            "type":"Manufacturing & Wholesale Goods"
        }
    ],
    "sg:phone":"+1 208 733 9553",
    "sg:postcode":"83301",
    "sg:province":"ID",
    "sg:tags":[
        "equipment",
        "welding"
    ],
    "wof:name":"Gem State Welders Supply",
    "wof:placetype":"venue"
},
  "geometry": {"coordinates":[-114.45494100000001,42.548581],"type":"Point"}
}