{
  "type": "Feature",
  "properties": {
    "iso:country":"US",
    "sg:address":"1239 Pole Line Rd E",
    "sg:city":"Twin Falls",
    "sg:classifiers":[
        {
            "category":"Restaurant",
            "type":"Food & Drink"
        }
    ],
    "sg:phone":"+1 208 733 9055",
    "sg:postcode":"83301",
    "sg:province":"ID",
    "wof:name":"New York Burrito",
    "wof:placetype":"venue"
},
  "geometry": {"coordinates":[-114.458365,42.592084],"type":"Point"}
}