{
  "type": "Feature",
  "properties": {
    "addr:full":"3845 W State St Boise ID 83703",
    "addr:housenumber":"3845",
    "addr:postcode":"83703",
    "addr:street":"W State St",
    "iso:country":"US",
    "sg:address":"3845 W State St",
    "sg:city":"Boise",
    "sg:classifiers":[
        {
            "category":"Banks & Credit Unions",
            "subcategory":"Bank",
            "type":"Services"
        }
    ],
    "sg:phone":"+1 208 342 2226",
    "sg:postcode":"83703",
    "sg:province":"ID",
    "sg:website":"www.dlevans.com",
    "wof:name":"D L Evans Bank",
    "wof:placetype":"venue"
},
  "geometry": {"coordinates":[-116.237387,43.641348],"type":"Point"}
}