{
  "type": "Feature",
  "properties": {
    "iso:country":"US",
    "sg:address":"418 Silcott St",
    "sg:city":"Lewiston",
    "sg:classifiers":[
        {
            "category":"Freight",
            "type":"Transportation"
        }
    ],
    "sg:phone":"+1 208 746 3051",
    "sg:postcode":"83501",
    "sg:province":"ID",
    "sg:tags":[
        "operator",
        "local",
        "trucking"
    ],
    "wof:name":"Ed Gustin Trucking",
    "wof:placetype":"venue"
},
  "geometry": {"coordinates":[-116.989088,46.416414],"type":"Point"}
}