{
  "type": "Feature",
  "properties": {
    "iso:country":"US",
    "sg:address":"31250 Hwy 200",
    "sg:city":"Sandpoint",
    "sg:classifiers":[
        {
            "category":"Retail",
            "subcategory":"Auto Repair",
            "type":"Services"
        }
    ],
    "sg:phone":"+1 208 263 8121",
    "sg:postcode":"83864",
    "sg:province":"ID",
    "sg:tags":[
        "repairing",
        "transmission",
        "general",
        "automobile"
    ],
    "wof:name":"T L C Automotive",
    "wof:placetype":"venue"
},
  "geometry": {"coordinates":[-116.533654,48.306312],"type":"Point"}
}