{
  "type": "Feature",
  "properties": {
    "addr:full":"6909 W Seltice Way Post Falls ID 83854",
    "addr:housenumber":"6909",
    "addr:postcode":"83854",
    "addr:street":"W Seltice Way",
    "iso:country":"US",
    "sg:address":"6909 W Seltice Way",
    "sg:city":"Post Falls",
    "sg:classifiers":[
        {
            "category":"Personal",
            "subcategory":"Beauty Salon",
            "type":"Services"
        }
    ],
    "sg:phone":"+1 208 773 2451",
    "sg:postcode":"83854",
    "sg:province":"ID",
    "wof:name":"Kay's Styling Salon",
    "wof:placetype":"venue"
},
  "geometry": {"coordinates":[-117.040559,47.70217],"type":"Point"}
}