{
  "type": "Feature",
  "properties": {
    "iso:country":"US",
    "sg:address":"925 E 17th St",
    "sg:city":"Idaho Falls",
    "sg:classifiers":[
        {
            "category":"Building & Trades",
            "subcategory":"Construction",
            "type":"Services"
        }
    ],
    "sg:phone":"+1 208 542 9030",
    "sg:postcode":"83404",
    "sg:province":"ID",
    "sg:tags":[
        "home",
        "improvement"
    ],
    "wof:name":"Lowe's Home Improvement-Idaho",
    "wof:placetype":"venue"
},
  "geometry": {"coordinates":[-112.015542,43.482581],"type":"Point"}
}