{
  "type": "Feature",
  "properties": {
    "addr:full":"200 W Hanley Ave Coeur D Alene ID 83815",
    "addr:housenumber":"200",
    "addr:postcode":"83815",
    "addr:street":"W Hanley Ave",
    "iso:country":"US",
    "sg:address":"200 W Hanley Ave",
    "sg:city":"Coeur D Alene",
    "sg:classifiers":[
        {
            "category":"Shopping",
            "subcategory":"Clothing, Apparel, & Fashions",
            "type":"Retail Goods"
        }
    ],
    "sg:phone":"+1 208 762 4522",
    "sg:postcode":"83815",
    "sg:province":"ID",
    "wof:name":"Christopher & Banks",
    "wof:placetype":"venue"
},
  "geometry": {"coordinates":[-116.788417,47.729844],"type":"Point"}
}