{
  "type": "Feature",
  "properties": {
    "iso:country":"US",
    "sg:address":"17455 Madison Rd",
    "sg:city":"Nampa",
    "sg:classifiers":[
        {
            "category":"Building & Trades",
            "subcategory":"Construction",
            "type":"Services"
        }
    ],
    "sg:phone":"+1 208 466 5488",
    "sg:postcode":"83687",
    "sg:province":"ID",
    "sg:tags":[
        "concrete",
        "contractor"
    ],
    "wof:name":"T S Concrete Construction Inc",
    "wof:placetype":"venue"
},
  "geometry": {"coordinates":[-116.56323999999999,43.624776],"type":"Point"}
}