{
  "type": "Feature",
  "properties": {
    "addr:full":"3134 E Mullan Ave Post Falls ID 83854",
    "addr:housenumber":"3134",
    "addr:postcode":"83854",
    "addr:street":"E Mullan Ave",
    "iso:country":"US",
    "sg:address":"3134 E Mullan Ave",
    "sg:city":"Post Falls",
    "sg:classifiers":[
        {
            "category":"Banks & Credit Unions",
            "subcategory":"Bank",
            "type":"Services"
        }
    ],
    "sg:phone":"+1 208 457 8358",
    "sg:postcode":"83854",
    "sg:province":"ID",
    "wof:name":"Washington Mutual",
    "wof:placetype":"venue"
},
  "geometry": {"coordinates":[-116.906693,47.715816],"type":"Point"}
}