{
  "type": "Feature",
  "properties": {
    "addr:full":"1399 Fillmore St Twin Falls ID 83301",
    "addr:housenumber":"1399",
    "addr:postcode":"83301",
    "addr:street":"Fillmore St",
    "iso:country":"US",
    "sg:address":"1399 Fillmore St",
    "sg:city":"Twin Falls",
    "sg:classifiers":[
        {
            "category":"Real Estate",
            "subcategory":"Architect",
            "type":"Services"
        }
    ],
    "sg:phone":"+1 208 736 8787",
    "sg:postcode":"83301",
    "sg:province":"ID",
    "wof:name":"Steven A Wilden Architect",
    "wof:placetype":"venue"
},
  "geometry": {"coordinates":[-114.464624,42.586498],"type":"Point"}
}