{
  "type": "Feature",
  "properties": {
    "addr:full":"2260 E Oakmont Dr Idaho Falls ID 83404",
    "addr:housenumber":"2260",
    "addr:postcode":"83404",
    "addr:street":"E Oakmont Dr",
    "iso:country":"US",
    "sg:address":"2260 E Oakmont Dr",
    "sg:city":"Idaho Falls",
    "sg:classifiers":[
        {
            "category":"Retail",
            "subcategory":"Portrait Studio",
            "type":"Services"
        }
    ],
    "sg:phone":"+1 208 522 6580",
    "sg:postcode":"83404",
    "sg:province":"ID",
    "sg:tags":[
        "photo"
    ],
    "wof:name":"Mountain Image Photography",
    "wof:placetype":"venue"
},
  "geometry": {"coordinates":[-111.988878,43.397576],"type":"Point"}
}