{
  "type": "Feature",
  "properties": {
    "iso:country":"US",
    "sg:address":"7584 W Mossy Cup St",
    "sg:city":"Boise",
    "sg:classifiers":[
        {
            "category":"Freight",
            "type":"Transportation"
        }
    ],
    "sg:phone":"+1 208 362 4500",
    "sg:postcode":"83709",
    "sg:province":"ID",
    "sg:tags":[
        "trucking"
    ],
    "sg:website":"www.con-way.com",
    "wof:name":"Con-Way Western Express",
    "wof:placetype":"venue"
},
  "geometry": {"coordinates":[-116.27668,43.577807],"type":"Point"}
}