{
  "type": "Feature",
  "properties": {
    "iso:country":"US",
    "sg:address":"17992 Oasis Rd",
    "sg:city":"Caldwell",
    "sg:classifiers":[
        {
            "category":"Retail",
            "subcategory":"Auto Repair",
            "type":"Services"
        }
    ],
    "sg:phone":"+1 208 454 8715",
    "sg:postcode":"83607",
    "sg:province":"ID",
    "sg:tags":[
        "body",
        "automobile",
        "painting",
        "repairing"
    ],
    "wof:name":"Brian Wallace Autobody",
    "wof:placetype":"venue"
},
  "geometry": {"coordinates":[-116.748608,43.807129],"type":"Point"}
}