{
  "type": "Feature",
  "properties": {
    "addr:full":"2220 E 25th St Idaho Falls ID 83404",
    "addr:housenumber":"2220",
    "addr:postcode":"83404",
    "addr:street":"E 25Th St",
    "iso:country":"US",
    "sg:address":"2220 E 25th St",
    "sg:city":"Idaho Falls",
    "sg:classifiers":[
        {
            "category":"Health Services",
            "subcategory":"Doctor",
            "type":"Services"
        }
    ],
    "sg:phone":"+1 208 523 1122",
    "sg:postcode":"83404",
    "sg:province":"ID",
    "sg:tags":[
        "physician",
        "surgeon"
    ],
    "wof:name":"Rocky Mountain Diabetes",
    "wof:placetype":"venue"
},
  "geometry": {"coordinates":[-111.989208,43.475953],"type":"Point"}
}