{
  "type": "Feature",
  "properties": {
    "addr:full":"6138 Emerald St Boise ID 83704",
    "addr:housenumber":"6138",
    "addr:postcode":"83704",
    "addr:street":"Emerald St",
    "iso:country":"US",
    "sg:address":"6138 Emerald St",
    "sg:city":"Boise",
    "sg:classifiers":[
        {
            "category":"Manufacturing",
            "subcategory":"Tools & Machinery",
            "type":"Manufacturing & Wholesale Goods"
        }
    ],
    "sg:phone":"+1 208 323 2802",
    "sg:postcode":"83704",
    "sg:province":"ID",
    "sg:tags":[
        "equipment",
        "electric"
    ],
    "wof:name":"Eaton Cutler-Hammer",
    "wof:placetype":"venue"
},
  "geometry": {"coordinates":[-116.25714499999999,43.611776],"type":"Point"}
}