{
  "type": "Feature",
  "properties": {
    "addr:full":"1817 N 12th St Boise ID 83702",
    "addr:housenumber":"1817",
    "addr:postcode":"83702",
    "addr:street":"N 12Th St",
    "iso:country":"US",
    "sg:address":"1817 N 12th St",
    "sg:city":"Boise",
    "sg:classifiers":[
        {
            "category":"Professional",
            "subcategory":"Management & Consulting",
            "type":"Services"
        }
    ],
    "sg:phone":"+1 208 429 5992",
    "sg:postcode":"83702",
    "sg:province":"ID",
    "sg:tags":[
        "fuel"
    ],
    "wof:name":"Intermountain Management",
    "wof:placetype":"venue"
},
  "geometry": {"coordinates":[-116.202275,43.632698],"type":"Point"}
}