{
  "type": "Feature",
  "properties": {
    "iso:country":"US",
    "sg:address":"1835 G St",
    "sg:city":"Lewiston",
    "sg:classifiers":[
        {
            "category":"Organizations",
            "subcategory":"Religious Organization",
            "type":"Services"
        }
    ],
    "sg:phone":"+1 208 746 9653",
    "sg:postcode":"83501",
    "sg:province":"ID",
    "sg:tags":[
        "place",
        "worship",
        "church"
    ],
    "sg:website":"http://www.salvationarmyusa.org",
    "wof:name":"Salvation Army",
    "wof:placetype":"venue"
},
  "geometry": {"coordinates":[-117.00588399999999,46.41565],"type":"Point"}
}