{
  "type": "Feature",
  "properties": {
    "iso:country":"US",
    "sg:address":"4288 Dye Ln",
    "sg:city":"Kuna",
    "sg:classifiers":[
        {
            "category":"Retail",
            "subcategory":"Repair Shop",
            "type":"Services"
        }
    ],
    "sg:phone":"+1 208 466 1306",
    "sg:postcode":"83634",
    "sg:province":"ID",
    "sg:tags":[
        "refrigeration"
    ],
    "wof:name":"Bb Refrigeration",
    "wof:placetype":"venue"
},
  "geometry": {"coordinates":[-116.47921700000001,43.510347],"type":"Point"}
}