{
  "type": "Feature",
  "properties": {
    "iso:country":"US",
    "sg:address":"4310 Mason St",
    "sg:city":"Idaho Falls",
    "sg:classifiers":[
        {
            "category":"Professional",
            "type":"Services"
        }
    ],
    "sg:phone":"+1 208 542 9412",
    "sg:postcode":"83406",
    "sg:province":"ID",
    "wof:name":"Digital Transcription Services",
    "wof:placetype":"venue"
},
  "geometry": {"coordinates":[-111.948452,43.473805],"type":"Point"}
}