{
  "type": "Feature",
  "properties": {
    "addr:full":"159 Silver Fox Trl Mccall ID 83638",
    "addr:housenumber":"159",
    "addr:postcode":"83638",
    "addr:street":"Silver Fox Trl",
    "iso:country":"US",
    "sg:address":"159 Silver Fox Trl",
    "sg:city":"Mccall",
    "sg:classifiers":[
        {
            "category":"Building & Trades",
            "subcategory":"Construction",
            "type":"Services"
        }
    ],
    "sg:phone":"+1 208 634 7541",
    "sg:postcode":"83638",
    "sg:province":"ID",
    "sg:tags":[
        "resurfacing",
        "floor",
        "laying",
        "refinishing",
        "contractor"
    ],
    "wof:name":"G & S Hardwood Flooring",
    "wof:placetype":"venue"
},
  "geometry": {"coordinates":[-116.01156899999999,44.828436],"type":"Point"}
}