{
  "type": "Feature",
  "properties": {
    "iso:country":"US",
    "sg:address":"23632 Upper Pleasant Ridge Rd",
    "sg:city":"Wilder",
    "sg:classifiers":[
        {
            "category":"Retail",
            "subcategory":"Auto Repair",
            "type":"Services"
        }
    ],
    "sg:phone":"+1 208 482 7465",
    "sg:postcode":"83676",
    "sg:province":"ID",
    "sg:tags":[
        "general"
    ],
    "wof:name":"Aceves Garage",
    "wof:placetype":"venue"
},
  "geometry": {"coordinates":[-116.864321,43.647163],"type":"Point"}
}