{
  "type": "Feature",
  "properties": {
    "addr:full":"1612 Annett St Boise ID 83705",
    "addr:housenumber":"1612",
    "addr:postcode":"83705",
    "addr:street":"Annett St",
    "iso:country":"US",
    "sg:address":"1612 Annett St",
    "sg:city":"Boise",
    "sg:classifiers":[
        {
            "category":"Building & Trades",
            "subcategory":"Construction",
            "type":"Services"
        }
    ],
    "sg:phone":"+1 208 343 1705",
    "sg:postcode":"83705",
    "sg:province":"ID",
    "sg:tags":[
        "layer",
        "carpet"
    ],
    "wof:name":"L & J Carpet Svc",
    "wof:placetype":"venue"
},
  "geometry": {"coordinates":[-116.203643,43.588258],"type":"Point"}
}