{
  "type": "Feature",
  "properties": {
    "iso:country":"US",
    "sg:address":"475 Yellowstone Ave",
    "sg:city":"Pocatello",
    "sg:classifiers":[
        {
            "category":"Banks & Credit Unions",
            "subcategory":"Bank",
            "type":"Services"
        }
    ],
    "sg:phone":"+1 208 237 8107",
    "sg:postcode":"83201",
    "sg:province":"ID",
    "sg:tags":[
        "loan",
        "real estate"
    ],
    "wof:name":"Advanced Mortgage Inc",
    "wof:placetype":"venue"
},
  "geometry": {"coordinates":[-112.451522,42.882811],"type":"Point"}
}