{
  "type": "Feature",
  "properties": {
    "iso:country":"US",
    "sg:address":"7800 E Mountain Oak Dr",
    "sg:city":"Nampa",
    "sg:classifiers":[
        {
            "category":"Freight",
            "type":"Transportation"
        }
    ],
    "sg:phone":"+1 208 465 5055",
    "sg:postcode":"83687",
    "sg:province":"ID",
    "sg:tags":[
        "broker",
        "trucking"
    ],
    "wof:name":"Extreme Line Logistics Inc",
    "wof:placetype":"venue"
},
  "geometry": {"coordinates":[-116.54962500000001,43.609133],"type":"Point"}
}