{
  "type": "Feature",
  "properties": {
    "iso:country":"US",
    "sg:address":"136 Mesa Vista Dr",
    "sg:city":"Boise",
    "sg:classifiers":[
        {
            "category":"Sports & Exercise",
            "subcategory":"Bowling",
            "type":"Entertainment"
        }
    ],
    "sg:phone":"+1 208 388 1777",
    "sg:postcode":"83705",
    "sg:province":"ID",
    "sg:tags":[
        "center"
    ],
    "wof:name":"Time To Spare Inc",
    "wof:placetype":"venue"
},
  "geometry": {"coordinates":[-116.207204,43.595778],"type":"Point"}
}