{
  "type": "Feature",
  "properties": {
    "iso:country":"US",
    "sg:address":"1682 Calico Cir",
    "sg:city":"Pocatello",
    "sg:classifiers":[
        {
            "category":"Professional",
            "subcategory":"Research",
            "type":"Services"
        }
    ],
    "sg:phone":"+1 208 237 2541",
    "sg:postcode":"83201",
    "sg:province":"ID",
    "sg:tags":[
        "development",
        "biotechnology"
    ],
    "wof:name":"Novapro  Inc",
    "wof:placetype":"venue"
},
  "geometry": {"coordinates":[-112.433688,42.904862],"type":"Point"}
}