{
  "type": "Feature",
  "properties": {
    "iso:country":"US",
    "sg:address":"159 S Milton Ave",
    "sg:city":"Shelley",
    "sg:classifiers":[
        {
            "category":"Retail",
            "subcategory":"Laundry & Dry Cleaning",
            "type":"Services"
        }
    ],
    "sg:phone":"+1 208 357 0500",
    "sg:postcode":"83274",
    "sg:province":"ID",
    "wof:name":"A + Carpet",
    "wof:placetype":"venue"
},
  "geometry": {"coordinates":[-112.118725,43.380604],"type":"Point"}
}