{
  "type": "Feature",
  "properties": {
    "iso:country":"US",
    "sg:address":"302 E 43rd St",
    "sg:city":"Boise",
    "sg:classifiers":[
        {
            "category":"Building & Trades",
            "subcategory":"Construction",
            "type":"Services"
        }
    ],
    "sg:phone":"+1 208 377 5151",
    "sg:postcode":"83714",
    "sg:province":"ID",
    "sg:tags":[
        "painter"
    ],
    "sg:website":"www.paintboise.com",
    "wof:name":"PAINTBOISE.COM",
    "wof:placetype":"venue"
},
  "geometry": {"coordinates":[-116.248897,43.635747],"type":"Point"}
}