{
  "type": "Feature",
  "properties": {
    "addr:full":"4718 E Horsehaven Ave Post Falls ID 83854",
    "addr:housenumber":"4718",
    "addr:postcode":"83854",
    "addr:street":"E Horsehaven Ave",
    "iso:country":"US",
    "sg:address":"4718 E Horsehaven Ave",
    "sg:city":"Post Falls",
    "sg:classifiers":[
        {
            "category":"Organizations",
            "subcategory":"Religious Organization",
            "type":"Services"
        }
    ],
    "sg:phone":"+1 208 777 1128",
    "sg:postcode":"83854",
    "sg:province":"ID",
    "sg:tags":[
        "church"
    ],
    "wof:name":"St John Bptst Orthodox Church",
    "wof:placetype":"venue"
},
  "geometry": {"coordinates":[-116.885655,47.726557],"type":"Point"}
}