{
  "type": "Feature",
  "properties": {
    "iso:country":"US",
    "sg:address":"3922 S Suntree Way",
    "sg:city":"Boise",
    "sg:classifiers":[
        {
            "category":"Manufacturing",
            "subcategory":"Lumber",
            "type":"Manufacturing & Wholesale Goods"
        }
    ],
    "sg:phone":"+1 208 343 6347",
    "sg:postcode":"83706",
    "sg:province":"ID",
    "sg:tags":[
        "forestry"
    ],
    "wof:name":"Stauber D Forestry Advisor",
    "wof:placetype":"venue"
},
  "geometry": {"coordinates":[-116.138919,43.566186],"type":"Point"}
}