{
  "type": "Feature",
  "properties": {
    "iso:country":"US",
    "sg:address":"620 Linder Ave",
    "sg:city":"Kuna",
    "sg:classifiers":[
        {
            "category":"Real Estate",
            "subcategory":"Real Estate Operator",
            "type":"Services"
        }
    ],
    "sg:phone":"+1 208 922 3553",
    "sg:postcode":"83634",
    "sg:province":"ID",
    "sg:tags":[
        "apartment"
    ],
    "wof:name":"Valley Run Apartments",
    "wof:placetype":"venue"
},
  "geometry": {"coordinates":[-116.413591,43.494107],"type":"Point"}
}