{
  "type": "Feature",
  "properties": {
    "iso:country":"US",
    "sg:address":"1974 Danbury Cir",
    "sg:city":"Idaho Falls",
    "sg:classifiers":[
        {
            "category":"Wholesale",
            "subcategory":"Groceries",
            "type":"Manufacturing & Wholesale Goods"
        }
    ],
    "sg:phone":"+1 208 529 0759",
    "sg:postcode":"83401",
    "sg:province":"ID",
    "sg:tags":[
        "food",
        "broker"
    ],
    "wof:name":"Rodon Foods",
    "wof:placetype":"venue"
},
  "geometry": {"coordinates":[-111.99579799999999,43.492131],"type":"Point"}
}