{
  "type": "Feature",
  "properties": {
    "addr:full":"610 S Lincoln Ave Jerome ID 83338",
    "addr:housenumber":"610",
    "addr:postcode":"83338",
    "addr:street":"S Lincoln Ave",
    "iso:country":"US",
    "sg:address":"610 S Lincoln Ave",
    "sg:city":"Jerome",
    "sg:classifiers":[
        {
            "category":"Professional",
            "subcategory":"Management & Consulting",
            "type":"Services"
        }
    ],
    "sg:phone":"+1 208 324 3870",
    "sg:postcode":"83338",
    "sg:province":"ID",
    "sg:tags":[
        "retail",
        "direct",
        "sales"
    ],
    "wof:name":"Aracelys Store",
    "wof:placetype":"venue"
},
  "geometry": {"coordinates":[-114.518351,42.718873],"type":"Point"}
}