{
  "type": "Feature",
  "properties": {
    "iso:country":"US",
    "sg:address":"520 W Main St",
    "sg:city":"Grangeville",
    "sg:classifiers":[
        {
            "category":"Shopping",
            "subcategory":"Used Merchandise",
            "type":"Retail Goods"
        }
    ],
    "sg:phone":"+1 208 983 1340",
    "sg:postcode":"83530",
    "sg:province":"ID",
    "sg:tags":[
        "antique",
        "stone"
    ],
    "wof:name":"Martin's Antiques",
    "wof:placetype":"venue"
},
  "geometry": {"coordinates":[-116.126643,45.926705],"type":"Point"}
}