{
  "type": "Feature",
  "properties": {
    "iso:country":"US",
    "sg:address":"1396 E State St",
    "sg:city":"Eagle",
    "sg:classifiers":[
        {
            "category":"Bars & Pubs",
            "subcategory":"Sports Bar",
            "type":"Food & Drink"
        }
    ],
    "sg:menulink":"http://www.allmenus.com/id/eagle/236569-busters-good-time-sports-bar--grill/menu/",
    "sg:phone":"+1 208 938 1800",
    "sg:postcode":"83616",
    "sg:province":"ID",
    "sg:tags":[
        "american"
    ],
    "wof:name":"Buster's Good Time Sports Bar & Grill",
    "wof:placetype":"venue"
},
  "geometry": {"coordinates":[-116.334551,43.691278],"type":"Point"}
}