{
  "type": "Feature",
  "properties": {
    "iso:country":"US",
    "sg:address":"955 S Tranquil Ln",
    "sg:city":"Eagle",
    "sg:classifiers":[
        {
            "category":"Farming",
            "subcategory":"Livestock Farm",
            "type":"Manufacturing & Wholesale Goods"
        }
    ],
    "sg:phone":"+1 208 939 2183",
    "sg:postcode":"83616",
    "sg:province":"ID",
    "sg:tags":[
        "animal",
        "general"
    ],
    "wof:name":"Go Ranches Inc",
    "wof:placetype":"venue"
},
  "geometry": {"coordinates":[-116.43345600000001,43.688253],"type":"Point"}
}