{
  "type": "Feature",
  "properties": {
    "iso:country":"US",
    "sg:address":"12 E 1st St N",
    "sg:city":"Middleton",
    "sg:classifiers":[
        {
            "category":"Organizations",
            "subcategory":"Religious Organization",
            "type":"Services"
        }
    ],
    "sg:phone":"+1 208 585 6634",
    "sg:postcode":"83644",
    "sg:province":"ID",
    "sg:tags":[
        "church"
    ],
    "wof:name":"Middleton Bible Church",
    "wof:placetype":"venue"
},
  "geometry": {"coordinates":[-116.62291,43.707314],"type":"Point"}
}