{
  "type": "Feature",
  "properties": {
    "iso:country":"US",
    "sg:address":"4205 N Boyer Ave",
    "sg:city":"Sandpoint",
    "sg:classifiers":[
        {
            "category":"Government",
            "subcategory":"Office",
            "type":"Public Place"
        }
    ],
    "sg:phone":"+1 208 263 8511",
    "sg:postcode":"83864",
    "sg:province":"ID",
    "wof:name":"Bonner County Extension Svc",
    "wof:placetype":"venue"
},
  "geometry": {"coordinates":[-116.557104,48.309538],"type":"Point"}
}