{
  "type": "Feature",
  "properties": {
    "addr:full":"1666 Ridenbaugh St Boise ID 83702",
    "addr:housenumber":"1666",
    "addr:postcode":"83702",
    "addr:street":"Ridenbaugh St",
    "iso:country":"US",
    "sg:address":"1666 Ridenbaugh St",
    "sg:city":"Boise",
    "sg:classifiers":[
        {
            "category":"Health Services",
            "subcategory":"Clinic",
            "type":"Services"
        }
    ],
    "sg:phone":"+1 208 375 7079",
    "sg:postcode":"83702",
    "sg:province":"ID",
    "sg:tags":[
        "organization",
        "medical",
        "surgical"
    ],
    "wof:name":"Ada County Paramedics",
    "wof:placetype":"venue"
},
  "geometry": {"coordinates":[-116.20926900000001,43.632074],"type":"Point"}
}