{
  "type": "Feature",
  "properties": {
    "iso:country":"US",
    "sg:address":"306 Virginia St",
    "sg:city":"New Meadows",
    "sg:classifiers":[
        {
            "category":"Personal",
            "subcategory":"Beauty Salon",
            "type":"Services"
        }
    ],
    "sg:phone":"+1 208 347 2314",
    "sg:postcode":"83654",
    "sg:province":"ID",
    "wof:name":"Strutter's Styles-Men & Women",
    "wof:placetype":"venue"
},
  "geometry": {"coordinates":[-116.283197,44.971182],"type":"Point"}
}