{
  "type": "Feature",
  "properties": {
    "iso:country":"US",
    "sg:address":"1027 Blue Lakes Blvd N",
    "sg:city":"Twin Falls",
    "sg:classifiers":[
        {
            "category":"Freight",
            "type":"Transportation"
        }
    ],
    "sg:phone":"+1 208 734 8050",
    "sg:postcode":"83301",
    "sg:province":"ID",
    "sg:tags":[
        "hauling",
        "trucking"
    ],
    "wof:name":"Transystems",
    "wof:placetype":"venue"
},
  "geometry": {"coordinates":[-114.46037800000001,42.580203],"type":"Point"}
}