{
  "type": "Feature",
  "properties": {
    "iso:country":"US",
    "sg:address":"303 Grandview Dr",
    "sg:city":"Twin Falls",
    "sg:classifiers":[
        {
            "category":"Organizations",
            "subcategory":"Religious Organization",
            "type":"Services"
        }
    ],
    "sg:phone":"+1 208 733 2886",
    "sg:postcode":"83301",
    "sg:province":"ID",
    "sg:tags":[
        "church"
    ],
    "wof:name":"Community Christian Church",
    "wof:placetype":"venue"
},
  "geometry": {"coordinates":[-114.499268,42.560872],"type":"Point"}
}