{
  "type": "Feature",
  "properties": {
    "iso:country":"US",
    "sg:address":"1535 Highland Dr",
    "sg:city":"Blackfoot",
    "sg:classifiers":[
        {
            "category":"Organizations",
            "subcategory":"Religious Organization",
            "type":"Services"
        }
    ],
    "sg:phone":"+1 208 785 5310",
    "sg:postcode":"83221",
    "sg:province":"ID",
    "sg:tags":[
        "church"
    ],
    "wof:name":"Jehovah's Witnesses",
    "wof:placetype":"venue"
},
  "geometry": {"coordinates":[-112.336315,43.201442],"type":"Point"}
}