{
  "type": "Feature",
  "properties": {
    "addr:full":"4630 W State St Boise ID 83703",
    "addr:housenumber":"4630",
    "addr:postcode":"83703",
    "addr:street":"W State St",
    "iso:country":"US",
    "sg:address":"4630 W State St",
    "sg:city":"Boise",
    "sg:classifiers":[
        {
            "category":"Banks & Credit Unions",
            "subcategory":"Bank",
            "type":"Services"
        }
    ],
    "sg:phone":"+1 208 389 4053",
    "sg:postcode":"83703",
    "sg:province":"ID",
    "sg:website":"www.wellsfargo.com",
    "wof:name":"Wells Fargo Bank",
    "wof:placetype":"venue"
},
  "geometry": {"coordinates":[-116.2482,43.649242],"type":"Point"}
}