{
  "type": "Feature",
  "properties": {
    "iso:country":"US",
    "sg:address":"2526 Harmony Ave",
    "sg:city":"Boise",
    "sg:classifiers":[
        {
            "category":"Professional",
            "subcategory":"Business Services",
            "type":"Services"
        }
    ],
    "sg:phone":"+1 208 384 1480",
    "sg:postcode":"83706",
    "sg:province":"ID",
    "sg:tags":[
        "lecture",
        "bureau",
        "seminar"
    ],
    "wof:name":"Knight Associates",
    "wof:placetype":"venue"
},
  "geometry": {"coordinates":[-116.16637,43.579896],"type":"Point"}
}