{
  "type": "Feature",
  "properties": {
    "iso:country":"US",
    "sg:address":"5165 Mohawk St",
    "sg:city":"Pocatello",
    "sg:classifiers":[
        {
            "category":"Wholesale",
            "subcategory":"Sporting Goods",
            "type":"Manufacturing & Wholesale Goods"
        }
    ],
    "sg:phone":"+1 208 233 7319",
    "sg:postcode":"83204",
    "sg:province":"ID",
    "wof:name":"Black Rock Distributing",
    "wof:placetype":"venue"
},
  "geometry": {"coordinates":[-112.413302,42.819555],"type":"Point"}
}