{
  "type": "Feature",
  "properties": {
    "iso:country":"US",
    "sg:address":"1188 S 800 E",
    "sg:city":"Preston",
    "sg:classifiers":[
        {
            "category":"Farming",
            "subcategory":"Livestock Farm",
            "type":"Manufacturing & Wholesale Goods"
        }
    ],
    "sg:phone":"+1 208 852 0285",
    "sg:postcode":"83263",
    "sg:province":"ID",
    "sg:tags":[
        "beef",
        "feedlot",
        "cattle"
    ],
    "wof:name":"T Alder",
    "wof:placetype":"venue"
},
  "geometry": {"coordinates":[-111.857087,42.074354],"type":"Point"}
}