{
  "type": "Feature",
  "properties": {
    "iso:country":"US",
    "sg:address":"1910 Amber St",
    "sg:city":"Boise",
    "sg:classifiers":[
        {
            "category":"Organizations",
            "subcategory":"Non-profit Organization",
            "type":"Services"
        }
    ],
    "sg:phone":"+1 208 376 3109",
    "sg:postcode":"83706",
    "sg:province":"ID",
    "sg:tags":[
        "social"
    ],
    "wof:name":"Idaho Bird Hunters Inc",
    "wof:placetype":"venue"
},
  "geometry": {"coordinates":[-116.250975,43.622853],"type":"Point"}
}