{
  "type": "Feature",
  "properties": {
    "addr:full":"617 N 1200 W Blackfoot ID 83221",
    "addr:housenumber":"617",
    "addr:postcode":"83221",
    "addr:street":"N 1200 W Blackfoot",
    "iso:country":"US",
    "sg:address":"617 N 1200 W",
    "sg:city":"Blackfoot",
    "sg:classifiers":[
        {
            "category":"Farming",
            "subcategory":"Livestock Farm",
            "type":"Manufacturing & Wholesale Goods"
        }
    ],
    "sg:phone":"+1 208 684 5312",
    "sg:postcode":"83221",
    "sg:province":"ID",
    "sg:tags":[
        "beef",
        "feedlot",
        "cattle"
    ],
    "wof:name":"Horse Shoe Sheep Co",
    "wof:placetype":"venue"
},
  "geometry": {"coordinates":[-112.534226,43.29009],"type":"Point"}
}