{
  "type": "Feature",
  "properties": {
    "iso:country":"US",
    "sg:address":"904 W Pullman Rd",
    "sg:city":"Moscow",
    "sg:classifiers":[
        {
            "category":"Food & Beverages",
            "subcategory":"Liquor & Beverages",
            "type":"Retail Goods"
        }
    ],
    "sg:phone":"+1 208 882 1538",
    "sg:postcode":"83843",
    "sg:province":"ID",
    "wof:name":"State Liquor Dispensary",
    "wof:placetype":"venue"
},
  "geometry": {"coordinates":[-117.012095,46.733441],"type":"Point"}
}