{
  "type": "Feature",
  "properties": {
    "iso:country":"US",
    "sg:address":"710 21st St",
    "sg:city":"Lewiston",
    "sg:classifiers":[
        {
            "category":"Building & Trades",
            "subcategory":"Construction",
            "type":"Services"
        }
    ],
    "sg:phone":"+1 208 798 1560",
    "sg:postcode":"83501",
    "sg:province":"ID",
    "sg:tags":[
        "general",
        "contractor"
    ],
    "wof:name":"Fleming Construction",
    "wof:placetype":"venue"
},
  "geometry": {"coordinates":[-117.00198399999999,46.413314],"type":"Point"}
}