{
  "type": "Feature",
  "properties": {
    "iso:country":"US",
    "sg:address":"560 Washington Ave",
    "sg:city":"Ketchum",
    "sg:classifiers":[
        {
            "category":"Shopping",
            "subcategory":"Catalog Store",
            "type":"Retail Goods"
        }
    ],
    "sg:phone":"+1 208 726 2821",
    "sg:postcode":"83340",
    "sg:province":"ID",
    "sg:tags":[
        "mail",
        "house"
    ],
    "wof:name":"JC Penney",
    "wof:placetype":"venue"
},
  "geometry": {"coordinates":[-114.366906,43.681436],"type":"Point"}
}