{
  "type": "Feature",
  "properties": {
    "iso:country":"US",
    "sg:address":"1565 Yellowstone Ave",
    "sg:city":"Pocatello",
    "sg:classifiers":[
        {
            "category":"Retail",
            "subcategory":"Portrait Studio",
            "type":"Services"
        }
    ],
    "sg:phone":"+1 208 637 1648",
    "sg:postcode":"83201",
    "sg:province":"ID",
    "sg:tags":[
        "photographer"
    ],
    "wof:name":"Daniel Photography Studio",
    "wof:placetype":"venue"
},
  "geometry": {"coordinates":[-112.45147799999999,42.904051],"type":"Point"}
}