{
  "type": "Feature",
  "properties": {
    "iso:country":"US",
    "sg:address":"309 Arizona St",
    "sg:city":"Gooding",
    "sg:classifiers":[
        {
            "category":"Personal",
            "type":"Services"
        }
    ],
    "sg:phone":"+1 208 934 4853",
    "sg:postcode":"83330",
    "sg:province":"ID",
    "wof:name":"Paoli Enterprise",
    "wof:placetype":"venue"
},
  "geometry": {"coordinates":[-114.72051500000001,42.942653],"type":"Point"}
}