{
  "type": "Feature",
  "properties": {
    "addr:full":"7495 E Nottingham Ln Nampa ID 83687",
    "addr:housenumber":"7495",
    "addr:postcode":"83687",
    "addr:street":"E Nottingham Ln",
    "iso:country":"US",
    "sg:address":"7495 E Nottingham Ln",
    "sg:city":"Nampa",
    "sg:classifiers":[
        {
            "category":"Communications",
            "subcategory":"Radio Station",
            "type":"Services"
        }
    ],
    "sg:phone":"+1 208 463 8999",
    "sg:postcode":"83687",
    "sg:province":"ID",
    "sg:tags":[
        "broadcast"
    ],
    "wof:name":"Kdbi 101 9 Fm Lagrand Spanish",
    "wof:placetype":"venue"
},
  "geometry": {"coordinates":[-116.542648,43.614815],"type":"Point"}
}