{
  "type": "Feature",
  "properties": {
    "addr:full":"618 N Orchard St Boise ID 83706",
    "addr:housenumber":"618",
    "addr:postcode":"83706",
    "addr:street":"N Orchard St",
    "iso:country":"US",
    "sg:address":"618 N Orchard St",
    "sg:city":"Boise",
    "sg:classifiers":[
        {
            "category":"Personal",
            "subcategory":"Barber",
            "type":"Services"
        }
    ],
    "sg:phone":"+1 208 338 5923",
    "sg:postcode":"83706",
    "sg:province":"ID",
    "wof:name":"Doc Scissors",
    "wof:placetype":"venue"
},
  "geometry": {"coordinates":[-116.243379,43.610541],"type":"Point"}
}