{
  "type": "Feature",
  "properties": {
    "iso:country":"US",
    "sg:address":"6426 Kootenai St",
    "sg:city":"Bonners Ferry",
    "sg:classifiers":[
        {
            "category":"Health Services",
            "subcategory":"Clinic",
            "type":"Services"
        }
    ],
    "sg:phone":"+1 208 267 1427",
    "sg:postcode":"83805",
    "sg:province":"ID",
    "sg:tags":[
        "home"
    ],
    "wof:name":"Boundary Personal Care Inc",
    "wof:placetype":"venue"
},
  "geometry": {"coordinates":[-116.313859,48.696034],"type":"Point"}
}