{
  "type": "Feature",
  "properties": {
    "iso:country":"US",
    "sg:address":"11869 W Rader Dr",
    "sg:city":"Boise",
    "sg:classifiers":[
        {
            "category":"Professional",
            "subcategory":"Computer Services",
            "type":"Services"
        }
    ],
    "sg:phone":"+1 208 378 4030",
    "sg:postcode":"83713",
    "sg:province":"ID",
    "sg:tags":[
        "related"
    ],
    "wof:name":"Kodiak Solutions",
    "wof:placetype":"venue"
},
  "geometry": {"coordinates":[-116.330417,43.650313],"type":"Point"}
}