{
  "type": "Feature",
  "properties": {
    "iso:country":"US",
    "sg:address":"1200 Roosevelt Ave",
    "sg:city":"Salmon",
    "sg:classifiers":[
        {
            "category":"Home & Garden",
            "subcategory":"Garden Supply",
            "type":"Retail Goods"
        }
    ],
    "sg:phone":"+1 208 756 2202",
    "sg:postcode":"83467",
    "sg:province":"ID",
    "sg:tags":[
        "control",
        "equipment",
        "weed"
    ],
    "wof:name":"Chemilogical Weed Management",
    "wof:placetype":"venue"
},
  "geometry": {"coordinates":[-113.91864099999999,45.182244],"type":"Point"}
}