{
  "type": "Feature",
  "properties": {
    "iso:country":"US",
    "sg:address":"276 E 300 N",
    "sg:city":"Jerome",
    "sg:classifiers":[
        {
            "category":"Building & Trades",
            "subcategory":"Electrical",
            "type":"Services"
        }
    ],
    "sg:phone":"+1 208 324 7250",
    "sg:postcode":"83338",
    "sg:province":"ID",
    "sg:tags":[
        "electric",
        "contractor"
    ],
    "wof:name":"Gregg's Electric",
    "wof:placetype":"venue"
},
  "geometry": {"coordinates":[-114.463477,42.767492],"type":"Point"}
}