{
  "type": "Feature",
  "properties": {
    "addr:full":"357 Reservoir Dr Lewiston ID 83501",
    "addr:housenumber":"357",
    "addr:postcode":"83501",
    "addr:street":"Reservoir Dr",
    "iso:country":"US",
    "sg:address":"357 Reservoir Dr",
    "sg:city":"Lewiston",
    "sg:classifiers":[
        {
            "category":"Real Estate",
            "subcategory":"Real Estate Agent",
            "type":"Services"
        }
    ],
    "sg:phone":"+1 208 798 8347",
    "sg:postcode":"83501",
    "sg:province":"ID",
    "sg:tags":[
        "appraiser"
    ],
    "wof:name":"White Appraisal Svc",
    "wof:placetype":"venue"
},
  "geometry": {"coordinates":[-117.03761900000001,46.380726],"type":"Point"}
}