{
  "type": "Feature",
  "properties": {
    "addr:full":"3527 S Federal Way Boise ID 83705",
    "addr:housenumber":"3527",
    "addr:postcode":"83705",
    "addr:street":"S Federal Way",
    "iso:country":"US",
    "sg:address":"3527 S Federal Way",
    "sg:city":"Boise",
    "sg:classifiers":[
        {
            "category":"Banks & Credit Unions",
            "subcategory":"Bank",
            "type":"Services"
        }
    ],
    "sg:phone":"+1 208 336 4051",
    "sg:postcode":"83705",
    "sg:province":"ID",
    "wof:name":"Washington Mutual",
    "wof:placetype":"venue"
},
  "geometry": {"coordinates":[-116.185779,43.569989],"type":"Point"}
}