{
  "type": "Feature",
  "properties": {
    "iso:country":"US",
    "sg:address":"3151 Dalton Ln",
    "sg:city":"Boise",
    "sg:classifiers":[
        {
            "category":"Shopping",
            "subcategory":"Books",
            "type":"Retail Goods"
        }
    ],
    "sg:phone":"+1 208 378 4079",
    "sg:postcode":"83704",
    "sg:province":"ID",
    "sg:tags":[
        "comic"
    ],
    "wof:name":"Toys In The Attic",
    "wof:placetype":"venue"
},
  "geometry": {"coordinates":[-116.29682,43.632192],"type":"Point"}
}