{
  "type": "Feature",
  "properties": {
    "addr:full":"7736 N Government Way Coeur D Alene ID 83815",
    "addr:housenumber":"7736",
    "addr:postcode":"83815",
    "addr:street":"N Government Way",
    "iso:country":"US",
    "sg:address":"7736 N Government Way",
    "sg:city":"Coeur D Alene",
    "sg:classifiers":[
        {
            "category":"Education",
            "subcategory":"Special Training",
            "type":"Public Place"
        }
    ],
    "sg:phone":"+1 208 762 7493",
    "sg:postcode":"83815",
    "sg:province":"ID",
    "wof:name":"Farrow M Music Instruction",
    "wof:placetype":"venue"
},
  "geometry": {"coordinates":[-116.786648,47.742621],"type":"Point"}
}