{
  "type": "Feature",
  "properties": {
    "addr:full":"2662 W King Rd Kuna ID 83634",
    "addr:housenumber":"2662",
    "addr:postcode":"83634",
    "addr:street":"W King Rd",
    "iso:country":"US",
    "sg:address":"2662 W King Rd",
    "sg:city":"Kuna",
    "sg:classifiers":[
        {
            "category":"Freight",
            "type":"Transportation"
        }
    ],
    "sg:phone":"+1 208 922 3351",
    "sg:postcode":"83634",
    "sg:province":"ID",
    "sg:tags":[
        "trucking"
    ],
    "wof:name":"Boehlke Trucking",
    "wof:placetype":"venue"
},
  "geometry": {"coordinates":[-116.445374,43.473824],"type":"Point"}
}