{
  "type": "Feature",
  "properties": {
    "addr:full":"259 E Center St Pocatello ID 83201",
    "addr:housenumber":"259",
    "addr:postcode":"83201",
    "addr:street":"E Center St",
    "iso:country":"US",
    "sg:address":"259 E Center St",
    "sg:city":"Pocatello",
    "sg:classifiers":[
        {
            "category":"Communications",
            "subcategory":"Radio Station",
            "type":"Services"
        }
    ],
    "sg:phone":"+1 208 233 4891",
    "sg:postcode":"83201",
    "sg:province":"ID",
    "sg:tags":[
        "company",
        "broadcasting"
    ],
    "wof:name":"KWIK",
    "wof:placetype":"venue"
},
  "geometry": {"coordinates":[-112.447002,42.86418],"type":"Point"}
}