{
  "type": "Feature",
  "properties": {
    "iso:country":"US",
    "sg:address":"9450 Ferry Rd",
    "sg:city":"Melba",
    "sg:classifiers":[
        {
            "category":"Farming",
            "subcategory":"Livestock Farm",
            "type":"Manufacturing & Wholesale Goods"
        }
    ],
    "sg:phone":"+1 208 495 2701",
    "sg:postcode":"83641",
    "sg:province":"ID",
    "sg:tags":[
        "animal",
        "general"
    ],
    "wof:name":"Stagecoach Ranch",
    "wof:placetype":"venue"
},
  "geometry": {"coordinates":[-116.579211,43.343911],"type":"Point"}
}