{
  "type": "Feature",
  "properties": {
    "addr:full":"204 S Juniper St Nampa ID 83686",
    "addr:housenumber":"204",
    "addr:postcode":"83686",
    "addr:street":"S Juniper St",
    "iso:country":"US",
    "sg:address":"204 S Juniper St",
    "sg:city":"Nampa",
    "sg:classifiers":[
        {
            "category":"Food & Beverages",
            "subcategory":"Specialty",
            "type":"Retail Goods"
        }
    ],
    "sg:phone":"+1 208 466 8808",
    "sg:postcode":"83686",
    "sg:province":"ID",
    "wof:name":"Shaklee Products",
    "wof:placetype":"venue"
},
  "geometry": {"coordinates":[-116.567126,43.567573],"type":"Point"}
}