{
  "type": "Feature",
  "properties": {
    "iso:country":"US",
    "sg:address":"135 E 23rd Dr",
    "sg:city":"Burley",
    "sg:classifiers":[
        {
            "category":"Food & Beverages",
            "subcategory":"Groceries & Convenience Stores",
            "type":"Retail Goods"
        }
    ],
    "sg:phone":"+1 208 878 4000",
    "sg:postcode":"83318",
    "sg:province":"ID",
    "sg:tags":[
        "product"
    ],
    "wof:name":"Innovative Food Development",
    "wof:placetype":"venue"
},
  "geometry": {"coordinates":[-113.792435,42.523573],"type":"Point"}
}