{
  "type": "Feature",
  "properties": {
    "iso:country":"US",
    "sg:address":"575 N Ralstin St",
    "sg:city":"Meridian",
    "sg:classifiers":[
        {
            "category":"Insurance",
            "subcategory":"Hazard Insurance",
            "type":"Services"
        }
    ],
    "sg:phone":"+1 208 288 1610",
    "sg:postcode":"83642",
    "sg:province":"ID",
    "sg:tags":[
        "employee",
        "benefit",
        "compensation",
        "plan"
    ],
    "wof:name":"Id Pipe Trade Trust Adm",
    "wof:placetype":"venue"
},
  "geometry": {"coordinates":[-116.37593699999999,43.610337],"type":"Point"}
}