{
  "type": "Feature",
  "properties": {
    "iso:country":"US",
    "sg:address":"913 River St",
    "sg:city":"Boise",
    "sg:classifiers":[
        {
            "category":"Professional",
            "subcategory":"Lawyer & Legal Services",
            "type":"Services"
        }
    ],
    "sg:phone":"+1 208 368 0800",
    "sg:postcode":"83702",
    "sg:province":"ID",
    "sg:tags":[
        "attorney"
    ],
    "wof:name":"Houst Law Office",
    "wof:placetype":"venue"
},
  "geometry": {"coordinates":[-116.21014700000001,43.61132],"type":"Point"}
}