{
  "type": "Feature",
  "properties": {
    "iso:country":"US",
    "sg:address":"615 N 3900 E",
    "sg:city":"Rigby",
    "sg:classifiers":[
        {
            "category":"Building & Trades",
            "subcategory":"Construction",
            "type":"Services"
        }
    ],
    "sg:phone":"+1 208 745 9355",
    "sg:postcode":"83442",
    "sg:province":"ID",
    "sg:tags":[
        "drywall",
        "contractor"
    ],
    "wof:name":"Quality Construction",
    "wof:placetype":"venue"
},
  "geometry": {"coordinates":[-111.923476,43.714714],"type":"Point"}
}