{
  "type": "Feature",
  "properties": {
    "addr:full":"6550 Plantation Ln Boise ID 83703",
    "addr:housenumber":"6550",
    "addr:postcode":"83703",
    "addr:street":"Plantation Ln",
    "iso:country":"US",
    "sg:address":"6550 Plantation Ln",
    "sg:city":"Boise",
    "sg:classifiers":[
        {
            "category":"Professional",
            "type":"Services"
        }
    ],
    "sg:phone":"+1 208 853 4900",
    "sg:postcode":"83703",
    "sg:province":"ID",
    "sg:tags":[
        "establishment"
    ],
    "wof:name":"D W Beary & Assoc Inc",
    "wof:placetype":"venue"
},
  "geometry": {"coordinates":[-116.27140199999999,43.658876],"type":"Point"}
}