{
  "type": "Feature",
  "properties": {
    "iso:country":"US",
    "sg:address":"901 Triangle Dr",
    "sg:city":"Sandpoint",
    "sg:classifiers":[
        {
            "category":"Education",
            "subcategory":"School",
            "type":"Public Place"
        }
    ],
    "sg:phone":"+1 208 263 2184",
    "sg:postcode":"83864",
    "sg:province":"ID",
    "sg:website":"www.sd84.k12.id.us",
    "wof:name":"Lake Pend Oreille Schl Dist 84",
    "wof:placetype":"venue"
},
  "geometry": {"coordinates":[-116.546153,48.303429],"type":"Point"}
}