{
  "type": "Feature",
  "properties": {
    "iso:country":"US",
    "sg:address":"2655 E Seltice Way",
    "sg:city":"Post Falls",
    "sg:classifiers":[
        {
            "category":"Freight",
            "type":"Transportation"
        }
    ],
    "sg:phone":"+1 208 773 7488",
    "sg:postcode":"83854",
    "sg:province":"ID",
    "sg:tags":[
        "commercial",
        "storage"
    ],
    "wof:name":"ABC Storage Ctr",
    "wof:placetype":"venue"
},
  "geometry": {"coordinates":[-116.905906,47.711078],"type":"Point"}
}