{
  "type": "Feature",
  "properties": {
    "iso:country":"US",
    "sg:address":"9225 Chinden Blvd",
    "sg:city":"Boise",
    "sg:classifiers":[
        {
            "category":"Education",
            "subcategory":"Dance Studio",
            "type":"Public Place"
        }
    ],
    "sg:phone":"+1 208 345 3225",
    "sg:postcode":"83714",
    "sg:province":"ID",
    "sg:tags":[
        "instruction",
        "dancing"
    ],
    "wof:name":"Dance Pros",
    "wof:placetype":"venue"
},
  "geometry": {"coordinates":[-116.297438,43.65538],"type":"Point"}
}