{
  "type": "Feature",
  "properties": {
    "iso:country":"US",
    "sg:address":"6058 E Cub River Rd",
    "sg:city":"Preston",
    "sg:phone":"+1 208 852 2134",
    "sg:postcode":"83263",
    "sg:province":"ID",
    "sg:tags":[
        "farm",
        "field",
        "grain",
        "cash",
        "crop"
    ],
    "wof:name":"Max Sharp",
    "wof:placetype":"venue"
},
  "geometry": {"coordinates":[-111.724718,42.105809],"type":"Point"}
}