{
  "type": "Feature",
  "properties": {
    "iso:country":"US",
    "sg:address":"7373 W Prince St",
    "sg:city":"Boise",
    "sg:classifiers":[
        {
            "category":"Building & Trades",
            "subcategory":"Construction",
            "type":"Services"
        }
    ],
    "sg:phone":"+1 208 853 1736",
    "sg:postcode":"83714",
    "sg:province":"ID",
    "sg:tags":[
        "contractor"
    ],
    "wof:name":"Mosaic Essential",
    "wof:placetype":"venue"
},
  "geometry": {"coordinates":[-116.280569,43.681335],"type":"Point"}
}