{
  "type": "Feature",
  "properties": {
    "addr:full":"84 Gerimonte Ln Old Town ID 83822",
    "addr:housenumber":"84",
    "addr:postcode":"83822",
    "addr:street":"Gerimonte Ln",
    "iso:country":"US",
    "sg:address":"84 Gerimonte Ln",
    "sg:city":"Old Town",
    "sg:classifiers":[
        {
            "category":"Retail",
            "subcategory":"Repair Shop",
            "type":"Services"
        }
    ],
    "sg:phone":"+1 208 437 4487",
    "sg:postcode":"83822",
    "sg:province":"ID",
    "sg:tags":[
        "welding"
    ],
    "wof:name":"Quality Welding Repair",
    "wof:placetype":"venue"
},
  "geometry": {"coordinates":[-117.02081800000001,48.148464],"type":"Point"}
}