{
  "type": "Feature",
  "properties": {
    "iso:country":"US",
    "sg:address":"1 W Kansas Ave",
    "sg:city":"Homedale",
    "sg:classifiers":[
        {
            "category":"Retail",
            "subcategory":"Veterinary Services",
            "type":"Services"
        }
    ],
    "sg:phone":"+1 208 337 4677",
    "sg:postcode":"83628",
    "sg:province":"ID",
    "sg:tags":[
        "hospital",
        "animal"
    ],
    "wof:name":"Owyhee Veterinary Clinic",
    "wof:placetype":"venue"
},
  "geometry": {"coordinates":[-116.932891,43.61042],"type":"Point"}
}