{
  "type": "Feature",
  "properties": {
    "iso:country":"US",
    "sg:address":"1311 6th St S",
    "sg:city":"Nampa",
    "sg:classifiers":[
        {
            "category":"Organizations",
            "subcategory":"Religious Organization",
            "type":"Services"
        }
    ],
    "sg:phone":"+1 208 466 0937",
    "sg:postcode":"83651",
    "sg:province":"ID",
    "sg:tags":[
        "church"
    ],
    "wof:name":"Church Of The Open Door",
    "wof:placetype":"venue"
},
  "geometry": {"coordinates":[-116.56357800000001,43.574166],"type":"Point"}
}