{
  "type": "Feature",
  "properties": {
    "iso:country":"US",
    "sg:address":"1420 Broadway Ave",
    "sg:city":"Boise",
    "sg:classifiers":[
        {
            "category":"Restaurant",
            "type":"Food & Drink"
        }
    ],
    "sg:menulink":"http://www.allmenus.com/id/boise-city/196132-taco-bell/menu/",
    "sg:postcode":"83706",
    "sg:province":"ID",
    "sg:tags":[
        "mexican"
    ],
    "wof:name":"Taco Bell",
    "wof:placetype":"venue"
},
  "geometry": {"coordinates":[-116.193043,43.594848],"type":"Point"}
}