{
  "type": "Feature",
  "properties": {
    "iso:country":"US",
    "sg:address":"1086 W Starling Ave",
    "sg:city":"Hayden",
    "sg:classifiers":[
        {
            "category":"Retail",
            "subcategory":"Auto Repair",
            "type":"Services"
        }
    ],
    "sg:phone":"+1 208 762 8127",
    "sg:postcode":"83835",
    "sg:province":"ID",
    "sg:tags":[
        "repairing",
        "automobile"
    ],
    "wof:name":"Home Auto Maintenance",
    "wof:placetype":"venue"
},
  "geometry": {"coordinates":[-116.802091,47.745005],"type":"Point"}
}