{
  "type": "Feature",
  "properties": {
    "iso:country":"US",
    "sg:address":"1628 Syringa St",
    "sg:city":"Pocatello",
    "sg:classifiers":[
        {
            "category":"Shopping",
            "subcategory":"Bicycles & Sporting Goods",
            "type":"Retail Goods"
        }
    ],
    "sg:phone":"+1 208 233 5030",
    "sg:postcode":"83201",
    "sg:province":"ID",
    "sg:tags":[
        "equipment",
        "golf",
        "supply"
    ],
    "wof:name":"Gordon's Golf",
    "wof:placetype":"venue"
},
  "geometry": {"coordinates":[-112.428122,42.899628],"type":"Point"}
}