{
  "type": "Feature",
  "properties": {
    "iso:country":"US",
    "sg:address":"27 Main St",
    "sg:city":"Victor",
    "sg:classifiers":[
        {
            "category":"Restaurant",
            "type":"Food & Drink"
        }
    ],
    "sg:phone":"+1 208 787 9800",
    "sg:postcode":"83455",
    "sg:province":"ID",
    "wof:name":"White Horse Cafe",
    "wof:placetype":"venue"
},
  "geometry": {"coordinates":[-111.111457,43.601642],"type":"Point"}
}