{
  "type": "Feature",
  "properties": {
    "iso:country":"US",
    "sg:address":"4508 N Old Hwy 91",
    "sg:city":"Pocatello",
    "sg:classifiers":[
        {
            "category":"Manufacturing",
            "subcategory":"Food",
            "type":"Manufacturing & Wholesale Goods"
        }
    ],
    "sg:phone":"+1 208 232 0325",
    "sg:postcode":"83204",
    "sg:province":"ID",
    "sg:tags":[
        "frozen",
        "processor"
    ],
    "wof:name":"Edwards Bros Inc",
    "wof:placetype":"venue"
},
  "geometry": {"coordinates":[-112.39023299999999,42.823877],"type":"Point"}
}