{
  "type": "Feature",
  "properties": {
    "iso:country":"US",
    "sg:address":"912 12th Ave S",
    "sg:city":"Nampa",
    "sg:classifiers":[
        {
            "category":"Shopping",
            "type":"Retail Goods"
        }
    ],
    "sg:phone":"+1 208 461 6616",
    "sg:postcode":"83651",
    "sg:province":"ID",
    "sg:tags":[
        "trophy",
        "medal",
        "award"
    ],
    "wof:name":"A J Awards Inc",
    "wof:placetype":"venue"
},
  "geometry": {"coordinates":[-116.568396,43.571962],"type":"Point"}
}