{
  "type": "Feature",
  "properties": {
    "addr:full":"13063 N Billy Ln Pocatello ID 83202",
    "addr:housenumber":"13063",
    "addr:postcode":"83202",
    "addr:street":"N Billy Ln",
    "iso:country":"US",
    "sg:address":"13063 N Billy Ln",
    "sg:city":"Pocatello",
    "sg:classifiers":[
        {
            "category":"Education",
            "subcategory":"Dance Studio",
            "type":"Public Place"
        }
    ],
    "sg:phone":"+1 208 237 8926",
    "sg:postcode":"83202",
    "sg:province":"ID",
    "sg:tags":[
        "instruction",
        "dancing"
    ],
    "wof:name":"T-N-T Dance Studio",
    "wof:placetype":"venue"
},
  "geometry": {"coordinates":[-112.45548100000001,42.950169],"type":"Point"}
}