{
  "type": "Feature",
  "properties": {
    "addr:full":"173 Millard Rd Dietrich ID 83324",
    "addr:housenumber":"173",
    "addr:postcode":"83324",
    "addr:street":"Millard Rd",
    "iso:country":"US",
    "sg:address":"173 Millard Rd",
    "sg:city":"Dietrich",
    "sg:classifiers":[
        {
            "category":"Farming",
            "subcategory":"Livestock Farm",
            "type":"Manufacturing & Wholesale Goods"
        }
    ],
    "sg:phone":"+1 208 886 2087",
    "sg:postcode":"83324",
    "sg:province":"ID",
    "sg:tags":[
        "feeding"
    ],
    "wof:name":"H & A Land & Cattle Inc",
    "wof:placetype":"venue"
},
  "geometry": {"coordinates":[-114.35423900000001,42.911566],"type":"Point"}
}