{
  "type": "Feature",
  "properties": {
    "iso:country":"US",
    "sg:address":"476841 Hwy 95",
    "sg:city":"Sandpoint",
    "sg:classifiers":[
        {
            "category":"Travel",
            "subcategory":"Hotels & Motels",
            "type":"Entertainment"
        }
    ],
    "sg:phone":"+1 208 263 2210",
    "sg:postcode":"83864",
    "sg:province":"ID",
    "wof:name":"Super 8 Motel",
    "wof:placetype":"venue"
},
  "geometry": {"coordinates":[-116.546071,48.304108],"type":"Point"}
}