{
  "type": "Feature",
  "properties": {
    "addr:full":"4024 Mountain Loop Pocatello ID 83204",
    "addr:housenumber":"4024",
    "addr:postcode":"83204",
    "addr:street":"Mountain Loop",
    "iso:country":"US",
    "sg:address":"4024 Mountain Loop",
    "sg:city":"Pocatello",
    "sg:classifiers":[
        {
            "category":"Organizations",
            "subcategory":"Non-profit Organization",
            "type":"Services"
        }
    ],
    "sg:phone":"+1 208 233 0735",
    "sg:postcode":"83204",
    "sg:province":"ID",
    "sg:tags":[
        "disability"
    ],
    "wof:name":"Crestview Care Ctr",
    "wof:placetype":"venue"
},
  "geometry": {"coordinates":[-112.427527,42.825732],"type":"Point"}
}