{
  "type": "Feature",
  "properties": {
    "iso:country":"US",
    "sg:address":"3901 Chinden Blvd",
    "sg:city":"Boise",
    "sg:classifiers":[
        {
            "category":"Retail",
            "subcategory":"Auto Repair",
            "type":"Services"
        }
    ],
    "sg:phone":"+1 208 344 7597",
    "sg:postcode":"83714",
    "sg:province":"ID",
    "sg:tags":[
        "body",
        "automobile",
        "painting"
    ],
    "wof:name":"ABC Auto Body Ctr",
    "wof:placetype":"venue"
},
  "geometry": {"coordinates":[-116.247884,43.628761],"type":"Point"}
}