{
  "type": "Feature",
  "properties": {
    "addr:full":"6117 Old Ranch Rd Pocatello ID 83204",
    "addr:housenumber":"6117",
    "addr:postcode":"83204",
    "addr:street":"Old Ranch Rd",
    "iso:country":"US",
    "sg:address":"6117 Old Ranch Rd",
    "sg:city":"Pocatello",
    "sg:classifiers":[
        {
            "category":"Building & Trades",
            "subcategory":"Construction",
            "type":"Services"
        }
    ],
    "sg:phone":"+1 208 233 3712",
    "sg:postcode":"83204",
    "sg:province":"ID",
    "sg:tags":[
        "house"
    ],
    "wof:name":"Paz Construction",
    "wof:placetype":"venue"
},
  "geometry": {"coordinates":[-112.397981,42.814596],"type":"Point"}
}