{
  "type": "Feature",
  "properties": {
    "iso:country":"US",
    "sg:address":"1407 Powers Ave",
    "sg:city":"Lewiston",
    "sg:classifiers":[
        {
            "category":"Shopping",
            "subcategory":"Bicycles & Sporting Goods",
            "type":"Retail Goods"
        }
    ],
    "sg:phone":"+1 208 746 1480",
    "sg:postcode":"83501",
    "sg:province":"ID",
    "sg:tags":[
        "gun",
        "gunsmith"
    ],
    "wof:name":"L S Arms & Ammunition",
    "wof:placetype":"venue"
},
  "geometry": {"coordinates":[-116.959501,46.369499],"type":"Point"}
}