{
  "type": "Feature",
  "properties": {
    "addr:full":"802 W Cameron Ave Kellogg ID 83837",
    "addr:housenumber":"802",
    "addr:postcode":"83837",
    "addr:street":"W Cameron Ave",
    "iso:country":"US",
    "sg:address":"802 W Cameron Ave",
    "sg:city":"Kellogg",
    "sg:classifiers":[
        {
            "category":"Food & Beverages",
            "subcategory":"Groceries & Convenience Stores",
            "type":"Retail Goods"
        }
    ],
    "sg:phone":"+1 208 783 0434",
    "sg:postcode":"83837",
    "sg:province":"ID",
    "wof:name":"Gondolier LLC",
    "wof:placetype":"venue"
},
  "geometry": {"coordinates":[-116.131832,47.546269],"type":"Point"}
}