{
  "type": "Feature",
  "properties": {
    "iso:country":"US",
    "sg:address":"212 W Ironwood Dr",
    "sg:city":"Coeur D Alene",
    "sg:classifiers":[
        {
            "category":"Building & Trades",
            "subcategory":"Construction",
            "type":"Services"
        }
    ],
    "sg:phone":"+1 208 762 2259",
    "sg:postcode":"83814",
    "sg:province":"ID",
    "sg:tags":[
        "painter"
    ],
    "wof:name":"Aros Painting",
    "wof:placetype":"venue"
},
  "geometry": {"coordinates":[-116.787782,47.694892],"type":"Point"}
}