{
  "type": "Feature",
  "properties": {
    "iso:country":"US",
    "sg:address":"697 E Dakota Ave",
    "sg:city":"Hayden Lake",
    "sg:classifiers":[
        {
            "category":"Organizations",
            "subcategory":"Religious Organization",
            "type":"Services"
        }
    ],
    "sg:phone":"+1 208 772 4267",
    "sg:postcode":"83835",
    "sg:province":"ID",
    "sg:tags":[
        "church"
    ],
    "wof:name":"Family Worship Ctr",
    "wof:placetype":"venue"
},
  "geometry": {"coordinates":[-116.777788,47.762669],"type":"Point"}
}