{
  "type": "Feature",
  "properties": {
    "iso:country":"US",
    "sg:address":"3 4th Ave",
    "sg:city":"Kooskia",
    "sg:classifiers":[
        {
            "category":"Local Transit",
            "type":"Transportation"
        }
    ],
    "sg:phone":"+1 208 926 4858",
    "sg:postcode":"83543",
    "sg:province":"ID",
    "sg:tags":[
        "ambulance"
    ],
    "wof:name":"Kooskia Ambulance",
    "wof:placetype":"venue"
},
  "geometry": {"coordinates":[-116.23746,46.235023],"type":"Point"}
}