{
  "type": "Feature",
  "properties": {
    "iso:country":"US",
    "sg:address":"97 E Palouse River Dr",
    "sg:city":"Moscow",
    "sg:classifiers":[
        {
            "category":"Retail",
            "subcategory":"Auto Repair",
            "type":"Services"
        }
    ],
    "sg:phone":"+1 208 882 4953",
    "sg:postcode":"83843",
    "sg:province":"ID",
    "sg:tags":[
        "repairing",
        "automobile"
    ],
    "wof:name":"Auto Lab",
    "wof:placetype":"venue"
},
  "geometry": {"coordinates":[-117.002656,46.715626],"type":"Point"}
}