{
  "type": "Feature",
  "properties": {
    "addr:full":"415 E Belmont St Caldwell ID 83605",
    "addr:housenumber":"415",
    "addr:postcode":"83605",
    "addr:street":"E Belmont St",
    "iso:country":"US",
    "sg:address":"415 E Belmont St",
    "sg:city":"Caldwell",
    "sg:classifiers":[
        {
            "category":"Professional",
            "subcategory":"Business Services",
            "type":"Services"
        }
    ],
    "sg:phone":"+1 208 459 7839",
    "sg:postcode":"83605",
    "sg:province":"ID",
    "sg:tags":[
        "painter",
        "sign"
    ],
    "wof:name":"Andersen Signs Inc",
    "wof:placetype":"venue"
},
  "geometry": {"coordinates":[-116.688855,43.670883],"type":"Point"}
}