{
  "type": "Feature",
  "properties": {
    "iso:country":"US",
    "sg:address":"212 1st St S",
    "sg:city":"Notus",
    "sg:classifiers":[
        {
            "category":"Building & Trades",
            "subcategory":"Construction",
            "type":"Services"
        }
    ],
    "sg:phone":"+1 208 454 2395",
    "sg:postcode":"83656",
    "sg:province":"ID",
    "sg:tags":[
        "repairing",
        "remodeling",
        "contractor"
    ],
    "wof:name":"A C Carpentry",
    "wof:placetype":"venue"
},
  "geometry": {"coordinates":[-116.801676,43.723527],"type":"Point"}
}