{
  "type": "Feature",
  "properties": {
    "iso:country":"US",
    "sg:address":"185 N Main St",
    "sg:city":"Paris",
    "sg:classifiers":[
        {
            "category":"Autos & Motor Vehicles",
            "subcategory":"Boat Sales",
            "type":"Retail Goods"
        }
    ],
    "sg:phone":"+1 208 945 7368",
    "sg:postcode":"83261",
    "sg:province":"ID",
    "sg:tags":[
        "watercraft"
    ],
    "wof:name":"Bear Lake Rental",
    "wof:placetype":"venue"
},
  "geometry": {"coordinates":[-111.401027,42.230158],"type":"Point"}
}