{
  "type": "Feature",
  "properties": {
    "addr:full":"114 N 3rd St Mccall ID 83638",
    "addr:housenumber":"114",
    "addr:postcode":"83638",
    "addr:street":"N 3Rd St",
    "iso:country":"US",
    "sg:address":"114 N 3rd St",
    "sg:city":"Mccall",
    "sg:classifiers":[
        {
            "category":"Professional",
            "type":"Services"
        }
    ],
    "sg:phone":"+1 208 634 1906",
    "sg:postcode":"83638",
    "sg:province":"ID",
    "sg:tags":[
        "establishment"
    ],
    "wof:name":"Phoenix Conveyor Belt Systems",
    "wof:placetype":"venue"
},
  "geometry": {"coordinates":[-116.09665699999999,44.897959],"type":"Point"}
}