{
  "type": "Feature",
  "properties": {
    "addr:full":"1501 Hiland Ave Burley ID 83318",
    "addr:housenumber":"1501",
    "addr:postcode":"83318",
    "addr:street":"Hiland Ave",
    "iso:country":"US",
    "sg:address":"1501 Hiland Ave",
    "sg:city":"Burley",
    "sg:classifiers":[
        {
            "category":"Social Services",
            "type":"Services"
        }
    ],
    "sg:phone":"+1 208 678 8844",
    "sg:postcode":"83318",
    "sg:province":"ID",
    "wof:name":"IHC Home Care - Burley",
    "wof:placetype":"venue"
},
  "geometry": {"coordinates":[-113.78338599999999,42.534203],"type":"Point"}
}