{
  "type": "Feature",
  "properties": {
    "addr:full":"2995 N Cole Rd Boise ID 83704",
    "addr:housenumber":"2995",
    "addr:postcode":"83704",
    "addr:street":"N Cole Rd",
    "iso:country":"US",
    "sg:address":"2995 N Cole Rd",
    "sg:city":"Boise",
    "sg:classifiers":[
        {
            "category":"Insurance",
            "subcategory":"Insurance Agent",
            "type":"Services"
        }
    ],
    "sg:phone":"+1 208 376 6448",
    "sg:postcode":"83704",
    "sg:province":"ID",
    "wof:name":"Glennon Financial Group",
    "wof:placetype":"venue"
},
  "geometry": {"coordinates":[-116.274308,43.633838],"type":"Point"}
}