{
  "type": "Feature",
  "properties": {
    "iso:country":"US",
    "sg:address":"801 E Sherman St",
    "sg:city":"Pocatello",
    "sg:classifiers":[
        {
            "category":"Government",
            "subcategory":"Office",
            "type":"Public Place"
        }
    ],
    "sg:phone":"+1 208 236 6817",
    "sg:postcode":"83201",
    "sg:province":"ID",
    "wof:name":"Senator Larry E Craig",
    "wof:placetype":"venue"
},
  "geometry": {"coordinates":[-112.447407,42.874505],"type":"Point"}
}