{
  "type": "Feature",
  "properties": {
    "iso:country":"US",
    "sg:address":"300 N Whitley Dr",
    "sg:city":"Fruitland",
    "sg:classifiers":[
        {
            "category":"Home & Garden",
            "subcategory":"Building Materials",
            "type":"Retail Goods"
        },
        {
            "category":"Retail",
            "subcategory":"Auto Repair",
            "type":"Services"
        }
    ],
    "sg:phone":"+1 208 452 4536",
    "sg:postcode":"83619",
    "sg:province":"ID",
    "sg:tags":[
        "body",
        "plate",
        "automobile",
        "glass",
        "window",
        "painting"
    ],
    "wof:name":"Jem Auto Glass",
    "wof:placetype":"venue"
},
  "geometry": {"coordinates":[-116.92366699999999,44.013279],"type":"Point"}
}