{
  "type": "Feature",
  "properties": {
    "addr:full":"9761 N Glen Hollow Ln Post Falls ID 83854",
    "addr:housenumber":"9761",
    "addr:postcode":"83854",
    "addr:street":"N Glen Hollow Ln",
    "iso:country":"US",
    "sg:address":"9761 N Glen Hollow Ln",
    "sg:city":"Post Falls",
    "sg:classifiers":[
        {
            "category":"Building & Trades",
            "subcategory":"Construction",
            "type":"Services"
        }
    ],
    "sg:phone":"+1 208 457 1075",
    "sg:postcode":"83854",
    "sg:province":"ID",
    "sg:tags":[
        "tile",
        "dealer"
    ],
    "wof:name":"RAM Interiors",
    "wof:placetype":"venue"
},
  "geometry": {"coordinates":[-117.016881,47.760568],"type":"Point"}
}