{
  "type": "Feature",
  "properties": {
    "iso:country":"US",
    "sg:address":"1115 W Ironwood Dr",
    "sg:city":"Coeur D Alene",
    "sg:classifiers":[
        {
            "category":"Social Services",
            "type":"Services"
        }
    ],
    "sg:phone":"+1 208 676 8183",
    "sg:postcode":"83814",
    "sg:province":"ID",
    "sg:tags":[
        "counseling"
    ],
    "wof:name":"Emily Maria Hart",
    "wof:placetype":"venue"
},
  "geometry": {"coordinates":[-116.80010299999999,47.69653],"type":"Point"}
}