{
  "type": "Feature",
  "properties": {
    "iso:country":"US",
    "sg:address":"1710 Dennis St",
    "sg:city":"Blackfoot",
    "sg:classifiers":[
        {
            "category":"Professional",
            "subcategory":"Art Services",
            "type":"Services"
        }
    ],
    "sg:phone":"+1 208 785 2300",
    "sg:postcode":"83221",
    "sg:province":"ID",
    "sg:tags":[
        "photographer"
    ],
    "wof:name":"Studio 41",
    "wof:placetype":"venue"
},
  "geometry": {"coordinates":[-112.359903,43.178418],"type":"Point"}
}