{
  "type": "Feature",
  "properties": {
    "iso:country":"US",
    "sg:address":"1142 S 2600 E",
    "sg:city":"Hazelton",
    "sg:classifiers":[
        {
            "category":"Farming",
            "subcategory":"Farm",
            "type":"Manufacturing & Wholesale Goods"
        }
    ],
    "sg:phone":"+1 208 829 5223",
    "sg:postcode":"83335",
    "sg:province":"ID",
    "sg:tags":[
        "crop",
        "general"
    ],
    "wof:name":"Triple N Farms",
    "wof:placetype":"venue"
},
  "geometry": {"coordinates":[-114.010277,42.556249],"type":"Point"}
}