{
  "type": "Feature",
  "properties": {
    "addr:full":"102 N Clark St Rigby ID 83442",
    "addr:housenumber":"102",
    "addr:postcode":"83442",
    "addr:street":"N Clark St",
    "iso:country":"US",
    "sg:address":"102 N Clark St",
    "sg:city":"Rigby",
    "sg:classifiers":[
        {
            "category":"Professional",
            "subcategory":"Lawyer & Legal Services",
            "type":"Services"
        }
    ],
    "sg:phone":"+1 208 745 6656",
    "sg:postcode":"83442",
    "sg:province":"ID",
    "sg:tags":[
        "attorney"
    ],
    "wof:name":"Robert L Crowley Jr",
    "wof:placetype":"venue"
},
  "geometry": {"coordinates":[-111.911849,43.672692],"type":"Point"}
}