{
  "type": "Feature",
  "properties": {
    "iso:country":"US",
    "sg:address":"1821 W Washington St",
    "sg:city":"Boise",
    "sg:classifiers":[
        {
            "category":"Shopping",
            "subcategory":"Used Merchandise",
            "type":"Retail Goods"
        }
    ],
    "sg:phone":"+1 208 344 0649",
    "sg:postcode":"83702",
    "sg:province":"ID",
    "sg:tags":[
        "shop",
        "thrift"
    ],
    "wof:name":"Good Samaritan Store",
    "wof:placetype":"venue"
},
  "geometry": {"coordinates":[-116.212639,43.625814],"type":"Point"}
}