{
  "type": "Feature",
  "properties": {
    "iso:country":"US",
    "sg:address":"2521 W Santa Clara Dr",
    "sg:city":"Meridian",
    "sg:classifiers":[
        {
            "category":"Professional",
            "subcategory":"Computer Services",
            "type":"Services"
        }
    ],
    "sg:phone":"+1 208 887 2087",
    "sg:postcode":"83642",
    "sg:province":"ID",
    "wof:name":"D G Pcs",
    "wof:placetype":"venue"
},
  "geometry": {"coordinates":[-116.424696,43.615885],"type":"Point"}
}