{
  "type": "Feature",
  "properties": {
    "iso:country":"US",
    "sg:address":"4841 Armga Dr",
    "sg:city":"Meridian",
    "sg:phone":"+1 208 376 1800",
    "sg:postcode":"83642",
    "sg:province":"ID",
    "sg:tags":[
        "farm",
        "field",
        "grain",
        "cash",
        "crop"
    ],
    "wof:name":"Tom Salove",
    "wof:placetype":"venue"
},
  "geometry": {"coordinates":[-116.335134,43.589367],"type":"Point"}
}