{
  "type": "Feature",
  "properties": {
    "iso:country":"US",
    "sg:address":"1190 E Lincoln Rd",
    "sg:city":"Idaho Falls",
    "sg:classifiers":[
        {
            "category":"Communications",
            "subcategory":"Radio Station",
            "type":"Services"
        }
    ],
    "sg:phone":"+1 208 523 9943",
    "sg:postcode":"83401",
    "sg:province":"ID",
    "sg:tags":[
        "company",
        "broadcasting"
    ],
    "wof:name":"KADQ",
    "wof:placetype":"venue"
},
  "geometry": {"coordinates":[-112.00746700000001,43.511183],"type":"Point"}
}