{
  "type": "Feature",
  "properties": {
    "addr:full":"1250 Ashment Ave Idaho Falls ID 83404",
    "addr:housenumber":"1250",
    "addr:postcode":"83404",
    "addr:street":"Ashment Ave",
    "iso:country":"US",
    "sg:address":"1250 Ashment Ave",
    "sg:city":"Idaho Falls",
    "sg:classifiers":[
        {
            "category":"Real Estate",
            "subcategory":"Real Estate Operator",
            "type":"Services"
        }
    ],
    "sg:phone":"+1 208 522 6500",
    "sg:postcode":"83404",
    "sg:province":"ID",
    "sg:tags":[
        "building",
        "apartment"
    ],
    "wof:name":"Sandcreek Apartments",
    "wof:placetype":"venue"
},
  "geometry": {"coordinates":[-111.98988300000001,43.487458],"type":"Point"}
}