{
  "type": "Feature",
  "properties": {
    "iso:country":"US",
    "sg:address":"5956 N Stafford Rd",
    "sg:city":"Coeur D Alene",
    "sg:classifiers":[
        {
            "category":"Shopping",
            "subcategory":"Used Merchandise",
            "type":"Retail Goods"
        }
    ],
    "sg:phone":"+1 208 664 4335",
    "sg:postcode":"83815",
    "sg:province":"ID",
    "wof:name":"Winter Swap",
    "wof:placetype":"venue"
},
  "geometry": {"coordinates":[-116.80976,47.725257],"type":"Point"}
}