{
  "type": "Feature",
  "properties": {
    "addr:full":"2235 Thain Grade Lewiston ID 83501",
    "addr:housenumber":"2235",
    "addr:postcode":"83501",
    "addr:street":"Thain Grade",
    "iso:country":"US",
    "sg:address":"2235 Thain Grade",
    "sg:city":"Lewiston",
    "sg:classifiers":[
        {
            "category":"Restaurant",
            "type":"Food & Drink"
        }
    ],
    "sg:menulink":"http://www.allmenus.com/id/lewiston/85211-applebees/menu/",
    "sg:phone":"+1 208 746 8000",
    "sg:postcode":"83501",
    "sg:province":"ID",
    "sg:tags":[
        "burger",
        "american",
        "sandwich",
        "soup"
    ],
    "wof:name":"Applebee's",
    "wof:placetype":"venue"
},
  "geometry": {"coordinates":[-116.998768,46.397592],"type":"Point"}
}