{
  "type": "Feature",
  "properties": {
    "iso:country":"US",
    "sg:address":"1255 S Yellowstone Hwy",
    "sg:city":"St Anthony",
    "sg:classifiers":[
        {
            "category":"Wholesale",
            "subcategory":"Machinery & Supplies",
            "type":"Manufacturing & Wholesale Goods"
        }
    ],
    "sg:phone":"+1 208 624 1099",
    "sg:postcode":"83445",
    "sg:province":"ID",
    "sg:tags":[
        "tractor"
    ],
    "wof:name":"T & S Equipment",
    "wof:placetype":"venue"
},
  "geometry": {"coordinates":[-111.687448,43.954284],"type":"Point"}
}