{
  "type": "Feature",
  "properties": {
    "iso:country":"US",
    "sg:address":"2775 N Howard St",
    "sg:city":"Coeur D Alene",
    "sg:classifiers":[
        {
            "category":"Professional",
            "subcategory":"Accounting & Tax Preparation",
            "type":"Services"
        }
    ],
    "sg:phone":"+1 208 664 2411",
    "sg:postcode":"83815",
    "sg:province":"ID",
    "sg:tags":[
        "bookkeeping",
        "general"
    ],
    "sg:website":"www.niyfc.com",
    "wof:name":"Micro Ledger",
    "wof:placetype":"venue"
},
  "geometry": {"coordinates":[-116.797179,47.701135],"type":"Point"}
}