{
  "type": "Feature",
  "properties": {
    "iso:country":"US",
    "sg:address":"443 N Hwy 33",
    "sg:city":"Tetonia",
    "sg:classifiers":[
        {
            "category":"Government",
            "subcategory":"Office",
            "type":"Public Place"
        }
    ],
    "sg:phone":"+1 208 456 2944",
    "sg:postcode":"83452",
    "sg:province":"ID",
    "sg:tags":[
        "federal"
    ],
    "wof:name":"US Consolidated Farm Svc Agcy",
    "wof:placetype":"venue"
},
  "geometry": {"coordinates":[-111.110826,43.784861],"type":"Point"}
}