{
  "type": "Feature",
  "properties": {
    "addr:full":"925 Franklin Blvd Nampa ID 83687",
    "addr:housenumber":"925",
    "addr:postcode":"83687",
    "addr:street":"Franklin Blvd",
    "iso:country":"US",
    "sg:address":"925 Franklin Blvd",
    "sg:city":"Nampa",
    "sg:classifiers":[
        {
            "category":"Wholesale",
            "subcategory":"Hardware",
            "type":"Manufacturing & Wholesale Goods"
        }
    ],
    "sg:phone":"+1 208 465 0400",
    "sg:postcode":"83687",
    "sg:province":"ID",
    "sg:tags":[
        "plumbing",
        "fixture",
        "supply"
    ],
    "wof:name":"Ferguson Enterprises Inc",
    "wof:placetype":"venue"
},
  "geometry": {"coordinates":[-116.553065,43.591574],"type":"Point"}
}