{
  "type": "Feature",
  "properties": {
    "addr:full":"1515 E Chicago St Caldwell ID 83605",
    "addr:housenumber":"1515",
    "addr:postcode":"83605",
    "addr:street":"E Chicago St",
    "iso:country":"US",
    "sg:address":"1515 E Chicago St",
    "sg:city":"Caldwell",
    "sg:classifiers":[
        {
            "category":"Freight",
            "type":"Transportation"
        }
    ],
    "sg:phone":"+1 208 454 3506",
    "sg:postcode":"83605",
    "sg:province":"ID",
    "sg:tags":[
        "hauling",
        "trucking"
    ],
    "wof:name":"Edward R Feller Trucking",
    "wof:placetype":"venue"
},
  "geometry": {"coordinates":[-116.67643700000001,43.663731],"type":"Point"}
}