{
  "type": "Feature",
  "properties": {
    "addr:full":"1259 Bear Creek Rd Princeton ID 83857",
    "addr:housenumber":"1259",
    "addr:postcode":"83857",
    "addr:street":"Bear Creek Rd",
    "iso:country":"US",
    "sg:address":"1259 Bear Creek Rd",
    "sg:city":"Princeton",
    "sg:classifiers":[
        {
            "category":"Building & Trades",
            "subcategory":"Construction",
            "type":"Services"
        }
    ],
    "sg:phone":"+1 208 875 8736",
    "sg:postcode":"83857",
    "sg:province":"ID",
    "sg:tags":[
        "floor",
        "laying",
        "contractor"
    ],
    "wof:name":"Palouse River Tile Etc",
    "wof:placetype":"venue"
},
  "geometry": {"coordinates":[-116.78546900000001,46.883871],"type":"Point"}
}