{
  "type": "Feature",
  "properties": {
    "addr:full":"265 N 3rd E Mountain Home ID 83647",
    "addr:housenumber":"265",
    "addr:postcode":"83647",
    "addr:street":"N 3Rd E",
    "iso:country":"US",
    "sg:address":"265 N 3rd E",
    "sg:city":"Mountain Home",
    "sg:classifiers":[
        {
            "category":"Shopping",
            "subcategory":"Gifts & Souvenirs",
            "type":"Retail Goods"
        }
    ],
    "sg:phone":"+1 208 587 5971",
    "sg:postcode":"83647",
    "sg:province":"ID",
    "sg:tags":[
        "shop"
    ],
    "sg:website":"www.heddasgifts.com",
    "wof:name":"Hedda's Gifts",
    "wof:placetype":"venue"
},
  "geometry": {"coordinates":[-115.693168,43.132662],"type":"Point"}
}