{
  "type": "Feature",
  "properties": {
    "iso:country":"US",
    "sg:address":"403 N Main St",
    "sg:city":"Cascade",
    "sg:classifiers":[
        {
            "category":"Travel",
            "subcategory":"Hotels & Motels",
            "type":"Entertainment"
        }
    ],
    "sg:phone":"+1 208 382 4370",
    "sg:postcode":"83611",
    "sg:province":"ID",
    "sg:tags":[
        "operation"
    ],
    "wof:name":"Bears Knight Inn & Gift Shop",
    "wof:placetype":"venue"
},
  "geometry": {"coordinates":[-116.044506,44.518679],"type":"Point"}
}