{
  "type": "Feature",
  "properties": {
    "addr:full":"4148 N Westview Way Boise ID 83704",
    "addr:housenumber":"4148",
    "addr:postcode":"83704",
    "addr:street":"N Westview Way",
    "iso:country":"US",
    "sg:address":"4148 N Westview Way",
    "sg:city":"Boise",
    "sg:classifiers":[
        {
            "category":"Professional",
            "subcategory":"Computer Services",
            "type":"Services"
        }
    ],
    "sg:phone":"+1 208 860 0719",
    "sg:postcode":"83704",
    "sg:province":"ID",
    "sg:tags":[
        "programming"
    ],
    "wof:name":"Catalyst Web Applications",
    "wof:placetype":"venue"
},
  "geometry": {"coordinates":[-116.30668799999999,43.642683],"type":"Point"}
}