{
  "type": "Feature",
  "properties": {
    "addr:full":"909 E Hwy 2 Oldtown ID 83822",
    "addr:housenumber":"909",
    "addr:postcode":"83822",
    "addr:street":"E Hwy 2",
    "iso:country":"US",
    "sg:address":"909 E Hwy 2",
    "sg:city":"Oldtown",
    "sg:classifiers":[
        {
            "category":"Retail",
            "subcategory":"Veterinary Services",
            "type":"Services"
        }
    ],
    "sg:phone":"+1 208 437 2145",
    "sg:postcode":"83822",
    "sg:province":"ID",
    "sg:tags":[
        "veterinarian"
    ],
    "wof:name":"Pend Oreille Veterinary Clinic",
    "wof:placetype":"venue"
},
  "geometry": {"coordinates":[-117.021778,48.186113],"type":"Point"}
}