{
  "type": "Feature",
  "properties": {
    "iso:country":"US",
    "sg:address":"3221 Garrity Blvd",
    "sg:city":"Nampa",
    "sg:classifiers":[
        {
            "category":"Retail",
            "subcategory":"Repair Shop",
            "type":"Services"
        }
    ],
    "sg:phone":"+1 208 467 6977",
    "sg:postcode":"83687",
    "sg:province":"ID",
    "sg:tags":[
        "upholsterer"
    ],
    "wof:name":"Fenster Upholstery",
    "wof:placetype":"venue"
},
  "geometry": {"coordinates":[-116.52765,43.589586],"type":"Point"}
}