{
  "type": "Feature",
  "properties": {
    "iso:country":"US",
    "sg:address":"601 E 44th St",
    "sg:city":"Boise",
    "sg:classifiers":[
        {
            "category":"Home & Garden",
            "subcategory":"Furniture",
            "type":"Retail Goods"
        }
    ],
    "sg:phone":"+1 208 375 9350",
    "sg:postcode":"83714",
    "sg:province":"ID",
    "sg:tags":[
        "builder",
        "custom"
    ],
    "wof:name":"Out Of The Woods",
    "wof:placetype":"venue"
},
  "geometry": {"coordinates":[-116.248018,43.638358],"type":"Point"}
}