{
  "type": "Feature",
  "properties": {
    "addr:full":"1623 River St Boise ID 83702",
    "addr:housenumber":"1623",
    "addr:postcode":"83702",
    "addr:street":"River St",
    "iso:country":"US",
    "sg:address":"1623 River St",
    "sg:city":"Boise",
    "sg:classifiers":[
        {
            "category":"Wholesale",
            "subcategory":"Plants",
            "type":"Manufacturing & Wholesale Goods"
        }
    ],
    "sg:phone":"+1 208 336 5275",
    "sg:postcode":"83702",
    "sg:province":"ID",
    "sg:tags":[
        "florist"
    ],
    "wof:name":"DWF Wholesale Florists",
    "wof:placetype":"venue"
},
  "geometry": {"coordinates":[-116.21704,43.618244],"type":"Point"}
}