{
  "type": "Feature",
  "properties": {
    "iso:country":"US",
    "sg:address":"13177 W Persimmon Ln",
    "sg:city":"Boise",
    "sg:classifiers":[
        {
            "category":"Social Services",
            "type":"Services"
        }
    ],
    "sg:phone":"+1 208 939 5553",
    "sg:postcode":"83713",
    "sg:province":"ID",
    "sg:tags":[
        "counseling"
    ],
    "wof:name":"Kristi Shohet Lpc",
    "wof:placetype":"venue"
},
  "geometry": {"coordinates":[-116.345714,43.64777],"type":"Point"}
}