{
  "type": "Feature",
  "properties": {
    "iso:country":"US",
    "sg:address":"303 E 5th St",
    "sg:city":"Moscow",
    "sg:classifiers":[
        {
            "category":"Building & Trades",
            "subcategory":"Construction",
            "type":"Services"
        }
    ],
    "sg:phone":"+1 208 883 1585",
    "sg:postcode":"83843",
    "sg:province":"ID",
    "sg:tags":[
        "roofing",
        "contractor"
    ],
    "wof:name":"Glen Barnett Roofing & Gutters",
    "wof:placetype":"venue"
},
  "geometry": {"coordinates":[-116.998589,46.730983],"type":"Point"}
}