{
  "type": "Feature",
  "properties": {
    "iso:country":"US",
    "sg:address":"1908 N 13th St",
    "sg:city":"Boise",
    "sg:classifiers":[
        {
            "category":"Health Services",
            "subcategory":"Nursing And Care Facility",
            "type":"Services"
        }
    ],
    "sg:phone":"+1 208 424 8107",
    "sg:postcode":"83702",
    "sg:province":"ID",
    "sg:tags":[
        "home",
        "retirement",
        "community"
    ],
    "wof:name":"Ashley Manor",
    "wof:placetype":"venue"
},
  "geometry": {"coordinates":[-116.203261,43.633653],"type":"Point"}
}