{
  "type": "Feature",
  "properties": {
    "addr:full":"5713 Cleveland Blvd Caldwell ID 83607",
    "addr:housenumber":"5713",
    "addr:postcode":"83607",
    "addr:street":"Cleveland Blvd",
    "iso:country":"US",
    "sg:address":"5713 Cleveland Blvd",
    "sg:city":"Caldwell",
    "sg:classifiers":[
        {
            "category":"Autos & Motor Vehicles",
            "subcategory":"Automobile Sales",
            "type":"Retail Goods"
        }
    ],
    "sg:phone":"+1 208 455 0480",
    "sg:postcode":"83607",
    "sg:province":"ID",
    "sg:tags":[
        "body",
        "repair",
        "sales",
        "automotive"
    ],
    "wof:name":"D & C Auto Sales",
    "wof:placetype":"venue"
},
  "geometry": {"coordinates":[-116.634379,43.626975],"type":"Point"}
}