{
  "type": "Feature",
  "properties": {
    "iso:country":"US",
    "sg:address":"161 5th Ave S",
    "sg:city":"Twin Falls",
    "sg:classifiers":[
        {
            "category":"Professional",
            "subcategory":"Accounting & Tax Preparation",
            "type":"Services"
        }
    ],
    "sg:phone":"+1 208 734 8932",
    "sg:postcode":"83301",
    "sg:province":"ID",
    "sg:tags":[
        "accountant"
    ],
    "wof:name":"Deagle Ames & Co",
    "wof:placetype":"venue"
},
  "geometry": {"coordinates":[-114.473102,42.552589],"type":"Point"}
}