{
  "type": "Feature",
  "properties": {
    "iso:country":"US",
    "sg:address":"1904 E Chicago St",
    "sg:city":"Caldwell",
    "sg:classifiers":[
        {
            "category":"Wholesale",
            "subcategory":"Farm Supplies",
            "type":"Manufacturing & Wholesale Goods"
        }
    ],
    "sg:phone":"+1 208 459 3657",
    "sg:postcode":"83605",
    "sg:province":"ID",
    "wof:name":"Outdoor Tactics Fence & Pond",
    "wof:placetype":"venue"
},
  "geometry": {"coordinates":[-116.672912,43.661011],"type":"Point"}
}