{
  "type": "Feature",
  "properties": {
    "addr:full":"270 S Sophie Pl Eagle ID 83616",
    "addr:housenumber":"270",
    "addr:postcode":"83616",
    "addr:street":"S Sophie Pl",
    "iso:country":"US",
    "sg:address":"270 S Sophie Pl",
    "sg:city":"Eagle",
    "sg:classifiers":[
        {
            "category":"Autos & Motor Vehicles",
            "subcategory":"Auto Supplies",
            "type":"Retail Goods"
        }
    ],
    "sg:phone":"+1 208 939 2975",
    "sg:postcode":"83616",
    "sg:province":"ID",
    "sg:tags":[
        "automobile",
        "stereo",
        "radio"
    ],
    "wof:name":"Sounds Alive",
    "wof:placetype":"venue"
},
  "geometry": {"coordinates":[-116.36078500000001,43.693082],"type":"Point"}
}