{
  "type": "Feature",
  "properties": {
    "iso:country":"US",
    "sg:address":"120 Fairway Dr",
    "sg:city":"Pocatello",
    "sg:classifiers":[
        {
            "category":"Organizations",
            "subcategory":"Religious Organization",
            "type":"Services"
        }
    ],
    "sg:phone":"+1 208 237 1364",
    "sg:postcode":"83201",
    "sg:province":"ID",
    "sg:tags":[
        "church"
    ],
    "sg:website":"www.lds.org",
    "wof:name":"Church Of Jesus Christ Of Lds",
    "wof:placetype":"venue"
},
  "geometry": {"coordinates":[-112.423137,42.909603],"type":"Point"}
}