{
  "type": "Feature",
  "properties": {
    "addr:full":"560 Jensen Grove Dr Blackfoot ID 83221",
    "addr:housenumber":"560",
    "addr:postcode":"83221",
    "addr:street":"Jensen Grove Dr",
    "iso:country":"US",
    "sg:address":"560 Jensen Grove Dr",
    "sg:city":"Blackfoot",
    "sg:classifiers":[
        {
            "category":"Wholesale",
            "subcategory":"Electrical",
            "type":"Manufacturing & Wholesale Goods"
        }
    ],
    "sg:phone":"+1 208 785 7244",
    "sg:postcode":"83221",
    "sg:province":"ID",
    "sg:tags":[
        "equipment",
        "electric",
        "supply"
    ],
    "wof:name":"Electrical Wholesale Co",
    "wof:placetype":"venue"
},
  "geometry": {"coordinates":[-112.35747600000001,43.199489],"type":"Point"}
}