{
  "type": "Feature",
  "properties": {
    "iso:country":"US",
    "sg:address":"300 Willow Dr",
    "sg:city":"Blackfoot",
    "sg:classifiers":[
        {
            "category":"Personal",
            "subcategory":"Beauty Salon",
            "type":"Services"
        }
    ],
    "sg:phone":"+1 208 785 4301",
    "sg:postcode":"83221",
    "sg:province":"ID",
    "sg:tags":[
        "shop"
    ],
    "wof:name":"Blackfoot Electrolysis",
    "wof:placetype":"venue"
},
  "geometry": {"coordinates":[-112.327287,43.196833],"type":"Point"}
}