{
  "type": "Feature",
  "properties": {
    "iso:country":"US",
    "sg:address":"11427 W Hickory Hill Ct",
    "sg:city":"Boise",
    "sg:classifiers":[
        {
            "category":"Professional",
            "subcategory":"Lawyer & Legal Services",
            "type":"Services"
        }
    ],
    "sg:phone":"+1 208 323 0024",
    "sg:postcode":"83713",
    "sg:province":"ID",
    "sg:tags":[
        "attorney"
    ],
    "wof:name":"Storer Injury Lawyers",
    "wof:placetype":"venue"
},
  "geometry": {"coordinates":[-116.32350599999999,43.652492],"type":"Point"}
}