{
  "type": "Feature",
  "properties": {
    "iso:country":"US",
    "sg:address":"236 N 200 W",
    "sg:city":"Jerome",
    "sg:classifiers":[
        {
            "category":"Sports & Exercise",
            "subcategory":"Bowling",
            "type":"Entertainment"
        }
    ],
    "sg:phone":"+1 208 324 2801",
    "sg:postcode":"83338",
    "sg:province":"ID",
    "sg:tags":[
        "center"
    ],
    "wof:name":"Jerome Bowling Alley",
    "wof:placetype":"venue"
},
  "geometry": {"coordinates":[-114.557767,42.759785],"type":"Point"}
}