{
  "type": "Feature",
  "properties": {
    "addr:full":"401 Filer Ave Twin Falls ID 83301",
    "addr:housenumber":"401",
    "addr:postcode":"83301",
    "addr:street":"Filer Ave",
    "iso:country":"US",
    "sg:address":"401 Filer Ave",
    "sg:city":"Twin Falls",
    "sg:classifiers":[
        {
            "category":"Personal",
            "subcategory":"Shoe Repair & Shine",
            "type":"Services"
        }
    ],
    "sg:phone":"+1 208 734 8429",
    "sg:postcode":"83301",
    "sg:province":"ID",
    "sg:tags":[
        "parlor"
    ],
    "wof:name":"Valley Shoe Repair",
    "wof:placetype":"venue"
},
  "geometry": {"coordinates":[-114.472573,42.570487],"type":"Point"}
}