{
  "type": "Feature",
  "properties": {
    "iso:country":"US",
    "sg:address":"3187 Whitman Dr",
    "sg:city":"Boise",
    "sg:classifiers":[
        {
            "category":"Travel",
            "subcategory":"Travel Agent",
            "type":"Entertainment"
        }
    ],
    "sg:phone":"+1 208 343 5897",
    "sg:postcode":"83716",
    "sg:province":"ID",
    "sg:tags":[
        "operator",
        "tour"
    ],
    "wof:name":"Training Unlimited Tours LLC",
    "wof:placetype":"venue"
},
  "geometry": {"coordinates":[-116.143438,43.554883],"type":"Point"}
}