{
  "type": "Feature",
  "properties": {
    "iso:country":"US",
    "sg:address":"403 E Fairview Ave",
    "sg:city":"Meridian",
    "sg:classifiers":[
        {
            "category":"Real Estate",
            "subcategory":"Developer",
            "type":"Services"
        }
    ],
    "sg:phone":"+1 208 888 6668",
    "sg:postcode":"83642",
    "sg:province":"ID",
    "sg:tags":[
        "mobile",
        "home"
    ],
    "wof:name":"Elm Grove Mobile Home Park",
    "wof:placetype":"venue"
},
  "geometry": {"coordinates":[-116.388959,43.619303],"type":"Point"}
}