{
  "type": "Feature",
  "properties": {
    "addr:full":"112 N Latah St Boise ID 83706",
    "addr:housenumber":"112",
    "addr:postcode":"83706",
    "addr:street":"N Latah St",
    "iso:country":"US",
    "sg:address":"112 N Latah St",
    "sg:city":"Boise",
    "sg:classifiers":[
        {
            "category":"Personal",
            "subcategory":"Beauty Salon",
            "type":"Services"
        }
    ],
    "sg:phone":"+1 208 344 0824",
    "sg:postcode":"83706",
    "sg:province":"ID",
    "wof:name":"Hair Designers",
    "wof:placetype":"venue"
},
  "geometry": {"coordinates":[-116.228435,43.607927],"type":"Point"}
}