{
  "type": "Feature",
  "properties": {
    "iso:country":"US",
    "sg:address":"611 Wilson Ave",
    "sg:city":"Pocatello",
    "sg:classifiers":[
        {
            "category":"Government",
            "subcategory":"Office",
            "type":"Public Place"
        }
    ],
    "sg:phone":"+1 208 236 6244",
    "sg:postcode":"83201",
    "sg:province":"ID",
    "sg:tags":[
        "state",
        "taxation"
    ],
    "sg:website":"www.idaho.gov",
    "wof:name":"Tax Commission",
    "wof:placetype":"venue"
},
  "geometry": {"coordinates":[-112.45225499999999,42.887597],"type":"Point"}
}