{
  "type": "Feature",
  "properties": {
    "iso:country":"US",
    "sg:address":"9148 Donnybrook Ct",
    "sg:city":"Boise",
    "sg:classifiers":[
        {
            "category":"Professional",
            "subcategory":"Computer Services",
            "type":"Services"
        }
    ],
    "sg:phone":"+1 208 658 1514",
    "sg:postcode":"83709",
    "sg:province":"ID",
    "sg:tags":[
        "related"
    ],
    "wof:name":"Midtech Consulting Services",
    "wof:placetype":"venue"
},
  "geometry": {"coordinates":[-116.294726,43.601801],"type":"Point"}
}