{
  "type": "Feature",
  "properties": {
    "iso:country":"US",
    "sg:address":"9245 N Government Way",
    "sg:city":"Hayden",
    "sg:classifiers":[
        {
            "category":"Home & Garden",
            "subcategory":"Home Furnishings",
            "type":"Retail Goods"
        }
    ],
    "sg:phone":"+1 208 209 0236",
    "sg:postcode":"83835",
    "sg:province":"ID",
    "sg:tags":[
        "lighting",
        "fixture"
    ],
    "wof:name":"Eclipse Lighting",
    "wof:placetype":"venue"
},
  "geometry": {"coordinates":[-116.78667299999999,47.756403],"type":"Point"}
}