{
  "type": "Feature",
  "properties": {
    "iso:country":"US",
    "sg:address":"651 S 45th W",
    "sg:city":"Idaho Falls",
    "sg:classifiers":[
        {
            "category":"Personal",
            "type":"Services"
        }
    ],
    "sg:phone":"+1 208 529 9656",
    "sg:postcode":"83402",
    "sg:province":"ID",
    "wof:name":"Costume Shop",
    "wof:placetype":"venue"
},
  "geometry": {"coordinates":[-112.12281,43.493873],"type":"Point"}
}