{
  "type": "Feature",
  "properties": {
    "iso:country":"US",
    "sg:address":"4215 N 2300 E",
    "sg:city":"Filer",
    "sg:classifiers":[
        {
            "category":"Building & Trades",
            "subcategory":"Construction",
            "type":"Services"
        }
    ],
    "sg:phone":"+1 208 326 7293",
    "sg:postcode":"83328",
    "sg:province":"ID",
    "sg:tags":[
        "house",
        "membership"
    ],
    "wof:name":"Foundation Builders Intl",
    "wof:placetype":"venue"
},
  "geometry": {"coordinates":[-114.594945,42.614419],"type":"Point"}
}