{
  "type": "Feature",
  "properties": {
    "iso:country":"US",
    "sg:address":"1213 21st St",
    "sg:city":"Lewiston",
    "sg:classifiers":[
        {
            "category":"Health Services",
            "subcategory":"Clinic",
            "type":"Services"
        }
    ],
    "sg:phone":"+1 208 717 0625",
    "sg:postcode":"83501",
    "sg:province":"ID",
    "wof:name":"Inland Northwest Blood Ctr",
    "wof:placetype":"venue"
},
  "geometry": {"coordinates":[-117.001885,46.408182],"type":"Point"}
}