{
  "type": "Feature",
  "properties": {
    "iso:country":"US",
    "sg:address":"3323 E 3600 N",
    "sg:city":"Kimberly",
    "sg:classifiers":[
        {
            "category":"Home & Garden",
            "subcategory":"Home Furnishings",
            "type":"Retail Goods"
        }
    ],
    "sg:phone":"+1 208 733 4285",
    "sg:postcode":"83341",
    "sg:province":"ID",
    "sg:tags":[
        "kitchen",
        "accessory"
    ],
    "wof:name":"Kitchen Magic",
    "wof:placetype":"venue"
},
  "geometry": {"coordinates":[-114.3976,42.519274],"type":"Point"}
}