{
  "type": "Feature",
  "properties": {
    "iso:country":"US",
    "sg:address":"2536 N Tuscan Ave",
    "sg:city":"Meridian",
    "sg:classifiers":[
        {
            "category":"Building & Trades",
            "subcategory":"Landscaping Services",
            "type":"Services"
        }
    ],
    "sg:phone":"+1 208 887 1478",
    "sg:postcode":"83646",
    "sg:province":"ID",
    "wof:name":"Tuscan Lawn & Landscape",
    "wof:placetype":"venue"
},
  "geometry": {"coordinates":[-116.390842,43.62786],"type":"Point"}
}