{
  "type": "Feature",
  "properties": {
    "iso:country":"US",
    "sg:address":"1301 Bennett Ave",
    "sg:city":"Burley",
    "sg:classifiers":[
        {
            "category":"Social Services",
            "subcategory":"Adult Care",
            "type":"Services"
        }
    ],
    "sg:phone":"+1 208 677 8212",
    "sg:postcode":"83318",
    "sg:province":"ID",
    "sg:tags":[
        "home",
        "residential"
    ],
    "wof:name":"Warren House",
    "wof:placetype":"venue"
},
  "geometry": {"coordinates":[-113.78039200000001,42.537015],"type":"Point"}
}