{
  "type": "Feature",
  "properties": {
    "addr:full":"60 N Millhollow Rd Rexburg ID 83440",
    "addr:housenumber":"60",
    "addr:postcode":"83440",
    "addr:street":"N Millhollow Rd",
    "iso:country":"US",
    "sg:address":"60 N Millhollow Rd",
    "sg:city":"Rexburg",
    "sg:classifiers":[
        {
            "category":"Banks & Credit Unions",
            "subcategory":"Financial Services",
            "type":"Services"
        }
    ],
    "sg:phone":"+1 208 356 7018",
    "sg:postcode":"83440",
    "sg:province":"ID",
    "sg:tags":[
        "investor"
    ],
    "wof:name":"Morris Investment",
    "wof:placetype":"venue"
},
  "geometry": {"coordinates":[-111.769015,43.828057],"type":"Point"}
}