{
  "type": "Feature",
  "properties": {
    "addr:full":"293 Hankins Rd N Twin Falls ID 83301",
    "addr:housenumber":"293",
    "addr:postcode":"83301",
    "addr:street":"Hankins Rd N",
    "iso:country":"US",
    "sg:address":"293 Hankins Rd N",
    "sg:city":"Twin Falls",
    "sg:classifiers":[
        {
            "category":"Building & Trades",
            "subcategory":"Construction",
            "type":"Services"
        }
    ],
    "sg:phone":"+1 208 735 5031",
    "sg:postcode":"83301",
    "sg:province":"ID",
    "sg:tags":[
        "insulation",
        "heat",
        "contractor"
    ],
    "wof:name":"Merlin's Insulation",
    "wof:placetype":"venue"
},
  "geometry": {"coordinates":[-114.42124200000001,42.566632],"type":"Point"}
}