{
  "type": "Feature",
  "properties": {
    "iso:country":"US",
    "sg:address":"2150 Broadway Ave",
    "sg:city":"Boise",
    "sg:classifiers":[
        {
            "category":"Food & Beverages",
            "subcategory":"Liquor & Beverages",
            "type":"Retail Goods"
        }
    ],
    "sg:phone":"+1 208 334 2458",
    "sg:postcode":"83706",
    "sg:province":"ID",
    "wof:name":"Idaho State Liquor Stores",
    "wof:placetype":"venue"
},
  "geometry": {"coordinates":[-116.193568,43.585602],"type":"Point"}
}