{
  "type": "Feature",
  "properties": {
    "iso:country":"US",
    "sg:address":"128 E Locust Ave",
    "sg:city":"Coeur D Alene",
    "sg:classifiers":[
        {
            "category":"Airline",
            "type":"Transportation"
        }
    ],
    "sg:phone":"+1 208 765 0620",
    "sg:postcode":"83814",
    "sg:province":"ID",
    "sg:tags":[
        "helicopter",
        "rental"
    ],
    "wof:name":"Big Country Communications",
    "wof:placetype":"venue"
},
  "geometry": {"coordinates":[-116.78528900000001,47.693342],"type":"Point"}
}