{
  "type": "Feature",
  "properties": {
    "iso:country":"US",
    "sg:address":"3390 N Lomah Ln",
    "sg:city":"Eagle",
    "sg:classifiers":[
        {
            "category":"Real Estate",
            "subcategory":"Real Estate Agent",
            "type":"Services"
        }
    ],
    "sg:phone":"+1 208 939 4383",
    "sg:postcode":"83616",
    "sg:province":"ID",
    "wof:name":"J P Properties LTD Co",
    "wof:placetype":"venue"
},
  "geometry": {"coordinates":[-116.360471,43.72617],"type":"Point"}
}