{
  "type": "Feature",
  "properties": {
    "iso:country":"US",
    "sg:address":"425 Overland Ave",
    "sg:city":"Burley",
    "sg:classifiers":[
        {
            "category":"Professional",
            "subcategory":"Business Services",
            "type":"Services"
        }
    ],
    "sg:phone":"+1 208 878 4236",
    "sg:postcode":"83318",
    "sg:province":"ID",
    "sg:tags":[
        "appraiser"
    ],
    "sg:website":"www.patmerrigan.com",
    "wof:name":"Cornerstone Appraisal Inc",
    "wof:placetype":"venue"
},
  "geometry": {"coordinates":[-113.79326,42.548362],"type":"Point"}
}