{
  "type": "Feature",
  "properties": {
    "iso:country":"US",
    "sg:address":"510 S Home St",
    "sg:city":"Moscow",
    "sg:classifiers":[
        {
            "category":"Education",
            "subcategory":"School",
            "type":"Public Place"
        }
    ],
    "sg:phone":"+1 208 882 2714",
    "sg:postcode":"83843",
    "sg:province":"ID",
    "sg:tags":[
        "elementary"
    ],
    "wof:name":"West Park Elementary School",
    "wof:placetype":"venue"
},
  "geometry": {"coordinates":[-117.010513,46.731404],"type":"Point"}
}