{
  "type": "Feature",
  "properties": {
    "addr:full":"1010 S Washington Ave Emmett ID 83617",
    "addr:housenumber":"1010",
    "addr:postcode":"83617",
    "addr:street":"S Washington Ave",
    "iso:country":"US",
    "sg:address":"1010 S Washington Ave",
    "sg:city":"Emmett",
    "sg:classifiers":[
        {
            "category":"Home & Garden",
            "subcategory":"Building Materials",
            "type":"Retail Goods"
        }
    ],
    "sg:phone":"+1 208 365 3771",
    "sg:postcode":"83617",
    "sg:province":"ID",
    "sg:tags":[
        "paint"
    ],
    "wof:name":"House Of Color Paint",
    "wof:placetype":"venue"
},
  "geometry": {"coordinates":[-116.499909,43.867232],"type":"Point"}
}