{
  "type": "Feature",
  "properties": {
    "iso:country":"US",
    "sg:address":"116 S Front St",
    "sg:city":"Sugar City",
    "sg:classifiers":[
        {
            "category":"Retail",
            "subcategory":"Laundry & Dry Cleaning",
            "type":"Services"
        }
    ],
    "sg:phone":"+1 208 656 3296",
    "sg:postcode":"83448",
    "sg:province":"ID",
    "sg:tags":[
        "cleaners",
        "rug",
        "carpet"
    ],
    "wof:name":"Day & Night Carpet & Cleaning",
    "wof:placetype":"venue"
},
  "geometry": {"coordinates":[-111.75272099999999,43.87071],"type":"Point"}
}