{
  "type": "Feature",
  "properties": {
    "iso:country":"US",
    "sg:address":"3370 US Hwy 30",
    "sg:city":"Pocatello",
    "sg:classifiers":[
        {
            "category":"Retail",
            "subcategory":"Auto Repair",
            "type":"Services"
        }
    ],
    "sg:phone":"+1 208 232 9066",
    "sg:postcode":"83201",
    "sg:province":"ID",
    "sg:tags":[
        "truck"
    ],
    "wof:name":"S K Truck & Trailer Repair Inc",
    "wof:placetype":"venue"
},
  "geometry": {"coordinates":[-112.47886200000001,42.892899],"type":"Point"}
}