{
  "type": "Feature",
  "properties": {
    "iso:country":"US",
    "sg:address":"1388 N Hwy 91",
    "sg:city":"Shelley",
    "sg:classifiers":[
        {
            "category":"Recreation",
            "subcategory":"Marina",
            "type":"Entertainment"
        }
    ],
    "sg:phone":"+1 208 357 5896",
    "sg:postcode":"83274",
    "sg:province":"ID",
    "sg:tags":[
        "storage",
        "boat"
    ],
    "wof:name":"C & S Storage",
    "wof:placetype":"venue"
},
  "geometry": {"coordinates":[-112.112977,43.394959],"type":"Point"}
}