{
  "type": "Feature",
  "properties": {
    "addr:full":"830 N 9th Ave Pocatello ID 83201",
    "addr:housenumber":"830",
    "addr:postcode":"83201",
    "addr:street":"N 9Th Ave",
    "iso:country":"US",
    "sg:address":"830 N 9th Ave",
    "sg:city":"Pocatello",
    "sg:classifiers":[
        {
            "category":"Freight",
            "type":"Transportation"
        }
    ],
    "sg:phone":"+1 208 478 9332",
    "sg:postcode":"83201",
    "sg:province":"ID",
    "sg:tags":[
        "courier"
    ],
    "wof:name":"J K Toklat Inc",
    "wof:placetype":"venue"
},
  "geometry": {"coordinates":[-112.44615,42.874942],"type":"Point"}
}