{
  "type": "Feature",
  "properties": {
    "addr:full":"330 Ave D Kuna ID 83634",
    "addr:housenumber":"330",
    "addr:postcode":"83634",
    "addr:street":"Ave D",
    "iso:country":"US",
    "sg:address":"330 Ave D",
    "sg:city":"Kuna",
    "sg:classifiers":[
        {
            "category":"Retail",
            "subcategory":"Animal Services",
            "type":"Services"
        }
    ],
    "sg:phone":"+1 208 922 1473",
    "sg:postcode":"83634",
    "sg:province":"ID",
    "sg:tags":[
        "pet",
        "grooming",
        "washing"
    ],
    "wof:name":"Doggieworks",
    "wof:placetype":"venue"
},
  "geometry": {"coordinates":[-116.419507,43.490557],"type":"Point"}
}