{
  "type": "Feature",
  "properties": {
    "iso:country":"US",
    "sg:address":"913 River St",
    "sg:city":"Boise",
    "sg:classifiers":[
        {
            "category":"Restaurant",
            "type":"Food & Drink"
        }
    ],
    "sg:phone":"+1 208 333 9800",
    "sg:postcode":"83702",
    "sg:province":"ID",
    "sg:tags":[
        "eating"
    ],
    "sg:website":"www.cottonwoodgrille.com",
    "wof:name":"Cottonwood Grille",
    "wof:placetype":"venue"
},
  "geometry": {"coordinates":[-116.21014700000001,43.61132],"type":"Point"}
}