{
  "type": "Feature",
  "properties": {
    "addr:full":"3521 S Arcaro Ave Meridian ID 83642",
    "addr:housenumber":"3521",
    "addr:postcode":"83642",
    "addr:street":"S Arcaro Ave",
    "iso:country":"US",
    "sg:address":"3521 S Arcaro Ave",
    "sg:city":"Meridian",
    "sg:classifiers":[
        {
            "category":"Building & Trades",
            "subcategory":"Landscaping Services",
            "type":"Services"
        }
    ],
    "sg:phone":"+1 208 884 8036",
    "sg:postcode":"83642",
    "sg:province":"ID",
    "sg:tags":[
        "landscape",
        "contractor"
    ],
    "wof:name":"Sunshine Landscape",
    "wof:placetype":"venue"
},
  "geometry": {"coordinates":[-116.401567,43.573136],"type":"Point"}
}