{
  "type": "Feature",
  "properties": {
    "iso:country":"US",
    "sg:address":"224 1st St S",
    "sg:city":"Nampa",
    "sg:classifiers":[
        {
            "category":"Home & Garden",
            "subcategory":"Building Materials",
            "type":"Retail Goods"
        }
    ],
    "sg:phone":"+1 208 466 2489",
    "sg:postcode":"83651",
    "sg:province":"ID",
    "wof:name":"Western Building Supply",
    "wof:placetype":"venue"
},
  "geometry": {"coordinates":[-116.570014,43.585869],"type":"Point"}
}