{
  "type": "Feature",
  "properties": {
    "iso:country":"US",
    "sg:address":"1629 N Main St",
    "sg:city":"Meridian",
    "sg:classifiers":[
        {
            "category":"Restaurant",
            "type":"Food & Drink"
        }
    ],
    "sg:menulink":"http://www.allmenus.com/id/boise-city/225042-chicago-connection/menu/",
    "sg:phone":"+1 208 888 1986",
    "sg:postcode":"83642",
    "sg:province":"ID",
    "sg:tags":[
        "italian"
    ],
    "wof:name":"Chicago Connection",
    "wof:placetype":"venue"
},
  "geometry": {"coordinates":[-116.391716,43.618719],"type":"Point"}
}