{
  "type": "Feature",
  "properties": {
    "addr:full":"915 S Main St Payette ID 83661",
    "addr:housenumber":"915",
    "addr:postcode":"83661",
    "addr:street":"S Main St",
    "iso:country":"US",
    "sg:address":"915 S Main St",
    "sg:city":"Payette",
    "sg:classifiers":[
        {
            "category":"Autos & Motor Vehicles",
            "subcategory":"Automobile Sales",
            "type":"Retail Goods"
        }
    ],
    "sg:phone":"+1 208 642 3348",
    "sg:postcode":"83661",
    "sg:province":"ID",
    "sg:tags":[
        "car",
        "dealer"
    ],
    "sg:website":"www.hanigan.com",
    "wof:name":"Hanigan Chevrolet",
    "wof:placetype":"venue"
},
  "geometry": {"coordinates":[-116.92975,44.064743],"type":"Point"}
}