{
  "type": "Feature",
  "properties": {
    "addr:full":"21751 Old Hwy 30 Caldwell ID 83607",
    "addr:housenumber":"21751",
    "addr:postcode":"83607",
    "addr:street":"Old Hwy 30",
    "iso:country":"US",
    "sg:address":"21751 Old Hwy 30",
    "sg:city":"Caldwell",
    "sg:phone":"+1 208 459 9102",
    "sg:postcode":"83607",
    "sg:province":"ID",
    "sg:tags":[
        "irrigation",
        "company"
    ],
    "wof:name":"Farmers Cooperative Ditch Co",
    "wof:placetype":"venue"
},
  "geometry": {"coordinates":[-116.690839,43.689309],"type":"Point"}
}