{
  "type": "Feature",
  "properties": {
    "iso:country":"US",
    "sg:address":"430 N 1800 E",
    "sg:city":"Saint Anthony",
    "sg:classifiers":[
        {
            "category":"Manufacturing",
            "subcategory":"Metals",
            "type":"Manufacturing & Wholesale Goods"
        }
    ],
    "sg:phone":"+1 208 624 7087",
    "sg:postcode":"83445",
    "sg:province":"ID",
    "sg:tags":[
        "decorative",
        "product",
        "mfg"
    ],
    "wof:name":"Old West Blacksmith Inc",
    "wof:placetype":"venue"
},
  "geometry": {"coordinates":[-111.797513,43.946015],"type":"Point"}
}