{
  "type": "Feature",
  "properties": {
    "iso:country":"US",
    "sg:address":"330 Shoup Ave",
    "sg:city":"Idaho Falls",
    "sg:classifiers":[
        {
            "category":"Shopping",
            "subcategory":"Computers & Home Electronics",
            "type":"Retail Goods"
        }
    ],
    "sg:phone":"+1 208 525 1327",
    "sg:postcode":"83402",
    "sg:province":"ID",
    "sg:tags":[
        "television",
        "radio"
    ],
    "wof:name":"Channel Blend",
    "wof:placetype":"venue"
},
  "geometry": {"coordinates":[-112.039728,43.491909],"type":"Point"}
}