{
  "type": "Feature",
  "properties": {
    "iso:country":"US",
    "sg:address":"310 N 9th St",
    "sg:city":"Boise",
    "sg:classifiers":[
        {
            "category":"Shopping",
            "subcategory":"Gifts & Souvenirs",
            "type":"Retail Goods"
        }
    ],
    "sg:phone":"+1 208 343 5008",
    "sg:postcode":"83702",
    "sg:province":"ID",
    "sg:tags":[
        "shop"
    ],
    "wof:name":"Purple Butterfly",
    "wof:placetype":"venue"
},
  "geometry": {"coordinates":[-116.20244700000001,43.618396],"type":"Point"}
}