{
  "type": "Feature",
  "properties": {
    "addr:full":"400 S Pine St Emmett ID 83617",
    "addr:housenumber":"400",
    "addr:postcode":"83617",
    "addr:street":"S Pine St",
    "iso:country":"US",
    "sg:address":"400 S Pine St",
    "sg:city":"Emmett",
    "sg:classifiers":[
        {
            "category":"Education",
            "subcategory":"School",
            "type":"Public Place"
        }
    ],
    "sg:phone":"+1 208 365 4691",
    "sg:postcode":"83617",
    "sg:province":"ID",
    "wof:name":"Butte View Elementary School",
    "wof:placetype":"venue"
},
  "geometry": {"coordinates":[-116.484914,43.872294],"type":"Point"}
}