{
  "type": "Feature",
  "properties": {
    "iso:country":"US",
    "sg:address":"5454 W Central Rd",
    "sg:city":"Emmett",
    "sg:phone":"+1 208 365 5686",
    "sg:postcode":"83617",
    "sg:province":"ID",
    "sg:tags":[
        "farm",
        "wheat"
    ],
    "wof:name":"Dar Olberding",
    "wof:placetype":"venue"
},
  "geometry": {"coordinates":[-116.60144099999999,43.901266],"type":"Point"}
}