{
  "type": "Feature",
  "properties": {
    "iso:country":"US",
    "sg:address":"836 E 2000 S",
    "sg:city":"Bliss",
    "sg:classifiers":[
        {
            "category":"Farming",
            "subcategory":"Farm",
            "type":"Manufacturing & Wholesale Goods"
        }
    ],
    "sg:phone":"+1 208 352 1139",
    "sg:postcode":"83314",
    "sg:province":"ID",
    "wof:name":"Gough Farms",
    "wof:placetype":"venue"
},
  "geometry": {"coordinates":[-114.923878,42.908987],"type":"Point"}
}