{
  "type": "Feature",
  "properties": {
    "iso:country":"US",
    "sg:address":"2108 S Juniper St",
    "sg:city":"Nampa",
    "sg:classifiers":[
        {
            "category":"Shopping",
            "subcategory":"Hobbies, Toys, & Games",
            "type":"Retail Goods"
        }
    ],
    "sg:phone":"+1 208 466 7132",
    "sg:postcode":"83686",
    "sg:province":"ID",
    "sg:tags":[
        "craft"
    ],
    "wof:name":"Larson Creatives Inc",
    "wof:placetype":"venue"
},
  "geometry": {"coordinates":[-116.567413,43.548626],"type":"Point"}
}