{
  "type": "Feature",
  "properties": {
    "addr:full":"5315 Diamond Cir Chubbuck ID 83202",
    "addr:housenumber":"5315",
    "addr:postcode":"83202",
    "addr:street":"Diamond Cir",
    "iso:country":"US",
    "sg:address":"5315 Diamond Cir",
    "sg:city":"Chubbuck",
    "sg:classifiers":[
        {
            "category":"Real Estate",
            "subcategory":"Real Estate Operator",
            "type":"Services"
        }
    ],
    "sg:phone":"+1 208 237 6549",
    "sg:postcode":"83202",
    "sg:province":"ID",
    "sg:tags":[
        "apartment"
    ],
    "wof:name":"Diamond Court Apartments",
    "wof:placetype":"venue"
},
  "geometry": {"coordinates":[-112.462475,42.929682],"type":"Point"}
}