{
  "type": "Feature",
  "properties": {
    "iso:country":"US",
    "sg:address":"6090 Emerald St",
    "sg:city":"Boise",
    "sg:classifiers":[
        {
            "category":"Health Services",
            "subcategory":"Medical Lab",
            "type":"Services"
        }
    ],
    "sg:phone":"+1 208 376 5359",
    "sg:postcode":"83704",
    "sg:province":"ID",
    "sg:tags":[
        "laboratory"
    ],
    "sg:website":"www.labcorp.com",
    "wof:name":"Laboratory Corp Of America",
    "wof:placetype":"venue"
},
  "geometry": {"coordinates":[-116.257746,43.611799],"type":"Point"}
}