{
  "type": "Feature",
  "properties": {
    "iso:country":"US",
    "sg:address":"1228 S Arbor Island Pl",
    "sg:city":"Eagle",
    "sg:classifiers":[
        {
            "category":"Recreation",
            "type":"Entertainment"
        }
    ],
    "sg:phone":"+1 208 938 1155",
    "sg:postcode":"83616",
    "sg:province":"ID",
    "wof:name":"Hoop Dreams",
    "wof:placetype":"venue"
},
  "geometry": {"coordinates":[-116.358046,43.68382],"type":"Point"}
}