{
  "type": "Feature",
  "properties": {
    "addr:full":"2422 12th Ave Rd Nampa ID 83686",
    "addr:housenumber":"2422",
    "addr:postcode":"83686",
    "addr:street":"12Th Ave Rd",
    "iso:country":"US",
    "sg:address":"2422 12th Ave Rd",
    "sg:city":"Nampa",
    "sg:classifiers":[
        {
            "category":"Retail",
            "subcategory":"Auto Repair",
            "type":"Services"
        }
    ],
    "sg:phone":"+1 208 412 3270",
    "sg:postcode":"83686",
    "sg:province":"ID",
    "sg:tags":[
        "glass",
        "coating",
        "tinting"
    ],
    "wof:name":"Idaho Window Tinting",
    "wof:placetype":"venue"
},
  "geometry": {"coordinates":[-116.572596,43.545872],"type":"Point"}
}