{
  "type": "Feature",
  "properties": {
    "iso:country":"US",
    "sg:address":"175 S School Ave",
    "sg:city":"Kuna",
    "sg:classifiers":[
        {
            "category":"Building & Trades",
            "subcategory":"Construction",
            "type":"Services"
        }
    ],
    "sg:phone":"+1 208 922 3545",
    "sg:postcode":"83634",
    "sg:province":"ID",
    "sg:tags":[
        "home",
        "improvement"
    ],
    "wof:name":"KUNA Lumber",
    "wof:placetype":"venue"
},
  "geometry": {"coordinates":[-116.423779,43.487727],"type":"Point"}
}