{
  "type": "Feature",
  "properties": {
    "iso:country":"US",
    "sg:address":"156 S 45th W",
    "sg:city":"Idaho Falls",
    "sg:classifiers":[
        {
            "category":"Farming",
            "subcategory":"Farm",
            "type":"Manufacturing & Wholesale Goods"
        }
    ],
    "sg:phone":"+1 208 524 6333",
    "sg:postcode":"83402",
    "sg:province":"ID",
    "sg:tags":[
        "crop",
        "general"
    ],
    "wof:name":"Beckman Farms",
    "wof:placetype":"venue"
},
  "geometry": {"coordinates":[-112.122911,43.497146],"type":"Point"}
}