{
  "type": "Feature",
  "properties": {
    "iso:country":"US",
    "sg:address":"521 Cedar St",
    "sg:city":"Sandpoint",
    "sg:classifiers":[
        {
            "category":"Education",
            "subcategory":"Dance Studio",
            "type":"Public Place"
        }
    ],
    "sg:phone":"+1 208 263 5220",
    "sg:postcode":"83864",
    "sg:province":"ID",
    "sg:tags":[
        "personal"
    ],
    "wof:name":"Dance Acadamy",
    "wof:placetype":"venue"
},
  "geometry": {"coordinates":[-116.553825,48.276021],"type":"Point"}
}