{
  "type": "Feature",
  "properties": {
    "addr:full":"4150 Yellowstone Ave Pocatello ID 83202",
    "addr:housenumber":"4150",
    "addr:postcode":"83202",
    "addr:street":"Yellowstone Ave",
    "iso:country":"US",
    "sg:address":"4150 Yellowstone Ave",
    "sg:city":"Pocatello",
    "sg:classifiers":[
        {
            "category":"Shopping",
            "subcategory":"Department Store",
            "type":"Retail Goods"
        }
    ],
    "sg:phone":"+1 208 238 5804",
    "sg:postcode":"83202",
    "sg:province":"ID",
    "sg:tags":[
        "shop"
    ],
    "wof:name":"Only One Dollar",
    "wof:placetype":"venue"
},
  "geometry": {"coordinates":[-112.46640600000001,42.908491],"type":"Point"}
}