{
  "type": "Feature",
  "properties": {
    "iso:country":"US",
    "sg:address":"1438 Camel Back Ln",
    "sg:city":"Boise",
    "sg:classifiers":[
        {
            "category":"Professional",
            "subcategory":"Management & Consulting",
            "type":"Services"
        }
    ],
    "sg:phone":"+1 208 336 7703",
    "sg:postcode":"83702",
    "sg:province":"ID",
    "wof:name":"Salisbury Consulting",
    "wof:placetype":"venue"
},
  "geometry": {"coordinates":[-116.204868,43.640123],"type":"Point"}
}