{
  "type": "Feature",
  "properties": {
    "iso:country":"US",
    "sg:address":"15920 Richway Dr",
    "sg:city":"Caldwell",
    "sg:classifiers":[
        {
            "category":"Utilities",
            "subcategory":"Telephone",
            "type":"Services"
        }
    ],
    "sg:phone":"+1 208 453 1674",
    "sg:postcode":"83607",
    "sg:province":"ID",
    "sg:tags":[
        "communications"
    ],
    "wof:name":"Aerislinkcom",
    "wof:placetype":"venue"
},
  "geometry": {"coordinates":[-116.71191,43.724508],"type":"Point"}
}