{
  "type": "Feature",
  "properties": {
    "iso:country":"US",
    "sg:address":"643 Railroad Ave",
    "sg:city":"Blanchard",
    "sg:classifiers":[
        {
            "category":"Wholesale",
            "subcategory":"Machinery & Supplies",
            "type":"Manufacturing & Wholesale Goods"
        }
    ],
    "sg:phone":"+1 208 437 2108",
    "sg:postcode":"83804",
    "sg:province":"ID",
    "wof:name":"Magee Enterprises",
    "wof:placetype":"venue"
},
  "geometry": {"coordinates":[-116.978447,48.014709],"type":"Point"}
}