{
  "type": "Feature",
  "properties": {
    "iso:country":"US",
    "sg:address":"1206 Riverdale Dr",
    "sg:city":"St Maries",
    "sg:classifiers":[
        {
            "category":"Manufacturing",
            "subcategory":"Lumber",
            "type":"Manufacturing & Wholesale Goods"
        }
    ],
    "sg:phone":"+1 208 245 0804",
    "sg:postcode":"83861",
    "sg:province":"ID",
    "sg:tags":[
        "company",
        "logging"
    ],
    "wof:name":"Roland Custom Milling",
    "wof:placetype":"venue"
},
  "geometry": {"coordinates":[-116.56049400000001,47.332498],"type":"Point"}
}