{
  "type": "Feature",
  "properties": {
    "iso:country":"US",
    "sg:address":"2926 Innis St",
    "sg:city":"Boise",
    "sg:classifiers":[
        {
            "category":"Personal",
            "subcategory":"Beauty Salon",
            "type":"Services"
        }
    ],
    "sg:phone":"+1 208 344 7772",
    "sg:postcode":"83703",
    "sg:province":"ID",
    "wof:name":"Shears To Ya",
    "wof:placetype":"venue"
},
  "geometry": {"coordinates":[-116.24123,43.647326],"type":"Point"}
}