{
  "type": "Feature",
  "properties": {
    "iso:country":"US",
    "sg:address":"1270 Elmore Ave",
    "sg:city":"Idaho Falls",
    "sg:classifiers":[
        {
            "category":"Retail",
            "subcategory":"Repair Shop",
            "type":"Services"
        }
    ],
    "sg:phone":"+1 208 522 2235",
    "sg:postcode":"83402",
    "sg:province":"ID",
    "sg:tags":[
        "lock",
        "locksmith"
    ],
    "wof:name":"A-Bonded Locksmith Svc",
    "wof:placetype":"venue"
},
  "geometry": {"coordinates":[-112.04580900000001,43.510533],"type":"Point"}
}