{
  "type": "Feature",
  "properties": {
    "addr:full":"507 N Dewey Ave Middleton ID 83644",
    "addr:housenumber":"507",
    "addr:postcode":"83644",
    "addr:street":"N Dewey Ave",
    "iso:country":"US",
    "sg:address":"507 N Dewey Ave",
    "sg:city":"Middleton",
    "sg:classifiers":[
        {
            "category":"Freight",
            "type":"Transportation"
        }
    ],
    "sg:phone":"+1 208 585 3350",
    "sg:postcode":"83644",
    "sg:province":"ID",
    "sg:tags":[
        "operator",
        "local",
        "trucking"
    ],
    "wof:name":"McConnell Trucking Inc",
    "wof:placetype":"venue"
},
  "geometry": {"coordinates":[-116.619658,43.712049],"type":"Point"}
}