{
  "type": "Feature",
  "properties": {
    "addr:full":"1081 N Mitchell St Boise ID 83704",
    "addr:housenumber":"1081",
    "addr:postcode":"83704",
    "addr:street":"N Mitchell St",
    "iso:country":"US",
    "sg:address":"1081 N Mitchell St",
    "sg:city":"Boise",
    "sg:classifiers":[
        {
            "category":"Building & Trades",
            "subcategory":"Landscaping Services",
            "type":"Services"
        }
    ],
    "sg:phone":"+1 208 322 4505",
    "sg:postcode":"83704",
    "sg:province":"ID",
    "sg:tags":[
        "landscape",
        "contractor"
    ],
    "sg:website":"www.sterlinglandscape.com",
    "wof:name":"Sterling Landscape",
    "wof:placetype":"venue"
},
  "geometry": {"coordinates":[-116.304255,43.615198],"type":"Point"}
}