{
  "type": "Feature",
  "properties": {
    "addr:full":"500 S 11th Ave Pocatello ID 83201",
    "addr:housenumber":"500",
    "addr:postcode":"83201",
    "addr:street":"S 11Th Ave",
    "iso:country":"US",
    "sg:address":"500 S 11th Ave",
    "sg:city":"Pocatello",
    "sg:classifiers":[
        {
            "category":"Shopping",
            "subcategory":"Pharmacy",
            "type":"Retail Goods"
        }
    ],
    "sg:phone":"+1 208 239 1179",
    "sg:postcode":"83201",
    "sg:province":"ID",
    "wof:name":"Bob's Pharmacy",
    "wof:placetype":"venue"
},
  "geometry": {"coordinates":[-112.43303899999999,42.866622],"type":"Point"}
}