{
  "type": "Feature",
  "properties": {
    "addr:full":"11 State Hwy 31 Swan Valley ID 83449",
    "addr:housenumber":"11",
    "addr:postcode":"83449",
    "addr:street":"State Hwy 31",
    "iso:country":"US",
    "sg:address":"11 State Hwy 31",
    "sg:city":"Swan Valley",
    "sg:classifiers":[
        {
            "category":"Utilities",
            "subcategory":"Refuse",
            "type":"Services"
        }
    ],
    "sg:phone":"+1 208 483 2142",
    "sg:postcode":"83449",
    "sg:province":"ID",
    "sg:tags":[
        "garbage",
        "collection"
    ],
    "wof:name":"South Fork Sanitation",
    "wof:placetype":"venue"
},
  "geometry": {"coordinates":[-111.355867,43.505885],"type":"Point"}
}