{
  "type": "Feature",
  "properties": {
    "iso:country":"US",
    "sg:address":"1300 W Fairwood Ave",
    "sg:city":"Nampa",
    "sg:classifiers":[
        {
            "category":"Shopping",
            "subcategory":"Clothing, Apparel, & Fashions",
            "type":"Retail Goods"
        }
    ],
    "sg:phone":"+1 208 468 4913",
    "sg:postcode":"83651",
    "sg:province":"ID",
    "wof:name":"Ace Products",
    "wof:placetype":"venue"
},
  "geometry": {"coordinates":[-116.59612,43.574911],"type":"Point"}
}