{
  "type": "Feature",
  "properties": {
    "addr:full":"205 E Fremont Ave Rigby ID 83442",
    "addr:housenumber":"205",
    "addr:postcode":"83442",
    "addr:street":"E Fremont Ave",
    "iso:country":"US",
    "sg:address":"205 E Fremont Ave",
    "sg:city":"Rigby",
    "sg:classifiers":[
        {
            "category":"Real Estate",
            "subcategory":"Real Estate Services",
            "type":"Services"
        }
    ],
    "sg:phone":"+1 208 745 9495",
    "sg:postcode":"83442",
    "sg:province":"ID",
    "sg:tags":[
        "company",
        "title"
    ],
    "wof:name":"Alliance Title & Escrow Corp",
    "wof:placetype":"venue"
},
  "geometry": {"coordinates":[-111.91189,43.673341],"type":"Point"}
}