{
  "type": "Feature",
  "properties": {
    "iso:country":"US",
    "sg:address":"8755 Joplin Rd",
    "sg:city":"Meridian",
    "sg:classifiers":[
        {
            "category":"Farming",
            "subcategory":"Livestock Farm",
            "type":"Manufacturing & Wholesale Goods"
        }
    ],
    "sg:phone":"+1 208 286 7888",
    "sg:postcode":"83642",
    "sg:province":"ID",
    "sg:tags":[
        "ranch"
    ],
    "sg:website":"www.doublenickelranch.com",
    "wof:name":"Double Nickel Ranch",
    "wof:placetype":"venue"
},
  "geometry": {"coordinates":[-116.496071,43.670215],"type":"Point"}
}