{
  "type": "Feature",
  "properties": {
    "addr:full":"3020 W Cherry Ln Boise ID 83705",
    "addr:housenumber":"3020",
    "addr:postcode":"83705",
    "addr:street":"W Cherry Ln",
    "iso:country":"US",
    "sg:address":"3020 W Cherry Ln",
    "sg:city":"Boise",
    "sg:classifiers":[
        {
            "category":"Organizations",
            "subcategory":"Religious Organization",
            "type":"Services"
        }
    ],
    "sg:phone":"+1 208 345 9409",
    "sg:postcode":"83705",
    "sg:province":"ID",
    "sg:tags":[
        "church"
    ],
    "wof:name":"Church Of Jesus Christ Of Lds",
    "wof:placetype":"venue"
},
  "geometry": {"coordinates":[-116.219499,43.580844],"type":"Point"}
}