{
  "type": "Feature",
  "properties": {
    "iso:country":"US",
    "sg:address":"114 E Idaho Ave",
    "sg:city":"Meridian",
    "sg:classifiers":[
        {
            "category":"Insurance",
            "subcategory":"Insurance Agent",
            "type":"Services"
        }
    ],
    "sg:phone":"+1 208 895 0202",
    "sg:postcode":"83642",
    "sg:province":"ID",
    "sg:website":"www.modern-woodmen.org",
    "wof:name":"Modern Woodmen Of America",
    "wof:placetype":"venue"
},
  "geometry": {"coordinates":[-116.39142699999999,43.611112],"type":"Point"}
}