{
  "type": "Feature",
  "properties": {
    "addr:full":"1000 Starr Ln Sandpoint ID 83864",
    "addr:housenumber":"1000",
    "addr:postcode":"83864",
    "addr:street":"Starr Ln",
    "iso:country":"US",
    "sg:address":"1000 Starr Ln",
    "sg:city":"Sandpoint",
    "sg:classifiers":[
        {
            "category":"Retail",
            "subcategory":"Repair Shop",
            "type":"Services"
        }
    ],
    "sg:phone":"+1 208 263 6404",
    "sg:postcode":"83864",
    "sg:province":"ID",
    "sg:tags":[
        "electrical"
    ],
    "wof:name":"Rainbow Appliance",
    "wof:placetype":"venue"
},
  "geometry": {"coordinates":[-116.542828,48.317264],"type":"Point"}
}