{
  "type": "Feature",
  "properties": {
    "iso:country":"US",
    "sg:address":"31 E Wyoming Ave",
    "sg:city":"Homedale",
    "sg:classifiers":[
        {
            "category":"Government",
            "subcategory":"Office",
            "type":"Public Place"
        }
    ],
    "sg:phone":"+1 208 337 4641",
    "sg:postcode":"83628",
    "sg:province":"ID",
    "sg:tags":[
        "city"
    ],
    "wof:name":"Homedale City Hall",
    "wof:placetype":"venue"
},
  "geometry": {"coordinates":[-116.932879,43.616847],"type":"Point"}
}