{
  "type": "Feature",
  "properties": {
    "iso:country":"US",
    "sg:address":"4203 N Boyer Ave",
    "sg:city":"Sandpoint",
    "sg:classifiers":[
        {
            "category":"Recreation",
            "type":"Entertainment"
        }
    ],
    "sg:phone":"+1 208 263 8414",
    "sg:postcode":"83864",
    "sg:province":"ID",
    "sg:tags":[
        "fairground"
    ],
    "wof:name":"Fair Grounds Managers Office",
    "wof:placetype":"venue"
},
  "geometry": {"coordinates":[-116.557106,48.309664],"type":"Point"}
}