{
  "type": "Feature",
  "properties": {
    "iso:country":"US",
    "sg:address":"245 S 5th St",
    "sg:city":"Saint Maries",
    "sg:classifiers":[
        {
            "category":"Professional",
            "subcategory":"Detective & Security Services",
            "type":"Services"
        }
    ],
    "sg:phone":"+1 208 245 0263",
    "sg:postcode":"83861",
    "sg:province":"ID",
    "sg:tags":[
        "car"
    ],
    "wof:name":"Assurance Security",
    "wof:placetype":"venue"
},
  "geometry": {"coordinates":[-116.56459099999999,47.314813],"type":"Point"}
}