{
  "type": "Feature",
  "properties": {
    "iso:country":"US",
    "sg:address":"612 W Logan St",
    "sg:city":"Caldwell",
    "sg:classifiers":[
        {
            "category":"Health Services",
            "subcategory":"Nursing And Care Facility",
            "type":"Services"
        }
    ],
    "sg:phone":"+1 208 454 0004",
    "sg:postcode":"83605",
    "sg:province":"ID",
    "sg:tags":[
        "home",
        "retirement",
        "community"
    ],
    "wof:name":"Logan Park Congregate Care",
    "wof:placetype":"venue"
},
  "geometry": {"coordinates":[-116.703149,43.655287],"type":"Point"}
}