{
  "type": "Feature",
  "properties": {
    "addr:full":"823 Reed St American Falls ID 83211",
    "addr:housenumber":"823",
    "addr:postcode":"83211",
    "addr:street":"Reed St",
    "iso:country":"US",
    "sg:address":"823 Reed St",
    "sg:city":"American Falls",
    "sg:classifiers":[
        {
            "category":"Health Services",
            "subcategory":"Doctor",
            "type":"Services"
        }
    ],
    "sg:phone":"+1 208 226 2822",
    "sg:postcode":"83211",
    "sg:province":"ID",
    "sg:tags":[
        "clinic"
    ],
    "wof:name":"American Falls Medical Clinic",
    "wof:placetype":"venue"
},
  "geometry": {"coordinates":[-112.84414599999999,42.785185],"type":"Point"}
}