{
  "type": "Feature",
  "properties": {
    "iso:country":"US",
    "sg:address":"705 S Challis St",
    "sg:city":"Salmon",
    "sg:classifiers":[
        {
            "category":"Travel",
            "subcategory":"Hotels & Motels",
            "type":"Entertainment"
        }
    ],
    "sg:phone":"+1 208 756 2294",
    "sg:postcode":"83467",
    "sg:province":"ID",
    "sg:tags":[
        "operation"
    ],
    "wof:name":"Suncrest Motel",
    "wof:placetype":"venue"
},
  "geometry": {"coordinates":[-113.890741,45.168581],"type":"Point"}
}