{
  "type": "Feature",
  "properties": {
    "iso:country":"US",
    "sg:address":"531 Henderson Canyon Rd",
    "sg:city":"Victor",
    "sg:classifiers":[
        {
            "category":"Home & Garden",
            "subcategory":"Building Materials",
            "type":"Retail Goods"
        }
    ],
    "sg:phone":"+1 208 354 8540",
    "sg:postcode":"83455",
    "sg:province":"ID",
    "sg:tags":[
        "glass",
        "leaded"
    ],
    "wof:name":"Teton Valley Stained Glass",
    "wof:placetype":"venue"
},
  "geometry": {"coordinates":[-111.216055,43.638687],"type":"Point"}
}