{
  "type": "Feature",
  "properties": {
    "addr:full":"8960 Ardene St Boise ID 83709",
    "addr:postcode":"8960;83709",
    "addr:street":"Ardene St",
    "iso:country":"US",
    "sg:address":"8960 Ardene St",
    "sg:city":"Boise",
    "sg:classifiers":[
        {
            "category":"Sports & Exercise",
            "subcategory":"Gym",
            "type":"Entertainment"
        }
    ],
    "sg:phone":"+1 208 378 4740",
    "sg:postcode":"83709",
    "sg:province":"ID",
    "sg:tags":[
        "club",
        "health",
        "studio",
        "gymnasium"
    ],
    "wof:name":"Curves For Women",
    "wof:placetype":"venue"
},
  "geometry": {"coordinates":[-116.293492,43.589181],"type":"Point"}
}