{
  "type": "Feature",
  "properties": {
    "addr:full":"299 US Hwy 30 Filer ID 83328",
    "addr:housenumber":"299",
    "addr:postcode":"83328",
    "addr:street":"Us Hwy 30",
    "iso:country":"US",
    "sg:address":"299 US Hwy 30",
    "sg:city":"Filer",
    "sg:classifiers":[
        {
            "category":"Education",
            "subcategory":"School",
            "type":"Public Place"
        }
    ],
    "sg:phone":"+1 208 326 5906",
    "sg:postcode":"83328",
    "sg:province":"ID",
    "wof:name":"Filer Middle School",
    "wof:placetype":"venue"
},
  "geometry": {"coordinates":[-114.60575900000001,42.563927],"type":"Point"}
}