{
  "type": "Feature",
  "properties": {
    "iso:country":"US",
    "sg:address":"211 E Coeur D Alene Ave",
    "sg:city":"Coeur D Alene",
    "sg:classifiers":[
        {
            "category":"Real Estate",
            "subcategory":"Architect",
            "type":"Services"
        }
    ],
    "sg:phone":"+1 208 765 2639",
    "sg:postcode":"83814",
    "sg:province":"ID",
    "wof:name":"William E Dahlberg",
    "wof:placetype":"venue"
},
  "geometry": {"coordinates":[-116.78396100000001,47.675247],"type":"Point"}
}