{
  "type": "Feature",
  "properties": {
    "addr:full":"1401 Lincoln Way Coeur D Alene ID 83814",
    "addr:housenumber":"1401",
    "addr:postcode":"83814",
    "addr:street":"Lincoln Way",
    "iso:country":"US",
    "sg:address":"1401 Lincoln Way",
    "sg:city":"Coeur D Alene",
    "sg:classifiers":[
        {
            "category":"Health Services",
            "subcategory":"Doctor",
            "type":"Services"
        }
    ],
    "sg:phone":"+1 208 676 1424",
    "sg:postcode":"83814",
    "sg:province":"ID",
    "sg:tags":[
        "physician",
        "surgeon"
    ],
    "wof:name":"Lakewood Physical Therapy",
    "wof:placetype":"venue"
},
  "geometry": {"coordinates":[-116.79174399999999,47.688423],"type":"Point"}
}