{
  "type": "Feature",
  "properties": {
    "iso:country":"US",
    "sg:address":"940 Coyote Creek Ln",
    "sg:city":"Sandpoint",
    "sg:classifiers":[
        {
            "category":"Professional",
            "subcategory":"Computer Services",
            "type":"Services"
        }
    ],
    "sg:phone":"+1 208 255 7169",
    "sg:postcode":"83864",
    "sg:province":"ID",
    "sg:tags":[
        "datum"
    ],
    "wof:name":"Strauss Creative Ima",
    "wof:placetype":"venue"
},
  "geometry": {"coordinates":[-116.382671,48.380753],"type":"Point"}
}