{
  "type": "Feature",
  "properties": {
    "iso:country":"US",
    "sg:address":"317 US Hwy 93 N",
    "sg:city":"Salmon",
    "sg:classifiers":[
        {
            "category":"Restaurant",
            "type":"Food & Drink"
        }
    ],
    "sg:phone":"+1 208 756 1010",
    "sg:postcode":"83467",
    "sg:province":"ID",
    "wof:name":"Stone Bridge Gardens Rstrnt",
    "wof:placetype":"venue"
},
  "geometry": {"coordinates":[-113.898082,45.179626],"type":"Point"}
}