{
  "type": "Feature",
  "properties": {
    "addr:full":"1018 Blaine St Caldwell ID 83605",
    "addr:housenumber":"1018",
    "addr:postcode":"83605",
    "addr:street":"Blaine St",
    "iso:country":"US",
    "sg:address":"1018 Blaine St",
    "sg:city":"Caldwell",
    "sg:classifiers":[
        {
            "category":"Banks & Credit Unions",
            "subcategory":"Bank",
            "type":"Services"
        }
    ],
    "sg:phone":"+1 208 453 2923",
    "sg:postcode":"83605",
    "sg:province":"ID",
    "sg:website":"www.wamu.net",
    "wof:name":"Washington Mutual",
    "wof:placetype":"venue"
},
  "geometry": {"coordinates":[-116.68670299999999,43.663348],"type":"Point"}
}