{
  "type": "Feature",
  "properties": {
    "iso:country":"US",
    "sg:address":"3929 Reed St",
    "sg:city":"Boise",
    "sg:classifiers":[
        {
            "category":"Retail",
            "subcategory":"Repair Shop",
            "type":"Services"
        }
    ],
    "sg:phone":"+1 208 344 1676",
    "sg:postcode":"83714",
    "sg:province":"ID",
    "sg:tags":[
        "appliance"
    ],
    "wof:name":"Able Appliance Repair",
    "wof:placetype":"venue"
},
  "geometry": {"coordinates":[-116.23985399999999,43.630937],"type":"Point"}
}