{
  "type": "Feature",
  "properties": {
    "iso:country":"US",
    "sg:address":"220 E 37th St",
    "sg:city":"Boise",
    "sg:classifiers":[
        {
            "category":"Building & Trades",
            "subcategory":"Electrical",
            "type":"Services"
        },
        {
            "category":"Professional",
            "subcategory":"Business Services",
            "type":"Services"
        }
    ],
    "sg:phone":"+1 208 345 7160",
    "sg:postcode":"83714",
    "sg:province":"ID",
    "sg:tags":[
        "installer",
        "paper",
        "computer",
        "cable",
        "sign"
    ],
    "wof:name":"Springfield Co",
    "wof:placetype":"venue"
},
  "geometry": {"coordinates":[-116.239526,43.627354],"type":"Point"}
}