{
  "type": "Feature",
  "properties": {
    "iso:country":"US",
    "sg:address":"3016 S 1000 E",
    "sg:city":"Hagerman",
    "sg:classifiers":[
        {
            "category":"Wholesale",
            "subcategory":"Non-durable Goods",
            "type":"Manufacturing & Wholesale Goods"
        }
    ],
    "sg:phone":"+1 208 837 6428",
    "sg:postcode":"83332",
    "sg:province":"ID",
    "wof:name":"Creative Candles",
    "wof:placetype":"venue"
},
  "geometry": {"coordinates":[-114.888786,42.767447],"type":"Point"}
}