{
  "type": "Feature",
  "properties": {
    "iso:country":"US",
    "sg:address":"2525 US Hwy 30",
    "sg:city":"Soda Springs",
    "sg:classifiers":[
        {
            "category":"Sports & Exercise",
            "subcategory":"Golf",
            "type":"Entertainment"
        }
    ],
    "sg:phone":"+1 208 547 2204",
    "sg:postcode":"83276",
    "sg:province":"ID",
    "sg:tags":[
        "course"
    ],
    "wof:name":"Oregon Trail Country Club",
    "wof:placetype":"venue"
},
  "geometry": {"coordinates":[-111.634513,42.660085],"type":"Point"}
}