{
  "type": "Feature",
  "properties": {
    "iso:country":"US",
    "sg:address":"180 W 300 S",
    "sg:city":"Burley",
    "sg:classifiers":[
        {
            "category":"Retail",
            "subcategory":"Car Wash",
            "type":"Services"
        }
    ],
    "sg:phone":"+1 208 678 1022",
    "sg:postcode":"83318",
    "sg:province":"ID",
    "sg:tags":[
        "carwash"
    ],
    "wof:name":"Auto Shine",
    "wof:placetype":"venue"
},
  "geometry": {"coordinates":[-113.82921899999999,42.489846],"type":"Point"}
}