{
  "type": "Feature",
  "properties": {
    "iso:country":"US",
    "sg:address":"1000 W Amity Rd",
    "sg:city":"Boise",
    "sg:classifiers":[
        {
            "category":"Wholesale",
            "subcategory":"Hardware",
            "type":"Manufacturing & Wholesale Goods"
        }
    ],
    "sg:phone":"+1 208 342 2677",
    "sg:postcode":"83705",
    "sg:province":"ID",
    "sg:tags":[
        "nut",
        "bolt"
    ],
    "wof:name":"Kowallis & Richards Inc",
    "wof:placetype":"venue"
},
  "geometry": {"coordinates":[-116.19847,43.560472],"type":"Point"}
}