{
  "type": "Feature",
  "properties": {
    "addr:full":"2900 Lawyer Creek Rd Kamiah ID 83536",
    "addr:postcode":"2900;83536",
    "addr:street":"Lawyer Creek Rd",
    "iso:country":"US",
    "sg:address":"2900 Lawyer Creek Rd",
    "sg:city":"Kamiah",
    "sg:classifiers":[
        {
            "category":"Farming",
            "subcategory":"Fish & Marine Products",
            "type":"Manufacturing & Wholesale Goods"
        }
    ],
    "sg:phone":"+1 208 935 0755",
    "sg:postcode":"83536",
    "sg:province":"ID",
    "sg:tags":[
        "preserves",
        "fishing",
        "hunting"
    ],
    "sg:website":"www.flyingbranch.com",
    "wof:name":"Flying B Ranch",
    "wof:placetype":"venue"
},
  "geometry": {"coordinates":[-116.12007199999999,46.213107],"type":"Point"}
}