{
  "type": "Feature",
  "properties": {
    "iso:country":"US",
    "sg:address":"3905 S Indiana Ave",
    "sg:city":"Caldwell",
    "sg:classifiers":[
        {
            "category":"Wholesale",
            "subcategory":"Machinery & Supplies",
            "type":"Manufacturing & Wholesale Goods"
        }
    ],
    "sg:phone":"+1 208 454 1515",
    "sg:postcode":"83605",
    "sg:province":"ID",
    "wof:name":"Pipe Dreams Ldscp & Sprnklr",
    "wof:placetype":"venue"
},
  "geometry": {"coordinates":[-116.673033,43.63509],"type":"Point"}
}