{
  "type": "Feature",
  "properties": {
    "iso:country":"US",
    "sg:address":"404 N Horton St",
    "sg:city":"Nampa",
    "sg:classifiers":[
        {
            "category":"Health Services",
            "subcategory":"Nursing And Care Facility",
            "type":"Services"
        }
    ],
    "sg:phone":"+1 208 466 9292",
    "sg:postcode":"83651",
    "sg:province":"ID",
    "sg:tags":[
        "home",
        "convalescent"
    ],
    "wof:name":"Nampa Care Ctr",
    "wof:placetype":"venue"
},
  "geometry": {"coordinates":[-116.588002,43.588571],"type":"Point"}
}