{
  "type": "Feature",
  "properties": {
    "iso:country":"US",
    "sg:address":"6700 W State St",
    "sg:city":"Boise",
    "sg:classifiers":[
        {
            "category":"Banks & Credit Unions",
            "subcategory":"Bank",
            "type":"Services"
        }
    ],
    "sg:phone":"+1 208 334 7974",
    "sg:postcode":"83714",
    "sg:province":"ID",
    "wof:name":"Key Bank",
    "wof:placetype":"venue"
},
  "geometry": {"coordinates":[-116.268548,43.661733],"type":"Point"}
}