{
  "type": "Feature",
  "properties": {
    "addr:full":"1091 Youmans Ln Moscow ID 83843",
    "addr:housenumber":"1091",
    "addr:postcode":"83843",
    "addr:street":"Youmans Ln",
    "iso:country":"US",
    "sg:address":"1091 Youmans Ln",
    "sg:city":"Moscow",
    "sg:classifiers":[
        {
            "category":"Manufacturing",
            "subcategory":"Lumber",
            "type":"Manufacturing & Wholesale Goods"
        }
    ],
    "sg:phone":"+1 208 882 8337",
    "sg:postcode":"83843",
    "sg:province":"ID",
    "sg:tags":[
        "forestry"
    ],
    "wof:name":"Carolyn R Berman",
    "wof:placetype":"venue"
},
  "geometry": {"coordinates":[-116.97792099999999,46.745751],"type":"Point"}
}