{
  "type": "Feature",
  "properties": {
    "addr:full":"1895 E Star Ln Meridian ID 83642",
    "addr:housenumber":"1895",
    "addr:postcode":"83642",
    "addr:street":"E Star Ln",
    "iso:country":"US",
    "sg:address":"1895 E Star Ln",
    "sg:city":"Meridian",
    "sg:classifiers":[
        {
            "category":"Arts & Performance",
            "subcategory":"Theater",
            "type":"Entertainment"
        }
    ],
    "sg:phone":"+1 208 888 7128",
    "sg:postcode":"83642",
    "sg:province":"ID",
    "sg:tags":[
        "live",
        "music"
    ],
    "wof:name":"Sapphire Productions Mobile DJ",
    "wof:placetype":"venue"
},
  "geometry": {"coordinates":[-116.372456,43.643742],"type":"Point"}
}