{
  "type": "Feature",
  "properties": {
    "addr:full":"2100 Niagara St Idaho Falls ID 83404",
    "addr:housenumber":"2100",
    "addr:postcode":"83404",
    "addr:street":"Niagara St",
    "iso:country":"US",
    "sg:address":"2100 Niagara St",
    "sg:city":"Idaho Falls",
    "sg:classifiers":[
        {
            "category":"Shopping",
            "subcategory":"Gifts & Souvenirs",
            "type":"Retail Goods"
        },
        {
            "category":"Personal",
            "subcategory":"Beauty Salon",
            "type":"Services"
        }
    ],
    "sg:phone":"+1 208 524 0808",
    "sg:postcode":"83404",
    "sg:province":"ID",
    "sg:tags":[
        "shop"
    ],
    "wof:name":"Nature's Path Store",
    "wof:placetype":"venue"
},
  "geometry": {"coordinates":[-111.99232000000001,43.480799],"type":"Point"}
}