{
  "type": "Feature",
  "properties": {
    "addr:full":"1123 Lake St Sandpoint ID 83864",
    "addr:housenumber":"1123",
    "addr:postcode":"83864",
    "addr:street":"Lake St",
    "iso:country":"US",
    "sg:address":"1123 Lake St",
    "sg:city":"Sandpoint",
    "sg:classifiers":[
        {
            "category":"Government",
            "subcategory":"Police Station",
            "type":"Public Place"
        }
    ],
    "sg:phone":"+1 208 265 1482",
    "sg:postcode":"83864",
    "sg:province":"ID",
    "sg:tags":[
        "department"
    ],
    "wof:name":"Sandpoint Police Animal Cntrl",
    "wof:placetype":"venue"
},
  "geometry": {"coordinates":[-116.56276800000001,48.271996],"type":"Point"}
}