{
  "type": "Feature",
  "properties": {
    "addr:full":"1955 Frontage Rd S Wendell ID 83355",
    "addr:housenumber":"1955",
    "addr:postcode":"83355",
    "addr:street":"Frontage Rd",
    "iso:country":"US",
    "sg:address":"1955 Frontage Rd S",
    "sg:city":"Wendell",
    "sg:classifiers":[
        {
            "category":"Restaurant",
            "type":"Food & Drink"
        }
    ],
    "sg:phone":"+1 208 536 6688",
    "sg:postcode":"83355",
    "sg:province":"ID",
    "wof:name":"Farmhouse Restaurant",
    "wof:placetype":"venue"
},
  "geometry": {"coordinates":[-114.70286900000001,42.764317],"type":"Point"}
}