{
  "type": "Feature",
  "properties": {
    "addr:full":"1495 Foote Dr Idaho Falls ID 83402",
    "addr:housenumber":"1495",
    "addr:postcode":"83402",
    "addr:street":"Foote Dr",
    "iso:country":"US",
    "sg:address":"1495 Foote Dr",
    "sg:city":"Idaho Falls",
    "sg:classifiers":[
        {
            "category":"Retail",
            "subcategory":"Auto Rental",
            "type":"Services"
        }
    ],
    "sg:phone":"+1 208 227 0444",
    "sg:postcode":"83402",
    "sg:province":"ID",
    "sg:tags":[
        "renting",
        "automobile"
    ],
    "wof:name":"Thrifty Car Rental",
    "wof:placetype":"venue"
},
  "geometry": {"coordinates":[-112.059078,43.508352],"type":"Point"}
}