{
  "type": "Feature",
  "properties": {
    "iso:country":"US",
    "sg:address":"11315 W 1st St",
    "sg:city":"Star",
    "sg:classifiers":[
        {
            "category":"Professional",
            "subcategory":"Management & Consulting",
            "type":"Services"
        }
    ],
    "sg:phone":"+1 208 286 0649",
    "sg:postcode":"83669",
    "sg:province":"ID",
    "sg:tags":[
        "roofing",
        "consultant"
    ],
    "wof:name":"Independent Wholesale",
    "wof:placetype":"venue"
},
  "geometry": {"coordinates":[-116.49448599999999,43.692842],"type":"Point"}
}