{
  "type": "Feature",
  "properties": {
    "iso:country":"US",
    "sg:address":"909 Saratoga Dr",
    "sg:city":"Boise",
    "sg:phone":"+1 208 344 5343",
    "sg:postcode":"83706",
    "sg:province":"ID",
    "sg:tags":[
        "scale"
    ],
    "wof:name":"Sales-Tech Assoc",
    "wof:placetype":"venue"
},
  "geometry": {"coordinates":[-116.17007700000001,43.565585],"type":"Point"}
}