{
  "type": "Feature",
  "properties": {
    "iso:country":"US",
    "sg:address":"8498 Blue Heaven Ln",
    "sg:city":"Boise",
    "sg:classifiers":[
        {
            "category":"Building & Trades",
            "subcategory":"Construction",
            "type":"Services"
        }
    ],
    "sg:phone":"+1 208 333 8411",
    "sg:postcode":"83716",
    "sg:province":"ID",
    "sg:tags":[
        "contractor"
    ],
    "wof:name":"M & M Drywall",
    "wof:placetype":"venue"
},
  "geometry": {"coordinates":[-116.159514,43.524666],"type":"Point"}
}