{
  "type": "Feature",
  "properties": {
    "addr:full":"6823 Eisenhower St Bonners Ferry ID 83805",
    "addr:housenumber":"6823",
    "addr:postcode":"83805",
    "addr:street":"Eisenhower St",
    "iso:country":"US",
    "sg:address":"6823 Eisenhower St",
    "sg:city":"Bonners Ferry",
    "sg:classifiers":[
        {
            "category":"Retail",
            "subcategory":"Repair Shop",
            "type":"Services"
        }
    ],
    "sg:phone":"+1 208 267 7199",
    "sg:postcode":"83805",
    "sg:province":"ID",
    "sg:tags":[
        "upholsterer"
    ],
    "wof:name":"Davey's Furniture Upholstery",
    "wof:placetype":"venue"
},
  "geometry": {"coordinates":[-116.32944999999999,48.67952],"type":"Point"}
}