{
  "type": "Feature",
  "properties": {
    "iso:country":"US",
    "sg:address":"837 Cleveland St",
    "sg:city":"Idaho Falls",
    "sg:classifiers":[
        {
            "category":"Professional",
            "subcategory":"Art Services",
            "type":"Services"
        }
    ],
    "sg:phone":"+1 208 523 1318",
    "sg:postcode":"83401",
    "sg:province":"ID",
    "sg:tags":[
        "graphic",
        "designer"
    ],
    "wof:name":"Eagle Rock Productions",
    "wof:placetype":"venue"
},
  "geometry": {"coordinates":[-112.016082,43.499692],"type":"Point"}
}