{
  "type": "Feature",
  "properties": {
    "iso:country":"US",
    "sg:address":"1156 W Heron Ave",
    "sg:city":"Hayden",
    "sg:classifiers":[
        {
            "category":"Professional",
            "subcategory":"Business Services",
            "type":"Services"
        }
    ],
    "sg:phone":"+1 208 772 5704",
    "sg:postcode":"83835",
    "sg:province":"ID",
    "wof:name":"Quality Home Inspections",
    "wof:placetype":"venue"
},
  "geometry": {"coordinates":[-116.801644,47.747603],"type":"Point"}
}