{
  "type": "Feature",
  "properties": {
    "iso:country":"US",
    "sg:address":"231 E 5th St",
    "sg:city":"Meridian",
    "sg:classifiers":[
        {
            "category":"Building & Trades",
            "subcategory":"Construction",
            "type":"Services"
        }
    ],
    "sg:phone":"+1 208 888 1220",
    "sg:postcode":"83642",
    "sg:province":"ID",
    "sg:tags":[
        "dry wall",
        "contractor"
    ],
    "wof:name":"SLA Inc",
    "wof:placetype":"venue"
},
  "geometry": {"coordinates":[-116.386107,43.60562],"type":"Point"}
}