{
  "type": "Feature",
  "properties": {
    "addr:full":"4083 E Hwy 36 Preston ID 83263",
    "addr:housenumber":"4083",
    "addr:postcode":"83263",
    "addr:street":"E Hwy 36",
    "iso:country":"US",
    "sg:address":"4083 E Hwy 36",
    "sg:city":"Preston",
    "sg:phone":"+1 208 852 1933",
    "sg:postcode":"83263",
    "sg:province":"ID",
    "sg:tags":[
        "beef",
        "farm",
        "crop",
        "field",
        "cattle",
        "feedlot"
    ],
    "wof:name":"W Hansen",
    "wof:placetype":"venue"
},
  "geometry": {"coordinates":[-111.777081,42.193884],"type":"Point"}
}