{
  "type": "Feature",
  "properties": {
    "iso:country":"US",
    "sg:address":"245 Greensboro Ct",
    "sg:city":"Boise",
    "sg:classifiers":[
        {
            "category":"Building & Trades",
            "subcategory":"Construction",
            "type":"Services"
        }
    ],
    "sg:phone":"+1 208 387 0761",
    "sg:postcode":"83706",
    "sg:province":"ID",
    "sg:tags":[
        "resurfacing",
        "laying",
        "refinishing",
        "floor"
    ],
    "wof:name":"Mason Flooring",
    "wof:placetype":"venue"
},
  "geometry": {"coordinates":[-116.18528499999999,43.572589],"type":"Point"}
}