{
  "type": "Feature",
  "properties": {
    "addr:full":"12870 S 2nd W Idaho Falls ID 83404",
    "addr:housenumber":"12870",
    "addr:postcode":"83404",
    "addr:street":"S 2Nd W",
    "iso:country":"US",
    "sg:address":"12870 S 2nd W",
    "sg:city":"Idaho Falls",
    "sg:classifiers":[
        {
            "category":"Personal",
            "type":"Services"
        }
    ],
    "sg:phone":"+1 208 357 7936",
    "sg:postcode":"83404",
    "sg:province":"ID",
    "wof:name":"Sandees Ladies Fitness & Ntrtn",
    "wof:placetype":"venue"
},
  "geometry": {"coordinates":[-112.03640300000001,43.381461],"type":"Point"}
}