{
  "type": "Feature",
  "properties": {
    "addr:full":"1315 Oakley Ave Burley ID 83318",
    "addr:housenumber":"1315",
    "addr:postcode":"83318",
    "addr:street":"Oakley Ave",
    "iso:country":"US",
    "sg:address":"1315 Oakley Ave",
    "sg:city":"Burley",
    "sg:classifiers":[
        {
            "category":"Real Estate",
            "subcategory":"Real Estate Agent",
            "type":"Services"
        }
    ],
    "sg:phone":"+1 208 678 5777",
    "sg:postcode":"83318",
    "sg:province":"ID",
    "wof:name":"Povlsen Co Realtors Inc",
    "wof:placetype":"venue"
},
  "geometry": {"coordinates":[-113.794496,42.536593],"type":"Point"}
}