{
  "type": "Feature",
  "properties": {
    "addr:full":"3852 S Schilling Loop Post Falls ID 83854",
    "addr:housenumber":"3852",
    "addr:postcode":"83854",
    "addr:street":"S Schilling Loop",
    "iso:country":"US",
    "sg:address":"3852 S Schilling Loop",
    "sg:city":"Post Falls",
    "sg:classifiers":[
        {
            "category":"Professional",
            "subcategory":"Management & Consulting",
            "type":"Services"
        }
    ],
    "sg:phone":"+1 208 773 4649",
    "sg:postcode":"83854",
    "sg:province":"ID",
    "wof:name":"Effective Life Management",
    "wof:placetype":"venue"
},
  "geometry": {"coordinates":[-116.95264299999999,47.687132],"type":"Point"}
}