{
  "type": "Feature",
  "properties": {
    "iso:country":"US",
    "sg:address":"3852 S Schilling Loop",
    "sg:city":"Post Falls",
    "sg:classifiers":[
        {
            "category":"Professional",
            "subcategory":"Management & Consulting",
            "type":"Services"
        }
    ],
    "sg:phone":"+1 208 773 4649",
    "sg:postcode":"83854",
    "sg:province":"ID",
    "wof:name":"Effective Life Management",
    "wof:placetype":"venue"
},
  "geometry": {"coordinates":[-116.952643,47.687132],"type":"Point"}
}