{
  "type": "Feature",
  "properties": {
    "iso:country":"US",
    "sg:address":"1604 G St",
    "sg:city":"Lewiston",
    "sg:classifiers":[
        {
            "category":"Home & Garden",
            "subcategory":"Household Appliances",
            "type":"Retail Goods"
        }
    ],
    "sg:phone":"+1 208 743 7717",
    "sg:postcode":"83501",
    "sg:province":"ID",
    "sg:tags":[
        "cleaners",
        "vacuum"
    ],
    "wof:name":"Mac's Vacs & Sewing",
    "wof:placetype":"venue"
},
  "geometry": {"coordinates":[-117.009579,46.416107],"type":"Point"}
}