{
  "type": "Feature",
  "properties": {
    "iso:country":"US",
    "sg:address":"1165 Cactus Dr",
    "sg:city":"Pocatello",
    "sg:classifiers":[
        {
            "category":"Organizations",
            "subcategory":"Religious Organization",
            "type":"Services"
        }
    ],
    "sg:phone":"+1 208 232 5190",
    "sg:postcode":"83204",
    "sg:province":"ID",
    "wof:name":"Baha'i Faith",
    "wof:placetype":"venue"
},
  "geometry": {"coordinates":[-112.42077999999999,42.824296],"type":"Point"}
}