{
  "type": "Feature",
  "properties": {
    "addr:full":"1404 S Blaine St Moscow ID 83843",
    "addr:housenumber":"1404",
    "addr:postcode":"83843",
    "addr:street":"S Blaine St",
    "iso:country":"US",
    "sg:address":"1404 S Blaine St",
    "sg:city":"Moscow",
    "sg:classifiers":[
        {
            "category":"Cinema",
            "subcategory":"Movie Rental",
            "type":"Entertainment"
        }
    ],
    "sg:phone":"+1 208 882 8639",
    "sg:postcode":"83843",
    "sg:province":"ID",
    "sg:tags":[
        "leasing",
        "video",
        "disc",
        "tape"
    ],
    "wof:name":"Movie Gallery",
    "wof:placetype":"venue"
},
  "geometry": {"coordinates":[-116.98559299999999,46.7219],"type":"Point"}
}