{
  "type": "Feature",
  "properties": {
    "addr:full":"404 N 15th St Coeur D Alene ID 83814",
    "addr:housenumber":"404",
    "addr:postcode":"83814",
    "addr:street":"N 15Th St Coeur D",
    "iso:country":"US",
    "sg:address":"404 N 15th St",
    "sg:city":"Coeur D Alene",
    "sg:classifiers":[
        {
            "category":"Building & Trades",
            "subcategory":"Construction",
            "type":"Services"
        }
    ],
    "sg:phone":"+1 208 755 9175",
    "sg:postcode":"83814",
    "sg:province":"ID",
    "sg:tags":[
        "repairing",
        "remodeling",
        "contractor"
    ],
    "wof:name":"Northern Lakes Construction",
    "wof:placetype":"venue"
},
  "geometry": {"coordinates":[-116.764689,47.676744],"type":"Point"}
}