{
  "type": "Feature",
  "properties": {
    "iso:country":"US",
    "sg:address":"9321 N Government Way",
    "sg:city":"Hayden",
    "sg:classifiers":[
        {
            "category":"Personal",
            "type":"Services"
        }
    ],
    "sg:phone":"+1 208 661 3745",
    "sg:postcode":"83835",
    "sg:province":"ID",
    "sg:tags":[
        "therapist",
        "massage"
    ],
    "wof:name":"A Heavenly Touch Massage",
    "wof:placetype":"venue"
},
  "geometry": {"coordinates":[-116.786677,47.755837],"type":"Point"}
}