{
  "type": "Feature",
  "properties": {
    "iso:country":"US",
    "sg:address":"1710 W Pullman Rd",
    "sg:city":"Moscow",
    "sg:classifiers":[
        {
            "category":"Bars & Pubs",
            "type":"Food & Drink"
        }
    ],
    "sg:menulink":"http://www.allmenus.com/id/moscow/97295-wingers-grill--bar/menu/",
    "sg:phone":"+1 208 882 9797",
    "sg:postcode":"83843",
    "sg:province":"ID",
    "sg:tags":[
        "american"
    ],
    "wof:name":"Winger's Grill & Bar",
    "wof:placetype":"venue"
},
  "geometry": {"coordinates":[-117.026025,46.732574],"type":"Point"}
}