{
  "type": "Feature",
  "properties": {
    "iso:country":"US",
    "sg:address":"1034 E 800 N",
    "sg:city":"Shelley",
    "sg:classifiers":[
        {
            "category":"Shopping",
            "type":"Retail Goods"
        }
    ],
    "sg:phone":"+1 208 346 4356",
    "sg:postcode":"83274",
    "sg:province":"ID",
    "sg:tags":[
        "merchandise"
    ],
    "wof:name":"Brookstone Candle Company",
    "wof:placetype":"venue"
},
  "geometry": {"coordinates":[-112.090656,43.311471],"type":"Point"}
}