{
  "type": "Feature",
  "properties": {
    "iso:country":"US",
    "sg:address":"312 Park Ave",
    "sg:city":"Idaho Falls",
    "sg:classifiers":[
        {
            "category":"Personal",
            "type":"Services"
        },
        {
            "category":"Personal",
            "subcategory":"Tattoo Parlor",
            "type":"Services"
        }
    ],
    "sg:phone":"+1 208 522 8292",
    "sg:postcode":"83402",
    "sg:province":"ID",
    "sg:tags":[
        "tattooing"
    ],
    "wof:name":"Visual Impressions Tattooing",
    "wof:placetype":"venue"
},
  "geometry": {"coordinates":[-112.040736,43.49252],"type":"Point"}
}