{
  "type": "Feature",
  "properties": {
    "iso:country":"US",
    "sg:address":"6397 W Platinum Dr",
    "sg:city":"Coeur D Alene",
    "sg:classifiers":[
        {
            "category":"Building & Trades",
            "subcategory":"Construction",
            "type":"Services"
        }
    ],
    "sg:phone":"+1 208 676 1768",
    "sg:postcode":"83814",
    "sg:province":"ID",
    "sg:tags":[
        "contractor"
    ],
    "wof:name":"Idaho Builders",
    "wof:placetype":"venue"
},
  "geometry": {"coordinates":[-116.867952,47.511258],"type":"Point"}
}