{
  "type": "Feature",
  "properties": {
    "iso:country":"US",
    "sg:address":"625 Lake St",
    "sg:city":"Grangeville",
    "sg:classifiers":[
        {
            "category":"Organizations",
            "subcategory":"Religious Organization",
            "type":"Services"
        }
    ],
    "sg:phone":"+1 208 983 1652",
    "sg:postcode":"83530",
    "sg:province":"ID",
    "sg:tags":[
        "monastery",
        "convent"
    ],
    "wof:name":"Sister Superior",
    "wof:placetype":"venue"
},
  "geometry": {"coordinates":[-116.12805,45.924095],"type":"Point"}
}