{
  "type": "Feature",
  "properties": {
    "iso:country":"US",
    "sg:address":"6190 N Sunshine St",
    "sg:city":"Coeur D Alene",
    "sg:classifiers":[
        {
            "category":"Health Services",
            "subcategory":"Health Practitioner",
            "type":"Services"
        },
        {
            "category":"Personal",
            "subcategory":"Beauty Salon",
            "type":"Services"
        }
    ],
    "sg:phone":"+1 208 762 9855",
    "sg:postcode":"83815",
    "sg:province":"ID",
    "sg:tags":[
        "spa",
        "day"
    ],
    "wof:name":"Rejuvenating You",
    "wof:placetype":"venue"
},
  "geometry": {"coordinates":[-116.790972,47.727926],"type":"Point"}
}