{
  "type": "Feature",
  "properties": {
    "addr:full":"10464 N Government Way Hayden ID 83835",
    "addr:housenumber":"10464",
    "addr:postcode":"83835",
    "addr:street":"N Government Way",
    "iso:country":"US",
    "sg:address":"10464 N Government Way",
    "sg:city":"Hayden",
    "sg:classifiers":[
        {
            "category":"Shopping",
            "subcategory":"Stationery & Office Supplies",
            "type":"Retail Goods"
        }
    ],
    "sg:phone":"+1 208 772 2159",
    "sg:postcode":"83835",
    "sg:province":"ID",
    "sg:tags":[
        "rubber",
        "stamp",
        "plastic"
    ],
    "wof:name":"Rubber Stamp Store",
    "wof:placetype":"venue"
},
  "geometry": {"coordinates":[-116.786399,47.769311],"type":"Point"}
}