{
  "type": "Feature",
  "properties": {
    "iso:country":"US",
    "sg:address":"2938 Tattenham Ave",
    "sg:city":"Boise",
    "sg:classifiers":[
        {
            "category":"Professional",
            "subcategory":"Management & Consulting",
            "type":"Services"
        }
    ],
    "sg:phone":"+1 208 376 5338",
    "sg:postcode":"83713",
    "sg:province":"ID",
    "sg:tags":[
        "business"
    ],
    "wof:name":"Barker 2k Co Technology Consul",
    "wof:placetype":"venue"
},
  "geometry": {"coordinates":[-116.329179,43.631361],"type":"Point"}
}