{
  "type": "Feature",
  "properties": {
    "addr:full":"8216 Colt Dr Boise ID 83709",
    "addr:housenumber":"8216",
    "addr:postcode":"83709",
    "addr:street":"Colt Dr",
    "iso:country":"US",
    "sg:address":"8216 Colt Dr",
    "sg:city":"Boise",
    "sg:classifiers":[
        {
            "category":"Building & Trades",
            "subcategory":"Landscaping Services",
            "type":"Services"
        }
    ],
    "sg:phone":"+1 208 323 8206",
    "sg:postcode":"83709",
    "sg:province":"ID",
    "sg:tags":[
        "lawn",
        "maintenance",
        "grounds"
    ],
    "wof:name":"Barnes' Yards",
    "wof:placetype":"venue"
},
  "geometry": {"coordinates":[-116.28553599999999,43.555883],"type":"Point"}
}