{
  "type": "Feature",
  "properties": {
    "iso:country":"US",
    "sg:address":"760 Warm Springs Ave",
    "sg:city":"Boise",
    "sg:classifiers":[
        {
            "category":"Social Services",
            "type":"Services"
        }
    ],
    "sg:phone":"+1 208 342 3206",
    "sg:postcode":"83712",
    "sg:province":"ID",
    "sg:tags":[
        "counselor",
        "marriage",
        "family"
    ],
    "wof:name":"Boise Psychiatric Clinic",
    "wof:placetype":"venue"
},
  "geometry": {"coordinates":[-116.186998,43.609133],"type":"Point"}
}