{
  "type": "Feature",
  "properties": {
    "iso:country":"US",
    "sg:address":"1420 Little Rock Rd",
    "sg:city":"Emmett",
    "sg:classifiers":[
        {
            "category":"Building & Trades",
            "subcategory":"Landscaping Services",
            "type":"Services"
        }
    ],
    "sg:phone":"+1 208 398 8477",
    "sg:postcode":"83617",
    "sg:province":"ID",
    "sg:tags":[
        "tree"
    ],
    "wof:name":"Tree Maintenance",
    "wof:placetype":"venue"
},
  "geometry": {"coordinates":[-116.694037,43.92339],"type":"Point"}
}