{
  "type": "Feature",
  "properties": {
    "addr:full":"1355 E 19th N Mountain Home ID 83647",
    "addr:housenumber":"1355",
    "addr:postcode":"83647",
    "addr:street":"E 19Th N",
    "iso:country":"US",
    "sg:address":"1355 E 19th N",
    "sg:city":"Mountain Home",
    "sg:classifiers":[
        {
            "category":"Building & Trades",
            "subcategory":"Electrical",
            "type":"Services"
        }
    ],
    "sg:phone":"+1 208 580 2088",
    "sg:postcode":"83647",
    "sg:province":"ID",
    "sg:tags":[
        "electric",
        "contractor"
    ],
    "wof:name":"Lohmeier Electric",
    "wof:placetype":"venue"
},
  "geometry": {"coordinates":[-115.683656,43.151209],"type":"Point"}
}