{
  "type": "Feature",
  "properties": {
    "iso:country":"US",
    "sg:address":"1401 3rd Ave S",
    "sg:city":"Payette",
    "sg:classifiers":[
        {
            "category":"Building & Trades",
            "subcategory":"Construction",
            "type":"Services"
        }
    ],
    "sg:phone":"+1 208 642 4870",
    "sg:postcode":"83661",
    "sg:province":"ID",
    "sg:tags":[
        "concrete",
        "contractor"
    ],
    "wof:name":"Dukes Septic Tanks",
    "wof:placetype":"venue"
},
  "geometry": {"coordinates":[-116.926114,44.0715],"type":"Point"}
}