{
  "type": "Feature",
  "properties": {
    "iso:country":"US",
    "sg:address":"1451 Hartman St",
    "sg:city":"Boise",
    "sg:classifiers":[
        {
            "category":"Professional",
            "subcategory":"Credit Reporting & Collection",
            "type":"Services"
        }
    ],
    "sg:phone":"+1 208 232 7328",
    "sg:postcode":"83704",
    "sg:province":"ID",
    "wof:name":"Pocatello Credit Bureau",
    "wof:placetype":"venue"
},
  "geometry": {"coordinates":[-116.258732,43.618936],"type":"Point"}
}