{
  "type": "Feature",
  "properties": {
    "iso:country":"US",
    "sg:address":"1569 Blue Lakes Blvd N",
    "sg:city":"Twin Falls",
    "sg:classifiers":[
        {
            "category":"Food & Beverages",
            "subcategory":"Groceries & Convenience Stores",
            "type":"Retail Goods"
        }
    ],
    "sg:phone":"+1 208 736 8259",
    "sg:postcode":"83301",
    "sg:province":"ID",
    "sg:tags":[
        "grocer"
    ],
    "wof:name":"Winco Foods",
    "wof:placetype":"venue"
},
  "geometry": {"coordinates":[-114.46020300000001,42.589249],"type":"Point"}
}