{
  "type": "Feature",
  "properties": {
    "iso:country":"US",
    "sg:address":"10909 W Poppy St",
    "sg:city":"Boise",
    "sg:classifiers":[
        {
            "category":"Restaurant",
            "type":"Food & Drink"
        }
    ],
    "sg:phone":"+1 208 322 2492",
    "sg:postcode":"83713",
    "sg:province":"ID",
    "sg:tags":[
        "eating"
    ],
    "wof:name":"Michelles Personal Chef Svc",
    "wof:placetype":"venue"
},
  "geometry": {"coordinates":[-116.318089,43.625627],"type":"Point"}
}