{
  "type": "Feature",
  "properties": {
    "iso:country":"US",
    "sg:address":"200 W Hanley Ave",
    "sg:city":"Coeur D Alene",
    "sg:classifiers":[
        {
            "category":"Shopping",
            "subcategory":"Department Store",
            "type":"Retail Goods"
        }
    ],
    "sg:phone":"+1 208 772 8700",
    "sg:postcode":"83815",
    "sg:province":"ID",
    "wof:name":"Macy's",
    "wof:placetype":"venue"
},
  "geometry": {"coordinates":[-116.788417,47.729844],"type":"Point"}
}