{
  "type": "Feature",
  "properties": {
    "addr:full":"240 N Yellowstone Hwy Rigby ID 83442",
    "addr:housenumber":"240",
    "addr:postcode":"83442",
    "addr:street":"N Yellowstone Hwy",
    "iso:country":"US",
    "sg:address":"240 N Yellowstone Hwy",
    "sg:city":"Rigby",
    "sg:classifiers":[
        {
            "category":"Personal",
            "subcategory":"Beauty Salon",
            "type":"Services"
        }
    ],
    "sg:phone":"+1 208 745 7155",
    "sg:postcode":"83442",
    "sg:province":"ID",
    "sg:tags":[
        "shop"
    ],
    "wof:name":"Cutting Corner",
    "wof:placetype":"venue"
},
  "geometry": {"coordinates":[-111.920106,43.657767],"type":"Point"}
}