{
  "type": "Feature",
  "properties": {
    "addr:full":"12187 Deer Flat Rd Nampa ID 83686",
    "addr:housenumber":"12187",
    "addr:postcode":"83686",
    "addr:street":"Deer Flat Rd",
    "iso:country":"US",
    "sg:address":"12187 Deer Flat Rd",
    "sg:city":"Nampa",
    "sg:classifiers":[
        {
            "category":"Professional",
            "subcategory":"Management & Consulting",
            "type":"Services"
        }
    ],
    "sg:phone":"+1 208 466 1420",
    "sg:postcode":"83686",
    "sg:province":"ID",
    "sg:tags":[
        "education"
    ],
    "wof:name":"Vantage Institute",
    "wof:placetype":"venue"
},
  "geometry": {"coordinates":[-116.63646300000001,43.502797],"type":"Point"}
}