{
  "type": "Feature",
  "properties": {
    "iso:country":"US",
    "sg:address":"2300 E 17th St",
    "sg:city":"Idaho Falls",
    "sg:classifiers":[
        {
            "category":"Professional",
            "subcategory":"Business Services",
            "type":"Services"
        }
    ],
    "sg:phone":"+1 208 529 3663",
    "sg:postcode":"83404",
    "sg:province":"ID",
    "sg:tags":[
        "interior",
        "consultant",
        "design",
        "decorator"
    ],
    "wof:name":"Nook & Cranny",
    "wof:placetype":"venue"
},
  "geometry": {"coordinates":[-111.986155,43.48206],"type":"Point"}
}