{
  "type": "Feature",
  "properties": {
    "iso:country":"US",
    "sg:address":"5220 W Cougar Gulch Rd",
    "sg:city":"Coeur D Alene",
    "sg:classifiers":[
        {
            "category":"Building & Trades",
            "subcategory":"Construction",
            "type":"Services"
        }
    ],
    "sg:phone":"+1 208 664 4171",
    "sg:postcode":"83814",
    "sg:province":"ID",
    "sg:tags":[
        "concrete",
        "contractor"
    ],
    "wof:name":"Vern Reames Contractors",
    "wof:placetype":"venue"
},
  "geometry": {"coordinates":[-116.85457599999999,47.650069],"type":"Point"}
}