{
  "type": "Feature",
  "properties": {
    "iso:country":"US",
    "sg:address":"113 S Garfield Ave",
    "sg:city":"Pocatello",
    "sg:classifiers":[
        {
            "category":"Education",
            "subcategory":"Library",
            "type":"Public Place"
        }
    ],
    "sg:phone":"+1 208 232 1263",
    "sg:postcode":"83204",
    "sg:province":"ID",
    "wof:name":"Pocatello Public Library",
    "wof:placetype":"venue"
},
  "geometry": {"coordinates":[-112.451938,42.860134],"type":"Point"}
}