{
  "type": "Feature",
  "properties": {
    "iso:country":"US",
    "sg:address":"120 S 9th Ave",
    "sg:city":"Caldwell",
    "sg:classifiers":[
        {
            "category":"Social Services",
            "type":"Services"
        }
    ],
    "sg:phone":"+1 208 454 9167",
    "sg:postcode":"83605",
    "sg:province":"ID",
    "sg:tags":[
        "organization",
        "welfare"
    ],
    "wof:name":"Children's Voices Inc",
    "wof:placetype":"venue"
},
  "geometry": {"coordinates":[-116.68617,43.665391],"type":"Point"}
}