{
  "type": "Feature",
  "properties": {
    "iso:country":"US",
    "sg:address":"420 N 5th Ave",
    "sg:city":"Caldwell",
    "sg:classifiers":[
        {
            "category":"Restaurant",
            "type":"Food & Drink"
        }
    ],
    "sg:phone":"+1 208 459 3003",
    "sg:postcode":"83605",
    "sg:province":"ID",
    "wof:name":"Las Enchiladas",
    "wof:placetype":"venue"
},
  "geometry": {"coordinates":[-116.68632100000001,43.671395],"type":"Point"}
}