{
  "type": "Feature",
  "properties": {
    "iso:country":"US",
    "sg:address":"1128 E 1300 N",
    "sg:city":"Shelley",
    "sg:classifiers":[
        {
            "category":"Building & Trades",
            "subcategory":"Plumbing",
            "type":"Services"
        }
    ],
    "sg:phone":"+1 208 357 5777",
    "sg:postcode":"83274",
    "sg:province":"ID",
    "sg:tags":[
        "plumbing",
        "contractor"
    ],
    "wof:name":"Ramrk Plumbing",
    "wof:placetype":"venue"
},
  "geometry": {"coordinates":[-112.058633,43.381362],"type":"Point"}
}