{
  "type": "Feature",
  "properties": {
    "iso:country":"US",
    "sg:address":"220 W 11th St",
    "sg:city":"Burley",
    "sg:classifiers":[
        {
            "category":"Shopping",
            "subcategory":"Books",
            "type":"Retail Goods"
        }
    ],
    "sg:phone":"+1 208 678 2505",
    "sg:postcode":"83318",
    "sg:province":"ID",
    "sg:tags":[
        "dealer"
    ],
    "wof:name":"Book",
    "wof:placetype":"venue"
},
  "geometry": {"coordinates":[-113.79477199999999,42.539473],"type":"Point"}
}