{
  "type": "Feature",
  "properties": {
    "addr:full":"10975 N Airport Rd Hayden ID 83835",
    "addr:housenumber":"10975",
    "addr:postcode":"83835",
    "addr:street":"N Airport Rd",
    "iso:country":"US",
    "sg:address":"10975 N Airport Rd",
    "sg:city":"Hayden",
    "sg:classifiers":[
        {
            "category":"Airport",
            "type":"Transportation"
        }
    ],
    "sg:phone":"+1 208 772 7583",
    "sg:postcode":"83835",
    "sg:province":"ID",
    "sg:tags":[
        "aircraft",
        "maintenance"
    ],
    "wof:name":"Hagadone Jetport",
    "wof:placetype":"venue"
},
  "geometry": {"coordinates":[-116.813733,47.770439],"type":"Point"}
}