{
  "type": "Feature",
  "properties": {
    "iso:country":"US",
    "sg:address":"473 Maple Dr",
    "sg:city":"Rexburg",
    "sg:classifiers":[
        {
            "category":"Professional",
            "subcategory":"Art Services",
            "type":"Services"
        }
    ],
    "sg:phone":"+1 208 356 0024",
    "sg:postcode":"83440",
    "sg:province":"ID",
    "sg:tags":[
        "commercial",
        "design"
    ],
    "wof:name":"Red Beetle Graphics",
    "wof:placetype":"venue"
},
  "geometry": {"coordinates":[-111.770337,43.824634],"type":"Point"}
}