{
  "type": "Feature",
  "properties": {
    "iso:country":"US",
    "sg:address":"5104 War Eagle Rd",
    "sg:city":"Caldwell",
    "sg:classifiers":[
        {
            "category":"Building & Trades",
            "subcategory":"Pest Control",
            "type":"Services"
        }
    ],
    "sg:phone":"+1 208 454 5589",
    "sg:postcode":"83607",
    "sg:province":"ID",
    "wof:name":"Top Gun Pest Control",
    "wof:placetype":"venue"
},
  "geometry": {"coordinates":[-116.64066,43.625147],"type":"Point"}
}