{
  "type": "Feature",
  "properties": {
    "iso:country":"US",
    "sg:address":"315 N Alaska Ave",
    "sg:city":"Caldwell",
    "sg:classifiers":[
        {
            "category":"Professional",
            "type":"Services"
        }
    ],
    "sg:phone":"+1 208 455 1010",
    "sg:postcode":"83605",
    "sg:province":"ID",
    "sg:tags":[
        "establishment"
    ],
    "wof:name":"About Face",
    "wof:placetype":"venue"
},
  "geometry": {"coordinates":[-116.66949700000001,43.671818],"type":"Point"}
}