{
  "type": "Feature",
  "properties": {
    "iso:country":"US",
    "sg:address":"1655 Fairview Ave",
    "sg:city":"Boise",
    "sg:classifiers":[
        {
            "category":"Government",
            "subcategory":"Office",
            "type":"Public Place"
        }
    ],
    "sg:phone":"+1 208 422 3820",
    "sg:postcode":"83702",
    "sg:province":"ID",
    "sg:tags":[
        "national",
        "guard"
    ],
    "wof:name":"Idaho Army National Guard",
    "wof:placetype":"venue"
},
  "geometry": {"coordinates":[-116.21374299999999,43.620456],"type":"Point"}
}