{
  "type": "Feature",
  "properties": {
    "addr:full":"368 E Avalon St Kuna ID 83634",
    "addr:housenumber":"368",
    "addr:postcode":"83634",
    "addr:street":"E Avalon St",
    "iso:country":"US",
    "sg:address":"368 E Avalon St",
    "sg:city":"Kuna",
    "sg:classifiers":[
        {
            "category":"Insurance",
            "subcategory":"Hazard Insurance",
            "type":"Services"
        },
        {
            "category":"Insurance",
            "subcategory":"Insurance Agent",
            "type":"Services"
        },
        {
            "category":"Insurance",
            "subcategory":"Life Insurance",
            "type":"Services"
        },
        {
            "category":"Insurance",
            "subcategory":"Title Insurance",
            "type":"Services"
        }
    ],
    "sg:phone":"+1 208 384 9385",
    "sg:postcode":"83634",
    "sg:province":"ID",
    "sg:tags":[
        "property",
        "casualty",
        "homeowner"
    ],
    "sg:website":"http://www.amfam.com/agentlocator/KAVER2?sourceid=yp9",
    "wof:name":"American Family Insurance- Kerri Avery",
    "wof:placetype":"venue"
},
  "geometry": {"coordinates":[-116.40995599999999,43.488441],"type":"Point"}
}