{
  "type": "Feature",
  "properties": {
    "iso:country":"US",
    "sg:address":"11854 W Flintlock Dr",
    "sg:city":"Boise",
    "sg:classifiers":[
        {
            "category":"Restaurant",
            "type":"Food & Drink"
        }
    ],
    "sg:phone":"+1 208 658 9980",
    "sg:postcode":"83713",
    "sg:province":"ID",
    "sg:tags":[
        "caterer"
    ],
    "wof:name":"Authentic Dutch Oven Catering",
    "wof:placetype":"venue"
},
  "geometry": {"coordinates":[-116.329959,43.636075],"type":"Point"}
}