{
  "type": "Feature",
  "properties": {
    "iso:country":"US",
    "sg:address":"8378 Overland Rd",
    "sg:city":"Boise",
    "sg:classifiers":[
        {
            "category":"Restaurant",
            "type":"Food & Drink"
        }
    ],
    "sg:phone":"+1 208 323 8807",
    "sg:postcode":"83709",
    "sg:province":"ID",
    "wof:name":"Burger King",
    "wof:placetype":"venue"
},
  "geometry": {"coordinates":[-116.28613799999999,43.590329],"type":"Point"}
}