{
  "type": "Feature",
  "properties": {
    "iso:country":"US",
    "sg:address":"1 Airport Ln",
    "sg:city":"Hailey",
    "sg:classifiers":[
        {
            "category":"Airline",
            "type":"Transportation"
        }
    ],
    "sg:phone":"+1 208 788 4494",
    "sg:postcode":"83320",
    "sg:province":"ID",
    "sg:tags":[
        "company"
    ],
    "wof:name":"Skywest Airlines",
    "wof:placetype":"venue"
},
  "geometry": {"coordinates":[-113.944062,43.309273],"type":"Point"}
}