{
  "type": "Feature",
  "properties": {
    "iso:country":"US",
    "sg:address":"101 E Seltice Way",
    "sg:city":"Post Falls",
    "sg:classifiers":[
        {
            "category":"Banks & Credit Unions",
            "subcategory":"Bank",
            "type":"Services"
        }
    ],
    "sg:phone":"+1 208 777 9644",
    "sg:postcode":"83854",
    "sg:province":"ID",
    "sg:tags":[
        "cashing",
        "check"
    ],
    "wof:name":"Quik Cash",
    "wof:placetype":"venue"
},
  "geometry": {"coordinates":[-116.948061,47.715139],"type":"Point"}
}