{
  "type": "Feature",
  "properties": {
    "iso:country":"US",
    "sg:address":"287 Cliff St",
    "sg:city":"Idaho Falls",
    "sg:classifiers":[
        {
            "category":"Shopping",
            "subcategory":"Hobbies, Toys, & Games",
            "type":"Retail Goods"
        }
    ],
    "sg:phone":"+1 208 557 0479",
    "sg:postcode":"83402",
    "sg:province":"ID",
    "sg:tags":[
        "product",
        "ceramic"
    ],
    "wof:name":"Crack'd Pot Ceramics",
    "wof:placetype":"venue"
},
  "geometry": {"coordinates":[-112.041763,43.488823],"type":"Point"}
}