{
  "type": "Feature",
  "properties": {
    "addr:full":"1109 Highview Ln Twin Falls ID 83301",
    "addr:housenumber":"1109",
    "addr:postcode":"83301",
    "addr:street":"Highview Ln",
    "iso:country":"US",
    "sg:address":"1109 Highview Ln",
    "sg:city":"Twin Falls",
    "sg:classifiers":[
        {
            "category":"Insurance",
            "subcategory":"Insurance Agent",
            "type":"Services"
        }
    ],
    "sg:phone":"+1 208 732 5363",
    "sg:postcode":"83301",
    "sg:province":"ID",
    "wof:name":"Peterson Insurance",
    "wof:placetype":"venue"
},
  "geometry": {"coordinates":[-114.44226,42.562615],"type":"Point"}
}