{
  "type": "Feature",
  "properties": {
    "iso:country":"US",
    "sg:address":"11797 W Rader Dr",
    "sg:city":"Boise",
    "sg:classifiers":[
        {
            "category":"Building & Trades",
            "subcategory":"Construction",
            "type":"Services"
        }
    ],
    "sg:phone":"+1 208 322 0374",
    "sg:postcode":"83713",
    "sg:province":"ID",
    "sg:tags":[
        "interior",
        "tile",
        "ceramic"
    ],
    "wof:name":"Dan Hemmer Construction Inc",
    "wof:placetype":"venue"
},
  "geometry": {"coordinates":[-116.32955800000001,43.650317],"type":"Point"}
}