{
  "type": "Feature",
  "properties": {
    "iso:country":"US",
    "sg:address":"1311 12th Ave S",
    "sg:city":"Nampa",
    "sg:classifiers":[
        {
            "category":"Personal",
            "subcategory":"Beauty Salon",
            "type":"Services"
        }
    ],
    "sg:phone":"+1 208 463 7727",
    "sg:postcode":"83651",
    "sg:province":"ID",
    "wof:name":"Charisma & Co Day Spa",
    "wof:placetype":"venue"
},
  "geometry": {"coordinates":[-116.571694,43.569689],"type":"Point"}
}