{
  "type": "Feature",
  "properties": {
    "addr:full":"800 Star Blvd Middleton ID 83644",
    "addr:housenumber":"800",
    "addr:postcode":"83644",
    "addr:street":"Star Blvd",
    "iso:country":"US",
    "sg:address":"800 Star Blvd",
    "sg:city":"Middleton",
    "sg:classifiers":[
        {
            "category":"Retail",
            "subcategory":"Veterinary Services",
            "type":"Services"
        }
    ],
    "sg:phone":"+1 208 585 3041",
    "sg:postcode":"83644",
    "sg:province":"ID",
    "sg:tags":[
        "veterinarian"
    ],
    "wof:name":"Middleton Veterinary Hospital",
    "wof:placetype":"venue"
},
  "geometry": {"coordinates":[-116.609387,43.703038],"type":"Point"}
}