{
  "type": "Feature",
  "properties": {
    "iso:country":"US",
    "sg:address":"35184 US Hwy 95",
    "sg:city":"Athol",
    "sg:classifiers":[
        {
            "category":"Building & Trades",
            "subcategory":"Construction",
            "type":"Services"
        }
    ],
    "sg:phone":"+1 208 683 3138",
    "sg:postcode":"83801",
    "sg:province":"ID",
    "sg:tags":[
        "siding",
        "contractor"
    ],
    "wof:name":"Panhandle Siding LTD",
    "wof:placetype":"venue"
},
  "geometry": {"coordinates":[-116.69832700000001,47.969806],"type":"Point"}
}