{
  "type": "Feature",
  "properties": {
    "iso:country":"US",
    "sg:address":"165 S State St",
    "sg:city":"Rigby",
    "sg:classifiers":[
        {
            "category":"Government",
            "subcategory":"Post Office",
            "type":"Public Place"
        }
    ],
    "sg:phone":"+1 208 745 6792",
    "sg:postcode":"83442",
    "sg:province":"ID",
    "wof:name":"US Post Office",
    "wof:placetype":"venue"
},
  "geometry": {"coordinates":[-111.914866,43.670846],"type":"Point"}
}