{
  "type": "Feature",
  "properties": {
    "iso:country":"US",
    "sg:address":"861 W 150 N",
    "sg:city":"Blackfoot",
    "sg:classifiers":[
        {
            "category":"Farming",
            "subcategory":"Farm & Veterinary Services",
            "type":"Manufacturing & Wholesale Goods"
        }
    ],
    "sg:phone":"+1 208 684 4156",
    "sg:postcode":"83221",
    "sg:province":"ID",
    "sg:tags":[
        "preparation",
        "soil"
    ],
    "wof:name":"Sensenbach Spraying",
    "wof:placetype":"venue"
},
  "geometry": {"coordinates":[-112.472003,43.21893],"type":"Point"}
}