{
  "type": "Feature",
  "properties": {
    "iso:country":"US",
    "sg:address":"121 N Center St",
    "sg:city":"Rexburg",
    "sg:classifiers":[
        {
            "category":"Real Estate",
            "subcategory":"Real Estate Operator",
            "type":"Services"
        }
    ],
    "sg:phone":"+1 208 356 6062",
    "sg:postcode":"83440",
    "sg:province":"ID",
    "sg:tags":[
        "apartment"
    ],
    "wof:name":"Village Community Gardens",
    "wof:placetype":"venue"
},
  "geometry": {"coordinates":[-111.783898,43.828984],"type":"Point"}
}