{
  "type": "Feature",
  "properties": {
    "addr:full":"141 E Carlton Ave Meridian ID 83642",
    "addr:housenumber":"141",
    "addr:postcode":"83642",
    "addr:street":"E Carlton Ave",
    "iso:country":"US",
    "sg:address":"141 E Carlton Ave",
    "sg:city":"Meridian",
    "sg:classifiers":[
        {
            "category":"Restaurant",
            "type":"Food & Drink"
        }
    ],
    "sg:phone":"+1 208 288 1898",
    "sg:postcode":"83642",
    "sg:province":"ID",
    "sg:tags":[
        "shop",
        "coffee"
    ],
    "wof:name":"Library Coffee House",
    "wof:placetype":"venue"
},
  "geometry": {"coordinates":[-116.391147,43.613701],"type":"Point"}
}