{
  "type": "Feature",
  "properties": {
    "iso:country":"US",
    "sg:address":"3610 12th St",
    "sg:city":"Lewiston",
    "sg:classifiers":[
        {
            "category":"Education",
            "subcategory":"School",
            "type":"Public Place"
        }
    ],
    "sg:phone":"+1 208 748 3400",
    "sg:postcode":"83501",
    "sg:province":"ID",
    "wof:name":"Sacajawea Junior High School",
    "wof:placetype":"venue"
},
  "geometry": {"coordinates":[-116.97052499999999,46.371888],"type":"Point"}
}