{
  "type": "Feature",
  "properties": {
    "iso:country":"US",
    "sg:address":"9530 S Powerline Rd",
    "sg:city":"Nampa",
    "sg:classifiers":[
        {
            "category":"Retail",
            "subcategory":"Auto Repair",
            "type":"Services"
        }
    ],
    "sg:phone":"+1 208 463 8055",
    "sg:postcode":"83686",
    "sg:province":"ID",
    "sg:tags":[
        "general"
    ],
    "wof:name":"Ss Auto",
    "wof:placetype":"venue"
},
  "geometry": {"coordinates":[-116.55288400000001,43.511795],"type":"Point"}
}