{
  "type": "Feature",
  "properties": {
    "iso:country":"US",
    "sg:address":"3 Plant Ln",
    "sg:city":"Donnelly",
    "sg:classifiers":[
        {
            "category":"Building & Trades",
            "subcategory":"Construction",
            "type":"Services"
        }
    ],
    "sg:phone":"+1 208 325 8637",
    "sg:postcode":"83615",
    "sg:province":"ID",
    "sg:tags":[
        "water",
        "well",
        "drilling"
    ],
    "wof:name":"Gestrin Well Drilling",
    "wof:placetype":"venue"
},
  "geometry": {"coordinates":[-116.05106000000001,44.691143],"type":"Point"}
}