{
  "type": "Feature",
  "properties": {
    "addr:full":"109 N 3rd Ave Sandpoint ID 83864",
    "addr:housenumber":"109",
    "addr:postcode":"83864",
    "addr:street":"N 3Rd Ave",
    "iso:country":"US",
    "sg:address":"109 N 3rd Ave",
    "sg:city":"Sandpoint",
    "sg:classifiers":[
        {
            "category":"Wholesale",
            "subcategory":"Durable Goods & Equipment",
            "type":"Manufacturing & Wholesale Goods"
        }
    ],
    "sg:phone":"+1 208 265 0247",
    "sg:postcode":"83864",
    "sg:province":"ID",
    "sg:tags":[
        "engineering",
        "supply"
    ],
    "wof:name":"Gii 2",
    "wof:placetype":"venue"
},
  "geometry": {"coordinates":[-116.55036200000001,48.27396],"type":"Point"}
}