{
  "type": "Feature",
  "properties": {
    "iso:country":"US",
    "sg:address":"4359 Colonial Way",
    "sg:city":"Idaho Falls",
    "sg:classifiers":[
        {
            "category":"Building & Trades",
            "subcategory":"Landscaping Services",
            "type":"Services"
        }
    ],
    "sg:phone":"+1 208 552 1550",
    "sg:postcode":"83404",
    "sg:province":"ID",
    "sg:tags":[
        "landscape",
        "contractor"
    ],
    "wof:name":"Gatekeeper Lawn & Landscape",
    "wof:placetype":"venue"
},
  "geometry": {"coordinates":[-112.034116,43.458182],"type":"Point"}
}