{
  "type": "Feature",
  "properties": {
    "iso:country":"US",
    "sg:address":"7615 Ustick Rd",
    "sg:city":"Boise",
    "sg:classifiers":[
        {
            "category":"Real Estate",
            "subcategory":"Developer",
            "type":"Services"
        }
    ],
    "sg:phone":"+1 208 375 1400",
    "sg:postcode":"83704",
    "sg:province":"ID",
    "sg:tags":[
        "mobile",
        "home"
    ],
    "wof:name":"Flying H Trailer Ranch",
    "wof:placetype":"venue"
},
  "geometry": {"coordinates":[-116.275413,43.634009],"type":"Point"}
}