{
  "type": "Feature",
  "properties": {
    "iso:country":"US",
    "sg:address":"11978 W Ustick Rd",
    "sg:city":"Boise",
    "sg:classifiers":[
        {
            "category":"Social Services",
            "subcategory":"Child Care",
            "type":"Services"
        }
    ],
    "sg:phone":"+1 208 323 8900",
    "sg:postcode":"83713",
    "sg:province":"ID",
    "sg:website":"www.newhorizonchildcare.com",
    "wof:name":"New Horizon Child Care",
    "wof:placetype":"venue"
},
  "geometry": {"coordinates":[-116.330563,43.633967],"type":"Point"}
}