{
  "type": "Feature",
  "properties": {
    "iso:country":"US",
    "sg:address":"25 E Main St",
    "sg:city":"Rexburg",
    "sg:classifiers":[
        {
            "category":"Utilities",
            "subcategory":"Electric",
            "type":"Services"
        }
    ],
    "sg:phone":"+1 208 359 4285",
    "sg:postcode":"83440",
    "sg:province":"ID",
    "wof:name":"Utah Power & Light",
    "wof:placetype":"venue"
},
  "geometry": {"coordinates":[-111.783214,43.826135],"type":"Point"}
}