{
  "type": "Feature",
  "properties": {
    "iso:country":"US",
    "sg:address":"1509 Oak St",
    "sg:city":"Sandpoint",
    "sg:classifiers":[
        {
            "category":"Real Estate",
            "subcategory":"Real Estate Operator",
            "type":"Services"
        }
    ],
    "sg:phone":"+1 208 265 8845",
    "sg:postcode":"83864",
    "sg:province":"ID",
    "sg:tags":[
        "apartment"
    ],
    "wof:name":"Oak Street Apartments",
    "wof:placetype":"venue"
},
  "geometry": {"coordinates":[-116.570825,48.27502],"type":"Point"}
}