{
  "type": "Feature",
  "properties": {
    "iso:country":"US",
    "sg:address":"310 E 2nd N",
    "sg:city":"Mountain Home",
    "sg:classifiers":[
        {
            "category":"Real Estate",
            "subcategory":"Real Estate Agent",
            "type":"Services"
        }
    ],
    "sg:phone":"+1 208 587 4471",
    "sg:postcode":"83647",
    "sg:province":"ID",
    "wof:name":"Mountain Home Real Estate Agcy",
    "wof:placetype":"venue"
},
  "geometry": {"coordinates":[-115.691764,43.132881],"type":"Point"}
}