{
  "type": "Feature",
  "properties": {
    "addr:full":"6848 N Government Way Coeur D Alene ID 83815",
    "addr:housenumber":"6848",
    "addr:postcode":"83815",
    "addr:street":"N Government Way",
    "iso:country":"US",
    "sg:address":"6848 N Government Way",
    "sg:city":"Coeur D Alene",
    "sg:classifiers":[
        {
            "category":"Shopping",
            "subcategory":"Department Store",
            "type":"Retail Goods"
        },
        {
            "category":"Shopping",
            "subcategory":"Gifts & Souvenirs",
            "type":"Retail Goods"
        }
    ],
    "sg:phone":"+1 208 762 8147",
    "sg:postcode":"83815",
    "sg:province":"ID",
    "sg:tags":[
        "shop"
    ],
    "wof:name":"Picket Fence",
    "wof:placetype":"venue"
},
  "geometry": {"coordinates":[-116.78667799999999,47.736688],"type":"Point"}
}