{
  "type": "Feature",
  "properties": {
    "iso:country":"US",
    "sg:address":"2323 Juniper Dr",
    "sg:city":"Lewiston",
    "sg:classifiers":[
        {
            "category":"Autos & Motor Vehicles",
            "subcategory":"Automobile Sales",
            "type":"Retail Goods"
        },
        {
            "category":"Autos & Motor Vehicles",
            "subcategory":"Auto Supplies",
            "type":"Retail Goods"
        },
        {
            "category":"Retail",
            "subcategory":"Auto Repair",
            "type":"Services"
        }
    ],
    "sg:phone":"+1 866 801 7225",
    "sg:postcode":"83501",
    "sg:province":"ID",
    "sg:tags":[
        "car",
        "part",
        "used",
        "leasing",
        "new"
    ],
    "sg:website":"http://www.mcclurehonda.com",
    "wof:name":"Mick McClure Honda",
    "wof:placetype":"venue"
},
  "geometry": {"coordinates":[-116.998593,46.402163],"type":"Point"}
}