{
  "type": "Feature",
  "properties": {
    "addr:full":"88 W Commerce Dr Hayden ID 83835",
    "addr:housenumber":"88",
    "addr:postcode":"83835",
    "addr:street":"W Commerce Dr",
    "iso:country":"US",
    "sg:address":"88 W Commerce Dr",
    "sg:city":"Hayden",
    "sg:classifiers":[
        {
            "category":"Wholesale",
            "subcategory":"Seafood",
            "type":"Manufacturing & Wholesale Goods"
        }
    ],
    "sg:phone":"+1 208 772 7707",
    "sg:postcode":"83835",
    "sg:province":"ID",
    "wof:name":"Harbor Crown Seafood Inc",
    "wof:placetype":"venue"
},
  "geometry": {"coordinates":[-116.78928500000001,47.753059],"type":"Point"}
}