{
  "type": "Feature",
  "properties": {
    "iso:country":"US",
    "sg:address":"606 N 5th Ave",
    "sg:city":"Sandpoint",
    "sg:classifiers":[
        {
            "category":"Banks & Credit Unions",
            "subcategory":"Bank",
            "type":"Services"
        }
    ],
    "sg:phone":"+1 208 255 5737",
    "sg:postcode":"83864",
    "sg:province":"ID",
    "sg:tags":[
        "loan"
    ],
    "wof:name":"First Choice Check Advance",
    "wof:placetype":"venue"
},
  "geometry": {"coordinates":[-116.553405,48.279133],"type":"Point"}
}