{
  "type": "Feature",
  "properties": {
    "addr:full":"514 W Jefferson St Boise ID 83702",
    "addr:housenumber":"514",
    "addr:postcode":"83702",
    "addr:street":"W Jefferson St",
    "iso:country":"US",
    "sg:address":"514 W Jefferson St",
    "sg:city":"Boise",
    "sg:classifiers":[
        {
            "category":"Government",
            "subcategory":"Office",
            "type":"Public Place"
        }
    ],
    "sg:phone":"+1 208 284 7473",
    "sg:postcode":"83702",
    "sg:province":"ID",
    "wof:name":"Honorable David Day",
    "wof:placetype":"venue"
},
  "geometry": {"coordinates":[-116.198757,43.616703],"type":"Point"}
}