{
  "type": "Feature",
  "properties": {
    "iso:country":"US",
    "sg:address":"2705 E 17th St",
    "sg:city":"Ammon",
    "sg:classifiers":[
        {
            "category":"Health Services",
            "subcategory":"Nursing And Care Facility",
            "type":"Services"
        }
    ],
    "sg:phone":"+1 208 522 4044",
    "sg:postcode":"83406",
    "sg:province":"ID",
    "sg:tags":[
        "home",
        "convalescent"
    ],
    "wof:name":"Aspen Grove",
    "wof:placetype":"venue"
},
  "geometry": {"coordinates":[-111.980265,43.482153],"type":"Point"}
}