{
  "type": "Feature",
  "properties": {
    "addr:full":"1705 Northwest Blvd Coeur D Alene ID 83814",
    "addr:housenumber":"1705",
    "addr:postcode":"83814",
    "addr:street":"Northwest Blvd",
    "iso:country":"US",
    "sg:address":"1705 Northwest Blvd",
    "sg:city":"Coeur D Alene",
    "sg:classifiers":[
        {
            "category":"Retail",
            "subcategory":"Repair Shop",
            "type":"Services"
        }
    ],
    "sg:phone":"+1 208 676 8420",
    "sg:postcode":"83814",
    "sg:province":"ID",
    "sg:tags":[
        "engine"
    ],
    "wof:name":"Power Equipment Sales",
    "wof:placetype":"venue"
},
  "geometry": {"coordinates":[-116.80132999999999,47.691675],"type":"Point"}
}