{
  "type": "Feature",
  "properties": {
    "iso:country":"US",
    "sg:address":"610 E 42nd St",
    "sg:city":"Boise",
    "sg:classifiers":[
        {
            "category":"Social Services",
            "type":"Services"
        }
    ],
    "sg:phone":"+1 208 321 9157",
    "sg:postcode":"83714",
    "sg:province":"ID",
    "sg:tags":[
        "youth",
        "organization",
        "center"
    ],
    "sg:website":"www.bgclubidaho.org",
    "wof:name":"Boys & Girls Club Of Ada Cty",
    "wof:placetype":"venue"
},
  "geometry": {"coordinates":[-116.245745,43.63513],"type":"Point"}
}