{
  "type": "Feature",
  "properties": {
    "addr:full":"160 Technology Dr Idaho Falls ID 83401",
    "addr:housenumber":"160",
    "addr:postcode":"83401",
    "addr:street":"Technology Dr",
    "iso:country":"US",
    "sg:address":"160 Technology Dr",
    "sg:city":"Idaho Falls",
    "sg:classifiers":[
        {
            "category":"Wholesale",
            "subcategory":"Construction Materials",
            "type":"Manufacturing & Wholesale Goods"
        }
    ],
    "sg:phone":"+1 208 522 0528",
    "sg:postcode":"83401",
    "sg:province":"ID",
    "sg:tags":[
        "building"
    ],
    "wof:name":"Ted Lansing Corp",
    "wof:placetype":"venue"
},
  "geometry": {"coordinates":[-112.032425,43.517538],"type":"Point"}
}