{
  "type": "Feature",
  "properties": {
    "addr:full":"411 6th St E Ketchum ID 83340",
    "addr:housenumber":"411",
    "addr:postcode":"83340",
    "addr:street":"6Th St E",
    "iso:country":"US",
    "sg:address":"411 6th St E",
    "sg:city":"Ketchum",
    "sg:classifiers":[
        {
            "category":"Social Services",
            "type":"Services"
        }
    ],
    "sg:phone":"+1 208 727 6880",
    "sg:postcode":"83340",
    "sg:province":"ID",
    "sg:tags":[
        "information",
        "cancer"
    ],
    "sg:website":"www.cancerconsultants.com",
    "wof:name":"CANCERCONSULTANTS.COM",
    "wof:placetype":"venue"
},
  "geometry": {"coordinates":[-114.365503,43.683037],"type":"Point"}
}