{
  "type": "Feature",
  "properties": {
    "addr:full":"330 E Benton St Pocatello ID 83201",
    "addr:housenumber":"330",
    "addr:postcode":"83201",
    "addr:street":"E Benton St",
    "iso:country":"US",
    "sg:address":"330 E Benton St",
    "sg:city":"Pocatello",
    "sg:classifiers":[
        {
            "category":"Banks & Credit Unions",
            "subcategory":"Bank",
            "type":"Services"
        }
    ],
    "sg:phone":"+1 208 478 4517",
    "sg:postcode":"83201",
    "sg:province":"ID",
    "wof:name":"Zions Bank",
    "wof:placetype":"venue"
},
  "geometry": {"coordinates":[-112.442487,42.862082],"type":"Point"}
}