{
  "type": "Feature",
  "properties": {
    "iso:country":"US",
    "sg:address":"2931 N Linda Vista Ln",
    "sg:city":"Boise",
    "sg:classifiers":[
        {
            "category":"Real Estate",
            "subcategory":"Developer",
            "type":"Services"
        }
    ],
    "sg:phone":"+1 208 378 0451",
    "sg:postcode":"83704",
    "sg:province":"ID",
    "sg:tags":[
        "mobile",
        "home"
    ],
    "wof:name":"Home Acre Village Mfrd Home",
    "wof:placetype":"venue"
},
  "geometry": {"coordinates":[-116.301714,43.631985],"type":"Point"}
}