{
  "type": "Feature",
  "properties": {
    "addr:full":"1516 W Karcher Rd Nampa ID 83651",
    "addr:housenumber":"1516",
    "addr:postcode":"83651",
    "addr:street":"W Karcher Rd",
    "iso:country":"US",
    "sg:address":"1516 W Karcher Rd",
    "sg:city":"Nampa",
    "sg:classifiers":[
        {
            "category":"Retail",
            "subcategory":"Auto Repair",
            "type":"Services"
        }
    ],
    "sg:phone":"+1 208 467 4488",
    "sg:postcode":"83651",
    "sg:province":"ID",
    "sg:tags":[
        "truck"
    ],
    "wof:name":"Karcher Truck Sales & Svc",
    "wof:placetype":"venue"
},
  "geometry": {"coordinates":[-116.600252,43.605062],"type":"Point"}
}