{
  "type": "Feature",
  "properties": {
    "addr:full":"236 N Lieuallen St Moscow ID 83843",
    "addr:housenumber":"236",
    "addr:postcode":"83843",
    "addr:street":"N Lieuallen St",
    "iso:country":"US",
    "sg:address":"236 N Lieuallen St",
    "sg:city":"Moscow",
    "sg:classifiers":[
        {
            "category":"Wholesale",
            "subcategory":"Durable Goods & Equipment",
            "type":"Manufacturing & Wholesale Goods"
        }
    ],
    "sg:phone":"+1 208 882 8648",
    "sg:postcode":"83843",
    "sg:province":"ID",
    "wof:name":"Kretas Collectibles",
    "wof:placetype":"venue"
},
  "geometry": {"coordinates":[-117.007915,46.73465],"type":"Point"}
}