{
  "type": "Feature",
  "properties": {
    "iso:country":"US",
    "sg:address":"464881 Hwy 95",
    "sg:city":"Sagle",
    "sg:classifiers":[
        {
            "category":"Food & Beverages",
            "subcategory":"Meat & Fish",
            "type":"Retail Goods"
        }
    ],
    "sg:phone":"+1 208 265 4647",
    "sg:postcode":"83860",
    "sg:province":"ID",
    "sg:tags":[
        "cutting"
    ],
    "wof:name":"Angus' Custom Cuts",
    "wof:placetype":"venue"
},
  "geometry": {"coordinates":[-116.600049,48.157178],"type":"Point"}
}