{
  "type": "Feature",
  "properties": {
    "iso:country":"US",
    "sg:address":"102 N Main St",
    "sg:city":"Moscow",
    "sg:classifiers":[
        {
            "category":"Health Services",
            "subcategory":"Podiatrist",
            "type":"Services"
        }
    ],
    "sg:phone":"+1 208 882 3513",
    "sg:postcode":"83843",
    "sg:province":"ID",
    "wof:name":"Ronald W Alm DPM",
    "wof:placetype":"venue"
},
  "geometry": {"coordinates":[-117.001296,46.733689],"type":"Point"}
}