{
  "type": "Feature",
  "properties": {
    "addr:full":"1529 S Timesquare Ln Boise ID 83709",
    "addr:housenumber":"1529",
    "addr:postcode":"83709",
    "addr:street":"S Timesquare Ln",
    "iso:country":"US",
    "sg:address":"1529 S Timesquare Ln",
    "sg:city":"Boise",
    "sg:classifiers":[
        {
            "category":"Health Services",
            "subcategory":"Doctor",
            "type":"Services"
        }
    ],
    "sg:phone":"+1 208 343 1981",
    "sg:postcode":"83709",
    "sg:province":"ID",
    "sg:tags":[
        "dentist"
    ],
    "wof:name":"Time Square Dental",
    "wof:placetype":"venue"
},
  "geometry": {"coordinates":[-116.300765,43.590495],"type":"Point"}
}