{
  "type": "Feature",
  "properties": {
    "addr:full":"2550 Overland Ave Burley ID 83318",
    "addr:housenumber":"2550",
    "addr:postcode":"83318",
    "addr:street":"Overland Ave",
    "iso:country":"US",
    "sg:address":"2550 Overland Ave",
    "sg:city":"Burley",
    "sg:classifiers":[
        {
            "category":"Shopping",
            "type":"Retail Goods"
        }
    ],
    "sg:phone":"+1 208 678 5678",
    "sg:postcode":"83318",
    "sg:province":"ID",
    "sg:tags":[
        "pet",
        "shop"
    ],
    "wof:name":"Animal Alley Pets & Supply",
    "wof:placetype":"venue"
},
  "geometry": {"coordinates":[-113.793316,42.52103],"type":"Point"}
}