{
  "type": "Feature",
  "properties": {
    "iso:country":"US",
    "sg:address":"555 Yellowstone Ave",
    "sg:city":"Idaho Falls",
    "sg:classifiers":[
        {
            "category":"Retail",
            "subcategory":"Auto Repair",
            "type":"Services"
        }
    ],
    "sg:phone":"+1 208 522 1566",
    "sg:postcode":"83402",
    "sg:province":"ID",
    "sg:tags":[
        "repairing",
        "automobile"
    ],
    "wof:name":"Oswald Sinclair",
    "wof:placetype":"venue"
},
  "geometry": {"coordinates":[-112.037546,43.493042],"type":"Point"}
}