{
  "type": "Feature",
  "properties": {
    "iso:country":"US",
    "sg:address":"173 W 4th St",
    "sg:city":"Kuna",
    "sg:classifiers":[
        {
            "category":"Shopping",
            "subcategory":"Pharmacy",
            "type":"Retail Goods"
        }
    ],
    "sg:phone":"+1 208 922 1257",
    "sg:postcode":"83634",
    "sg:province":"ID",
    "wof:name":"Vic's Family Pharmacy",
    "wof:placetype":"venue"
},
  "geometry": {"coordinates":[-116.41444799999999,43.491614],"type":"Point"}
}