{
  "type": "Feature",
  "properties": {
    "addr:full":"33361 Island Rd Parma ID 83660",
    "addr:housenumber":"33361",
    "addr:postcode":"83660",
    "addr:street":"Island Rd",
    "iso:country":"US",
    "sg:address":"33361 Island Rd",
    "sg:city":"Parma",
    "sg:classifiers":[
        {
            "category":"Building & Trades",
            "subcategory":"Construction",
            "type":"Services"
        }
    ],
    "sg:phone":"+1 208 722 6449",
    "sg:postcode":"83660",
    "sg:province":"ID",
    "sg:tags":[
        "repairing",
        "remodeling",
        "contractor"
    ],
    "wof:name":"Mary Luna Renovation",
    "wof:placetype":"venue"
},
  "geometry": {"coordinates":[-116.964392,43.857022],"type":"Point"}
}