{
  "type": "Feature",
  "properties": {
    "iso:country":"US",
    "sg:address":"125 W 300 N",
    "sg:city":"Jerome",
    "sg:classifiers":[
        {
            "category":"Building & Trades",
            "subcategory":"Construction",
            "type":"Services"
        }
    ],
    "sg:phone":"+1 208 324 6786",
    "sg:postcode":"83338",
    "sg:province":"ID",
    "sg:tags":[
        "masonry",
        "contractor"
    ],
    "wof:name":"Barry Heck Masonary",
    "wof:placetype":"venue"
},
  "geometry": {"coordinates":[-114.53827699999999,42.767583],"type":"Point"}
}