{
  "type": "Feature",
  "properties": {
    "iso:country":"US",
    "sg:address":"8060 N Cornerstone Dr",
    "sg:city":"Hayden",
    "sg:classifiers":[
        {
            "category":"Banks & Credit Unions",
            "subcategory":"Bank",
            "type":"Services"
        }
    ],
    "sg:phone":"+1 208 762 2760",
    "sg:postcode":"83835",
    "sg:province":"ID",
    "wof:name":"First Bank Northwest",
    "wof:placetype":"venue"
},
  "geometry": {"coordinates":[-116.793493,47.746613],"type":"Point"}
}