{
  "type": "Feature",
  "properties": {
    "iso:country":"US",
    "sg:address":"2105 N 4th St",
    "sg:city":"Coeur D Alene",
    "sg:classifiers":[
        {
            "category":"Autos & Motor Vehicles",
            "subcategory":"Fuel & Gas Station",
            "type":"Retail Goods"
        }
    ],
    "sg:phone":"+1 208 664 5845",
    "sg:postcode":"83814",
    "sg:province":"ID",
    "sg:tags":[
        "oil"
    ],
    "wof:name":"Exxon Jifi Stop",
    "wof:placetype":"venue"
},
  "geometry": {"coordinates":[-116.780776,47.696541],"type":"Point"}
}