{
  "type": "Feature",
  "properties": {
    "addr:full":"7709 W Overland Rd Boise ID 83709",
    "addr:housenumber":"7709",
    "addr:postcode":"83709",
    "addr:street":"W Overland Rd",
    "iso:country":"US",
    "sg:address":"7709 W Overland Rd",
    "sg:city":"Boise",
    "sg:classifiers":[
        {
            "category":"Restaurant",
            "type":"Food & Drink"
        }
    ],
    "sg:menulink":"http://www.allmenus.com/id/boise-city/135831-jamba-juice/menu/",
    "sg:phone":"+1 208 658 1765",
    "sg:postcode":"83709",
    "sg:province":"ID",
    "sg:tags":[
        "smoothy",
        "juice",
        "american"
    ],
    "wof:name":"Jamba Juice",
    "wof:placetype":"venue"
},
  "geometry": {"coordinates":[-116.277841,43.588802],"type":"Point"}
}