{
  "type": "Feature",
  "properties": {
    "iso:country":"US",
    "sg:address":"720 E Industrial Pl",
    "sg:city":"Soda Springs",
    "sg:classifiers":[
        {
            "category":"Manufacturing",
            "subcategory":"Chemicals & Compounds",
            "type":"Manufacturing & Wholesale Goods"
        }
    ],
    "sg:phone":"+1 208 547 3494",
    "sg:postcode":"83276",
    "sg:province":"ID",
    "sg:tags":[
        "fertilizer"
    ],
    "wof:name":"Soda Springs Phosphate 11 LLC",
    "wof:placetype":"venue"
},
  "geometry": {"coordinates":[-111.583361,42.676256],"type":"Point"}
}