{
  "type": "Feature",
  "properties": {
    "addr:full":"580 W 9th S Mountain Home ID 83647",
    "addr:housenumber":"580",
    "addr:postcode":"83647",
    "addr:street":"W 9Th S Mountain",
    "iso:country":"US",
    "sg:address":"580 W 9th S",
    "sg:city":"Mountain Home",
    "sg:classifiers":[
        {
            "category":"Freight",
            "type":"Transportation"
        }
    ],
    "sg:phone":"+1 208 587 9546",
    "sg:postcode":"83647",
    "sg:province":"ID",
    "sg:tags":[
        "operator",
        "local",
        "trucking"
    ],
    "wof:name":"Gaytan Trucking",
    "wof:placetype":"venue"
},
  "geometry": {"coordinates":[-115.699487,43.121901],"type":"Point"}
}