{
  "type": "Feature",
  "properties": {
    "addr:full":"1141 Airport Rd Hailey ID 83335",
    "addr:housenumber":"1141",
    "addr:postcode":"83335",
    "addr:street":"Airport Rd",
    "iso:country":"US",
    "sg:address":"1141 Airport Rd",
    "sg:city":"Hailey",
    "sg:classifiers":[
        {
            "category":"Professional",
            "type":"Services"
        }
    ],
    "sg:phone":"+1 208 788 4220",
    "sg:postcode":"83335",
    "sg:province":"ID",
    "sg:tags":[
        "establishment"
    ],
    "wof:name":"Seclusion Valley LLC",
    "wof:placetype":"venue"
},
  "geometry": {"coordinates":[-114.12825100000001,42.555967],"type":"Point"}
}