{
  "type": "Feature",
  "properties": {
    "iso:country":"US",
    "sg:address":"3920 Bowman Rd",
    "sg:city":"Emmett",
    "sg:classifiers":[
        {
            "category":"Insurance",
            "subcategory":"Hazard Insurance",
            "type":"Services"
        }
    ],
    "sg:phone":"+1 208 365 7788",
    "sg:postcode":"83617",
    "sg:province":"ID",
    "sg:tags":[
        "bond"
    ],
    "wof:name":"K & K Bail Bonds",
    "wof:placetype":"venue"
},
  "geometry": {"coordinates":[-116.62233000000001,43.852993],"type":"Point"}
}