{
  "type": "Feature",
  "properties": {
    "addr:full":"8793 W Lancelot St Boise ID 83704",
    "addr:housenumber":"8793",
    "addr:postcode":"83704",
    "addr:street":"W Lancelot St",
    "iso:country":"US",
    "sg:address":"8793 W Lancelot St",
    "sg:city":"Boise",
    "sg:classifiers":[
        {
            "category":"Wholesale",
            "subcategory":"Groceries",
            "type":"Manufacturing & Wholesale Goods"
        }
    ],
    "sg:phone":"+1 208 375 6132",
    "sg:postcode":"83704",
    "sg:province":"ID",
    "wof:name":"Herbalife Independent Distr",
    "wof:placetype":"venue"
},
  "geometry": {"coordinates":[-116.293284,43.631325],"type":"Point"}
}