{
  "type": "Feature",
  "properties": {
    "iso:country":"US",
    "sg:address":"1113 Winella Dr",
    "sg:city":"Caldwell",
    "sg:classifiers":[
        {
            "category":"Professional",
            "type":"Services"
        }
    ],
    "sg:phone":"+1 208 454 0123",
    "sg:postcode":"83605",
    "sg:province":"ID",
    "sg:tags":[
        "establishment"
    ],
    "wof:name":"Micro Supplements",
    "wof:placetype":"venue"
},
  "geometry": {"coordinates":[-116.66888899999999,43.679088],"type":"Point"}
}