{
  "type": "Feature",
  "properties": {
    "iso:country":"US",
    "sg:address":"9918 Landruff Ln",
    "sg:city":"Middleton",
    "sg:classifiers":[
        {
            "category":"Farming",
            "subcategory":"Farm",
            "type":"Manufacturing & Wholesale Goods"
        }
    ],
    "sg:phone":"+1 208 585 9298",
    "sg:postcode":"83644",
    "sg:province":"ID",
    "sg:tags":[
        "crop",
        "general"
    ],
    "wof:name":"Sea Horse Farms",
    "wof:placetype":"venue"
},
  "geometry": {"coordinates":[-116.587813,43.692118],"type":"Point"}
}