{
  "type": "Feature",
  "properties": {
    "addr:full":"1251 N Five Mile Rd Boise ID 83713",
    "addr:housenumber":"1251",
    "addr:postcode":"83713",
    "addr:street":"N Five Mile Rd",
    "iso:country":"US",
    "sg:address":"1251 N Five Mile Rd",
    "sg:city":"Boise",
    "sg:classifiers":[
        {
            "category":"Insurance",
            "subcategory":"Insurance Agent",
            "type":"Services"
        }
    ],
    "sg:phone":"+1 208 364 8440",
    "sg:postcode":"83713",
    "sg:province":"ID",
    "wof:name":"United Long Term Care Inc",
    "wof:placetype":"venue"
},
  "geometry": {"coordinates":[-116.314369,43.616042],"type":"Point"}
}