{
  "type": "Feature",
  "properties": {
    "iso:country":"US",
    "sg:address":"1102 W Orchard Ave",
    "sg:city":"Nampa",
    "sg:classifiers":[
        {
            "category":"Local Transit",
            "type":"Transportation"
        }
    ],
    "sg:phone":"+1 208 467 3497",
    "sg:postcode":"83651",
    "sg:province":"ID",
    "wof:name":"Kiser Transport",
    "wof:placetype":"venue"
},
  "geometry": {"coordinates":[-116.59759,43.590423],"type":"Point"}
}