{
  "type": "Feature",
  "properties": {
    "iso:country":"US",
    "sg:address":"83 Aspen Way",
    "sg:city":"Kingston",
    "sg:classifiers":[
        {
            "category":"Home & Garden",
            "subcategory":"Household Appliances",
            "type":"Retail Goods"
        }
    ],
    "sg:phone":"+1 208 682 2135",
    "sg:postcode":"83839",
    "sg:province":"ID",
    "sg:tags":[
        "sell",
        "repair"
    ],
    "wof:name":"Dan Kuykendall",
    "wof:placetype":"venue"
},
  "geometry": {"coordinates":[-116.29441300000001,47.548883],"type":"Point"}
}