{
  "type": "Feature",
  "properties": {
    "iso:country":"US",
    "sg:address":"11168 Barden Tower Dr",
    "sg:city":"Boise",
    "sg:classifiers":[
        {
            "category":"Retail",
            "subcategory":"Repair Shop",
            "type":"Services"
        }
    ],
    "sg:phone":"+1 208 377 9093",
    "sg:postcode":"83709",
    "sg:province":"ID",
    "sg:tags":[
        "spa",
        "hot",
        "tub"
    ],
    "wof:name":"Boise Waterworks",
    "wof:placetype":"venue"
},
  "geometry": {"coordinates":[-116.31969700000001,43.598451],"type":"Point"}
}