{
  "type": "Feature",
  "properties": {
    "iso:country":"US",
    "sg:address":"920 Main St",
    "sg:city":"Buhl",
    "sg:classifiers":[
        {
            "category":"Education",
            "subcategory":"School",
            "type":"Public Place"
        }
    ],
    "sg:phone":"+1 208 543 6436",
    "sg:postcode":"83316",
    "sg:province":"ID",
    "wof:name":"Buhl School Superintendent",
    "wof:placetype":"venue"
},
  "geometry": {"coordinates":[-114.758955,42.599581],"type":"Point"}
}