{
  "type": "Feature",
  "properties": {
    "iso:country":"US",
    "sg:address":"350 N Milwaukee St",
    "sg:city":"Boise",
    "sg:classifiers":[
        {
            "category":"Shopping",
            "subcategory":"Musical Instruments",
            "type":"Retail Goods"
        }
    ],
    "sg:phone":"+1 208 376 1286",
    "sg:postcode":"83704",
    "sg:province":"ID",
    "sg:tags":[
        "music",
        "dealer"
    ],
    "wof:name":"Treasure Valley Music",
    "wof:placetype":"venue"
},
  "geometry": {"coordinates":[-116.28222,43.607228],"type":"Point"}
}