{
  "type": "Feature",
  "properties": {
    "iso:country":"US",
    "sg:address":"1526 Vista Ave",
    "sg:city":"Boise",
    "sg:classifiers":[
        {
            "category":"Arts & Performance",
            "subcategory":"Theater",
            "type":"Entertainment"
        }
    ],
    "sg:phone":"+1 208 331 7872",
    "sg:postcode":"83705",
    "sg:province":"ID",
    "sg:tags":[
        "karaoke"
    ],
    "sg:website":"www.karaokesource.com",
    "wof:name":"Center Stage",
    "wof:placetype":"venue"
},
  "geometry": {"coordinates":[-116.213626,43.589901],"type":"Point"}
}