{
  "type": "Feature",
  "properties": {
    "iso:country":"US",
    "sg:address":"101 Park Ln",
    "sg:city":"Eagle",
    "sg:classifiers":[
        {
            "category":"Travel",
            "subcategory":"Campground",
            "type":"Entertainment"
        }
    ],
    "sg:phone":"+1 208 939 0400",
    "sg:postcode":"83616",
    "sg:province":"ID",
    "sg:tags":[
        "camp"
    ],
    "wof:name":"Rick Ranches",
    "wof:placetype":"venue"
},
  "geometry": {"coordinates":[-116.40377700000001,43.695319],"type":"Point"}
}