{
  "type": "Feature",
  "properties": {
    "iso:country":"US",
    "sg:address":"205 N 10th St",
    "sg:city":"Boise",
    "sg:classifiers":[
        {
            "category":"Professional",
            "subcategory":"Accounting & Tax Preparation",
            "type":"Services"
        }
    ],
    "sg:phone":"+1 208 433 1500",
    "sg:postcode":"83702",
    "sg:province":"ID",
    "sg:tags":[
        "accountant"
    ],
    "wof:name":"Severn Winkle & Magette",
    "wof:placetype":"venue"
},
  "geometry": {"coordinates":[-116.204446,43.618362],"type":"Point"}
}