{
  "type": "Feature",
  "properties": {
    "addr:full":"5605 Murphy Rd Kuna ID 83634",
    "addr:housenumber":"5605",
    "addr:postcode":"83634",
    "addr:street":"Murphy Rd",
    "iso:country":"US",
    "sg:address":"5605 Murphy Rd",
    "sg:city":"Kuna",
    "sg:classifiers":[
        {
            "category":"Manufacturing",
            "subcategory":"Chemicals & Compounds",
            "type":"Manufacturing & Wholesale Goods"
        }
    ],
    "sg:phone":"+1 208 466 3891",
    "sg:postcode":"83634",
    "sg:province":"ID",
    "sg:tags":[
        "compost"
    ],
    "wof:name":"Basin Compost",
    "wof:placetype":"venue"
},
  "geometry": {"coordinates":[-116.491174,43.455541],"type":"Point"}
}