{
  "type": "Feature",
  "properties": {
    "addr:full":"26420 US Hwy 2 Sandpoint ID 83864",
    "addr:postcode":"26420;83864",
    "addr:street":"Us Hwy 2",
    "iso:country":"US",
    "sg:address":"26420 US Hwy 2",
    "sg:city":"Sandpoint",
    "sg:classifiers":[
        {
            "category":"Organizations",
            "subcategory":"Religious Organization",
            "type":"Services"
        }
    ],
    "sg:phone":"+1 208 263 0976",
    "sg:postcode":"83864",
    "sg:province":"ID",
    "sg:tags":[
        "church"
    ],
    "wof:name":"Jehovah's Witnesses",
    "wof:placetype":"venue"
},
  "geometry": {"coordinates":[-116.61079599999999,48.252603],"type":"Point"}
}