{
  "type": "Feature",
  "properties": {
    "iso:country":"US",
    "sg:address":"7 Cottonwood Ave",
    "sg:city":"Salmon",
    "sg:classifiers":[
        {
            "category":"Building & Trades",
            "subcategory":"Construction",
            "type":"Services"
        }
    ],
    "sg:phone":"+1 208 756 4826",
    "sg:postcode":"83467",
    "sg:province":"ID",
    "sg:tags":[
        "nonresidential"
    ],
    "wof:name":"Tom Sherman Construction",
    "wof:placetype":"venue"
},
  "geometry": {"coordinates":[-113.897598,45.189408],"type":"Point"}
}