{
  "type": "Feature",
  "properties": {
    "iso:country":"US",
    "sg:address":"8151 Chinden Blvd",
    "sg:city":"Boise",
    "sg:classifiers":[
        {
            "category":"Retail",
            "subcategory":"Auto Rental",
            "type":"Services"
        }
    ],
    "sg:phone":"+1 208 377 2755",
    "sg:postcode":"83714",
    "sg:province":"ID",
    "sg:tags":[
        "renting",
        "truck",
        "leasing"
    ],
    "sg:website":"www.uhaul.com",
    "wof:name":"U-Haul Co",
    "wof:placetype":"venue"
},
  "geometry": {"coordinates":[-116.282752,43.650245],"type":"Point"}
}