{
  "type": "Feature",
  "properties": {
    "addr:full":"302 N Jackson St Moscow ID 83843",
    "addr:housenumber":"302",
    "addr:postcode":"83843",
    "addr:street":"N Jackson St",
    "iso:country":"US",
    "sg:address":"302 N Jackson St",
    "sg:city":"Moscow",
    "sg:classifiers":[
        {
            "category":"Organizations",
            "subcategory":"Labor Organization",
            "type":"Services"
        }
    ],
    "sg:phone":"+1 208 892 3886",
    "sg:postcode":"83843",
    "sg:province":"ID",
    "wof:name":"Pacific Nw Regional Council",
    "wof:placetype":"venue"
},
  "geometry": {"coordinates":[-117.002708,46.735949],"type":"Point"}
}