{
  "type": "Feature",
  "properties": {
    "iso:country":"US",
    "sg:address":"6386 Santa Cruz Dr",
    "sg:city":"Boise",
    "sg:classifiers":[
        {
            "category":"Building & Trades",
            "subcategory":"Construction",
            "type":"Services"
        }
    ],
    "sg:phone":"+1 208 362 0910",
    "sg:postcode":"83709",
    "sg:province":"ID",
    "sg:tags":[
        "hanging",
        "contractor"
    ],
    "wof:name":"Kays Decorating",
    "wof:placetype":"venue"
},
  "geometry": {"coordinates":[-116.33036199999999,43.542551],"type":"Point"}
}