{
  "type": "Feature",
  "properties": {
    "addr:full":"1407 Cedar St Sandpoint ID 83864",
    "addr:housenumber":"1407",
    "addr:postcode":"83864",
    "addr:street":"Cedar St",
    "iso:country":"US",
    "sg:address":"1407 Cedar St",
    "sg:city":"Sandpoint",
    "sg:classifiers":[
        {
            "category":"Education",
            "subcategory":"Library",
            "type":"Public Place"
        }
    ],
    "sg:phone":"+1 208 263 6930",
    "sg:postcode":"83864",
    "sg:province":"ID",
    "sg:website":"www.ebcl.lib.id.us",
    "wof:name":"East Bonner County Library",
    "wof:placetype":"venue"
},
  "geometry": {"coordinates":[-116.569333,48.275935],"type":"Point"}
}