{
  "type": "Feature",
  "properties": {
    "iso:country":"US",
    "sg:address":"2830 N Canyon Creek Rd",
    "sg:city":"Newdale",
    "sg:classifiers":[
        {
            "category":"Farming",
            "subcategory":"Farm",
            "type":"Manufacturing & Wholesale Goods"
        }
    ],
    "sg:phone":"+1 208 458 4361",
    "sg:postcode":"83436",
    "sg:province":"ID",
    "wof:name":"C L Farms",
    "wof:placetype":"venue"
},
  "geometry": {"coordinates":[-111.43817,43.80119],"type":"Point"}
}