{
  "type": "Feature",
  "properties": {
    "addr:full":"6075 E Commerce Loop Post Falls ID 83854",
    "addr:housenumber":"6075",
    "addr:postcode":"83854",
    "addr:street":"E Commerce Loop",
    "iso:country":"US",
    "sg:address":"6075 E Commerce Loop",
    "sg:city":"Post Falls",
    "sg:classifiers":[
        {
            "category":"Building & Trades",
            "subcategory":"Landscaping Services",
            "type":"Services"
        }
    ],
    "sg:phone":"+1 208 667 7511",
    "sg:postcode":"83854",
    "sg:province":"ID",
    "sg:tags":[
        "landscape",
        "contractor"
    ],
    "wof:name":"Aspen Nursery",
    "wof:placetype":"venue"
},
  "geometry": {"coordinates":[-116.864717,47.703544],"type":"Point"}
}