{
  "type": "Feature",
  "properties": {
    "iso:country":"US",
    "sg:address":"2116 12th Ave",
    "sg:city":"Lewiston",
    "sg:classifiers":[
        {
            "category":"Travel",
            "subcategory":"Travel Agent",
            "type":"Entertainment"
        }
    ],
    "sg:phone":"+1 208 746 0407",
    "sg:postcode":"83501",
    "sg:province":"ID",
    "sg:tags":[
        "agency"
    ],
    "sg:website":"http://www.aaawa.com/travel/index.asp",
    "wof:name":"AAA Travel",
    "wof:placetype":"venue"
},
  "geometry": {"coordinates":[-117.001802,46.408312],"type":"Point"}
}