{
  "type": "Feature",
  "properties": {
    "addr:full":"1200 W Ironwood Dr Coeur D Alene ID 83814",
    "addr:housenumber":"1200",
    "addr:postcode":"83814",
    "addr:street":"W Ironwood Dr",
    "iso:country":"US",
    "sg:address":"1200 W Ironwood Dr",
    "sg:city":"Coeur D Alene",
    "sg:classifiers":[
        {
            "category":"Professional",
            "subcategory":"Lawyer & Legal Services",
            "type":"Services"
        }
    ],
    "sg:phone":"+1 208 665 5563",
    "sg:postcode":"83814",
    "sg:province":"ID",
    "wof:name":"Theodore Ponticelli & Assoc",
    "wof:placetype":"venue"
},
  "geometry": {"coordinates":[-116.80051400000001,47.696507],"type":"Point"}
}