{
  "type": "Feature",
  "properties": {
    "addr:full":"15417 Willis Rd Caldwell ID 83607",
    "addr:housenumber":"15417",
    "addr:postcode":"83607",
    "addr:street":"Willis Rd",
    "iso:country":"US",
    "sg:address":"15417 Willis Rd",
    "sg:city":"Caldwell",
    "sg:classifiers":[
        {
            "category":"Professional",
            "subcategory":"Business Services",
            "type":"Services"
        }
    ],
    "sg:phone":"+1 208 455 7663",
    "sg:postcode":"83607",
    "sg:province":"ID",
    "wof:name":"Environmental Solutions Inc",
    "wof:placetype":"venue"
},
  "geometry": {"coordinates":[-116.701262,43.720467],"type":"Point"}
}