{
  "type": "Feature",
  "properties": {
    "addr:full":"1568 W Broadway St Idaho Falls ID 83402",
    "addr:housenumber":"1568",
    "addr:postcode":"83402",
    "addr:street":"W Broadway St",
    "iso:country":"US",
    "sg:address":"1568 W Broadway St",
    "sg:city":"Idaho Falls",
    "sg:classifiers":[
        {
            "category":"Insurance",
            "subcategory":"Insurance Agent",
            "type":"Services"
        }
    ],
    "sg:phone":"+1 208 524 8242",
    "sg:postcode":"83402",
    "sg:province":"ID",
    "wof:name":"Allstate Insurance",
    "wof:placetype":"venue"
},
  "geometry": {"coordinates":[-112.061187,43.496859],"type":"Point"}
}