{
  "type": "Feature",
  "properties": {
    "addr:full":"1310 N Orchard St Boise ID 83706",
    "addr:housenumber":"1310",
    "addr:postcode":"83706",
    "addr:street":"N Orchard St",
    "iso:country":"US",
    "sg:address":"1310 N Orchard St",
    "sg:city":"Boise",
    "sg:classifiers":[
        {
            "category":"Shopping",
            "subcategory":"Photographic Equipment",
            "type":"Retail Goods"
        }
    ],
    "sg:phone":"+1 208 377 3686",
    "sg:postcode":"83706",
    "sg:province":"ID",
    "sg:tags":[
        "supply"
    ],
    "sg:website":"www.idahocamera.com",
    "wof:name":"Idaho Camera",
    "wof:placetype":"venue"
},
  "geometry": {"coordinates":[-116.24350800000001,43.616322],"type":"Point"}
}