{
  "type": "Feature",
  "properties": {
    "addr:full":"7455 S Federal Way Boise ID 83716",
    "addr:housenumber":"7455",
    "addr:postcode":"83716",
    "addr:street":"S Federal Way",
    "iso:country":"US",
    "sg:address":"7455 S Federal Way",
    "sg:city":"Boise",
    "sg:classifiers":[
        {
            "category":"Building & Trades",
            "subcategory":"Construction",
            "type":"Services"
        }
    ],
    "sg:phone":"+1 208 345 1584",
    "sg:postcode":"83716",
    "sg:province":"ID",
    "sg:tags":[
        "retaining",
        "wall"
    ],
    "wof:name":"Mutual Materials Co",
    "wof:placetype":"venue"
},
  "geometry": {"coordinates":[-116.152776,43.535427],"type":"Point"}
}