{
  "type": "Feature",
  "properties": {
    "addr:full":"1301 Kimberly Rd Twin Falls ID 83301",
    "addr:housenumber":"1301",
    "addr:postcode":"83301",
    "addr:street":"Kimberly Rd",
    "iso:country":"US",
    "sg:address":"1301 Kimberly Rd",
    "sg:city":"Twin Falls",
    "sg:classifiers":[
        {
            "category":"Home & Garden",
            "subcategory":"Building Materials",
            "type":"Retail Goods"
        }
    ],
    "sg:phone":"+1 208 736 1915",
    "sg:postcode":"83301",
    "sg:province":"ID",
    "sg:tags":[
        "glass",
        "window",
        "plate"
    ],
    "wof:name":"Safelite Auto Glass",
    "wof:placetype":"venue"
},
  "geometry": {"coordinates":[-114.457707,42.548677],"type":"Point"}
}