{
  "type": "Feature",
  "properties": {
    "addr:full":"1976 S Lincoln Ave Jerome ID 83338",
    "addr:housenumber":"1976",
    "addr:postcode":"83338",
    "addr:street":"S Lincoln Ave",
    "iso:country":"US",
    "sg:address":"1976 S Lincoln Ave",
    "sg:city":"Jerome",
    "sg:classifiers":[
        {
            "category":"Professional",
            "subcategory":"Management & Consulting",
            "type":"Services"
        }
    ],
    "sg:phone":"+1 208 324 1373",
    "sg:postcode":"83338",
    "sg:province":"ID",
    "sg:tags":[
        "consultant",
        "business"
    ],
    "wof:name":"Arc Agriculture Resource",
    "wof:placetype":"venue"
},
  "geometry": {"coordinates":[-114.518396,42.706558],"type":"Point"}
}