{
  "type": "Feature",
  "properties": {
    "addr:full":"118 N Milwaukee St Boise ID 83704",
    "addr:housenumber":"118",
    "addr:postcode":"83704",
    "addr:street":"N Milwaukee St",
    "iso:country":"US",
    "sg:address":"118 N Milwaukee St",
    "sg:city":"Boise",
    "sg:classifiers":[
        {
            "category":"Shopping",
            "subcategory":"Shoes",
            "type":"Retail Goods"
        }
    ],
    "sg:phone":"+1 208 377 4755",
    "sg:postcode":"83704",
    "sg:province":"ID",
    "wof:name":"Red Wing Shoe Store",
    "wof:placetype":"venue"
},
  "geometry": {"coordinates":[-116.28154000000001,43.606496],"type":"Point"}
}