{
  "type": "Feature",
  "properties": {
    "iso:country":"US",
    "sg:address":"1088 E 1500 N",
    "sg:city":"Terreton",
    "sg:classifiers":[
        {
            "category":"Manufacturing",
            "subcategory":"Toys & Sporting Goods",
            "type":"Manufacturing & Wholesale Goods"
        }
    ],
    "sg:phone":"+1 208 663 4459",
    "sg:postcode":"83450",
    "sg:province":"ID",
    "sg:tags":[
        "mfg"
    ],
    "wof:name":"Arts & Crafts",
    "wof:placetype":"venue"
},
  "geometry": {"coordinates":[-112.478711,43.841311],"type":"Point"}
}