{
  "type": "Feature",
  "properties": {
    "addr:full":"414 Caldwell Blvd Nampa ID 83651",
    "addr:housenumber":"414",
    "addr:postcode":"83651",
    "addr:street":"Caldwell Blvd",
    "iso:country":"US",
    "sg:address":"414 Caldwell Blvd",
    "sg:city":"Nampa",
    "sg:classifiers":[
        {
            "category":"Wholesale",
            "subcategory":"Auto Parts",
            "type":"Manufacturing & Wholesale Goods"
        }
    ],
    "sg:phone":"+1 208 461 2400",
    "sg:postcode":"83651",
    "sg:province":"ID",
    "sg:tags":[
        "supply"
    ],
    "wof:name":"Ameraguard Of Treasure Valley",
    "wof:placetype":"venue"
},
  "geometry": {"coordinates":[-116.58223700000001,43.59158],"type":"Point"}
}