{
  "type": "Feature",
  "properties": {
    "iso:country":"US",
    "sg:address":"5927 Old River Rd",
    "sg:city":"Kingston",
    "sg:classifiers":[
        {
            "category":"Travel",
            "subcategory":"Campground",
            "type":"Entertainment"
        }
    ],
    "sg:phone":"+1 208 682 2698",
    "sg:postcode":"83839",
    "sg:province":"ID",
    "wof:name":"Country Lane RV Resort",
    "wof:placetype":"venue"
},
  "geometry": {"coordinates":[-116.202737,47.62466],"type":"Point"}
}