{
  "type": "Feature",
  "properties": {
    "iso:country":"US",
    "sg:address":"20431 N Main St",
    "sg:city":"Carey",
    "sg:classifiers":[
        {
            "category":"Manufacturing",
            "subcategory":"Metals",
            "type":"Manufacturing & Wholesale Goods"
        }
    ],
    "sg:phone":"+1 208 823 4619",
    "sg:postcode":"83320",
    "sg:province":"ID",
    "sg:tags":[
        "foundry"
    ],
    "wof:name":"Sun Valley Bronze Carey Div",
    "wof:placetype":"venue"
},
  "geometry": {"coordinates":[-113.94591,43.306366],"type":"Point"}
}