{
  "type": "Feature",
  "properties": {
    "iso:country":"US",
    "sg:address":"634 Bryden Ave",
    "sg:city":"Lewiston",
    "sg:classifiers":[
        {
            "category":"Professional",
            "subcategory":"Accounting & Tax Preparation",
            "type":"Services"
        }
    ],
    "sg:phone":"+1 208 746 3681",
    "sg:postcode":"83501",
    "sg:province":"ID",
    "sg:tags":[
        "accountant"
    ],
    "wof:name":"Battles & Ells Pa",
    "wof:placetype":"venue"
},
  "geometry": {"coordinates":[-116.999235,46.380462],"type":"Point"}
}