{
  "type": "Feature",
  "properties": {
    "iso:country":"US",
    "sg:address":"2728 S Cole Rd",
    "sg:city":"Boise",
    "sg:classifiers":[
        {
            "category":"Manufacturing",
            "subcategory":"Furniture",
            "type":"Manufacturing & Wholesale Goods"
        }
    ],
    "sg:phone":"+1 208 362 8001",
    "sg:postcode":"83709",
    "sg:province":"ID",
    "sg:website":"www.ad-as.com",
    "wof:name":"Adas",
    "wof:placetype":"venue"
},
  "geometry": {"coordinates":[-116.273983,43.576331],"type":"Point"}
}