{
  "type": "Feature",
  "properties": {
    "addr:full":"1142 N Orchard St Boise ID 83706",
    "addr:housenumber":"1142",
    "addr:postcode":"83706",
    "addr:street":"N Orchard St",
    "iso:country":"US",
    "sg:address":"1142 N Orchard St",
    "sg:city":"Boise",
    "sg:classifiers":[
        {
            "category":"Restaurant",
            "type":"Food & Drink"
        }
    ],
    "sg:phone":"+1 208 336 0191",
    "sg:postcode":"83706",
    "sg:province":"ID",
    "wof:name":"Golden Star Restaurant",
    "wof:placetype":"venue"
},
  "geometry": {"coordinates":[-116.243369,43.614849],"type":"Point"}
}