{
  "type": "Feature",
  "properties": {
    "iso:country":"US",
    "sg:address":"6143 N 17th St",
    "sg:city":"Coeur D Alene",
    "sg:classifiers":[
        {
            "category":"Professional",
            "subcategory":"Computer Services",
            "type":"Services"
        }
    ],
    "sg:phone":"+1 208 762 4039",
    "sg:postcode":"83815",
    "sg:province":"ID",
    "sg:tags":[
        "programing",
        "custom"
    ],
    "wof:name":"Coeur D Escrime Inc",
    "wof:placetype":"venue"
},
  "geometry": {"coordinates":[-116.754386,47.724812],"type":"Point"}
}