{
  "type": "Feature",
  "properties": {
    "iso:country":"US",
    "sg:address":"600 High Circle Rd",
    "sg:city":"Sandpoint",
    "sg:classifiers":[
        {
            "category":"Building & Trades",
            "subcategory":"Electrical",
            "type":"Services"
        }
    ],
    "sg:phone":"+1 208 263 4094",
    "sg:postcode":"83864",
    "sg:province":"ID",
    "sg:tags":[
        "electrical",
        "contractor"
    ],
    "wof:name":"Moutainwood Electric",
    "wof:placetype":"venue"
},
  "geometry": {"coordinates":[-116.72429700000001,48.263841],"type":"Point"}
}