{
  "type": "Feature",
  "properties": {
    "iso:country":"US",
    "sg:address":"224 N 10th St",
    "sg:city":"Boise",
    "sg:classifiers":[
        {
            "category":"Manufacturing",
            "subcategory":"Printing",
            "type":"Manufacturing & Wholesale Goods"
        }
    ],
    "sg:phone":"+1 208 345 4180",
    "sg:postcode":"83702",
    "sg:province":"ID",
    "sg:tags":[
        "printer"
    ],
    "wof:name":"Downtown Printers",
    "wof:placetype":"venue"
},
  "geometry": {"coordinates":[-116.204432,43.61812],"type":"Point"}
}