{
  "type": "Feature",
  "properties": {
    "iso:country":"US",
    "sg:address":"105 Pine St",
    "sg:city":"Sandpoint",
    "sg:classifiers":[
        {
            "category":"Real Estate",
            "subcategory":"Real Estate Agent",
            "type":"Services"
        }
    ],
    "sg:phone":"+1 208 263 9546",
    "sg:postcode":"83864",
    "sg:province":"ID",
    "sg:website":"www.lanakayrealty.com",
    "wof:name":"Lana Kay Realty",
    "wof:placetype":"venue"
},
  "geometry": {"coordinates":[-116.548687,48.27304],"type":"Point"}
}