{
  "type": "Feature",
  "properties": {
    "iso:country":"US",
    "sg:address":"7160 Ash St",
    "sg:city":"Bonners Ferry",
    "sg:classifiers":[
        {
            "category":"Organizations",
            "subcategory":"Religious Organization",
            "type":"Services"
        }
    ],
    "sg:phone":"+1 208 267 2121",
    "sg:postcode":"83805",
    "sg:province":"ID",
    "sg:tags":[
        "church"
    ],
    "wof:name":"Community Fellowship Church",
    "wof:placetype":"venue"
},
  "geometry": {"coordinates":[-116.30846200000001,48.695072],"type":"Point"}
}