{
  "type": "Feature",
  "properties": {
    "addr:full":"230 Meadows Loop Ketchum ID 83340",
    "addr:housenumber":"230",
    "addr:postcode":"83340",
    "addr:street":"Meadows Loop",
    "iso:country":"US",
    "sg:address":"230 Meadows Loop",
    "sg:city":"Ketchum",
    "sg:classifiers":[
        {
            "category":"Personal",
            "subcategory":"Beauty Salon",
            "type":"Services"
        }
    ],
    "sg:phone":"+1 208 725 0708",
    "sg:postcode":"83340",
    "sg:province":"ID",
    "sg:tags":[
        "treatment",
        "skin"
    ],
    "wof:name":"Collettes Custom Skin Care",
    "wof:placetype":"venue"
},
  "geometry": {"coordinates":[-114.35319800000001,43.630685],"type":"Point"}
}