{
  "type": "Feature",
  "properties": {
    "addr:full":"2171 Centurion Pl Boise ID 83709",
    "addr:housenumber":"2171",
    "addr:postcode":"83709",
    "addr:street":"Centurion Pl",
    "iso:country":"US",
    "sg:address":"2171 Centurion Pl",
    "sg:city":"Boise",
    "sg:classifiers":[
        {
            "category":"Building & Trades",
            "subcategory":"Cleaning & Sanitation",
            "type":"Services"
        }
    ],
    "sg:phone":"+1 208 327 0300",
    "sg:postcode":"83709",
    "sg:province":"ID",
    "sg:tags":[
        "janitor"
    ],
    "wof:name":"Service Master Commercial",
    "wof:placetype":"venue"
},
  "geometry": {"coordinates":[-116.271624,43.583859],"type":"Point"}
}