{
  "type": "Feature",
  "properties": {
    "addr:full":"8482 W Marcum Ct Boise ID 83704",
    "addr:housenumber":"8482",
    "addr:postcode":"83704",
    "addr:street":"W Marcum Ct",
    "iso:country":"US",
    "sg:address":"8482 W Marcum Ct",
    "sg:city":"Boise",
    "sg:classifiers":[
        {
            "category":"Professional",
            "subcategory":"Management & Consulting",
            "type":"Services"
        }
    ],
    "sg:phone":"+1 208 658 0052",
    "sg:postcode":"83704",
    "sg:province":"ID",
    "sg:tags":[
        "construction"
    ],
    "wof:name":"Target Construction",
    "wof:placetype":"venue"
},
  "geometry": {"coordinates":[-116.28857000000001,43.629807],"type":"Point"}
}