{
  "type": "Feature",
  "properties": {
    "addr:full":"10496 Purple Sage Rd Middleton ID 83644",
    "addr:housenumber":"10496",
    "addr:postcode":"83644",
    "addr:street":"Purple Sage Rd",
    "iso:country":"US",
    "sg:address":"10496 Purple Sage Rd",
    "sg:city":"Middleton",
    "sg:classifiers":[
        {
            "category":"Farming",
            "subcategory":"Farm",
            "type":"Manufacturing & Wholesale Goods"
        }
    ],
    "sg:phone":"+1 208 585 2277",
    "sg:postcode":"83644",
    "sg:province":"ID",
    "sg:tags":[
        "crop",
        "general"
    ],
    "wof:name":"McEvoy Farms",
    "wof:placetype":"venue"
},
  "geometry": {"coordinates":[-116.602936,43.73553],"type":"Point"}
}