{
  "type": "Feature",
  "properties": {
    "iso:country":"US",
    "sg:address":"476653 Hwy 95",
    "sg:city":"Ponderay",
    "sg:classifiers":[
        {
            "category":"Health Services",
            "subcategory":"Doctor",
            "type":"Services"
        }
    ],
    "sg:phone":"+1 208 265 6771",
    "sg:postcode":"83864",
    "sg:province":"ID",
    "sg:tags":[
        "dentist"
    ],
    "wof:name":"Ponderay Dental",
    "wof:placetype":"venue"
},
  "geometry": {"coordinates":[-116.546122,48.302551],"type":"Point"}
}