{
  "type": "Feature",
  "properties": {
    "addr:full":"335 W Appleway Ave Coeur D Alene ID 83814",
    "addr:housenumber":"335",
    "addr:postcode":"83814",
    "addr:street":"W Appleway Ave",
    "iso:country":"US",
    "sg:address":"335 W Appleway Ave",
    "sg:city":"Coeur D Alene",
    "sg:classifiers":[
        {
            "category":"Shopping",
            "subcategory":"Pharmacy",
            "type":"Retail Goods"
        }
    ],
    "sg:phone":"+1 208 765 1153",
    "sg:postcode":"83814",
    "sg:province":"ID",
    "wof:name":"Walgreens",
    "wof:placetype":"venue"
},
  "geometry": {"coordinates":[-116.791569,47.700748],"type":"Point"}
}