{
  "type": "Feature",
  "properties": {
    "addr:full":"652 N 9th St Boise ID 83702",
    "addr:housenumber":"652",
    "addr:postcode":"83702",
    "addr:street":"N 9Th St",
    "iso:country":"US",
    "sg:address":"652 N 9th St",
    "sg:city":"Boise",
    "sg:classifiers":[
        {
            "category":"Professional",
            "subcategory":"Management & Consulting",
            "type":"Services"
        }
    ],
    "sg:phone":"+1 208 384 0404",
    "sg:postcode":"83702",
    "sg:province":"ID",
    "sg:tags":[
        "international",
        "consultant"
    ],
    "wof:name":"A P Lynch Foreign Svc Corp",
    "wof:placetype":"venue"
},
  "geometry": {"coordinates":[-116.20047099999999,43.620363],"type":"Point"}
}