{
  "type": "Feature",
  "properties": {
    "addr:full":"1010 E 9th S Mountain Home ID 83647",
    "addr:housenumber":"1010",
    "addr:postcode":"83647",
    "addr:street":"E 9Th S Mountain",
    "iso:country":"US",
    "sg:address":"1010 E 9th S",
    "sg:city":"Mountain Home",
    "sg:classifiers":[
        {
            "category":"Freight",
            "type":"Transportation"
        }
    ],
    "sg:phone":"+1 208 587 4308",
    "sg:postcode":"83647",
    "sg:province":"ID",
    "sg:tags":[
        "operator",
        "local",
        "trucking"
    ],
    "wof:name":"Mario Trucking Inc",
    "wof:placetype":"venue"
},
  "geometry": {"coordinates":[-115.68720999999999,43.12302],"type":"Point"}
}