{
  "type": "Feature",
  "properties": {
    "iso:country":"US",
    "sg:address":"6210 Edgewater Dr",
    "sg:city":"Boise",
    "sg:classifiers":[
        {
            "category":"Shopping",
            "subcategory":"Bicycles & Sporting Goods",
            "type":"Retail Goods"
        }
    ],
    "sg:phone":"+1 208 376 2256",
    "sg:postcode":"83709",
    "sg:province":"ID",
    "sg:tags":[
        "small",
        "arms",
        "mfg"
    ],
    "wof:name":"T K Grips & Hobbies",
    "wof:placetype":"venue"
},
  "geometry": {"coordinates":[-116.259669,43.602135],"type":"Point"}
}