{
  "type": "Feature",
  "properties": {
    "iso:country":"US",
    "sg:address":"1000 N 2nd St",
    "sg:city":"Coeur D Alene",
    "sg:classifiers":[
        {
            "category":"Real Estate",
            "subcategory":"Real Estate Agent",
            "type":"Services"
        }
    ],
    "sg:phone":"+1 208 664 7530",
    "sg:postcode":"83814",
    "sg:province":"ID",
    "wof:name":"Windemere Realty",
    "wof:placetype":"venue"
},
  "geometry": {"coordinates":[-116.78376900000001,47.683611],"type":"Point"}
}