{
  "type": "Feature",
  "properties": {
    "iso:country":"US",
    "sg:address":"201 S Juniper Ct",
    "sg:city":"Post Falls",
    "sg:classifiers":[
        {
            "category":"Health Services",
            "subcategory":"Health Practitioner",
            "type":"Services"
        }
    ],
    "sg:phone":"+1 208 773 3352",
    "sg:postcode":"83854",
    "sg:province":"ID",
    "wof:name":"B W Billington PA",
    "wof:placetype":"venue"
},
  "geometry": {"coordinates":[-116.88749799999999,47.703465],"type":"Point"}
}