{
  "type": "Feature",
  "properties": {
    "addr:full":"3790 W State St Boise ID 83703",
    "addr:housenumber":"3790",
    "addr:postcode":"83703",
    "addr:street":"W State St",
    "iso:country":"US",
    "sg:address":"3790 W State St",
    "sg:city":"Boise",
    "sg:classifiers":[
        {
            "category":"Restaurant",
            "type":"Food & Drink"
        }
    ],
    "sg:phone":"+1 208 342 7289",
    "sg:postcode":"83703",
    "sg:province":"ID",
    "wof:name":"Viking Drive In",
    "wof:placetype":"venue"
},
  "geometry": {"coordinates":[-116.236215,43.640645],"type":"Point"}
}