{
  "type": "Feature",
  "properties": {
    "iso:country":"US",
    "sg:address":"6379 Kootenai St",
    "sg:city":"Bonners Ferry",
    "sg:classifiers":[
        {
            "category":"Home & Garden",
            "subcategory":"Hardware",
            "type":"Retail Goods"
        }
    ],
    "sg:phone":"+1 208 267 5213",
    "sg:postcode":"83805",
    "sg:province":"ID",
    "wof:name":"Quality Farm & Garden Ctr",
    "wof:placetype":"venue"
},
  "geometry": {"coordinates":[-116.31314500000001,48.696118],"type":"Point"}
}