{
  "type": "Feature",
  "properties": {
    "addr:full":"2769 Hiawatha Way Twin Falls ID 83301",
    "addr:housenumber":"2769",
    "addr:postcode":"83301",
    "addr:street":"Hiawatha Way",
    "iso:country":"US",
    "sg:address":"2769 Hiawatha Way",
    "sg:city":"Twin Falls",
    "sg:classifiers":[
        {
            "category":"Building & Trades",
            "subcategory":"Construction",
            "type":"Services"
        }
    ],
    "sg:phone":"+1 208 734 3594",
    "sg:postcode":"83301",
    "sg:province":"ID",
    "sg:tags":[
        "general",
        "contractor"
    ],
    "wof:name":"Ken Reed Construction Inc",
    "wof:placetype":"venue"
},
  "geometry": {"coordinates":[-114.426807,42.557186],"type":"Point"}
}