{
  "type": "Feature",
  "properties": {
    "iso:country":"US",
    "sg:address":"415 Main St",
    "sg:city":"Lewiston",
    "sg:classifiers":[
        {
            "category":"Museum",
            "type":"Entertainment"
        }
    ],
    "sg:phone":"+1 208 792 2243",
    "sg:postcode":"83501",
    "sg:province":"ID",
    "wof:name":"Lewis-Clark Ctr For Arts",
    "wof:placetype":"venue"
},
  "geometry": {"coordinates":[-117.028485,46.421645],"type":"Point"}
}