{
  "type": "Feature",
  "properties": {
    "iso:country":"US",
    "sg:address":"315 Stampede Dr",
    "sg:city":"Nampa",
    "sg:classifiers":[
        {
            "category":"Banks & Credit Unions",
            "subcategory":"Bank",
            "type":"Services"
        }
    ],
    "sg:phone":"+1 208 468 5031",
    "sg:postcode":"83687",
    "sg:province":"ID",
    "wof:name":"Home Federal Bank",
    "wof:placetype":"venue"
},
  "geometry": {"coordinates":[-116.54682699999999,43.587761],"type":"Point"}
}