{
  "type": "Feature",
  "properties": {
    "addr:full":"7229 Franklin Rd Boise ID 83709",
    "addr:housenumber":"7229",
    "addr:postcode":"83709",
    "addr:street":"Franklin Rd",
    "iso:country":"US",
    "sg:address":"7229 Franklin Rd",
    "sg:city":"Boise",
    "sg:classifiers":[
        {
            "category":"Health Services",
            "subcategory":"Clinic",
            "type":"Services"
        }
    ],
    "sg:phone":"+1 208 323 9926",
    "sg:postcode":"83709",
    "sg:province":"ID",
    "sg:tags":[
        "hypnotherapy"
    ],
    "wof:name":"New Horizons Hypnosis Ctr",
    "wof:placetype":"venue"
},
  "geometry": {"coordinates":[-116.26824499999999,43.604062],"type":"Point"}
}