{
  "type": "Feature",
  "properties": {
    "iso:country":"US",
    "sg:address":"5906 W Victory Rd",
    "sg:city":"Boise",
    "sg:classifiers":[
        {
            "category":"Building & Trades",
            "subcategory":"Electrical",
            "type":"Services"
        }
    ],
    "sg:phone":"+1 208 362 9061",
    "sg:postcode":"83709",
    "sg:province":"ID",
    "sg:tags":[
        "electric",
        "contractor"
    ],
    "wof:name":"A & B Electric",
    "wof:placetype":"venue"
},
  "geometry": {"coordinates":[-116.25378,43.575399],"type":"Point"}
}