{
  "type": "Feature",
  "properties": {
    "iso:country":"US",
    "sg:address":"21300 US Hwy 30",
    "sg:city":"Twin Falls",
    "sg:classifiers":[
        {
            "category":"Wholesale",
            "subcategory":"Farm Supplies",
            "type":"Manufacturing & Wholesale Goods"
        }
    ],
    "sg:phone":"+1 208 733 4072",
    "sg:postcode":"83301",
    "sg:province":"ID",
    "sg:tags":[
        "fertilizer"
    ],
    "wof:name":"Plant Foods Inc",
    "wof:placetype":"venue"
},
  "geometry": {"coordinates":[-114.555206,42.564046],"type":"Point"}
}