{
  "type": "Feature",
  "properties": {
    "addr:full":"226 E 50 S Malad City ID 83252",
    "addr:housenumber":"226;50",
    "addr:postcode":"83252",
    "addr:street":"E;S Malad",
    "iso:country":"US",
    "sg:address":"226 E 50 S",
    "sg:city":"Malad City",
    "sg:classifiers":[
        {
            "category":"Restaurant",
            "type":"Food & Drink"
        }
    ],
    "sg:phone":"+1 208 766 5455",
    "sg:postcode":"83252",
    "sg:province":"ID",
    "wof:name":"Paula's Goodies & Sandwich Shp",
    "wof:placetype":"venue"
},
  "geometry": {"coordinates":[-112.239711,42.184661],"type":"Point"}
}