{
  "type": "Feature",
  "properties": {
    "iso:country":"US",
    "sg:address":"10715 Cruser Dr",
    "sg:city":"Boise",
    "sg:classifiers":[
        {
            "category":"Building & Trades",
            "subcategory":"Construction",
            "type":"Services"
        }
    ],
    "sg:phone":"+1 208 376 7822",
    "sg:postcode":"83709",
    "sg:province":"ID",
    "sg:tags":[
        "house"
    ],
    "wof:name":"Mark Gerla Construction",
    "wof:placetype":"venue"
},
  "geometry": {"coordinates":[-116.31777200000001,43.603481],"type":"Point"}
}