{
  "type": "Feature",
  "properties": {
    "iso:country":"US",
    "sg:address":"177 S Duke Ave",
    "sg:city":"Eagle",
    "sg:classifiers":[
        {
            "category":"Shopping",
            "subcategory":"Gifts & Souvenirs",
            "type":"Retail Goods"
        }
    ],
    "sg:phone":"+1 208 938 3274",
    "sg:postcode":"83616",
    "sg:province":"ID",
    "wof:name":"Sonas World of Gifts",
    "wof:placetype":"venue"
},
  "geometry": {"coordinates":[-116.336061,43.693214],"type":"Point"}
}