{
  "type": "Feature",
  "properties": {
    "addr:full":"1726 Helen St Boise ID 83705",
    "addr:housenumber":"1726",
    "addr:postcode":"83705",
    "addr:street":"Helen St",
    "iso:country":"US",
    "sg:address":"1726 Helen St",
    "sg:city":"Boise",
    "sg:classifiers":[
        {
            "category":"Home & Garden",
            "subcategory":"Garden Supply",
            "type":"Retail Goods"
        }
    ],
    "sg:phone":"+1 208 345 1753",
    "sg:postcode":"83705",
    "sg:province":"ID",
    "sg:tags":[
        "lawn",
        "mower"
    ],
    "wof:name":"Gem State Small Engine Repair",
    "wof:placetype":"venue"
},
  "geometry": {"coordinates":[-116.211123,43.587671],"type":"Point"}
}