{
  "type": "Feature",
  "properties": {
    "iso:country":"US",
    "sg:address":"2406 S Montana Ave",
    "sg:city":"Caldwell",
    "sg:classifiers":[
        {
            "category":"Autos & Motor Vehicles",
            "subcategory":"Fuel & Gas Station",
            "type":"Retail Goods"
        },
        {
            "category":"Manufacturing",
            "subcategory":"Food",
            "type":"Manufacturing & Wholesale Goods"
        },
        {
            "category":"Food & Beverages",
            "subcategory":"Groceries & Convenience Stores",
            "type":"Retail Goods"
        }
    ],
    "sg:phone":"+1 208 454 1691",
    "sg:postcode":"83605",
    "sg:province":"ID",
    "sg:tags":[
        "product"
    ],
    "wof:name":"Jackson's Food",
    "wof:placetype":"venue"
},
  "geometry": {"coordinates":[-116.683128,43.648885],"type":"Point"}
}