{
  "type": "Feature",
  "properties": {
    "iso:country":"US",
    "sg:address":"1366 John Adams Pkwy",
    "sg:city":"Idaho Falls",
    "sg:classifiers":[
        {
            "category":"Real Estate",
            "subcategory":"Real Estate Agent",
            "type":"Services"
        }
    ],
    "sg:phone":"+1 208 522 9308",
    "sg:postcode":"83401",
    "sg:province":"ID",
    "wof:name":"Henderson Investment Co",
    "wof:placetype":"venue"
},
  "geometry": {"coordinates":[-112.00676199999999,43.492691],"type":"Point"}
}