{
  "type": "Feature",
  "properties": {
    "iso:country":"US",
    "sg:address":"6464 W State St",
    "sg:city":"Boise",
    "sg:classifiers":[
        {
            "category":"Shopping",
            "subcategory":"Used Merchandise",
            "type":"Retail Goods"
        }
    ],
    "sg:phone":"+1 208 853 4921",
    "sg:postcode":"83714",
    "sg:province":"ID",
    "sg:tags":[
        "second",
        "store",
        "hand"
    ],
    "wof:name":"St Vincent Thrift Store",
    "wof:placetype":"venue"
},
  "geometry": {"coordinates":[-116.270048,43.662559],"type":"Point"}
}