{
  "type": "Feature",
  "properties": {
    "addr:full":"609 S Washington St Moscow ID 83843",
    "addr:housenumber":"609",
    "addr:postcode":"83843",
    "addr:street":"S Washington St",
    "iso:country":"US",
    "sg:address":"609 S Washington St",
    "sg:city":"Moscow",
    "sg:classifiers":[
        {
            "category":"Banks & Credit Unions",
            "subcategory":"Bank",
            "type":"Services"
        }
    ],
    "sg:phone":"+1 208 882 6504",
    "sg:postcode":"83843",
    "sg:province":"ID",
    "sg:website":"www.sterlingsavingsbank.com",
    "wof:name":"Sterling Savings Bank",
    "wof:placetype":"venue"
},
  "geometry": {"coordinates":[-117.000024,46.730082],"type":"Point"}
}