{
  "type": "Feature",
  "properties": {
    "iso:country":"US",
    "sg:address":"385 W 100 S",
    "sg:city":"Burley",
    "sg:phone":"+1 208 678 9118",
    "sg:postcode":"83318",
    "sg:province":"ID",
    "sg:tags":[
        "farm",
        "field",
        "crop"
    ],
    "wof:name":"Lynn Hanks",
    "wof:placetype":"venue"
},
  "geometry": {"coordinates":[-113.872187,42.518744],"type":"Point"}
}