{
  "type": "Feature",
  "properties": {
    "iso:country":"US",
    "sg:address":"3500 Garrity Blvd",
    "sg:city":"Nampa",
    "sg:classifiers":[
        {
            "category":"Wholesale",
            "subcategory":"Construction Materials",
            "type":"Manufacturing & Wholesale Goods"
        }
    ],
    "sg:phone":"+1 208 467 4231",
    "sg:postcode":"83687",
    "sg:province":"ID",
    "sg:tags":[
        "concrete",
        "form"
    ],
    "sg:website":"www.acsr.net",
    "wof:name":"American Construction Supply",
    "wof:placetype":"venue"
},
  "geometry": {"coordinates":[-116.529971,43.588447],"type":"Point"}
}