{
  "type": "Feature",
  "properties": {
    "addr:full":"53 N 1250 W Paul ID 83347",
    "addr:housenumber":"53",
    "addr:postcode":"83347",
    "addr:street":"N 1250 W Paul",
    "iso:country":"US",
    "sg:address":"53 N 1250 W",
    "sg:city":"Paul",
    "sg:classifiers":[
        {
            "category":"Building & Trades",
            "subcategory":"Construction",
            "type":"Services"
        }
    ],
    "sg:phone":"+1 208 438 8637",
    "sg:postcode":"83347",
    "sg:province":"ID",
    "sg:tags":[
        "hanging",
        "contractor"
    ],
    "wof:name":"Paintman",
    "wof:placetype":"venue"
},
  "geometry": {"coordinates":[-113.91181,42.633019],"type":"Point"}
}