{
  "type": "Feature",
  "properties": {
    "addr:full":"212 S 4th Ave Caldwell ID 83605",
    "addr:housenumber":"212",
    "addr:postcode":"83605",
    "addr:street":"S 4Th Ave",
    "iso:country":"US",
    "sg:address":"212 S 4th Ave",
    "sg:city":"Caldwell",
    "sg:classifiers":[
        {
            "category":"Local Transit",
            "type":"Transportation"
        }
    ],
    "sg:phone":"+1 208 453 1107",
    "sg:postcode":"83605",
    "sg:province":"ID",
    "sg:tags":[
        "bus",
        "line"
    ],
    "wof:name":"J & P Enterprises",
    "wof:placetype":"venue"
},
  "geometry": {"coordinates":[-116.692824,43.668078],"type":"Point"}
}