{
  "type": "Feature",
  "properties": {
    "iso:country":"US",
    "sg:address":"817 E Washington St",
    "sg:city":"Boise",
    "sg:classifiers":[
        {
            "category":"Utilities",
            "subcategory":"Telephone",
            "type":"Services"
        }
    ],
    "sg:phone":"+1 208 345 6412",
    "sg:postcode":"83712",
    "sg:province":"ID",
    "sg:tags":[
        "communications"
    ],
    "wof:name":"Comlink",
    "wof:placetype":"venue"
},
  "geometry": {"coordinates":[-116.182587,43.611353],"type":"Point"}
}