{
  "type": "Feature",
  "properties": {
    "iso:country":"US",
    "sg:address":"250 Bobwhite Ct",
    "sg:city":"Boise",
    "sg:classifiers":[
        {
            "category":"Professional",
            "subcategory":"Engineering",
            "type":"Services"
        }
    ],
    "sg:phone":"+1 208 389 7848",
    "sg:postcode":"83706",
    "sg:province":"ID",
    "sg:tags":[
        "engineer"
    ],
    "wof:name":"Environmental Co Inc",
    "wof:placetype":"venue"
},
  "geometry": {"coordinates":[-116.185388,43.597593],"type":"Point"}
}