{
  "type": "Feature",
  "properties": {
    "iso:country":"US",
    "sg:address":"1114 2nd St S",
    "sg:city":"Nampa",
    "sg:classifiers":[
        {
            "category":"Shopping",
            "subcategory":"Musical Instruments",
            "type":"Retail Goods"
        }
    ],
    "sg:phone":"+1 208 466 2221",
    "sg:postcode":"83651",
    "sg:province":"ID",
    "wof:name":"Lit'l Mama's Music",
    "wof:placetype":"venue"
},
  "geometry": {"coordinates":[-116.561564,43.578705],"type":"Point"}
}