{
  "type": "Feature",
  "properties": {
    "iso:country":"US",
    "sg:address":"6531 Business Way",
    "sg:city":"Boise",
    "sg:classifiers":[
        {
            "category":"Building & Trades",
            "subcategory":"Construction",
            "type":"Services"
        }
    ],
    "sg:phone":"+1 208 384 0500",
    "sg:postcode":"83716",
    "sg:province":"ID",
    "sg:tags":[
        "concrete",
        "cutting",
        "breaking",
        "sawing"
    ],
    "sg:website":"www.a-core.com",
    "wof:name":"A-Core Of Boise Inc",
    "wof:placetype":"venue"
},
  "geometry": {"coordinates":[-116.179437,43.542133],"type":"Point"}
}