{
  "type": "Feature",
  "properties": {
    "addr:full":"2300 E 17th St Idaho Falls ID 83404",
    "addr:housenumber":"2300",
    "addr:postcode":"83404",
    "addr:street":"E 17Th St",
    "iso:country":"US",
    "sg:address":"2300 E 17th St",
    "sg:city":"Idaho Falls",
    "sg:classifiers":[
        {
            "category":"Shopping",
            "subcategory":"Clothing, Apparel, & Fashions",
            "type":"Retail Goods"
        }
    ],
    "sg:phone":"+1 208 552 6453",
    "sg:postcode":"83404",
    "sg:province":"ID",
    "sg:tags":[
        "sportswear"
    ],
    "sg:website":"www.pacsun.com",
    "wof:name":"Pacific Sunwear",
    "wof:placetype":"venue"
},
  "geometry": {"coordinates":[-111.986155,43.48206],"type":"Point"}
}