{
  "type": "Feature",
  "properties": {
    "addr:full":"419 S Main St Hailey ID 83320",
    "addr:housenumber":"419",
    "addr:postcode":"83320",
    "addr:street":"S Main St",
    "iso:country":"US",
    "sg:address":"419 S Main St",
    "sg:city":"Hailey",
    "sg:classifiers":[
        {
            "category":"Professional",
            "subcategory":"Accounting & Tax Preparation",
            "type":"Services"
        }
    ],
    "sg:phone":"+1 208 788 3805",
    "sg:postcode":"83320",
    "sg:province":"ID",
    "sg:tags":[
        "return",
        "filing"
    ],
    "wof:name":"H & R Block Tax Svc",
    "wof:placetype":"venue"
},
  "geometry": {"coordinates":[-114.313158,43.516538],"type":"Point"}
}