{
  "type": "Feature",
  "properties": {
    "iso:country":"US",
    "sg:address":"16198 Latah Dr",
    "sg:city":"Nampa",
    "sg:classifiers":[
        {
            "category":"Professional",
            "type":"Services"
        }
    ],
    "sg:phone":"+1 208 467 5390",
    "sg:postcode":"83651",
    "sg:province":"ID",
    "wof:name":"Nu Machine",
    "wof:placetype":"venue"
},
  "geometry": {"coordinates":[-116.618697,43.608128],"type":"Point"}
}