{
  "type": "Feature",
  "properties": {
    "iso:country":"US",
    "sg:address":"8701 W Hackamore Dr",
    "sg:city":"Boise",
    "sg:classifiers":[
        {
            "category":"Professional",
            "subcategory":"Engineering",
            "type":"Services"
        }
    ],
    "sg:phone":"+1 208 375 8240",
    "sg:postcode":"83709",
    "sg:province":"ID",
    "sg:tags":[
        "engineer"
    ],
    "sg:website":"www.stapley.net",
    "wof:name":"Stapley Engineering",
    "wof:placetype":"venue"
},
  "geometry": {"coordinates":[-116.290232,43.595047],"type":"Point"}
}