{
  "type": "Feature",
  "properties": {
    "addr:full":"10884 N Yellowstone Hwy Ucon ID 83401",
    "addr:housenumber":"10884",
    "addr:postcode":"83401",
    "addr:street":"N Yellowstone Hwy",
    "iso:country":"US",
    "sg:address":"10884 N Yellowstone Hwy",
    "sg:city":"Ucon",
    "sg:classifiers":[
        {
            "category":"Food & Beverages",
            "subcategory":"Groceries & Convenience Stores",
            "type":"Retail Goods"
        }
    ],
    "sg:phone":"+1 208 524 3773",
    "sg:postcode":"83401",
    "sg:province":"ID",
    "sg:tags":[
        "grocer"
    ],
    "wof:name":"Ucon Market",
    "wof:placetype":"venue"
},
  "geometry": {"coordinates":[-111.963736,43.593381],"type":"Point"}
}