{
  "type": "Feature",
  "properties": {
    "iso:country":"US",
    "sg:address":"477227 Hwy 95",
    "sg:city":"Ponderay",
    "sg:classifiers":[
        {
            "category":"Building & Trades",
            "subcategory":"Construction",
            "type":"Services"
        }
    ],
    "sg:phone":"+1 208 265 1724",
    "sg:postcode":"83864",
    "sg:province":"ID",
    "sg:tags":[
        "masonry",
        "contractor"
    ],
    "wof:name":"Northwest Masonry & Plastering",
    "wof:placetype":"venue"
},
  "geometry": {"coordinates":[-116.54617,48.312944],"type":"Point"}
}