{
  "type": "Feature",
  "properties": {
    "addr:full":"501 W Broadway St Idaho Falls ID 83402",
    "addr:housenumber":"501",
    "addr:postcode":"83402",
    "addr:street":"W Broadway St",
    "iso:country":"US",
    "sg:address":"501 W Broadway St",
    "sg:city":"Idaho Falls",
    "sg:classifiers":[
        {
            "category":"Professional",
            "subcategory":"Engineering",
            "type":"Services"
        }
    ],
    "sg:phone":"+1 208 529 5337",
    "sg:postcode":"83402",
    "sg:province":"ID",
    "sg:tags":[
        "engineer"
    ],
    "wof:name":"Intrepid Engineering Svc Inc",
    "wof:placetype":"venue"
},
  "geometry": {"coordinates":[-112.04371500000001,43.492675],"type":"Point"}
}