{
  "type": "Feature",
  "properties": {
    "addr:full":"264 W Hilgren Ave Hayden Lake ID 83835",
    "addr:housenumber":"264",
    "addr:postcode":"83835",
    "addr:street":"W Hilgren Ave",
    "iso:country":"US",
    "sg:address":"264 W Hilgren Ave",
    "sg:city":"Hayden Lake",
    "sg:classifiers":[
        {
            "category":"Health Services",
            "subcategory":"Nursing And Care Facility",
            "type":"Services"
        }
    ],
    "sg:phone":"+1 208 772 5728",
    "sg:postcode":"83835",
    "sg:province":"ID",
    "sg:tags":[
        "adult"
    ],
    "wof:name":"Autumn Haven",
    "wof:placetype":"venue"
},
  "geometry": {"coordinates":[-116.789823,47.761233],"type":"Point"}
}