{
  "type": "Feature",
  "properties": {
    "addr:full":"935 Lowell Dr Idaho Falls ID 83402",
    "addr:housenumber":"935",
    "addr:postcode":"83402",
    "addr:street":"Lowell Dr",
    "iso:country":"US",
    "sg:address":"935 Lowell Dr",
    "sg:city":"Idaho Falls",
    "sg:classifiers":[
        {
            "category":"Professional",
            "subcategory":"Engineering",
            "type":"Services"
        }
    ],
    "sg:phone":"+1 208 523 2796",
    "sg:postcode":"83402",
    "sg:province":"ID",
    "sg:website":"www.controlsys.com",
    "wof:name":"Control System Technology",
    "wof:placetype":"venue"
},
  "geometry": {"coordinates":[-112.092235,43.48829],"type":"Point"}
}