{
  "type": "Feature",
  "properties": {
    "iso:country":"US",
    "sg:address":"2100 Tammany Creek Rd",
    "sg:city":"Lewiston",
    "sg:classifiers":[
        {
            "category":"Organizations",
            "subcategory":"Professional Association",
            "type":"Services"
        }
    ],
    "sg:phone":"+1 208 746 6324",
    "sg:postcode":"83501",
    "sg:province":"ID",
    "sg:website":"www.lewistonroundup.org",
    "wof:name":"Lewiston Roundup Assn",
    "wof:placetype":"venue"
},
  "geometry": {"coordinates":[-117.029877,46.351603],"type":"Point"}
}