{
  "type": "Feature",
  "properties": {
    "addr:full":"1201 S Kimball Ave Caldwell ID 83605",
    "addr:housenumber":"1201",
    "addr:postcode":"83605",
    "addr:street":"S Kimball Ave",
    "iso:country":"US",
    "sg:address":"1201 S Kimball Ave",
    "sg:city":"Caldwell",
    "sg:classifiers":[
        {
            "category":"Real Estate",
            "subcategory":"Real Estate Agent",
            "type":"Services"
        }
    ],
    "sg:phone":"+1 208 459 2001",
    "sg:postcode":"83605",
    "sg:province":"ID",
    "sg:tags":[
        "investment"
    ],
    "wof:name":"Ralph E Smeed",
    "wof:placetype":"venue"
},
  "geometry": {"coordinates":[-116.695595,43.659734],"type":"Point"}
}