{
  "type": "Feature",
  "properties": {
    "iso:country":"US",
    "sg:address":"11101 Sandhurst Dr",
    "sg:city":"Boise",
    "sg:classifiers":[
        {
            "category":"Building & Trades",
            "subcategory":"Construction",
            "type":"Services"
        }
    ],
    "sg:phone":"+1 208 322 0232",
    "sg:postcode":"83709",
    "sg:province":"ID",
    "sg:tags":[
        "residential",
        "painter"
    ],
    "wof:name":"Dallas Painting",
    "wof:placetype":"venue"
},
  "geometry": {"coordinates":[-116.320373,43.599014],"type":"Point"}
}