{
  "type": "Feature",
  "properties": {
    "iso:country":"US",
    "sg:address":"1255 W Hwy 25",
    "sg:city":"Heyburn",
    "sg:classifiers":[
        {
            "category":"Shopping",
            "type":"Retail Goods"
        }
    ],
    "sg:phone":"+1 208 438 8911",
    "sg:postcode":"83347",
    "sg:province":"ID",
    "sg:tags":[
        "merchandise"
    ],
    "wof:name":"Harrison Ranch Equipment L L C",
    "wof:placetype":"venue"
},
  "geometry": {"coordinates":[-113.913488,42.589872],"type":"Point"}
}