{
  "type": "Feature",
  "properties": {
    "iso:country":"US",
    "sg:address":"221 E Main St",
    "sg:city":"Grangeville",
    "sg:classifiers":[
        {
            "category":"Insurance",
            "subcategory":"Insurance Agent",
            "type":"Services"
        }
    ],
    "sg:phone":"+1 208 983 1983",
    "sg:postcode":"83530",
    "sg:province":"ID",
    "wof:name":"Likkel Insurance Inc",
    "wof:placetype":"venue"
},
  "geometry": {"coordinates":[-116.117885,45.925349],"type":"Point"}
}