{
  "type": "Feature",
  "properties": {
    "iso:country":"US",
    "sg:address":"116 W Bullion St",
    "sg:city":"Hailey",
    "sg:classifiers":[
        {
            "category":"Health Services",
            "subcategory":"Doctor",
            "type":"Services"
        }
    ],
    "sg:phone":"+1 208 788 4507",
    "sg:postcode":"83333",
    "sg:province":"ID",
    "sg:tags":[
        "dentist"
    ],
    "wof:name":"Luke Whalen DDS",
    "wof:placetype":"venue"
},
  "geometry": {"coordinates":[-114.31834499999999,43.518512],"type":"Point"}
}