{
  "type": "Feature",
  "properties": {
    "iso:country":"US",
    "sg:address":"1012 Hemlock Ave",
    "sg:city":"Lewiston",
    "sg:classifiers":[
        {
            "category":"Shopping",
            "type":"Retail Goods"
        }
    ],
    "sg:phone":"+1 208 746 3742",
    "sg:postcode":"83501",
    "sg:province":"ID",
    "sg:tags":[
        "cosmetic",
        "perfume"
    ],
    "wof:name":"Jafra Cosmetics",
    "wof:placetype":"venue"
},
  "geometry": {"coordinates":[-116.980056,46.363975],"type":"Point"}
}