{
  "type": "Feature",
  "properties": {
    "addr:full":"7465 W Happy Hill Rd Coeur D Alene ID 83814",
    "addr:housenumber":"7465",
    "addr:postcode":"83814",
    "addr:street":"W Happy Hill Rd Coeur D",
    "iso:country":"US",
    "sg:address":"7465 W Happy Hill Rd",
    "sg:city":"Coeur D Alene",
    "sg:classifiers":[
        {
            "category":"Banks & Credit Unions",
            "subcategory":"Bank",
            "type":"Services"
        }
    ],
    "sg:phone":"+1 208 667 3833",
    "sg:postcode":"83814",
    "sg:province":"ID",
    "sg:tags":[
        "loan",
        "mortgage",
        "real estate"
    ],
    "wof:name":"Pacific Mortgage Corporation",
    "wof:placetype":"venue"
},
  "geometry": {"coordinates":[-116.887141,47.663575],"type":"Point"}
}