{
  "type": "Feature",
  "properties": {
    "addr:full":"578 W Sly Fox Meridian ID 83642",
    "addr:housenumber":"578",
    "addr:postcode":"83642",
    "addr:street":"W Sly",
    "iso:country":"US",
    "sg:address":"578 W Sly Fox",
    "sg:city":"Meridian",
    "sg:classifiers":[
        {
            "category":"Building & Trades",
            "subcategory":"Construction",
            "type":"Services"
        }
    ],
    "sg:phone":"+1 208 895 8309",
    "sg:postcode":"83642",
    "sg:province":"ID",
    "sg:tags":[
        "house"
    ],
    "wof:name":"Renaissance Homes",
    "wof:placetype":"venue"
},
  "geometry": {"coordinates":[-116.400401,43.665253],"type":"Point"}
}