{
  "type": "Feature",
  "properties": {
    "iso:country":"US",
    "sg:address":"4 Scenic Cir",
    "sg:city":"Lowman",
    "sg:classifiers":[
        {
            "category":"Building & Trades",
            "subcategory":"Construction",
            "type":"Services"
        }
    ],
    "sg:phone":"+1 208 259 3335",
    "sg:postcode":"83637",
    "sg:province":"ID",
    "sg:tags":[
        "general",
        "contractor"
    ],
    "wof:name":"Gene Oaklund Construction Inc",
    "wof:placetype":"venue"
},
  "geometry": {"coordinates":[-115.43481300000001,44.112215],"type":"Point"}
}