{
  "type": "Feature",
  "properties": {
    "iso:country":"US",
    "sg:address":"1565 State Hwy 6",
    "sg:city":"Potlatch",
    "sg:phone":"+1 208 875 0691",
    "sg:postcode":"83855",
    "sg:province":"ID",
    "sg:tags":[
        "farm",
        "field",
        "grain",
        "cash",
        "crop"
    ],
    "wof:name":"Dan Walser",
    "wof:placetype":"venue"
},
  "geometry": {"coordinates":[-116.95047599999999,46.919993],"type":"Point"}
}