{
  "type": "Feature",
  "properties": {
    "iso:country":"US",
    "sg:address":"1260 Jefferson Ave",
    "sg:city":"Idaho Falls",
    "sg:classifiers":[
        {
            "category":"Manufacturing",
            "subcategory":"Tools & Machinery",
            "type":"Manufacturing & Wholesale Goods"
        },
        {
            "category":"Building & Trades",
            "subcategory":"Plumbing",
            "type":"Services"
        }
    ],
    "sg:phone":"+1 208 523 8116",
    "sg:postcode":"83402",
    "sg:province":"ID",
    "sg:tags":[
        "equipment",
        "refrigeration",
        "contractor"
    ],
    "wof:name":"Aire West Refrigeration",
    "wof:placetype":"venue"
},
  "geometry": {"coordinates":[-112.04336000000001,43.510073],"type":"Point"}
}