{
  "type": "Feature",
  "properties": {
    "iso:country":"US",
    "sg:address":"1111 E Lancaster Rd",
    "sg:city":"Hayden",
    "sg:classifiers":[
        {
            "category":"Retail",
            "subcategory":"Animal Services",
            "type":"Services"
        }
    ],
    "sg:phone":"+1 208 762 5238",
    "sg:postcode":"83835",
    "sg:province":"ID",
    "sg:tags":[
        "breeder",
        "horse"
    ],
    "wof:name":"Bridle Path Quarter Horses",
    "wof:placetype":"venue"
},
  "geometry": {"coordinates":[-116.77218,47.788023],"type":"Point"}
}