{
  "type": "Feature",
  "properties": {
    "iso:country":"US",
    "sg:address":"5602 W Fairview Ave",
    "sg:city":"Boise",
    "sg:classifiers":[
        {
            "category":"Deli",
            "type":"Food & Drink"
        }
    ],
    "sg:menulink":"http://www.allmenus.com/id/boise-city/3613-deli-george!/menu/",
    "sg:phone":"+1 208 323 2582",
    "sg:postcode":"83706",
    "sg:province":"ID",
    "sg:tags":[
        "american"
    ],
    "wof:name":"Deli George!",
    "wof:placetype":"venue"
},
  "geometry": {"coordinates":[-116.25116800000001,43.619003],"type":"Point"}
}