{
  "type": "Feature",
  "properties": {
    "iso:country":"US",
    "sg:address":"1020 Main St",
    "sg:city":"Buhl",
    "sg:classifiers":[
        {
            "category":"Professional",
            "subcategory":"Accounting & Tax Preparation",
            "type":"Services"
        }
    ],
    "sg:phone":"+1 208 543 6491",
    "sg:postcode":"83316",
    "sg:province":"ID",
    "sg:tags":[
        "accountant"
    ],
    "wof:name":"Deagle Ames & Co",
    "wof:placetype":"venue"
},
  "geometry": {"coordinates":[-114.75989199999999,42.598879],"type":"Point"}
}