{
  "type": "Feature",
  "properties": {
    "iso:country":"US",
    "sg:address":"4470 N 25th E",
    "sg:city":"Idaho Falls",
    "sg:classifiers":[
        {
            "category":"Building & Trades",
            "subcategory":"Construction",
            "type":"Services"
        }
    ],
    "sg:phone":"+1 208 522 6248",
    "sg:postcode":"83401",
    "sg:province":"ID",
    "sg:tags":[
        "excavating",
        "contractor"
    ],
    "wof:name":"Clay Excavation Inc",
    "wof:placetype":"venue"
},
  "geometry": {"coordinates":[-111.983819,43.53437],"type":"Point"}
}