{
  "type": "Feature",
  "properties": {
    "iso:country":"US",
    "sg:address":"3646 N 2100 E",
    "sg:city":"Filer",
    "sg:phone":"+1 208 326 3346",
    "sg:postcode":"83328",
    "sg:province":"ID",
    "sg:tags":[
        "farm",
        "grain",
        "wheat",
        "cash"
    ],
    "wof:name":"Robert Kohntopp",
    "wof:placetype":"venue"
},
  "geometry": {"coordinates":[-114.63330999999999,42.527177],"type":"Point"}
}