{
  "type": "Feature",
  "properties": {
    "addr:full":"5294 E 3610 N Murtaugh ID 83344",
    "addr:housenumber":"5294",
    "addr:postcode":"83344",
    "addr:street":"E 3610 N",
    "iso:country":"US",
    "sg:address":"5294 E 3610 N",
    "sg:city":"Murtaugh",
    "sg:phone":"+1 208 432 5560",
    "sg:postcode":"83344",
    "sg:province":"ID",
    "sg:tags":[
        "irrigation",
        "company"
    ],
    "wof:name":"Milner Irrigation District",
    "wof:placetype":"venue"
},
  "geometry": {"coordinates":[-114.01132200000001,42.519297],"type":"Point"}
}