{
  "type": "Feature",
  "properties": {
    "addr:full":"3212 E Chinden Blvd Eagle ID 83616",
    "addr:housenumber":"3212",
    "addr:postcode":"83616",
    "addr:street":"E Chinden Blvd",
    "iso:country":"US",
    "sg:address":"3212 E Chinden Blvd",
    "sg:city":"Eagle",
    "sg:classifiers":[
        {
            "category":"Shopping",
            "subcategory":"Pharmacy",
            "type":"Retail Goods"
        }
    ],
    "sg:phone":"+1 208 319 0535",
    "sg:postcode":"83616",
    "sg:province":"ID",
    "wof:name":"Walgreens",
    "wof:placetype":"venue"
},
  "geometry": {"coordinates":[-116.35341099999999,43.663078],"type":"Point"}
}