{
  "type": "Feature",
  "properties": {
    "addr:full":"245 S Capitol Blvd Boise ID 83702",
    "addr:housenumber":"245",
    "addr:postcode":"83702",
    "addr:street":"S Capitol Blvd",
    "iso:country":"US",
    "sg:address":"245 S Capitol Blvd",
    "sg:city":"Boise",
    "sg:classifiers":[
        {
            "category":"Restaurant",
            "type":"Food & Drink"
        }
    ],
    "sg:menulink":"http://www.allmenus.com/id/boise-city/26163-emilios/menu/",
    "sg:phone":"+1 208 333 8002",
    "sg:postcode":"83702",
    "sg:province":"ID",
    "sg:tags":[
        "new",
        "american"
    ],
    "wof:name":"Emilio's",
    "wof:placetype":"venue"
},
  "geometry": {"coordinates":[-116.20339,43.613908],"type":"Point"}
}