{
  "type": "Feature",
  "properties": {
    "addr:full":"709 W North St Grangeville ID 83530",
    "addr:housenumber":"709",
    "addr:postcode":"83530",
    "addr:street":"W North St",
    "iso:country":"US",
    "sg:address":"709 W North St",
    "sg:city":"Grangeville",
    "sg:classifiers":[
        {
            "category":"Food & Beverages",
            "subcategory":"Specialty",
            "type":"Retail Goods"
        }
    ],
    "sg:phone":"+1 208 983 1276",
    "sg:postcode":"83530",
    "sg:province":"ID",
    "sg:tags":[
        "health",
        "diet"
    ],
    "wof:name":"Health Food Store",
    "wof:placetype":"venue"
},
  "geometry": {"coordinates":[-116.12821700000001,45.927632],"type":"Point"}
}