{
  "type": "Feature",
  "properties": {
    "addr:full":"1200 E 1st St Meridian ID 83642",
    "addr:housenumber":"1200",
    "addr:postcode":"83642",
    "addr:street":"E 1St St",
    "iso:country":"US",
    "sg:address":"1200 E 1st St",
    "sg:city":"Meridian",
    "sg:classifiers":[
        {
            "category":"Government",
            "subcategory":"Post Office",
            "type":"Public Place"
        }
    ],
    "sg:phone":"+1 208 000 1111",
    "sg:postcode":"83642",
    "sg:province":"ID",
    "wof:name":"US Post Office",
    "wof:placetype":"venue"
},
  "geometry": {"coordinates":[-116.39157,43.61461],"type":"Point"}
}