{
  "type": "Feature",
  "properties": {
    "iso:country":"US",
    "sg:address":"616 E Coeur D Alene Ave",
    "sg:city":"Coeur D Alene",
    "sg:classifiers":[
        {
            "category":"Shopping",
            "subcategory":"Computers & Home Electronics",
            "type":"Retail Goods"
        }
    ],
    "sg:phone":"+1 208 765 2615",
    "sg:postcode":"83814",
    "sg:province":"ID",
    "wof:name":"B & R Computers",
    "wof:placetype":"venue"
},
  "geometry": {"coordinates":[-116.776916,47.674971],"type":"Point"}
}