{
  "type": "Feature",
  "properties": {
    "addr:full":"810 Main Wardner St Kellogg ID 83837",
    "addr:housenumber":"810",
    "addr:postcode":"83837",
    "addr:street":"Main Wardner St",
    "iso:country":"US",
    "sg:address":"810 Main Wardner St",
    "sg:city":"Kellogg",
    "sg:classifiers":[
        {
            "category":"Building & Trades",
            "subcategory":"Construction",
            "type":"Services"
        }
    ],
    "sg:phone":"+1 208 783 1134",
    "sg:postcode":"83837",
    "sg:province":"ID",
    "sg:tags":[
        "excavation",
        "parking",
        "lot",
        "maintenance",
        "contractor"
    ],
    "wof:name":"Parking Lot Maint & Excav",
    "wof:placetype":"venue"
},
  "geometry": {"coordinates":[-116.125674,47.529314],"type":"Point"}
}