{
  "type": "Feature",
  "properties": {
    "addr:full":"1329 Goldenrod Dr Nampa ID 83686",
    "addr:housenumber":"1329",
    "addr:postcode":"83686",
    "addr:street":"Goldenrod Dr",
    "iso:country":"US",
    "sg:address":"1329 Goldenrod Dr",
    "sg:city":"Nampa",
    "sg:classifiers":[
        {
            "category":"Professional",
            "type":"Services"
        }
    ],
    "sg:phone":"+1 208 467 5941",
    "sg:postcode":"83686",
    "sg:province":"ID",
    "wof:name":"Craig Alexander",
    "wof:placetype":"venue"
},
  "geometry": {"coordinates":[-116.53911600000001,43.555586],"type":"Point"}
}