{
  "type": "Feature",
  "properties": {
    "iso:country":"US",
    "sg:address":"7300 W State St",
    "sg:city":"Boise",
    "sg:classifiers":[
        {
            "category":"Restaurant",
            "type":"Food & Drink"
        }
    ],
    "sg:phone":"+1 208 853 8337",
    "sg:postcode":"83714",
    "sg:province":"ID",
    "sg:tags":[
        "dessert",
        "parlor",
        "ice",
        "cream"
    ],
    "sg:website":"http://www.tcby.com",
    "wof:name":"Tcby",
    "wof:placetype":"venue"
},
  "geometry": {"coordinates":[-116.27954099999999,43.66861],"type":"Point"}
}