{
  "type": "Feature",
  "properties": {
    "iso:country":"US",
    "sg:address":"3684 US Hwy 30",
    "sg:city":"Pocatello",
    "sg:classifiers":[
        {
            "category":"Restaurant",
            "type":"Food & Drink"
        }
    ],
    "sg:phone":"+1 208 232 9704",
    "sg:postcode":"83201",
    "sg:province":"ID",
    "sg:tags":[
        "caterer"
    ],
    "wof:name":"Mc Dermotts",
    "wof:placetype":"venue"
},
  "geometry": {"coordinates":[-112.49757099999999,42.900827],"type":"Point"}
}