{
  "type": "Feature",
  "properties": {
    "addr:full":"2441 N Henry St Post Falls ID 83854",
    "addr:housenumber":"2441",
    "addr:postcode":"83854",
    "addr:street":"N Henry St",
    "iso:country":"US",
    "sg:address":"2441 N Henry St",
    "sg:city":"Post Falls",
    "sg:classifiers":[
        {
            "category":"Health Services",
            "subcategory":"Nursing And Care Facility",
            "type":"Services"
        }
    ],
    "sg:phone":"+1 208 777 8468",
    "sg:postcode":"83854",
    "sg:province":"ID",
    "sg:tags":[
        "automobile"
    ],
    "wof:name":"BMW of Idaho Inc",
    "wof:placetype":"venue"
},
  "geometry": {"coordinates":[-116.944413,47.733728],"type":"Point"}
}