{
  "type": "Feature",
  "properties": {
    "iso:country":"US",
    "sg:address":"224 E Avalon St",
    "sg:city":"Kuna",
    "sg:classifiers":[
        {
            "category":"Organizations",
            "subcategory":"Religious Organization",
            "type":"Services"
        }
    ],
    "sg:phone":"+1 208 922 4250",
    "sg:postcode":"83634",
    "sg:province":"ID",
    "sg:tags":[
        "church"
    ],
    "wof:name":"KUNA First LDS Ward",
    "wof:placetype":"venue"
},
  "geometry": {"coordinates":[-116.412341,43.488473],"type":"Point"}
}