{
  "type": "Feature",
  "properties": {
    "iso:country":"US",
    "sg:address":"3433 Chinden Blvd",
    "sg:city":"Boise",
    "sg:classifiers":[
        {
            "category":"Travel",
            "subcategory":"Hotels & Motels",
            "type":"Entertainment"
        }
    ],
    "sg:phone":"+1 208 344 7647",
    "sg:postcode":"83714",
    "sg:province":"ID",
    "sg:tags":[
        "operation"
    ],
    "wof:name":"Sunliner Motel",
    "wof:placetype":"venue"
},
  "geometry": {"coordinates":[-116.24001800000001,43.623025],"type":"Point"}
}