{
  "type": "Feature",
  "properties": {
    "iso:country":"US",
    "sg:address":"58 E Fairview Ave",
    "sg:city":"Meridian",
    "sg:classifiers":[
        {
            "category":"Utilities",
            "subcategory":"Mobile Phone",
            "type":"Services"
        }
    ],
    "sg:phone":"+1 208 895 7964",
    "sg:postcode":"83642",
    "sg:province":"ID",
    "sg:tags":[
        "telephone",
        "cellular"
    ],
    "wof:name":"CBS Cellular",
    "wof:placetype":"venue"
},
  "geometry": {"coordinates":[-116.392404,43.619237],"type":"Point"}
}