{
  "type": "Feature",
  "properties": {
    "addr:full":"220 Eastland Dr S Twin Falls ID 83301",
    "addr:housenumber":"220",
    "addr:postcode":"83301",
    "addr:street":"Eastland Dr S",
    "iso:country":"US",
    "sg:address":"220 Eastland Dr S",
    "sg:city":"Twin Falls",
    "sg:classifiers":[
        {
            "category":"Freight",
            "type":"Transportation"
        }
    ],
    "sg:phone":"+1 208 733 7174",
    "sg:postcode":"83301",
    "sg:province":"ID",
    "sg:tags":[
        "trucking"
    ],
    "wof:name":"Magic Transport Inc",
    "wof:placetype":"venue"
},
  "geometry": {"coordinates":[-114.440511,42.546125],"type":"Point"}
}