{
  "type": "Feature",
  "properties": {
    "iso:country":"US",
    "sg:address":"821 N William St",
    "sg:city":"Post Falls",
    "sg:classifiers":[
        {
            "category":"Wholesale",
            "subcategory":"Hardware",
            "type":"Manufacturing & Wholesale Goods"
        }
    ],
    "sg:phone":"+1 208 773 4313",
    "sg:postcode":"83854",
    "sg:province":"ID",
    "sg:tags":[
        "equipment",
        "energy",
        "solar"
    ],
    "wof:name":"Solar Eclipse",
    "wof:placetype":"venue"
},
  "geometry": {"coordinates":[-116.94504499999999,47.716778],"type":"Point"}
}