{
  "type": "Feature",
  "properties": {
    "iso:country":"US",
    "sg:address":"4133 N 45th E",
    "sg:city":"Idaho Falls",
    "sg:classifiers":[
        {
            "category":"Wholesale",
            "subcategory":"Electrical",
            "type":"Manufacturing & Wholesale Goods"
        }
    ],
    "sg:phone":"+1 208 522 7329",
    "sg:postcode":"83401",
    "sg:province":"ID",
    "sg:tags":[
        "light",
        "tube",
        "bulb"
    ],
    "wof:name":"Hatch Lighting Commercial",
    "wof:placetype":"venue"
},
  "geometry": {"coordinates":[-111.944183,43.532386],"type":"Point"}
}