{
  "type": "Feature",
  "properties": {
    "addr:full":"127 W 5th St Burley ID 83318",
    "addr:housenumber":"127",
    "addr:postcode":"83318",
    "addr:street":"W 5Th St",
    "iso:country":"US",
    "sg:address":"127 W 5th St",
    "sg:city":"Burley",
    "sg:classifiers":[
        {
            "category":"Government",
            "subcategory":"Office",
            "type":"Public Place"
        }
    ],
    "sg:phone":"+1 208 678 3332",
    "sg:postcode":"83318",
    "sg:province":"ID",
    "sg:tags":[
        "state",
        "resource"
    ],
    "wof:name":"Industrial Commission",
    "wof:placetype":"venue"
},
  "geometry": {"coordinates":[-113.793678,42.547217],"type":"Point"}
}