{
  "type": "Feature",
  "properties": {
    "iso:country":"US",
    "sg:address":"448 Eastland Dr S",
    "sg:city":"Twin Falls",
    "sg:classifiers":[
        {
            "category":"Retail",
            "subcategory":"Auto Repair",
            "type":"Services"
        }
    ],
    "sg:phone":"+1 208 733 1128",
    "sg:postcode":"83301",
    "sg:province":"ID",
    "sg:tags":[
        "machine",
        "automobile",
        "shop"
    ],
    "wof:name":"KIDD Performance-Valley Engine",
    "wof:placetype":"venue"
},
  "geometry": {"coordinates":[-114.440547,42.542136],"type":"Point"}
}