{
  "type": "Feature",
  "properties": {
    "iso:country":"US",
    "sg:address":"237 E 1100 S",
    "sg:city":"Burley",
    "sg:classifiers":[
        {
            "category":"Freight",
            "type":"Transportation"
        }
    ],
    "sg:phone":"+1 208 677 3008",
    "sg:postcode":"83318",
    "sg:province":"ID",
    "wof:name":"Gallatin Transportation Inc",
    "wof:placetype":"venue"
},
  "geometry": {"coordinates":[-113.75459499999999,42.372274],"type":"Point"}
}