{
  "type": "Feature",
  "properties": {
    "iso:country":"US",
    "sg:address":"25 N 6th St",
    "sg:city":"Payette",
    "sg:classifiers":[
        {
            "category":"Manufacturing",
            "subcategory":"Food",
            "type":"Manufacturing & Wholesale Goods"
        }
    ],
    "sg:phone":"+1 208 642 9061",
    "sg:postcode":"83661",
    "sg:province":"ID",
    "sg:tags":[
        "canning"
    ],
    "wof:name":"Seneca Foods Corp",
    "wof:placetype":"venue"
},
  "geometry": {"coordinates":[-116.938154,44.074978],"type":"Point"}
}