{
  "type": "Feature",
  "properties": {
    "iso:country":"US",
    "sg:address":"434 W Main St",
    "sg:city":"Burley",
    "sg:classifiers":[
        {
            "category":"Autos & Motor Vehicles",
            "subcategory":"Automobile Sales",
            "type":"Retail Goods"
        }
    ],
    "sg:phone":"+1 208 677 2277",
    "sg:postcode":"83318",
    "sg:province":"ID",
    "sg:tags":[
        "car",
        "dealer"
    ],
    "wof:name":"Gramp's Wholesale Auto",
    "wof:placetype":"venue"
},
  "geometry": {"coordinates":[-113.79748600000001,42.538155],"type":"Point"}
}