{
  "type": "Feature",
  "properties": {
    "addr:full":"208 Main St Mackay ID 83251",
    "addr:housenumber":"208",
    "addr:postcode":"83251",
    "addr:street":"Main St",
    "iso:country":"US",
    "sg:address":"208 Main St",
    "sg:city":"Mackay",
    "sg:classifiers":[
        {
            "category":"Food & Beverages",
            "subcategory":"Specialty",
            "type":"Retail Goods"
        }
    ],
    "sg:phone":"+1 208 588 3016",
    "sg:postcode":"83251",
    "sg:province":"ID",
    "sg:tags":[
        "health",
        "diet"
    ],
    "wof:name":"Prospector Health & Nutrition",
    "wof:placetype":"venue"
},
  "geometry": {"coordinates":[-113.611103,43.915829],"type":"Point"}
}