{
  "type": "Feature",
  "properties": {
    "addr:full":"973 Grays Creek Rd Indian Valley ID 83632",
    "addr:housenumber":"973",
    "addr:postcode":"83632",
    "addr:street":"Grays Creek Rd",
    "iso:country":"US",
    "sg:address":"973 Grays Creek Rd",
    "sg:city":"Indian Valley",
    "sg:classifiers":[
        {
            "category":"Professional",
            "type":"Services"
        }
    ],
    "sg:phone":"+1 208 256 4455",
    "sg:postcode":"83632",
    "sg:province":"ID",
    "sg:tags":[
        "establishment"
    ],
    "wof:name":"Barbara J Inc",
    "wof:placetype":"venue"
},
  "geometry": {"coordinates":[-116.412819,44.576429],"type":"Point"}
}