{
  "type": "Feature",
  "properties": {
    "iso:country":"US",
    "sg:address":"3050 S 1950 E",
    "sg:city":"Wendell",
    "sg:classifiers":[
        {
            "category":"Restaurant",
            "type":"Food & Drink"
        }
    ],
    "sg:phone":"+1 208 536 4648",
    "sg:postcode":"83355",
    "sg:province":"ID",
    "sg:tags":[
        "eating"
    ],
    "wof:name":"DC Branding Iron Steakhouse",
    "wof:placetype":"venue"
},
  "geometry": {"coordinates":[-114.70385,42.759295],"type":"Point"}
}