{
  "type": "Feature",
  "properties": {
    "iso:country":"US",
    "sg:address":"5414 Bear Ln",
    "sg:city":"Caldwell",
    "sg:classifiers":[
        {
            "category":"Professional",
            "type":"Services"
        }
    ],
    "sg:phone":"+1 208 455 5668",
    "sg:postcode":"83607",
    "sg:province":"ID",
    "wof:name":"B O C Gases",
    "wof:placetype":"venue"
},
  "geometry": {"coordinates":[-116.70305399999999,43.622371],"type":"Point"}
}