{
  "type": "Feature",
  "properties": {
    "iso:country":"US",
    "sg:address":"1322 el Rancho Blvd",
    "sg:city":"Pocatello",
    "sg:classifiers":[
        {
            "category":"Building & Trades",
            "subcategory":"Construction",
            "type":"Services"
        }
    ],
    "sg:phone":"+1 208 238 7224",
    "sg:postcode":"83201",
    "sg:province":"ID",
    "sg:tags":[
        "general",
        "contractor"
    ],
    "wof:name":"Thompson Custom Homes",
    "wof:placetype":"venue"
},
  "geometry": {"coordinates":[-112.441022,42.895621],"type":"Point"}
}