{
  "type": "Feature",
  "properties": {
    "iso:country":"US",
    "sg:address":"615 N Water Ave",
    "sg:city":"Idaho Falls",
    "sg:classifiers":[
        {
            "category":"Organizations",
            "subcategory":"Religious Organization",
            "type":"Services"
        }
    ],
    "sg:phone":"+1 208 524 3506",
    "sg:postcode":"83402",
    "sg:province":"ID",
    "sg:tags":[
        "church"
    ],
    "wof:name":"Primera Igelsia Bautista",
    "wof:placetype":"venue"
},
  "geometry": {"coordinates":[-112.034288,43.494154],"type":"Point"}
}