{
  "type": "Feature",
  "properties": {
    "iso:country":"US",
    "sg:address":"1865 N 1900 E",
    "sg:city":"Hamer",
    "sg:classifiers":[
        {
            "category":"Health Services",
            "subcategory":"Health Practitioner",
            "type":"Services"
        }
    ],
    "sg:phone":"+1 208 662 5412",
    "sg:postcode":"83425",
    "sg:province":"ID",
    "sg:tags":[
        "therapy"
    ],
    "wof:name":"Soft Touch Therapy",
    "wof:placetype":"venue"
},
  "geometry": {"coordinates":[-112.317585,43.894438],"type":"Point"}
}