{
  "type": "Feature",
  "properties": {
    "addr:full":"107 Carrie Rex Ave Melba ID 83641",
    "addr:housenumber":"107",
    "addr:postcode":"83641",
    "addr:street":"Carrie Rex Ave",
    "iso:country":"US",
    "sg:address":"107 Carrie Rex Ave",
    "sg:city":"Melba",
    "sg:classifiers":[
        {
            "category":"Retail",
            "subcategory":"Repair Shop",
            "type":"Services"
        }
    ],
    "sg:phone":"+1 208 495 1165",
    "sg:postcode":"83641",
    "sg:province":"ID",
    "sg:tags":[
        "related"
    ],
    "wof:name":"Melba Supply & Repair",
    "wof:placetype":"venue"
},
  "geometry": {"coordinates":[-116.529904,43.373769],"type":"Point"}
}