{
  "type": "Feature",
  "properties": {
    "addr:full":"525 Cedar St Wallace ID 83873",
    "addr:housenumber":"525",
    "addr:postcode":"83873",
    "addr:street":"Cedar St",
    "iso:country":"US",
    "sg:address":"525 Cedar St",
    "sg:city":"Wallace",
    "sg:classifiers":[
        {
            "category":"Shopping",
            "subcategory":"Gifts & Souvenirs",
            "type":"Retail Goods"
        }
    ],
    "sg:phone":"+1 208 753 6141",
    "sg:postcode":"83873",
    "sg:province":"ID",
    "sg:tags":[
        "used",
        "merchandise"
    ],
    "wof:name":"Wallace Corner",
    "wof:placetype":"venue"
},
  "geometry": {"coordinates":[-115.92418000000001,47.472497],"type":"Point"}
}