{
  "type": "Feature",
  "properties": {
    "iso:country":"US",
    "sg:address":"300 E Bannock St",
    "sg:city":"Boise",
    "sg:classifiers":[
        {
            "category":"Health Services",
            "subcategory":"Doctor",
            "type":"Services"
        }
    ],
    "sg:phone":"+1 208 342 7400",
    "sg:postcode":"83712",
    "sg:province":"ID",
    "sg:tags":[
        "physician",
        "surgeon"
    ],
    "wof:name":"Center For Lifetime Health",
    "wof:placetype":"venue"
},
  "geometry": {"coordinates":[-116.190406,43.61126],"type":"Point"}
}