{
  "type": "Feature",
  "properties": {
    "iso:country":"US",
    "sg:address":"4352 N 1325 E",
    "sg:city":"Buhl",
    "sg:classifiers":[
        {
            "category":"Farming",
            "subcategory":"Livestock Farm",
            "type":"Manufacturing & Wholesale Goods"
        }
    ],
    "sg:phone":"+1 208 543 8075",
    "sg:postcode":"83316",
    "sg:province":"ID",
    "sg:tags":[
        "beef",
        "feedlot",
        "cattle"
    ],
    "wof:name":"Rock Bartlett",
    "wof:placetype":"venue"
},
  "geometry": {"coordinates":[-114.794422,42.621281],"type":"Point"}
}