{
  "type": "Feature",
  "properties": {
    "addr:full":"326 2nd Ave S Twin Falls ID 83301",
    "addr:housenumber":"326",
    "addr:postcode":"83301",
    "addr:street":"2Nd Ave S Twin",
    "iso:country":"US",
    "sg:address":"326 2nd Ave S",
    "sg:city":"Twin Falls",
    "sg:classifiers":[
        {
            "category":"Freight",
            "type":"Transportation"
        }
    ],
    "sg:phone":"+1 208 733 2859",
    "sg:postcode":"83301",
    "sg:province":"ID",
    "sg:tags":[
        "trucking"
    ],
    "wof:name":"Gilbert Trucking & Transport",
    "wof:placetype":"venue"
},
  "geometry": {"coordinates":[-114.468322,42.553052],"type":"Point"}
}