{
  "type": "Feature",
  "properties": {
    "iso:country":"US",
    "sg:address":"812 E 7th St",
    "sg:city":"Moscow",
    "sg:classifiers":[
        {
            "category":"Building & Trades",
            "subcategory":"Construction",
            "type":"Services"
        }
    ],
    "sg:phone":"+1 208 882 0527",
    "sg:postcode":"83843",
    "sg:province":"ID",
    "sg:tags":[
        "residential"
    ],
    "wof:name":"Carpenter Construction",
    "wof:placetype":"venue"
},
  "geometry": {"coordinates":[-116.99043399999999,46.728965],"type":"Point"}
}