{
  "type": "Feature",
  "properties": {
    "addr:full":"915 W Iowa Ave Nampa ID 83686",
    "addr:housenumber":"915",
    "addr:postcode":"83686",
    "addr:street":"W Iowa Ave",
    "iso:country":"US",
    "sg:address":"915 W Iowa Ave",
    "sg:city":"Nampa",
    "sg:classifiers":[
        {
            "category":"Building & Trades",
            "subcategory":"Construction",
            "type":"Services"
        }
    ],
    "sg:phone":"+1 208 467 4240",
    "sg:postcode":"83686",
    "sg:province":"ID",
    "sg:tags":[
        "repairing",
        "remodeling",
        "contractor"
    ],
    "wof:name":"First Class Home Improvements",
    "wof:placetype":"venue"
},
  "geometry": {"coordinates":[-116.590249,43.554485],"type":"Point"}
}