{
  "type": "Feature",
  "properties": {
    "addr:full":"100 E Corporate Dr Meridian ID 83642",
    "addr:housenumber":"100",
    "addr:postcode":"83642",
    "addr:street":"E Corporate Dr",
    "iso:country":"US",
    "sg:address":"100 E Corporate Dr",
    "sg:city":"Meridian",
    "sg:classifiers":[
        {
            "category":"Restaurant",
            "type":"Food & Drink"
        }
    ],
    "sg:menulink":"http://www.allmenus.com/id/boise-city/180928-wendys/menu/",
    "sg:phone":"+1 208 888 2900",
    "sg:postcode":"83642",
    "sg:province":"ID",
    "sg:tags":[
        "burger",
        "american",
        "soup"
    ],
    "wof:name":"Wendy's",
    "wof:placetype":"venue"
},
  "geometry": {"coordinates":[-116.392715,43.599826],"type":"Point"}
}