{
  "type": "Feature",
  "properties": {
    "addr:full":"415 Thain Rd Lewiston ID 83501",
    "addr:housenumber":"415",
    "addr:postcode":"83501",
    "addr:street":"Thain Rd",
    "iso:country":"US",
    "sg:address":"415 Thain Rd",
    "sg:city":"Lewiston",
    "sg:classifiers":[
        {
            "category":"Shopping",
            "subcategory":"Clothing, Apparel, & Fashions",
            "type":"Retail Goods"
        }
    ],
    "sg:phone":"+1 208 798 5151",
    "sg:postcode":"83501",
    "sg:province":"ID",
    "sg:tags":[
        "maternity"
    ],
    "wof:name":"Oh Baby Children's Resale",
    "wof:placetype":"venue"
},
  "geometry": {"coordinates":[-116.97472999999999,46.3795],"type":"Point"}
}