{
  "type": "Feature",
  "properties": {
    "iso:country":"US",
    "sg:address":"1007 Warm Springs Rd",
    "sg:city":"Ketchum",
    "sg:classifiers":[
        {
            "category":"Building & Trades",
            "subcategory":"Construction",
            "type":"Services"
        }
    ],
    "sg:phone":"+1 208 726 9000",
    "sg:postcode":"83340",
    "sg:province":"ID",
    "sg:tags":[
        "dry wall",
        "contractor"
    ],
    "wof:name":"William Glenn Dry Wall Contr",
    "wof:placetype":"venue"
},
  "geometry": {"coordinates":[-114.452345,43.666582],"type":"Point"}
}