{
  "type": "Feature",
  "properties": {
    "iso:country":"US",
    "sg:address":"376 E St",
    "sg:city":"Idaho Falls",
    "sg:classifiers":[
        {
            "category":"Personal",
            "subcategory":"Barber",
            "type":"Services"
        }
    ],
    "sg:phone":"+1 208 523 5080",
    "sg:postcode":"83402",
    "sg:province":"ID",
    "sg:tags":[
        "shop",
        "beauty"
    ],
    "wof:name":"Merrill's The Headmaster",
    "wof:placetype":"venue"
},
  "geometry": {"coordinates":[-112.037453,43.495824],"type":"Point"}
}