{
  "type": "Feature",
  "properties": {
    "iso:country":"US",
    "sg:address":"2712 E Iowa Ave",
    "sg:city":"Nampa",
    "sg:classifiers":[
        {
            "category":"Building & Trades",
            "subcategory":"Cleaning & Sanitation",
            "type":"Services"
        }
    ],
    "sg:phone":"+1 208 461 6247",
    "sg:postcode":"83686",
    "sg:province":"ID",
    "sg:tags":[
        "sanitation",
        "restroom"
    ],
    "wof:name":"Aire-Master Of The Gem State",
    "wof:placetype":"venue"
},
  "geometry": {"coordinates":[-116.537209,43.552719],"type":"Point"}
}