{
  "type": "Feature",
  "properties": {
    "iso:country":"US",
    "sg:address":"201 N Hornet Creek St",
    "sg:city":"Council",
    "sg:classifiers":[
        {
            "category":"Social Services",
            "type":"Services"
        }
    ],
    "sg:phone":"+1 208 253 0011",
    "sg:postcode":"83612",
    "sg:province":"ID",
    "wof:name":"EOA Council Senior Housing",
    "wof:placetype":"venue"
},
  "geometry": {"coordinates":[-116.445582,44.730267],"type":"Point"}
}