{
  "type": "Feature",
  "properties": {
    "addr:full":"Us 95 Worley ID 83876",
    "addr:postcode":"83876",
    "addr:street":"Us 95",
    "iso:country":"US",
    "sg:address":"Us 95",
    "sg:city":"Worley",
    "sg:classifiers":[
        {
            "category":"Cafe",
            "type":"Food & Drink"
        }
    ],
    "sg:menulink":"http://www.allmenus.com/id/worley/3477-sweetgrass-cafe/menu/",
    "sg:phone":"+1 800 523 2464",
    "sg:postcode":"83876",
    "sg:province":"ID",
    "sg:tags":[
        "american"
    ],
    "wof:name":"Sweetgrass Cafe",
    "wof:placetype":"venue"
},
  "geometry": {"coordinates":[-116.92113000000001,47.40058],"type":"Point"}
}