{
  "type": "Feature",
  "properties": {
    "iso:country":"US",
    "sg:address":"280 N 8th St",
    "sg:city":"Boise",
    "sg:classifiers":[
        {
            "category":"Manufacturing",
            "subcategory":"Jewelry",
            "type":"Manufacturing & Wholesale Goods"
        }
    ],
    "sg:phone":"+1 208 363 9293",
    "sg:postcode":"83702",
    "sg:province":"ID",
    "sg:tags":[
        "precious",
        "metal",
        "mfg"
    ],
    "wof:name":"Michael Rogers",
    "wof:placetype":"venue"
},
  "geometry": {"coordinates":[-116.202382,43.61649],"type":"Point"}
}