{
  "type": "Feature",
  "properties": {
    "iso:country":"US",
    "sg:address":"755 S Ithaca St",
    "sg:city":"Post Falls",
    "sg:classifiers":[
        {
            "category":"Building & Trades",
            "subcategory":"Construction",
            "type":"Services"
        }
    ],
    "sg:phone":"+1 208 773 4666",
    "sg:postcode":"83854",
    "sg:province":"ID",
    "sg:tags":[
        "general",
        "contractor"
    ],
    "wof:name":"Neely Construction Inc",
    "wof:placetype":"venue"
},
  "geometry": {"coordinates":[-116.888075,47.698461],"type":"Point"}
}