{
  "type": "Feature",
  "properties": {
    "iso:country":"US",
    "sg:address":"105 N 4th St",
    "sg:city":"Coeur D Alene",
    "sg:classifiers":[
        {
            "category":"Real Estate",
            "subcategory":"Real Estate Agent",
            "type":"Services"
        }
    ],
    "sg:phone":"+1 208 664 9674",
    "sg:postcode":"83814",
    "sg:province":"ID",
    "sg:tags":[
        "desk",
        "space"
    ],
    "wof:name":"Johnston's Office & Retail",
    "wof:placetype":"venue"
},
  "geometry": {"coordinates":[-116.78124699999999,47.673852],"type":"Point"}
}