{
  "type": "Feature",
  "properties": {
    "addr:full":"630 Preston Ave Lewiston ID 83501",
    "addr:housenumber":"630",
    "addr:postcode":"83501",
    "addr:street":"Preston Ave",
    "iso:country":"US",
    "sg:address":"630 Preston Ave",
    "sg:city":"Lewiston",
    "sg:classifiers":[
        {
            "category":"Building & Trades",
            "subcategory":"Construction",
            "type":"Services"
        }
    ],
    "sg:phone":"+1 208 553 8088",
    "sg:postcode":"83501",
    "sg:province":"ID",
    "sg:tags":[
        "roofing",
        "industrial",
        "altering",
        "contractor",
        "contractors-commercial",
        "remodeling"
    ],
    "sg:website":"http://www.anbsolutionsllc.com",
    "wof:name":"ANB Solutions, LLC",
    "wof:placetype":"venue"
},
  "geometry": {"coordinates":[-116.998009,46.387749],"type":"Point"}
}