{
  "type": "Feature",
  "properties": {
    "iso:country":"US",
    "sg:address":"118 S Jackson St",
    "sg:city":"Moscow",
    "sg:classifiers":[
        {
            "category":"Professional",
            "subcategory":"Business Services",
            "type":"Services"
        }
    ],
    "sg:phone":"+1 208 882 8421",
    "sg:postcode":"83843",
    "sg:province":"ID",
    "wof:name":"Guitars Friend Production",
    "wof:placetype":"venue"
},
  "geometry": {"coordinates":[-117.002662,46.733133],"type":"Point"}
}