{
  "type": "Feature",
  "properties": {
    "addr:full":"703 Americana Blvd Boise ID 83702",
    "addr:housenumber":"703",
    "addr:postcode":"83702",
    "addr:street":"Americana Blvd",
    "iso:country":"US",
    "sg:address":"703 Americana Blvd",
    "sg:city":"Boise",
    "sg:classifiers":[
        {
            "category":"Banks & Credit Unions",
            "subcategory":"Bank",
            "type":"Services"
        }
    ],
    "sg:phone":"+1 208 319 0405",
    "sg:postcode":"83702",
    "sg:province":"ID",
    "wof:name":"Farmers & Merchant State Bank",
    "wof:placetype":"venue"
},
  "geometry": {"coordinates":[-116.219926,43.616815],"type":"Point"}
}