{
  "type": "Feature",
  "properties": {
    "addr:full":"950 W Quinn Rd Pocatello ID 83202",
    "addr:housenumber":"950",
    "addr:postcode":"83202",
    "addr:street":"W Quinn Rd",
    "iso:country":"US",
    "sg:address":"950 W Quinn Rd",
    "sg:city":"Pocatello",
    "sg:classifiers":[
        {
            "category":"Building & Trades",
            "subcategory":"Landscaping Services",
            "type":"Services"
        }
    ],
    "sg:phone":"+1 208 238 1770",
    "sg:postcode":"83202",
    "sg:province":"ID",
    "sg:tags":[
        "landscape"
    ],
    "wof:name":"Bobs Chore Service",
    "wof:placetype":"venue"
},
  "geometry": {"coordinates":[-112.470877,42.905656],"type":"Point"}
}