{
  "type": "Feature",
  "properties": {
    "addr:full":"12301 W Explorer Dr Ste 270 Boise ID 83713",
    "addr:housenumber":"12301",
    "addr:postcode":"83713",
    "addr:street":"W Explorer Dr Ste 270",
    "iso:country":"US",
    "sg:address":"12301 W Explorer Dr Ste 270",
    "sg:city":"Boise",
    "sg:classifiers":[
        {
            "category":"Professional",
            "subcategory":"Employment Agencies",
            "type":"Services"
        }
    ],
    "sg:phone":"+1 208 376 7500",
    "sg:postcode":"83713",
    "sg:province":"ID",
    "sg:tags":[
        "temporary",
        "secretarial",
        "contractor"
    ],
    "sg:website":"http://www.usadecco.com",
    "wof:name":"Adecco Employment Svc",
    "wof:placetype":"venue"
},
  "geometry": {"coordinates":[-116.33442700000001,43.659489],"type":"Point"}
}