{
  "type": "Feature",
  "properties": {
    "iso:country":"US",
    "sg:address":"121 N Orchard St",
    "sg:city":"Boise",
    "sg:classifiers":[
        {
            "category":"Retail",
            "subcategory":"Car Wash",
            "type":"Services"
        }
    ],
    "sg:phone":"+1 208 323 6115",
    "sg:postcode":"83706",
    "sg:province":"ID",
    "sg:tags":[
        "polishing",
        "washing"
    ],
    "wof:name":"Orchard Shell Express Gas",
    "wof:placetype":"venue"
},
  "geometry": {"coordinates":[-116.24354200000001,43.605511],"type":"Point"}
}