{
  "type": "Feature",
  "properties": {
    "iso:country":"US",
    "sg:address":"2353 E Glacier Rd",
    "sg:city":"Hayden",
    "sg:classifiers":[
        {
            "category":"Retail",
            "subcategory":"Repair Shop",
            "type":"Services"
        }
    ],
    "sg:phone":"+1 208 762 0368",
    "sg:postcode":"83835",
    "sg:province":"ID",
    "wof:name":"AAA Crime Scene",
    "wof:placetype":"venue"
},
  "geometry": {"coordinates":[-116.759025,47.821623],"type":"Point"}
}