{
  "type": "Feature",
  "properties": {
    "iso:country":"US",
    "sg:address":"6524 E Trinity Ln",
    "sg:city":"Athol",
    "sg:classifiers":[
        {
            "category":"Freight",
            "type":"Transportation"
        }
    ],
    "sg:phone":"+1 208 683 2181",
    "sg:postcode":"83801",
    "sg:province":"ID",
    "sg:tags":[
        "commercial",
        "storage"
    ],
    "wof:name":"Farragut Mini Storage",
    "wof:placetype":"venue"
},
  "geometry": {"coordinates":[-116.687603,47.957627],"type":"Point"}
}