{
  "type": "Feature",
  "properties": {
    "iso:country":"US",
    "sg:address":"1675 Commerce Ave",
    "sg:city":"Boise",
    "sg:classifiers":[
        {
            "category":"Wholesale",
            "subcategory":"Metals & Minerals",
            "type":"Manufacturing & Wholesale Goods"
        }
    ],
    "sg:phone":"+1 208 384 0400",
    "sg:postcode":"83705",
    "sg:province":"ID",
    "sg:tags":[
        "steel",
        "warehouse"
    ],
    "wof:name":"Metalwest",
    "wof:placetype":"venue"
},
  "geometry": {"coordinates":[-116.200389,43.564158],"type":"Point"}
}