{
  "type": "Feature",
  "properties": {
    "addr:full":"3416 S Bennett St Boise ID 83705",
    "addr:housenumber":"3416",
    "addr:postcode":"83705",
    "addr:street":"S Bennett St",
    "iso:country":"US",
    "sg:address":"3416 S Bennett St",
    "sg:city":"Boise",
    "sg:classifiers":[
        {
            "category":"Manufacturing",
            "subcategory":"Tools & Machinery",
            "type":"Manufacturing & Wholesale Goods"
        }
    ],
    "sg:phone":"+1 208 343 9946",
    "sg:postcode":"83705",
    "sg:province":"ID",
    "sg:tags":[
        "shop",
        "industrial",
        "apparatus",
        "mfg",
        "machine",
        "welding"
    ],
    "wof:name":"Champion Machine Shop & Mfg Co",
    "wof:placetype":"venue"
},
  "geometry": {"coordinates":[-116.197378,43.571188],"type":"Point"}
}