{
  "type": "Feature",
  "properties": {
    "iso:country":"US",
    "sg:address":"2237 W Oconnell Ave",
    "sg:city":"Coeur D Alene",
    "sg:classifiers":[
        {
            "category":"Building & Trades",
            "subcategory":"Landscaping Services",
            "type":"Services"
        }
    ],
    "sg:phone":"+1 208 659 5664",
    "sg:postcode":"83858",
    "sg:province":"ID",
    "sg:tags":[
        "tree"
    ],
    "wof:name":"Rick's Tree Svc",
    "wof:placetype":"venue"
},
  "geometry": {"coordinates":[-116.815017,47.808223],"type":"Point"}
}