{
  "type": "Feature",
  "properties": {
    "iso:country":"US",
    "sg:address":"1181 Kortnee Dr",
    "sg:city":"Idaho Falls",
    "sg:classifiers":[
        {
            "category":"Recreation",
            "type":"Entertainment"
        }
    ],
    "sg:phone":"+1 208 522 7244",
    "sg:postcode":"83402",
    "sg:province":"ID",
    "wof:name":"Reftech",
    "wof:placetype":"venue"
},
  "geometry": {"coordinates":[-112.089526,43.487618],"type":"Point"}
}