{
  "type": "Feature",
  "properties": {
    "iso:country":"US",
    "sg:address":"5311 Glenwood St",
    "sg:city":"Boise",
    "sg:classifiers":[
        {
            "category":"Wholesale",
            "subcategory":"Machinery & Supplies",
            "type":"Manufacturing & Wholesale Goods"
        }
    ],
    "sg:phone":"+1 208 342 4773",
    "sg:postcode":"83714",
    "sg:province":"ID",
    "sg:tags":[
        "dock",
        "loading",
        "equipment"
    ],
    "sg:website":"www.issrack.com",
    "wof:name":"Industrial Storage Systems Inc",
    "wof:placetype":"venue"
},
  "geometry": {"coordinates":[-116.279824,43.650807],"type":"Point"}
}