{
  "type": "Feature",
  "properties": {
    "iso:country":"US",
    "sg:address":"5707 W Guido Ln",
    "sg:city":"Nampa",
    "sg:classifiers":[
        {
            "category":"Autos & Motor Vehicles",
            "subcategory":"Automobile Sales",
            "type":"Retail Goods"
        }
    ],
    "sg:phone":"+1 208 466 4615",
    "sg:postcode":"83687",
    "sg:province":"ID",
    "sg:tags":[
        "car",
        "dealer"
    ],
    "sg:website":"www.danwieboldford.com",
    "wof:name":"Dan Wiebold Ford",
    "wof:placetype":"venue"
},
  "geometry": {"coordinates":[-116.467451,43.555694],"type":"Point"}
}