{
  "type": "Feature",
  "properties": {
    "iso:country":"US",
    "sg:address":"123 S 3rd Ave",
    "sg:city":"Sandpoint",
    "sg:classifiers":[
        {
            "category":"Insurance",
            "subcategory":"Insurance Agent",
            "type":"Services"
        }
    ],
    "sg:phone":"+1 208 263 0466",
    "sg:postcode":"83864",
    "sg:province":"ID",
    "sg:tags":[
        "consultant"
    ],
    "wof:name":"Northwest Financial Designs",
    "wof:placetype":"venue"
},
  "geometry": {"coordinates":[-116.550307,48.272891],"type":"Point"}
}