{
  "type": "Feature",
  "properties": {
    "addr:full":"5819 Overland Rd Boise ID 83709",
    "addr:housenumber":"5819",
    "addr:postcode":"83709",
    "addr:street":"Overland Rd",
    "iso:country":"US",
    "sg:address":"5819 Overland Rd",
    "sg:city":"Boise",
    "sg:classifiers":[
        {
            "category":"Personal",
            "subcategory":"Beauty Salon",
            "type":"Services"
        }
    ],
    "sg:phone":"+1 208 323 4393",
    "sg:postcode":"83709",
    "sg:province":"ID",
    "wof:name":"Bond & Co Hairstyles",
    "wof:placetype":"venue"
},
  "geometry": {"coordinates":[-116.254587,43.589824],"type":"Point"}
}