{
  "type": "Feature",
  "properties": {
    "iso:country":"US",
    "sg:address":"211 W 40th St",
    "sg:city":"Boise",
    "sg:classifiers":[
        {
            "category":"Freight",
            "type":"Transportation"
        }
    ],
    "sg:phone":"+1 208 336 0999",
    "sg:postcode":"83714",
    "sg:province":"ID",
    "sg:tags":[
        "commercial",
        "storage"
    ],
    "wof:name":"Handy Storage",
    "wof:placetype":"venue"
},
  "geometry": {"coordinates":[-116.249456,43.627699],"type":"Point"}
}