{
  "type": "Feature",
  "properties": {
    "addr:full":"895 N 6th E Mountain Home ID 83647",
    "addr:housenumber":"895",
    "addr:postcode":"83647",
    "addr:street":"N 6Th E",
    "iso:country":"US",
    "sg:address":"895 N 6th E",
    "sg:city":"Mountain Home",
    "sg:classifiers":[
        {
            "category":"Government",
            "subcategory":"Office",
            "type":"Public Place"
        }
    ],
    "sg:phone":"+1 208 000 1111",
    "sg:postcode":"83647",
    "sg:province":"ID",
    "wof:name":"Elmore County Ambulance",
    "wof:placetype":"venue"
},
  "geometry": {"coordinates":[-115.692553,43.13841],"type":"Point"}
}