{
  "type": "Feature",
  "properties": {
    "iso:country":"US",
    "sg:address":"509 Cedar St",
    "sg:city":"Wallace",
    "sg:classifiers":[
        {
            "category":"Recreation",
            "subcategory":"Arcade",
            "type":"Entertainment"
        }
    ],
    "sg:phone":"+1 208 752 1082",
    "sg:postcode":"83873",
    "sg:province":"ID",
    "wof:name":"Wallace Vintage Games",
    "wof:placetype":"venue"
},
  "geometry": {"coordinates":[-115.924013,47.47249],"type":"Point"}
}