{
  "type": "Feature",
  "properties": {
    "iso:country":"US",
    "sg:address":"5123 Glenwood St",
    "sg:city":"Boise",
    "sg:classifiers":[
        {
            "category":"Wholesale",
            "subcategory":"Electrical",
            "type":"Manufacturing & Wholesale Goods"
        }
    ],
    "sg:phone":"+1 208 321 7422",
    "sg:postcode":"83714",
    "sg:province":"ID",
    "sg:tags":[
        "testing",
        "apparatus"
    ],
    "wof:name":"Prometric Testing",
    "wof:placetype":"venue"
},
  "geometry": {"coordinates":[-116.279825,43.651073],"type":"Point"}
}