{
  "type": "Feature",
  "properties": {
    "iso:country":"US",
    "sg:address":"603 2nd St S",
    "sg:city":"Nampa",
    "sg:classifiers":[
        {
            "category":"Health Services",
            "subcategory":"Medical Lab",
            "type":"Services"
        }
    ],
    "sg:phone":"+1 208 461 5151",
    "sg:postcode":"83651",
    "sg:province":"ID",
    "sg:tags":[
        "detection",
        "equipment",
        "drug"
    ],
    "wof:name":"Advanced Drug Detection",
    "wof:placetype":"venue"
},
  "geometry": {"coordinates":[-116.56705599999999,43.58227],"type":"Point"}
}