{
  "type": "Feature",
  "properties": {
    "iso:country":"US",
    "sg:address":"635 Falcon St",
    "sg:city":"Mountain Hm Afb",
    "sg:classifiers":[
        {
            "category":"Education",
            "subcategory":"College",
            "type":"Public Place"
        }
    ],
    "sg:phone":"+1 208 828 4188",
    "sg:postcode":"83648",
    "sg:province":"ID",
    "sg:tags":[
        "academic",
        "school"
    ],
    "wof:name":"University Of Oklahoma",
    "wof:placetype":"venue"
},
  "geometry": {"coordinates":[-115.85371499999999,43.051698],"type":"Point"}
}