{
  "type": "Feature",
  "properties": {
    "addr:full":"4217 Garrity Blvd Nampa ID 83687",
    "addr:housenumber":"4217",
    "addr:postcode":"83687",
    "addr:street":"Garrity Blvd",
    "iso:country":"US",
    "sg:address":"4217 Garrity Blvd",
    "sg:city":"Nampa",
    "sg:classifiers":[
        {
            "category":"Banks & Credit Unions",
            "subcategory":"Bank",
            "type":"Services"
        }
    ],
    "sg:phone":"+1 208 468 9044",
    "sg:postcode":"83687",
    "sg:province":"ID",
    "sg:tags":[
        "cashing",
        "check"
    ],
    "wof:name":"ACE Cash Express",
    "wof:placetype":"venue"
},
  "geometry": {"coordinates":[-116.518952,43.594022],"type":"Point"}
}