{
  "type": "Feature",
  "properties": {
    "iso:country":"US",
    "sg:address":"5950 W Hayden Ave",
    "sg:city":"Rathdrum",
    "sg:classifiers":[
        {
            "category":"Professional",
            "subcategory":"Management & Consulting",
            "type":"Services"
        }
    ],
    "sg:phone":"+1 208 687 0760",
    "sg:postcode":"83858",
    "sg:province":"ID",
    "wof:name":"Hanson & Associates",
    "wof:placetype":"venue"
},
  "geometry": {"coordinates":[-116.858035,47.759259],"type":"Point"}
}