{
  "type": "Feature",
  "properties": {
    "addr:full":"360 3rd Ave S Ketchum ID 83340",
    "addr:housenumber":"360",
    "addr:postcode":"83340",
    "addr:street":"3Rd Ave S",
    "iso:country":"US",
    "sg:address":"360 3rd Ave S",
    "sg:city":"Ketchum",
    "sg:classifiers":[
        {
            "category":"Personal",
            "subcategory":"Beauty Salon",
            "type":"Services"
        }
    ],
    "sg:phone":"+1 208 726 1772",
    "sg:postcode":"83340",
    "sg:province":"ID",
    "sg:tags":[
        "manicuring"
    ],
    "wof:name":"Ketchum Nail Salon",
    "wof:placetype":"venue"
},
  "geometry": {"coordinates":[-114.365724,43.67608],"type":"Point"}
}