{
  "type": "Feature",
  "properties": {
    "iso:country":"US",
    "sg:address":"9685 Silver Leaf Rd",
    "sg:city":"Emmett",
    "sg:phone":"+1 208 365 7714",
    "sg:postcode":"83617",
    "sg:province":"ID",
    "sg:tags":[
        "farm",
        "field",
        "crop"
    ],
    "wof:name":"Skip Scott",
    "wof:placetype":"venue"
},
  "geometry": {"coordinates":[-116.685349,43.94515],"type":"Point"}
}