{
  "type": "Feature",
  "properties": {
    "iso:country":"US",
    "sg:address":"566 E Fork Rd",
    "sg:city":"Hailey",
    "sg:classifiers":[
        {
            "category":"Autos & Motor Vehicles",
            "subcategory":"Automobile Sales",
            "type":"Retail Goods"
        }
    ],
    "sg:phone":"+1 208 788 7076",
    "sg:postcode":"83340",
    "sg:province":"ID",
    "wof:name":"Andrew K Bick Inc",
    "wof:placetype":"venue"
},
  "geometry": {"coordinates":[-114.252708,43.645514],"type":"Point"}
}