{
  "type": "Feature",
  "properties": {
    "iso:country":"US",
    "sg:address":"40 W Main St",
    "sg:city":"St Anthony",
    "sg:classifiers":[
        {
            "category":"Building & Trades",
            "subcategory":"Plumbing",
            "type":"Services"
        }
    ],
    "sg:phone":"+1 208 624 3772",
    "sg:postcode":"83445",
    "sg:province":"ID",
    "sg:tags":[
        "plumbing",
        "contractor"
    ],
    "wof:name":"Housley Pumps Sales & Svc",
    "wof:placetype":"venue"
},
  "geometry": {"coordinates":[-111.683463,43.966311],"type":"Point"}
}