{
  "type": "Feature",
  "properties": {
    "addr:full":"111 S Meadow St Grangeville ID 83530",
    "addr:housenumber":"111",
    "addr:postcode":"83530",
    "addr:street":"S Meadow St",
    "iso:country":"US",
    "sg:address":"111 S Meadow St",
    "sg:city":"Grangeville",
    "sg:classifiers":[
        {
            "category":"Organizations",
            "subcategory":"Community Association",
            "type":"Services"
        }
    ],
    "sg:phone":"+1 208 983 1761",
    "sg:postcode":"83530",
    "sg:province":"ID",
    "sg:tags":[
        "fraternal"
    ],
    "wof:name":"Elks Lodge",
    "wof:placetype":"venue"
},
  "geometry": {"coordinates":[-116.11845599999999,45.924718],"type":"Point"}
}