{
  "type": "Feature",
  "properties": {
    "addr:full":"1448 E Center St Pocatello ID 83201",
    "addr:housenumber":"1448",
    "addr:postcode":"83201",
    "addr:street":"E Center St",
    "iso:country":"US",
    "sg:address":"1448 E Center St",
    "sg:city":"Pocatello",
    "sg:classifiers":[
        {
            "category":"Health Services",
            "subcategory":"Health Practitioner",
            "type":"Services"
        }
    ],
    "sg:phone":"+1 208 233 3237",
    "sg:postcode":"83201",
    "sg:province":"ID",
    "sg:tags":[
        "medicine",
        "alternative"
    ],
    "wof:name":"Stillwaters Acupuncture",
    "wof:placetype":"venue"
},
  "geometry": {"coordinates":[-112.433357,42.873004],"type":"Point"}
}