{
  "type": "Feature",
  "properties": {
    "iso:country":"US",
    "sg:address":"270 N Linder Rd",
    "sg:city":"Meridian",
    "sg:classifiers":[
        {
            "category":"Retail",
            "subcategory":"Auto Repair",
            "type":"Services"
        }
    ],
    "sg:phone":"+1 208 887 7993",
    "sg:postcode":"83642",
    "sg:province":"ID",
    "sg:tags":[
        "trailer"
    ],
    "wof:name":"Wilson Trailer Co",
    "wof:placetype":"venue"
},
  "geometry": {"coordinates":[-116.413546,43.607128],"type":"Point"}
}