{
  "type": "Feature",
  "properties": {
    "addr:full":"7596 Mohawk St Bonners Ferry ID 83805",
    "addr:housenumber":"7596",
    "addr:postcode":"83805",
    "addr:street":"Mohawk St",
    "iso:country":"US",
    "sg:address":"7596 Mohawk St",
    "sg:city":"Bonners Ferry",
    "sg:classifiers":[
        {
            "category":"Professional",
            "subcategory":"Art Services",
            "type":"Services"
        }
    ],
    "sg:phone":"+1 208 267 5586",
    "sg:postcode":"83805",
    "sg:province":"ID",
    "sg:tags":[
        "photographer"
    ],
    "wof:name":"Brent Rosengrant Photography",
    "wof:placetype":"venue"
},
  "geometry": {"coordinates":[-116.313776,48.703709],"type":"Point"}
}