{
  "type": "Feature",
  "properties": {
    "addr:full":"196 N State St Preston ID 83263",
    "addr:housenumber":"196",
    "addr:postcode":"83263",
    "addr:street":"N State St",
    "iso:country":"US",
    "sg:address":"196 N State St",
    "sg:city":"Preston",
    "sg:classifiers":[
        {
            "category":"Restaurant",
            "type":"Food & Drink"
        }
    ],
    "sg:menulink":"http://www.allmenus.com/id/preston/157621-taco-maker/menu/",
    "sg:phone":"+1 208 852 3241",
    "sg:postcode":"83263",
    "sg:province":"ID",
    "sg:tags":[
        "mexican"
    ],
    "wof:name":"Taco Maker",
    "wof:placetype":"venue"
},
  "geometry": {"coordinates":[-111.876608,42.100356],"type":"Point"}
}