{
  "type": "Feature",
  "properties": {
    "iso:country":"US",
    "sg:address":"5122 W Stoker Ln",
    "sg:city":"Boise",
    "sg:classifiers":[
        {
            "category":"Real Estate",
            "subcategory":"Real Estate Operator",
            "type":"Services"
        }
    ],
    "sg:phone":"+1 208 853 8109",
    "sg:postcode":"83703",
    "sg:province":"ID",
    "sg:tags":[
        "apartment"
    ],
    "wof:name":"Blue Meadow Apartments",
    "wof:placetype":"venue"
},
  "geometry": {"coordinates":[-116.252494,43.653685],"type":"Point"}
}