{
  "type": "Feature",
  "properties": {
    "iso:country":"US",
    "sg:address":"6385 Grandview Dr",
    "sg:city":"Boise",
    "sg:classifiers":[
        {
            "category":"Professional",
            "subcategory":"Business Services",
            "type":"Services"
        }
    ],
    "sg:phone":"+1 208 377 4395",
    "sg:postcode":"83709",
    "sg:province":"ID",
    "wof:name":"4t Gold Enterprises Ltd",
    "wof:placetype":"venue"
},
  "geometry": {"coordinates":[-116.26079900000001,43.584591],"type":"Point"}
}