{
  "type": "Feature",
  "properties": {
    "iso:country":"US",
    "sg:address":"600 N Curtis Rd",
    "sg:city":"Boise",
    "sg:classifiers":[
        {
            "category":"Social Services",
            "type":"Services"
        }
    ],
    "sg:phone":"+1 208 376 7439",
    "sg:postcode":"83706",
    "sg:province":"ID",
    "sg:tags":[
        "organization",
        "welfare"
    ],
    "wof:name":"MTM",
    "wof:placetype":"venue"
},
  "geometry": {"coordinates":[-116.25363,43.611649],"type":"Point"}
}