{
  "type": "Feature",
  "properties": {
    "iso:country":"US",
    "sg:address":"42 E 100 N",
    "sg:city":"Malad City",
    "sg:classifiers":[
        {
            "category":"Wholesale",
            "subcategory":"Construction Materials",
            "type":"Manufacturing & Wholesale Goods"
        }
    ],
    "sg:phone":"+1 208 766 3535",
    "sg:postcode":"83252",
    "sg:province":"ID",
    "sg:tags":[
        "sand",
        "gravel"
    ],
    "wof:name":"Dale Beckstead Gravel & Fill",
    "wof:placetype":"venue"
},
  "geometry": {"coordinates":[-112.24290499999999,42.187483],"type":"Point"}
}