{
  "type": "Feature",
  "properties": {
    "addr:full":"304 Rio Vista Blvd Mc Call ID 83638",
    "addr:housenumber":"304",
    "addr:postcode":"83638",
    "addr:street":"Rio Vista Blvd Mc Call",
    "iso:country":"US",
    "sg:address":"304 Rio Vista Blvd",
    "sg:city":"Mc Call",
    "sg:classifiers":[
        {
            "category":"Shopping",
            "subcategory":"Bicycles & Sporting Goods",
            "type":"Retail Goods"
        }
    ],
    "sg:phone":"+1 208 634 2075",
    "sg:postcode":"83638",
    "sg:province":"ID",
    "sg:tags":[
        "equipment"
    ],
    "wof:name":"Class VI Whitewater",
    "wof:placetype":"venue"
},
  "geometry": {"coordinates":[-116.11500100000001,44.899154],"type":"Point"}
}