{
  "type": "Feature",
  "properties": {
    "iso:country":"US",
    "sg:address":"2405 E Deer Flat Rd",
    "sg:city":"Kuna",
    "sg:classifiers":[
        {
            "category":"Manufacturing",
            "subcategory":"Lumber",
            "type":"Manufacturing & Wholesale Goods"
        }
    ],
    "sg:phone":"+1 208 922 3561",
    "sg:postcode":"83634",
    "sg:province":"ID",
    "sg:tags":[
        "operation",
        "timber",
        "tract"
    ],
    "wof:name":"High Desert Tree Farm",
    "wof:placetype":"venue"
},
  "geometry": {"coordinates":[-116.38583199999999,43.502725],"type":"Point"}
}