{
  "type": "Feature",
  "properties": {
    "iso:country":"US",
    "sg:address":"3016 Rush Creek Rd",
    "sg:city":"Cambridge",
    "sg:classifiers":[
        {
            "category":"Ferry",
            "type":"Transportation"
        }
    ],
    "sg:phone":"+1 208 257 3477",
    "sg:postcode":"83610",
    "sg:province":"ID",
    "sg:tags":[
        "river",
        "trip"
    ],
    "sg:website":"www.hughesriver.com",
    "wof:name":"Hughes River Expeditions",
    "wof:placetype":"venue"
},
  "geometry": {"coordinates":[-116.699026,44.592889],"type":"Point"}
}