{
  "type": "Feature",
  "properties": {
    "addr:full":"1400 E Terry St Pocatello ID 83201",
    "addr:housenumber":"1400",
    "addr:postcode":"83201",
    "addr:street":"E Terry St",
    "iso:country":"US",
    "sg:address":"1400 E Terry St",
    "sg:city":"Pocatello",
    "sg:classifiers":[
        {
            "category":"Health Services",
            "subcategory":"Health Practitioner",
            "type":"Services"
        }
    ],
    "sg:phone":"+1 208 282 2129",
    "sg:postcode":"83201",
    "sg:province":"ID",
    "sg:tags":[
        "psychologist"
    ],
    "wof:name":"Id State Univ Psychology Clinc",
    "wof:placetype":"venue"
},
  "geometry": {"coordinates":[-112.428392,42.865716],"type":"Point"}
}