{
  "type": "Feature",
  "properties": {
    "iso:country":"US",
    "sg:address":"222 E 11th St",
    "sg:city":"Burley",
    "sg:classifiers":[
        {
            "category":"Shopping",
            "subcategory":"Books",
            "type":"Retail Goods"
        }
    ],
    "sg:phone":"+1 208 878 2505",
    "sg:postcode":"83318",
    "sg:province":"ID",
    "sg:tags":[
        "dealer"
    ],
    "wof:name":"Book Plaza",
    "wof:placetype":"venue"
},
  "geometry": {"coordinates":[-113.791699,42.53948],"type":"Point"}
}