{
  "type": "Feature",
  "properties": {
    "addr:full":"3918 Overland Rd Boise ID 83705",
    "addr:housenumber":"3918",
    "addr:postcode":"83705",
    "addr:street":"Overland Rd",
    "iso:country":"US",
    "sg:address":"3918 Overland Rd",
    "sg:city":"Boise",
    "sg:classifiers":[
        {
            "category":"Retail",
            "subcategory":"Car Wash",
            "type":"Services"
        }
    ],
    "sg:phone":"+1 208 344 8316",
    "sg:postcode":"83705",
    "sg:province":"ID",
    "sg:tags":[
        "automobile",
        "detail",
        "clean"
    ],
    "wof:name":"Franco Auto Detail",
    "wof:placetype":"venue"
},
  "geometry": {"coordinates":[-116.22925499999999,43.589875],"type":"Point"}
}