{
  "type": "Feature",
  "properties": {
    "addr:full":"1400 N Eagle Rd Meridian ID 83642",
    "addr:housenumber":"1400",
    "addr:postcode":"83642",
    "addr:street":"N Eagle Rd",
    "iso:country":"US",
    "sg:address":"1400 N Eagle Rd",
    "sg:city":"Meridian",
    "sg:classifiers":[
        {
            "category":"Wholesale",
            "subcategory":"Wine & Distilled Alcoholic Beverages",
            "type":"Manufacturing & Wholesale Goods"
        },
        {
            "category":"Food & Beverages",
            "subcategory":"Liquor & Beverages",
            "type":"Retail Goods"
        }
    ],
    "sg:phone":"+1 208 855 9230",
    "sg:postcode":"83642",
    "sg:province":"ID",
    "wof:name":"A New Vintage Wine Shop",
    "wof:placetype":"venue"
},
  "geometry": {"coordinates":[-116.354461,43.617628],"type":"Point"}
}