{
  "type": "Feature",
  "properties": {
    "addr:full":"5369 Irving St Boise ID 83706",
    "addr:housenumber":"5369",
    "addr:postcode":"83706",
    "addr:street":"Irving St",
    "iso:country":"US",
    "sg:address":"5369 Irving St",
    "sg:city":"Boise",
    "sg:classifiers":[
        {
            "category":"Professional",
            "subcategory":"Computer Services",
            "type":"Services"
        }
    ],
    "sg:phone":"+1 208 322 1540",
    "sg:postcode":"83706",
    "sg:province":"ID",
    "sg:website":"www.simplot.com",
    "wof:name":"J R Simplot Co",
    "wof:placetype":"venue"
},
  "geometry": {"coordinates":[-116.246627,43.615165],"type":"Point"}
}