{
  "type": "Feature",
  "properties": {
    "iso:country":"US",
    "sg:address":"160 E Main St",
    "sg:city":"Rigby",
    "sg:classifiers":[
        {
            "category":"Restaurant",
            "type":"Food & Drink"
        }
    ],
    "sg:phone":"+1 208 745 0010",
    "sg:postcode":"83442",
    "sg:province":"ID",
    "wof:name":"Papa Kelsey's Pizza & Subs",
    "wof:placetype":"venue"
},
  "geometry": {"coordinates":[-111.912494,43.672151],"type":"Point"}
}