{
  "type": "Feature",
  "properties": {
    "addr:full":"2060 S Eagle Rd Kuna ID 83634",
    "addr:housenumber":"2060",
    "addr:postcode":"83634",
    "addr:street":"S Eagle Rd",
    "iso:country":"US",
    "sg:address":"2060 S Eagle Rd",
    "sg:city":"Kuna",
    "sg:classifiers":[
        {
            "category":"Real Estate",
            "subcategory":"Real Estate Agent",
            "type":"Services"
        }
    ],
    "sg:phone":"+1 208 323 1477",
    "sg:postcode":"83634",
    "sg:province":"ID",
    "sg:tags":[
        "appraiser"
    ],
    "wof:name":"Digital Appraisals",
    "wof:placetype":"venue"
},
  "geometry": {"coordinates":[-116.354375,43.468906],"type":"Point"}
}