{
  "type": "Feature",
  "properties": {
    "addr:full":"1876 E 2900 S Wendell ID 83355",
    "addr:housenumber":"1876",
    "addr:postcode":"83355",
    "addr:street":"E 2900 S",
    "iso:country":"US",
    "sg:address":"1876 E 2900 S",
    "sg:city":"Wendell",
    "sg:classifiers":[
        {
            "category":"Professional",
            "type":"Services"
        }
    ],
    "sg:phone":"+1 208 536 2574",
    "sg:postcode":"83355",
    "sg:province":"ID",
    "sg:tags":[
        "establishment"
    ],
    "wof:name":"J& R Equipment & Parts",
    "wof:placetype":"venue"
},
  "geometry": {"coordinates":[-114.717483,42.782725],"type":"Point"}
}