{
  "type": "Feature",
  "properties": {
    "addr:full":"2308 E Franklin Rd Meridian ID 83642",
    "addr:housenumber":"2308",
    "addr:postcode":"83642",
    "addr:street":"E Franklin Rd",
    "iso:country":"US",
    "sg:address":"2308 E Franklin Rd",
    "sg:city":"Meridian",
    "sg:classifiers":[
        {
            "category":"Real Estate",
            "subcategory":"Real Estate Operator",
            "type":"Services"
        }
    ],
    "sg:phone":"+1 208 887 1686",
    "sg:postcode":"83642",
    "sg:province":"ID",
    "sg:tags":[
        "apartment"
    ],
    "wof:name":"Meridian Foothills Apartments",
    "wof:placetype":"venue"
},
  "geometry": {"coordinates":[-116.36462299999999,43.604893],"type":"Point"}
}