{
  "type": "Feature",
  "properties": {
    "iso:country":"US",
    "sg:address":"331 Ave D",
    "sg:city":"Kuna",
    "sg:classifiers":[
        {
            "category":"Food & Beverages",
            "subcategory":"Groceries & Convenience Stores",
            "type":"Retail Goods"
        }
    ],
    "sg:phone":"+1 208 922 4506",
    "sg:postcode":"83634",
    "sg:province":"ID",
    "wof:name":"Super C",
    "wof:placetype":"venue"
},
  "geometry": {"coordinates":[-116.419507,43.49056],"type":"Point"}
}