{
  "type": "Feature",
  "properties": {
    "addr:full":"845 W Center St Pocatello ID 83204",
    "addr:housenumber":"845",
    "addr:postcode":"83204",
    "addr:street":"W Center St",
    "iso:country":"US",
    "sg:address":"845 W Center St",
    "sg:city":"Pocatello",
    "sg:classifiers":[
        {
            "category":"Real Estate",
            "subcategory":"Real Estate Operator",
            "type":"Services"
        }
    ],
    "sg:phone":"+1 208 233 5580",
    "sg:postcode":"83204",
    "sg:province":"ID",
    "sg:tags":[
        "building",
        "nonresidential"
    ],
    "wof:name":"Poco II LLC",
    "wof:placetype":"venue"
},
  "geometry": {"coordinates":[-112.45584700000001,42.858811],"type":"Point"}
}