{
  "type": "Feature",
  "properties": {
    "iso:country":"US",
    "sg:address":"6614 W State St",
    "sg:city":"Boise",
    "sg:classifiers":[
        {
            "category":"Autos & Motor Vehicles",
            "subcategory":"Automobile Sales",
            "type":"Retail Goods"
        },
        {
            "category":"Real Estate",
            "subcategory":"Real Estate Operator",
            "type":"Services"
        }
    ],
    "sg:phone":"+1 208 853 4400",
    "sg:postcode":"83714",
    "sg:province":"ID",
    "sg:tags":[
        "used",
        "mobile",
        "car",
        "site",
        "home",
        "dealer"
    ],
    "wof:name":"Plantation Park & Sell",
    "wof:placetype":"venue"
},
  "geometry": {"coordinates":[-116.269374,43.66204],"type":"Point"}
}