{
  "type": "Feature",
  "properties": {
    "iso:country":"US",
    "sg:address":"532 Blue Lakes Blvd N",
    "sg:city":"Twin Falls",
    "sg:classifiers":[
        {
            "category":"Social Services",
            "subcategory":"Job Training",
            "type":"Services"
        }
    ],
    "sg:phone":"+1 208 678 1673",
    "sg:postcode":"83301",
    "sg:province":"ID",
    "wof:name":"Skills Resource Training Ctr",
    "wof:placetype":"venue"
},
  "geometry": {"coordinates":[-114.460245,42.570978],"type":"Point"}
}