{
  "type": "Feature",
  "properties": {
    "addr:full":"3810 11th St E Lewiston ID 83501",
    "addr:housenumber":"3810",
    "addr:postcode":"83501",
    "addr:street":"11Th St E",
    "iso:country":"US",
    "sg:address":"3810 11th St E",
    "sg:city":"Lewiston",
    "sg:classifiers":[
        {
            "category":"Building & Trades",
            "subcategory":"Electrical",
            "type":"Services"
        }
    ],
    "sg:phone":"+1 208 743 8734",
    "sg:postcode":"83501",
    "sg:province":"ID",
    "sg:tags":[
        "electrician"
    ],
    "wof:name":"Elben Communications",
    "wof:placetype":"venue"
},
  "geometry": {"coordinates":[-116.96990099999999,46.365686],"type":"Point"}
}