{
  "type": "Feature",
  "properties": {
    "addr:full":"6111 N Mt Carrol St Dalton Gardens ID 83815",
    "addr:housenumber":"6111",
    "addr:postcode":"83815",
    "addr:street":"N Mt Carrol St",
    "iso:country":"US",
    "sg:address":"6111 N Mt Carrol St",
    "sg:city":"Dalton Gardens",
    "sg:classifiers":[
        {
            "category":"Real Estate",
            "subcategory":"Real Estate Agent",
            "type":"Services"
        }
    ],
    "sg:phone":"+1 208 772 0477",
    "sg:postcode":"83815",
    "sg:province":"ID",
    "sg:tags":[
        "appraiser"
    ],
    "wof:name":"First Team Real Estate Svc",
    "wof:placetype":"venue"
},
  "geometry": {"coordinates":[-116.77063699999999,47.725183],"type":"Point"}
}