{
  "type": "Feature",
  "properties": {
    "iso:country":"US",
    "sg:address":"150 E Quinn Rd",
    "sg:city":"Pocatello",
    "sg:classifiers":[
        {
            "category":"Shopping",
            "subcategory":"Computers & Home Electronics",
            "type":"Retail Goods"
        }
    ],
    "sg:phone":"+1 208 232 1655",
    "sg:postcode":"83201",
    "sg:province":"ID",
    "sg:tags":[
        "equipment",
        "satellite",
        "system"
    ],
    "wof:name":"Merlins TV",
    "wof:placetype":"venue"
},
  "geometry": {"coordinates":[-112.449876,42.905916],"type":"Point"}
}