{
  "type": "Feature",
  "properties": {
    "iso:country":"US",
    "sg:address":"352 N 150 W",
    "sg:city":"Blackfoot",
    "sg:classifiers":[
        {
            "category":"Professional",
            "type":"Services"
        }
    ],
    "sg:phone":"+1 208 785 6456",
    "sg:postcode":"83221",
    "sg:province":"ID",
    "wof:name":"Lifestyle Solutions",
    "wof:placetype":"venue"
},
  "geometry": {"coordinates":[-112.326302,43.254209],"type":"Point"}
}