{
  "type": "Feature",
  "properties": {
    "iso:country":"US",
    "sg:address":"2800 N Wendell Rd",
    "sg:city":"Wendell",
    "sg:classifiers":[
        {
            "category":"Wholesale",
            "subcategory":"Vending Machines",
            "type":"Manufacturing & Wholesale Goods"
        }
    ],
    "sg:phone":"+1 208 536 5140",
    "sg:postcode":"83355",
    "sg:province":"ID",
    "sg:tags":[
        "operator"
    ],
    "wof:name":"North Star Vending",
    "wof:placetype":"venue"
},
  "geometry": {"coordinates":[-114.706462,42.798047],"type":"Point"}
}