{
  "type": "Feature",
  "properties": {
    "addr:full":"4193 N 1380 E Buhl ID 83316",
    "addr:housenumber":"4193;1380 e",
    "addr:postcode":"83316",
    "addr:street":"N",
    "iso:country":"US",
    "sg:address":"4193 N 1380 E",
    "sg:city":"Buhl",
    "sg:classifiers":[
        {
            "category":"Retail",
            "subcategory":"Auto Repair",
            "type":"Services"
        }
    ],
    "sg:phone":"+1 208 543 5460",
    "sg:postcode":"83316",
    "sg:province":"ID",
    "sg:tags":[
        "body",
        "automobile",
        "painting"
    ],
    "wof:name":"Dean's Buhl Collision Repair",
    "wof:placetype":"venue"
},
  "geometry": {"coordinates":[-114.77821,42.607588],"type":"Point"}
}