{
  "type": "Feature",
  "properties": {
    "addr:full":"3110 Brown St Boise ID 83714",
    "addr:housenumber":"3110",
    "addr:postcode":"83714",
    "addr:street":"Brown St",
    "iso:country":"US",
    "sg:address":"3110 Brown St",
    "sg:city":"Boise",
    "sg:classifiers":[
        {
            "category":"Restaurant",
            "type":"Food & Drink"
        }
    ],
    "sg:phone":"+1 208 338 6632",
    "sg:postcode":"83714",
    "sg:province":"ID",
    "wof:name":"Kessler's Cafe",
    "wof:placetype":"venue"
},
  "geometry": {"coordinates":[-116.238394,43.620406],"type":"Point"}
}