{
  "type": "Feature",
  "properties": {
    "iso:country":"US",
    "sg:address":"404 Holly St",
    "sg:city":"Nampa",
    "sg:classifiers":[
        {
            "category":"Banks & Credit Unions",
            "subcategory":"Bank",
            "type":"Services"
        }
    ],
    "sg:phone":"+1 208 459 3500",
    "sg:postcode":"83686",
    "sg:province":"ID",
    "wof:name":"Canyon Medical Health CU",
    "wof:placetype":"venue"
},
  "geometry": {"coordinates":[-116.564246,43.565394],"type":"Point"}
}