{
  "type": "Feature",
  "properties": {
    "addr:full":"523 River St Salmon ID 83467",
    "addr:housenumber":"523",
    "addr:postcode":"83467",
    "addr:street":"River St",
    "iso:country":"US",
    "sg:address":"523 River St",
    "sg:city":"Salmon",
    "sg:classifiers":[
        {
            "category":"Education",
            "subcategory":"Special Training",
            "type":"Public Place"
        }
    ],
    "sg:phone":"+1 208 756 2813",
    "sg:postcode":"83467",
    "sg:province":"ID",
    "wof:name":"Db Piano Studio",
    "wof:placetype":"venue"
},
  "geometry": {"coordinates":[-113.901752,45.17272],"type":"Point"}
}