{
  "type": "Feature",
  "properties": {
    "addr:full":"1512 N 10th St Boise ID 83702",
    "addr:housenumber":"1512",
    "addr:postcode":"83702",
    "addr:street":"N 10Th St",
    "iso:country":"US",
    "sg:address":"1512 N 10th St",
    "sg:city":"Boise",
    "sg:classifiers":[
        {
            "category":"Recreation",
            "type":"Entertainment"
        }
    ],
    "sg:phone":"+1 208 387 0410",
    "sg:postcode":"83702",
    "sg:province":"ID",
    "wof:name":"Tekio Seishin Kai",
    "wof:placetype":"venue"
},
  "geometry": {"coordinates":[-116.199809,43.629164],"type":"Point"}
}