{
  "type": "Feature",
  "properties": {
    "addr:full":"1034 Cedar Ave Lewiston ID 83501",
    "addr:housenumber":"1034",
    "addr:postcode":"83501",
    "addr:street":"Cedar Ave",
    "iso:country":"US",
    "sg:address":"1034 Cedar Ave",
    "sg:city":"Lewiston",
    "sg:classifiers":[
        {
            "category":"Retail",
            "subcategory":"Laundry & Dry Cleaning",
            "type":"Services"
        }
    ],
    "sg:phone":"+1 208 743 6337",
    "sg:postcode":"83501",
    "sg:province":"ID",
    "sg:tags":[
        "cleaners",
        "rug",
        "carpet"
    ],
    "wof:name":"Valley Carpet Care",
    "wof:placetype":"venue"
},
  "geometry": {"coordinates":[-116.976996,46.374816],"type":"Point"}
}