{
  "type": "Feature",
  "properties": {
    "iso:country":"US",
    "sg:address":"4271 E 3700 N",
    "sg:city":"Hansen",
    "sg:classifiers":[
        {
            "category":"Wholesale",
            "subcategory":"Farm Supplies",
            "type":"Manufacturing & Wholesale Goods"
        }
    ],
    "sg:phone":"+1 208 423 5511",
    "sg:postcode":"83334",
    "sg:province":"ID",
    "sg:tags":[
        "fertilizer"
    ],
    "wof:name":"Western Farm Svc",
    "wof:placetype":"venue"
},
  "geometry": {"coordinates":[-114.211748,42.53297],"type":"Point"}
}