{
  "type": "Feature",
  "properties": {
    "iso:country":"US",
    "sg:address":"6003 Overland Rd",
    "sg:city":"Boise",
    "sg:classifiers":[
        {
            "category":"Building & Trades",
            "subcategory":"Construction",
            "type":"Services"
        }
    ],
    "sg:phone":"+1 208 376 2388",
    "sg:postcode":"83709",
    "sg:province":"ID",
    "sg:tags":[
        "home",
        "builder"
    ],
    "wof:name":"New Homes Access",
    "wof:placetype":"venue"
},
  "geometry": {"coordinates":[-116.256882,43.589937],"type":"Point"}
}