{
  "type": "Feature",
  "properties": {
    "iso:country":"US",
    "sg:address":"1014 Main St",
    "sg:city":"Lewiston",
    "sg:classifiers":[
        {
            "category":"Real Estate",
            "subcategory":"Real Estate Agent",
            "type":"Services"
        }
    ],
    "sg:phone":"+1 208 746 9891",
    "sg:postcode":"83501",
    "sg:province":"ID",
    "sg:tags":[
        "appraiser"
    ],
    "wof:name":"Western Appraisals",
    "wof:placetype":"venue"
},
  "geometry": {"coordinates":[-117.020437,46.419242],"type":"Point"}
}