{
  "type": "Feature",
  "properties": {
    "addr:full":"17355 N Circle S Trl Rathdrum ID 83858",
    "addr:housenumber":"17355",
    "addr:postcode":"83858",
    "addr:street":"N Circle S Trl",
    "iso:country":"US",
    "sg:address":"17355 N Circle S Trl",
    "sg:city":"Rathdrum",
    "sg:classifiers":[
        {
            "category":"Professional",
            "subcategory":"Business Services",
            "type":"Services"
        }
    ],
    "sg:phone":"+1 208 687 1315",
    "sg:postcode":"83858",
    "sg:province":"ID",
    "sg:tags":[
        "water",
        "hauling"
    ],
    "wof:name":"Standish Water Trucks",
    "wof:placetype":"venue"
},
  "geometry": {"coordinates":[-116.79714800000001,47.82817],"type":"Point"}
}