{
  "type": "Feature",
  "properties": {
    "addr:full":"3736 State Hwy 6 Princeton ID 83857",
    "addr:housenumber":"3736",
    "addr:postcode":"83857",
    "addr:street":"State Hwy 6",
    "iso:country":"US",
    "sg:address":"3736 State Hwy 6",
    "sg:city":"Princeton",
    "sg:phone":"+1 208 875 0281",
    "sg:postcode":"83857",
    "sg:province":"ID",
    "sg:tags":[
        "farm",
        "wheat",
        "grain",
        "cash"
    ],
    "wof:name":"Dean Butterfield",
    "wof:placetype":"venue"
},
  "geometry": {"coordinates":[-116.832888,46.913824],"type":"Point"}
}