{
  "type": "Feature",
  "properties": {
    "addr:full":"743 S 50 W Burley ID 83318",
    "addr:housenumber":"743;50",
    "addr:postcode":"83318",
    "addr:street":"S;W Burley",
    "iso:country":"US",
    "sg:address":"743 S 50 W",
    "sg:city":"Burley",
    "sg:classifiers":[
        {
            "category":"Farming",
            "subcategory":"Farm",
            "type":"Manufacturing & Wholesale Goods"
        }
    ],
    "sg:phone":"+1 208 677 2038",
    "sg:postcode":"83318",
    "sg:province":"ID",
    "sg:tags":[
        "crop",
        "general"
    ],
    "wof:name":"Alan B Garrard Farms Inc",
    "wof:placetype":"venue"
},
  "geometry": {"coordinates":[-113.803804,42.425546],"type":"Point"}
}