{
  "type": "Feature",
  "properties": {
    "iso:country":"US",
    "sg:address":"4425 Burley Dr",
    "sg:city":"Chubbuck",
    "sg:classifiers":[
        {
            "category":"Banks & Credit Unions",
            "subcategory":"Bank",
            "type":"Services"
        }
    ],
    "sg:phone":"+1 208 239 3000",
    "sg:postcode":"83202",
    "sg:province":"ID",
    "wof:name":"Idaho Central Credit Union",
    "wof:placetype":"venue"
},
  "geometry": {"coordinates":[-112.461293,42.914991],"type":"Point"}
}