{
  "type": "Feature",
  "properties": {
    "addr:full":"1280 Filer Ave E Twin Falls ID 83301",
    "addr:housenumber":"1280",
    "addr:postcode":"83301",
    "addr:street":"Filer Ave E",
    "iso:country":"US",
    "sg:address":"1280 Filer Ave E",
    "sg:city":"Twin Falls",
    "sg:classifiers":[
        {
            "category":"Home & Garden",
            "subcategory":"Building Materials",
            "type":"Retail Goods"
        }
    ],
    "sg:phone":"+1 208 733 5333",
    "sg:postcode":"83301",
    "sg:province":"ID",
    "sg:tags":[
        "paint"
    ],
    "sg:website":"www.kellymoore.com",
    "wof:name":"Kelley-Moore Paint Co",
    "wof:placetype":"venue"
},
  "geometry": {"coordinates":[-114.45822800000001,42.570332],"type":"Point"}
}