{
  "type": "Feature",
  "properties": {
    "iso:country":"US",
    "sg:address":"9873 N Government Way",
    "sg:city":"Hayden",
    "sg:classifiers":[
        {
            "category":"Wholesale",
            "subcategory":"Farm Supplies",
            "type":"Manufacturing & Wholesale Goods"
        }
    ],
    "sg:phone":"+1 208 762 9553",
    "sg:postcode":"83835",
    "sg:province":"ID",
    "sg:tags":[
        "feed"
    ],
    "wof:name":"Half Moon Feeds-Mill Direct",
    "wof:placetype":"venue"
},
  "geometry": {"coordinates":[-116.786632,47.760957],"type":"Point"}
}