{
  "type": "Feature",
  "properties": {
    "iso:country":"US",
    "sg:address":"5820 Oak St",
    "sg:city":"Nampa",
    "sg:classifiers":[
        {
            "category":"Manufacturing",
            "subcategory":"Printing",
            "type":"Manufacturing & Wholesale Goods"
        }
    ],
    "sg:phone":"+1 208 461 4842",
    "sg:postcode":"83687",
    "sg:province":"ID",
    "sg:tags":[
        "screen",
        "retail"
    ],
    "wof:name":"Rainbow Prints",
    "wof:placetype":"venue"
},
  "geometry": {"coordinates":[-116.499056,43.584393],"type":"Point"}
}