{
  "type": "Feature",
  "properties": {
    "iso:country":"US",
    "sg:address":"1308 W Hale St",
    "sg:city":"Boise",
    "sg:classifiers":[
        {
            "category":"Organizations",
            "subcategory":"Religious Organization",
            "type":"Services"
        }
    ],
    "sg:phone":"+1 208 343 5314",
    "sg:postcode":"83706",
    "sg:province":"ID",
    "sg:tags":[
        "church"
    ],
    "wof:name":"Euclid Community Chr-Nazarene",
    "wof:placetype":"venue"
},
  "geometry": {"coordinates":[-116.198534,43.595936],"type":"Point"}
}