{
  "type": "Feature",
  "properties": {
    "iso:country":"US",
    "sg:address":"246 E Center St",
    "sg:city":"Pocatello",
    "sg:classifiers":[
        {
            "category":"Personal",
            "subcategory":"Beauty Salon",
            "type":"Services"
        }
    ],
    "sg:phone":"+1 208 232 1614",
    "sg:postcode":"83201",
    "sg:province":"ID",
    "wof:name":"Shear Designers",
    "wof:placetype":"venue"
},
  "geometry": {"coordinates":[-112.447006,42.864374],"type":"Point"}
}