{
  "type": "Feature",
  "properties": {
    "iso:country":"US",
    "sg:address":"1 E Main St",
    "sg:city":"Franklin",
    "sg:classifiers":[
        {
            "category":"Health Services",
            "subcategory":"Doctor",
            "type":"Services"
        }
    ],
    "sg:phone":"+1 208 646 2211",
    "sg:postcode":"83263",
    "sg:province":"ID",
    "sg:tags":[
        "dentist"
    ],
    "wof:name":"Harris Denture Design",
    "wof:placetype":"venue"
},
  "geometry": {"coordinates":[-111.804273,42.017184],"type":"Point"}
}