{
  "type": "Feature",
  "properties": {
    "iso:country":"US",
    "sg:address":"1111 1st St S",
    "sg:city":"Nampa",
    "sg:classifiers":[
        {
            "category":"Autos & Motor Vehicles",
            "subcategory":"Auto Supplies",
            "type":"Retail Goods"
        }
    ],
    "sg:phone":"+1 208 466 8473",
    "sg:postcode":"83651",
    "sg:province":"ID",
    "sg:tags":[
        "tire"
    ],
    "sg:website":"www.kingsprotire.com",
    "wof:name":"King's Pro-Tire Ctr",
    "wof:placetype":"venue"
},
  "geometry": {"coordinates":[-116.560734,43.579381],"type":"Point"}
}