{
  "type": "Feature",
  "properties": {
    "iso:country":"US",
    "sg:address":"4473 S 15th W",
    "sg:city":"Idaho Falls",
    "sg:phone":"+1 208 523 0184",
    "sg:postcode":"83402",
    "sg:province":"ID",
    "sg:tags":[
        "bulk",
        "gas"
    ],
    "sg:website":"www.airgas.com",
    "wof:name":"Airgas Intermountain",
    "wof:placetype":"venue"
},
  "geometry": {"coordinates":[-112.063422,43.457871],"type":"Point"}
}