{
  "type": "Feature",
  "properties": {
    "iso:country":"US",
    "sg:address":"920 E 1200 N",
    "sg:city":"Shelley",
    "sg:classifiers":[
        {
            "category":"Professional",
            "type":"Services"
        }
    ],
    "sg:phone":"+1 208 357 3799",
    "sg:postcode":"83274",
    "sg:province":"ID",
    "sg:tags":[
        "establishment"
    ],
    "wof:name":"Alfalfa Express",
    "wof:placetype":"venue"
},
  "geometry": {"coordinates":[-112.100471,43.366834],"type":"Point"}
}