{
  "type": "Feature",
  "properties": {
    "iso:country":"US",
    "sg:address":"840 Crestmont Ave",
    "sg:city":"Idaho Falls",
    "sg:classifiers":[
        {
            "category":"Retail",
            "subcategory":"Repair Shop",
            "type":"Services"
        }
    ],
    "sg:phone":"+1 208 557 0349",
    "sg:postcode":"83402",
    "sg:province":"ID",
    "wof:name":"Corner Status Cleaning",
    "wof:placetype":"venue"
},
  "geometry": {"coordinates":[-112.05937299999999,43.502253],"type":"Point"}
}