{
  "type": "Feature",
  "properties": {
    "addr:full":"201 Arizona St Gooding ID 83330",
    "addr:housenumber":"201",
    "addr:postcode":"83330",
    "addr:street":"Arizona St",
    "iso:country":"US",
    "sg:address":"201 Arizona St",
    "sg:city":"Gooding",
    "sg:classifiers":[
        {
            "category":"Manufacturing",
            "subcategory":"Printing",
            "type":"Manufacturing & Wholesale Goods"
        }
    ],
    "sg:phone":"+1 208 934 5268",
    "sg:postcode":"83330",
    "sg:province":"ID",
    "sg:tags":[
        "publishing"
    ],
    "wof:name":"Huckleberry Press Inc",
    "wof:placetype":"venue"
},
  "geometry": {"coordinates":[-114.72044099999999,42.943542],"type":"Point"}
}