{
  "type": "Feature",
  "properties": {
    "addr:full":"1445 Fillmore St Twin Falls ID 83301",
    "addr:housenumber":"1445",
    "addr:postcode":"83301",
    "addr:street":"Fillmore St",
    "iso:country":"US",
    "sg:address":"1445 Fillmore St",
    "sg:city":"Twin Falls",
    "sg:classifiers":[
        {
            "category":"Insurance",
            "subcategory":"Insurance Agent",
            "type":"Services"
        }
    ],
    "sg:phone":"+1 208 733 2363",
    "sg:postcode":"83301",
    "sg:province":"ID",
    "wof:name":"Mony Group",
    "wof:placetype":"venue"
},
  "geometry": {"coordinates":[-114.464598,42.587329],"type":"Point"}
}