{
  "type": "Feature",
  "properties": {
    "addr:full":"5916 Clinton St Boise ID 83704",
    "addr:housenumber":"5916",
    "addr:postcode":"83704",
    "addr:street":"Clinton St",
    "iso:country":"US",
    "sg:address":"5916 Clinton St",
    "sg:city":"Boise",
    "sg:classifiers":[
        {
            "category":"Organizations",
            "subcategory":"Community Association",
            "type":"Services"
        }
    ],
    "sg:phone":"+1 208 376 5019",
    "sg:postcode":"83704",
    "sg:province":"ID",
    "sg:tags":[
        "club"
    ],
    "wof:name":"Bonami Investment Group",
    "wof:placetype":"venue"
},
  "geometry": {"coordinates":[-116.255099,43.609081],"type":"Point"}
}