{
  "type": "Feature",
  "properties": {
    "addr:full":"9055 Highlander Rd Boise ID 83709",
    "addr:housenumber":"9055",
    "addr:postcode":"83709",
    "addr:street":"Highlander Rd",
    "iso:country":"US",
    "sg:address":"9055 Highlander Rd",
    "sg:city":"Boise",
    "sg:classifiers":[
        {
            "category":"Building & Trades",
            "subcategory":"Construction",
            "type":"Services"
        }
    ],
    "sg:phone":"+1 208 362 6653",
    "sg:postcode":"83709",
    "sg:province":"ID",
    "sg:tags":[
        "home",
        "builder"
    ],
    "wof:name":"R K Ventures",
    "wof:placetype":"venue"
},
  "geometry": {"coordinates":[-116.294766,43.55616],"type":"Point"}
}