{
  "type": "Feature",
  "properties": {
    "iso:country":"US",
    "sg:address":"301 E Mullan Ave",
    "sg:city":"Osburn",
    "sg:classifiers":[
        {
            "category":"Home & Garden",
            "subcategory":"Building Materials",
            "type":"Retail Goods"
        }
    ],
    "sg:phone":"+1 208 752 1178",
    "sg:postcode":"83849",
    "sg:province":"ID",
    "sg:tags":[
        "mixed",
        "concrete"
    ],
    "wof:name":"Zanetti Bros Inc",
    "wof:placetype":"venue"
},
  "geometry": {"coordinates":[-115.999629,47.50595],"type":"Point"}
}