{
  "type": "Feature",
  "properties": {
    "iso:country":"US",
    "sg:address":"137 2nd St",
    "sg:city":"Dubois",
    "sg:classifiers":[
        {
            "category":"Education",
            "subcategory":"School",
            "type":"Public Place"
        }
    ],
    "sg:phone":"+1 208 374 5500",
    "sg:postcode":"83401",
    "sg:province":"ID",
    "wof:name":"Clark County School District",
    "wof:placetype":"venue"
},
  "geometry": {"coordinates":[-112.033199,43.496102],"type":"Point"}
}