{
  "type": "Feature",
  "properties": {
    "addr:full":"1011 Washington St Montpelier ID 83254",
    "addr:housenumber":"1011",
    "addr:postcode":"83254",
    "addr:street":"Washington St",
    "iso:country":"US",
    "sg:address":"1011 Washington St",
    "sg:city":"Montpelier",
    "sg:classifiers":[
        {
            "category":"Personal",
            "subcategory":"Beauty Salon",
            "type":"Services"
        }
    ],
    "sg:phone":"+1 208 847 0875",
    "sg:postcode":"83254",
    "sg:province":"ID",
    "sg:tags":[
        "shop"
    ],
    "wof:name":"Noticeable Nails By Marti",
    "wof:placetype":"venue"
},
  "geometry": {"coordinates":[-111.311852,42.317509],"type":"Point"}
}