{
  "type": "Feature",
  "properties": {
    "iso:country":"US",
    "sg:address":"459 State Hwy 55",
    "sg:city":"Horseshoe Bend",
    "sg:classifiers":[
        {
            "category":"Autos & Motor Vehicles",
            "subcategory":"Fuel & Gas Station",
            "type":"Retail Goods"
        }
    ],
    "sg:phone":"+1 208 793 4321",
    "sg:postcode":"83629",
    "sg:province":"ID",
    "sg:tags":[
        "oil"
    ],
    "wof:name":"Valley View Chevron",
    "wof:placetype":"venue"
},
  "geometry": {"coordinates":[-116.20314399999999,43.901453],"type":"Point"}
}