{
  "type": "Feature",
  "properties": {
    "addr:full":"239 SW 3rd St Fruitland ID 83619",
    "addr:housenumber":"239",
    "addr:postcode":"83619",
    "addr:street":"Sw 3Rd St",
    "iso:country":"US",
    "sg:address":"239 SW 3rd St",
    "sg:city":"Fruitland",
    "sg:classifiers":[
        {
            "category":"Professional",
            "subcategory":"Engineering",
            "type":"Services"
        }
    ],
    "sg:phone":"+1 208 452 2296",
    "sg:postcode":"83619",
    "sg:province":"ID",
    "sg:tags":[
        "engineer"
    ],
    "wof:name":"Basic Engineering PC",
    "wof:placetype":"venue"
},
  "geometry": {"coordinates":[-116.916139,44.008921],"type":"Point"}
}