{
  "type": "Feature",
  "properties": {
    "iso:country":"US",
    "sg:address":"425 Shoshone St N",
    "sg:city":"Twin Falls",
    "sg:classifiers":[
        {
            "category":"Government",
            "subcategory":"Office",
            "type":"Public Place"
        }
    ],
    "sg:phone":"+1 208 736 4174",
    "sg:postcode":"83301",
    "sg:province":"ID",
    "wof:name":"Twin Falls County Human Rsrcs",
    "wof:placetype":"venue"
},
  "geometry": {"coordinates":[-114.465835,42.558997],"type":"Point"}
}