{
  "type": "Feature",
  "properties": {
    "iso:country":"US",
    "sg:address":"102 E Wallace Ave",
    "sg:city":"Coeur D Alene",
    "sg:classifiers":[
        {
            "category":"Professional",
            "subcategory":"Advertising",
            "type":"Services"
        }
    ],
    "sg:phone":"+1 208 667 8744",
    "sg:postcode":"83814",
    "sg:province":"ID",
    "sg:tags":[
        "guide"
    ],
    "sg:website":"www.hdiblackbook.net",
    "wof:name":"Hagadone Directories",
    "wof:placetype":"venue"
},
  "geometry": {"coordinates":[-116.785454,47.676774],"type":"Point"}
}