{
  "type": "Feature",
  "properties": {
    "addr:full":"7110 Settlers Dr Boise ID 83704",
    "addr:housenumber":"7110",
    "addr:postcode":"83704",
    "addr:street":"Settlers Dr",
    "iso:country":"US",
    "sg:address":"7110 Settlers Dr",
    "sg:city":"Boise",
    "sg:classifiers":[
        {
            "category":"Building & Trades",
            "subcategory":"Construction",
            "type":"Services"
        }
    ],
    "sg:phone":"+1 208 362 1157",
    "sg:postcode":"83704",
    "sg:province":"ID",
    "sg:tags":[
        "dry wall",
        "contractor"
    ],
    "wof:name":"Wootton Drywall",
    "wof:placetype":"venue"
},
  "geometry": {"coordinates":[-116.271755,43.62974],"type":"Point"}
}