{
  "type": "Feature",
  "properties": {
    "addr:full":"701 S Samson Trl Mccall ID 83638",
    "addr:housenumber":"701",
    "addr:postcode":"83638",
    "addr:street":"S Samson Trl",
    "iso:country":"US",
    "sg:address":"701 S Samson Trl",
    "sg:city":"Mccall",
    "sg:classifiers":[
        {
            "category":"Building & Trades",
            "subcategory":"Construction",
            "type":"Services"
        }
    ],
    "sg:phone":"+1 208 634 8336",
    "sg:postcode":"83638",
    "sg:province":"ID",
    "sg:tags":[
        "general",
        "contractor"
    ],
    "wof:name":"Bob Kibby Construction",
    "wof:placetype":"venue"
},
  "geometry": {"coordinates":[-116.085447,44.884469],"type":"Point"}
}