{
  "type": "Feature",
  "properties": {
    "iso:country":"US",
    "sg:address":"4200 McGhee Rd",
    "sg:city":"Sandpoint",
    "sg:classifiers":[
        {
            "category":"Real Estate",
            "subcategory":"Developer",
            "type":"Services"
        }
    ],
    "sg:phone":"+1 208 265 8154",
    "sg:postcode":"83864",
    "sg:province":"ID",
    "wof:name":"Graham Industries",
    "wof:placetype":"venue"
},
  "geometry": {"coordinates":[-116.52451600000001,48.317684],"type":"Point"}
}