{
  "type": "Feature",
  "properties": {
    "iso:country":"US",
    "sg:address":"205 N 4th St",
    "sg:city":"Montpelier",
    "sg:classifiers":[
        {
            "category":"Autos & Motor Vehicles",
            "subcategory":"Automobile Sales",
            "type":"Retail Goods"
        }
    ],
    "sg:phone":"+1 208 847 1212",
    "sg:postcode":"83254",
    "sg:province":"ID",
    "sg:tags":[
        "car",
        "dealer"
    ],
    "wof:name":"Jensen-Wood Motor Co",
    "wof:placetype":"venue"
},
  "geometry": {"coordinates":[-111.297866,42.320701],"type":"Point"}
}