{
  "type": "Feature",
  "properties": {
    "addr:full":"208 N 2nd Ave Sandpoint ID 83864",
    "addr:housenumber":"208",
    "addr:postcode":"83864",
    "addr:street":"N 2Nd Ave",
    "iso:country":"US",
    "sg:address":"208 N 2nd Ave",
    "sg:city":"Sandpoint",
    "sg:classifiers":[
        {
            "category":"Professional",
            "subcategory":"Accounting & Tax Preparation",
            "type":"Services"
        }
    ],
    "sg:phone":"+1 208 263 5179",
    "sg:postcode":"83864",
    "sg:province":"ID",
    "sg:tags":[
        "return",
        "filing"
    ],
    "wof:name":"H & R Block Tax Svc",
    "wof:placetype":"venue"
},
  "geometry": {"coordinates":[-116.548659,48.274897],"type":"Point"}
}