{
  "type": "Feature",
  "properties": {
    "iso:country":"US",
    "sg:address":"700 Stevens Ave",
    "sg:city":"Filer",
    "sg:classifiers":[
        {
            "category":"Education",
            "subcategory":"School",
            "type":"Public Place"
        }
    ],
    "sg:phone":"+1 208 326 5981",
    "sg:postcode":"83328",
    "sg:province":"ID",
    "wof:name":"Filer School Superintendent",
    "wof:placetype":"venue"
},
  "geometry": {"coordinates":[-114.614073,42.56637],"type":"Point"}
}