{
  "type": "Feature",
  "properties": {
    "iso:country":"US",
    "sg:address":"963 Malibu St",
    "sg:city":"Pocatello",
    "sg:classifiers":[
        {
            "category":"Retail",
            "subcategory":"Portrait Studio",
            "type":"Services"
        }
    ],
    "sg:phone":"+1 208 637 8913",
    "sg:postcode":"83201",
    "sg:province":"ID",
    "sg:tags":[
        "photo"
    ],
    "wof:name":"Picture Perfect Photography",
    "wof:placetype":"venue"
},
  "geometry": {"coordinates":[-112.438884,42.897319],"type":"Point"}
}