{
  "type": "Feature",
  "properties": {
    "addr:full":"28177 N Clagstone Rd Athol ID 83801",
    "addr:housenumber":"28177",
    "addr:postcode":"83801",
    "addr:street":"N Clagstone Rd",
    "iso:country":"US",
    "sg:address":"28177 N Clagstone Rd",
    "sg:city":"Athol",
    "sg:classifiers":[
        {
            "category":"Organizations",
            "subcategory":"Religious Organization",
            "type":"Services"
        }
    ],
    "sg:phone":"+1 208 683 1638",
    "sg:postcode":"83801",
    "sg:province":"ID",
    "sg:tags":[
        "church"
    ],
    "wof:name":"Living Word Presbyterian Chr",
    "wof:placetype":"venue"
},
  "geometry": {"coordinates":[-116.74232499999999,47.917037],"type":"Point"}
}