{
  "type": "Feature",
  "properties": {
    "iso:country":"US",
    "sg:address":"527 E 23rd Ave",
    "sg:city":"Post Falls",
    "sg:classifiers":[
        {
            "category":"Building & Trades",
            "subcategory":"Construction",
            "type":"Services"
        }
    ],
    "sg:phone":"+1 208 773 6201",
    "sg:postcode":"83854",
    "sg:province":"ID",
    "sg:tags":[
        "house"
    ],
    "wof:name":"G W Marquart Construction",
    "wof:placetype":"venue"
},
  "geometry": {"coordinates":[-116.941699,47.730153],"type":"Point"}
}