{
  "type": "Feature",
  "properties": {
    "iso:country":"US",
    "sg:address":"218 Carson St",
    "sg:city":"Emmett",
    "sg:classifiers":[
        {
            "category":"Freight",
            "type":"Transportation"
        }
    ],
    "sg:phone":"+1 208 365 3878",
    "sg:postcode":"83617",
    "sg:province":"ID",
    "sg:tags":[
        "log",
        "hauling"
    ],
    "wof:name":"Canaday Trucking Inc",
    "wof:placetype":"venue"
},
  "geometry": {"coordinates":[-116.50278299999999,43.881079],"type":"Point"}
}