{
  "type": "Feature",
  "properties": {
    "iso:country":"US",
    "sg:address":"6856 E French Gulch Rd",
    "sg:city":"Coeur D Alene",
    "sg:classifiers":[
        {
            "category":"Real Estate",
            "subcategory":"Real Estate Agent",
            "type":"Services"
        }
    ],
    "sg:phone":"+1 208 769 7091",
    "sg:postcode":"83814",
    "sg:province":"ID",
    "wof:name":"Sabaka Inc",
    "wof:placetype":"venue"
},
  "geometry": {"coordinates":[-116.71143499999999,47.689786],"type":"Point"}
}