{
  "type": "Feature",
  "properties": {
    "addr:full":"9035 N Ramsey Rd Hayden Lake ID 83835",
    "addr:housenumber":"9035",
    "addr:postcode":"83835",
    "addr:street":"N Ramsey Rd",
    "iso:country":"US",
    "sg:address":"9035 N Ramsey Rd",
    "sg:city":"Hayden Lake",
    "sg:classifiers":[
        {
            "category":"Wholesale",
            "subcategory":"Electrical",
            "type":"Manufacturing & Wholesale Goods"
        }
    ],
    "sg:phone":"+1 208 772 5615",
    "sg:postcode":"83835",
    "sg:province":"ID",
    "sg:tags":[
        "video",
        "disc",
        "tape"
    ],
    "wof:name":"Inland Video Supply",
    "wof:placetype":"venue"
},
  "geometry": {"coordinates":[-116.80831499999999,47.753744],"type":"Point"}
}