{
  "type": "Feature",
  "properties": {
    "iso:country":"US",
    "sg:address":"14309 S 5th W",
    "sg:city":"Shelley",
    "sg:classifiers":[
        {
            "category":"Professional",
            "subcategory":"Management & Consulting",
            "type":"Services"
        }
    ],
    "sg:phone":"+1 208 357 3722",
    "sg:postcode":"83274",
    "sg:province":"ID",
    "sg:tags":[
        "retail",
        "direct",
        "sales"
    ],
    "wof:name":"Three Generation Creations LLC",
    "wof:placetype":"venue"
},
  "geometry": {"coordinates":[-112.04371500000001,43.373476],"type":"Point"}
}