{
  "type": "Feature",
  "properties": {
    "iso:country":"US",
    "sg:address":"708 Main St",
    "sg:city":"Caldwell",
    "sg:classifiers":[
        {
            "category":"Organizations",
            "subcategory":"Non-profit Organization",
            "type":"Services"
        }
    ],
    "sg:phone":"+1 208 455 8600",
    "sg:postcode":"83605",
    "sg:province":"ID",
    "sg:tags":[
        "information",
        "alcoholism",
        "treatment"
    ],
    "wof:name":"Renewal Services Of Idaho",
    "wof:placetype":"venue"
},
  "geometry": {"coordinates":[-116.68822299999999,43.666921],"type":"Point"}
}