{
  "type": "Feature",
  "properties": {
    "iso:country":"US",
    "sg:address":"201 8th St E",
    "sg:city":"Twin Falls",
    "sg:classifiers":[
        {
            "category":"Professional",
            "subcategory":"Business Services",
            "type":"Services"
        }
    ],
    "sg:phone":"+1 208 733 1027",
    "sg:postcode":"83301",
    "sg:province":"ID",
    "sg:tags":[
        "water",
        "treatment"
    ],
    "wof:name":"Kinetico Of Magic Valley",
    "wof:placetype":"venue"
},
  "geometry": {"coordinates":[-114.46021500000001,42.550605],"type":"Point"}
}