{
  "type": "Feature",
  "properties": {
    "iso:country":"US",
    "sg:address":"4239 E 400 N",
    "sg:city":"Rigby",
    "sg:classifiers":[
        {
            "category":"Retail",
            "subcategory":"Auto Repair",
            "type":"Services"
        }
    ],
    "sg:phone":"+1 208 745 8010",
    "sg:postcode":"83442",
    "sg:province":"ID",
    "sg:tags":[
        "general"
    ],
    "wof:name":"Dana Killian Automotive",
    "wof:placetype":"venue"
},
  "geometry": {"coordinates":[-111.857547,43.684832],"type":"Point"}
}