{
  "type": "Feature",
  "properties": {
    "iso:country":"US",
    "sg:address":"1927 Idaho St",
    "sg:city":"Lewiston",
    "sg:classifiers":[
        {
            "category":"Wholesale",
            "subcategory":"Medical Equipment & Supplies",
            "type":"Manufacturing & Wholesale Goods"
        }
    ],
    "sg:phone":"+1 208 746 8547",
    "sg:postcode":"83501",
    "sg:province":"ID",
    "sg:tags":[
        "assistive",
        "aid",
        "device",
        "hearing"
    ],
    "sg:website":"http://www.miracle-ear.com",
    "wof:name":"Miracle-Ear",
    "wof:placetype":"venue"
},
  "geometry": {"coordinates":[-117.004002,46.414416],"type":"Point"}
}