{
  "type": "Feature",
  "properties": {
    "iso:country":"US",
    "sg:address":"2355 Henryanna Ave",
    "sg:city":"Idaho Falls",
    "sg:classifiers":[
        {
            "category":"Professional",
            "subcategory":"Computer Services",
            "type":"Services"
        }
    ],
    "sg:phone":"+1 208 403 9359",
    "sg:postcode":"83404",
    "sg:province":"ID",
    "sg:tags":[
        "related"
    ],
    "wof:name":"Safexchange LLC",
    "wof:placetype":"venue"
},
  "geometry": {"coordinates":[-111.992816,43.477505],"type":"Point"}
}