{
  "type": "Feature",
  "properties": {
    "iso:country":"US",
    "sg:address":"310 W Idaho St",
    "sg:city":"Blackfoot",
    "sg:classifiers":[
        {
            "category":"Health Services",
            "subcategory":"Doctor",
            "type":"Services"
        }
    ],
    "sg:phone":"+1 208 785 2255",
    "sg:postcode":"83221",
    "sg:province":"ID",
    "sg:tags":[
        "dentist"
    ],
    "wof:name":"Blackfoot Smiles",
    "wof:placetype":"venue"
},
  "geometry": {"coordinates":[-112.34730500000001,43.192312],"type":"Point"}
}