{
  "type": "Feature",
  "properties": {
    "iso:country":"US",
    "sg:address":"17333 Wagner Rd",
    "sg:city":"Caldwell",
    "sg:classifiers":[
        {
            "category":"Wholesale",
            "subcategory":"Farm Supplies",
            "type":"Manufacturing & Wholesale Goods"
        }
    ],
    "sg:phone":"+1 208 453 4990",
    "sg:postcode":"83607",
    "sg:province":"ID",
    "sg:tags":[
        "bulb",
        "seed"
    ],
    "wof:name":"Abbott & Cobb Seed Co Inc",
    "wof:placetype":"venue"
},
  "geometry": {"coordinates":[-116.733081,43.625179],"type":"Point"}
}