{
  "type": "Feature",
  "properties": {
    "iso:country":"US",
    "sg:address":"3830 N 3300 E",
    "sg:city":"Kimberly",
    "sg:classifiers":[
        {
            "category":"Farming",
            "subcategory":"Farm",
            "type":"Manufacturing & Wholesale Goods"
        }
    ],
    "sg:phone":"+1 208 734 2774",
    "sg:postcode":"83341",
    "sg:province":"ID",
    "sg:tags":[
        "crop",
        "general"
    ],
    "wof:name":"Easley Farm",
    "wof:placetype":"venue"
},
  "geometry": {"coordinates":[-114.401364,42.552694],"type":"Point"}
}