{
  "type": "Feature",
  "properties": {
    "addr:full":"402 Old State Hwy Cascade ID 83611",
    "addr:housenumber":"402",
    "addr:postcode":"83611",
    "addr:street":"Old State Hwy Cascade",
    "iso:country":"US",
    "sg:address":"402 Old State Hwy",
    "sg:city":"Cascade",
    "sg:classifiers":[
        {
            "category":"Health Services",
            "subcategory":"Doctor",
            "type":"Services"
        }
    ],
    "sg:phone":"+1 208 382 4285",
    "sg:postcode":"83611",
    "sg:province":"ID",
    "sg:tags":[
        "clinic"
    ],
    "wof:name":"Cascade Family Practice",
    "wof:placetype":"venue"
},
  "geometry": {"coordinates":[-116.049379,44.51772],"type":"Point"}
}