{
  "type": "Feature",
  "properties": {
    "iso:country":"US",
    "sg:address":"1485 Pole Line Rd E",
    "sg:city":"Twin Falls",
    "sg:classifiers":[
        {
            "category":"Shopping",
            "subcategory":"Clothing, Apparel, & Fashions",
            "type":"Retail Goods"
        }
    ],
    "sg:phone":"+1 208 736 1843",
    "sg:postcode":"83301",
    "sg:province":"ID",
    "wof:name":"Anchor Blue",
    "wof:placetype":"venue"
},
  "geometry": {"coordinates":[-114.456535,42.592073],"type":"Point"}
}