{
  "type": "Feature",
  "properties": {
    "addr:full":"1750 Osterloh Ave Twin Falls ID 83301",
    "addr:housenumber":"1750",
    "addr:postcode":"83301",
    "addr:street":"Osterloh Ave",
    "iso:country":"US",
    "sg:address":"1750 Osterloh Ave",
    "sg:city":"Twin Falls",
    "sg:classifiers":[
        {
            "category":"Wholesale",
            "subcategory":"Auto Parts",
            "type":"Manufacturing & Wholesale Goods"
        }
    ],
    "sg:phone":"+1 208 734 5350",
    "sg:postcode":"83301",
    "sg:province":"ID",
    "sg:tags":[
        "automobile",
        "rebuilt"
    ],
    "wof:name":"Idaho Equipment & Salvage",
    "wof:placetype":"venue"
},
  "geometry": {"coordinates":[-114.451611,42.537564],"type":"Point"}
}