{
  "type": "Feature",
  "properties": {
    "iso:country":"US",
    "sg:address":"202 W Cameron Ave",
    "sg:city":"Kellogg",
    "sg:classifiers":[
        {
            "category":"Insurance",
            "subcategory":"Insurance Agent",
            "type":"Services"
        }
    ],
    "sg:phone":"+1 208 783 1176",
    "sg:postcode":"83837",
    "sg:province":"ID",
    "wof:name":"Kellogg Insurance",
    "wof:placetype":"venue"
},
  "geometry": {"coordinates":[-116.123856,47.541419],"type":"Point"}
}