{
  "type": "Feature",
  "properties": {
    "addr:full":"960 Broadway Ave Boise ID 83706",
    "addr:housenumber":"960",
    "addr:postcode":"83706",
    "addr:street":"Broadway Ave",
    "iso:country":"US",
    "sg:address":"960 Broadway Ave",
    "sg:city":"Boise",
    "sg:classifiers":[
        {
            "category":"Professional",
            "subcategory":"Lawyer & Legal Services",
            "type":"Services"
        }
    ],
    "sg:phone":"+1 208 342 6066",
    "sg:postcode":"83706",
    "sg:province":"ID",
    "sg:tags":[
        "attorney"
    ],
    "sg:website":"www.lawidaho.com",
    "wof:name":"Meuleman & Miller",
    "wof:placetype":"venue"
},
  "geometry": {"coordinates":[-116.1934,43.603269],"type":"Point"}
}