{
  "type": "Feature",
  "properties": {
    "iso:country":"US",
    "sg:address":"2755 Central Ave",
    "sg:city":"Idaho Falls",
    "sg:classifiers":[
        {
            "category":"Freight",
            "type":"Transportation"
        }
    ],
    "sg:phone":"+1 208 523 3134",
    "sg:postcode":"83406",
    "sg:province":"ID",
    "sg:tags":[
        "operator",
        "local",
        "trucking"
    ],
    "wof:name":"Dale Corbit Trucking",
    "wof:placetype":"venue"
},
  "geometry": {"coordinates":[-111.967072,43.472884],"type":"Point"}
}