{
  "type": "Feature",
  "properties": {
    "iso:country":"US",
    "sg:address":"2045 W Lake Hazel Rd",
    "sg:city":"Meridian",
    "sg:classifiers":[
        {
            "category":"Farming",
            "subcategory":"Livestock Farm",
            "type":"Manufacturing & Wholesale Goods"
        }
    ],
    "sg:phone":"+1 208 888 9761",
    "sg:postcode":"83642",
    "sg:province":"ID",
    "sg:tags":[
        "animal",
        "general"
    ],
    "wof:name":"G/J Ranch",
    "wof:placetype":"venue"
},
  "geometry": {"coordinates":[-116.42063400000001,43.54645],"type":"Point"}
}