{
  "type": "Feature",
  "properties": {
    "iso:country":"US",
    "sg:address":"410 N Greensferry Rd",
    "sg:city":"Post Falls",
    "sg:classifiers":[
        {
            "category":"Freight",
            "type":"Transportation"
        }
    ],
    "sg:phone":"+1 208 773 3556",
    "sg:postcode":"83854",
    "sg:province":"ID",
    "sg:tags":[
        "commercial",
        "storage",
        "general"
    ],
    "wof:name":"Stow & Go Self Storage",
    "wof:placetype":"venue"
},
  "geometry": {"coordinates":[-116.915618,47.709627],"type":"Point"}
}