{
  "type": "Feature",
  "properties": {
    "iso:country":"US",
    "sg:address":"189 Locust St N",
    "sg:city":"Twin Falls",
    "sg:classifiers":[
        {
            "category":"Organizations",
            "subcategory":"Religious Organization",
            "type":"Services"
        }
    ],
    "sg:phone":"+1 208 733 5349",
    "sg:postcode":"83301",
    "sg:province":"ID",
    "sg:tags":[
        "church"
    ],
    "wof:name":"First Assembly Of God",
    "wof:placetype":"venue"
},
  "geometry": {"coordinates":[-114.45543600000001,42.564707],"type":"Point"}
}