{
  "type": "Feature",
  "properties": {
    "addr:full":"1961 E Shalimar Dr Eagle ID 83616",
    "addr:housenumber":"1961",
    "addr:postcode":"83616",
    "addr:street":"E Shalimar Dr",
    "iso:country":"US",
    "sg:address":"1961 E Shalimar Dr",
    "sg:city":"Eagle",
    "sg:classifiers":[
        {
            "category":"Building & Trades",
            "subcategory":"Landscaping Services",
            "type":"Services"
        }
    ],
    "sg:phone":"+1 208 939 4369",
    "sg:postcode":"83616",
    "sg:province":"ID",
    "wof:name":"A Plus Lawn & Irrigation LLC",
    "wof:placetype":"venue"
},
  "geometry": {"coordinates":[-116.329352,43.708901],"type":"Point"}
}