{
  "type": "Feature",
  "properties": {
    "addr:full":"6212 W State St Boise ID 83703",
    "addr:housenumber":"6212",
    "addr:postcode":"83703",
    "addr:street":"W State St",
    "iso:country":"US",
    "sg:address":"6212 W State St",
    "sg:city":"Boise",
    "sg:classifiers":[
        {
            "category":"Shopping",
            "type":"Retail Goods"
        }
    ],
    "sg:phone":"+1 208 854 0700",
    "sg:postcode":"83703",
    "sg:province":"ID",
    "sg:tags":[
        "pet",
        "shop"
    ],
    "wof:name":"Idaho Saltwater Emporium",
    "wof:placetype":"venue"
},
  "geometry": {"coordinates":[-116.265792,43.659647],"type":"Point"}
}