{
  "type": "Feature",
  "properties": {
    "iso:country":"US",
    "sg:address":"508 N 13th St",
    "sg:city":"Boise",
    "sg:classifiers":[
        {
            "category":"Professional",
            "subcategory":"Lawyer & Legal Services",
            "type":"Services"
        }
    ],
    "sg:phone":"+1 208 385 7400",
    "sg:postcode":"83702",
    "sg:province":"ID",
    "sg:tags":[
        "attorney"
    ],
    "wof:name":"Michael R Jones LLC",
    "wof:placetype":"venue"
},
  "geometry": {"coordinates":[-116.205671,43.622328],"type":"Point"}
}