{
  "type": "Feature",
  "properties": {
    "addr:full":"106 S Harlan Pl Eagle ID 83616",
    "addr:housenumber":"106",
    "addr:postcode":"83616",
    "addr:street":"S Harlan Pl",
    "iso:country":"US",
    "sg:address":"106 S Harlan Pl",
    "sg:city":"Eagle",
    "sg:classifiers":[
        {
            "category":"Professional",
            "subcategory":"Business Services",
            "type":"Services"
        }
    ],
    "sg:phone":"+1 208 939 4245",
    "sg:postcode":"83616",
    "sg:province":"ID",
    "sg:tags":[
        "transcribing",
        "disc"
    ],
    "wof:name":"Anderson Transcription Svc",
    "wof:placetype":"venue"
},
  "geometry": {"coordinates":[-116.357962,43.692136],"type":"Point"}
}