{
  "type": "Feature",
  "properties": {
    "addr:full":"3540 W Elk Dr Post Falls ID 83854",
    "addr:housenumber":"3540",
    "addr:postcode":"83854",
    "addr:street":"W Elk",
    "iso:country":"US",
    "sg:address":"3540 W Elk Dr",
    "sg:city":"Post Falls",
    "sg:classifiers":[
        {
            "category":"Retail",
            "subcategory":"Auto Repair",
            "type":"Services"
        }
    ],
    "sg:phone":"+1 208 457 0700",
    "sg:postcode":"83854",
    "sg:province":"ID",
    "sg:tags":[
        "engine"
    ],
    "wof:name":"Panther Engineering & Sales",
    "wof:placetype":"venue"
},
  "geometry": {"coordinates":[-116.99420499999999,47.718057],"type":"Point"}
}