{
  "type": "Feature",
  "properties": {
    "iso:country":"US",
    "sg:address":"585 Marlu St",
    "sg:city":"Pocatello",
    "sg:classifiers":[
        {
            "category":"Professional",
            "subcategory":"Computer Services",
            "type":"Services"
        }
    ],
    "sg:phone":"+1 208 233 9249",
    "sg:postcode":"83201",
    "sg:province":"ID",
    "sg:tags":[
        "repair"
    ],
    "wof:name":"Rfm Sales & Svc",
    "wof:placetype":"venue"
},
  "geometry": {"coordinates":[-112.456788,42.889596],"type":"Point"}
}