{
  "type": "Feature",
  "properties": {
    "addr:full":"7280 N 16th St Coeur D Alene ID 83815",
    "addr:housenumber":"7280",
    "addr:postcode":"83815",
    "addr:street":"N 16Th St Coeur D",
    "iso:country":"US",
    "sg:address":"7280 N 16th St",
    "sg:city":"Coeur D Alene",
    "sg:classifiers":[
        {
            "category":"Building & Trades",
            "subcategory":"Construction",
            "type":"Services"
        }
    ],
    "sg:phone":"+1 208 772 4020",
    "sg:postcode":"83815",
    "sg:province":"ID",
    "sg:tags":[
        "contractor"
    ],
    "wof:name":"Bryan Michael Shop",
    "wof:placetype":"venue"
},
  "geometry": {"coordinates":[-116.759602,47.738323],"type":"Point"}
}