{
  "type": "Feature",
  "properties": {
    "iso:country":"US",
    "sg:address":"385 N 2nd E",
    "sg:city":"Mountain Home",
    "sg:classifiers":[
        {
            "category":"Shopping",
            "subcategory":"Used Merchandise",
            "type":"Retail Goods"
        }
    ],
    "sg:phone":"+1 208 587 2360",
    "sg:postcode":"83647",
    "sg:province":"ID",
    "sg:tags":[
        "shop",
        "thrift"
    ],
    "wof:name":"Idaho Youth Ranch Thrift Store",
    "wof:placetype":"venue"
},
  "geometry": {"coordinates":[-115.694732,43.1329],"type":"Point"}
}