{
  "type": "Feature",
  "properties": {
    "iso:country":"US",
    "sg:address":"1625 W Bannock St",
    "sg:city":"Boise",
    "sg:classifiers":[
        {
            "category":"Shopping",
            "subcategory":"Musical Instruments",
            "type":"Retail Goods"
        }
    ],
    "sg:phone":"+1 208 395 0211",
    "sg:postcode":"83702",
    "sg:province":"ID",
    "wof:name":"Idaho Percussion",
    "wof:placetype":"venue"
},
  "geometry": {"coordinates":[-116.212445,43.622302],"type":"Point"}
}