{
  "type": "Feature",
  "properties": {
    "iso:country":"US",
    "sg:address":"423 Partridge Pl",
    "sg:city":"Boise",
    "sg:classifiers":[
        {
            "category":"Manufacturing",
            "subcategory":"Metals",
            "type":"Manufacturing & Wholesale Goods"
        }
    ],
    "sg:phone":"+1 208 377 0942",
    "sg:postcode":"83713",
    "sg:province":"ID",
    "sg:tags":[
        "ornamental",
        "work"
    ],
    "sg:website":"www.precisionfencing.com",
    "wof:name":"Precision Fencing & Custom",
    "wof:placetype":"venue"
},
  "geometry": {"coordinates":[-116.316023,43.609307],"type":"Point"}
}