{
  "type": "Feature",
  "properties": {
    "iso:country":"US",
    "sg:address":"16041 Lake Shore Dr",
    "sg:city":"Caldwell",
    "sg:classifiers":[
        {
            "category":"Freight",
            "type":"Transportation"
        }
    ],
    "sg:phone":"+1 208 459 4142",
    "sg:postcode":"83607",
    "sg:province":"ID",
    "sg:tags":[
        "operator",
        "local",
        "trucking"
    ],
    "wof:name":"Rodriguez Trucking",
    "wof:placetype":"venue"
},
  "geometry": {"coordinates":[-116.712969,43.548642],"type":"Point"}
}