{
  "type": "Feature",
  "properties": {
    "iso:country":"US",
    "sg:address":"90 W 500 S",
    "sg:city":"Jerome",
    "sg:classifiers":[
        {
            "category":"Retail",
            "subcategory":"Animal Services",
            "type":"Services"
        }
    ],
    "sg:phone":"+1 208 324 5444",
    "sg:postcode":"83338",
    "sg:province":"ID",
    "wof:name":"Steve Bandy ABS",
    "wof:placetype":"venue"
},
  "geometry": {"coordinates":[-114.536399,42.651662],"type":"Point"}
}