{
  "type": "Feature",
  "properties": {
    "iso:country":"US",
    "sg:address":"120 Ramage St",
    "sg:city":"Twin Falls",
    "sg:classifiers":[
        {
            "category":"Personal",
            "subcategory":"Tattoo Parlor",
            "type":"Services"
        }
    ],
    "sg:phone":"+1 208 734 5999",
    "sg:postcode":"83301",
    "sg:province":"ID",
    "sg:tags":[
        "tattooing"
    ],
    "wof:name":"Silver Needle Tattoo",
    "wof:placetype":"venue"
},
  "geometry": {"coordinates":[-114.478383,42.548959],"type":"Point"}
}