{
  "type": "Feature",
  "properties": {
    "iso:country":"US",
    "sg:address":"6176 N Government Way",
    "sg:city":"Dalton Gardens",
    "sg:classifiers":[
        {
            "category":"Health Services",
            "subcategory":"Doctor",
            "type":"Services"
        }
    ],
    "sg:phone":"+1 208 762 3027",
    "sg:postcode":"83815",
    "sg:province":"ID",
    "sg:tags":[
        "dentist"
    ],
    "wof:name":"Silver Lake Dental Clinic",
    "wof:placetype":"venue"
},
  "geometry": {"coordinates":[-116.786646,47.728488],"type":"Point"}
}