{
  "type": "Feature",
  "properties": {
    "addr:full":"1149 S 3rd St Saint Maries ID 83861",
    "addr:housenumber":"1149",
    "addr:postcode":"83861",
    "addr:street":"S 3Rd St",
    "iso:country":"US",
    "sg:address":"1149 S 3rd St",
    "sg:city":"Saint Maries",
    "sg:classifiers":[
        {
            "category":"Personal",
            "type":"Services"
        }
    ],
    "sg:phone":"+1 208 245 4126",
    "sg:postcode":"83861",
    "sg:province":"ID",
    "wof:name":"Teresa Jeffrey",
    "wof:placetype":"venue"
},
  "geometry": {"coordinates":[-116.562552,47.306084],"type":"Point"}
}