{
  "type": "Feature",
  "properties": {
    "addr:full":"635 Main Ave W Twin Falls ID 83301",
    "addr:housenumber":"635",
    "addr:postcode":"83301",
    "addr:street":"Main Ave W",
    "iso:country":"US",
    "sg:address":"635 Main Ave W",
    "sg:city":"Twin Falls",
    "sg:classifiers":[
        {
            "category":"Building & Trades",
            "subcategory":"Construction",
            "type":"Services"
        }
    ],
    "sg:phone":"+1 208 733 9678",
    "sg:postcode":"83301",
    "sg:province":"ID",
    "sg:tags":[
        "roofing",
        "contractor"
    ],
    "wof:name":"American Roof",
    "wof:placetype":"venue"
},
  "geometry": {"coordinates":[-114.477108,42.560831],"type":"Point"}
}