{
  "type": "Feature",
  "properties": {
    "iso:country":"US",
    "sg:address":"1515 Shoshone St",
    "sg:city":"Boise",
    "sg:classifiers":[
        {
            "category":"Real Estate",
            "subcategory":"Real Estate Agent",
            "type":"Services"
        }
    ],
    "sg:phone":"+1 208 387 2637",
    "sg:postcode":"83705",
    "sg:province":"ID",
    "sg:tags":[
        "appraiser"
    ],
    "wof:name":"Ames Appraisal Co Inc",
    "wof:placetype":"venue"
},
  "geometry": {"coordinates":[-116.218712,43.590921],"type":"Point"}
}