{
  "type": "Feature",
  "properties": {
    "addr:full":"1923 N 4th St Coeur D Alene ID 83814",
    "addr:housenumber":"1923",
    "addr:postcode":"83814",
    "addr:street":"N 4Th St Coeur D",
    "iso:country":"US",
    "sg:address":"1923 N 4th St",
    "sg:city":"Coeur D Alene",
    "sg:classifiers":[
        {
            "category":"Wholesale",
            "subcategory":"Auto Parts",
            "type":"Manufacturing & Wholesale Goods"
        }
    ],
    "sg:phone":"+1 208 664 1432",
    "sg:postcode":"83814",
    "sg:province":"ID",
    "sg:tags":[
        "body",
        "automobile",
        "shop"
    ],
    "wof:name":"K C Auto Paint & Supplies",
    "wof:placetype":"venue"
},
  "geometry": {"coordinates":[-116.780807,47.694716],"type":"Point"}
}