{
  "type": "Feature",
  "properties": {
    "iso:country":"US",
    "sg:address":"4642 N Zimri Pl",
    "sg:city":"Boise",
    "sg:classifiers":[
        {
            "category":"Real Estate",
            "subcategory":"Real Estate Agent",
            "type":"Services"
        }
    ],
    "sg:phone":"+1 208 939 8991",
    "sg:postcode":"83713",
    "sg:province":"ID",
    "wof:name":"Mitchell & Assoc Inc",
    "wof:placetype":"venue"
},
  "geometry": {"coordinates":[-116.33096,43.647217],"type":"Point"}
}