{
  "type": "Feature",
  "properties": {
    "addr:full":"2833 Londonderry Ave Idaho Falls ID 83404",
    "addr:housenumber":"2833",
    "addr:postcode":"83404",
    "addr:street":"Londonderry Ave",
    "iso:country":"US",
    "sg:address":"2833 Londonderry Ave",
    "sg:city":"Idaho Falls",
    "sg:classifiers":[
        {
            "category":"Shopping",
            "type":"Retail Goods"
        }
    ],
    "sg:phone":"+1 208 529 9001",
    "sg:postcode":"83404",
    "sg:province":"ID",
    "sg:tags":[
        "cosmetic",
        "perfume"
    ],
    "wof:name":"Timeless Cosmetics",
    "wof:placetype":"venue"
},
  "geometry": {"coordinates":[-112.008376,43.468716],"type":"Point"}
}