{
  "type": "Feature",
  "properties": {
    "addr:full":"1002 Blaine St Caldwell ID 83605",
    "addr:housenumber":"1002",
    "addr:postcode":"83605",
    "addr:street":"Blaine St",
    "iso:country":"US",
    "sg:address":"1002 Blaine St",
    "sg:city":"Caldwell",
    "sg:classifiers":[
        {
            "category":"Wholesale",
            "subcategory":"Construction Materials",
            "type":"Manufacturing & Wholesale Goods"
        }
    ],
    "sg:phone":"+1 208 939 3678",
    "sg:postcode":"83605",
    "sg:province":"ID",
    "sg:tags":[
        "concrete",
        "product"
    ],
    "sg:website":"www.eagleprecast.com",
    "wof:name":"Eagle Precast",
    "wof:placetype":"venue"
},
  "geometry": {"coordinates":[-116.686825,43.663464],"type":"Point"}
}