{
  "type": "Feature",
  "properties": {
    "iso:country":"US",
    "sg:address":"1311 S Broadway St",
    "sg:city":"Blackfoot",
    "sg:classifiers":[
        {
            "category":"Retail",
            "subcategory":"Auto Repair",
            "type":"Services"
        }
    ],
    "sg:phone":"+1 208 785 9676",
    "sg:postcode":"83221",
    "sg:province":"ID",
    "sg:tags":[
        "body",
        "automobile",
        "painting"
    ],
    "wof:name":"Bowers Collision",
    "wof:placetype":"venue"
},
  "geometry": {"coordinates":[-112.35685599999999,43.17962],"type":"Point"}
}