{
  "type": "Feature",
  "properties": {
    "iso:country":"US",
    "sg:address":"6910 Main St",
    "sg:city":"Bonners Ferry",
    "sg:classifiers":[
        {
            "category":"Health Services",
            "subcategory":"Chiropractor",
            "type":"Services"
        }
    ],
    "sg:phone":"+1 208 267 7355",
    "sg:postcode":"83805",
    "sg:province":"ID",
    "wof:name":"Pamela Svec DC",
    "wof:placetype":"venue"
},
  "geometry": {"coordinates":[-116.31631899999999,48.688916],"type":"Point"}
}