{
  "type": "Feature",
  "properties": {
    "iso:country":"US",
    "sg:address":"10437 W Sawtail St",
    "sg:city":"Boise",
    "sg:classifiers":[
        {
            "category":"Professional",
            "subcategory":"Art Services",
            "type":"Services"
        }
    ],
    "sg:phone":"+1 208 939 4762",
    "sg:postcode":"83714",
    "sg:province":"ID",
    "sg:tags":[
        "commercial",
        "design"
    ],
    "wof:name":"Idea Graphics",
    "wof:placetype":"venue"
},
  "geometry": {"coordinates":[-116.31132599999999,43.698288],"type":"Point"}
}