{
  "type": "Feature",
  "properties": {
    "iso:country":"US",
    "sg:address":"3845 E 12 N",
    "sg:city":"Rigby",
    "sg:classifiers":[
        {
            "category":"Personal",
            "subcategory":"Beauty Salon",
            "type":"Services"
        }
    ],
    "sg:phone":"+1 208 745 9923",
    "sg:postcode":"83442",
    "sg:province":"ID",
    "sg:tags":[
        "hair",
        "stylist"
    ],
    "wof:name":"Julie Haircare",
    "wof:placetype":"venue"
},
  "geometry": {"coordinates":[-111.935607,43.62797],"type":"Point"}
}