{
  "type": "Feature",
  "properties": {
    "iso:country":"US",
    "sg:address":"415 Sierra Dr",
    "sg:city":"Boise",
    "sg:classifiers":[
        {
            "category":"Real Estate",
            "subcategory":"Architect",
            "type":"Services"
        }
    ],
    "sg:phone":"+1 208 336 9961",
    "sg:postcode":"83705",
    "sg:province":"ID",
    "sg:tags":[
        "home",
        "planning",
        "design"
    ],
    "wof:name":"Matrix Design Studio",
    "wof:placetype":"venue"
},
  "geometry": {"coordinates":[-116.228557,43.59894],"type":"Point"}
}