{
  "type": "Feature",
  "properties": {
    "addr:full":"915 H St Rupert ID 83350",
    "addr:housenumber":"915",
    "addr:postcode":"83350",
    "addr:street":"H St",
    "iso:country":"US",
    "sg:address":"915 H St",
    "sg:city":"Rupert",
    "sg:classifiers":[
        {
            "category":"Professional",
            "subcategory":"Management & Consulting",
            "type":"Services"
        }
    ],
    "sg:phone":"+1 208 436 9694",
    "sg:postcode":"83350",
    "sg:province":"ID",
    "wof:name":"Aerobics At 505",
    "wof:placetype":"venue"
},
  "geometry": {"coordinates":[-113.677851,42.621572],"type":"Point"}
}