{
  "type": "Feature",
  "properties": {
    "iso:country":"US",
    "sg:address":"1225 Idaho St",
    "sg:city":"Lewiston",
    "sg:classifiers":[
        {
            "category":"Government",
            "subcategory":"Office",
            "type":"Public Place"
        }
    ],
    "sg:phone":"+1 208 799 3035",
    "sg:postcode":"83501",
    "sg:province":"ID",
    "wof:name":"Nez Perce County Building Insp",
    "wof:placetype":"venue"
},
  "geometry": {"coordinates":[-117.016665,46.416576],"type":"Point"}
}