{
  "type": "Feature",
  "properties": {
    "iso:country":"US",
    "sg:address":"270 E 7th St",
    "sg:city":"Weiser",
    "sg:classifiers":[
        {
            "category":"Food & Beverages",
            "subcategory":"Liquor & Beverages",
            "type":"Retail Goods"
        }
    ],
    "sg:phone":"+1 208 549 0900",
    "sg:postcode":"83672",
    "sg:province":"ID",
    "wof:name":"Idaho Liquor Store",
    "wof:placetype":"venue"
},
  "geometry": {"coordinates":[-116.958304,44.243841],"type":"Point"}
}