{
  "type": "Feature",
  "properties": {
    "iso:country":"US",
    "sg:address":"1299 Mann Creek Rd",
    "sg:city":"Weiser",
    "sg:classifiers":[
        {
            "category":"Retail",
            "subcategory":"Animal Services",
            "type":"Services"
        }
    ],
    "sg:phone":"+1 208 549 0798",
    "sg:postcode":"83672",
    "sg:province":"ID",
    "wof:name":"Queen Quarter Horses",
    "wof:placetype":"venue"
},
  "geometry": {"coordinates":[-116.865274,44.341446],"type":"Point"}
}