{
  "type": "Feature",
  "properties": {
    "iso:country":"US",
    "sg:address":"30336 Hwy 200",
    "sg:city":"Sandpoint",
    "sg:classifiers":[
        {
            "category":"Health Services",
            "subcategory":"Doctor",
            "type":"Services"
        }
    ],
    "sg:phone":"+1 208 255 1255",
    "sg:postcode":"83864",
    "sg:province":"ID",
    "sg:tags":[
        "dentist"
    ],
    "wof:name":"Family Dental Care",
    "wof:placetype":"venue"
},
  "geometry": {"coordinates":[-116.54665900000001,48.295054],"type":"Point"}
}