{
  "type": "Feature",
  "properties": {
    "addr:full":"2821 Tamarack Dr Boise ID 83703",
    "addr:housenumber":"2821",
    "addr:postcode":"83703",
    "addr:street":"Tamarack Dr",
    "iso:country":"US",
    "sg:address":"2821 Tamarack Dr",
    "sg:city":"Boise",
    "sg:classifiers":[
        {
            "category":"Building & Trades",
            "subcategory":"Construction",
            "type":"Services"
        }
    ],
    "sg:phone":"+1 208 387 1241",
    "sg:postcode":"83703",
    "sg:province":"ID",
    "sg:tags":[
        "painting",
        "contractor"
    ],
    "wof:name":"American Heritage Pntg Contrs",
    "wof:placetype":"venue"
},
  "geometry": {"coordinates":[-116.239684,43.645661],"type":"Point"}
}