{
  "type": "Feature",
  "properties": {
    "iso:country":"US",
    "sg:address":"739 N Ralstin St",
    "sg:city":"Meridian",
    "sg:classifiers":[
        {
            "category":"Wholesale",
            "subcategory":"Durable Goods & Equipment",
            "type":"Manufacturing & Wholesale Goods"
        }
    ],
    "sg:phone":"+1 208 888 6706",
    "sg:postcode":"83642",
    "sg:province":"ID",
    "sg:tags":[
        "representative",
        "manufacturer"
    ],
    "wof:name":"Westar Medical LLC",
    "wof:placetype":"venue"
},
  "geometry": {"coordinates":[-116.375939,43.611646],"type":"Point"}
}