{
  "type": "Feature",
  "properties": {
    "iso:country":"US",
    "sg:address":"200 S Main St",
    "sg:city":"Pocatello",
    "sg:classifiers":[
        {
            "category":"Shopping",
            "subcategory":"Gifts & Souvenirs",
            "type":"Retail Goods"
        }
    ],
    "sg:phone":"+1 208 478 2718",
    "sg:postcode":"83204",
    "sg:province":"ID",
    "sg:tags":[
        "basket",
        "parcel"
    ],
    "wof:name":"Baskets Balloons & Beyond",
    "wof:placetype":"venue"
},
  "geometry": {"coordinates":[-112.44887199999999,42.860594],"type":"Point"}
}