{
  "type": "Feature",
  "properties": {
    "addr:full":"624 W Miles Ave Hayden ID 83835",
    "addr:housenumber":"624",
    "addr:postcode":"83835",
    "addr:street":"W Miles Ave",
    "iso:country":"US",
    "sg:address":"624 W Miles Ave",
    "sg:city":"Hayden",
    "sg:classifiers":[
        {
            "category":"Building & Trades",
            "subcategory":"Construction",
            "type":"Services"
        }
    ],
    "sg:phone":"+1 208 762 5121",
    "sg:postcode":"83835",
    "sg:province":"ID",
    "sg:tags":[
        "residential"
    ],
    "wof:name":"Scenic Investments Inc",
    "wof:placetype":"venue"
},
  "geometry": {"coordinates":[-116.79689399999999,47.766216],"type":"Point"}
}