{
  "type": "Feature",
  "properties": {
    "iso:country":"US",
    "sg:address":"7221 Wright Ln",
    "sg:city":"Nampa",
    "sg:classifiers":[
        {
            "category":"Building & Trades",
            "subcategory":"Equipment Rental",
            "type":"Services"
        }
    ],
    "sg:phone":"+1 208 463 8944",
    "sg:postcode":"83686",
    "sg:province":"ID",
    "sg:tags":[
        "crane"
    ],
    "wof:name":"Graffics Construction Inc",
    "wof:placetype":"venue"
},
  "geometry": {"coordinates":[-116.48325800000001,43.524785],"type":"Point"}
}