{
  "type": "Feature",
  "properties": {
    "addr:full":"159 Stone Run Ln Idaho Falls ID 83404",
    "addr:housenumber":"159",
    "addr:postcode":"83404",
    "addr:street":"Stone Run Ln",
    "iso:country":"US",
    "sg:address":"159 Stone Run Ln",
    "sg:city":"Idaho Falls",
    "sg:classifiers":[
        {
            "category":"Shopping",
            "type":"Retail Goods"
        }
    ],
    "sg:phone":"+1 208 529 8353",
    "sg:postcode":"83404",
    "sg:province":"ID",
    "sg:tags":[
        "picture",
        "frame",
        "merchandise"
    ],
    "wof:name":"Mats n That",
    "wof:placetype":"venue"
},
  "geometry": {"coordinates":[-112.033182,43.467059],"type":"Point"}
}