{
  "type": "Feature",
  "properties": {
    "iso:country":"US",
    "sg:address":"9963 W Geronimo St",
    "sg:city":"Boise",
    "sg:classifiers":[
        {
            "category":"Building & Trades",
            "subcategory":"Pest Control",
            "type":"Services"
        }
    ],
    "sg:phone":"+1 208 362 5802",
    "sg:postcode":"83709",
    "sg:province":"ID",
    "wof:name":"Best Pest Control",
    "wof:placetype":"venue"
},
  "geometry": {"coordinates":[-116.309146,43.576367],"type":"Point"}
}