{
  "type": "Feature",
  "properties": {
    "iso:country":"US",
    "sg:address":"121 S Five Mile Rd",
    "sg:city":"Boise",
    "sg:classifiers":[
        {
            "category":"Professional",
            "subcategory":"Art Services",
            "type":"Services"
        }
    ],
    "sg:phone":"+1 208 672 9115",
    "sg:postcode":"83709",
    "sg:province":"ID",
    "sg:tags":[
        "photography",
        "commercial"
    ],
    "wof:name":"Studio III",
    "wof:placetype":"venue"
},
  "geometry": {"coordinates":[-116.314362,43.604049],"type":"Point"}
}