{
  "type": "Feature",
  "properties": {
    "iso:country":"US",
    "sg:address":"101 Eagle Glen Ln Ste A",
    "sg:city":"Eagle",
    "sg:classifiers":[
        {
            "category":"Professional",
            "subcategory":"Lawyer & Legal Services",
            "type":"Services"
        }
    ],
    "sg:phone":"+1 208 939 2600",
    "sg:postcode":"83616",
    "sg:province":"ID",
    "sg:tags":[
        "attorney",
        "planning",
        "estate"
    ],
    "sg:website":"http://barrypeters-law.com",
    "wof:name":"Barry Peters, Attorney At Law",
    "wof:placetype":"venue"
},
  "geometry": {"coordinates":[-116.358101,43.695141],"type":"Point"}
}