{
  "type": "Feature",
  "properties": {
    "iso:country":"US",
    "sg:address":"5777 Glenwood St",
    "sg:city":"Boise",
    "sg:classifiers":[
        {
            "category":"Home & Garden",
            "subcategory":"Furniture",
            "type":"Retail Goods"
        }
    ],
    "sg:phone":"+1 208 321 7500",
    "sg:postcode":"83714",
    "sg:province":"ID",
    "wof:name":"Trading Place Home Cnsgnmnt",
    "wof:placetype":"venue"
},
  "geometry": {"coordinates":[-116.279836,43.657719],"type":"Point"}
}