{
  "type": "Feature",
  "properties": {
    "addr:full":"7998 US Hwy 26 Nampa ID 83687",
    "addr:housenumber":"7998",
    "addr:postcode":"83687",
    "addr:street":"Us Hwy 26",
    "iso:country":"US",
    "sg:address":"7998 US Hwy 26",
    "sg:city":"Nampa",
    "sg:classifiers":[
        {
            "category":"Food & Beverages",
            "subcategory":"Fruits & Vegetables",
            "type":"Retail Goods"
        }
    ],
    "sg:phone":"+1 208 466 3860",
    "sg:postcode":"83687",
    "sg:province":"ID",
    "sg:tags":[
        "produce"
    ],
    "sg:website":"www.theberryranch.com",
    "wof:name":"Berry Ranch",
    "wof:placetype":"venue"
},
  "geometry": {"coordinates":[-116.550658,43.66321],"type":"Point"}
}