{
  "type": "Feature",
  "properties": {
    "iso:country":"US",
    "sg:address":"3647 Rickenbacker St",
    "sg:city":"Boise",
    "sg:classifiers":[
        {
            "category":"Building & Trades",
            "subcategory":"Equipment Rental",
            "type":"Services"
        }
    ],
    "sg:phone":"+1 208 389 9906",
    "sg:postcode":"83705",
    "sg:province":"ID",
    "sg:tags":[
        "aircraft",
        "leasing",
        "charter"
    ],
    "sg:website":"www.accessair.net",
    "wof:name":"Access Air",
    "wof:placetype":"venue"
},
  "geometry": {"coordinates":[-116.223878,43.571019],"type":"Point"}
}