{
  "type": "Feature",
  "properties": {
    "iso:country":"US",
    "sg:address":"2417 12th Ave",
    "sg:city":"Lewiston",
    "sg:classifiers":[
        {
            "category":"Shopping",
            "subcategory":"Bicycles & Sporting Goods",
            "type":"Retail Goods"
        }
    ],
    "sg:phone":"+1 208 743 8774",
    "sg:postcode":"83501",
    "sg:province":"ID",
    "sg:tags":[
        "equipment",
        "golf",
        "supply"
    ],
    "wof:name":"Northwest Golf",
    "wof:placetype":"venue"
},
  "geometry": {"coordinates":[-116.99674400000001,46.408394],"type":"Point"}
}