{
  "type": "Feature",
  "properties": {
    "iso:country":"US",
    "sg:address":"121 Aspenwood Dr",
    "sg:city":"Twin Falls",
    "sg:classifiers":[
        {
            "category":"Real Estate",
            "subcategory":"Real Estate Agent",
            "type":"Services"
        }
    ],
    "sg:phone":"+1 208 734 1091",
    "sg:postcode":"83301",
    "sg:province":"ID",
    "wof:name":"Kezele Co",
    "wof:placetype":"venue"
},
  "geometry": {"coordinates":[-114.435225,42.550127],"type":"Point"}
}