{
  "type": "Feature",
  "properties": {
    "addr:full":"655 E Kingsford Dr Meridian ID 83642",
    "addr:housenumber":"655",
    "addr:postcode":"83642",
    "addr:street":"E Kingsford Dr",
    "iso:country":"US",
    "sg:address":"655 E Kingsford Dr",
    "sg:city":"Meridian",
    "sg:classifiers":[
        {
            "category":"Manufacturing",
            "subcategory":"Printing",
            "type":"Manufacturing & Wholesale Goods"
        }
    ],
    "sg:phone":"+1 208 887 6473",
    "sg:postcode":"83642",
    "sg:province":"ID",
    "sg:tags":[
        "publisher"
    ],
    "wof:name":"Porch Swing Books",
    "wof:placetype":"venue"
},
  "geometry": {"coordinates":[-116.38824700000001,43.587067],"type":"Point"}
}