{
  "type": "Feature",
  "properties": {
    "iso:country":"US",
    "sg:address":"400 S Main St",
    "sg:city":"Hailey",
    "sg:classifiers":[
        {
            "category":"Personal",
            "subcategory":"Beauty Salon",
            "type":"Services"
        }
    ],
    "sg:phone":"+1 208 578 7779",
    "sg:postcode":"83320",
    "sg:province":"ID",
    "sg:tags":[
        "spa",
        "day"
    ],
    "wof:name":"Third Floor",
    "wof:placetype":"venue"
},
  "geometry": {"coordinates":[-114.31319499999999,43.516746],"type":"Point"}
}