{
  "type": "Feature",
  "properties": {
    "iso:country":"US",
    "sg:address":"166 S 2nd W",
    "sg:city":"Preston",
    "sg:classifiers":[
        {
            "category":"Health Services",
            "subcategory":"Chiropractor",
            "type":"Services"
        }
    ],
    "sg:phone":"+1 208 852 2240",
    "sg:postcode":"83263",
    "sg:province":"ID",
    "wof:name":"Cox Chiropractic",
    "wof:placetype":"venue"
},
  "geometry": {"coordinates":[-111.882201,42.092773],"type":"Point"}
}