{
  "type": "Feature",
  "properties": {
    "iso:country":"US",
    "sg:address":"1020 W Franklin St",
    "sg:city":"Boise",
    "sg:classifiers":[
        {
            "category":"Education",
            "subcategory":"College",
            "type":"Public Place"
        }
    ],
    "sg:phone":"+1 208 343 6660",
    "sg:postcode":"83702",
    "sg:province":"ID",
    "sg:tags":[
        "health"
    ],
    "wof:name":"Psychometric Software Inc",
    "wof:placetype":"venue"
},
  "geometry": {"coordinates":[-116.202384,43.621945],"type":"Point"}
}