{
  "type": "Feature",
  "properties": {
    "iso:country":"US",
    "sg:address":"165 Kentucky St",
    "sg:city":"Bliss",
    "sg:classifiers":[
        {
            "category":"Government",
            "subcategory":"Office",
            "type":"Public Place"
        }
    ],
    "sg:phone":"+1 208 352 1117",
    "sg:postcode":"83314",
    "sg:province":"ID",
    "sg:tags":[
        "village"
    ],
    "wof:name":"Bliss City Office",
    "wof:placetype":"venue"
},
  "geometry": {"coordinates":[-114.950041,42.925756],"type":"Point"}
}