{
  "type": "Feature",
  "properties": {
    "iso:country":"US",
    "sg:address":"300 Shoup St",
    "sg:city":"Salmon",
    "sg:classifiers":[
        {
            "category":"Home & Garden",
            "subcategory":"Furniture",
            "type":"Retail Goods"
        }
    ],
    "sg:phone":"+1 208 756 2270",
    "sg:postcode":"83467",
    "sg:province":"ID",
    "wof:name":"House of Bargains",
    "wof:placetype":"venue"
},
  "geometry": {"coordinates":[-113.895848,45.177243],"type":"Point"}
}