{
  "type": "Feature",
  "properties": {
    "iso:country":"US",
    "sg:address":"120 Maple Ave W",
    "sg:city":"Hansen",
    "sg:classifiers":[
        {
            "category":"Education",
            "subcategory":"Library",
            "type":"Public Place"
        }
    ],
    "sg:phone":"+1 208 423 4122",
    "sg:postcode":"83334",
    "sg:province":"ID",
    "wof:name":"Hansen Public Library",
    "wof:placetype":"venue"
},
  "geometry": {"coordinates":[-114.30219,42.530621],"type":"Point"}
}