{
  "type": "Feature",
  "properties": {
    "iso:country":"US",
    "sg:address":"148 N 2nd E",
    "sg:city":"Mountain Home",
    "sg:classifiers":[
        {
            "category":"Personal",
            "subcategory":"Barber",
            "type":"Services"
        }
    ],
    "sg:phone":"+1 208 587 9723",
    "sg:postcode":"83647",
    "sg:province":"ID",
    "wof:name":"Hairbase",
    "wof:placetype":"venue"
},
  "geometry": {"coordinates":[-115.69340800000001,43.131511],"type":"Point"}
}