{
  "type": "Feature",
  "properties": {
    "iso:country":"US",
    "sg:address":"3815 Cleveland Blvd",
    "sg:city":"Caldwell",
    "sg:classifiers":[
        {
            "category":"Shopping",
            "subcategory":"Used Merchandise",
            "type":"Retail Goods"
        }
    ],
    "sg:phone":"+1 208 455 1842",
    "sg:postcode":"83605",
    "sg:province":"ID",
    "sg:tags":[
        "pawnbroker"
    ],
    "wof:name":"M K Sales & Pawn",
    "wof:placetype":"venue"
},
  "geometry": {"coordinates":[-116.652973,43.639364],"type":"Point"}
}