{
  "type": "Feature",
  "properties": {
    "iso:country":"US",
    "sg:address":"364 2nd Ave E",
    "sg:city":"Twin Falls",
    "sg:classifiers":[
        {
            "category":"Shopping",
            "type":"Retail Goods"
        }
    ],
    "sg:phone":"+1 208 733 1560",
    "sg:postcode":"83301",
    "sg:province":"ID",
    "sg:tags":[
        "trophy",
        "medal",
        "award"
    ],
    "wof:name":"Mason's Trophies",
    "wof:placetype":"venue"
},
  "geometry": {"coordinates":[-114.466132,42.554114],"type":"Point"}
}