{
  "type": "Feature",
  "properties": {
    "iso:country":"US",
    "sg:address":"391 S 700 W",
    "sg:city":"Heyburn",
    "sg:phone":"+1 208 678 4856",
    "sg:postcode":"83336",
    "sg:province":"ID",
    "sg:tags":[
        "farm",
        "grain",
        "cash",
        "crop",
        "general"
    ],
    "wof:name":"Elite Frames",
    "wof:placetype":"venue"
},
  "geometry": {"coordinates":[-113.803094,42.56218],"type":"Point"}
}