{
  "type": "Feature",
  "properties": {
    "iso:country":"US",
    "sg:address":"95 Tamarack Ln",
    "sg:city":"Sagle",
    "sg:classifiers":[
        {
            "category":"Health Services",
            "subcategory":"Health Practitioner",
            "type":"Services"
        }
    ],
    "sg:phone":"+1 208 265 2625",
    "sg:postcode":"83860",
    "sg:province":"ID",
    "wof:name":"ABC Midwifery",
    "wof:placetype":"venue"
},
  "geometry": {"coordinates":[-116.54404599999999,48.175926],"type":"Point"}
}