{
  "type": "Feature",
  "properties": {
    "addr:full":"128 N 2nd Ave Pocatello ID 83201",
    "addr:housenumber":"128",
    "addr:postcode":"83201",
    "addr:street":"N 2Nd Ave",
    "iso:country":"US",
    "sg:address":"128 N 2nd Ave",
    "sg:city":"Pocatello",
    "sg:classifiers":[
        {
            "category":"Shopping",
            "subcategory":"Used Merchandise",
            "type":"Retail Goods"
        }
    ],
    "sg:phone":"+1 208 232 0236",
    "sg:postcode":"83201",
    "sg:province":"ID",
    "sg:tags":[
        "antique"
    ],
    "wof:name":"Eastside Antique Mall",
    "wof:placetype":"venue"
},
  "geometry": {"coordinates":[-112.447232,42.865213],"type":"Point"}
}