{
  "type": "Feature",
  "properties": {
    "iso:country":"US",
    "sg:address":"683 Filer Ave",
    "sg:city":"Twin Falls",
    "sg:classifiers":[
        {
            "category":"Personal",
            "subcategory":"Barber",
            "type":"Services"
        }
    ],
    "sg:phone":"+1 208 733 9884",
    "sg:postcode":"83301",
    "sg:province":"ID",
    "wof:name":"Mod Barber & Salon",
    "wof:placetype":"venue"
},
  "geometry": {"coordinates":[-114.465828,42.570523],"type":"Point"}
}