{
  "type": "Feature",
  "properties": {
    "iso:country":"US",
    "sg:address":"402 Main Ave N",
    "sg:city":"Twin Falls",
    "sg:classifiers":[
        {
            "category":"Bars & Pubs",
            "type":"Food & Drink"
        }
    ],
    "sg:phone":"+1 208 733 9808",
    "sg:postcode":"83301",
    "sg:province":"ID",
    "wof:name":"Klover KLUB",
    "wof:placetype":"venue"
},
  "geometry": {"coordinates":[-114.474884,42.559451],"type":"Point"}
}