{
  "type": "Feature",
  "properties": {
    "addr:full":"2001 Main St Sandpoint ID 83864",
    "addr:housenumber":"2001",
    "addr:postcode":"83864",
    "addr:street":"Main St",
    "iso:country":"US",
    "sg:address":"2001 Main St",
    "sg:city":"Sandpoint",
    "sg:classifiers":[
        {
            "category":"Railroad",
            "type":"Transportation"
        }
    ],
    "sg:phone":"+1 208 265 9138",
    "sg:postcode":"83864",
    "sg:province":"ID",
    "wof:name":"BNSF Railway Co",
    "wof:placetype":"venue"
},
  "geometry": {"coordinates":[-116.576474,48.279978],"type":"Point"}
}