{
  "type": "Feature",
  "properties": {
    "addr:full":"736 S Logan St Moscow ID 83843",
    "addr:housenumber":"736",
    "addr:postcode":"83843",
    "addr:street":"S Logan St",
    "iso:country":"US",
    "sg:address":"736 S Logan St",
    "sg:city":"Moscow",
    "sg:classifiers":[
        {
            "category":"Organizations",
            "subcategory":"Community Association",
            "type":"Services"
        }
    ],
    "sg:phone":"+1 208 882 6654",
    "sg:postcode":"83843",
    "sg:province":"ID",
    "wof:name":"Order of Demolay Internat",
    "wof:placetype":"venue"
},
  "geometry": {"coordinates":[-116.993498,46.7281],"type":"Point"}
}