{
  "type": "Feature",
  "properties": {
    "iso:country":"US",
    "sg:address":"7171 S Five Mile Rd",
    "sg:city":"Boise",
    "sg:classifiers":[
        {
            "category":"Retail",
            "subcategory":"Animal Services",
            "type":"Services"
        }
    ],
    "sg:phone":"+1 208 362 2785",
    "sg:postcode":"83709",
    "sg:province":"ID",
    "wof:name":"Kims Pet Grooming",
    "wof:placetype":"venue"
},
  "geometry": {"coordinates":[-116.314522,43.53756],"type":"Point"}
}