{
  "type": "Feature",
  "properties": {
    "iso:country":"US",
    "sg:address":"201 3rd Ave E",
    "sg:city":"Twin Falls",
    "sg:classifiers":[
        {
            "category":"Insurance",
            "subcategory":"Hazard Insurance",
            "type":"Services"
        }
    ],
    "sg:phone":"+1 208 736 9111",
    "sg:postcode":"83301",
    "sg:province":"ID",
    "sg:tags":[
        "bond"
    ],
    "wof:name":"Aladdin Bail Bonds",
    "wof:placetype":"venue"
},
  "geometry": {"coordinates":[-114.466984,42.556293],"type":"Point"}
}