{
  "type": "Feature",
  "properties": {
    "iso:country":"US",
    "sg:address":"327 Madrona St",
    "sg:city":"Twin Falls",
    "sg:classifiers":[
        {
            "category":"Retail",
            "subcategory":"Auto Repair",
            "type":"Services"
        }
    ],
    "sg:phone":"+1 208 733 7156",
    "sg:postcode":"83301",
    "sg:province":"ID",
    "sg:tags":[
        "repairing",
        "automobile",
        "general"
    ],
    "wof:name":"Import Service Center",
    "wof:placetype":"venue"
},
  "geometry": {"coordinates":[-114.450455,42.551967],"type":"Point"}
}