{
  "type": "Feature",
  "properties": {
    "addr:full":"2999 N Lakeharbor Ln Boise ID 83703",
    "addr:housenumber":"2999",
    "addr:postcode":"83703",
    "addr:street":"N Lakeharbor Ln",
    "iso:country":"US",
    "sg:address":"2999 N Lakeharbor Ln",
    "sg:city":"Boise",
    "sg:classifiers":[
        {
            "category":"Personal",
            "subcategory":"Beauty Salon",
            "type":"Services"
        }
    ],
    "sg:phone":"+1 208 853 1929",
    "sg:postcode":"83703",
    "sg:province":"ID",
    "wof:name":"Boise Hair Fitns Salon & Nail",
    "wof:placetype":"venue"
},
  "geometry": {"coordinates":[-116.25601899999999,43.652273],"type":"Point"}
}