{
  "type": "Feature",
  "properties": {
    "iso:country":"US",
    "sg:address":"745 W Bridge St",
    "sg:city":"Blackfoot",
    "sg:classifiers":[
        {
            "category":"Professional",
            "type":"Services"
        }
    ],
    "sg:phone":"+1 208 782 3515",
    "sg:postcode":"83221",
    "sg:province":"ID",
    "sg:tags":[
        "establishment"
    ],
    "wof:name":"Southeastern Idaho",
    "wof:placetype":"venue"
},
  "geometry": {"coordinates":[-112.35304600000001,43.193113],"type":"Point"}
}