{
  "type": "Feature",
  "properties": {
    "iso:country":"US",
    "sg:address":"701 N Indiana Ave",
    "sg:city":"Caldwell",
    "sg:classifiers":[
        {
            "category":"Organizations",
            "subcategory":"Religious Organization",
            "type":"Services"
        }
    ],
    "sg:phone":"+1 208 453 8200",
    "sg:postcode":"83605",
    "sg:province":"ID",
    "sg:tags":[
        "church"
    ],
    "wof:name":"Evergreen Heights Mennonite",
    "wof:placetype":"venue"
},
  "geometry": {"coordinates":[-116.67320599999999,43.67717],"type":"Point"}
}