{
  "type": "Feature",
  "properties": {
    "addr:full":"527 S Main St Moscow ID 83843",
    "addr:housenumber":"527",
    "addr:postcode":"83843",
    "addr:street":"S Main St",
    "iso:country":"US",
    "sg:address":"527 S Main St",
    "sg:city":"Moscow",
    "sg:classifiers":[
        {
            "category":"Restaurant",
            "type":"Food & Drink"
        }
    ],
    "sg:phone":"+1 208 882 0780",
    "sg:postcode":"83843",
    "sg:province":"ID",
    "wof:name":"Mikey's Greek Gyros",
    "wof:placetype":"venue"
},
  "geometry": {"coordinates":[-117.00141600000001,46.730351],"type":"Point"}
}