{
  "type": "Feature",
  "properties": {
    "addr:full":"3736 W Angelica Dr Meridian ID 83642",
    "addr:housenumber":"3736",
    "addr:postcode":"83642",
    "addr:street":"W Angelica Dr",
    "iso:country":"US",
    "sg:address":"3736 W Angelica Dr",
    "sg:city":"Meridian",
    "sg:classifiers":[
        {
            "category":"Professional",
            "subcategory":"Business Services",
            "type":"Services"
        }
    ],
    "sg:phone":"+1 208 288 2654",
    "sg:postcode":"83642",
    "sg:province":"ID",
    "wof:name":"A2 Enterprises LLC",
    "wof:placetype":"venue"
},
  "geometry": {"coordinates":[-116.439944,43.630667],"type":"Point"}
}