{
  "type": "Feature",
  "properties": {
    "addr:full":"1106 W State St Boise ID 83702",
    "addr:housenumber":"1106",
    "addr:postcode":"83702",
    "addr:street":"W State St",
    "iso:country":"US",
    "sg:address":"1106 W State St",
    "sg:city":"Boise",
    "sg:classifiers":[
        {
            "category":"Restaurant",
            "type":"Food & Drink"
        }
    ],
    "sg:menulink":"http://www.allmenus.com/id/boise-city/120330-subway/menu/",
    "sg:phone":"+1 208 331 7827",
    "sg:postcode":"83702",
    "sg:province":"ID",
    "sg:tags":[
        "american",
        "sandwich"
    ],
    "wof:name":"Subway",
    "wof:placetype":"venue"
},
  "geometry": {"coordinates":[-116.20421,43.620883],"type":"Point"}
}