{
  "type": "Feature",
  "properties": {
    "addr:full":"23 Fox Meadow Ln Idaho City ID 83631",
    "addr:housenumber":"23",
    "addr:postcode":"83631",
    "addr:street":"Fox Meadow Ln Idaho",
    "iso:country":"US",
    "sg:address":"23 Fox Meadow Ln",
    "sg:city":"Idaho City",
    "sg:classifiers":[
        {
            "category":"Travel",
            "subcategory":"Hotels & Motels",
            "type":"Entertainment"
        }
    ],
    "sg:phone":"+1 208 392 2273",
    "sg:postcode":"83631",
    "sg:province":"ID",
    "sg:tags":[
        "breakfast",
        "accommodation",
        "bed"
    ],
    "wof:name":"Guest House The B & B",
    "wof:placetype":"venue"
},
  "geometry": {"coordinates":[-115.857871,43.82472],"type":"Point"}
}