{
  "type": "Feature",
  "properties": {
    "addr:full":"960 Bryan Rd Pocatello ID 83201",
    "addr:housenumber":"960",
    "addr:postcode":"83201",
    "addr:street":"Bryan Rd",
    "iso:country":"US",
    "sg:address":"960 Bryan Rd",
    "sg:city":"Pocatello",
    "sg:classifiers":[
        {
            "category":"Building & Trades",
            "subcategory":"Construction",
            "type":"Services"
        }
    ],
    "sg:phone":"+1 208 237 1386",
    "sg:postcode":"83201",
    "sg:province":"ID",
    "sg:tags":[
        "demolition",
        "contractor"
    ],
    "wof:name":"Koger Excavation",
    "wof:placetype":"venue"
},
  "geometry": {"coordinates":[-112.467529,42.893874],"type":"Point"}
}