{
  "type": "Feature",
  "properties": {
    "addr:full":"150 N 2nd E Mountain Home ID 83647",
    "addr:housenumber":"150",
    "addr:postcode":"83647",
    "addr:street":"N 2Nd E",
    "iso:country":"US",
    "sg:address":"150 N 2nd E",
    "sg:city":"Mountain Home",
    "sg:classifiers":[
        {
            "category":"Shopping",
            "subcategory":"Jewelry",
            "type":"Retail Goods"
        }
    ],
    "sg:phone":"+1 208 587 5372",
    "sg:postcode":"83647",
    "sg:province":"ID",
    "sg:tags":[
        "jeweler"
    ],
    "wof:name":"Stoecker Jewelers",
    "wof:placetype":"venue"
},
  "geometry": {"coordinates":[-115.693397,43.131493],"type":"Point"}
}