{
  "type": "Feature",
  "properties": {
    "iso:country":"US",
    "sg:address":"715 N Kings Rd",
    "sg:city":"Nampa",
    "sg:classifiers":[
        {
            "category":"Wholesale",
            "subcategory":"Machinery & Supplies",
            "type":"Manufacturing & Wholesale Goods"
        }
    ],
    "sg:phone":"+1 208 463 1500",
    "sg:postcode":"83687",
    "sg:province":"ID",
    "sg:tags":[
        "compressor",
        "gas"
    ],
    "sg:website":"www.rogers-machinery.com",
    "wof:name":"Rogers Machinery Co",
    "wof:placetype":"venue"
},
  "geometry": {"coordinates":[-116.53312,43.591121],"type":"Point"}
}