{
  "type": "Feature",
  "properties": {
    "iso:country":"US",
    "sg:address":"709 Cleveland Blvd",
    "sg:city":"Caldwell",
    "sg:phone":"+1 208 459 3421",
    "sg:postcode":"83605",
    "sg:province":"ID",
    "sg:tags":[
        "irrigation",
        "company"
    ],
    "wof:name":"Wilder Irrigation District",
    "wof:placetype":"venue"
},
  "geometry": {"coordinates":[-116.69071099999999,43.664987],"type":"Point"}
}