{
  "type": "Feature",
  "properties": {
    "iso:country":"US",
    "sg:address":"11323 N Government Way",
    "sg:city":"Hayden",
    "sg:classifiers":[
        {
            "category":"Home & Garden",
            "subcategory":"Building Materials",
            "type":"Retail Goods"
        }
    ],
    "sg:phone":"+1 208 255 8654",
    "sg:postcode":"83835",
    "sg:province":"ID",
    "wof:name":"Cedar Etc",
    "wof:placetype":"venue"
},
  "geometry": {"coordinates":[-116.786463,47.775485],"type":"Point"}
}