{
  "type": "Feature",
  "properties": {
    "iso:country":"US",
    "sg:address":"1244 W Hempstead Dr",
    "sg:city":"Eagle",
    "sg:classifiers":[
        {
            "category":"Building & Trades",
            "subcategory":"Construction",
            "type":"Services"
        }
    ],
    "sg:phone":"+1 208 939 8003",
    "sg:postcode":"83616",
    "sg:province":"ID",
    "sg:tags":[
        "plastering",
        "contractor"
    ],
    "wof:name":"John Delsman Plastering Inc",
    "wof:placetype":"venue"
},
  "geometry": {"coordinates":[-116.369083,43.663934],"type":"Point"}
}