{
  "type": "Feature",
  "properties": {
    "iso:country":"US",
    "sg:address":"209 W Main St",
    "sg:city":"Grangeville",
    "sg:classifiers":[
        {
            "category":"Shopping",
            "subcategory":"Stationery & Office Supplies",
            "type":"Retail Goods"
        }
    ],
    "sg:phone":"+1 208 983 1822",
    "sg:postcode":"83530",
    "sg:province":"ID",
    "sg:tags":[
        "album",
        "scrapbook"
    ],
    "wof:name":"Crafting Keepsakes",
    "wof:placetype":"venue"
},
  "geometry": {"coordinates":[-116.122185,45.926347],"type":"Point"}
}