{
  "type": "Feature",
  "properties": {
    "iso:country":"US",
    "sg:address":"5574 N Cattail Way",
    "sg:city":"Boise",
    "sg:classifiers":[
        {
            "category":"Professional",
            "subcategory":"Business Services",
            "type":"Services"
        }
    ],
    "sg:phone":"+1 208 853 2700",
    "sg:postcode":"83714",
    "sg:province":"ID",
    "wof:name":"Mary Chapin",
    "wof:placetype":"venue"
},
  "geometry": {"coordinates":[-116.293455,43.671016],"type":"Point"}
}