{
  "type": "Feature",
  "properties": {
    "iso:country":"US",
    "sg:address":"226 S 1st W",
    "sg:city":"Rexburg",
    "sg:classifiers":[
        {
            "category":"Real Estate",
            "subcategory":"Real Estate Operator",
            "type":"Services"
        }
    ],
    "sg:phone":"+1 208 356 4376",
    "sg:postcode":"83440",
    "sg:province":"ID",
    "sg:tags":[
        "apartment"
    ],
    "wof:name":"Breckenridge Apartments",
    "wof:placetype":"venue"
},
  "geometry": {"coordinates":[-111.78676400000001,43.821305],"type":"Point"}
}