{
  "type": "Feature",
  "properties": {
    "iso:country":"US",
    "sg:address":"755 State Hwy 41",
    "sg:city":"Post Falls",
    "sg:classifiers":[
        {
            "category":"Food & Beverages",
            "subcategory":"Specialty",
            "type":"Retail Goods"
        }
    ],
    "sg:phone":"+1 208 773 1323",
    "sg:postcode":"83854",
    "sg:province":"ID",
    "sg:tags":[
        "tea",
        "coffee"
    ],
    "wof:name":"Northern Espresso",
    "wof:placetype":"venue"
},
  "geometry": {"coordinates":[-116.89439900000001,47.714492],"type":"Point"}
}