{
  "type": "Feature",
  "properties": {
    "iso:country":"US",
    "sg:address":"402 E Court St",
    "sg:city":"Weiser",
    "sg:classifiers":[
        {
            "category":"Organizations",
            "subcategory":"Religious Organization",
            "type":"Services"
        }
    ],
    "sg:phone":"+1 208 549 2563",
    "sg:postcode":"83672",
    "sg:province":"ID",
    "sg:tags":[
        "churches-lutheran",
        "church"
    ],
    "wof:name":"Lutheran Concordia Church",
    "wof:placetype":"venue"
},
  "geometry": {"coordinates":[-116.964032,44.246811],"type":"Point"}
}