{
  "type": "Feature",
  "properties": {
    "addr:full":"10890 W Alliance St Boise ID 83713",
    "addr:housenumber":"10890",
    "addr:postcode":"83713",
    "addr:street":"W Alliance St",
    "iso:country":"US",
    "sg:address":"10890 W Alliance St",
    "sg:city":"Boise",
    "sg:classifiers":[
        {
            "category":"Building & Trades",
            "subcategory":"Electrical",
            "type":"Services"
        }
    ],
    "sg:phone":"+1 208 322 8213",
    "sg:postcode":"83713",
    "sg:province":"ID",
    "sg:tags":[
        "installation"
    ],
    "wof:name":"Zumbrunnen's Installations",
    "wof:placetype":"venue"
},
  "geometry": {"coordinates":[-116.315068,43.640547],"type":"Point"}
}