{
  "type": "Feature",
  "properties": {
    "iso:country":"US",
    "sg:address":"2900 N Government Way",
    "sg:city":"Coeur D Alene",
    "sg:classifiers":[
        {
            "category":"Health Services",
            "subcategory":"Health Practitioner",
            "type":"Services"
        }
    ],
    "sg:phone":"+1 208 676 0926",
    "sg:postcode":"83815",
    "sg:province":"ID",
    "sg:tags":[
        "psychologist"
    ],
    "wof:name":"La Ver L Wilhelm",
    "wof:placetype":"venue"
},
  "geometry": {"coordinates":[-116.786337,47.703467],"type":"Point"}
}