{
  "type": "Feature",
  "properties": {
    "iso:country":"US",
    "sg:address":"511 Ave H",
    "sg:city":"Boise",
    "sg:classifiers":[
        {
            "category":"Real Estate",
            "subcategory":"Real Estate Operator",
            "type":"Services"
        }
    ],
    "sg:phone":"+1 208 345 5455",
    "sg:postcode":"83712",
    "sg:province":"ID",
    "sg:tags":[
        "apartment"
    ],
    "wof:name":"Laurel Park Apartments",
    "wof:placetype":"venue"
},
  "geometry": {"coordinates":[-116.183515,43.612768],"type":"Point"}
}