{
  "type": "Feature",
  "properties": {
    "addr:full":"20 W 200 N Jerome ID 83338",
    "addr:housenumber":"20",
    "addr:postcode":"83338",
    "addr:street":"W 200 N",
    "iso:country":"US",
    "sg:address":"20 W 200 N",
    "sg:city":"Jerome",
    "sg:classifiers":[
        {
            "category":"Wholesale",
            "subcategory":"Farm Supplies",
            "type":"Manufacturing & Wholesale Goods"
        }
    ],
    "sg:phone":"+1 208 324 4000",
    "sg:postcode":"83338",
    "sg:province":"ID",
    "sg:tags":[
        "feed",
        "concentrate",
        "supplement"
    ],
    "wof:name":"Adm Animal Health & Nutrition",
    "wof:placetype":"venue"
},
  "geometry": {"coordinates":[-114.523886,42.753127],"type":"Point"}
}