{
  "type": "Feature",
  "properties": {
    "iso:country":"US",
    "sg:address":"1247 Morehouse Rd",
    "sg:city":"Emmett",
    "sg:classifiers":[
        {
            "category":"Building & Trades",
            "subcategory":"Construction",
            "type":"Services"
        }
    ],
    "sg:phone":"+1 208 365 2053",
    "sg:postcode":"83617",
    "sg:province":"ID",
    "sg:tags":[
        "contractor"
    ],
    "wof:name":"Bullock Contracting",
    "wof:placetype":"venue"
},
  "geometry": {"coordinates":[-116.612195,43.872352],"type":"Point"}
}