{
  "type": "Feature",
  "properties": {
    "addr:full":"8011 Ustick Rd Boise ID 83704",
    "addr:postcode":"8011;83704",
    "addr:street":"Ustick Rd",
    "iso:country":"US",
    "sg:address":"8011 Ustick Rd",
    "sg:city":"Boise",
    "sg:classifiers":[
        {
            "category":"Organizations",
            "subcategory":"Membership Organization",
            "type":"Services"
        }
    ],
    "sg:phone":"+1 208 322 5505",
    "sg:postcode":"83704",
    "sg:province":"ID",
    "sg:tags":[
        "athletic"
    ],
    "sg:website":"www.idhsaa.org",
    "wof:name":"Idaho High School Activities",
    "wof:placetype":"venue"
},
  "geometry": {"coordinates":[-116.284132,43.633846],"type":"Point"}
}