{
  "type": "Feature",
  "properties": {
    "iso:country":"US",
    "sg:address":"435 S 100 W",
    "sg:city":"Preston",
    "sg:classifiers":[
        {
            "category":"Wholesale",
            "subcategory":"Durable Goods & Equipment",
            "type":"Manufacturing & Wholesale Goods"
        }
    ],
    "sg:phone":"+1 208 852 1296",
    "sg:postcode":"83252",
    "sg:province":"ID",
    "wof:name":"Pickin Grinn",
    "wof:placetype":"venue"
},
  "geometry": {"coordinates":[-112.247969,42.177396],"type":"Point"}
}