{
  "type": "Feature",
  "properties": {
    "addr:full":"110 Railroad St Hazelton ID 83335",
    "addr:housenumber":"110",
    "addr:postcode":"83335",
    "addr:street":"Railroad St",
    "iso:country":"US",
    "sg:address":"110 Railroad St",
    "sg:city":"Hazelton",
    "sg:classifiers":[
        {
            "category":"Retail",
            "subcategory":"Repair Shop",
            "type":"Services"
        }
    ],
    "sg:phone":"+1 208 829 5812",
    "sg:postcode":"83335",
    "sg:province":"ID",
    "sg:tags":[
        "scooter",
        "motorcycle",
        "motor"
    ],
    "wof:name":"Gary's Allsports Part Svc",
    "wof:placetype":"venue"
},
  "geometry": {"coordinates":[-114.138043,42.597622],"type":"Point"}
}