{
  "type": "Feature",
  "properties": {
    "addr:full":"611 E Seltice Way Post Falls ID 83854",
    "addr:housenumber":"611",
    "addr:postcode":"83854",
    "addr:street":"E Seltice Way",
    "iso:country":"US",
    "sg:address":"611 E Seltice Way",
    "sg:city":"Post Falls",
    "sg:classifiers":[
        {
            "category":"Restaurant",
            "type":"Food & Drink"
        }
    ],
    "sg:phone":"+1 208 773 2051",
    "sg:postcode":"83854",
    "sg:province":"ID",
    "wof:name":"Falls Club",
    "wof:placetype":"venue"
},
  "geometry": {"coordinates":[-116.94025499999999,47.714468],"type":"Point"}
}