{
  "type": "Feature",
  "properties": {
    "addr:full":"2559 W 1800 S Aberdeen ID 83210",
    "addr:housenumber":"2559",
    "addr:postcode":"83210",
    "addr:street":"W 1800 S",
    "iso:country":"US",
    "sg:address":"2559 W 1800 S",
    "sg:city":"Aberdeen",
    "sg:classifiers":[
        {
            "category":"Utilities",
            "subcategory":"Refuse",
            "type":"Services"
        }
    ],
    "sg:phone":"+1 208 397 3835",
    "sg:postcode":"83210",
    "sg:province":"ID",
    "sg:tags":[
        "landfill"
    ],
    "wof:name":"Aberdeen C & D Site",
    "wof:placetype":"venue"
},
  "geometry": {"coordinates":[-112.802353,42.936923],"type":"Point"}
}