{
  "type": "Feature",
  "properties": {
    "iso:country":"US",
    "sg:address":"5067 N Building Center Dr",
    "sg:city":"Coeur D Alene",
    "sg:classifiers":[
        {
            "category":"Building & Trades",
            "subcategory":"Construction",
            "type":"Services"
        }
    ],
    "sg:phone":"+1 208 765 5059",
    "sg:postcode":"83815",
    "sg:province":"ID",
    "sg:tags":[
        "general",
        "contractor"
    ],
    "wof:name":"Copper Basin Construction",
    "wof:placetype":"venue"
},
  "geometry": {"coordinates":[-116.79466499999999,47.718104],"type":"Point"}
}