{
  "type": "Feature",
  "properties": {
    "addr:full":"3380 W Americana Ter Boise ID 83706",
    "addr:housenumber":"3380",
    "addr:postcode":"83706",
    "addr:street":"W Americana Ter",
    "iso:country":"US",
    "sg:address":"3380 W Americana Ter",
    "sg:city":"Boise",
    "sg:classifiers":[
        {
            "category":"Government",
            "subcategory":"Office",
            "type":"Public Place"
        }
    ],
    "sg:phone":"+1 208 334 3833",
    "sg:postcode":"83706",
    "sg:province":"ID",
    "sg:tags":[
        "state",
        "resource"
    ],
    "sg:website":"www.idahoaging.com",
    "wof:name":"Aging Office",
    "wof:placetype":"venue"
},
  "geometry": {"coordinates":[-116.226403,43.616535],"type":"Point"}
}