{
  "type": "Feature",
  "properties": {
    "iso:country":"US",
    "sg:address":"46 N Fairview St",
    "sg:city":"Nampa",
    "sg:classifiers":[
        {
            "category":"Organizations",
            "subcategory":"Religious Organization",
            "type":"Services"
        }
    ],
    "sg:phone":"+1 208 466 6211",
    "sg:postcode":"83651",
    "sg:province":"ID",
    "sg:tags":[
        "church"
    ],
    "wof:name":"Fairview Church-Nazarene",
    "wof:placetype":"venue"
},
  "geometry": {"coordinates":[-116.575498,43.576004],"type":"Point"}
}