{
  "type": "Feature",
  "properties": {
    "addr:full":"6710 Overland Rd Boise ID 83709",
    "addr:housenumber":"6710",
    "addr:postcode":"83709",
    "addr:street":"Overland Rd",
    "iso:country":"US",
    "sg:address":"6710 Overland Rd",
    "sg:city":"Boise",
    "sg:classifiers":[
        {
            "category":"Real Estate",
            "subcategory":"Architect",
            "type":"Services"
        }
    ],
    "sg:phone":"+1 208 376 4474",
    "sg:postcode":"83709",
    "sg:province":"ID",
    "wof:name":"Crowder Associates Architect",
    "wof:placetype":"venue"
},
  "geometry": {"coordinates":[-116.26617299999999,43.590157],"type":"Point"}
}