{
  "type": "Feature",
  "properties": {
    "iso:country":"US",
    "sg:address":"1760 N Mitchell St",
    "sg:city":"Boise",
    "sg:classifiers":[
        {
            "category":"Real Estate",
            "subcategory":"Real Estate Operator",
            "type":"Services"
        }
    ],
    "sg:phone":"+1 208 375 2272",
    "sg:postcode":"83704",
    "sg:province":"ID",
    "sg:tags":[
        "property",
        "lessor"
    ],
    "wof:name":"Exeter Inc",
    "wof:placetype":"venue"
},
  "geometry": {"coordinates":[-116.304159,43.621037],"type":"Point"}
}