{
  "type": "Feature",
  "properties": {
    "addr:full":"514 Main St Lewiston ID 83501",
    "addr:housenumber":"514",
    "addr:postcode":"83501",
    "addr:street":"Main St",
    "iso:country":"US",
    "sg:address":"514 Main St",
    "sg:city":"Lewiston",
    "sg:classifiers":[
        {
            "category":"Shopping",
            "subcategory":"Gifts & Souvenirs",
            "type":"Retail Goods"
        },
        {
            "category":"Shopping",
            "subcategory":"Clothing, Apparel, & Fashions",
            "type":"Retail Goods"
        }
    ],
    "sg:phone":"+1 208 746 6144",
    "sg:postcode":"83501",
    "sg:province":"ID",
    "sg:tags":[
        "lingerie"
    ],
    "wof:name":"Giggles and Gifts",
    "wof:placetype":"venue"
},
  "geometry": {"coordinates":[-117.027098,46.421432],"type":"Point"}
}