{
  "type": "Feature",
  "properties": {
    "iso:country":"US",
    "sg:address":"1755 N Westgate Dr",
    "sg:city":"Boise",
    "sg:classifiers":[
        {
            "category":"Health Services",
            "subcategory":"Health Practitioner",
            "type":"Services"
        }
    ],
    "sg:phone":"+1 208 373 0771",
    "sg:postcode":"83704",
    "sg:province":"ID",
    "wof:name":"Todd Bennett PHD",
    "wof:placetype":"venue"
},
  "geometry": {"coordinates":[-116.2808,43.621185],"type":"Point"}
}