{
  "type": "Feature",
  "properties": {
    "iso:country":"US",
    "sg:address":"1900 16th St",
    "sg:city":"Heyburn",
    "sg:classifiers":[
        {
            "category":"Professional",
            "type":"Services"
        }
    ],
    "sg:phone":"+1 208 878 4438",
    "sg:postcode":"83336",
    "sg:province":"ID",
    "sg:tags":[
        "establishment"
    ],
    "wof:name":"Twenty Is The Limit",
    "wof:placetype":"venue"
},
  "geometry": {"coordinates":[-113.769448,42.556762],"type":"Point"}
}