{
  "type": "Feature",
  "properties": {
    "iso:country":"US",
    "sg:address":"2865 N Ammon Rd",
    "sg:city":"Idaho Falls",
    "sg:classifiers":[
        {
            "category":"Shopping",
            "subcategory":"Clothing, Apparel, & Fashions",
            "type":"Retail Goods"
        }
    ],
    "sg:phone":"+1 208 522 1819",
    "sg:postcode":"83401",
    "sg:province":"ID",
    "sg:tags":[
        "leather"
    ],
    "wof:name":"Eagle Rock Fur & Leather",
    "wof:placetype":"venue"
},
  "geometry": {"coordinates":[-111.964192,43.522271],"type":"Point"}
}