{
  "type": "Feature",
  "properties": {
    "iso:country":"US",
    "sg:address":"1520 N 17th St",
    "sg:city":"Boise",
    "sg:classifiers":[
        {
            "category":"Professional",
            "subcategory":"Detective & Security Services",
            "type":"Services"
        }
    ],
    "sg:phone":"+1 208 336 5949",
    "sg:postcode":"83702",
    "sg:province":"ID",
    "sg:tags":[
        "car"
    ],
    "wof:name":"Henderson Associates",
    "wof:placetype":"venue"
},
  "geometry": {"coordinates":[-116.209489,43.63358],"type":"Point"}
}