{
  "type": "Feature",
  "properties": {
    "iso:country":"US",
    "sg:address":"115 S 8th St",
    "sg:city":"St Maries",
    "sg:classifiers":[
        {
            "category":"Personal",
            "subcategory":"Beauty Salon",
            "type":"Services"
        }
    ],
    "sg:phone":"+1 208 245 6530",
    "sg:postcode":"83861",
    "sg:province":"ID",
    "wof:name":"Natural Beauty Salon",
    "wof:placetype":"venue"
},
  "geometry": {"coordinates":[-116.567859,47.316117],"type":"Point"}
}