{
  "type": "Feature",
  "properties": {
    "addr:full":"11433 N Church Rd Rathdrum ID 83858",
    "addr:housenumber":"11433",
    "addr:postcode":"83858",
    "addr:street":"N Church Rd",
    "iso:country":"US",
    "sg:address":"11433 N Church Rd",
    "sg:city":"Rathdrum",
    "sg:classifiers":[
        {
            "category":"Building & Trades",
            "subcategory":"Plumbing",
            "type":"Services"
        }
    ],
    "sg:phone":"+1 208 687 0475",
    "sg:postcode":"83858",
    "sg:province":"ID",
    "sg:tags":[
        "plumbing",
        "contractor"
    ],
    "wof:name":"Three V Plumbing & Heating",
    "wof:placetype":"venue"
},
  "geometry": {"coordinates":[-116.975216,47.775878],"type":"Point"}
}