{
  "type": "Feature",
  "properties": {
    "iso:country":"US",
    "sg:address":"1175 E Parkcenter Blvd",
    "sg:city":"Boise",
    "sg:classifiers":[
        {
            "category":"Freight",
            "type":"Transportation"
        }
    ],
    "sg:phone":"+1 208 331 1888",
    "sg:postcode":"83706",
    "sg:province":"ID",
    "sg:tags":[
        "commercial",
        "storage"
    ],
    "wof:name":"Stor-It Rental Storages",
    "wof:placetype":"venue"
},
  "geometry": {"coordinates":[-116.17341999999999,43.587749],"type":"Point"}
}