{
  "type": "Feature",
  "properties": {
    "iso:country":"US",
    "sg:address":"721 W North St",
    "sg:city":"Grangeville",
    "sg:classifiers":[
        {
            "category":"Health Services",
            "subcategory":"Doctor",
            "type":"Services"
        }
    ],
    "sg:phone":"+1 208 983 0300",
    "sg:postcode":"83530",
    "sg:province":"ID",
    "sg:tags":[
        "physician",
        "surgeon"
    ],
    "wof:name":"Wayne Hollopeter MD",
    "wof:placetype":"venue"
},
  "geometry": {"coordinates":[-116.128097,45.92763],"type":"Point"}
}