{
  "type": "Feature",
  "properties": {
    "iso:country":"US",
    "sg:address":"159 S Main St",
    "sg:city":"Pocatello",
    "sg:classifiers":[
        {
            "category":"Professional",
            "subcategory":"Employment Agencies",
            "type":"Services"
        }
    ],
    "sg:phone":"+1 208 232 6900",
    "sg:postcode":"83204",
    "sg:province":"ID",
    "sg:tags":[
        "modeling"
    ],
    "wof:name":"Fancy Faces Modeling Ctr",
    "wof:placetype":"venue"
},
  "geometry": {"coordinates":[-112.450336,42.861742],"type":"Point"}
}