{
  "type": "Feature",
  "properties": {
    "iso:country":"US",
    "sg:address":"3619 Beacon Ave",
    "sg:city":"Emmett",
    "sg:classifiers":[
        {
            "category":"Wholesale",
            "subcategory":"Plants",
            "type":"Manufacturing & Wholesale Goods"
        }
    ],
    "sg:phone":"+1 208 365 2329",
    "sg:postcode":"83617",
    "sg:province":"ID",
    "sg:tags":[
        "nursery",
        "tree"
    ],
    "wof:name":"Peterson Tree Farm",
    "wof:placetype":"venue"
},
  "geometry": {"coordinates":[-116.61246300000001,43.917624],"type":"Point"}
}