{
  "type": "Feature",
  "properties": {
    "addr:full":"2732 Cherry Cir Emmett ID 83617",
    "addr:housenumber":"2732",
    "addr:postcode":"83617",
    "addr:street":"Cherry Cir",
    "iso:country":"US",
    "sg:address":"2732 Cherry Cir",
    "sg:city":"Emmett",
    "sg:classifiers":[
        {
            "category":"Building & Trades",
            "subcategory":"Construction",
            "type":"Services"
        }
    ],
    "sg:phone":"+1 208 869 0111",
    "sg:postcode":"83617",
    "sg:province":"ID",
    "sg:tags":[
        "house"
    ],
    "wof:name":"On The Level Excavating Inc",
    "wof:placetype":"venue"
},
  "geometry": {"coordinates":[-116.46996,43.851244],"type":"Point"}
}