{
  "type": "Feature",
  "properties": {
    "iso:country":"US",
    "sg:address":"145 N 2nd E",
    "sg:city":"Mountain Home",
    "sg:classifiers":[
        {
            "category":"Restaurant",
            "type":"Food & Drink"
        }
    ],
    "sg:phone":"+1 208 587 9223",
    "sg:postcode":"83647",
    "sg:province":"ID",
    "wof:name":"Charlies Top Hat Barbeque",
    "wof:placetype":"venue"
},
  "geometry": {"coordinates":[-115.693652,43.131473],"type":"Point"}
}