{
  "type": "Feature",
  "properties": {
    "iso:country":"US",
    "sg:address":"795 S 5th W",
    "sg:city":"Mountain Home",
    "sg:classifiers":[
        {
            "category":"Recreation",
            "type":"Entertainment"
        }
    ],
    "sg:phone":"+1 208 587 2112",
    "sg:postcode":"83647",
    "sg:province":"ID",
    "sg:tags":[
        "parks"
    ],
    "wof:name":"Mountain Home Parks Dept",
    "wof:placetype":"venue"
},
  "geometry": {"coordinates":[-115.697416,43.125692],"type":"Point"}
}