{
  "type": "Feature",
  "properties": {
    "iso:country":"US",
    "sg:address":"4105 Adams St",
    "sg:city":"Boise",
    "sg:classifiers":[
        {
            "category":"Shopping",
            "subcategory":"Bicycles & Sporting Goods",
            "type":"Retail Goods"
        }
    ],
    "sg:phone":"+1 208 376 4440",
    "sg:postcode":"83714",
    "sg:province":"ID",
    "sg:tags":[
        "gun",
        "gunsmith"
    ],
    "sg:website":"www.boisegun.com",
    "wof:name":"Boise Gun Co",
    "wof:placetype":"venue"
},
  "geometry": {"coordinates":[-116.246178,43.633727],"type":"Point"}
}