{
  "type": "Feature",
  "properties": {
    "iso:country":"US",
    "sg:address":"902 S Division St",
    "sg:city":"Pinehurst",
    "sg:classifiers":[
        {
            "category":"Organizations",
            "subcategory":"Religious Organization",
            "type":"Services"
        }
    ],
    "sg:phone":"+1 208 682 2911",
    "sg:postcode":"83850",
    "sg:province":"ID",
    "sg:tags":[
        "church"
    ],
    "wof:name":"Church Of Jesus Christ Of Lds",
    "wof:placetype":"venue"
},
  "geometry": {"coordinates":[-116.240816,47.530282],"type":"Point"}
}