{
  "type": "Feature",
  "properties": {
    "iso:country":"US",
    "sg:address":"202 S 1st Ave",
    "sg:city":"Sandpoint",
    "sg:classifiers":[
        {
            "category":"Real Estate",
            "subcategory":"Real Estate Agent",
            "type":"Services"
        }
    ],
    "sg:phone":"+1 208 263 6802",
    "sg:postcode":"83864",
    "sg:province":"ID",
    "sg:website":"www.cbsandpoint.com",
    "wof:name":"Resort Realty",
    "wof:placetype":"venue"
},
  "geometry": {"coordinates":[-116.547865,48.272106],"type":"Point"}
}