{
  "type": "Feature",
  "properties": {
    "iso:country":"US",
    "sg:address":"903 11th Ave S",
    "sg:city":"Nampa",
    "sg:classifiers":[
        {
            "category":"Social Services",
            "subcategory":"Adult Care",
            "type":"Services"
        }
    ],
    "sg:phone":"+1 208 466 1311",
    "sg:postcode":"83651",
    "sg:province":"ID",
    "sg:tags":[
        "home",
        "residential"
    ],
    "wof:name":"R & V Shelter Home",
    "wof:placetype":"venue"
},
  "geometry": {"coordinates":[-116.56870600000001,43.573479],"type":"Point"}
}