{
  "type": "Feature",
  "properties": {
    "addr:full":"404 2nd St S Nampa ID 83651",
    "addr:housenumber":"404",
    "addr:postcode":"83651",
    "addr:street":"2Nd St S",
    "iso:country":"US",
    "sg:address":"404 2nd St S",
    "sg:city":"Nampa",
    "sg:classifiers":[
        {
            "category":"Building & Trades",
            "subcategory":"Equipment Rental",
            "type":"Services"
        }
    ],
    "sg:phone":"+1 208 465 7368",
    "sg:postcode":"83651",
    "sg:province":"ID",
    "sg:tags":[
        "yard"
    ],
    "sg:website":"www.tatesrents.com",
    "wof:name":"Tates Rents",
    "wof:placetype":"venue"
},
  "geometry": {"coordinates":[-116.569041,43.583766],"type":"Point"}
}