{
  "type": "Feature",
  "properties": {
    "iso:country":"US",
    "sg:address":"68 E Fork Rd",
    "sg:city":"Hailey",
    "sg:classifiers":[
        {
            "category":"Restaurant",
            "type":"Food & Drink"
        }
    ],
    "sg:phone":"+1 208 788 3638",
    "sg:postcode":"83333",
    "sg:province":"ID",
    "sg:tags":[
        "eating"
    ],
    "wof:name":"Delightful Occasions Catering",
    "wof:placetype":"venue"
},
  "geometry": {"coordinates":[-114.331101,43.606448],"type":"Point"}
}