{
  "type": "Feature",
  "properties": {
    "iso:country":"US",
    "sg:address":"2002 N Ridgeview Dr",
    "sg:city":"Post Falls",
    "sg:classifiers":[
        {
            "category":"Building & Trades",
            "subcategory":"Construction",
            "type":"Services"
        }
    ],
    "sg:phone":"+1 208 773 9634",
    "sg:postcode":"83854",
    "sg:province":"ID",
    "sg:tags":[
        "contractor"
    ],
    "wof:name":"Nesbitt Masonry",
    "wof:placetype":"venue"
},
  "geometry": {"coordinates":[-116.900222,47.728563],"type":"Point"}
}