{
  "type": "Feature",
  "properties": {
    "addr:full":"155 South St Blackfoot ID 83221",
    "addr:housenumber":"155",
    "addr:postcode":"83221",
    "addr:street":"South St",
    "iso:country":"US",
    "sg:address":"155 South St",
    "sg:city":"Blackfoot",
    "sg:classifiers":[
        {
            "category":"Education",
            "subcategory":"Dance Studio",
            "type":"Public Place"
        }
    ],
    "sg:phone":"+1 208 785 0763",
    "sg:postcode":"83221",
    "sg:province":"ID",
    "wof:name":"Dance Lowell",
    "wof:placetype":"venue"
},
  "geometry": {"coordinates":[-112.34571,43.183603],"type":"Point"}
}