{
  "type": "Feature",
  "properties": {
    "addr:full":"107 3rd Ave W Jerome ID 83338",
    "addr:housenumber":"107",
    "addr:postcode":"83338",
    "addr:street":"3Rd Ave W",
    "iso:country":"US",
    "sg:address":"107 3rd Ave W",
    "sg:city":"Jerome",
    "sg:classifiers":[
        {
            "category":"Education",
            "subcategory":"School",
            "type":"Public Place"
        }
    ],
    "sg:phone":"+1 208 324 2392",
    "sg:postcode":"83338",
    "sg:province":"ID",
    "wof:name":"Jerome School District",
    "wof:placetype":"venue"
},
  "geometry": {"coordinates":[-114.522001,42.727039],"type":"Point"}
}