{
  "type": "Feature",
  "properties": {
    "iso:country":"US",
    "sg:address":"1409 Taft Ave",
    "sg:city":"Salmon",
    "sg:classifiers":[
        {
            "category":"Building & Trades",
            "subcategory":"Construction",
            "type":"Services"
        }
    ],
    "sg:phone":"+1 208 756 4657",
    "sg:postcode":"83467",
    "sg:province":"ID",
    "sg:tags":[
        "carpentry"
    ],
    "wof:name":"Rocking K Custom Renovations",
    "wof:placetype":"venue"
},
  "geometry": {"coordinates":[-113.921323,45.183359],"type":"Point"}
}