{
  "type": "Feature",
  "properties": {
    "iso:country":"US",
    "sg:address":"1190 N 6th E",
    "sg:city":"Mountain Home",
    "sg:classifiers":[
        {
            "category":"Organizations",
            "subcategory":"Religious Organization",
            "type":"Services"
        }
    ],
    "sg:phone":"+1 208 587 4127",
    "sg:postcode":"83647",
    "sg:province":"ID",
    "sg:tags":[
        "church"
    ],
    "wof:name":"Faith Lutheran School",
    "wof:placetype":"venue"
},
  "geometry": {"coordinates":[-115.692539,43.141847],"type":"Point"}
}