{
  "type": "Feature",
  "properties": {
    "iso:country":"US",
    "sg:address":"1307 S Maple Grove Rd",
    "sg:city":"Boise",
    "sg:classifiers":[
        {
            "category":"Building & Trades",
            "subcategory":"Landscaping Services",
            "type":"Services"
        }
    ],
    "sg:phone":"+1 208 376 6599",
    "sg:postcode":"83709",
    "sg:province":"ID",
    "sg:tags":[
        "landscape",
        "contractor"
    ],
    "wof:name":"Avalon Landscapes Inc",
    "wof:placetype":"venue"
},
  "geometry": {"coordinates":[-116.294196,43.592624],"type":"Point"}
}