{
  "type": "Feature",
  "properties": {
    "addr:full":"8515 W Canary Ct Boise ID 83714",
    "addr:housenumber":"8515",
    "addr:postcode":"83714",
    "addr:street":"W Canary Ct",
    "iso:country":"US",
    "sg:address":"8515 W Canary Ct",
    "sg:city":"Boise",
    "sg:classifiers":[
        {
            "category":"Real Estate",
            "subcategory":"Real Estate Agent",
            "type":"Services"
        }
    ],
    "sg:phone":"+1 208 376 1522",
    "sg:postcode":"83714",
    "sg:province":"ID",
    "sg:tags":[
        "inspection"
    ],
    "wof:name":"Ameri Spec Home Inspection Svc",
    "wof:placetype":"venue"
},
  "geometry": {"coordinates":[-116.28734799999999,43.661159],"type":"Point"}
}