{
  "type": "Feature",
  "properties": {
    "addr:full":"1084 Camelot Dr Boise ID 83704",
    "addr:housenumber":"1084",
    "addr:postcode":"83704",
    "addr:street":"Camelot Dr",
    "iso:country":"US",
    "sg:address":"1084 Camelot Dr",
    "sg:city":"Boise",
    "sg:classifiers":[
        {
            "category":"Home & Garden",
            "subcategory":"Home Furnishings",
            "type":"Retail Goods"
        }
    ],
    "sg:phone":"+1 208 321 1034",
    "sg:postcode":"83704",
    "sg:province":"ID",
    "wof:name":"Evas Customs Draperies",
    "wof:placetype":"venue"
},
  "geometry": {"coordinates":[-116.270557,43.613741],"type":"Point"}
}