{
  "type": "Feature",
  "properties": {
    "iso:country":"US",
    "sg:address":"10950 Liberty Rd",
    "sg:city":"Sweet",
    "sg:classifiers":[
        {
            "category":"Personal",
            "type":"Services"
        }
    ],
    "sg:phone":"+1 208 584 3626",
    "sg:postcode":"83670",
    "sg:province":"ID",
    "sg:tags":[
        "therapist",
        "massage"
    ],
    "wof:name":"Madsen Alternative Therapeutic",
    "wof:placetype":"venue"
},
  "geometry": {"coordinates":[-116.300258,44.018802],"type":"Point"}
}