{
  "type": "Feature",
  "properties": {
    "addr:full":"1819 Albion Ave Burley ID 83318",
    "addr:housenumber":"1819",
    "addr:postcode":"83318",
    "addr:street":"Albion Ave",
    "iso:country":"US",
    "sg:address":"1819 Albion Ave",
    "sg:city":"Burley",
    "sg:classifiers":[
        {
            "category":"Organizations",
            "subcategory":"Religious Organization",
            "type":"Services"
        }
    ],
    "sg:phone":"+1 208 678 8119",
    "sg:postcode":"83318",
    "sg:province":"ID",
    "wof:name":"Burley Foursquare Church",
    "wof:placetype":"venue"
},
  "geometry": {"coordinates":[-113.791827,42.530079],"type":"Point"}
}