{
  "type": "Feature",
  "properties": {
    "iso:country":"US",
    "sg:address":"830 W Bannock St",
    "sg:city":"Boise",
    "sg:classifiers":[
        {
            "category":"Home & Garden",
            "subcategory":"Home Furnishings",
            "type":"Retail Goods"
        }
    ],
    "sg:phone":"+1 208 336 1443",
    "sg:postcode":"83702",
    "sg:province":"ID",
    "sg:tags":[
        "lamp",
        "shades"
    ],
    "wof:name":"So Many Shades",
    "wof:placetype":"venue"
},
  "geometry": {"coordinates":[-116.202884,43.617632],"type":"Point"}
}