{
  "type": "Feature",
  "properties": {
    "addr:full":"2922 Cleveland Blvd Caldwell ID 83605",
    "addr:housenumber":"2922",
    "addr:postcode":"83605",
    "addr:street":"Cleveland Blvd",
    "iso:country":"US",
    "sg:address":"2922 Cleveland Blvd",
    "sg:city":"Caldwell",
    "sg:classifiers":[
        {
            "category":"Social Services",
            "type":"Services"
        }
    ],
    "sg:phone":"+1 208 455 2772",
    "sg:postcode":"83605",
    "sg:province":"ID",
    "sg:tags":[
        "stress",
        "management"
    ],
    "wof:name":"Soothing Touch Massage Therapy",
    "wof:placetype":"venue"
},
  "geometry": {"coordinates":[-116.667275,43.648801],"type":"Point"}
}