{
  "type": "Feature",
  "properties": {
    "iso:country":"US",
    "sg:address":"1680 Shaw Mountain Rd",
    "sg:city":"Boise",
    "sg:classifiers":[
        {
            "category":"Travel",
            "subcategory":"Travel Agent",
            "type":"Entertainment"
        }
    ],
    "sg:phone":"+1 208 385 9510",
    "sg:postcode":"83712",
    "sg:province":"ID",
    "sg:tags":[
        "destination",
        "management"
    ],
    "sg:website":"www.themeetingnetworkinc.com",
    "wof:name":"Meeting Network",
    "wof:placetype":"venue"
},
  "geometry": {"coordinates":[-116.16973,43.617346],"type":"Point"}
}