{
  "type": "Feature",
  "properties": {
    "iso:country":"US",
    "sg:address":"1757 E 4500 N",
    "sg:city":"Buhl",
    "sg:phone":"+1 208 543 8047",
    "sg:postcode":"83316",
    "sg:province":"ID",
    "sg:tags":[
        "farm",
        "corn",
        "grain",
        "cash"
    ],
    "wof:name":"Riley Maxwell",
    "wof:placetype":"venue"
},
  "geometry": {"coordinates":[-114.702882,42.651416],"type":"Point"}
}