{
  "type": "Feature",
  "properties": {
    "iso:country":"US",
    "sg:address":"1625 Bench Rd",
    "sg:city":"Pocatello",
    "sg:classifiers":[
        {
            "category":"Professional",
            "subcategory":"Management & Consulting",
            "type":"Services"
        }
    ],
    "sg:phone":"+1 208 637 2688",
    "sg:postcode":"83201",
    "sg:province":"ID",
    "wof:name":"Worth Marketing LLC",
    "wof:placetype":"venue"
},
  "geometry": {"coordinates":[-112.42829500000001,42.903952],"type":"Point"}
}