{
  "type": "Feature",
  "properties": {
    "iso:country":"US",
    "sg:address":"8995 N Finucane Dr",
    "sg:city":"Hayden",
    "sg:classifiers":[
        {
            "category":"Building & Trades",
            "subcategory":"Plumbing",
            "type":"Services"
        }
    ],
    "sg:phone":"+1 208 762 2627",
    "sg:postcode":"83835",
    "sg:province":"ID",
    "sg:tags":[
        "business",
        "contractor"
    ],
    "wof:name":"Troxel Engineering",
    "wof:placetype":"venue"
},
  "geometry": {"coordinates":[-116.773899,47.753351],"type":"Point"}
}