{
  "type": "Feature",
  "properties": {
    "iso:country":"US",
    "sg:address":"1526 N Washington Ave",
    "sg:city":"Emmett",
    "sg:classifiers":[
        {
            "category":"Retail",
            "subcategory":"Veterinary Services",
            "type":"Services"
        }
    ],
    "sg:phone":"+1 208 365 6008",
    "sg:postcode":"83617",
    "sg:province":"ID",
    "sg:tags":[
        "veterinarian"
    ],
    "wof:name":"Gem Veterinary Clinic",
    "wof:placetype":"venue"
},
  "geometry": {"coordinates":[-116.502377,43.892877],"type":"Point"}
}