{
  "type": "Feature",
  "properties": {
    "iso:country":"US",
    "sg:address":"9124 N Hess St",
    "sg:city":"Hayden",
    "sg:classifiers":[
        {
            "category":"Autos & Motor Vehicles",
            "subcategory":"Auto Supplies",
            "type":"Retail Goods"
        }
    ],
    "sg:phone":"+1 208 762 4657",
    "sg:postcode":"83835",
    "sg:province":"ID",
    "sg:tags":[
        "automobile",
        "parts"
    ],
    "wof:name":"Schuck's Auto Supply",
    "wof:placetype":"venue"
},
  "geometry": {"coordinates":[-116.794145,47.752034],"type":"Point"}
}