{
  "type": "Feature",
  "properties": {
    "iso:country":"US",
    "sg:address":"383 F St",
    "sg:city":"Idaho Falls",
    "sg:classifiers":[
        {
            "category":"Professional",
            "subcategory":"Printing & Photocopies",
            "type":"Services"
        }
    ],
    "sg:phone":"+1 208 523 8831",
    "sg:postcode":"83402",
    "sg:province":"ID",
    "sg:tags":[
        "duplicating",
        "copying"
    ],
    "wof:name":"Zip Print",
    "wof:placetype":"venue"
},
  "geometry": {"coordinates":[-112.036815,43.496534],"type":"Point"}
}