{
  "type": "Feature",
  "properties": {
    "iso:country":"US",
    "sg:address":"718 Main St",
    "sg:city":"Caldwell",
    "sg:classifiers":[
        {
            "category":"Freight",
            "type":"Transportation"
        }
    ],
    "sg:phone":"+1 208 455 0064",
    "sg:postcode":"83605",
    "sg:province":"ID",
    "sg:tags":[
        "broker",
        "trucking"
    ],
    "wof:name":"Zamora Freight Management",
    "wof:placetype":"venue"
},
  "geometry": {"coordinates":[-116.68814399999999,43.666847],"type":"Point"}
}