{
  "type": "Feature",
  "properties": {
    "iso:country":"US",
    "sg:address":"338 Meadowlark Ln",
    "sg:city":"Moscow",
    "sg:classifiers":[
        {
            "category":"Retail",
            "subcategory":"Repair Shop",
            "type":"Services"
        }
    ],
    "sg:phone":"+1 208 882 1754",
    "sg:postcode":"83843",
    "sg:province":"ID",
    "sg:tags":[
        "taxidermist"
    ],
    "wof:name":"Stewart's Taxidermy",
    "wof:placetype":"venue"
},
  "geometry": {"coordinates":[-116.970144,46.736682],"type":"Point"}
}