{
  "type": "Feature",
  "properties": {
    "iso:country":"US",
    "sg:address":"2482 State Hwy 25",
    "sg:city":"Hazelton",
    "sg:classifiers":[
        {
            "category":"Farming",
            "subcategory":"Farm",
            "type":"Manufacturing & Wholesale Goods"
        }
    ],
    "sg:phone":"+1 208 829 4235",
    "sg:postcode":"83335",
    "sg:province":"ID",
    "sg:tags":[
        "crop",
        "general"
    ],
    "wof:name":"Shawver Farms Inc",
    "wof:placetype":"venue"
},
  "geometry": {"coordinates":[-114.162775,42.598212],"type":"Point"}
}