{
  "type": "Feature",
  "properties": {
    "addr:full":"2948 N Burley Way Meridian ID 83646",
    "addr:housenumber":"2948",
    "addr:postcode":"83646",
    "addr:street":"N Burley Way",
    "iso:country":"US",
    "sg:address":"2948 N Burley Way",
    "sg:city":"Meridian",
    "sg:classifiers":[
        {
            "category":"Building & Trades",
            "subcategory":"Electrical",
            "type":"Services"
        }
    ],
    "sg:phone":"+1 208 884 8765",
    "sg:postcode":"83646",
    "sg:province":"ID",
    "sg:tags":[
        "electric",
        "contractor"
    ],
    "wof:name":"Citylight Electric LLC",
    "wof:placetype":"venue"
},
  "geometry": {"coordinates":[-116.433661,43.631215],"type":"Point"}
}