{
  "type": "Feature",
  "properties": {
    "iso:country":"US",
    "sg:address":"4020 N 2600 E",
    "sg:city":"Filer",
    "sg:classifiers":[
        {
            "category":"Building & Trades",
            "subcategory":"Construction",
            "type":"Services"
        }
    ],
    "sg:phone":"+1 208 734 8298",
    "sg:postcode":"83328",
    "sg:province":"ID",
    "sg:tags":[
        "excavating",
        "contractor"
    ],
    "wof:name":"Nix Excavating",
    "wof:placetype":"venue"
},
  "geometry": {"coordinates":[-114.535436,42.584104],"type":"Point"}
}