{
  "type": "Feature",
  "properties": {
    "iso:country":"US",
    "sg:address":"1304 Idaho St",
    "sg:city":"Lewiston",
    "sg:classifiers":[
        {
            "category":"Professional",
            "subcategory":"Lawyer & Legal Services",
            "type":"Services"
        }
    ],
    "sg:phone":"+1 208 743 3591",
    "sg:postcode":"83501",
    "sg:province":"ID",
    "sg:tags":[
        "attorney"
    ],
    "wof:name":"Jones Brower & Callery",
    "wof:placetype":"venue"
},
  "geometry": {"coordinates":[-117.015377,46.416182],"type":"Point"}
}