{
  "type": "Feature",
  "properties": {
    "addr:full":"4204 Kilarney Dr Boise ID 83704",
    "addr:housenumber":"4204",
    "addr:postcode":"83704",
    "addr:street":"Kilarney Dr",
    "iso:country":"US",
    "sg:address":"4204 Kilarney Dr",
    "sg:city":"Boise",
    "sg:classifiers":[
        {
            "category":"Professional",
            "subcategory":"Business Services",
            "type":"Services"
        }
    ],
    "sg:phone":"+1 208 322 4149",
    "sg:postcode":"83704",
    "sg:province":"ID",
    "wof:name":"Wahl To Wahl Inc",
    "wof:placetype":"venue"
},
  "geometry": {"coordinates":[-116.293142,43.643188],"type":"Point"}
}