{
  "type": "Feature",
  "properties": {
    "addr:full":"236 Washington St S Twin Falls ID 83301",
    "addr:housenumber":"236",
    "addr:postcode":"83301",
    "addr:street":"Washington St S",
    "iso:country":"US",
    "sg:address":"236 Washington St S",
    "sg:city":"Twin Falls",
    "sg:classifiers":[
        {
            "category":"Manufacturing",
            "subcategory":"Food",
            "type":"Manufacturing & Wholesale Goods"
        }
    ],
    "sg:phone":"+1 208 733 3226",
    "sg:postcode":"83301",
    "sg:province":"ID",
    "sg:tags":[
        "cheese",
        "processor"
    ],
    "wof:name":"Glanbia Foods Inc",
    "wof:placetype":"venue"
},
  "geometry": {"coordinates":[-114.47969000000001,42.546951],"type":"Point"}
}