{
  "type": "Feature",
  "properties": {
    "iso:country":"US",
    "sg:address":"1215 N 1st Ave",
    "sg:city":"Caldwell",
    "sg:classifiers":[
        {
            "category":"Real Estate",
            "subcategory":"Real Estate Operator",
            "type":"Services"
        }
    ],
    "sg:phone":"+1 208 453 1206",
    "sg:postcode":"83605",
    "sg:province":"ID",
    "sg:tags":[
        "apartment"
    ],
    "wof:name":"Columbia Gardens Apartments",
    "wof:placetype":"venue"
},
  "geometry": {"coordinates":[-116.682761,43.680452],"type":"Point"}
}