{
  "type": "Feature",
  "properties": {
    "iso:country":"US",
    "sg:address":"701 E Front Ave",
    "sg:city":"Coeur D Alene",
    "sg:classifiers":[
        {
            "category":"Professional",
            "type":"Services"
        }
    ],
    "sg:phone":"+1 208 664 6241",
    "sg:postcode":"83814",
    "sg:province":"ID",
    "wof:name":"Mikabio Inc",
    "wof:placetype":"venue"
},
  "geometry": {"coordinates":[-116.776853,47.67256],"type":"Point"}
}