{
  "type": "Feature",
  "properties": {
    "iso:country":"US",
    "sg:address":"4828 Emerald St",
    "sg:city":"Boise",
    "sg:classifiers":[
        {
            "category":"Utilities",
            "subcategory":"Sewage",
            "type":"Services"
        }
    ],
    "sg:phone":"+1 208 345 5363",
    "sg:postcode":"83706",
    "sg:province":"ID",
    "sg:tags":[
        "disposal",
        "system"
    ],
    "wof:name":"Bench Sewer District",
    "wof:placetype":"venue"
},
  "geometry": {"coordinates":[-116.241991,43.611684],"type":"Point"}
}