{
  "type": "Feature",
  "properties": {
    "addr:full":"126 S Cole Rd Boise ID 83709",
    "addr:housenumber":"126",
    "addr:postcode":"83709",
    "addr:street":"S Cole Rd",
    "iso:country":"US",
    "sg:address":"126 S Cole Rd",
    "sg:city":"Boise",
    "sg:classifiers":[
        {
            "category":"Insurance",
            "subcategory":"Insurance Agent",
            "type":"Services"
        }
    ],
    "sg:phone":"+1 208 376 6100",
    "sg:postcode":"83709",
    "sg:province":"ID",
    "wof:name":"Phil Price Insurance",
    "wof:placetype":"venue"
},
  "geometry": {"coordinates":[-116.274125,43.604168],"type":"Point"}
}