{
  "type": "Feature",
  "properties": {
    "addr:full":"248 Alturas St Idaho Falls ID 83401",
    "addr:housenumber":"248",
    "addr:postcode":"83401",
    "addr:street":"Alturas St",
    "iso:country":"US",
    "sg:address":"248 Alturas St",
    "sg:city":"Idaho Falls",
    "sg:classifiers":[
        {
            "category":"Professional",
            "subcategory":"Accounting & Tax Preparation",
            "type":"Services"
        }
    ],
    "sg:phone":"+1 208 522 1116",
    "sg:postcode":"83401",
    "sg:province":"ID",
    "sg:tags":[
        "return"
    ],
    "wof:name":"Iriss Tax Service",
    "wof:placetype":"venue"
},
  "geometry": {"coordinates":[-111.996697,43.495223],"type":"Point"}
}