{
  "type": "Feature",
  "properties": {
    "iso:country":"US",
    "sg:address":"5103 Sunnyridge Rd",
    "sg:city":"Nampa",
    "sg:classifiers":[
        {
            "category":"Building & Trades",
            "subcategory":"Landscaping Services",
            "type":"Services"
        }
    ],
    "sg:phone":"+1 208 466 5963",
    "sg:postcode":"83686",
    "sg:province":"ID",
    "sg:tags":[
        "landscape",
        "contractor"
    ],
    "wof:name":"Ray Gamel Landscape Care",
    "wof:placetype":"venue"
},
  "geometry": {"coordinates":[-116.5629,43.52108],"type":"Point"}
}