{
  "type": "Feature",
  "properties": {
    "iso:country":"US",
    "sg:address":"1131 Cameron Ave",
    "sg:city":"Idaho Falls",
    "sg:classifiers":[
        {
            "category":"Professional",
            "subcategory":"Management & Consulting",
            "type":"Services"
        }
    ],
    "sg:phone":"+1 208 522 7459",
    "sg:postcode":"83402",
    "sg:province":"ID",
    "wof:name":"Homesite Management Servi",
    "wof:placetype":"venue"
},
  "geometry": {"coordinates":[-112.066606,43.508584],"type":"Point"}
}