{
  "type": "Feature",
  "properties": {
    "iso:country":"US",
    "sg:address":"331 N 8th St",
    "sg:city":"Montpelier",
    "sg:classifiers":[
        {
            "category":"Retail",
            "subcategory":"Laundry & Dry Cleaning",
            "type":"Services"
        }
    ],
    "sg:phone":"+1 208 847 3369",
    "sg:postcode":"83254",
    "sg:province":"ID",
    "sg:tags":[
        "cleaners",
        "rug",
        "carpet"
    ],
    "wof:name":"EZ2 Plez Carpet Sales & Svc",
    "wof:placetype":"venue"
},
  "geometry": {"coordinates":[-111.306912,42.322549],"type":"Point"}
}