{
  "type": "Feature",
  "properties": {
    "addr:full":"3122 Pole Line Rd Pocatello ID 83201",
    "addr:housenumber":"3122",
    "addr:postcode":"83201",
    "addr:street":"Pole Line Rd",
    "iso:country":"US",
    "sg:address":"3122 Pole Line Rd",
    "sg:city":"Pocatello",
    "sg:classifiers":[
        {
            "category":"Restaurant",
            "type":"Food & Drink"
        }
    ],
    "sg:phone":"+1 208 237 2158",
    "sg:postcode":"83201",
    "sg:province":"ID",
    "wof:name":"Jeri's Jumbo's Cafe",
    "wof:placetype":"venue"
},
  "geometry": {"coordinates":[-112.46610699999999,42.891041],"type":"Point"}
}