{
  "type": "Feature",
  "properties": {
    "addr:full":"855 W Idaho St Boise ID 83702",
    "addr:housenumber":"855",
    "addr:postcode":"83702",
    "addr:street":"W Idaho St",
    "iso:country":"US",
    "sg:address":"855 W Idaho St",
    "sg:city":"Boise",
    "sg:classifiers":[
        {
            "category":"Parking",
            "type":"Transportation"
        }
    ],
    "sg:phone":"+1 208 336 1068",
    "sg:postcode":"83702",
    "sg:province":"ID",
    "sg:tags":[
        "garage"
    ],
    "wof:name":"Republic Parking Northwest",
    "wof:placetype":"venue"
},
  "geometry": {"coordinates":[-116.203496,43.616599],"type":"Point"}
}