{
  "type": "Feature",
  "properties": {
    "iso:country":"US",
    "sg:address":"36 N 2nd W",
    "sg:city":"Rexburg",
    "sg:classifiers":[
        {
            "category":"Social Services",
            "type":"Services"
        }
    ],
    "sg:phone":"+1 208 359 0519",
    "sg:postcode":"83440",
    "sg:province":"ID",
    "sg:tags":[
        "counselor",
        "marriage",
        "family"
    ],
    "wof:name":"Upper Valley Resource & Cnslng",
    "wof:placetype":"venue"
},
  "geometry": {"coordinates":[-111.78948800000001,43.82677],"type":"Point"}
}