{
  "type": "Feature",
  "properties": {
    "addr:full":"280 W Prairie Ave Coeur D Alene ID 83815",
    "addr:housenumber":"280",
    "addr:postcode":"83815",
    "addr:street":"W Prairie Ave",
    "iso:country":"US",
    "sg:address":"280 W Prairie Ave",
    "sg:city":"Coeur D Alene",
    "sg:classifiers":[
        {
            "category":"Professional",
            "subcategory":"Engineering",
            "type":"Services"
        }
    ],
    "sg:phone":"+1 208 772 2428",
    "sg:postcode":"83815",
    "sg:province":"ID",
    "sg:tags":[
        "engineer"
    ],
    "wof:name":"Strata Inc",
    "wof:placetype":"venue"
},
  "geometry": {"coordinates":[-116.79050599999999,47.744394],"type":"Point"}
}