{
  "type": "Feature",
  "properties": {
    "iso:country":"US",
    "sg:address":"4141 Sawtelle Peak Rd",
    "sg:city":"Island Park",
    "sg:classifiers":[
        {
            "category":"Restaurant",
            "type":"Food & Drink"
        }
    ],
    "sg:menulink":"http://www.allmenus.com/id/island-park/120387-subway/menu/",
    "sg:phone":"+1 208 558 9884",
    "sg:postcode":"83429",
    "sg:province":"ID",
    "sg:tags":[
        "american",
        "sandwich"
    ],
    "wof:name":"Subway",
    "wof:placetype":"venue"
},
  "geometry": {"coordinates":[-111.364604,44.536364],"type":"Point"}
}