{
  "type": "Feature",
  "properties": {
    "addr:full":"1267 W Cardinal Ave Hayden ID 83835",
    "addr:housenumber":"1267",
    "addr:postcode":"83835",
    "addr:street":"W Cardinal Ave",
    "iso:country":"US",
    "sg:address":"1267 W Cardinal Ave",
    "sg:city":"Hayden",
    "sg:classifiers":[
        {
            "category":"Retail",
            "subcategory":"Repair Shop",
            "type":"Services"
        }
    ],
    "sg:phone":"+1 208 762 0125",
    "sg:postcode":"83835",
    "sg:province":"ID",
    "wof:name":"Victoria Contreras",
    "wof:placetype":"venue"
},
  "geometry": {"coordinates":[-116.80463399999999,47.746848],"type":"Point"}
}