{
  "type": "Feature",
  "properties": {
    "addr:full":"1314 12th Ave S Nampa ID 83651",
    "addr:housenumber":"1314",
    "addr:postcode":"83651",
    "addr:street":"12Th Ave S",
    "iso:country":"US",
    "sg:address":"1314 12th Ave S",
    "sg:city":"Nampa",
    "sg:classifiers":[
        {
            "category":"Shopping",
            "subcategory":"Clothing, Apparel, & Fashions",
            "type":"Retail Goods"
        }
    ],
    "sg:phone":"+1 208 442 8426",
    "sg:postcode":"83651",
    "sg:province":"ID",
    "sg:tags":[
        "swimwear",
        "accessory"
    ],
    "wof:name":"H2o With Kick",
    "wof:placetype":"venue"
},
  "geometry": {"coordinates":[-116.572277,43.568951],"type":"Point"}
}