{
  "type": "Feature",
  "properties": {
    "iso:country":"US",
    "sg:address":"3709 N Maple Grove Rd",
    "sg:city":"Boise",
    "sg:classifiers":[
        {
            "category":"Food & Beverages",
            "subcategory":"Groceries & Convenience Stores",
            "type":"Retail Goods"
        }
    ],
    "sg:phone":"+1 208 378 7025",
    "sg:postcode":"83704",
    "sg:province":"ID",
    "sg:tags":[
        "product",
        "mfg"
    ],
    "wof:name":"Airragance Finer Finishes",
    "wof:placetype":"venue"
},
  "geometry": {"coordinates":[-116.294343,43.638245],"type":"Point"}
}