{
  "type": "Feature",
  "properties": {
    "iso:country":"US",
    "sg:address":"214 E Hwy 24",
    "sg:city":"Rupert",
    "sg:classifiers":[
        {
            "category":"Wholesale",
            "subcategory":"Electrical",
            "type":"Manufacturing & Wholesale Goods"
        }
    ],
    "sg:phone":"+1 208 436 4658",
    "sg:postcode":"83350",
    "sg:province":"ID",
    "sg:tags":[
        "electric",
        "motor"
    ],
    "wof:name":"Electric Motor Rewind Inc",
    "wof:placetype":"venue"
},
  "geometry": {"coordinates":[-113.674233,42.613992],"type":"Point"}
}