{
  "type": "Feature",
  "properties": {
    "addr:full":"1317 Allumbaugh St Boise ID 83704",
    "addr:housenumber":"1317",
    "addr:postcode":"83704",
    "addr:street":"Allumbaugh St",
    "iso:country":"US",
    "sg:address":"1317 Allumbaugh St",
    "sg:city":"Boise",
    "sg:classifiers":[
        {
            "category":"Building & Trades",
            "subcategory":"Construction",
            "type":"Services"
        }
    ],
    "sg:phone":"+1 208 377 3215",
    "sg:postcode":"83704",
    "sg:province":"ID",
    "sg:tags":[
        "contractor"
    ],
    "wof:name":"Gem State Sign Installation",
    "wof:placetype":"venue"
},
  "geometry": {"coordinates":[-116.266273,43.616942],"type":"Point"}
}