{
  "type": "Feature",
  "properties": {
    "iso:country":"US",
    "sg:address":"6524 Grandview Dr",
    "sg:city":"Boise",
    "sg:classifiers":[
        {
            "category":"Professional",
            "subcategory":"Business Services",
            "type":"Services"
        }
    ],
    "sg:phone":"+1 208 378 1758",
    "sg:postcode":"83709",
    "sg:province":"ID",
    "wof:name":"Robinson Rita",
    "wof:placetype":"venue"
},
  "geometry": {"coordinates":[-116.261931,43.585371],"type":"Point"}
}