{
  "type": "Feature",
  "properties": {
    "addr:full":"400 N 200 W Malad City ID 83252",
    "addr:housenumber":"400",
    "addr:postcode":"83252",
    "addr:street":"N 200 W Malad",
    "iso:country":"US",
    "sg:address":"400 N 200 W",
    "sg:city":"Malad City",
    "sg:classifiers":[
        {
            "category":"Organizations",
            "subcategory":"Religious Organization",
            "type":"Services"
        }
    ],
    "sg:phone":"+1 208 766 4082",
    "sg:postcode":"83252",
    "sg:province":"ID",
    "sg:tags":[
        "church"
    ],
    "wof:name":"Church Of Jesus Christ Of Lds",
    "wof:placetype":"venue"
},
  "geometry": {"coordinates":[-112.250624,42.194859],"type":"Point"}
}