{
  "type": "Feature",
  "properties": {
    "addr:full":"447 W Myrtle St Boise ID 83702",
    "addr:housenumber":"447",
    "addr:postcode":"83702",
    "addr:street":"W Myrtle St",
    "iso:country":"US",
    "sg:address":"447 W Myrtle St",
    "sg:city":"Boise",
    "sg:classifiers":[
        {
            "category":"Professional",
            "subcategory":"Lawyer & Legal Services",
            "type":"Services"
        }
    ],
    "sg:phone":"+1 208 384 1627",
    "sg:postcode":"83702",
    "sg:province":"ID",
    "sg:tags":[
        "attorney"
    ],
    "sg:website":"http://www.schroederlezamiz.com",
    "wof:name":"Schroeder & Lez Miz Law Offices",
    "wof:placetype":"venue"
},
  "geometry": {"coordinates":[-116.202187,43.61042],"type":"Point"}
}