{
  "type": "Feature",
  "properties": {
    "addr:full":"6301 W Gowen Rd Boise ID 83709",
    "addr:housenumber":"6301",
    "addr:postcode":"83709",
    "addr:street":"W Gowen Rd",
    "iso:country":"US",
    "sg:address":"6301 W Gowen Rd",
    "sg:city":"Boise",
    "sg:classifiers":[
        {
            "category":"Autos & Motor Vehicles",
            "subcategory":"Automobile Sales",
            "type":"Retail Goods"
        }
    ],
    "sg:phone":"+1 208 362 5830",
    "sg:postcode":"83709",
    "sg:province":"ID",
    "sg:tags":[
        "car",
        "dealer"
    ],
    "wof:name":"Auto 4 Bid",
    "wof:placetype":"venue"
},
  "geometry": {"coordinates":[-116.25976,43.567171],"type":"Point"}
}