{
  "type": "Feature",
  "properties": {
    "addr:full":"500 Main St S Ketchum ID 83340",
    "addr:housenumber":"500",
    "addr:postcode":"83340",
    "addr:street":"Main St S",
    "iso:country":"US",
    "sg:address":"500 Main St S",
    "sg:city":"Ketchum",
    "sg:classifiers":[
        {
            "category":"Insurance",
            "subcategory":"Insurance Agent",
            "type":"Services"
        }
    ],
    "sg:phone":"+1 208 726 2471",
    "sg:postcode":"83340",
    "sg:province":"ID",
    "wof:name":"Allstate Insurance",
    "wof:placetype":"venue"
},
  "geometry": {"coordinates":[-114.361108,43.673516],"type":"Point"}
}