{
  "type": "Feature",
  "properties": {
    "addr:full":"1375 US Hwy 26 Blackfoot ID 83221",
    "addr:housenumber":"1375",
    "addr:postcode":"83221",
    "addr:street":"Us Hwy 26",
    "iso:country":"US",
    "sg:address":"1375 US Hwy 26",
    "sg:city":"Blackfoot",
    "sg:classifiers":[
        {
            "category":"Building & Trades",
            "subcategory":"Construction",
            "type":"Services"
        }
    ],
    "sg:phone":"+1 208 684 3698",
    "sg:postcode":"83221",
    "sg:province":"ID",
    "sg:tags":[
        "contractor"
    ],
    "wof:name":"D C Building Svc",
    "wof:placetype":"venue"
},
  "geometry": {"coordinates":[-112.559517,43.30959],"type":"Point"}
}