{
  "type": "Feature",
  "properties": {
    "iso:country":"US",
    "sg:address":"2386 E Poppy Hills St",
    "sg:city":"Eagle",
    "sg:classifiers":[
        {
            "category":"Professional",
            "subcategory":"Business Services",
            "type":"Services"
        }
    ],
    "sg:phone":"+1 208 939 3961",
    "sg:postcode":"83616",
    "sg:province":"ID",
    "wof:name":"A&G Storage Solutions Inc",
    "wof:placetype":"venue"
},
  "geometry": {"coordinates":[-116.325245,43.705935],"type":"Point"}
}