{
  "type": "Feature",
  "properties": {
    "iso:country":"US",
    "sg:address":"534 N Milwaukee St",
    "sg:city":"Boise",
    "sg:classifiers":[
        {
            "category":"Home & Garden",
            "subcategory":"Home Furnishings",
            "type":"Retail Goods"
        }
    ],
    "sg:phone":"+1 208 321 1116",
    "sg:postcode":"83704",
    "sg:province":"ID",
    "sg:tags":[
        "linen"
    ],
    "sg:website":"www.linensnthings.com",
    "wof:name":"Linens 'n Things",
    "wof:placetype":"venue"
},
  "geometry": {"coordinates":[-116.284683,43.609051],"type":"Point"}
}