{
  "type": "Feature",
  "properties": {
    "iso:country":"US",
    "sg:address":"4003 Professional Way",
    "sg:city":"Idaho Falls",
    "sg:classifiers":[
        {
            "category":"Building & Trades",
            "subcategory":"Electrical",
            "type":"Services"
        }
    ],
    "sg:phone":"+1 208 542 0321",
    "sg:postcode":"83402",
    "sg:province":"ID",
    "sg:tags":[
        "electrical",
        "contractor"
    ],
    "wof:name":"Skyview Electric Inc",
    "wof:placetype":"venue"
},
  "geometry": {"coordinates":[-112.058853,43.462103],"type":"Point"}
}