{
  "type": "Feature",
  "properties": {
    "addr:full":"311 N Curtis Rd Boise ID 83706",
    "addr:housenumber":"311",
    "addr:postcode":"83706",
    "addr:street":"N Curtis Rd",
    "iso:country":"US",
    "sg:address":"311 N Curtis Rd",
    "sg:city":"Boise",
    "sg:phone":"+1 208 375 7767",
    "sg:postcode":"83706",
    "sg:province":"ID",
    "sg:tags":[
        "oil",
        "gasoline"
    ],
    "sg:website":"www.bairdoil.com",
    "wof:name":"Baird Oil Co",
    "wof:placetype":"venue"
},
  "geometry": {"coordinates":[-116.25362699999999,43.606232],"type":"Point"}
}