{
  "type": "Feature",
  "properties": {
    "addr:full":"1012 Aldape Cove Boise ID 83712",
    "addr:housenumber":"1012",
    "addr:postcode":"83712",
    "addr:street":"Aldape Cove",
    "iso:country":"US",
    "sg:address":"1012 Aldape Cove",
    "sg:city":"Boise",
    "sg:classifiers":[
        {
            "category":"Travel",
            "subcategory":"Travel Agent",
            "type":"Entertainment"
        }
    ],
    "sg:phone":"+1 208 336 7639",
    "sg:postcode":"83712",
    "sg:province":"ID",
    "wof:name":"Cruiseone",
    "wof:placetype":"venue"
},
  "geometry": {"coordinates":[-116.180284,43.615185],"type":"Point"}
}