{
  "type": "Feature",
  "properties": {
    "iso:country":"US",
    "sg:address":"1107 E 1250 N",
    "sg:city":"Shelley",
    "sg:classifiers":[
        {
            "category":"Farming",
            "subcategory":"Farm",
            "type":"Manufacturing & Wholesale Goods"
        }
    ],
    "sg:phone":"+1 208 357 7016",
    "sg:postcode":"83274",
    "sg:province":"ID",
    "sg:tags":[
        "food",
        "covered",
        "crop"
    ],
    "wof:name":"Neldon Gotch Greenhouse",
    "wof:placetype":"venue"
},
  "geometry": {"coordinates":[-112.061389,43.373881],"type":"Point"}
}