{
  "type": "Feature",
  "properties": {
    "iso:country":"US",
    "sg:address":"1991 S Sub Station Rd",
    "sg:city":"Emmett",
    "sg:classifiers":[
        {
            "category":"Organizations",
            "subcategory":"Non-profit Organization",
            "type":"Services"
        }
    ],
    "sg:phone":"+1 208 365 5100",
    "sg:postcode":"83617",
    "sg:province":"ID",
    "sg:tags":[
        "social"
    ],
    "wof:name":"All Valley Agency Inc",
    "wof:placetype":"venue"
},
  "geometry": {"coordinates":[-116.47281599999999,43.86089],"type":"Point"}
}