{
  "type": "Feature",
  "properties": {
    "iso:country":"US",
    "sg:address":"1494 S 2700 W",
    "sg:city":"Aberdeen",
    "sg:classifiers":[
        {
            "category":"Government",
            "subcategory":"Office",
            "type":"Public Place"
        }
    ],
    "sg:phone":"+1 208 397 4501",
    "sg:postcode":"83210",
    "sg:province":"ID",
    "sg:tags":[
        "federal"
    ],
    "wof:name":"Natural Resources Conservation",
    "wof:placetype":"venue"
},
  "geometry": {"coordinates":[-112.82866300000001,42.991196],"type":"Point"}
}