{
  "type": "Feature",
  "properties": {
    "addr:full":"1350 Parkway Dr Blackfoot ID 83221",
    "addr:housenumber":"1350",
    "addr:postcode":"83221",
    "addr:street":"Parkway Dr",
    "iso:country":"US",
    "sg:address":"1350 Parkway Dr",
    "sg:city":"Blackfoot",
    "sg:classifiers":[
        {
            "category":"Wholesale",
            "subcategory":"Medical Equipment & Supplies",
            "type":"Manufacturing & Wholesale Goods"
        }
    ],
    "sg:phone":"+1 208 782 0456",
    "sg:postcode":"83221",
    "sg:province":"ID",
    "sg:tags":[
        "physician",
        "surgeon"
    ],
    "wof:name":"Valley Medical Shoppe",
    "wof:placetype":"venue"
},
  "geometry": {"coordinates":[-112.36058300000001,43.195424],"type":"Point"}
}