{
  "type": "Feature",
  "properties": {
    "iso:country":"US",
    "sg:address":"420 S Fanning Ave",
    "sg:city":"Idaho Falls",
    "sg:classifiers":[
        {
            "category":"Retail",
            "subcategory":"Repair Shop",
            "type":"Services"
        }
    ],
    "sg:phone":"+1 208 542 2781",
    "sg:postcode":"83401",
    "sg:province":"ID",
    "sg:tags":[
        "instrument",
        "musical"
    ],
    "wof:name":"Sound Power Music Co",
    "wof:placetype":"venue"
},
  "geometry": {"coordinates":[-112.016457,43.494027],"type":"Point"}
}