{
  "type": "Feature",
  "properties": {
    "iso:country":"US",
    "sg:address":"1735 Main St",
    "sg:city":"Gooding",
    "sg:classifiers":[
        {
            "category":"Freight",
            "type":"Transportation"
        }
    ],
    "sg:phone":"+1 208 934 4451",
    "sg:postcode":"83330",
    "sg:province":"ID",
    "sg:tags":[
        "broker",
        "trucking"
    ],
    "sg:website":"www.ddtransportation.com",
    "wof:name":"D & D Transportation Svc",
    "wof:placetype":"venue"
},
  "geometry": {"coordinates":[-114.712907,42.92815],"type":"Point"}
}