{
  "type": "Feature",
  "properties": {
    "iso:country":"US",
    "sg:address":"450 W 15th St",
    "sg:city":"Idaho Falls",
    "sg:classifiers":[
        {
            "category":"Professional",
            "subcategory":"Art Services",
            "type":"Services"
        }
    ],
    "sg:phone":"+1 208 525 1354",
    "sg:postcode":"83402",
    "sg:province":"ID",
    "sg:tags":[
        "photographer"
    ],
    "wof:name":"Artisan Photograpy Studio",
    "wof:placetype":"venue"
},
  "geometry": {"coordinates":[-112.041547,43.484606],"type":"Point"}
}