{
  "type": "Feature",
  "properties": {
    "addr:full":"8665 Emerald St Boise ID 83704",
    "addr:housenumber":"8665",
    "addr:postcode":"83704",
    "addr:street":"Emerald St",
    "iso:country":"US",
    "sg:address":"8665 Emerald St",
    "sg:city":"Boise",
    "sg:classifiers":[
        {
            "category":"Real Estate",
            "subcategory":"Real Estate Services",
            "type":"Services"
        }
    ],
    "sg:phone":"+1 208 377 3190",
    "sg:postcode":"83704",
    "sg:province":"ID",
    "sg:tags":[
        "company",
        "title"
    ],
    "wof:name":"Land America Transnation Title",
    "wof:placetype":"venue"
},
  "geometry": {"coordinates":[-116.289114,43.611221],"type":"Point"}
}