{
  "type": "Feature",
  "properties": {
    "iso:country":"US",
    "sg:address":"905 20th St S",
    "sg:city":"Nampa",
    "sg:classifiers":[
        {
            "category":"Shopping",
            "type":"Retail Goods"
        },
        {
            "category":"Retail",
            "subcategory":"Portrait Studio",
            "type":"Services"
        }
    ],
    "sg:phone":"+1 208 466 0512",
    "sg:postcode":"83686",
    "sg:province":"ID",
    "sg:tags":[
        "photo",
        "wedding",
        "supply"
    ],
    "wof:name":"Gerry Slabaugh Photography",
    "wof:placetype":"venue"
},
  "geometry": {"coordinates":[-116.546493,43.559919],"type":"Point"}
}