{
  "type": "Feature",
  "properties": {
    "iso:country":"US",
    "sg:address":"1120 W Finch Dr",
    "sg:city":"Nampa",
    "sg:classifiers":[
        {
            "category":"Building & Trades",
            "subcategory":"Cleaning & Sanitation",
            "type":"Services"
        }
    ],
    "sg:phone":"+1 208 467 0931",
    "sg:postcode":"83651",
    "sg:province":"ID",
    "sg:tags":[
        "ventilating",
        "system"
    ],
    "wof:name":"Breathe Better",
    "wof:placetype":"venue"
},
  "geometry": {"coordinates":[-116.59392800000001,43.602689],"type":"Point"}
}