{
  "type": "Feature",
  "properties": {
    "iso:country":"US",
    "sg:address":"215 S 1st Ave E",
    "sg:city":"Middleton",
    "sg:classifiers":[
        {
            "category":"Professional",
            "subcategory":"Accounting & Tax Preparation",
            "type":"Services"
        }
    ],
    "sg:phone":"+1 208 585 3661",
    "sg:postcode":"83644",
    "sg:province":"ID",
    "sg:tags":[
        "bookkeeping",
        "general"
    ],
    "wof:name":"Middleton Bookkeeping & Tax",
    "wof:placetype":"venue"
},
  "geometry": {"coordinates":[-116.621674,43.706004],"type":"Point"}
}