{
  "type": "Feature",
  "properties": {
    "iso:country":"US",
    "sg:address":"721 Hannibal St",
    "sg:city":"Caldwell",
    "sg:classifiers":[
        {
            "category":"Autos & Motor Vehicles",
            "subcategory":"Automobile Sales",
            "type":"Retail Goods"
        }
    ],
    "sg:phone":"+1 208 453 2222",
    "sg:postcode":"83605",
    "sg:province":"ID",
    "sg:tags":[
        "new",
        "used",
        "car"
    ],
    "wof:name":"Discount Motor Sports",
    "wof:placetype":"venue"
},
  "geometry": {"coordinates":[-116.680015,43.672598],"type":"Point"}
}