{
  "type": "Feature",
  "properties": {
    "addr:full":"321 2nd Ave E Twin Falls ID 83301",
    "addr:housenumber":"321",
    "addr:postcode":"83301",
    "addr:street":"2Nd Ave E",
    "iso:country":"US",
    "sg:address":"321 2nd Ave E",
    "sg:city":"Twin Falls",
    "sg:classifiers":[
        {
            "category":"Government",
            "subcategory":"Office",
            "type":"Public Place"
        }
    ],
    "sg:phone":"+1 208 735 7267",
    "sg:postcode":"83301",
    "sg:province":"ID",
    "sg:tags":[
        "city",
        "planning",
        "dev"
    ],
    "wof:name":"Twin Falls Planning Zoning",
    "wof:placetype":"venue"
},
  "geometry": {"coordinates":[-114.466436,42.554629],"type":"Point"}
}