{
  "type": "Feature",
  "properties": {
    "iso:country":"US",
    "sg:address":"145 7th Ave E",
    "sg:city":"Gooding",
    "sg:classifiers":[
        {
            "category":"Government",
            "subcategory":"Office",
            "type":"Public Place"
        }
    ],
    "sg:phone":"+1 208 934 5668",
    "sg:postcode":"83330",
    "sg:province":"ID",
    "sg:tags":[
        "county",
        "govt",
        "program"
    ],
    "wof:name":"Gooding County Motor Vehicles",
    "wof:placetype":"venue"
},
  "geometry": {"coordinates":[-114.712583,42.938453],"type":"Point"}
}