{
  "type": "Feature",
  "properties": {
    "iso:country":"US",
    "sg:address":"311 N 10th St",
    "sg:city":"Coeur D Alene",
    "sg:classifiers":[
        {
            "category":"Education",
            "subcategory":"School",
            "type":"Public Place"
        }
    ],
    "sg:phone":"+1 208 664 8241",
    "sg:postcode":"83814",
    "sg:province":"ID",
    "wof:name":"Coeur D'Alene School Dist 271",
    "wof:placetype":"venue"
},
  "geometry": {"coordinates":[-116.772409,47.675302],"type":"Point"}
}