{
  "type": "Feature",
  "properties": {
    "addr:full":"2315 Mountain View Dr Boise ID 83706",
    "addr:housenumber":"2315",
    "addr:postcode":"83706",
    "addr:street":"Mountain View Dr",
    "iso:country":"US",
    "sg:address":"2315 Mountain View Dr",
    "sg:city":"Boise",
    "sg:classifiers":[
        {
            "category":"Professional",
            "subcategory":"Art Services",
            "type":"Services"
        }
    ],
    "sg:phone":"+1 208 375 2269",
    "sg:postcode":"83706",
    "sg:province":"ID",
    "sg:tags":[
        "photographer"
    ],
    "sg:website":"www.pixellight.com",
    "wof:name":"Pixel Light Digital Imaging",
    "wof:placetype":"venue"
},
  "geometry": {"coordinates":[-116.251437,43.626523],"type":"Point"}
}