{
  "type": "Feature",
  "properties": {
    "addr:full":"829 D St Lewiston ID 83501",
    "addr:housenumber":"829",
    "addr:postcode":"83501",
    "addr:street":"D St",
    "iso:country":"US",
    "sg:address":"829 D St",
    "sg:city":"Lewiston",
    "sg:classifiers":[
        {
            "category":"Shopping",
            "subcategory":"Bicycles & Sporting Goods",
            "type":"Retail Goods"
        }
    ],
    "sg:phone":"+1 208 743 6567",
    "sg:postcode":"83501",
    "sg:province":"ID",
    "wof:name":"Pedals-N-Spokes",
    "wof:placetype":"venue"
},
  "geometry": {"coordinates":[-117.023214,46.421288],"type":"Point"}
}