{
  "type": "Feature",
  "properties": {
    "iso:country":"US",
    "sg:address":"305 E Main St",
    "sg:city":"Burley",
    "sg:classifiers":[
        {
            "category":"Banks & Credit Unions",
            "subcategory":"Bank",
            "type":"Services"
        }
    ],
    "sg:phone":"+1 208 878 4452",
    "sg:postcode":"83318",
    "sg:province":"ID",
    "sg:tags":[
        "cashing",
        "check"
    ],
    "wof:name":"Minuteman",
    "wof:placetype":"venue"
},
  "geometry": {"coordinates":[-113.7906,42.538015],"type":"Point"}
}