{
  "type": "Feature",
  "properties": {
    "iso:country":"US",
    "sg:address":"8108 W Peterson St",
    "sg:city":"Boise",
    "sg:classifiers":[
        {
            "category":"Retail",
            "subcategory":"Repair Shop",
            "type":"Services"
        }
    ],
    "sg:phone":"+1 208 853 6442",
    "sg:postcode":"83714",
    "sg:province":"ID",
    "sg:tags":[
        "refrigerator",
        "freezer"
    ],
    "wof:name":"Rhodes Refrigeration",
    "wof:placetype":"venue"
},
  "geometry": {"coordinates":[-116.286919,43.683406],"type":"Point"}
}