{
  "type": "Feature",
  "properties": {
    "addr:full":"218 Holly St Nampa ID 83686",
    "addr:housenumber":"218",
    "addr:postcode":"83686",
    "addr:street":"Holly St",
    "iso:country":"US",
    "sg:address":"218 Holly St",
    "sg:city":"Nampa",
    "sg:classifiers":[
        {
            "category":"Retail",
            "subcategory":"Self-service Laundry",
            "type":"Services"
        }
    ],
    "sg:phone":"+1 208 463 1668",
    "sg:postcode":"83686",
    "sg:province":"ID",
    "wof:name":"Washboard Laundry",
    "wof:placetype":"venue"
},
  "geometry": {"coordinates":[-116.564232,43.567422],"type":"Point"}
}