{
  "type": "Feature",
  "properties": {
    "iso:country":"US",
    "sg:address":"215 S 9th Ave",
    "sg:city":"Caldwell",
    "sg:classifiers":[
        {
            "category":"Banks & Credit Unions",
            "subcategory":"Investment Brokerage",
            "type":"Services"
        }
    ],
    "sg:phone":"+1 208 459 1100",
    "sg:postcode":"83605",
    "sg:province":"ID",
    "sg:tags":[
        "stock",
        "bond"
    ],
    "wof:name":"Continental Investors Svc",
    "wof:placetype":"venue"
},
  "geometry": {"coordinates":[-116.68711500000001,43.664652],"type":"Point"}
}