{
  "type": "Feature",
  "properties": {
    "iso:country":"US",
    "sg:address":"620 Oneida St",
    "sg:city":"Rupert",
    "sg:classifiers":[
        {
            "category":"Wholesale",
            "subcategory":"Machinery & Supplies",
            "type":"Manufacturing & Wholesale Goods"
        }
    ],
    "sg:phone":"+1 208 436 3154",
    "sg:postcode":"83350",
    "sg:province":"ID",
    "sg:tags":[
        "farm",
        "equipment"
    ],
    "wof:name":"Trevino Bearing & Supply",
    "wof:placetype":"venue"
},
  "geometry": {"coordinates":[-113.668195,42.618346],"type":"Point"}
}