{
  "type": "Feature",
  "properties": {
    "addr:full":"1930 W Pullman Rd Moscow ID 83843",
    "addr:housenumber":"1930",
    "addr:postcode":"83843",
    "addr:street":"W Pullman Rd",
    "iso:country":"US",
    "sg:address":"1930 W Pullman Rd",
    "sg:city":"Moscow",
    "sg:classifiers":[
        {
            "category":"Wholesale",
            "subcategory":"Painting Supplies",
            "type":"Manufacturing & Wholesale Goods"
        },
        {
            "category":"Building & Trades",
            "subcategory":"Construction",
            "type":"Services"
        },
        {
            "category":"Home & Garden",
            "subcategory":"Building Materials",
            "type":"Retail Goods"
        },
        {
            "category":"Manufacturing",
            "subcategory":"Chemicals & Compounds",
            "type":"Manufacturing & Wholesale Goods"
        },
        {
            "category":"Manufacturing",
            "subcategory":"Tools & Machinery",
            "type":"Manufacturing & Wholesale Goods"
        },
        {
            "category":"Autos & Motor Vehicles",
            "subcategory":"Auto Supplies",
            "type":"Retail Goods"
        },
        {
            "category":"Building & Trades",
            "subcategory":"Equipment Rental",
            "type":"Services"
        },
        {
            "category":"Manufacturing",
            "subcategory":"Building Materials",
            "type":"Manufacturing & Wholesale Goods"
        }
    ],
    "sg:phone":"+1 208 883 8465",
    "sg:postcode":"83843",
    "sg:province":"ID",
    "sg:tags":[
        "shop",
        "spraying",
        "wall",
        "automobile",
        "wallpaper",
        "coating",
        "contractor",
        "paint-wholesale",
        "paint",
        "body",
        "wallcoverings-installation",
        "wallcoverings",
        "improvement",
        "equipment-renting",
        "painter",
        "manufacturer"
    ],
    "sg:website":"http://national.citysearch.com/profile/external/3424607/moscow_id/sherwin_williams.html?publisher=yellowpages&reference_id=1&placement=ypwebsitemip",
    "wof:name":"Sherwin-Williams",
    "wof:placetype":"venue"
},
  "geometry": {"coordinates":[-117.029668,46.73253],"type":"Point"}
}