{
  "type": "Feature",
  "properties": {
    "iso:country":"US",
    "sg:address":"2070 E Commercial St",
    "sg:city":"Meridian",
    "sg:classifiers":[
        {
            "category":"Building & Trades",
            "subcategory":"Landscaping Services",
            "type":"Services"
        }
    ],
    "sg:phone":"+1 208 288 5589",
    "sg:postcode":"83642",
    "sg:province":"ID",
    "sg:tags":[
        "lawn",
        "maintenance",
        "grounds"
    ],
    "sg:website":"www.idaholawncare.com",
    "wof:name":"Pro Care Landscape Management",
    "wof:placetype":"venue"
},
  "geometry": {"coordinates":[-116.370819,43.609778],"type":"Point"}
}