{
  "type": "Feature",
  "properties": {
    "addr:full":"337 E Idaho Ave Homedale ID 83628",
    "addr:housenumber":"337",
    "addr:postcode":"83628",
    "addr:street":"E Idaho Ave",
    "iso:country":"US",
    "sg:address":"337 E Idaho Ave",
    "sg:city":"Homedale",
    "sg:classifiers":[
        {
            "category":"Manufacturing",
            "subcategory":"Signs",
            "type":"Manufacturing & Wholesale Goods"
        }
    ],
    "sg:phone":"+1 208 337 6215",
    "sg:postcode":"83628",
    "sg:province":"ID",
    "wof:name":"Allied Sign",
    "wof:placetype":"venue"
},
  "geometry": {"coordinates":[-116.928433,43.617813],"type":"Point"}
}