{
  "type": "Feature",
  "properties": {
    "iso:country":"US",
    "sg:address":"1134 American Legion Blvd",
    "sg:city":"Mountain Home",
    "sg:classifiers":[
        {
            "category":"Social Services",
            "subcategory":"Child Care",
            "type":"Services"
        }
    ],
    "sg:phone":"+1 208 587 8161",
    "sg:postcode":"83647",
    "sg:province":"ID",
    "sg:tags":[
        "kindergarten",
        "academic",
        "school"
    ],
    "wof:name":"Children's House Montessori",
    "wof:placetype":"venue"
},
  "geometry": {"coordinates":[-115.68623,43.133838],"type":"Point"}
}