{
  "type": "Feature",
  "properties": {
    "iso:country":"US",
    "sg:address":"1904 N 32nd St",
    "sg:city":"Boise",
    "sg:classifiers":[
        {
            "category":"Building & Trades",
            "subcategory":"Plumbing",
            "type":"Services"
        }
    ],
    "sg:phone":"+1 208 368 0496",
    "sg:postcode":"83703",
    "sg:province":"ID",
    "sg:tags":[
        "contractor"
    ],
    "wof:name":"Excel Plumbing",
    "wof:placetype":"venue"
},
  "geometry": {"coordinates":[-116.228217,43.638208],"type":"Point"}
}