{
  "type": "Feature",
  "properties": {
    "addr:full":"11915 W Silverking Dr Boise ID 83709",
    "addr:housenumber":"11915",
    "addr:postcode":"83709",
    "addr:street":"W Silverking Dr",
    "iso:country":"US",
    "sg:address":"11915 W Silverking Dr",
    "sg:city":"Boise",
    "sg:classifiers":[
        {
            "category":"Professional",
            "subcategory":"Detective & Security Services",
            "type":"Services"
        }
    ],
    "sg:phone":"+1 208 362 9875",
    "sg:postcode":"83709",
    "sg:province":"ID",
    "sg:tags":[
        "equipment",
        "electrical",
        "system"
    ],
    "wof:name":"Mountain States SEC Systems",
    "wof:placetype":"venue"
},
  "geometry": {"coordinates":[-116.330782,43.586357],"type":"Point"}
}