{
  "type": "Feature",
  "properties": {
    "iso:country":"US",
    "sg:address":"1265 W 1st St",
    "sg:city":"Weiser",
    "sg:classifiers":[
        {
            "category":"Professional",
            "subcategory":"Management & Consulting",
            "type":"Services"
        }
    ],
    "sg:phone":"+1 208 549 3869",
    "sg:postcode":"83672",
    "sg:province":"ID",
    "sg:tags":[
        "retail",
        "direct",
        "sales"
    ],
    "wof:name":"Something Special",
    "wof:placetype":"venue"
},
  "geometry": {"coordinates":[-116.969848,44.253984],"type":"Point"}
}