{
  "type": "Feature",
  "properties": {
    "iso:country":"US",
    "sg:address":"3636 S Findley Ave",
    "sg:city":"Boise",
    "sg:classifiers":[
        {
            "category":"Professional",
            "type":"Services"
        }
    ],
    "sg:phone":"+1 208 429 0076",
    "sg:postcode":"83705",
    "sg:province":"ID",
    "sg:tags":[
        "establishment"
    ],
    "wof:name":"Dakota Co",
    "wof:placetype":"venue"
},
  "geometry": {"coordinates":[-116.187613,43.570536],"type":"Point"}
}