{
  "type": "Feature",
  "properties": {
    "addr:full":"211 N Whitley Dr Fruitland ID 83619",
    "addr:housenumber":"211",
    "addr:postcode":"83619",
    "addr:street":"N Whitley Dr",
    "iso:country":"US",
    "sg:address":"211 N Whitley Dr",
    "sg:city":"Fruitland",
    "sg:classifiers":[
        {
            "category":"Health Services",
            "subcategory":"Chiropractor",
            "type":"Services"
        }
    ],
    "sg:phone":"+1 208 452 7582",
    "sg:postcode":"83619",
    "sg:province":"ID",
    "wof:name":"Back 2 Beck Chiropractic",
    "wof:placetype":"venue"
},
  "geometry": {"coordinates":[-116.92393800000001,44.011983],"type":"Point"}
}