{
  "type": "Feature",
  "properties": {
    "iso:country":"US",
    "sg:address":"400 Virginia St",
    "sg:city":"New Meadows",
    "sg:classifiers":[
        {
            "category":"Education",
            "subcategory":"Library",
            "type":"Public Place"
        }
    ],
    "sg:phone":"+1 208 347 3147",
    "sg:postcode":"83654",
    "sg:province":"ID",
    "wof:name":"Meadows Valley Public Library",
    "wof:placetype":"venue"
},
  "geometry": {"coordinates":[-116.28380300000001,44.971022],"type":"Point"}
}