{
  "type": "Feature",
  "properties": {
    "iso:country":"US",
    "sg:address":"535 W Main St",
    "sg:city":"Burley",
    "sg:classifiers":[
        {
            "category":"Autos & Motor Vehicles",
            "subcategory":"Automobile Sales",
            "type":"Retail Goods"
        }
    ],
    "sg:phone":"+1 208 878 3300",
    "sg:postcode":"83318",
    "sg:province":"ID",
    "sg:tags":[
        "car",
        "dealer"
    ],
    "wof:name":"E Z Money Auto",
    "wof:placetype":"venue"
},
  "geometry": {"coordinates":[-113.798788,42.538005],"type":"Point"}
}