{
  "type": "Feature",
  "properties": {
    "addr:full":"121 N 1st Ave Sandpoint ID 83864",
    "addr:housenumber":"121",
    "addr:postcode":"83864",
    "addr:street":"N 1St Ave",
    "iso:country":"US",
    "sg:address":"121 N 1st Ave",
    "sg:city":"Sandpoint",
    "sg:classifiers":[
        {
            "category":"Banks & Credit Unions",
            "subcategory":"Bank",
            "type":"Services"
        }
    ],
    "sg:phone":"+1 208 255 5626",
    "sg:postcode":"83864",
    "sg:province":"ID",
    "sg:tags":[
        "loan",
        "real estate"
    ],
    "sg:website":"www.choicefundinginc.com",
    "wof:name":"Choice Funding",
    "wof:placetype":"venue"
},
  "geometry": {"coordinates":[-116.547757,48.273843],"type":"Point"}
}