{
  "type": "Feature",
  "properties": {
    "iso:country":"US",
    "sg:address":"990 Jefferson Ave",
    "sg:city":"Pocatello",
    "sg:classifiers":[
        {
            "category":"Retail",
            "subcategory":"Auto Rental",
            "type":"Services"
        }
    ],
    "sg:phone":"+1 208 233 5954",
    "sg:postcode":"83201",
    "sg:province":"ID",
    "sg:tags":[
        "renting",
        "leasing",
        "trailer"
    ],
    "wof:name":"U-Haul Co",
    "wof:placetype":"venue"
},
  "geometry": {"coordinates":[-112.441496,42.891485],"type":"Point"}
}