{
  "type": "Feature",
  "properties": {
    "iso:country":"US",
    "sg:address":"427 N Arthur Ave",
    "sg:city":"Pocatello",
    "sg:classifiers":[
        {
            "category":"Personal",
            "subcategory":"Beauty Salon",
            "type":"Services"
        }
    ],
    "sg:phone":"+1 208 478 9085",
    "sg:postcode":"83204",
    "sg:province":"ID",
    "sg:tags":[
        "manicuring"
    ],
    "wof:name":"Jones & Assoc Skin & Nail Sln",
    "wof:placetype":"venue"
},
  "geometry": {"coordinates":[-112.45500699999999,42.86423],"type":"Point"}
}