{
  "type": "Feature",
  "properties": {
    "iso:country":"US",
    "sg:address":"700 Stratford Dr",
    "sg:city":"Meridian",
    "sg:classifiers":[
        {
            "category":"Health Services",
            "subcategory":"Hospital",
            "type":"Services"
        }
    ],
    "sg:phone":"+1 208 846 7622",
    "sg:postcode":"83642",
    "sg:province":"ID",
    "sg:tags":[
        "medical",
        "surgical",
        "emergency"
    ],
    "wof:name":"Emergency Medical System",
    "wof:placetype":"venue"
},
  "geometry": {"coordinates":[-116.384552,43.598824],"type":"Point"}
}