{
  "type": "Feature",
  "properties": {
    "iso:country":"US",
    "sg:address":"5022 S 10th Ave",
    "sg:city":"Caldwell",
    "sg:classifiers":[
        {
            "category":"Retail",
            "subcategory":"Repair Shop",
            "type":"Services"
        }
    ],
    "sg:phone":"+1 208 454 5641",
    "sg:postcode":"83607",
    "sg:province":"ID",
    "wof:name":"Bears Workshop",
    "wof:placetype":"venue"
},
  "geometry": {"coordinates":[-116.693012,43.628455],"type":"Point"}
}