{
  "type": "Feature",
  "properties": {
    "iso:country":"US",
    "sg:address":"118 N Garden St",
    "sg:city":"Boise",
    "sg:classifiers":[
        {
            "category":"Real Estate",
            "subcategory":"Real Estate Operator",
            "type":"Services"
        }
    ],
    "sg:phone":"+1 208 433 1372",
    "sg:postcode":"83706",
    "sg:province":"ID",
    "sg:tags":[
        "property",
        "lessor"
    ],
    "wof:name":"Knightsbridge LLC",
    "wof:placetype":"venue"
},
  "geometry": {"coordinates":[-116.238417,43.605385],"type":"Point"}
}