{
  "type": "Feature",
  "properties": {
    "iso:country":"US",
    "sg:address":"1205 W Broadway St",
    "sg:city":"Idaho Falls",
    "sg:classifiers":[
        {
            "category":"Autos & Motor Vehicles",
            "subcategory":"Fuel & Gas Station",
            "type":"Retail Goods"
        }
    ],
    "sg:phone":"+1 208 522 5235",
    "sg:postcode":"83402",
    "sg:province":"ID",
    "sg:tags":[
        "oil"
    ],
    "wof:name":"Broadway 66",
    "wof:placetype":"venue"
},
  "geometry": {"coordinates":[-112.05255200000001,43.496186],"type":"Point"}
}