{
  "type": "Feature",
  "properties": {
    "iso:country":"US",
    "sg:address":"102 W 11th Ave",
    "sg:city":"Post Falls",
    "sg:classifiers":[
        {
            "category":"Health Services",
            "subcategory":"Doctor",
            "type":"Services"
        }
    ],
    "sg:phone":"+1 208 777 1542",
    "sg:postcode":"83854",
    "sg:province":"ID",
    "sg:tags":[
        "dentist"
    ],
    "wof:name":"Airo Dental Health Care",
    "wof:placetype":"venue"
},
  "geometry": {"coordinates":[-116.949568,47.71887],"type":"Point"}
}