{
  "type": "Feature",
  "properties": {
    "iso:country":"US",
    "sg:address":"560 W 100 S",
    "sg:city":"Paul",
    "sg:classifiers":[
        {
            "category":"Retail",
            "subcategory":"Auto Repair",
            "type":"Services"
        }
    ],
    "sg:phone":"+1 208 438 5361",
    "sg:postcode":"83347",
    "sg:province":"ID",
    "sg:tags":[
        "repairing",
        "automobile"
    ],
    "wof:name":"Dan's Tune-Up & Repair",
    "wof:placetype":"venue"
},
  "geometry": {"coordinates":[-113.774298,42.60511],"type":"Point"}
}