{
  "type": "Feature",
  "properties": {
    "iso:country":"US",
    "sg:address":"2212 E Amity Ave",
    "sg:city":"Nampa",
    "sg:classifiers":[
        {
            "category":"Organizations",
            "subcategory":"Religious Organization",
            "type":"Services"
        }
    ],
    "sg:phone":"+1 208 461 3690",
    "sg:postcode":"83686",
    "sg:province":"ID",
    "sg:tags":[
        "church"
    ],
    "wof:name":"Church Of Jesus Christ Of Lds",
    "wof:placetype":"venue"
},
  "geometry": {"coordinates":[-116.544349,43.561535],"type":"Point"}
}