{
  "type": "Feature",
  "properties": {
    "addr:full":"500 S 10th St Boise ID 83702",
    "addr:housenumber":"500",
    "addr:postcode":"83702",
    "addr:street":"S 10Th St",
    "iso:country":"US",
    "sg:address":"500 S 10th St",
    "sg:city":"Boise",
    "sg:classifiers":[
        {
            "category":"Shopping",
            "subcategory":"Computers & Home Electronics",
            "type":"Retail Goods"
        }
    ],
    "sg:phone":"+1 208 344 1630",
    "sg:postcode":"83702",
    "sg:province":"ID",
    "sg:tags":[
        "software"
    ],
    "wof:name":"Pro Clarity Corp",
    "wof:placetype":"venue"
},
  "geometry": {"coordinates":[-116.209982,43.6125],"type":"Point"}
}