{
  "type": "Feature",
  "properties": {
    "addr:full":"3113 Rose Hill St Boise ID 83705",
    "addr:housenumber":"3113",
    "addr:postcode":"83705",
    "addr:street":"Rose Hill St",
    "iso:country":"US",
    "sg:address":"3113 Rose Hill St",
    "sg:city":"Boise",
    "sg:classifiers":[
        {
            "category":"Recreation",
            "type":"Entertainment"
        }
    ],
    "sg:phone":"+1 208 343 9786",
    "sg:postcode":"83705",
    "sg:province":"ID",
    "sg:tags":[
        "instruction",
        "yoga"
    ],
    "wof:name":"Yoga Center Boise",
    "wof:placetype":"venue"
},
  "geometry": {"coordinates":[-116.22009,43.600645],"type":"Point"}
}