{
  "type": "Feature",
  "properties": {
    "iso:country":"US",
    "sg:address":"307 7th Ave",
    "sg:city":"Lewiston",
    "sg:classifiers":[
        {
            "category":"Health Services",
            "subcategory":"Doctor",
            "type":"Services"
        }
    ],
    "sg:phone":"+1 208 798 7388",
    "sg:postcode":"83501",
    "sg:province":"ID",
    "sg:tags":[
        "physician",
        "surgeon"
    ],
    "wof:name":"Carlos W Bond DO",
    "wof:placetype":"venue"
},
  "geometry": {"coordinates":[-117.029757,46.413591],"type":"Point"}
}