{
  "type": "Feature",
  "properties": {
    "iso:country":"US",
    "sg:address":"1526 N Main St",
    "sg:city":"Meridian",
    "sg:classifiers":[
        {
            "category":"Restaurant",
            "type":"Food & Drink"
        }
    ],
    "sg:menulink":"http://www.allmenus.com/id/boise-city/81172-papa-johns-pizza/menu/",
    "sg:phone":"+1 208 888 7272",
    "sg:postcode":"83642",
    "sg:province":"ID",
    "sg:tags":[
        "american",
        "pizza"
    ],
    "wof:name":"Papa John's Pizza",
    "wof:placetype":"venue"
},
  "geometry": {"coordinates":[-116.391555,43.617678],"type":"Point"}
}