{
  "type": "Feature",
  "properties": {
    "iso:country":"US",
    "sg:address":"873 E 800 N",
    "sg:city":"Shelley",
    "sg:classifiers":[
        {
            "category":"Professional",
            "subcategory":"Management & Consulting",
            "type":"Services"
        }
    ],
    "sg:phone":"+1 208 346 6147",
    "sg:postcode":"83274",
    "sg:province":"ID",
    "wof:name":"Bay Horse Marketing",
    "wof:placetype":"venue"
},
  "geometry": {"coordinates":[-112.126439,43.311357],"type":"Point"}
}