{
  "type": "Feature",
  "properties": {
    "addr:full":"1910 S Owyhee St Boise ID 83705",
    "addr:housenumber":"1910",
    "addr:postcode":"83705",
    "addr:street":"S Owyhee St",
    "iso:country":"US",
    "sg:address":"1910 S Owyhee St",
    "sg:city":"Boise",
    "sg:classifiers":[
        {
            "category":"Bars & Pubs",
            "type":"Food & Drink"
        }
    ],
    "sg:phone":"+1 208 342 9034",
    "sg:postcode":"83705",
    "sg:province":"ID",
    "wof:name":"Little Dutch Garden",
    "wof:placetype":"venue"
},
  "geometry": {"coordinates":[-116.223536,43.585183],"type":"Point"}
}