{
  "type": "Feature",
  "properties": {
    "addr:full":"438 State Hwy 55 Horseshoe Bend ID 83629",
    "addr:housenumber":"438",
    "addr:postcode":"83629",
    "addr:street":"State Hwy 55",
    "iso:country":"US",
    "sg:address":"438 State Hwy 55",
    "sg:city":"Horseshoe Bend",
    "sg:classifiers":[
        {
            "category":"Home & Garden",
            "subcategory":"Furniture",
            "type":"Retail Goods"
        }
    ],
    "sg:phone":"+1 208 793 3355",
    "sg:postcode":"83629",
    "sg:province":"ID",
    "sg:tags":[
        "cabinet"
    ],
    "wof:name":"Castle Rock Custom Cabinets",
    "wof:placetype":"venue"
},
  "geometry": {"coordinates":[-116.203142,43.901458],"type":"Point"}
}