{
  "type": "Feature",
  "properties": {
    "iso:country":"US",
    "sg:address":"301 E Bower Ave",
    "sg:city":"Meridian",
    "sg:classifiers":[
        {
            "category":"Manufacturing",
            "subcategory":"Leather Goods",
            "type":"Manufacturing & Wholesale Goods"
        }
    ],
    "sg:phone":"+1 208 884 3766",
    "sg:postcode":"83642",
    "sg:province":"ID",
    "wof:name":"Gfeller Casemakers Inc",
    "wof:placetype":"venue"
},
  "geometry": {"coordinates":[-116.38875,43.607922],"type":"Point"}
}