{
  "type": "Feature",
  "properties": {
    "iso:country":"US",
    "sg:address":"800 W Judicial St",
    "sg:city":"Blackfoot",
    "sg:classifiers":[
        {
            "category":"Professional",
            "subcategory":"Accounting & Tax Preparation",
            "type":"Services"
        }
    ],
    "sg:phone":"+1 208 785 3366",
    "sg:postcode":"83221",
    "sg:province":"ID",
    "sg:tags":[
        "accountant"
    ],
    "wof:name":"Austin L Moses CPA",
    "wof:placetype":"venue"
},
  "geometry": {"coordinates":[-112.354506,43.192987],"type":"Point"}
}