{
  "type": "Feature",
  "properties": {
    "iso:country":"US",
    "sg:address":"804 W Fort St",
    "sg:city":"Boise",
    "sg:classifiers":[
        {
            "category":"Wholesale",
            "subcategory":"Durable Goods & Equipment",
            "type":"Manufacturing & Wholesale Goods"
        }
    ],
    "sg:phone":"+1 208 331 1212",
    "sg:postcode":"83702",
    "sg:province":"ID",
    "sg:tags":[
        "importer"
    ],
    "wof:name":"Eyes Of The World Imports Inc",
    "wof:placetype":"venue"
},
  "geometry": {"coordinates":[-116.198758,43.622355],"type":"Point"}
}