{
  "type": "Feature",
  "properties": {
    "addr:full":"1801 N Elder St Nampa ID 83687",
    "addr:housenumber":"1801",
    "addr:postcode":"83687",
    "addr:street":"N Elder St",
    "iso:country":"US",
    "sg:address":"1801 N Elder St",
    "sg:city":"Nampa",
    "sg:classifiers":[
        {
            "category":"Manufacturing",
            "subcategory":"Food",
            "type":"Manufacturing & Wholesale Goods"
        }
    ],
    "sg:phone":"+1 208 467 7441",
    "sg:postcode":"83687",
    "sg:province":"ID",
    "sg:tags":[
        "product",
        "manufacturer"
    ],
    "sg:website":"www.hydroblendinc.com",
    "wof:name":"Hydroblend LTD",
    "wof:placetype":"venue"
},
  "geometry": {"coordinates":[-116.55928299999999,43.605052],"type":"Point"}
}