{
  "type": "Feature",
  "properties": {
    "iso:country":"US",
    "sg:address":"5892 W Hidden Springs Dr",
    "sg:city":"Boise",
    "sg:classifiers":[
        {
            "category":"Building & Trades",
            "subcategory":"Construction",
            "type":"Services"
        }
    ],
    "sg:phone":"+1 208 229 2553",
    "sg:postcode":"83714",
    "sg:province":"ID",
    "sg:tags":[
        "home",
        "builder"
    ],
    "sg:website":"www.chuckmillerconstruction.com",
    "wof:name":"Chuck Miller Construction Inc",
    "wof:placetype":"venue"
},
  "geometry": {"coordinates":[-116.26260499999999,43.724722],"type":"Point"}
}