{
  "type": "Feature",
  "properties": {
    "iso:country":"US",
    "sg:address":"825 S Washington Ave",
    "sg:city":"Emmett",
    "sg:classifiers":[
        {
            "category":"Health Services",
            "subcategory":"Health Practitioner",
            "type":"Services"
        }
    ],
    "sg:phone":"+1 208 365 4400",
    "sg:postcode":"83617",
    "sg:province":"ID",
    "sg:tags":[
        "therapist",
        "physical"
    ],
    "wof:name":"Scott King",
    "wof:placetype":"venue"
},
  "geometry": {"coordinates":[-116.500069,43.868796],"type":"Point"}
}