{
  "type": "Feature",
  "properties": {
    "iso:country":"US",
    "sg:address":"1212 Oakley Ave",
    "sg:city":"Burley",
    "sg:classifiers":[
        {
            "category":"Professional",
            "subcategory":"Business Services",
            "type":"Services"
        }
    ],
    "sg:phone":"+1 208 878 7674",
    "sg:postcode":"83318",
    "sg:province":"ID",
    "sg:tags":[
        "interior",
        "consultant",
        "design",
        "decorator"
    ],
    "wof:name":"Posh Pear",
    "wof:placetype":"venue"
},
  "geometry": {"coordinates":[-113.794648,42.537926],"type":"Point"}
}