{
  "type": "Feature",
  "properties": {
    "iso:country":"US",
    "sg:address":"3114 N Government Way",
    "sg:city":"Coeur D Alene",
    "sg:classifiers":[
        {
            "category":"Professional",
            "type":"Services"
        }
    ],
    "sg:phone":"+1 208 687 3832",
    "sg:postcode":"83815",
    "sg:province":"ID",
    "sg:tags":[
        "establishment"
    ],
    "wof:name":"S D Design",
    "wof:placetype":"venue"
},
  "geometry": {"coordinates":[-116.78637000000001,47.705766],"type":"Point"}
}