{
  "type": "Feature",
  "properties": {
    "addr:full":"451 Trotter Dr Twin Falls ID 83301",
    "addr:housenumber":"451",
    "addr:postcode":"83301",
    "addr:street":"Trotter Dr",
    "iso:country":"US",
    "sg:address":"451 Trotter Dr",
    "sg:city":"Twin Falls",
    "sg:classifiers":[
        {
            "category":"Freight",
            "type":"Transportation"
        }
    ],
    "sg:phone":"+1 208 734 0386",
    "sg:postcode":"83301",
    "sg:province":"ID",
    "sg:tags":[
        "trucking"
    ],
    "wof:name":"Ortegel Enterprises Inc",
    "wof:placetype":"venue"
},
  "geometry": {"coordinates":[-114.427949,42.553134],"type":"Point"}
}