{
  "type": "Feature",
  "properties": {
    "addr:full":"251 E Front St Boise ID 83702",
    "addr:housenumber":"251",
    "addr:postcode":"83702",
    "addr:street":"E Front St",
    "iso:country":"US",
    "sg:address":"251 E Front St",
    "sg:city":"Boise",
    "sg:classifiers":[
        {
            "category":"Shopping",
            "subcategory":"Bicycles & Sporting Goods",
            "type":"Retail Goods"
        }
    ],
    "sg:phone":"+1 208 343 3782",
    "sg:postcode":"83702",
    "sg:province":"ID",
    "wof:name":"George's Cycles & Fitness",
    "wof:placetype":"venue"
},
  "geometry": {"coordinates":[-116.19449,43.6086],"type":"Point"}
}