{
  "type": "Feature",
  "properties": {
    "addr:full":"1193 W Hempstead Dr Eagle ID 83616",
    "addr:housenumber":"1193",
    "addr:postcode":"83616",
    "addr:street":"W Hempstead Dr",
    "iso:country":"US",
    "sg:address":"1193 W Hempstead Dr",
    "sg:city":"Eagle",
    "sg:classifiers":[
        {
            "category":"Building & Trades",
            "subcategory":"Landscaping Services",
            "type":"Services"
        }
    ],
    "sg:phone":"+1 208 938 4568",
    "sg:postcode":"83616",
    "sg:province":"ID",
    "sg:tags":[
        "landscape"
    ],
    "wof:name":"Macs Landscape",
    "wof:placetype":"venue"
},
  "geometry": {"coordinates":[-116.368521,43.663785],"type":"Point"}
}