{
  "type": "Feature",
  "properties": {
    "addr:full":"1955 W Broadway St Idaho Falls ID 83402",
    "addr:housenumber":"1955",
    "addr:postcode":"83402",
    "addr:street":"W Broadway St",
    "iso:country":"US",
    "sg:address":"1955 W Broadway St",
    "sg:city":"Idaho Falls",
    "sg:classifiers":[
        {
            "category":"Autos & Motor Vehicles",
            "subcategory":"Auto Supplies",
            "type":"Retail Goods"
        }
    ],
    "sg:phone":"+1 208 524 1475",
    "sg:postcode":"83402",
    "sg:province":"ID",
    "sg:tags":[
        "automobile",
        "parts"
    ],
    "wof:name":"Checker Auto Parts",
    "wof:placetype":"venue"
},
  "geometry": {"coordinates":[-112.069804,43.496676],"type":"Point"}
}