{
  "type": "Feature",
  "properties": {
    "iso:country":"US",
    "sg:address":"151 N Ridge Ave",
    "sg:city":"Idaho Falls",
    "sg:classifiers":[
        {
            "category":"Professional",
            "type":"Services"
        }
    ],
    "sg:phone":"+1 208 523 1863",
    "sg:postcode":"83402",
    "sg:province":"ID",
    "sg:tags":[
        "establishment"
    ],
    "wof:name":"CH2N Hill",
    "wof:placetype":"venue"
},
  "geometry": {"coordinates":[-112.03657,43.488997],"type":"Point"}
}