{
  "type": "Feature",
  "properties": {
    "iso:country":"US",
    "sg:address":"302 3rd Ave S",
    "sg:city":"Twin Falls",
    "sg:classifiers":[
        {
            "category":"Autos & Motor Vehicles",
            "subcategory":"Automobile Sales",
            "type":"Retail Goods"
        }
    ],
    "sg:phone":"+1 208 733 7223",
    "sg:postcode":"83301",
    "sg:province":"ID",
    "sg:tags":[
        "cart"
    ],
    "wof:name":"Nazz Kart",
    "wof:placetype":"venue"
},
  "geometry": {"coordinates":[-114.469426,42.552593],"type":"Point"}
}