{
  "type": "Feature",
  "properties": {
    "iso:country":"US",
    "sg:address":"147 W Orchard Ave",
    "sg:city":"Hayden Lake",
    "sg:classifiers":[
        {
            "category":"Farming",
            "subcategory":"Orchard",
            "type":"Manufacturing & Wholesale Goods"
        }
    ],
    "sg:phone":"+1 208 762 7759",
    "sg:postcode":"83835",
    "sg:province":"ID",
    "sg:tags":[
        "grove",
        "management"
    ],
    "wof:name":"Orchard Center",
    "wof:placetype":"venue"
},
  "geometry": {"coordinates":[-116.790986,47.755393],"type":"Point"}
}