{
  "type": "Feature",
  "properties": {
    "addr:full":"9211 Overland Rd Boise ID 83709",
    "addr:housenumber":"9211",
    "addr:postcode":"83709",
    "addr:street":"Overland Rd",
    "iso:country":"US",
    "sg:address":"9211 Overland Rd",
    "sg:city":"Boise",
    "sg:classifiers":[
        {
            "category":"Health Services",
            "subcategory":"Chiropractor",
            "type":"Services"
        }
    ],
    "sg:phone":"+1 208 377 8777",
    "sg:postcode":"83709",
    "sg:province":"ID",
    "wof:name":"Jason Haycock DC",
    "wof:placetype":"venue"
},
  "geometry": {"coordinates":[-116.29657400000001,43.590269],"type":"Point"}
}