{
  "type": "Feature",
  "properties": {
    "iso:country":"US",
    "sg:address":"11900 Lower Bench Rd",
    "sg:city":"Emmett",
    "sg:classifiers":[
        {
            "category":"Farming",
            "subcategory":"Farm & Veterinary Services",
            "type":"Manufacturing & Wholesale Goods"
        }
    ],
    "sg:phone":"+1 208 398 8120",
    "sg:postcode":"83617",
    "sg:province":"ID",
    "sg:tags":[
        "breeder",
        "livestock"
    ],
    "wof:name":"Simplot Cattle Co",
    "wof:placetype":"venue"
},
  "geometry": {"coordinates":[-116.70784,43.955907],"type":"Point"}
}