{
  "type": "Feature",
  "properties": {
    "addr:full":"824 Bank St Wallace ID 83873",
    "addr:housenumber":"824",
    "addr:postcode":"83873",
    "addr:street":"Bank St",
    "iso:country":"US",
    "sg:address":"824 Bank St",
    "sg:city":"Wallace",
    "sg:classifiers":[
        {
            "category":"Autos & Motor Vehicles",
            "subcategory":"Auto Supplies",
            "type":"Retail Goods"
        }
    ],
    "sg:phone":"+1 208 752 1185",
    "sg:postcode":"83873",
    "sg:province":"ID",
    "sg:tags":[
        "automobile",
        "parts"
    ],
    "wof:name":"Stovern Supply Co",
    "wof:placetype":"venue"
},
  "geometry": {"coordinates":[-115.920115,47.471549],"type":"Point"}
}