{
  "type": "Feature",
  "properties": {
    "iso:country":"US",
    "sg:address":"525 N 2nd E",
    "sg:city":"Rexburg",
    "sg:classifiers":[
        {
            "category":"Home & Garden",
            "subcategory":"Furniture",
            "type":"Retail Goods"
        }
    ],
    "sg:phone":"+1 208 356 0063",
    "sg:postcode":"83440",
    "sg:province":"ID",
    "wof:name":"O'Dell's Furniture & Sleep Ctr",
    "wof:placetype":"venue"
},
  "geometry": {"coordinates":[-111.778159,43.835679],"type":"Point"}
}