{
  "type": "Feature",
  "properties": {
    "iso:country":"US",
    "sg:address":"11209 Tioga St",
    "sg:city":"Boise",
    "sg:classifiers":[
        {
            "category":"Insurance",
            "subcategory":"Insurance Agent",
            "type":"Services"
        }
    ],
    "sg:phone":"+1 208 345 5500",
    "sg:postcode":"83709",
    "sg:province":"ID",
    "wof:name":"Retirement and Insurance Plg",
    "wof:placetype":"venue"
},
  "geometry": {"coordinates":[-116.320251,43.577302],"type":"Point"}
}