{
  "type": "Feature",
  "properties": {
    "iso:country":"US",
    "sg:address":"3660 Mill Rd",
    "sg:city":"Emmett",
    "sg:classifiers":[
        {
            "category":"Professional",
            "type":"Services"
        }
    ],
    "sg:phone":"+1 208 365 0697",
    "sg:postcode":"83617",
    "sg:province":"ID",
    "wof:name":"Power Equipment Services",
    "wof:placetype":"venue"
},
  "geometry": {"coordinates":[-116.51257699999999,43.83859],"type":"Point"}
}