{
  "type": "Feature",
  "properties": {
    "iso:country":"US",
    "sg:address":"1171 N 1350 E",
    "sg:city":"Shelley",
    "sg:classifiers":[
        {
            "category":"Wholesale",
            "subcategory":"Construction Materials",
            "type":"Manufacturing & Wholesale Goods"
        }
    ],
    "sg:phone":"+1 208 357 7615",
    "sg:postcode":"83274",
    "sg:province":"ID",
    "sg:tags":[
        "fence"
    ],
    "wof:name":"Timber's Edge Fence Co",
    "wof:placetype":"venue"
},
  "geometry": {"coordinates":[-112.02883300000001,43.363125],"type":"Point"}
}