{
  "type": "Feature",
  "properties": {
    "iso:country":"US",
    "sg:address":"250 Bluegill Ln",
    "sg:city":"Pocatello",
    "sg:classifiers":[
        {
            "category":"Retail",
            "subcategory":"Auto Repair",
            "type":"Services"
        }
    ],
    "sg:phone":"+1 208 637 8964",
    "sg:postcode":"83202",
    "sg:province":"ID",
    "sg:tags":[
        "body",
        "automobile",
        "painting"
    ],
    "wof:name":"Flatline Collision Repair",
    "wof:placetype":"venue"
},
  "geometry": {"coordinates":[-112.462456,42.922746],"type":"Point"}
}