{
  "type": "Feature",
  "properties": {
    "addr:full":"506 Yellowstone Ave Pocatello ID 83201",
    "addr:housenumber":"506",
    "addr:postcode":"83201",
    "addr:street":"Yellowstone Ave",
    "iso:country":"US",
    "sg:address":"506 Yellowstone Ave",
    "sg:city":"Pocatello",
    "sg:classifiers":[
        {
            "category":"Shopping",
            "subcategory":"Used Merchandise",
            "type":"Retail Goods"
        }
    ],
    "sg:phone":"+1 208 232 4614",
    "sg:postcode":"83201",
    "sg:province":"ID",
    "sg:tags":[
        "pawnbroker"
    ],
    "wof:name":"Shamrock Coins",
    "wof:placetype":"venue"
},
  "geometry": {"coordinates":[-112.45137,42.884654],"type":"Point"}
}