{
  "type": "Feature",
  "properties": {
    "addr:full":"9194 N Clarkview Pl Hayden ID 83835",
    "addr:housenumber":"9194",
    "addr:postcode":"83835",
    "addr:street":"N Clarkview Pl",
    "iso:country":"US",
    "sg:address":"9194 N Clarkview Pl",
    "sg:city":"Hayden",
    "sg:classifiers":[
        {
            "category":"Shopping",
            "subcategory":"Computers & Home Electronics",
            "type":"Retail Goods"
        }
    ],
    "sg:phone":"+1 208 772 7344",
    "sg:postcode":"83835",
    "sg:province":"ID",
    "sg:tags":[
        "audio"
    ],
    "wof:name":"Audio Video Specialist",
    "wof:placetype":"venue"
},
  "geometry": {"coordinates":[-116.73004,47.752224],"type":"Point"}
}