{
  "type": "Feature",
  "properties": {
    "addr:full":"500 N Capital Ave Idaho Falls ID 83402",
    "addr:housenumber":"500",
    "addr:postcode":"83402",
    "addr:street":"N Capital Ave",
    "iso:country":"US",
    "sg:address":"500 N Capital Ave",
    "sg:city":"Idaho Falls",
    "sg:classifiers":[
        {
            "category":"Banks & Credit Unions",
            "subcategory":"Bank",
            "type":"Services"
        }
    ],
    "sg:phone":"+1 208 522 4251",
    "sg:postcode":"83402",
    "sg:province":"ID",
    "sg:tags":[
        "savings",
        "loan",
        "association"
    ],
    "wof:name":"Washington Federal Savings",
    "wof:placetype":"venue"
},
  "geometry": {"coordinates":[-112.040559,43.494831],"type":"Point"}
}