{
  "type": "Feature",
  "properties": {
    "addr:full":"1029 Air Base Rd Mountain Home ID 83647",
    "addr:housenumber":"1029",
    "addr:postcode":"83647",
    "addr:street":"Air Base Rd",
    "iso:country":"US",
    "sg:address":"1029 Air Base Rd",
    "sg:city":"Mountain Home",
    "sg:classifiers":[
        {
            "category":"Real Estate",
            "subcategory":"Real Estate Agent",
            "type":"Services"
        }
    ],
    "sg:phone":"+1 208 580 0960",
    "sg:postcode":"83647",
    "sg:province":"ID",
    "sg:tags":[
        "management"
    ],
    "wof:name":"Cornerstone Property Mgmt",
    "wof:placetype":"venue"
},
  "geometry": {"coordinates":[-115.68714,43.126541],"type":"Point"}
}