{
  "type": "Feature",
  "properties": {
    "iso:country":"US",
    "sg:address":"11288 Dufort Rd",
    "sg:city":"Priest River",
    "sg:classifiers":[
        {
            "category":"Building & Trades",
            "subcategory":"Electrical",
            "type":"Services"
        }
    ],
    "sg:phone":"+1 208 265 7887",
    "sg:postcode":"83856",
    "sg:province":"ID",
    "sg:tags":[
        "electric",
        "contractor"
    ],
    "wof:name":"Electrends LLC",
    "wof:placetype":"venue"
},
  "geometry": {"coordinates":[-116.784772,48.146111],"type":"Point"}
}