{
  "type": "Feature",
  "properties": {
    "addr:full":"417 Northwest Blvd Coeur D Alene ID 83814",
    "addr:housenumber":"417",
    "addr:postcode":"83814",
    "addr:street":"Northwest Blvd",
    "iso:country":"US",
    "sg:address":"417 Northwest Blvd",
    "sg:city":"Coeur D Alene",
    "sg:classifiers":[
        {
            "category":"Wholesale",
            "subcategory":"Auto Parts",
            "type":"Manufacturing & Wholesale Goods"
        }
    ],
    "sg:phone":"+1 208 664 1559",
    "sg:postcode":"83814",
    "sg:province":"ID",
    "sg:tags":[
        "automobile",
        "rebuilt"
    ],
    "wof:name":"Foreign Engines Inc",
    "wof:placetype":"venue"
},
  "geometry": {"coordinates":[-116.78926199999999,47.677473],"type":"Point"}
}