{
  "type": "Feature",
  "properties": {
    "iso:country":"US",
    "sg:address":"905 N Mullan Trl",
    "sg:city":"Post Falls",
    "sg:classifiers":[
        {
            "category":"Building & Trades",
            "subcategory":"Construction",
            "type":"Services"
        }
    ],
    "sg:phone":"+1 208 773 1608",
    "sg:postcode":"83854",
    "sg:province":"ID",
    "sg:tags":[
        "excavation",
        "excavating",
        "contractor"
    ],
    "wof:name":"Evenson Excavating",
    "wof:placetype":"venue"
},
  "geometry": {"coordinates":[-116.91917100000001,47.716744],"type":"Point"}
}