{
  "type": "Feature",
  "properties": {
    "iso:country":"US",
    "sg:address":"31466 Hwy 200",
    "sg:city":"Sandpoint",
    "sg:classifiers":[
        {
            "category":"Retail",
            "subcategory":"Auto Rental",
            "type":"Services"
        }
    ],
    "sg:phone":"+1 208 255 7909",
    "sg:postcode":"83864",
    "sg:province":"ID",
    "sg:tags":[
        "passenger",
        "car"
    ],
    "wof:name":"Thrifty Car Rental",
    "wof:placetype":"venue"
},
  "geometry": {"coordinates":[-116.52970500000001,48.309149],"type":"Point"}
}