{
  "type": "Feature",
  "properties": {
    "iso:country":"US",
    "sg:address":"1422 3rd Ave N",
    "sg:city":"Lewiston",
    "sg:classifiers":[
        {
            "category":"Wholesale",
            "subcategory":"Durable Goods & Equipment",
            "type":"Manufacturing & Wholesale Goods"
        }
    ],
    "sg:phone":"+1 208 746 0102",
    "sg:postcode":"83501",
    "sg:province":"ID",
    "sg:tags":[
        "exporter"
    ],
    "sg:website":"www.cldpacific.com",
    "wof:name":"Cld Pacific Grain",
    "wof:placetype":"venue"
},
  "geometry": {"coordinates":[-117.013047,46.425607],"type":"Point"}
}