{
  "type": "Feature",
  "properties": {
    "iso:country":"US",
    "sg:address":"407 Chinook Cir",
    "sg:city":"Post Falls",
    "sg:classifiers":[
        {
            "category":"Retail",
            "subcategory":"Portrait Studio",
            "type":"Services"
        }
    ],
    "sg:phone":"+1 208 457 1111",
    "sg:postcode":"83854",
    "sg:province":"ID",
    "sg:tags":[
        "photographer"
    ],
    "sg:website":"www.fineimage.net",
    "wof:name":"Art Of Photography-D Linhart",
    "wof:placetype":"venue"
},
  "geometry": {"coordinates":[-116.937834,47.704512],"type":"Point"}
}