{
  "type": "Feature",
  "properties": {
    "iso:country":"US",
    "sg:address":"395 S Broadway St",
    "sg:city":"Blackfoot",
    "sg:classifiers":[
        {
            "category":"Home & Garden",
            "subcategory":"Garden Supply",
            "type":"Retail Goods"
        }
    ],
    "sg:phone":"+1 208 785 0830",
    "sg:postcode":"83221",
    "sg:province":"ID",
    "sg:tags":[
        "bulb",
        "seed"
    ],
    "wof:name":"Idaho Grimm Growers Warehouse",
    "wof:placetype":"venue"
},
  "geometry": {"coordinates":[-112.348941,43.186658],"type":"Point"}
}