{
  "type": "Feature",
  "properties": {
    "iso:country":"US",
    "sg:address":"222 E Ellis St",
    "sg:city":"Paul",
    "sg:classifiers":[
        {
            "category":"Retail",
            "subcategory":"Repair Shop",
            "type":"Services"
        }
    ],
    "sg:phone":"+1 208 438 5818",
    "sg:postcode":"83347",
    "sg:province":"ID",
    "sg:tags":[
        "upholsterer"
    ],
    "wof:name":"Frontier Enterprises",
    "wof:placetype":"venue"
},
  "geometry": {"coordinates":[-113.780593,42.605103],"type":"Point"}
}