{
  "type": "Feature",
  "properties": {
    "iso:country":"US",
    "sg:address":"1614 E Hastings Ave",
    "sg:city":"Coeur D Alene",
    "sg:classifiers":[
        {
            "category":"Social Services",
            "subcategory":"Child Care",
            "type":"Services"
        },
        {
            "category":"Education",
            "subcategory":"School",
            "type":"Public Place"
        }
    ],
    "sg:phone":"+1 208 676 9000",
    "sg:postcode":"83814",
    "sg:province":"ID",
    "sg:tags":[
        "day"
    ],
    "wof:name":"Angel Academy Daycare Preschoo",
    "wof:placetype":"venue"
},
  "geometry": {"coordinates":[-116.759809,47.682504],"type":"Point"}
}