{
  "type": "Feature",
  "properties": {
    "iso:country":"US",
    "sg:address":"2720 Fargo St",
    "sg:city":"Boise",
    "sg:classifiers":[
        {
            "category":"Wholesale",
            "subcategory":"Electrical",
            "type":"Manufacturing & Wholesale Goods"
        }
    ],
    "sg:phone":"+1 208 342 0278",
    "sg:postcode":"83703",
    "sg:province":"ID",
    "sg:tags":[
        "communication",
        "radio",
        "system"
    ],
    "wof:name":"Electronic Enterprises",
    "wof:placetype":"venue"
},
  "geometry": {"coordinates":[-116.240369,43.645017],"type":"Point"}
}