{
  "type": "Feature",
  "properties": {
    "addr:full":"1490 Lindsay Blvd Idaho Falls ID 83402",
    "addr:housenumber":"1490",
    "addr:postcode":"83402",
    "addr:street":"Lindsay Blvd",
    "iso:country":"US",
    "sg:address":"1490 Lindsay Blvd",
    "sg:city":"Idaho Falls",
    "sg:classifiers":[
        {
            "category":"Manufacturing",
            "subcategory":"Metals",
            "type":"Manufacturing & Wholesale Goods"
        }
    ],
    "sg:phone":"+1 208 529 8545",
    "sg:postcode":"83402",
    "sg:province":"ID",
    "sg:tags":[
        "fabricator",
        "sheet"
    ],
    "wof:name":"Delta Industries",
    "wof:placetype":"venue"
},
  "geometry": {"coordinates":[-112.055271,43.508836],"type":"Point"}
}