{
  "type": "Feature",
  "properties": {
    "iso:country":"US",
    "sg:address":"920 Caldwell Blvd",
    "sg:city":"Nampa",
    "sg:classifiers":[
        {
            "category":"Retail",
            "subcategory":"Laundry & Dry Cleaning",
            "type":"Services"
        }
    ],
    "sg:phone":"+1 208 461 4960",
    "sg:postcode":"83651",
    "sg:province":"ID",
    "sg:tags":[
        "cleaners"
    ],
    "wof:name":"Cleaners Express",
    "wof:placetype":"venue"
},
  "geometry": {"coordinates":[-116.592645,43.598476],"type":"Point"}
}