{
  "type": "Feature",
  "properties": {
    "iso:country":"US",
    "sg:address":"1290 Bailey Creek Eight Mile Rd",
    "sg:city":"Soda Springs",
    "sg:classifiers":[
        {
            "category":"Real Estate",
            "subcategory":"Real Estate Agent",
            "type":"Services"
        }
    ],
    "sg:phone":"+1 208 547 0033",
    "sg:postcode":"83276",
    "sg:province":"ID",
    "sg:tags":[
        "inspection"
    ],
    "wof:name":"Home Inspection Svc",
    "wof:placetype":"venue"
},
  "geometry": {"coordinates":[-111.574478,42.603929],"type":"Point"}
}