{
  "type": "Feature",
  "properties": {
    "iso:country":"US",
    "sg:address":"105 S Division St",
    "sg:city":"Kellogg",
    "sg:classifiers":[
        {
            "category":"Personal",
            "subcategory":"Beauty Salon",
            "type":"Services"
        }
    ],
    "sg:phone":"+1 208 783 2731",
    "sg:postcode":"83837",
    "sg:province":"ID",
    "sg:tags":[
        "treatment",
        "skin"
    ],
    "wof:name":"Elements Skin Care Studio",
    "wof:placetype":"venue"
},
  "geometry": {"coordinates":[-116.120829,47.536233],"type":"Point"}
}