{
  "type": "Feature",
  "properties": {
    "iso:country":"US",
    "sg:address":"1604 State Hwy 57",
    "sg:city":"Priest River",
    "sg:classifiers":[
        {
            "category":"Health Services",
            "subcategory":"Health Practitioner",
            "type":"Services"
        }
    ],
    "sg:phone":"+1 208 448 1064",
    "sg:postcode":"83856",
    "sg:province":"ID",
    "sg:tags":[
        "acupuncture"
    ],
    "wof:name":"Rosemary Yocum LLC",
    "wof:placetype":"venue"
},
  "geometry": {"coordinates":[-117.039585,48.177834],"type":"Point"}
}