{
  "type": "Feature",
  "properties": {
    "addr:full":"306 N Jackson St Moscow ID 83843",
    "addr:housenumber":"306",
    "addr:postcode":"83843",
    "addr:street":"N Jackson St",
    "iso:country":"US",
    "sg:address":"306 N Jackson St",
    "sg:city":"Moscow",
    "sg:classifiers":[
        {
            "category":"Personal",
            "subcategory":"Barber",
            "type":"Services"
        }
    ],
    "sg:phone":"+1 208 883 3138",
    "sg:postcode":"83843",
    "sg:province":"ID",
    "wof:name":"Kazumi's Barber Shop",
    "wof:placetype":"venue"
},
  "geometry": {"coordinates":[-117.002708,46.735748],"type":"Point"}
}