{
  "type": "Feature",
  "properties": {
    "iso:country":"US",
    "sg:address":"19 State Hwy 31",
    "sg:city":"Swan Valley",
    "sg:classifiers":[
        {
            "category":"Travel",
            "subcategory":"Hotels & Motels",
            "type":"Entertainment"
        }
    ],
    "sg:phone":"+1 208 483 0411",
    "sg:postcode":"83449",
    "sg:province":"ID",
    "wof:name":"Sleepy J Cabins",
    "wof:placetype":"venue"
},
  "geometry": {"coordinates":[-111.35597300000001,43.505753],"type":"Point"}
}