{
  "type": "Feature",
  "properties": {
    "iso:country":"US",
    "sg:address":"1023 Winther Blvd",
    "sg:city":"Nampa",
    "sg:classifiers":[
        {
            "category":"Building & Trades",
            "subcategory":"Electrical",
            "type":"Services"
        }
    ],
    "sg:phone":"+1 208 467 3478",
    "sg:postcode":"83651",
    "sg:province":"ID",
    "sg:tags":[
        "installation"
    ],
    "wof:name":"Paul Davenport Installation",
    "wof:placetype":"venue"
},
  "geometry": {"coordinates":[-116.596416,43.587145],"type":"Point"}
}