{
  "type": "Feature",
  "properties": {
    "addr:full":"1139 Santa Maria Dr Boise ID 83712",
    "addr:housenumber":"1139",
    "addr:postcode":"83712",
    "addr:street":"Santa Maria Dr",
    "iso:country":"US",
    "sg:address":"1139 Santa Maria Dr",
    "sg:city":"Boise",
    "sg:classifiers":[
        {
            "category":"Professional",
            "subcategory":"Management & Consulting",
            "type":"Services"
        }
    ],
    "sg:phone":"+1 208 384 1532",
    "sg:postcode":"83712",
    "sg:province":"ID",
    "sg:tags":[
        "consultant",
        "business"
    ],
    "wof:name":"Pinnacle & Assoc",
    "wof:placetype":"venue"
},
  "geometry": {"coordinates":[-116.18149200000001,43.615571],"type":"Point"}
}