{
  "type": "Feature",
  "properties": {
    "iso:country":"US",
    "sg:address":"1000 Northwest Blvd",
    "sg:city":"Coeur D Alene",
    "sg:classifiers":[
        {
            "category":"Real Estate",
            "subcategory":"Real Estate Agent",
            "type":"Services"
        }
    ],
    "sg:phone":"+1 208 769 7131",
    "sg:postcode":"83814",
    "sg:province":"ID",
    "wof:name":"Estate Marketing Group",
    "wof:placetype":"venue"
},
  "geometry": {"coordinates":[-116.794915,47.684498],"type":"Point"}
}