{
  "type": "Feature",
  "properties": {
    "iso:country":"US",
    "sg:address":"206 N Arthur Ave",
    "sg:city":"Pocatello",
    "sg:classifiers":[
        {
            "category":"Banks & Credit Unions",
            "subcategory":"Bank",
            "type":"Services"
        }
    ],
    "sg:phone":"+1 208 232 9468",
    "sg:postcode":"83204",
    "sg:province":"ID",
    "sg:tags":[
        "loan"
    ],
    "sg:website":"www.pnhs.org",
    "wof:name":"PNHS Homeownership Ctr",
    "wof:placetype":"venue"
},
  "geometry": {"coordinates":[-112.453275,42.862972],"type":"Point"}
}