{
  "type": "Feature",
  "properties": {
    "iso:country":"US",
    "sg:address":"1471 Shoreline Dr",
    "sg:city":"Boise",
    "sg:classifiers":[
        {
            "category":"Banks & Credit Unions",
            "subcategory":"Bank",
            "type":"Services"
        }
    ],
    "sg:phone":"+1 208 383 3473",
    "sg:postcode":"83702",
    "sg:province":"ID",
    "sg:tags":[
        "loan"
    ],
    "wof:name":"Capital Matrix",
    "wof:placetype":"venue"
},
  "geometry": {"coordinates":[-116.219571,43.616051],"type":"Point"}
}