{
  "type": "Feature",
  "properties": {
    "iso:country":"US",
    "sg:address":"33 S 700 W",
    "sg:city":"Blackfoot",
    "sg:classifiers":[
        {
            "category":"Building & Trades",
            "subcategory":"Construction",
            "type":"Services"
        }
    ],
    "sg:phone":"+1 208 684 5223",
    "sg:postcode":"83221",
    "sg:province":"ID",
    "sg:tags":[
        "general",
        "contractor"
    ],
    "wof:name":"Duane Sanders Construction",
    "wof:placetype":"venue"
},
  "geometry": {"coordinates":[-112.435148,43.191794],"type":"Point"}
}