{
  "type": "Feature",
  "properties": {
    "iso:country":"US",
    "sg:address":"11069 W State St",
    "sg:city":"Star",
    "sg:classifiers":[
        {
            "category":"Building & Trades",
            "subcategory":"Construction",
            "type":"Services"
        }
    ],
    "sg:phone":"+1 208 286 0216",
    "sg:postcode":"83669",
    "sg:province":"ID",
    "sg:tags":[
        "stucco",
        "contractor"
    ],
    "wof:name":"Treasure Valley Rock & Stucco",
    "wof:placetype":"venue"
},
  "geometry": {"coordinates":[-116.490906,43.691927],"type":"Point"}
}