{
  "type": "Feature",
  "properties": {
    "addr:full":"1211 N School St Kuna ID 83634",
    "addr:housenumber":"1211",
    "addr:postcode":"83634",
    "addr:street":"N School St",
    "iso:country":"US",
    "sg:address":"1211 N School St",
    "sg:city":"Kuna",
    "sg:classifiers":[
        {
            "category":"Professional",
            "subcategory":"Management & Consulting",
            "type":"Services"
        }
    ],
    "sg:phone":"+1 208 922 5579",
    "sg:postcode":"83634",
    "sg:province":"ID",
    "sg:tags":[
        "business"
    ],
    "wof:name":"Darrell Summit Consulting",
    "wof:placetype":"venue"
},
  "geometry": {"coordinates":[-116.423693,43.499474],"type":"Point"}
}