{
  "type": "Feature",
  "properties": {
    "iso:country":"US",
    "sg:address":"426 4th St",
    "sg:city":"Hazelton",
    "sg:classifiers":[
        {
            "category":"Freight",
            "type":"Transportation"
        }
    ],
    "sg:phone":"+1 208 829 5930",
    "sg:postcode":"83335",
    "sg:province":"ID",
    "sg:tags":[
        "hauling",
        "trucking"
    ],
    "wof:name":"J & S Trucking Inc",
    "wof:placetype":"venue"
},
  "geometry": {"coordinates":[-114.134328,42.592159],"type":"Point"}
}