{
  "type": "Feature",
  "properties": {
    "iso:country":"US",
    "sg:address":"3538 S Five Mile Rd",
    "sg:city":"Boise",
    "sg:classifiers":[
        {
            "category":"Real Estate",
            "subcategory":"Real Estate Operator",
            "type":"Services"
        }
    ],
    "sg:phone":"+1 208 362 9586",
    "sg:postcode":"83709",
    "sg:province":"ID",
    "sg:tags":[
        "apartment"
    ],
    "wof:name":"Casa Blanca Apartments",
    "wof:placetype":"venue"
},
  "geometry": {"coordinates":[-116.314093,43.571012],"type":"Point"}
}