{
  "type": "Feature",
  "properties": {
    "addr:full":"1102 Arlington Dr Eagle ID 83616",
    "addr:housenumber":"1102",
    "addr:postcode":"83616",
    "addr:street":"Arlington Dr",
    "iso:country":"US",
    "sg:address":"1102 Arlington Dr",
    "sg:city":"Eagle",
    "sg:classifiers":[
        {
            "category":"Professional",
            "subcategory":"Business Services",
            "type":"Services"
        }
    ],
    "sg:phone":"+1 208 939 4561",
    "sg:postcode":"83616",
    "sg:province":"ID",
    "wof:name":"Infinite Solutions",
    "wof:placetype":"venue"
},
  "geometry": {"coordinates":[-116.36064,43.70414],"type":"Point"}
}