{
  "type": "Feature",
  "properties": {
    "iso:country":"US",
    "sg:address":"3597 Grove Ln",
    "sg:city":"Idaho Falls",
    "sg:classifiers":[
        {
            "category":"Health Services",
            "subcategory":"Health Practitioner",
            "type":"Services"
        }
    ],
    "sg:phone":"+1 208 542 2701",
    "sg:postcode":"83404",
    "sg:province":"ID",
    "sg:tags":[
        "therapist",
        "physical"
    ],
    "wof:name":"Earth-Therapy",
    "wof:placetype":"venue"
},
  "geometry": {"coordinates":[-112.018334,43.465636],"type":"Point"}
}