{
  "type": "Feature",
  "properties": {
    "iso:country":"US",
    "sg:address":"1350 Parkway Dr",
    "sg:city":"Blackfoot",
    "sg:classifiers":[
        {
            "category":"Shopping",
            "subcategory":"Florist",
            "type":"Retail Goods"
        }
    ],
    "sg:phone":"+1 208 785 1441",
    "sg:postcode":"83221",
    "sg:province":"ID",
    "wof:name":"Hilary's-Desert Oasis",
    "wof:placetype":"venue"
},
  "geometry": {"coordinates":[-112.36058300000001,43.195424],"type":"Point"}
}