{
  "type": "Feature",
  "properties": {
    "addr:full":"175 W 5th S Rexburg ID 83440",
    "addr:housenumber":"175",
    "addr:postcode":"83440",
    "addr:street":"W 5Th S",
    "iso:country":"US",
    "sg:address":"175 W 5th S",
    "sg:city":"Rexburg",
    "sg:classifiers":[
        {
            "category":"Real Estate",
            "subcategory":"Real Estate Operator",
            "type":"Services"
        }
    ],
    "sg:phone":"+1 208 356 7756",
    "sg:postcode":"83440",
    "sg:province":"ID",
    "sg:tags":[
        "apartment"
    ],
    "wof:name":"Nauvoo House",
    "wof:placetype":"venue"
},
  "geometry": {"coordinates":[-111.788749,43.815514],"type":"Point"}
}