{
  "type": "Feature",
  "properties": {
    "addr:full":"6579 N Bogart Ln Boise ID 83714",
    "addr:housenumber":"6579",
    "addr:postcode":"83714",
    "addr:street":"N Bogart Ln",
    "iso:country":"US",
    "sg:address":"6579 N Bogart Ln",
    "sg:city":"Boise",
    "sg:classifiers":[
        {
            "category":"Professional",
            "subcategory":"Research",
            "type":"Services"
        }
    ],
    "sg:phone":"+1 208 378 0312",
    "sg:postcode":"83714",
    "sg:province":"ID",
    "sg:tags":[
        "development",
        "marketing",
        "product"
    ],
    "wof:name":"C & S Corp",
    "wof:placetype":"venue"
},
  "geometry": {"coordinates":[-116.294259,43.678315],"type":"Point"}
}