{
  "type": "Feature",
  "properties": {
    "iso:country":"US",
    "sg:address":"1220 4th St S",
    "sg:city":"Nampa",
    "sg:classifiers":[
        {
            "category":"Organizations",
            "subcategory":"Religious Organization",
            "type":"Services"
        }
    ],
    "sg:phone":"+1 208 461 4164",
    "sg:postcode":"83651",
    "sg:province":"ID",
    "sg:tags":[
        "church"
    ],
    "wof:name":"LA Luz Del Mundo",
    "wof:placetype":"venue"
},
  "geometry": {"coordinates":[-116.562526,43.576443],"type":"Point"}
}