{
  "type": "Feature",
  "properties": {
    "iso:country":"US",
    "sg:address":"10700 Ustick Rd",
    "sg:city":"Boise",
    "sg:classifiers":[
        {
            "category":"Government",
            "subcategory":"Police Station",
            "type":"Public Place"
        }
    ],
    "sg:phone":"+1 208 327 1792",
    "sg:postcode":"83713",
    "sg:province":"ID",
    "sg:tags":[
        "department"
    ],
    "wof:name":"Boise Police Dept",
    "wof:placetype":"venue"
},
  "geometry": {"coordinates":[-116.317004,43.633919],"type":"Point"}
}