{
  "type": "Feature",
  "properties": {
    "iso:country":"US",
    "sg:address":"410 N Kings Rd",
    "sg:city":"Nampa",
    "sg:classifiers":[
        {
            "category":"Building & Trades",
            "subcategory":"Construction",
            "type":"Services"
        }
    ],
    "sg:phone":"+1 208 466 6494",
    "sg:postcode":"83687",
    "sg:province":"ID",
    "sg:tags":[
        "general",
        "contractor"
    ],
    "wof:name":"Aggregate Construction Inc",
    "wof:placetype":"venue"
},
  "geometry": {"coordinates":[-116.532971,43.590118],"type":"Point"}
}