{
  "type": "Feature",
  "properties": {
    "addr:full":"2805 Stoll Ct Caldwell ID 83607",
    "addr:housenumber":"2805",
    "addr:postcode":"83607",
    "addr:street":"Stoll Ct",
    "iso:country":"US",
    "sg:address":"2805 Stoll Ct",
    "sg:city":"Caldwell",
    "sg:classifiers":[
        {
            "category":"Education",
            "subcategory":"Music School",
            "type":"Public Place"
        },
        {
            "category":"Travel",
            "subcategory":"Hotels & Motels",
            "type":"Entertainment"
        },
        {
            "category":"Social Services",
            "subcategory":"Job Training",
            "type":"Services"
        },
        {
            "category":"Landmark",
            "subcategory":"Tourist Information",
            "type":"Public Place"
        }
    ],
    "sg:phone":"+1 208 459 8367",
    "sg:postcode":"83607",
    "sg:province":"ID",
    "sg:tags":[
        "control",
        "attraction",
        "pollution",
        "air"
    ],
    "wof:name":"Treasure Valley Weatherfone",
    "wof:placetype":"venue"
},
  "geometry": {"coordinates":[-116.664574,43.62307],"type":"Point"}
}