{
  "type": "Feature",
  "properties": {
    "addr:full":"1102 Hill St Kamiah ID 83536",
    "addr:housenumber":"1102",
    "addr:postcode":"83536",
    "addr:street":"Hill St",
    "iso:country":"US",
    "sg:address":"1102 Hill St",
    "sg:city":"Kamiah",
    "sg:classifiers":[
        {
            "category":"Education",
            "subcategory":"School",
            "type":"Public Place"
        }
    ],
    "sg:phone":"+1 208 935 2991",
    "sg:postcode":"83536",
    "sg:province":"ID",
    "wof:name":"Kamiah Superintendent Office",
    "wof:placetype":"venue"
},
  "geometry": {"coordinates":[-116.029398,46.221528],"type":"Point"}
}