{
  "type": "Feature",
  "properties": {
    "iso:country":"US",
    "sg:address":"1600 Yale Ave",
    "sg:city":"Burley",
    "sg:classifiers":[
        {
            "category":"Professional",
            "type":"Services"
        }
    ],
    "sg:phone":"+1 208 878 8875",
    "sg:postcode":"83318",
    "sg:province":"ID",
    "sg:tags":[
        "establishment"
    ],
    "wof:name":"Lafaunce & Lafaunce",
    "wof:placetype":"venue"
},
  "geometry": {"coordinates":[-113.80105,42.53297],"type":"Point"}
}