{
  "type": "Feature",
  "properties": {
    "addr:full":"698 E Whitehall St Meridian ID 83642",
    "addr:housenumber":"698",
    "addr:postcode":"83642",
    "addr:street":"E Whitehall St",
    "iso:country":"US",
    "sg:address":"698 E Whitehall St",
    "sg:city":"Meridian",
    "sg:classifiers":[
        {
            "category":"Professional",
            "type":"Services"
        },
        {
            "category":"Insurance",
            "subcategory":"Insurance Agent",
            "type":"Services"
        }
    ],
    "sg:phone":"+1 208 866 4611",
    "sg:postcode":"83642",
    "sg:province":"ID",
    "sg:tags":[
        "establishment"
    ],
    "wof:name":"Pensions Plus",
    "wof:placetype":"venue"
},
  "geometry": {"coordinates":[-116.385778,43.579769],"type":"Point"}
}