{
  "type": "Feature",
  "properties": {
    "iso:country":"US",
    "sg:address":"118 E State St",
    "sg:city":"Eagle",
    "sg:classifiers":[
        {
            "category":"Museum",
            "type":"Entertainment"
        }
    ],
    "sg:phone":"+1 208 939 5889",
    "sg:postcode":"83616",
    "sg:province":"ID",
    "sg:tags":[
        "gallery"
    ],
    "wof:name":"Ditz Lesile",
    "wof:placetype":"venue"
},
  "geometry": {"coordinates":[-116.352459,43.69526],"type":"Point"}
}