{
  "type": "Feature",
  "properties": {
    "iso:country":"US",
    "sg:address":"450 B St",
    "sg:city":"Idaho Falls",
    "sg:classifiers":[
        {
            "category":"Real Estate",
            "subcategory":"Real Estate Agent",
            "type":"Services"
        }
    ],
    "sg:phone":"+1 208 535 0399",
    "sg:postcode":"83402",
    "sg:province":"ID",
    "wof:name":"Idaho Falls Downtown Dev Corp",
    "wof:placetype":"venue"
},
  "geometry": {"coordinates":[-112.04076999999999,43.493807],"type":"Point"}
}