{
  "type": "Feature",
  "properties": {
    "iso:country":"US",
    "sg:address":"250 S 5th St",
    "sg:city":"Boise",
    "sg:classifiers":[
        {
            "category":"Real Estate",
            "subcategory":"Architect",
            "type":"Services"
        }
    ],
    "sg:phone":"+1 208 343 4635",
    "sg:postcode":"83702",
    "sg:province":"ID",
    "sg:website":"www.cshqa.com",
    "wof:name":"CSHQA A Professional Assn",
    "wof:placetype":"venue"
},
  "geometry": {"coordinates":[-116.201201,43.612562],"type":"Point"}
}