{
  "type": "Feature",
  "properties": {
    "iso:country":"US",
    "sg:address":"2804 E Hill Rd",
    "sg:city":"Eagle",
    "sg:classifiers":[
        {
            "category":"Wholesale",
            "subcategory":"Construction Materials",
            "type":"Manufacturing & Wholesale Goods"
        }
    ],
    "sg:phone":"+1 208 939 0771",
    "sg:postcode":"83616",
    "sg:province":"ID",
    "sg:tags":[
        "sand",
        "gravel"
    ],
    "wof:name":"Prime Earth Inc",
    "wof:placetype":"venue"
},
  "geometry": {"coordinates":[-116.316183,43.692957],"type":"Point"}
}