{
  "type": "Feature",
  "properties": {
    "addr:full":"715 E 3rd St Rupert ID 83350",
    "addr:housenumber":"715",
    "addr:postcode":"83350",
    "addr:street":"E 3Rd St",
    "iso:country":"US",
    "sg:address":"715 E 3rd St",
    "sg:city":"Rupert",
    "sg:classifiers":[
        {
            "category":"Building & Trades",
            "subcategory":"Construction",
            "type":"Services"
        }
    ],
    "sg:phone":"+1 208 436 9594",
    "sg:postcode":"83350",
    "sg:province":"ID",
    "sg:tags":[
        "contractor"
    ],
    "wof:name":"Home Tech & Tile",
    "wof:placetype":"venue"
},
  "geometry": {"coordinates":[-113.65512200000001,42.614365],"type":"Point"}
}