{
  "type": "Feature",
  "properties": {
    "iso:country":"US",
    "sg:address":"16548 Franklin Rd",
    "sg:city":"Nampa",
    "sg:classifiers":[
        {
            "category":"Health Services",
            "subcategory":"Doctor",
            "type":"Services"
        }
    ],
    "sg:phone":"+1 208 461 3070",
    "sg:postcode":"83687",
    "sg:province":"ID",
    "sg:tags":[
        "dentist"
    ],
    "wof:name":"David L Farris DDS",
    "wof:placetype":"venue"
},
  "geometry": {"coordinates":[-116.553076,43.612881],"type":"Point"}
}