{
  "type": "Feature",
  "properties": {
    "iso:country":"US",
    "sg:address":"1351 Mann Creek Rd",
    "sg:city":"Weiser",
    "sg:classifiers":[
        {
            "category":"Building & Trades",
            "subcategory":"Construction",
            "type":"Services"
        }
    ],
    "sg:phone":"+1 208 549 1090",
    "sg:postcode":"83672",
    "sg:province":"ID",
    "sg:tags":[
        "general",
        "contractor"
    ],
    "wof:name":"Else Construction",
    "wof:placetype":"venue"
},
  "geometry": {"coordinates":[-116.867103,44.349858],"type":"Point"}
}