{
  "type": "Feature",
  "properties": {
    "addr:full":"25464 Hop Rd Caldwell ID 83607",
    "addr:housenumber":"25464",
    "addr:postcode":"83607",
    "addr:street":"Hop Rd",
    "iso:country":"US",
    "sg:address":"25464 Hop Rd",
    "sg:city":"Caldwell",
    "sg:phone":"+1 208 459 7214",
    "sg:postcode":"83607",
    "sg:province":"ID",
    "sg:tags":[
        "wheat",
        "farmer"
    ],
    "wof:name":"Robert Hultz",
    "wof:placetype":"venue"
},
  "geometry": {"coordinates":[-116.77274199999999,43.741802],"type":"Point"}
}