{
  "type": "Feature",
  "properties": {
    "iso:country":"US",
    "sg:address":"48 N 740 W",
    "sg:city":"Blackfoot",
    "sg:classifiers":[
        {
            "category":"Home & Garden",
            "subcategory":"Carpets & Floor Coverings",
            "type":"Retail Goods"
        }
    ],
    "sg:phone":"+1 208 684 5368",
    "sg:postcode":"83221",
    "sg:province":"ID",
    "wof:name":"Arens Floor Covering Inc",
    "wof:placetype":"venue"
},
  "geometry": {"coordinates":[-112.442532,43.200704],"type":"Point"}
}