{
  "type": "Feature",
  "properties": {
    "addr:full":"1485 Poleline Rd E Twin Falls ID 83301",
    "addr:housenumber":"1485",
    "addr:postcode":"83301",
    "addr:street":"Poleline Rd E",
    "iso:country":"US",
    "sg:address":"1485 Poleline Rd E",
    "sg:city":"Twin Falls",
    "sg:classifiers":[
        {
            "category":"Restaurant",
            "type":"Food & Drink"
        }
    ],
    "sg:menulink":"http://www.allmenus.com/id/twin-falls/120340-subway/menu/",
    "sg:phone":"+1 208 736 6004",
    "sg:postcode":"83301",
    "sg:province":"ID",
    "sg:tags":[
        "american",
        "sandwich"
    ],
    "wof:name":"Subway",
    "wof:placetype":"venue"
},
  "geometry": {"coordinates":[-114.454701,42.592],"type":"Point"}
}