{
  "type": "Feature",
  "properties": {
    "iso:country":"US",
    "sg:address":"5500 N Pierce Park Ln",
    "sg:city":"Boise",
    "sg:classifiers":[
        {
            "category":"Home & Garden",
            "subcategory":"Garden Supply",
            "type":"Retail Goods"
        }
    ],
    "sg:phone":"+1 208 703 7239",
    "sg:postcode":"83714",
    "sg:province":"ID",
    "sg:tags":[
        "sprinkler"
    ],
    "wof:name":"Baugh Sprinklers & Landscaping",
    "wof:placetype":"venue"
},
  "geometry": {"coordinates":[-116.268415,43.669505],"type":"Point"}
}