{
  "type": "Feature",
  "properties": {
    "addr:full":"342 E 5th St Burley ID 83318",
    "addr:housenumber":"342",
    "addr:postcode":"83318",
    "addr:street":"E 5Th St",
    "iso:country":"US",
    "sg:address":"342 E 5th St",
    "sg:city":"Burley",
    "sg:classifiers":[
        {
            "category":"Shopping",
            "subcategory":"Discount & Variety Stores",
            "type":"Retail Goods"
        }
    ],
    "sg:phone":"+1 208 677 2887",
    "sg:postcode":"83318",
    "sg:province":"ID",
    "wof:name":"Honk's One Dollar Store",
    "wof:placetype":"venue"
},
  "geometry": {"coordinates":[-113.79022000000001,42.54737],"type":"Point"}
}