{
  "type": "Feature",
  "properties": {
    "iso:country":"US",
    "sg:address":"34 E State St",
    "sg:city":"Eagle",
    "sg:classifiers":[
        {
            "category":"Restaurant",
            "type":"Food & Drink"
        }
    ],
    "sg:menulink":"http://www.allmenus.com/id/eagle/3792-smokey-mountain-pizza--pasta/menu/",
    "sg:phone":"+1 208 939 0212",
    "sg:postcode":"83616",
    "sg:province":"ID",
    "sg:tags":[
        "american",
        "pizza"
    ],
    "wof:name":"Smokey Mountain Pizza & Pasta",
    "wof:placetype":"venue"
},
  "geometry": {"coordinates":[-116.353478,43.695193],"type":"Point"}
}