{
  "type": "Feature",
  "properties": {
    "iso:country":"US",
    "sg:address":"4109 Buckboard Way",
    "sg:city":"Boise",
    "sg:classifiers":[
        {
            "category":"Professional",
            "subcategory":"Business Services",
            "type":"Services"
        }
    ],
    "sg:phone":"+1 208 322 6039",
    "sg:postcode":"83713",
    "sg:province":"ID",
    "wof:name":"Wong Enterprises Inc",
    "wof:placetype":"venue"
},
  "geometry": {"coordinates":[-116.315444,43.642576],"type":"Point"}
}