{
  "type": "Feature",
  "properties": {
    "iso:country":"US",
    "sg:address":"355 S Emerson Ave",
    "sg:city":"Shelley",
    "sg:classifiers":[
        {
            "category":"Building & Trades",
            "subcategory":"Construction",
            "type":"Services"
        }
    ],
    "sg:phone":"+1 208 357 3480",
    "sg:postcode":"83274",
    "sg:province":"ID",
    "sg:tags":[
        "grading",
        "contractor"
    ],
    "wof:name":"Bingham County Road Dept",
    "wof:placetype":"venue"
},
  "geometry": {"coordinates":[-112.125766,43.376538],"type":"Point"}
}