{
  "type": "Feature",
  "properties": {
    "addr:full":"401 Evergreen Ln Ketchum ID 83340",
    "addr:housenumber":"401",
    "addr:postcode":"83340",
    "addr:street":"Evergreen Ln",
    "iso:country":"US",
    "sg:address":"401 Evergreen Ln",
    "sg:city":"Ketchum",
    "sg:classifiers":[
        {
            "category":"Building & Trades",
            "subcategory":"Construction",
            "type":"Services"
        }
    ],
    "sg:phone":"+1 208 726 6968",
    "sg:postcode":"83340",
    "sg:province":"ID",
    "sg:tags":[
        "general",
        "contractor"
    ],
    "wof:name":"Hoffman Construction Corp",
    "wof:placetype":"venue"
},
  "geometry": {"coordinates":[-114.372327,43.678332],"type":"Point"}
}