{
  "type": "Feature",
  "properties": {
    "addr:full":"4499 E Ohio Match Rd Hayden Lake ID 83835",
    "addr:housenumber":"4499",
    "addr:postcode":"83835",
    "addr:street":"E Ohio Match Rd",
    "iso:country":"US",
    "sg:address":"4499 E Ohio Match Rd",
    "sg:city":"Hayden Lake",
    "sg:classifiers":[
        {
            "category":"Building & Trades",
            "subcategory":"Construction",
            "type":"Services"
        }
    ],
    "sg:phone":"+1 208 772 2547",
    "sg:postcode":"83835",
    "sg:province":"ID",
    "sg:tags":[
        "general",
        "contractor"
    ],
    "wof:name":"Laminated Building Systems",
    "wof:placetype":"venue"
},
  "geometry": {"coordinates":[-116.72507899999999,47.843715],"type":"Point"}
}