{
  "type": "Feature",
  "properties": {
    "addr:full":"111 Main St Lewiston ID 83501",
    "addr:housenumber":"111",
    "addr:postcode":"83501",
    "addr:street":"Main St",
    "iso:country":"US",
    "sg:address":"111 Main St",
    "sg:city":"Lewiston",
    "sg:classifiers":[
        {
            "category":"Insurance",
            "subcategory":"Insurance Agent",
            "type":"Services"
        }
    ],
    "sg:phone":"+1 208 743 3800",
    "sg:postcode":"83501",
    "sg:province":"ID",
    "wof:name":"Sound Insurance",
    "wof:placetype":"venue"
},
  "geometry": {"coordinates":[-117.030411,46.421637],"type":"Point"}
}