{
  "type": "Feature",
  "properties": {
    "iso:country":"US",
    "sg:address":"56 S State St",
    "sg:city":"Preston",
    "sg:classifiers":[
        {
            "category":"Personal",
            "subcategory":"Beauty Salon",
            "type":"Services"
        }
    ],
    "sg:phone":"+1 208 852 2820",
    "sg:postcode":"83263",
    "sg:province":"ID",
    "wof:name":"Cuttin Curral",
    "wof:placetype":"venue"
},
  "geometry": {"coordinates":[-111.87660099999999,42.095141],"type":"Point"}
}