{
  "type": "Feature",
  "properties": {
    "iso:country":"US",
    "sg:address":"806 Yellowstone Ave",
    "sg:city":"Pocatello",
    "sg:classifiers":[
        {
            "category":"Wholesale",
            "subcategory":"Machinery & Supplies",
            "type":"Manufacturing & Wholesale Goods"
        }
    ],
    "sg:phone":"+1 208 232 2962",
    "sg:postcode":"83201",
    "sg:province":"ID",
    "sg:tags":[
        "salon",
        "beauty"
    ],
    "wof:name":"Peerless Beauty & Barber Supl",
    "wof:placetype":"venue"
},
  "geometry": {"coordinates":[-112.451284,42.889338],"type":"Point"}
}