{
  "type": "Feature",
  "properties": {
    "addr:full":"708 S Daisy St Salmon ID 83467",
    "addr:housenumber":"708",
    "addr:postcode":"83467",
    "addr:street":"S Daisy St",
    "iso:country":"US",
    "sg:address":"708 S Daisy St",
    "sg:city":"Salmon",
    "sg:classifiers":[
        {
            "category":"Home & Garden",
            "subcategory":"Furniture",
            "type":"Retail Goods"
        }
    ],
    "sg:phone":"+1 208 756 4951",
    "sg:postcode":"83467",
    "sg:province":"ID",
    "sg:tags":[
        "builder",
        "custom"
    ],
    "wof:name":"Back Country Western Design",
    "wof:placetype":"venue"
},
  "geometry": {"coordinates":[-113.894139,45.170239],"type":"Point"}
}