{
  "type": "Feature",
  "properties": {
    "iso:country":"US",
    "sg:address":"340 S 1st W",
    "sg:city":"Rexburg",
    "sg:classifiers":[
        {
            "category":"Real Estate",
            "subcategory":"Real Estate Operator",
            "type":"Services"
        }
    ],
    "sg:phone":"+1 208 356 7778",
    "sg:postcode":"83440",
    "sg:province":"ID",
    "sg:tags":[
        "apartment"
    ],
    "wof:name":"Royal Crest Apartments",
    "wof:placetype":"venue"
},
  "geometry": {"coordinates":[-111.786776,43.818995],"type":"Point"}
}