{
  "type": "Feature",
  "properties": {
    "addr:full":"704 Lapwai Rd Lewiston ID 83501",
    "addr:housenumber":"704",
    "addr:postcode":"83501",
    "addr:street":"Lapwai Rd",
    "iso:country":"US",
    "sg:address":"704 Lapwai Rd",
    "sg:city":"Lewiston",
    "sg:classifiers":[
        {
            "category":"Manufacturing",
            "subcategory":"Buildings",
            "type":"Manufacturing & Wholesale Goods"
        },
        {
            "category":"Building & Trades",
            "subcategory":"Construction",
            "type":"Services"
        }
    ],
    "sg:phone":"+1 208 746 6405",
    "sg:postcode":"83501",
    "sg:province":"ID",
    "sg:tags":[
        "industrial",
        "system",
        "specialty",
        "builder",
        "heating",
        "contractor",
        "contractors-commercial",
        "home",
        "air conditioning"
    ],
    "wof:name":"Runsvold Construction",
    "wof:placetype":"venue"
},
  "geometry": {"coordinates":[-116.98135600000001,46.41366],"type":"Point"}
}