{
  "type": "Feature",
  "properties": {
    "addr:full":"1210 NW 16th St Fruitland ID 83619",
    "addr:housenumber":"1210",
    "addr:postcode":"83619",
    "addr:street":"Nw 16Th St",
    "iso:country":"US",
    "sg:address":"1210 NW 16th St",
    "sg:city":"Fruitland",
    "sg:classifiers":[
        {
            "category":"Home & Garden",
            "subcategory":"Mobile Homes",
            "type":"Retail Goods"
        }
    ],
    "sg:phone":"+1 208 452 6810",
    "sg:postcode":"83619",
    "sg:province":"ID",
    "wof:name":"Homes America",
    "wof:placetype":"venue"
},
  "geometry": {"coordinates":[-116.929929,44.025235],"type":"Point"}
}