{
  "type": "Feature",
  "properties": {
    "addr:full":"6560 S Federal Way Boise ID 83716",
    "addr:housenumber":"6560",
    "addr:postcode":"83716",
    "addr:street":"S Federal Way",
    "iso:country":"US",
    "sg:address":"6560 S Federal Way",
    "sg:city":"Boise",
    "sg:classifiers":[
        {
            "category":"Banks & Credit Unions",
            "subcategory":"Bank",
            "type":"Services"
        }
    ],
    "sg:phone":"+1 208 385 0846",
    "sg:postcode":"83716",
    "sg:province":"ID",
    "wof:name":"US Bank",
    "wof:placetype":"venue"
},
  "geometry": {"coordinates":[-116.156074,43.543339],"type":"Point"}
}