{
  "type": "Feature",
  "properties": {
    "addr:full":"906 E Karcher Rd Nampa ID 83687",
    "addr:housenumber":"906",
    "addr:postcode":"83687",
    "addr:street":"E Karcher Rd",
    "iso:country":"US",
    "sg:address":"906 E Karcher Rd",
    "sg:city":"Nampa",
    "sg:classifiers":[
        {
            "category":"Wholesale",
            "subcategory":"Computers",
            "type":"Manufacturing & Wholesale Goods"
        }
    ],
    "sg:phone":"+1 208 893 3434",
    "sg:postcode":"83687",
    "sg:province":"ID",
    "wof:name":"Mpc-G LLC",
    "wof:placetype":"venue"
},
  "geometry": {"coordinates":[-116.56199599999999,43.605142],"type":"Point"}
}