{
  "type": "Feature",
  "properties": {
    "iso:country":"US",
    "sg:address":"5517 W State St",
    "sg:city":"Boise",
    "sg:classifiers":[
        {
            "category":"Food & Beverages",
            "subcategory":"Specialty",
            "type":"Retail Goods"
        },
        {
            "category":"Coffee & Tea",
            "type":"Food & Drink"
        }
    ],
    "sg:menulink":"http://www.allmenus.com/id/boise-city/30242-big-city-coffee/menu/",
    "sg:phone":"+1 208 853 9161",
    "sg:postcode":"83703",
    "sg:province":"ID",
    "sg:tags":[
        "tea",
        "coffee",
        "american"
    ],
    "wof:name":"Big City Coffee",
    "wof:placetype":"venue"
},
  "geometry": {"coordinates":[-116.257091,43.654926],"type":"Point"}
}