{
  "type": "Feature",
  "properties": {
    "iso:country":"US",
    "sg:address":"255 E 20th St",
    "sg:city":"Idaho Falls",
    "sg:classifiers":[
        {
            "category":"Shopping",
            "subcategory":"Gifts & Souvenirs",
            "type":"Retail Goods"
        }
    ],
    "sg:phone":"+1 208 529 4428",
    "sg:postcode":"83404",
    "sg:province":"ID",
    "wof:name":"Tortoise Shell",
    "wof:placetype":"venue"
},
  "geometry": {"coordinates":[-112.029579,43.479954],"type":"Point"}
}