{
  "type": "Feature",
  "properties": {
    "iso:country":"US",
    "sg:address":"2118 W Overland Rd",
    "sg:city":"Boise",
    "sg:classifiers":[
        {
            "category":"Building & Trades",
            "subcategory":"Plumbing",
            "type":"Services"
        }
    ],
    "sg:phone":"+1 208 331 9122",
    "sg:postcode":"83705",
    "sg:province":"ID",
    "sg:tags":[
        "heating",
        "contractor"
    ],
    "wof:name":"Thomas Appliance Heating",
    "wof:placetype":"venue"
},
  "geometry": {"coordinates":[-116.208479,43.589933],"type":"Point"}
}