{
  "type": "Feature",
  "properties": {
    "addr:full":"2672 US Hwy 95 Council ID 83612",
    "addr:housenumber":"2672",
    "addr:postcode":"83612",
    "addr:street":"Us Hwy 95",
    "iso:country":"US",
    "sg:address":"2672 US Hwy 95",
    "sg:city":"Council",
    "sg:classifiers":[
        {
            "category":"Museum",
            "type":"Entertainment"
        }
    ],
    "sg:phone":"+1 208 253 0021",
    "sg:postcode":"83612",
    "sg:province":"ID",
    "sg:tags":[
        "society",
        "historical"
    ],
    "wof:name":"Historic Preservation Servicce",
    "wof:placetype":"venue"
},
  "geometry": {"coordinates":[-116.398595,44.827218],"type":"Point"}
}