{
  "type": "Feature",
  "properties": {
    "iso:country":"US",
    "sg:address":"429 Main St",
    "sg:city":"Marsing",
    "sg:classifiers":[
        {
            "category":"Restaurant",
            "type":"Food & Drink"
        }
    ],
    "sg:phone":"+1 208 896 4555",
    "sg:postcode":"83639",
    "sg:province":"ID",
    "wof:name":"Pepe's Pizza",
    "wof:placetype":"venue"
},
  "geometry": {"coordinates":[-116.810002,43.54525],"type":"Point"}
}