{
  "type": "Feature",
  "properties": {
    "iso:country":"US",
    "sg:address":"510 Roosevelt St",
    "sg:city":"American Falls",
    "sg:classifiers":[
        {
            "category":"Health Services",
            "subcategory":"Hospital",
            "type":"Services"
        }
    ],
    "sg:phone":"+1 208 226 3200",
    "sg:postcode":"83211",
    "sg:province":"ID",
    "wof:name":"Harms Memorial Hospital",
    "wof:placetype":"venue"
},
  "geometry": {"coordinates":[-112.847983,42.781948],"type":"Point"}
}