{
  "type": "Feature",
  "properties": {
    "addr:full":"804 Airport Way Sandpoint ID 83864",
    "addr:housenumber":"804",
    "addr:postcode":"83864",
    "addr:street":"Airport Way",
    "iso:country":"US",
    "sg:address":"804 Airport Way",
    "sg:city":"Sandpoint",
    "sg:classifiers":[
        {
            "category":"Professional",
            "subcategory":"Management & Consulting",
            "type":"Services"
        }
    ],
    "sg:phone":"+1 208 263 4073",
    "sg:postcode":"83864",
    "sg:province":"ID",
    "sg:tags":[
        "consultant",
        "business"
    ],
    "wof:name":"Bonner Business Ctr",
    "wof:placetype":"venue"
},
  "geometry": {"coordinates":[-116.558053,48.294089],"type":"Point"}
}