{
  "type": "Feature",
  "properties": {
    "addr:full":"650 N Idaho St Post Falls ID 83854",
    "addr:housenumber":"650",
    "addr:postcode":"83854",
    "addr:street":"N Idaho St",
    "iso:country":"US",
    "sg:address":"650 N Idaho St",
    "sg:city":"Post Falls",
    "sg:classifiers":[
        {
            "category":"Food & Beverages",
            "subcategory":"Groceries & Convenience Stores",
            "type":"Retail Goods"
        }
    ],
    "sg:phone":"+1 208 773 9103",
    "sg:postcode":"83854",
    "sg:province":"ID",
    "wof:name":"7-Eleven",
    "wof:placetype":"venue"
},
  "geometry": {"coordinates":[-116.93723,47.71456],"type":"Point"}
}