{
  "type": "Feature",
  "properties": {
    "addr:full":"517 N Jefferson St Moscow ID 83843",
    "addr:housenumber":"517",
    "addr:postcode":"83843",
    "addr:street":"N Jefferson St",
    "iso:country":"US",
    "sg:address":"517 N Jefferson St",
    "sg:city":"Moscow",
    "sg:classifiers":[
        {
            "category":"Retail",
            "subcategory":"Portrait Studio",
            "type":"Services"
        }
    ],
    "sg:phone":"+1 208 882 2501",
    "sg:postcode":"83843",
    "sg:province":"ID",
    "sg:tags":[
        "photographer",
        "photo"
    ],
    "sg:website":"www.wendtphoto.com",
    "wof:name":"C Wendt Photographics",
    "wof:placetype":"venue"
},
  "geometry": {"coordinates":[-116.99870900000001,46.739583],"type":"Point"}
}