{
  "type": "Feature",
  "properties": {
    "addr:full":"6086 Emerald St Boise ID 83704",
    "addr:housenumber":"6086",
    "addr:postcode":"83704",
    "addr:street":"Emerald St",
    "iso:country":"US",
    "sg:address":"6086 Emerald St",
    "sg:city":"Boise",
    "sg:classifiers":[
        {
            "category":"Health Services",
            "subcategory":"Doctor",
            "type":"Services"
        }
    ],
    "sg:phone":"+1 208 377 1969",
    "sg:postcode":"83704",
    "sg:province":"ID",
    "sg:tags":[
        "physician",
        "surgeon"
    ],
    "wof:name":"Idx Pathology",
    "wof:placetype":"venue"
},
  "geometry": {"coordinates":[-116.257785,43.611803],"type":"Point"}
}