{
  "type": "Feature",
  "properties": {
    "iso:country":"US",
    "sg:address":"404 N Jefferson St",
    "sg:city":"Moscow",
    "sg:classifiers":[
        {
            "category":"Shopping",
            "subcategory":"Clothing, Apparel, & Fashions",
            "type":"Retail Goods"
        }
    ],
    "sg:phone":"+1 208 882 0231",
    "sg:postcode":"83843",
    "sg:province":"ID",
    "sg:tags":[
        "alteration"
    ],
    "wof:name":"Bobi's Sewing Room",
    "wof:placetype":"venue"
},
  "geometry": {"coordinates":[-116.998587,46.738509],"type":"Point"}
}