{
  "type": "Feature",
  "properties": {
    "iso:country":"US",
    "sg:address":"955 N 10th E",
    "sg:city":"Mountain Home",
    "sg:classifiers":[
        {
            "category":"Professional",
            "subcategory":"Accounting & Tax Preparation",
            "type":"Services"
        }
    ],
    "sg:phone":"+1 208 587 8227",
    "sg:postcode":"83647",
    "sg:province":"ID",
    "wof:name":"Wayne Waters",
    "wof:placetype":"venue"
},
  "geometry": {"coordinates":[-115.687569,43.140031],"type":"Point"}
}