{
  "type": "Feature",
  "properties": {
    "addr:full":"276 S Moonbeam Way Eagle ID 83616",
    "addr:housenumber":"276",
    "addr:postcode":"83616",
    "addr:street":"S Moonbeam Way",
    "iso:country":"US",
    "sg:address":"276 S Moonbeam Way",
    "sg:city":"Eagle",
    "sg:classifiers":[
        {
            "category":"Retail",
            "subcategory":"Portrait Studio",
            "type":"Services"
        }
    ],
    "sg:phone":"+1 208 286 0906",
    "sg:postcode":"83616",
    "sg:province":"ID",
    "sg:tags":[
        "photo"
    ],
    "wof:name":"Porcelain Portraits",
    "wof:placetype":"venue"
},
  "geometry": {"coordinates":[-116.430256,43.690833],"type":"Point"}
}