{
  "type": "Feature",
  "properties": {
    "iso:country":"US",
    "sg:address":"2065 Meadow St",
    "sg:city":"Idaho Falls",
    "sg:classifiers":[
        {
            "category":"Communications",
            "subcategory":"Film & Video Production",
            "type":"Services"
        }
    ],
    "sg:phone":"+1 208 528 2327",
    "sg:postcode":"83401",
    "sg:province":"ID",
    "sg:tags":[
        "taping"
    ],
    "wof:name":"Teton Video Svc",
    "wof:placetype":"venue"
},
  "geometry": {"coordinates":[-111.993318,43.493774],"type":"Point"}
}