{
  "type": "Feature",
  "properties": {
    "addr:full":"110 Main St Dixie ID 83525",
    "addr:housenumber":"110",
    "addr:postcode":"83525",
    "addr:street":"Main St",
    "iso:country":"US",
    "sg:address":"110 Main St",
    "sg:city":"Dixie",
    "sg:classifiers":[
        {
            "category":"Food & Beverages",
            "subcategory":"Groceries & Convenience Stores",
            "type":"Retail Goods"
        }
    ],
    "sg:phone":"+1 208 842 2551",
    "sg:postcode":"83525",
    "sg:province":"ID",
    "wof:name":"Carol & Val's",
    "wof:placetype":"venue"
},
  "geometry": {"coordinates":[-115.45521599999999,45.562604],"type":"Point"}
}