{
  "type": "Feature",
  "properties": {
    "iso:country":"US",
    "sg:address":"83 E State St",
    "sg:city":"Eagle",
    "sg:classifiers":[
        {
            "category":"Bakery",
            "type":"Food & Drink"
        }
    ],
    "sg:menulink":"http://www.allmenus.com/id/eagle/225010-wild-west-bakery-/menu/",
    "sg:phone":"+1 208 939 5677",
    "sg:postcode":"83616",
    "sg:province":"ID",
    "sg:tags":[
        "american",
        "pastry"
    ],
    "wof:name":"Wild West Bakery ",
    "wof:placetype":"venue"
},
  "geometry": {"coordinates":[-116.35324799999999,43.694941],"type":"Point"}
}