{
  "type": "Feature",
  "properties": {
    "addr:full":"2305 Ellis Ave Boise ID 83702",
    "addr:housenumber":"2305",
    "addr:postcode":"83702",
    "addr:street":"Ellis Ave",
    "iso:country":"US",
    "sg:address":"2305 Ellis Ave",
    "sg:city":"Boise",
    "sg:classifiers":[
        {
            "category":"Freight",
            "type":"Transportation"
        }
    ],
    "sg:phone":"+1 208 890 0647",
    "sg:postcode":"83702",
    "sg:province":"ID",
    "sg:tags":[
        "operator",
        "trucking"
    ],
    "wof:name":"Hyland Transportation",
    "wof:placetype":"venue"
},
  "geometry": {"coordinates":[-116.218335,43.629937],"type":"Point"}
}