{
  "type": "Feature",
  "properties": {
    "iso:country":"US",
    "sg:address":"610 S 1st E",
    "sg:city":"Saint Anthony",
    "sg:classifiers":[
        {
            "category":"Manufacturing",
            "subcategory":"Tools & Machinery",
            "type":"Manufacturing & Wholesale Goods"
        }
    ],
    "sg:phone":"+1 208 624 3808",
    "sg:postcode":"83445",
    "sg:province":"ID",
    "sg:tags":[
        "machine",
        "shop"
    ],
    "wof:name":"Parkers Mch & Decorative Stl",
    "wof:placetype":"venue"
},
  "geometry": {"coordinates":[-111.680498,43.960509],"type":"Point"}
}