{
  "type": "Feature",
  "properties": {
    "iso:country":"US",
    "sg:address":"2105 N 32nd St",
    "sg:city":"Boise",
    "sg:classifiers":[
        {
            "category":"Retail",
            "subcategory":"Laundry & Dry Cleaning",
            "type":"Services"
        }
    ],
    "sg:phone":"+1 208 385 9344",
    "sg:postcode":"83703",
    "sg:province":"ID",
    "wof:name":"Steam Pro",
    "wof:placetype":"venue"
},
  "geometry": {"coordinates":[-116.228362,43.639962],"type":"Point"}
}