{
  "type": "Feature",
  "properties": {
    "iso:country":"US",
    "sg:address":"1630 S Eagle Rd Ste 100",
    "sg:city":"Meridian",
    "sg:classifiers":[
        {
            "category":"Restaurant",
            "type":"Food & Drink"
        },
        {
            "category":"Ice Cream",
            "type":"Food & Drink"
        }
    ],
    "sg:phone":"+1 208 888 4205",
    "sg:postcode":"83642",
    "sg:province":"ID",
    "sg:tags":[
        "frozen",
        "dessert"
    ],
    "wof:name":"Tcby",
    "wof:placetype":"venue"
},
  "geometry": {"coordinates":[-116.354506,43.590207],"type":"Point"}
}