{
  "type": "Feature",
  "properties": {
    "iso:country":"US",
    "sg:address":"150 S Arthur Ave",
    "sg:city":"Pocatello",
    "sg:classifiers":[
        {
            "category":"Wholesale",
            "subcategory":"Hardware",
            "type":"Manufacturing & Wholesale Goods"
        }
    ],
    "sg:phone":"+1 208 233 7398",
    "sg:postcode":"83204",
    "sg:province":"ID",
    "sg:tags":[
        "plumbing",
        "fixture",
        "supply"
    ],
    "wof:name":"FNW",
    "wof:placetype":"venue"
},
  "geometry": {"coordinates":[-112.451037,42.861154],"type":"Point"}
}