{
  "type": "Feature",
  "properties": {
    "addr:full":"1020 Caldwell Blvd Nampa ID 83651",
    "addr:housenumber":"1020",
    "addr:postcode":"83651",
    "addr:street":"Caldwell Blvd",
    "iso:country":"US",
    "sg:address":"1020 Caldwell Blvd",
    "sg:city":"Nampa",
    "sg:classifiers":[
        {
            "category":"Banks & Credit Unions",
            "subcategory":"Bank",
            "type":"Services"
        }
    ],
    "sg:phone":"+1 208 466 8958",
    "sg:postcode":"83651",
    "sg:province":"ID",
    "sg:tags":[
        "loan"
    ],
    "wof:name":"Key Bank",
    "wof:placetype":"venue"
},
  "geometry": {"coordinates":[-116.59325,43.598984],"type":"Point"}
}