{
  "type": "Feature",
  "properties": {
    "addr:full":"3528 W Seltice Way Coeur D Alene ID 83814",
    "addr:housenumber":"3528",
    "addr:postcode":"83814",
    "addr:street":"W Seltice Way",
    "iso:country":"US",
    "sg:address":"3528 W Seltice Way",
    "sg:city":"Coeur D Alene",
    "sg:classifiers":[
        {
            "category":"Manufacturing",
            "subcategory":"Wood Products",
            "type":"Manufacturing & Wholesale Goods"
        }
    ],
    "sg:phone":"+1 208 765 0608",
    "sg:postcode":"83814",
    "sg:province":"ID",
    "sg:website":"www.atlaspellets.com",
    "wof:name":"Coeur D'Alene Fiber Fuels Inc",
    "wof:placetype":"venue"
},
  "geometry": {"coordinates":[-116.83393599999999,47.700851],"type":"Point"}
}