{
  "type": "Feature",
  "properties": {
    "iso:country":"US",
    "sg:address":"4155 Yellowstone Ave",
    "sg:city":"Pocatello",
    "sg:classifiers":[
        {
            "category":"Shopping",
            "subcategory":"Clothing, Apparel, & Fashions",
            "type":"Retail Goods"
        }
    ],
    "sg:phone":"+1 208 237 5106",
    "sg:postcode":"83202",
    "sg:province":"ID",
    "sg:tags":[
        "sportswear"
    ],
    "wof:name":"American Eagle Outfitters",
    "wof:placetype":"venue"
},
  "geometry": {"coordinates":[-112.466407,42.908455],"type":"Point"}
}