{
  "type": "Feature",
  "properties": {
    "addr:full":"1052 Lewis Rd Moscow ID 83843",
    "addr:housenumber":"1052",
    "addr:postcode":"83843",
    "addr:street":"Lewis Rd",
    "iso:country":"US",
    "sg:address":"1052 Lewis Rd",
    "sg:city":"Moscow",
    "sg:phone":"+1 208 882 1290",
    "sg:postcode":"83843",
    "sg:province":"ID",
    "sg:tags":[
        "farm",
        "wheat"
    ],
    "wof:name":"Kyle Hawley",
    "wof:placetype":"venue"
},
  "geometry": {"coordinates":[-116.97943100000001,46.802896],"type":"Point"}
}