{
  "type": "Feature",
  "properties": {
    "iso:country":"US",
    "sg:address":"580 US Hwy 30",
    "sg:city":"Soda Springs",
    "sg:classifiers":[
        {
            "category":"Autos & Motor Vehicles",
            "subcategory":"Auto Supplies",
            "type":"Retail Goods"
        }
    ],
    "sg:phone":"+1 208 547 2148",
    "sg:postcode":"83276",
    "sg:province":"ID",
    "sg:tags":[
        "tire"
    ],
    "wof:name":"Denny Lee's Tire Co",
    "wof:placetype":"venue"
},
  "geometry": {"coordinates":[-111.587968,42.654561],"type":"Point"}
}