{
  "type": "Feature",
  "properties": {
    "iso:country":"US",
    "sg:address":"71 Old River Rd",
    "sg:city":"Avery",
    "sg:classifiers":[
        {
            "category":"Bars & Pubs",
            "type":"Food & Drink"
        }
    ],
    "sg:phone":"+1 208 245 3996",
    "sg:postcode":"83864",
    "sg:province":"ID",
    "wof:name":"Avery Trading Post",
    "wof:placetype":"venue"
},
  "geometry": {"coordinates":[-116.401539,48.35355],"type":"Point"}
}