{
  "type": "Feature",
  "properties": {
    "iso:country":"US",
    "sg:address":"8000 S Cole Rd",
    "sg:city":"Boise",
    "sg:classifiers":[
        {
            "category":"Retail",
            "subcategory":"Repair Shop",
            "type":"Services"
        }
    ],
    "sg:phone":"+1 208 362 0599",
    "sg:postcode":"83709",
    "sg:province":"ID",
    "wof:name":"Bill S Field Service",
    "wof:placetype":"venue"
},
  "geometry": {"coordinates":[-116.274089,43.530454],"type":"Point"}
}