{
  "type": "Feature",
  "properties": {
    "addr:full":"106 Clear Creek Canyon Rd Ketchum ID 83340",
    "addr:housenumber":"106",
    "addr:postcode":"83340",
    "addr:street":"Clear Creek Canyon Rd",
    "iso:country":"US",
    "sg:address":"106 Clear Creek Canyon Rd",
    "sg:city":"Ketchum",
    "sg:classifiers":[
        {
            "category":"Retail",
            "subcategory":"Veterinary Services",
            "type":"Services"
        }
    ],
    "sg:phone":"+1 208 726 7777",
    "sg:postcode":"83340",
    "sg:province":"ID",
    "sg:tags":[
        "veterinarian"
    ],
    "sg:website":"www.svanimal.com",
    "wof:name":"Animal Center Sun Valley",
    "wof:placetype":"venue"
},
  "geometry": {"coordinates":[-114.356409,43.638648],"type":"Point"}
}