{
  "type": "Feature",
  "properties": {
    "addr:full":"2700 N Yellowstone Hwy Idaho Falls ID 83401",
    "addr:housenumber":"2700",
    "addr:postcode":"83401",
    "addr:street":"N Yellowstone Hwy",
    "iso:country":"US",
    "sg:address":"2700 N Yellowstone Hwy",
    "sg:city":"Idaho Falls",
    "sg:classifiers":[
        {
            "category":"Autos & Motor Vehicles",
            "subcategory":"Boat Sales",
            "type":"Retail Goods"
        }
    ],
    "sg:phone":"+1 208 552 0622",
    "sg:postcode":"83401",
    "sg:province":"ID",
    "sg:tags":[
        "dealer",
        "sales"
    ],
    "wof:name":"Clackacraft Driftboats",
    "wof:placetype":"venue"
},
  "geometry": {"coordinates":[-111.99893899999999,43.519909],"type":"Point"}
}