{
  "type": "Feature",
  "properties": {
    "iso:country":"US",
    "sg:address":"2528 N Cloverdale Rd",
    "sg:city":"Boise",
    "sg:classifiers":[
        {
            "category":"Home & Garden",
            "subcategory":"Garden Supply",
            "type":"Retail Goods"
        }
    ],
    "sg:phone":"+1 208 375 5262",
    "sg:postcode":"83713",
    "sg:province":"ID",
    "sg:tags":[
        "nurseryman"
    ],
    "wof:name":"Cloverdale Nursery",
    "wof:placetype":"venue"
},
  "geometry": {"coordinates":[-116.334337,43.627772],"type":"Point"}
}