{
  "type": "Feature",
  "properties": {
    "iso:country":"US",
    "sg:address":"196 W Elva St",
    "sg:city":"Idaho Falls",
    "sg:classifiers":[
        {
            "category":"Shopping",
            "type":"Retail Goods"
        }
    ],
    "sg:phone":"+1 208 227 0422",
    "sg:postcode":"83402",
    "sg:province":"ID",
    "sg:tags":[
        "mexican"
    ],
    "wof:name":"LA Reyna Meat Market",
    "wof:placetype":"venue"
},
  "geometry": {"coordinates":[-112.034239,43.503993],"type":"Point"}
}