{
  "type": "Feature",
  "properties": {
    "iso:country":"US",
    "sg:address":"8646 N Rude St",
    "sg:city":"Hayden",
    "sg:classifiers":[
        {
            "category":"Freight",
            "type":"Transportation"
        }
    ],
    "sg:phone":"+1 208 762 9109",
    "sg:postcode":"83835",
    "sg:province":"ID",
    "sg:tags":[
        "operator",
        "local",
        "trucking"
    ],
    "wof:name":"Vannett Trucking",
    "wof:placetype":"venue"
},
  "geometry": {"coordinates":[-116.782231,47.750227],"type":"Point"}
}