{
  "type": "Feature",
  "properties": {
    "addr:full":"413 S 8th St Boise ID 83702",
    "addr:housenumber":"413",
    "addr:postcode":"83702",
    "addr:street":"S 8Th St",
    "iso:country":"US",
    "sg:address":"413 S 8th St",
    "sg:city":"Boise",
    "sg:classifiers":[
        {
            "category":"Banks & Credit Unions",
            "subcategory":"Investment Brokerage",
            "type":"Services"
        }
    ],
    "sg:phone":"+1 208 338 2525",
    "sg:postcode":"83702",
    "sg:province":"ID",
    "sg:tags":[
        "commodity"
    ],
    "wof:name":"Futures West",
    "wof:placetype":"venue"
},
  "geometry": {"coordinates":[-116.206416,43.612703],"type":"Point"}
}