{
  "type": "Feature",
  "properties": {
    "iso:country":"US",
    "sg:address":"2966 S Mayflower Way",
    "sg:city":"Boise",
    "sg:classifiers":[
        {
            "category":"Professional",
            "type":"Services"
        }
    ],
    "sg:phone":"+1 208 562 0438",
    "sg:postcode":"83709",
    "sg:province":"ID",
    "wof:name":"Schweiger Real Estate Services",
    "wof:placetype":"venue"
},
  "geometry": {"coordinates":[-116.33690300000001,43.581121],"type":"Point"}
}