{
  "type": "Feature",
  "properties": {
    "iso:country":"US",
    "sg:address":"457 S 4th W",
    "sg:city":"Rexburg",
    "sg:classifiers":[
        {
            "category":"Real Estate",
            "subcategory":"Real Estate Operator",
            "type":"Services"
        }
    ],
    "sg:phone":"+1 208 356 7700",
    "sg:postcode":"83440",
    "sg:province":"ID",
    "sg:tags":[
        "apartment"
    ],
    "wof:name":"Draper Oaks Apartments",
    "wof:placetype":"venue"
},
  "geometry": {"coordinates":[-111.79516,43.816521],"type":"Point"}
}