{
  "type": "Feature",
  "properties": {
    "iso:country":"US",
    "sg:address":"438 State St",
    "sg:city":"Weiser",
    "sg:classifiers":[
        {
            "category":"Food & Beverages",
            "subcategory":"Specialty",
            "type":"Retail Goods"
        },
        {
            "category":"Restaurant",
            "type":"Food & Drink"
        }
    ],
    "sg:phone":"+1 208 549 3365",
    "sg:postcode":"83672",
    "sg:province":"ID",
    "sg:tags":[
        "eating",
        "bars",
        "espresso"
    ],
    "wof:name":"Huckleberry Coffee Company",
    "wof:placetype":"venue"
},
  "geometry": {"coordinates":[-116.96993399999999,44.245985],"type":"Point"}
}