{
  "type": "Feature",
  "properties": {
    "addr:full":"3648 N 3900 E Hansen ID 83334",
    "addr:housenumber":"3648;3900 e",
    "addr:postcode":"83334",
    "addr:street":"N;Hansen",
    "iso:country":"US",
    "sg:address":"3648 N 3900 E",
    "sg:city":"Hansen",
    "sg:classifiers":[
        {
            "category":"Real Estate",
            "subcategory":"Real Estate Operator",
            "type":"Services"
        }
    ],
    "sg:phone":"+1 208 423 5259",
    "sg:postcode":"83334",
    "sg:province":"ID",
    "sg:tags":[
        "property",
        "lessor"
    ],
    "wof:name":"Clark Bennett",
    "wof:placetype":"venue"
},
  "geometry": {"coordinates":[-114.28622799999999,42.527884],"type":"Point"}
}