{
  "type": "Feature",
  "properties": {
    "iso:country":"US",
    "sg:address":"816 N Whitley Dr",
    "sg:city":"Fruitland",
    "sg:classifiers":[
        {
            "category":"Food & Beverages",
            "subcategory":"Specialty",
            "type":"Retail Goods"
        }
    ],
    "sg:phone":"+1 208 452 5696",
    "sg:postcode":"83619",
    "sg:province":"ID",
    "sg:tags":[
        "bars",
        "espresso"
    ],
    "wof:name":"Moxie Java",
    "wof:placetype":"venue"
},
  "geometry": {"coordinates":[-116.923497,44.01859],"type":"Point"}
}