{
  "type": "Feature",
  "properties": {
    "iso:country":"US",
    "sg:address":"2335 S 1600 E",
    "sg:city":"Gooding",
    "sg:classifiers":[
        {
            "category":"Building & Trades",
            "subcategory":"Plumbing",
            "type":"Services"
        }
    ],
    "sg:phone":"+1 208 934 9441",
    "sg:postcode":"83330",
    "sg:province":"ID",
    "sg:tags":[
        "contractor"
    ],
    "wof:name":"Big Sky Plumbing",
    "wof:placetype":"venue"
},
  "geometry": {"coordinates":[-114.771907,42.860419],"type":"Point"}
}