{
  "type": "Feature",
  "properties": {
    "iso:country":"US",
    "sg:address":"761 Hutchinson Ave",
    "sg:city":"American Falls",
    "sg:classifiers":[
        {
            "category":"Farming",
            "subcategory":"Livestock Farm",
            "type":"Manufacturing & Wholesale Goods"
        }
    ],
    "sg:phone":"+1 208 226 2216",
    "sg:postcode":"83211",
    "sg:province":"ID",
    "sg:tags":[
        "ranch"
    ],
    "wof:name":"Roth Ranches",
    "wof:placetype":"venue"
},
  "geometry": {"coordinates":[-112.855237,42.78044],"type":"Point"}
}