{
  "type": "Feature",
  "properties": {
    "iso:country":"US",
    "sg:address":"13750 Surrey Ln",
    "sg:city":"Nampa",
    "sg:classifiers":[
        {
            "category":"Manufacturing",
            "subcategory":"Food",
            "type":"Manufacturing & Wholesale Goods"
        }
    ],
    "sg:phone":"+1 208 467 1200",
    "sg:postcode":"83686",
    "sg:province":"ID",
    "sg:tags":[
        "winery"
    ],
    "wof:name":"Sawtooth Winery",
    "wof:placetype":"venue"
},
  "geometry": {"coordinates":[-116.667135,43.466508],"type":"Point"}
}