{
  "type": "Feature",
  "properties": {
    "iso:country":"US",
    "sg:address":"4275 E 1400 N",
    "sg:city":"Ashton",
    "sg:classifiers":[
        {
            "category":"Farming",
            "subcategory":"Farm",
            "type":"Manufacturing & Wholesale Goods"
        }
    ],
    "sg:phone":"+1 208 652 3450",
    "sg:postcode":"83420",
    "sg:province":"ID",
    "sg:tags":[
        "crop",
        "general"
    ],
    "wof:name":"Howell Farms Inc",
    "wof:placetype":"venue"
},
  "geometry": {"coordinates":[-111.30177999999999,44.085559],"type":"Point"}
}