{
  "type": "Feature",
  "properties": {
    "iso:country":"US",
    "sg:address":"319 E Main St",
    "sg:city":"Grangeville",
    "sg:classifiers":[
        {
            "category":"Organizations",
            "subcategory":"Religious Organization",
            "type":"Services"
        }
    ],
    "sg:phone":"+1 208 983 2450",
    "sg:postcode":"83530",
    "sg:province":"ID",
    "sg:tags":[
        "church"
    ],
    "wof:name":"Evergreen Assembly Of God",
    "wof:placetype":"venue"
},
  "geometry": {"coordinates":[-116.116274,45.925014],"type":"Point"}
}