{
  "type": "Feature",
  "properties": {
    "iso:country":"US",
    "sg:address":"247 W Washington St",
    "sg:city":"Boise",
    "sg:classifiers":[
        {
            "category":"Health Services",
            "subcategory":"Doctor",
            "type":"Services"
        }
    ],
    "sg:phone":"+1 208 381 2055",
    "sg:postcode":"83702",
    "sg:province":"ID",
    "sg:tags":[
        "clinic"
    ],
    "wof:name":"Mountain States Tumor Inst",
    "wof:placetype":"venue"
},
  "geometry": {"coordinates":[-116.19369500000001,43.616227],"type":"Point"}
}