{
  "type": "Feature",
  "properties": {
    "iso:country":"US",
    "sg:address":"1235 Allen Ln",
    "sg:city":"Emmett",
    "sg:classifiers":[
        {
            "category":"Building & Trades",
            "subcategory":"Plumbing",
            "type":"Services"
        }
    ],
    "sg:phone":"+1 208 365 4257",
    "sg:postcode":"83617",
    "sg:province":"ID",
    "sg:tags":[
        "plumbing",
        "contractor"
    ],
    "wof:name":"Goff's Plumbing Inc",
    "wof:placetype":"venue"
},
  "geometry": {"coordinates":[-116.513502,43.865976],"type":"Point"}
}