{
  "type": "Feature",
  "properties": {
    "addr:full":"5315 N Brookside Ln Boise ID 83714",
    "addr:housenumber":"5315",
    "addr:postcode":"83714",
    "addr:street":"N Brookside Ln",
    "iso:country":"US",
    "sg:address":"5315 N Brookside Ln",
    "sg:city":"Boise",
    "sg:classifiers":[
        {
            "category":"Building & Trades",
            "subcategory":"Construction",
            "type":"Services"
        }
    ],
    "sg:phone":"+1 208 938 5135",
    "sg:postcode":"83714",
    "sg:province":"ID",
    "wof:name":"T C Mac Construction",
    "wof:placetype":"venue"
},
  "geometry": {"coordinates":[-116.30577,43.73559],"type":"Point"}
}