{
  "type": "Feature",
  "properties": {
    "iso:country":"US",
    "sg:address":"323 Oak St",
    "sg:city":"Sandpoint",
    "sg:classifiers":[
        {
            "category":"Restaurant",
            "type":"Food & Drink"
        }
    ],
    "sg:phone":"+1 208 263 6458",
    "sg:postcode":"83864",
    "sg:province":"ID",
    "wof:name":"Pitas Eclectic Kitchen",
    "wof:placetype":"venue"
},
  "geometry": {"coordinates":[-116.550449,48.275009],"type":"Point"}
}