{
  "type": "Feature",
  "properties": {
    "iso:country":"US",
    "sg:address":"337 N 200 E",
    "sg:city":"Blackfoot",
    "sg:classifiers":[
        {
            "category":"Organizations",
            "subcategory":"Religious Organization",
            "type":"Services"
        }
    ],
    "sg:phone":"+1 208 785 1551",
    "sg:postcode":"83221",
    "sg:province":"ID",
    "sg:tags":[
        "church"
    ],
    "wof:name":"Church Of Jesus Christ Of Lds",
    "wof:placetype":"venue"
},
  "geometry": {"coordinates":[-112.257784,43.243932],"type":"Point"}
}