{
  "type": "Feature",
  "properties": {
    "iso:country":"US",
    "sg:address":"1763 N Yellowstone Hwy",
    "sg:city":"Idaho Falls",
    "sg:classifiers":[
        {
            "category":"Real Estate",
            "subcategory":"Real Estate Operator",
            "type":"Services"
        }
    ],
    "sg:phone":"+1 208 528 0558",
    "sg:postcode":"83401",
    "sg:province":"ID",
    "sg:tags":[
        "mall",
        "shopping",
        "center"
    ],
    "wof:name":"Grand Teton Mall",
    "wof:placetype":"venue"
},
  "geometry": {"coordinates":[-112.015666,43.511495],"type":"Point"}
}