{
  "type": "Feature",
  "properties": {
    "iso:country":"US",
    "sg:address":"35 Horizon Dr",
    "sg:city":"Boise",
    "sg:classifiers":[
        {
            "category":"Professional",
            "subcategory":"Business Services",
            "type":"Services"
        }
    ],
    "sg:phone":"+1 208 343 8278",
    "sg:postcode":"83702",
    "sg:province":"ID",
    "wof:name":"Bakedspud Music Studio",
    "wof:placetype":"venue"
},
  "geometry": {"coordinates":[-116.18772800000001,43.624976],"type":"Point"}
}