{
  "type": "Feature",
  "properties": {
    "iso:country":"US",
    "sg:address":"6829 Kaniksu St",
    "sg:city":"Bonners Ferry",
    "sg:classifiers":[
        {
            "category":"Organizations",
            "subcategory":"Religious Organization",
            "type":"Services"
        }
    ],
    "sg:phone":"+1 208 267 5746",
    "sg:postcode":"83805",
    "sg:province":"ID",
    "sg:tags":[
        "church"
    ],
    "wof:name":"Jehovah's Witnesses",
    "wof:placetype":"venue"
},
  "geometry": {"coordinates":[-116.322906,48.702577],"type":"Point"}
}