{
  "type": "Feature",
  "properties": {
    "addr:full":"2395 SW 1st Ave Fruitland ID 83619",
    "addr:housenumber":"2395",
    "addr:postcode":"83619",
    "addr:street":"Sw 1St Ave",
    "iso:country":"US",
    "sg:address":"2395 SW 1st Ave",
    "sg:city":"Fruitland",
    "sg:classifiers":[
        {
            "category":"Shopping",
            "subcategory":"Shoes",
            "type":"Retail Goods"
        }
    ],
    "sg:phone":"+1 208 452 4707",
    "sg:postcode":"83619",
    "sg:province":"ID",
    "sg:tags":[
        "boot"
    ],
    "wof:name":"B C Sales",
    "wof:placetype":"venue"
},
  "geometry": {"coordinates":[-116.899931,43.967254],"type":"Point"}
}