{
  "type": "Feature",
  "properties": {
    "iso:country":"US",
    "sg:address":"2787 US Hwy 95",
    "sg:city":"Cambridge",
    "sg:classifiers":[
        {
            "category":"Organizations",
            "subcategory":"Religious Organization",
            "type":"Services"
        }
    ],
    "sg:phone":"+1 208 257 3374",
    "sg:postcode":"83610",
    "sg:province":"ID",
    "sg:tags":[
        "church"
    ],
    "wof:name":"Seventh-Day Adventist Church",
    "wof:placetype":"venue"
},
  "geometry": {"coordinates":[-116.68833100000001,44.560654],"type":"Point"}
}