{
  "type": "Feature",
  "properties": {
    "addr:full":"1512 12th Ave Rd Nampa ID 83686",
    "addr:housenumber":"1512",
    "addr:postcode":"83686",
    "addr:street":"12Th Ave Rd",
    "iso:country":"US",
    "sg:address":"1512 12th Ave Rd",
    "sg:city":"Nampa",
    "sg:classifiers":[
        {
            "category":"Health Services",
            "subcategory":"Doctor",
            "type":"Services"
        }
    ],
    "sg:phone":"+1 208 466 2661",
    "sg:postcode":"83686",
    "sg:province":"ID",
    "sg:tags":[
        "physician",
        "surgeon"
    ],
    "wof:name":"Diagnostic Pathology Svc Inc",
    "wof:placetype":"venue"
},
  "geometry": {"coordinates":[-116.572687,43.554172],"type":"Point"}
}