{
  "type": "Feature",
  "properties": {
    "iso:country":"US",
    "sg:address":"3757 N Old Hwy 91",
    "sg:city":"Pocatello",
    "sg:classifiers":[
        {
            "category":"Utilities",
            "subcategory":"Refuse",
            "type":"Services"
        }
    ],
    "sg:phone":"+1 208 234 0056",
    "sg:postcode":"83204",
    "sg:province":"ID",
    "sg:tags":[
        "disposal",
        "waste"
    ],
    "wof:name":"PSI Waste Systems",
    "wof:placetype":"venue"
},
  "geometry": {"coordinates":[-112.379333,42.816121],"type":"Point"}
}