{
  "type": "Feature",
  "properties": {
    "iso:country":"US",
    "sg:address":"1150 N 3400 E",
    "sg:city":"Ashton",
    "sg:classifiers":[
        {
            "category":"Utilities",
            "subcategory":"Electric",
            "type":"Services"
        }
    ],
    "sg:phone":"+1 208 652 7431",
    "sg:postcode":"83420",
    "sg:province":"ID",
    "sg:tags":[
        "company"
    ],
    "sg:website":"www.frrec.com",
    "wof:name":"Fall River Rural Electric",
    "wof:placetype":"venue"
},
  "geometry": {"coordinates":[-111.478336,44.050405],"type":"Point"}
}