{
  "type": "Feature",
  "properties": {
    "iso:country":"US",
    "sg:address":"1000 1st St",
    "sg:city":"Mccall",
    "sg:classifiers":[
        {
            "category":"Professional",
            "subcategory":"Advertising",
            "type":"Services"
        }
    ],
    "sg:phone":"+1 208 634 2123",
    "sg:postcode":"83638",
    "sg:province":"ID",
    "wof:name":"Star News",
    "wof:placetype":"venue"
},
  "geometry": {"coordinates":[-116.100853,44.910646],"type":"Point"}
}