{
  "type": "Feature",
  "properties": {
    "iso:country":"US",
    "sg:address":"1507 Madison Ave",
    "sg:city":"Nampa",
    "sg:classifiers":[
        {
            "category":"Building & Trades",
            "subcategory":"Construction",
            "type":"Services"
        }
    ],
    "sg:phone":"+1 208 286 7199",
    "sg:postcode":"83687",
    "sg:province":"ID",
    "sg:tags":[
        "house"
    ],
    "wof:name":"Hannus Construction",
    "wof:placetype":"venue"
},
  "geometry": {"coordinates":[-116.561587,43.594281],"type":"Point"}
}