{
  "type": "Feature",
  "properties": {
    "iso:country":"US",
    "sg:address":"126 6th Ave E",
    "sg:city":"Jerome",
    "sg:classifiers":[
        {
            "category":"Building & Trades",
            "subcategory":"Construction",
            "type":"Services"
        }
    ],
    "sg:phone":"+1 208 324 5398",
    "sg:postcode":"83338",
    "sg:province":"ID",
    "sg:tags":[
        "general",
        "contractor"
    ],
    "wof:name":"Brian Bartlett Construction",
    "wof:placetype":"venue"
},
  "geometry": {"coordinates":[-114.518118,42.730003],"type":"Point"}
}