{
  "type": "Feature",
  "properties": {
    "iso:country":"US",
    "sg:address":"300 S Straughan Ave",
    "sg:city":"Boise",
    "sg:classifiers":[
        {
            "category":"Real Estate",
            "subcategory":"Real Estate Operator",
            "type":"Services"
        }
    ],
    "sg:phone":"+1 208 342 6061",
    "sg:postcode":"83712",
    "sg:province":"ID",
    "sg:tags":[
        "apartment"
    ],
    "wof:name":"Cambridge Dorchester",
    "wof:placetype":"venue"
},
  "geometry": {"coordinates":[-116.18822299999999,43.606452],"type":"Point"}
}