{
  "type": "Feature",
  "properties": {
    "iso:country":"US",
    "sg:address":"1305 9th St",
    "sg:city":"Idaho Falls",
    "sg:classifiers":[
        {
            "category":"Education",
            "subcategory":"School",
            "type":"Public Place"
        }
    ],
    "sg:phone":"+1 208 525 7642",
    "sg:postcode":"83404",
    "sg:province":"ID",
    "wof:name":"Linden Park Elementary School",
    "wof:placetype":"venue"
},
  "geometry": {"coordinates":[-112.008368,43.489769],"type":"Point"}
}