{
  "type": "Feature",
  "properties": {
    "addr:full":"1875 N 4000 W Dayton ID 83232",
    "addr:housenumber":"1875",
    "addr:postcode":"83232",
    "addr:street":"N 4000 W",
    "iso:country":"US",
    "sg:address":"1875 N 4000 W",
    "sg:city":"Dayton",
    "sg:classifiers":[
        {
            "category":"Building & Trades",
            "subcategory":"Construction",
            "type":"Services"
        }
    ],
    "sg:phone":"+1 208 747 3642",
    "sg:postcode":"83232",
    "sg:province":"ID",
    "sg:tags":[
        "house"
    ],
    "wof:name":"M & M Homes LLC",
    "wof:placetype":"venue"
},
  "geometry": {"coordinates":[-111.973786,42.128698],"type":"Point"}
}