{
  "type": "Feature",
  "properties": {
    "addr:full":"785 S Progress Ave Meridian ID 83642",
    "addr:housenumber":"785",
    "addr:postcode":"83642",
    "addr:street":"S Progress Ave",
    "iso:country":"US",
    "sg:address":"785 S Progress Ave",
    "sg:city":"Meridian",
    "sg:classifiers":[
        {
            "category":"Restaurant",
            "type":"Food & Drink"
        }
    ],
    "sg:menulink":"http://www.allmenus.com/id/boise-city/235345-taco-time/menu/",
    "sg:phone":"+1 208 887 1973",
    "sg:postcode":"83642",
    "sg:province":"ID",
    "sg:tags":[
        "american",
        "mexican",
        "tex-mex"
    ],
    "wof:name":"Taco Time",
    "wof:placetype":"venue"
},
  "geometry": {"coordinates":[-116.391947,43.597536],"type":"Point"}
}