{
  "type": "Feature",
  "properties": {
    "iso:country":"US",
    "sg:address":"36004 Hwy 41",
    "sg:city":"Old Town",
    "sg:classifiers":[
        {
            "category":"Manufacturing",
            "subcategory":"Lumber",
            "type":"Manufacturing & Wholesale Goods"
        }
    ],
    "sg:phone":"+1 208 437 4196",
    "sg:postcode":"83822",
    "sg:province":"ID",
    "sg:tags":[
        "logging",
        "contractor"
    ],
    "wof:name":"Was Logging",
    "wof:placetype":"venue"
},
  "geometry": {"coordinates":[-117.022804,48.147548],"type":"Point"}
}