{
  "type": "Feature",
  "properties": {
    "iso:country":"US",
    "sg:address":"1448 W Broadway St",
    "sg:city":"Idaho Falls",
    "sg:classifiers":[
        {
            "category":"Travel",
            "subcategory":"Hotels & Motels",
            "type":"Entertainment"
        }
    ],
    "sg:phone":"+1 208 522 0112",
    "sg:postcode":"83402",
    "sg:province":"ID",
    "wof:name":"Motel 6",
    "wof:placetype":"venue"
},
  "geometry": {"coordinates":[-112.05653100000001,43.49684],"type":"Point"}
}