{
  "type": "Feature",
  "properties": {
    "addr:full":"2822 S Monitor Ave Boise ID 83709",
    "addr:housenumber":"2822",
    "addr:postcode":"83709",
    "addr:street":"S Monitor Ave",
    "iso:country":"US",
    "sg:address":"2822 S Monitor Ave",
    "sg:city":"Boise",
    "sg:classifiers":[
        {
            "category":"Building & Trades",
            "subcategory":"Construction",
            "type":"Services"
        }
    ],
    "sg:phone":"+1 208 362 5340",
    "sg:postcode":"83709",
    "sg:province":"ID",
    "sg:tags":[
        "hanging",
        "contractor"
    ],
    "wof:name":"Jnb Painting Inc",
    "wof:placetype":"venue"
},
  "geometry": {"coordinates":[-116.308148,43.577185],"type":"Point"}
}