{
  "type": "Feature",
  "properties": {
    "addr:full":"191 Syringa Ln Ketchum ID 83340",
    "addr:housenumber":"191",
    "addr:postcode":"83340",
    "addr:street":"Syringa Ln",
    "iso:country":"US",
    "sg:address":"191 Syringa Ln",
    "sg:city":"Ketchum",
    "sg:classifiers":[
        {
            "category":"Professional",
            "subcategory":"Art Services",
            "type":"Services"
        }
    ],
    "sg:phone":"+1 208 726 1113",
    "sg:postcode":"83340",
    "sg:province":"ID",
    "sg:tags":[
        "photographer"
    ],
    "wof:name":"KIRK Anderson Photographer",
    "wof:placetype":"venue"
},
  "geometry": {"coordinates":[-114.38486399999999,43.717538],"type":"Point"}
}