{
  "type": "Feature",
  "properties": {
    "iso:country":"US",
    "sg:address":"100 N 4th St E",
    "sg:city":"Homedale",
    "sg:classifiers":[
        {
            "category":"Building & Trades",
            "subcategory":"Electrical",
            "type":"Services"
        }
    ],
    "sg:phone":"+1 208 859 8849",
    "sg:postcode":"83628",
    "sg:province":"ID",
    "sg:tags":[
        "satellite",
        "install"
    ],
    "wof:name":"C & D Satellite",
    "wof:placetype":"venue"
},
  "geometry": {"coordinates":[-116.92727499999999,43.618711],"type":"Point"}
}