{
  "type": "Feature",
  "properties": {
    "iso:country":"US",
    "sg:address":"4440 S Yellowstone Hwy",
    "sg:city":"Idaho Falls",
    "sg:classifiers":[
        {
            "category":"Wholesale",
            "subcategory":"Machinery & Supplies",
            "type":"Manufacturing & Wholesale Goods"
        }
    ],
    "sg:phone":"+1 208 522 3703",
    "sg:postcode":"83402",
    "sg:province":"ID",
    "sg:tags":[
        "equipment",
        "irrigation",
        "system"
    ],
    "wof:name":"Advanced Irrigation Inc",
    "wof:placetype":"venue"
},
  "geometry": {"coordinates":[-112.06172599999999,43.461373],"type":"Point"}
}