{
  "type": "Feature",
  "properties": {
    "addr:full":"1615 Eldridge Ave Twin Falls ID 83301",
    "addr:housenumber":"1615",
    "addr:postcode":"83301",
    "addr:street":"Eldridge Ave",
    "iso:country":"US",
    "sg:address":"1615 Eldridge Ave",
    "sg:city":"Twin Falls",
    "sg:classifiers":[
        {
            "category":"Manufacturing",
            "subcategory":"Wood Products",
            "type":"Manufacturing & Wholesale Goods"
        },
        {
            "category":"Home & Garden",
            "subcategory":"Furniture",
            "type":"Retail Goods"
        }
    ],
    "sg:phone":"+1 208 733 8644",
    "sg:postcode":"83301",
    "sg:province":"ID",
    "sg:tags":[
        "mfg",
        "cabinet"
    ],
    "wof:name":"Superior Woodworking",
    "wof:placetype":"venue"
},
  "geometry": {"coordinates":[-114.45383,42.541381],"type":"Point"}
}