{
  "type": "Feature",
  "properties": {
    "addr:full":"11990 W Armga Dr Boise ID 83709",
    "addr:housenumber":"11990",
    "addr:postcode":"83709",
    "addr:street":"W Armga Dr",
    "iso:country":"US",
    "sg:address":"11990 W Armga Dr",
    "sg:city":"Boise",
    "sg:classifiers":[
        {
            "category":"Building & Trades",
            "subcategory":"Equipment Rental",
            "type":"Services"
        }
    ],
    "sg:phone":"+1 208 375 4913",
    "sg:postcode":"83709",
    "sg:province":"ID",
    "wof:name":"Sophies Snacks",
    "wof:placetype":"venue"
},
  "geometry": {"coordinates":[-116.33064400000001,43.588973],"type":"Point"}
}