{
  "type": "Feature",
  "properties": {
    "iso:country":"US",
    "sg:address":"13275 N 55th E",
    "sg:city":"Idaho Falls",
    "sg:classifiers":[
        {
            "category":"Building & Trades",
            "subcategory":"Construction",
            "type":"Services"
        }
    ],
    "sg:phone":"+1 208 524 4908",
    "sg:postcode":"83401",
    "sg:province":"ID",
    "sg:tags":[
        "plastering",
        "contractor"
    ],
    "wof:name":"DAVIS Plastering Inc",
    "wof:placetype":"venue"
},
  "geometry": {"coordinates":[-111.92388099999999,43.612255],"type":"Point"}
}