{
  "type": "Feature",
  "properties": {
    "iso:country":"US",
    "sg:address":"1615 N 13th St",
    "sg:city":"Boise",
    "sg:classifiers":[
        {
            "category":"Shopping",
            "subcategory":"Crafts & Fabrics",
            "type":"Retail Goods"
        }
    ],
    "sg:phone":"+1 208 344 4066",
    "sg:postcode":"83702",
    "sg:province":"ID",
    "sg:tags":[
        "sewing"
    ],
    "wof:name":"Fabricworks",
    "wof:placetype":"venue"
},
  "geometry": {"coordinates":[-116.203434,43.630973],"type":"Point"}
}