{
  "type": "Feature",
  "properties": {
    "addr:full":"107 N Main St Payette ID 83661",
    "addr:housenumber":"107",
    "addr:postcode":"83661",
    "addr:street":"N Main St",
    "iso:country":"US",
    "sg:address":"107 N Main St",
    "sg:city":"Payette",
    "sg:classifiers":[
        {
            "category":"Restaurant",
            "type":"Food & Drink"
        }
    ],
    "sg:phone":"+1 208 642 3567",
    "sg:postcode":"83661",
    "sg:province":"ID",
    "wof:name":"Mandarin Restaurant",
    "wof:placetype":"venue"
},
  "geometry": {"coordinates":[-116.93512,44.07696],"type":"Point"}
}