{
  "type": "Feature",
  "properties": {
    "iso:country":"US",
    "sg:address":"1213 Burley Ave",
    "sg:city":"Buhl",
    "sg:classifiers":[
        {
            "category":"Professional",
            "type":"Services"
        }
    ],
    "sg:phone":"+1 208 543 4726",
    "sg:postcode":"83316",
    "sg:province":"ID",
    "sg:tags":[
        "establishment"
    ],
    "wof:name":"Larry Sisson Inc",
    "wof:placetype":"venue"
},
  "geometry": {"coordinates":[-114.76375299999999,42.593345],"type":"Point"}
}