{
  "type": "Feature",
  "properties": {
    "iso:country":"US",
    "sg:address":"2303 N Locust Grove Rd",
    "sg:city":"Kuna",
    "sg:phone":"+1 208 922 4472",
    "sg:postcode":"83634",
    "sg:province":"ID",
    "sg:tags":[
        "beef",
        "farm",
        "crop",
        "field",
        "cattle",
        "feedlot"
    ],
    "wof:name":"Roger Stagg",
    "wof:placetype":"venue"
},
  "geometry": {"coordinates":[-116.37437199999999,43.509187],"type":"Point"}
}