{
  "type": "Feature",
  "properties": {
    "addr:full":"4567 Cavendish Rd Lenore ID 83541",
    "addr:housenumber":"4567",
    "addr:postcode":"83541",
    "addr:street":"Cavendish Rd",
    "iso:country":"US",
    "sg:address":"4567 Cavendish Rd",
    "sg:city":"Lenore",
    "sg:classifiers":[
        {
            "category":"Building & Trades",
            "subcategory":"Construction",
            "type":"Services"
        }
    ],
    "sg:phone":"+1 208 476 7484",
    "sg:postcode":"83541",
    "sg:province":"ID",
    "sg:tags":[
        "carpentry",
        "contractor"
    ],
    "wof:name":"Vital Existence",
    "wof:placetype":"venue"
},
  "geometry": {"coordinates":[-116.42797,46.518162],"type":"Point"}
}