{
  "type": "Feature",
  "properties": {
    "addr:full":"7509 Camas St Boise ID 83709",
    "addr:housenumber":"7509",
    "addr:postcode":"83709",
    "addr:street":"Camas St",
    "iso:country":"US",
    "sg:address":"7509 Camas St",
    "sg:city":"Boise",
    "sg:classifiers":[
        {
            "category":"Social Services",
            "subcategory":"Child Care",
            "type":"Services"
        }
    ],
    "sg:phone":"+1 208 376 3961",
    "sg:postcode":"83709",
    "sg:province":"ID",
    "wof:name":"Nina-Belles Playhouse",
    "wof:placetype":"venue"
},
  "geometry": {"coordinates":[-116.276535,43.596458],"type":"Point"}
}