{
  "type": "Feature",
  "properties": {
    "addr:full":"3441 US Hwy 95 Homedale ID 83610",
    "addr:housenumber":"3441",
    "addr:postcode":"83610",
    "addr:street":"Us Hwy 95",
    "iso:country":"US",
    "sg:address":"3441 US Hwy 95",
    "sg:city":"Homedale",
    "sg:classifiers":[
        {
            "category":"Autos & Motor Vehicles",
            "subcategory":"Automobile Sales",
            "type":"Retail Goods"
        }
    ],
    "sg:phone":"+1 208 337 5040",
    "sg:postcode":"83610",
    "sg:province":"ID",
    "sg:tags":[
        "car",
        "dealer"
    ],
    "wof:name":"Heart Land Car Co",
    "wof:placetype":"venue"
},
  "geometry": {"coordinates":[-116.539112,44.57586],"type":"Point"}
}