{
  "type": "Feature",
  "properties": {
    "addr:full":"991 E Best Ave Coeur D Alene ID 83814",
    "addr:housenumber":"991",
    "addr:postcode":"83814",
    "addr:street":"E Best Ave",
    "iso:country":"US",
    "sg:address":"991 E Best Ave",
    "sg:city":"Coeur D Alene",
    "sg:classifiers":[
        {
            "category":"Professional",
            "subcategory":"Business Services",
            "type":"Services"
        }
    ],
    "sg:phone":"+1 208 664 3216",
    "sg:postcode":"83814",
    "sg:province":"ID",
    "sg:tags":[
        "water",
        "treatment"
    ],
    "wof:name":"Culligan Water Conditioning",
    "wof:placetype":"venue"
},
  "geometry": {"coordinates":[-116.772487,47.700822],"type":"Point"}
}