{
  "type": "Feature",
  "properties": {
    "iso:country":"US",
    "sg:address":"1460 Caldwell Blvd",
    "sg:city":"Nampa",
    "sg:classifiers":[
        {
            "category":"Banks & Credit Unions",
            "subcategory":"Bank",
            "type":"Services"
        }
    ],
    "sg:phone":"+1 208 467 6591",
    "sg:postcode":"83651",
    "sg:province":"ID",
    "wof:name":"Bank Of America",
    "wof:placetype":"venue"
},
  "geometry": {"coordinates":[-116.59862699999999,43.602821],"type":"Point"}
}