{
  "type": "Feature",
  "properties": {
    "addr:full":"220 12th Ave S Nampa ID 83651",
    "addr:housenumber":"220",
    "addr:postcode":"83651",
    "addr:street":"12Th Ave S",
    "iso:country":"US",
    "sg:address":"220 12th Ave S",
    "sg:city":"Nampa",
    "sg:classifiers":[
        {
            "category":"Shopping",
            "subcategory":"Bicycles & Sporting Goods",
            "type":"Retail Goods"
        }
    ],
    "sg:phone":"+1 208 466 3647",
    "sg:postcode":"83651",
    "sg:province":"ID",
    "wof:name":"Cafferty's Cyclery",
    "wof:placetype":"venue"
},
  "geometry": {"coordinates":[-116.560802,43.577857],"type":"Point"}
}