{
  "type": "Feature",
  "properties": {
    "iso:country":"US",
    "sg:address":"220 12th Ave S",
    "sg:city":"Nampa",
    "sg:classifiers":[
        {
            "category":"Shopping",
            "subcategory":"Bicycles & Sporting Goods",
            "type":"Retail Goods"
        }
    ],
    "sg:phone":"+1 208 466 3647",
    "sg:postcode":"83651",
    "sg:province":"ID",
    "wof:name":"Cafferty's Cyclery",
    "wof:placetype":"venue"
},
  "geometry": {"coordinates":[-116.560802,43.577857],"type":"Point"}
}