{
  "type": "Feature",
  "properties": {
    "iso:country":"US",
    "sg:address":"31301 Red Top Rd",
    "sg:city":"Wilder",
    "sg:classifiers":[
        {
            "category":"Farming",
            "subcategory":"Farm & Veterinary Services",
            "type":"Manufacturing & Wholesale Goods"
        }
    ],
    "sg:phone":"+1 208 482 7449",
    "sg:postcode":"83676",
    "sg:province":"ID",
    "sg:tags":[
        "livestock"
    ],
    "wof:name":"Darwin Schweiter",
    "wof:placetype":"venue"
},
  "geometry": {"coordinates":[-117.016054,43.694109],"type":"Point"}
}