{
  "type": "Feature",
  "properties": {
    "iso:country":"US",
    "sg:address":"14838 Indiana Ave",
    "sg:city":"Nampa",
    "sg:classifiers":[
        {
            "category":"Manufacturing",
            "subcategory":"Tools & Machinery",
            "type":"Manufacturing & Wholesale Goods"
        }
    ],
    "sg:phone":"+1 208 467 2640",
    "sg:postcode":"83651",
    "sg:province":"ID",
    "sg:tags":[
        "machine",
        "shop"
    ],
    "wof:name":"Swenson's Machine & Mfg",
    "wof:placetype":"venue"
},
  "geometry": {"coordinates":[-116.672865,43.587609],"type":"Point"}
}