{
  "type": "Feature",
  "properties": {
    "iso:country":"US",
    "sg:address":"519 E Fairview Ave",
    "sg:city":"Meridian",
    "sg:classifiers":[
        {
            "category":"Banks & Credit Unions",
            "subcategory":"Bank",
            "type":"Services"
        }
    ],
    "sg:phone":"+1 208 884 2104",
    "sg:postcode":"83642",
    "sg:province":"ID",
    "sg:tags":[
        "state"
    ],
    "wof:name":"Washington Mutual",
    "wof:placetype":"venue"
},
  "geometry": {"coordinates":[-116.38753800000001,43.619334],"type":"Point"}
}