{
  "type": "Feature",
  "properties": {
    "iso:country":"US",
    "sg:address":"308 6th St",
    "sg:city":"Wallace",
    "sg:classifiers":[
        {
            "category":"Bars & Pubs",
            "type":"Food & Drink"
        }
    ],
    "sg:phone":"+1 208 556 5408",
    "sg:postcode":"83873",
    "sg:province":"ID",
    "sg:tags":[
        "lounge",
        "cocktail"
    ],
    "wof:name":"Sweets Lounge Inc",
    "wof:placetype":"venue"
},
  "geometry": {"coordinates":[-115.92402,47.473179],"type":"Point"}
}