{
  "type": "Feature",
  "properties": {
    "iso:country":"US",
    "sg:address":"618 D St Suite B",
    "sg:city":"Lewiston",
    "sg:classifiers":[
        {
            "category":"Insurance",
            "subcategory":"Insurance Agent",
            "type":"Services"
        },
        {
            "category":"Insurance",
            "subcategory":"Hazard Insurance",
            "type":"Services"
        },
        {
            "category":"Insurance",
            "subcategory":"Health Insurance",
            "type":"Services"
        }
    ],
    "sg:phone":"+1 208 743 5441",
    "sg:postcode":"83501",
    "sg:province":"ID",
    "sg:tags":[
        "auto"
    ],
    "wof:name":"Al Reagan Insurance & Investments LUTCF",
    "wof:placetype":"venue"
},
  "geometry": {"coordinates":[-117.025666,46.421929],"type":"Point"}
}