{
  "type": "Feature",
  "properties": {
    "iso:country":"US",
    "sg:address":"5621 W Fairview Ave",
    "sg:city":"Boise",
    "sg:classifiers":[
        {
            "category":"Home & Garden",
            "subcategory":"Furniture",
            "type":"Retail Goods"
        }
    ],
    "sg:phone":"+1 208 322 9292",
    "sg:postcode":"83706",
    "sg:province":"ID",
    "sg:website":"www.morfurnitures.com",
    "wof:name":"Mor Furniture For Less",
    "wof:placetype":"venue"
},
  "geometry": {"coordinates":[-116.252175,43.618973],"type":"Point"}
}