{
  "type": "Feature",
  "properties": {
    "iso:country":"US",
    "sg:address":"401 W North St",
    "sg:city":"Grangeville",
    "sg:classifiers":[
        {
            "category":"Professional",
            "subcategory":"Lawyer & Legal Services",
            "type":"Services"
        }
    ],
    "sg:phone":"+1 208 983 2310",
    "sg:postcode":"83530",
    "sg:province":"ID",
    "sg:tags":[
        "attorney"
    ],
    "wof:name":"Dennis L Albers",
    "wof:placetype":"venue"
},
  "geometry": {"coordinates":[-116.124047,45.927476],"type":"Point"}
}