{
  "type": "Feature",
  "properties": {
    "iso:country":"US",
    "sg:address":"297 S Wooddale Ave",
    "sg:city":"Eagle",
    "sg:classifiers":[
        {
            "category":"Building & Trades",
            "subcategory":"Construction",
            "type":"Services"
        }
    ],
    "sg:phone":"+1 208 629 3754",
    "sg:postcode":"83616",
    "sg:province":"ID",
    "sg:tags":[
        "roofing",
        "contractor"
    ],
    "wof:name":"Tip Top Roofing",
    "wof:placetype":"venue"
},
  "geometry": {"coordinates":[-116.321191,43.692069],"type":"Point"}
}