{
  "type": "Feature",
  "properties": {
    "iso:country":"US",
    "sg:address":"19879 Lonkey Ln",
    "sg:city":"Caldwell",
    "sg:phone":"+1 208 454 2918",
    "sg:postcode":"83607",
    "sg:province":"ID",
    "sg:tags":[
        "farm",
        "corn"
    ],
    "wof:name":"Talkington Merle",
    "wof:placetype":"venue"
},
  "geometry": {"coordinates":[-116.78960600000001,43.62478],"type":"Point"}
}