{
  "type": "Feature",
  "properties": {
    "iso:country":"US",
    "sg:address":"220 6th St",
    "sg:city":"Wallace",
    "sg:classifiers":[
        {
            "category":"Restaurant",
            "type":"Food & Drink"
        }
    ],
    "sg:phone":"+1 208 753 3071",
    "sg:postcode":"83873",
    "sg:province":"ID",
    "wof:name":"Albi's Steak House & Lounge",
    "wof:placetype":"venue"
},
  "geometry": {"coordinates":[-115.924022,47.473545],"type":"Point"}
}