{
  "type": "Feature",
  "properties": {
    "iso:country":"US",
    "sg:address":"5764 Eden St",
    "sg:city":"Chubbuck",
    "sg:classifiers":[
        {
            "category":"Insurance",
            "subcategory":"Insurance Agent",
            "type":"Services"
        }
    ],
    "sg:phone":"+1 208 232 1498",
    "sg:postcode":"83202",
    "sg:province":"ID",
    "wof:name":"Richard Rommel Insurance",
    "wof:placetype":"venue"
},
  "geometry": {"coordinates":[-112.46944000000001,42.937604],"type":"Point"}
}