{
  "type": "Feature",
  "properties": {
    "iso:country":"US",
    "sg:address":"14334 W Promise Ln",
    "sg:city":"Pocatello",
    "sg:classifiers":[
        {
            "category":"Building & Trades",
            "subcategory":"Construction",
            "type":"Services"
        }
    ],
    "sg:phone":"+1 208 238 1009",
    "sg:postcode":"83202",
    "sg:province":"ID",
    "sg:tags":[
        "contractor"
    ],
    "wof:name":"Springsteed Roofing",
    "wof:placetype":"venue"
},
  "geometry": {"coordinates":[-112.502365,42.931415],"type":"Point"}
}