{
  "type": "Feature",
  "properties": {
    "iso:country":"US",
    "sg:address":"1140 Science Center Dr",
    "sg:city":"Idaho Falls",
    "sg:classifiers":[
        {
            "category":"Health Services",
            "subcategory":"Nursing And Care Facility",
            "type":"Services"
        }
    ],
    "sg:phone":"+1 208 542 6856",
    "sg:postcode":"83402",
    "sg:province":"ID",
    "sg:tags":[
        "home",
        "convalescent"
    ],
    "wof:name":"Beehive Homes Of Idaho Falls",
    "wof:placetype":"venue"
},
  "geometry": {"coordinates":[-112.046297,43.514959],"type":"Point"}
}