{
  "type": "Feature",
  "properties": {
    "iso:country":"US",
    "sg:address":"725 Vista Ave",
    "sg:city":"Boise",
    "sg:classifiers":[
        {
            "category":"Shopping",
            "subcategory":"Tobacco",
            "type":"Retail Goods"
        }
    ],
    "sg:phone":"+1 208 342 6330",
    "sg:postcode":"83705",
    "sg:province":"ID",
    "sg:tags":[
        "cigarette",
        "cigar",
        "dealer"
    ],
    "wof:name":"Tobacco Connection & Beverage",
    "wof:placetype":"venue"
},
  "geometry": {"coordinates":[-116.21368699999999,43.597944],"type":"Point"}
}