{
  "type": "Feature",
  "properties": {
    "iso:country":"US",
    "sg:address":"133 S Rail St W",
    "sg:city":"Shoshone",
    "sg:classifiers":[
        {
            "category":"Restaurant",
            "type":"Food & Drink"
        }
    ],
    "sg:phone":"+1 208 886 2142",
    "sg:postcode":"83352",
    "sg:province":"ID",
    "wof:name":"Manhattan Cafe",
    "wof:placetype":"venue"
},
  "geometry": {"coordinates":[-114.407779,42.935666],"type":"Point"}
}