{
  "type": "Feature",
  "properties": {
    "iso:country":"US",
    "sg:address":"245 Rio Vista St",
    "sg:city":"Osburn",
    "sg:classifiers":[
        {
            "category":"Building & Trades",
            "subcategory":"Construction",
            "type":"Services"
        }
    ],
    "sg:phone":"+1 208 556 0590",
    "sg:postcode":"83849",
    "sg:province":"ID",
    "sg:tags":[
        "downspouts",
        "gutter"
    ],
    "wof:name":"Border Fence & Gutters",
    "wof:placetype":"venue"
},
  "geometry": {"coordinates":[-116.017931,47.516342],"type":"Point"}
}