{
  "type": "Feature",
  "properties": {
    "iso:country":"US",
    "sg:address":"9211 Overland Rd",
    "sg:city":"Boise",
    "sg:classifiers":[
        {
            "category":"Health Services",
            "subcategory":"Chiropractor",
            "type":"Services"
        }
    ],
    "sg:phone":"+1 208 377 7970",
    "sg:postcode":"83709",
    "sg:province":"ID",
    "wof:name":"Henze Chiropractic",
    "wof:placetype":"venue"
},
  "geometry": {"coordinates":[-116.29657400000001,43.590269],"type":"Point"}
}