{
  "type": "Feature",
  "properties": {
    "iso:country":"US",
    "sg:address":"1740 E Bergeson St",
    "sg:city":"Boise",
    "sg:classifiers":[
        {
            "category":"Education",
            "subcategory":"School",
            "type":"Public Place"
        }
    ],
    "sg:phone":"+1 208 338 3464",
    "sg:postcode":"83706",
    "sg:province":"ID",
    "wof:name":"Liberty Elementary School",
    "wof:placetype":"venue"
},
  "geometry": {"coordinates":[-116.160801,43.567869],"type":"Point"}
}