{
  "type": "Feature",
  "properties": {
    "addr:full":"2859 Ridgecrest Dr Idaho Falls ID 83404",
    "addr:housenumber":"2859",
    "addr:postcode":"83404",
    "addr:street":"Ridgecrest Dr",
    "iso:country":"US",
    "sg:address":"2859 Ridgecrest Dr",
    "sg:city":"Idaho Falls",
    "sg:classifiers":[
        {
            "category":"Professional",
            "type":"Services"
        }
    ],
    "sg:phone":"+1 208 524 3847",
    "sg:postcode":"83404",
    "sg:province":"ID",
    "wof:name":"Intermountain Services",
    "wof:placetype":"venue"
},
  "geometry": {"coordinates":[-112.01384299999999,43.472485],"type":"Point"}
}