{
  "type": "Feature",
  "properties": {
    "iso:country":"US",
    "sg:address":"2323 W Main St",
    "sg:city":"Boise",
    "sg:classifiers":[
        {
            "category":"Autos & Motor Vehicles",
            "subcategory":"Fuel & Gas Station",
            "type":"Retail Goods"
        }
    ],
    "sg:phone":"+1 208 342 2512",
    "sg:postcode":"83702",
    "sg:province":"ID",
    "sg:website":"http://www.stinker.com",
    "wof:name":"Stinker Station",
    "wof:placetype":"venue"
},
  "geometry": {"coordinates":[-116.218646,43.621811],"type":"Point"}
}