{
  "type": "Feature",
  "properties": {
    "iso:country":"US",
    "sg:address":"9196 W Barnes Dr",
    "sg:city":"Boise",
    "sg:classifiers":[
        {
            "category":"Insurance",
            "subcategory":"Insurance Agent",
            "type":"Services"
        }
    ],
    "sg:phone":"+1 208 376 1161",
    "sg:postcode":"83709",
    "sg:province":"ID",
    "sg:website":"www.swett.com",
    "wof:name":"Swett Insurance Managers",
    "wof:placetype":"venue"
},
  "geometry": {"coordinates":[-116.29575199999999,43.593524],"type":"Point"}
}