{
  "type": "Feature",
  "properties": {
    "iso:country":"US",
    "sg:address":"1 Professional Plz",
    "sg:city":"Rexburg",
    "sg:classifiers":[
        {
            "category":"Health Services",
            "subcategory":"Doctor",
            "type":"Services"
        }
    ],
    "sg:phone":"+1 208 356 8733",
    "sg:postcode":"83440",
    "sg:province":"ID",
    "sg:tags":[
        "physician",
        "surgeon"
    ],
    "wof:name":"Laser Skin Care",
    "wof:placetype":"venue"
},
  "geometry": {"coordinates":[-111.77628900000001,43.825979],"type":"Point"}
}