{
  "type": "Feature",
  "properties": {
    "addr:full":"11486 W Jenilyn Ct Boise ID 83713",
    "addr:housenumber":"11486",
    "addr:postcode":"83713",
    "addr:street":"W Jenilyn Ct",
    "iso:country":"US",
    "sg:address":"11486 W Jenilyn Ct",
    "sg:city":"Boise",
    "sg:classifiers":[
        {
            "category":"Shopping",
            "type":"Retail Goods"
        }
    ],
    "sg:phone":"+1 208 939 1070",
    "sg:postcode":"83713",
    "sg:province":"ID",
    "sg:tags":[
        "merchandise"
    ],
    "wof:name":"E C O Air Pro",
    "wof:placetype":"venue"
},
  "geometry": {"coordinates":[-116.325959,43.654857],"type":"Point"}
}