{
  "type": "Feature",
  "properties": {
    "iso:country":"US",
    "sg:address":"1063 E Victory Rd",
    "sg:city":"Boise",
    "sg:classifiers":[
        {
            "category":"Banks & Credit Unions",
            "subcategory":"Financial Services",
            "type":"Services"
        }
    ],
    "sg:phone":"+1 208 344 9250",
    "sg:postcode":"83706",
    "sg:province":"ID",
    "sg:tags":[
        "investor"
    ],
    "wof:name":"Griffin Family Investments LLC",
    "wof:placetype":"venue"
},
  "geometry": {"coordinates":[-116.17077,43.575054],"type":"Point"}
}