{
  "type": "Feature",
  "properties": {
    "addr:full":"3466 S Pimmit Ave Boise ID 83706",
    "addr:housenumber":"3466",
    "addr:postcode":"83706",
    "addr:street":"S Pimmit Ave",
    "iso:country":"US",
    "sg:address":"3466 S Pimmit Ave",
    "sg:city":"Boise",
    "sg:classifiers":[
        {
            "category":"Freight",
            "type":"Transportation"
        }
    ],
    "sg:phone":"+1 208 850 0991",
    "sg:postcode":"83706",
    "sg:province":"ID",
    "sg:tags":[
        "operator",
        "local",
        "trucking"
    ],
    "wof:name":"R & E Zahara Trucking",
    "wof:placetype":"venue"
},
  "geometry": {"coordinates":[-116.173931,43.57091],"type":"Point"}
}