{
  "type": "Feature",
  "properties": {
    "iso:country":"US",
    "sg:address":"1004 7th St S",
    "sg:city":"Nampa",
    "sg:classifiers":[
        {
            "category":"Professional",
            "subcategory":"Accounting & Tax Preparation",
            "type":"Services"
        }
    ],
    "sg:phone":"+1 208 466 9573",
    "sg:postcode":"83651",
    "sg:province":"ID",
    "sg:tags":[
        "bookkeeping",
        "general"
    ],
    "wof:name":"Barrett Bookkeeping & Tax Svc",
    "wof:placetype":"venue"
},
  "geometry": {"coordinates":[-116.567667,43.575712],"type":"Point"}
}