{
  "type": "Feature",
  "properties": {
    "iso:country":"US",
    "sg:address":"1920 E 17th St",
    "sg:city":"Idaho Falls",
    "sg:classifiers":[
        {
            "category":"Professional",
            "type":"Services"
        }
    ],
    "sg:phone":"+1 208 524 8991",
    "sg:postcode":"83404",
    "sg:province":"ID",
    "sg:tags":[
        "establishment"
    ],
    "wof:name":"Adolescent Family Treatment",
    "wof:placetype":"venue"
},
  "geometry": {"coordinates":[-111.993408,43.482262],"type":"Point"}
}