{
  "type": "Feature",
  "properties": {
    "iso:country":"US",
    "sg:address":"1306 Filer Ave E",
    "sg:city":"Twin Falls",
    "sg:classifiers":[
        {
            "category":"Education",
            "subcategory":"School",
            "type":"Public Place"
        }
    ],
    "sg:phone":"+1 208 733 7055",
    "sg:postcode":"83301",
    "sg:province":"ID",
    "wof:name":"Acorn Learning Ctr",
    "wof:placetype":"venue"
},
  "geometry": {"coordinates":[-114.457798,42.570329],"type":"Point"}
}