{
  "type": "Feature",
  "properties": {
    "iso:country":"US",
    "sg:address":"837 Chamberlain Ave",
    "sg:city":"Idaho Falls",
    "sg:classifiers":[
        {
            "category":"Building & Trades",
            "subcategory":"Electrical",
            "type":"Services"
        }
    ],
    "sg:phone":"+1 208 522 6482",
    "sg:postcode":"83402",
    "sg:province":"ID",
    "sg:tags":[
        "electric",
        "contractor"
    ],
    "wof:name":"Castle Electric",
    "wof:placetype":"venue"
},
  "geometry": {"coordinates":[-112.04521,43.485567],"type":"Point"}
}