{
  "type": "Feature",
  "properties": {
    "iso:country":"US",
    "sg:address":"645 N Skyline Dr",
    "sg:city":"Idaho Falls",
    "sg:classifiers":[
        {
            "category":"Cinema",
            "subcategory":"Movie Theater",
            "type":"Entertainment"
        }
    ],
    "sg:phone":"+1 208 523 4111",
    "sg:postcode":"83402",
    "sg:province":"ID",
    "wof:name":"Movie World",
    "wof:placetype":"venue"
},
  "geometry": {"coordinates":[-112.06335300000001,43.497562],"type":"Point"}
}