{
  "type": "Feature",
  "properties": {
    "iso:country":"US",
    "sg:address":"311 N 5th Ave",
    "sg:city":"Caldwell",
    "sg:classifiers":[
        {
            "category":"Food & Beverages",
            "subcategory":"Dairy",
            "type":"Retail Goods"
        }
    ],
    "sg:phone":"+1 208 459 3143",
    "sg:postcode":"83605",
    "sg:province":"ID",
    "sg:tags":[
        "product"
    ],
    "wof:name":"Skyline Enterprises Inc",
    "wof:placetype":"venue"
},
  "geometry": {"coordinates":[-116.68724,43.670901],"type":"Point"}
}