{
  "type": "Feature",
  "properties": {
    "addr:full":"6200 N Meeker Pl Boise ID 83713",
    "addr:housenumber":"6200",
    "addr:postcode":"83713",
    "addr:street":"N Meeker Pl",
    "iso:country":"US",
    "sg:address":"6200 N Meeker Pl",
    "sg:city":"Boise",
    "sg:classifiers":[
        {
            "category":"Real Estate",
            "subcategory":"Developer",
            "type":"Services"
        }
    ],
    "sg:phone":"+1 208 377 3939",
    "sg:postcode":"83713",
    "sg:province":"ID",
    "wof:name":"Capital Development Inc",
    "wof:placetype":"venue"
},
  "geometry": {"coordinates":[-116.336507,43.660718],"type":"Point"}
}