{
  "type": "Feature",
  "properties": {
    "addr:full":"1168 Lavina Ave Twin Falls ID 83301",
    "addr:housenumber":"1168",
    "addr:postcode":"83301",
    "addr:street":"Lavina Ave",
    "iso:country":"US",
    "sg:address":"1168 Lavina Ave",
    "sg:city":"Twin Falls",
    "sg:classifiers":[
        {
            "category":"Building & Trades",
            "subcategory":"Plumbing",
            "type":"Services"
        }
    ],
    "sg:phone":"+1 208 733 8269",
    "sg:postcode":"83301",
    "sg:province":"ID",
    "sg:tags":[
        "contractor"
    ],
    "wof:name":"Action Plumbing",
    "wof:placetype":"venue"
},
  "geometry": {"coordinates":[-114.502056,42.55236],"type":"Point"}
}