{
  "type": "Feature",
  "properties": {
    "addr:full":"163 Riley Creek Rd Laclede ID 83841",
    "addr:housenumber":"163",
    "addr:postcode":"83841",
    "addr:street":"Riley Creek Rd",
    "iso:country":"US",
    "sg:address":"163 Riley Creek Rd",
    "sg:city":"Laclede",
    "sg:classifiers":[
        {
            "category":"Government",
            "subcategory":"Post Office",
            "type":"Public Place"
        }
    ],
    "sg:phone":"+1 208 263 7138",
    "sg:postcode":"83841",
    "sg:province":"ID",
    "wof:name":"US Post Office",
    "wof:placetype":"venue"
},
  "geometry": {"coordinates":[-116.75603700000001,48.16946],"type":"Point"}
}