{
  "type": "Feature",
  "properties": {
    "iso:country":"US",
    "sg:address":"212 N 3800 E",
    "sg:city":"Rigby",
    "sg:classifiers":[
        {
            "category":"Professional",
            "subcategory":"Management & Consulting",
            "type":"Services"
        }
    ],
    "sg:phone":"+1 208 745 0887",
    "sg:postcode":"83442",
    "sg:province":"ID",
    "wof:name":"J R Investments Management",
    "wof:placetype":"venue"
},
  "geometry": {"coordinates":[-111.943782,43.657402],"type":"Point"}
}