{
  "type": "Feature",
  "properties": {
    "addr:full":"12655 Old US Hwy 91 Arimo ID 83214",
    "addr:housenumber":"12655",
    "addr:postcode":"83214",
    "addr:street":"Old Us Hwy 91",
    "iso:country":"US",
    "sg:address":"12655 Old US Hwy 91",
    "sg:city":"Arimo",
    "sg:classifiers":[
        {
            "category":"Education",
            "subcategory":"School",
            "type":"Public Place"
        }
    ],
    "sg:phone":"+1 208 254 3711",
    "sg:postcode":"83214",
    "sg:province":"ID",
    "sg:website":"www.mvsd21.org",
    "wof:name":"Marsh Valley High School",
    "wof:placetype":"venue"
},
  "geometry": {"coordinates":[-112.18054100000001,42.581506],"type":"Point"}
}