{
  "type": "Feature",
  "properties": {
    "iso:country":"US",
    "sg:address":"1595 W Broadway St",
    "sg:city":"Idaho Falls",
    "sg:classifiers":[
        {
            "category":"Shopping",
            "subcategory":"Tobacco",
            "type":"Retail Goods"
        }
    ],
    "sg:phone":"+1 208 542 0357",
    "sg:postcode":"83402",
    "sg:province":"ID",
    "sg:tags":[
        "cigarette",
        "cigar",
        "dealer"
    ],
    "wof:name":"Tobacco Connection",
    "wof:placetype":"venue"
},
  "geometry": {"coordinates":[-112.062826,43.496711],"type":"Point"}
}