{
  "type": "Feature",
  "properties": {
    "addr:full":"504 E 43rd St Boise ID 83714",
    "addr:housenumber":"504",
    "addr:postcode":"83714",
    "addr:street":"E 43Rd St",
    "iso:country":"US",
    "sg:address":"504 E 43rd St",
    "sg:city":"Boise",
    "sg:classifiers":[
        {
            "category":"Autos & Motor Vehicles",
            "subcategory":"Automobile Sales",
            "type":"Retail Goods"
        }
    ],
    "sg:phone":"+1 208 367 0244",
    "sg:postcode":"83714",
    "sg:province":"ID",
    "sg:tags":[
        "car",
        "dealer"
    ],
    "wof:name":"Courtesy Motors",
    "wof:placetype":"venue"
},
  "geometry": {"coordinates":[-116.245831,43.637808],"type":"Point"}
}