{
  "type": "Feature",
  "properties": {
    "iso:country":"US",
    "sg:address":"715 8th Ave N",
    "sg:city":"Payette",
    "sg:classifiers":[
        {
            "category":"Manufacturing",
            "subcategory":"Tools & Machinery",
            "type":"Manufacturing & Wholesale Goods"
        }
    ],
    "sg:phone":"+1 208 642 3503",
    "sg:postcode":"83661",
    "sg:province":"ID",
    "sg:tags":[
        "woodworking",
        "mfg"
    ],
    "wof:name":"Mill Direct Wood Products",
    "wof:placetype":"venue"
},
  "geometry": {"coordinates":[-116.934552,44.083011],"type":"Point"}
}