{
  "type": "Feature",
  "properties": {
    "addr:full":"725 E Anderson St Idaho Falls ID 83401",
    "addr:housenumber":"725",
    "addr:postcode":"83401",
    "addr:street":"E Anderson St",
    "iso:country":"US",
    "sg:address":"725 E Anderson St",
    "sg:city":"Idaho Falls",
    "sg:classifiers":[
        {
            "category":"Restaurant",
            "type":"Food & Drink"
        }
    ],
    "sg:menulink":"http://www.allmenus.com/id/idaho-falls/78941-pizza-hut/menu/",
    "sg:phone":"+1 208 524 2727",
    "sg:postcode":"83401",
    "sg:province":"ID",
    "sg:tags":[
        "american",
        "pizza"
    ],
    "wof:name":"Pizza Hut",
    "wof:placetype":"venue"
},
  "geometry": {"coordinates":[-112.017849,43.511312],"type":"Point"}
}