{
  "type": "Feature",
  "properties": {
    "addr:full":"415 E Parkcenter Blvd Boise ID 83706",
    "addr:housenumber":"415",
    "addr:postcode":"83706",
    "addr:street":"E Parkcenter Blvd",
    "iso:country":"US",
    "sg:address":"415 E Parkcenter Blvd",
    "sg:city":"Boise",
    "sg:classifiers":[
        {
            "category":"Professional",
            "subcategory":"Employment Agencies",
            "type":"Services"
        }
    ],
    "sg:phone":"+1 208 343 5190",
    "sg:postcode":"83706",
    "sg:province":"ID",
    "sg:tags":[
        "consultant",
        "search",
        "executive"
    ],
    "wof:name":"Fortune Consultants",
    "wof:placetype":"venue"
},
  "geometry": {"coordinates":[-116.177931,43.594627],"type":"Point"}
}