{
  "type": "Feature",
  "properties": {
    "iso:country":"US",
    "sg:address":"3210 E Chinden Blvd",
    "sg:city":"Eagle",
    "sg:classifiers":[
        {
            "category":"Shopping",
            "subcategory":"Clothing, Apparel, & Fashions",
            "type":"Retail Goods"
        }
    ],
    "sg:phone":"+1 208 938 3333",
    "sg:postcode":"83616",
    "sg:province":"ID",
    "sg:tags":[
        "lingerie"
    ],
    "wof:name":"Bella Sera",
    "wof:placetype":"venue"
},
  "geometry": {"coordinates":[-116.353387,43.663078],"type":"Point"}
}