{
  "type": "Feature",
  "properties": {
    "addr:full":"502 Church St Sandpoint ID 83864",
    "addr:housenumber":"502",
    "addr:postcode":"83864",
    "addr:street":"Church St",
    "iso:country":"US",
    "sg:address":"502 Church St",
    "sg:city":"Sandpoint",
    "sg:classifiers":[
        {
            "category":"Shopping",
            "subcategory":"Used Merchandise",
            "type":"Retail Goods"
        }
    ],
    "sg:phone":"+1 208 263 4444",
    "sg:postcode":"83864",
    "sg:province":"ID",
    "sg:tags":[
        "antique"
    ],
    "wof:name":"Marketplace Antiques & Gifts",
    "wof:placetype":"venue"
},
  "geometry": {"coordinates":[-116.55547300000001,48.27409],"type":"Point"}
}