{
  "type": "Feature",
  "properties": {
    "iso:country":"US",
    "sg:address":"465 E 1500 N",
    "sg:city":"Rupert",
    "sg:classifiers":[
        {
            "category":"Farming",
            "subcategory":"Livestock Farm",
            "type":"Manufacturing & Wholesale Goods"
        }
    ],
    "sg:phone":"+1 208 532 4568",
    "sg:postcode":"83343",
    "sg:province":"ID",
    "sg:tags":[
        "ranch"
    ],
    "wof:name":"Harman Land Ranch",
    "wof:placetype":"venue"
},
  "geometry": {"coordinates":[-113.577469,42.836906],"type":"Point"}
}