{
  "type": "Feature",
  "properties": {
    "iso:country":"US",
    "sg:address":"7510 Holbrook Ln",
    "sg:city":"Boise",
    "sg:classifiers":[
        {
            "category":"Real Estate",
            "subcategory":"Real Estate Operator",
            "type":"Services"
        }
    ],
    "sg:phone":"+1 208 377 4459",
    "sg:postcode":"83704",
    "sg:province":"ID",
    "sg:tags":[
        "apartment"
    ],
    "wof:name":"Cole Meadows Apartments",
    "wof:placetype":"venue"
},
  "geometry": {"coordinates":[-116.27524699999999,43.629306],"type":"Point"}
}