{
  "type": "Feature",
  "properties": {
    "iso:country":"US",
    "sg:address":"29 W 50 S",
    "sg:city":"Blackfoot",
    "sg:classifiers":[
        {
            "category":"Freight",
            "type":"Transportation"
        }
    ],
    "sg:phone":"+1 208 785 4859",
    "sg:postcode":"83221",
    "sg:province":"ID",
    "sg:tags":[
        "building",
        "house",
        "mover"
    ],
    "wof:name":"Parrish Moving Specialties Inc",
    "wof:placetype":"venue"
},
  "geometry": {"coordinates":[-112.304063,43.189039],"type":"Point"}
}