{
  "type": "Feature",
  "properties": {
    "iso:country":"US",
    "sg:address":"509 N 13th St",
    "sg:city":"Boise",
    "sg:classifiers":[
        {
            "category":"Professional",
            "subcategory":"Advertising",
            "type":"Services"
        }
    ],
    "sg:phone":"+1 208 385 0807",
    "sg:postcode":"83702",
    "sg:province":"ID",
    "sg:tags":[
        "agency"
    ],
    "wof:name":"Marketing By Dsgn-Krsti Smmons",
    "wof:placetype":"venue"
},
  "geometry": {"coordinates":[-116.205794,43.622413],"type":"Point"}
}