{
  "type": "Feature",
  "properties": {
    "iso:country":"US",
    "sg:address":"285 W Hesston St",
    "sg:city":"Kuna",
    "sg:classifiers":[
        {
            "category":"Social Services",
            "subcategory":"Child Care",
            "type":"Services"
        }
    ],
    "sg:phone":"+1 208 922 9135",
    "sg:postcode":"83634",
    "sg:province":"ID",
    "sg:tags":[
        "day"
    ],
    "wof:name":"Circle of Friends Family",
    "wof:placetype":"venue"
},
  "geometry": {"coordinates":[-116.417996,43.502487],"type":"Point"}
}