{
  "type": "Feature",
  "properties": {
    "iso:country":"US",
    "sg:address":"2002 Nez Perce St",
    "sg:city":"Boise",
    "sg:classifiers":[
        {
            "category":"Manufacturing",
            "subcategory":"Electronics",
            "type":"Manufacturing & Wholesale Goods"
        }
    ],
    "sg:phone":"+1 208 336 3617",
    "sg:postcode":"83705",
    "sg:province":"ID",
    "sg:tags":[
        "prerecorded",
        "motion",
        "prod",
        "mfg"
    ],
    "wof:name":"Memories Video Productions",
    "wof:placetype":"venue"
},
  "geometry": {"coordinates":[-116.207787,43.587356],"type":"Point"}
}