{
  "type": "Feature",
  "properties": {
    "addr:full":"1076 E Hayden Ave Hayden ID 83835",
    "addr:housenumber":"1076",
    "addr:postcode":"83835",
    "addr:street":"E Hayden Ave",
    "iso:country":"US",
    "sg:address":"1076 E Hayden Ave",
    "sg:city":"Hayden",
    "sg:classifiers":[
        {
            "category":"Health Services",
            "subcategory":"Doctor",
            "type":"Services"
        }
    ],
    "sg:phone":"+1 208 772 2823",
    "sg:postcode":"83835",
    "sg:province":"ID",
    "sg:tags":[
        "physician",
        "surgeon"
    ],
    "wof:name":"Dayspring Midwifery Svc",
    "wof:placetype":"venue"
},
  "geometry": {"coordinates":[-116.772357,47.758863],"type":"Point"}
}