{
  "type": "Feature",
  "properties": {
    "iso:country":"US",
    "sg:address":"1505 N Mitchell St",
    "sg:city":"Boise",
    "sg:classifiers":[
        {
            "category":"Travel",
            "subcategory":"Campground",
            "type":"Entertainment"
        }
    ],
    "sg:phone":"+1 208 375 6638",
    "sg:postcode":"83704",
    "sg:province":"ID",
    "sg:tags":[
        "recreational",
        "parks",
        "vehicle"
    ],
    "wof:name":"Brookside Rv Park",
    "wof:placetype":"venue"
},
  "geometry": {"coordinates":[-116.304272,43.619066],"type":"Point"}
}