{
  "type": "Feature",
  "properties": {
    "iso:country":"US",
    "sg:address":"11655 W Peak View Ct",
    "sg:city":"Boise",
    "sg:classifiers":[
        {
            "category":"Professional",
            "subcategory":"Accounting & Tax Preparation",
            "type":"Services"
        }
    ],
    "sg:phone":"+1 208 362 9263",
    "sg:postcode":"83709",
    "sg:province":"ID",
    "sg:tags":[
        "accountant"
    ],
    "wof:name":"Walt Czarniecki CPA",
    "wof:placetype":"venue"
},
  "geometry": {"coordinates":[-116.326272,43.569008],"type":"Point"}
}