{
  "type": "Feature",
  "properties": {
    "addr:full":"551 Sykes Dr Idaho Falls ID 83401",
    "addr:housenumber":"551",
    "addr:postcode":"83401",
    "addr:street":"Sykes Dr",
    "iso:country":"US",
    "sg:address":"551 Sykes Dr",
    "sg:city":"Idaho Falls",
    "sg:classifiers":[
        {
            "category":"Organizations",
            "subcategory":"Religious Organization",
            "type":"Services"
        }
    ],
    "sg:phone":"+1 208 524 4068",
    "sg:postcode":"83401",
    "sg:province":"ID",
    "wof:name":"ID Jurisdiction Church of God",
    "wof:placetype":"venue"
},
  "geometry": {"coordinates":[-111.992605,43.499385],"type":"Point"}
}