{
  "type": "Feature",
  "properties": {
    "iso:country":"US",
    "sg:address":"9728 Colburn Culver Rd",
    "sg:city":"Sandpoint",
    "sg:classifiers":[
        {
            "category":"Real Estate",
            "subcategory":"Developer",
            "type":"Services"
        }
    ],
    "sg:phone":"+1 208 267 4306",
    "sg:postcode":"83864",
    "sg:province":"ID",
    "sg:tags":[
        "cemetery"
    ],
    "sg:website":"www.celebrationforest.com",
    "wof:name":"Stockton Business Svc",
    "wof:placetype":"venue"
},
  "geometry": {"coordinates":[-116.43997,48.337963],"type":"Point"}
}