{
  "type": "Feature",
  "properties": {
    "iso:country":"US",
    "sg:address":"1236 N Salem Rd",
    "sg:city":"Rexburg",
    "sg:classifiers":[
        {
            "category":"Wholesale",
            "subcategory":"Farm Supplies",
            "type":"Manufacturing & Wholesale Goods"
        }
    ],
    "sg:phone":"+1 208 356 3616",
    "sg:postcode":"83440",
    "sg:province":"ID",
    "sg:tags":[
        "auction",
        "livestock",
        "market"
    ],
    "wof:name":"Rexburg Livestock Co",
    "wof:placetype":"venue"
},
  "geometry": {"coordinates":[-111.77792700000001,43.84558],"type":"Point"}
}