{
  "type": "Feature",
  "properties": {
    "iso:country":"US",
    "sg:address":"977 Logan St",
    "sg:city":"Boise",
    "sg:classifiers":[
        {
            "category":"Manufacturing",
            "subcategory":"Tools & Machinery",
            "type":"Manufacturing & Wholesale Goods"
        }
    ],
    "sg:phone":"+1 208 342 0110",
    "sg:postcode":"83712",
    "sg:province":"ID",
    "sg:tags":[
        "mining",
        "mfg"
    ],
    "wof:name":"Gulch Placer Mining Equipment",
    "wof:placetype":"venue"
},
  "geometry": {"coordinates":[-116.182878,43.613443],"type":"Point"}
}