{
  "type": "Feature",
  "properties": {
    "iso:country":"US",
    "sg:address":"1044 N C St",
    "sg:city":"Coeur D Alene",
    "sg:classifiers":[
        {
            "category":"Real Estate",
            "subcategory":"Real Estate Agent",
            "type":"Services"
        }
    ],
    "sg:phone":"+1 208 667 2399",
    "sg:postcode":"83814",
    "sg:province":"ID",
    "wof:name":"Keller Williams Realty",
    "wof:placetype":"venue"
},
  "geometry": {"coordinates":[-116.78979,47.685083],"type":"Point"}
}