{
  "type": "Feature",
  "properties": {
    "addr:full":"2084 S Eagle Rd Meridian ID 83642",
    "addr:housenumber":"2084",
    "addr:postcode":"83642",
    "addr:street":"S Eagle Rd",
    "iso:country":"US",
    "sg:address":"2084 S Eagle Rd",
    "sg:city":"Meridian",
    "sg:classifiers":[
        {
            "category":"Banks & Credit Unions",
            "subcategory":"Bank",
            "type":"Services"
        }
    ],
    "sg:phone":"+1 208 376 8935",
    "sg:postcode":"83642",
    "sg:province":"ID",
    "sg:tags":[
        "loan",
        "real estate"
    ],
    "wof:name":"Far West Mortgage",
    "wof:placetype":"venue"
},
  "geometry": {"coordinates":[-116.354443,43.587982],"type":"Point"}
}