{
  "type": "Feature",
  "properties": {
    "iso:country":"US",
    "sg:address":"73 W 900 S",
    "sg:city":"Victor",
    "sg:classifiers":[
        {
            "category":"Social Services",
            "subcategory":"Adult Care",
            "type":"Services"
        }
    ],
    "sg:phone":"+1 208 787 2861",
    "sg:postcode":"83455",
    "sg:province":"ID",
    "sg:tags":[
        "home",
        "residential"
    ],
    "wof:name":"Teton Valley Care",
    "wof:placetype":"venue"
},
  "geometry": {"coordinates":[-111.11554099999999,43.592335],"type":"Point"}
}