{
  "type": "Feature",
  "properties": {
    "iso:country":"US",
    "sg:address":"599 S Rivershore Ln",
    "sg:city":"Eagle",
    "sg:classifiers":[
        {
            "category":"Manufacturing",
            "subcategory":"Food",
            "type":"Manufacturing & Wholesale Goods"
        }
    ],
    "sg:phone":"+1 208 938 1022",
    "sg:postcode":"83616",
    "sg:province":"ID",
    "sg:tags":[
        "frozen",
        "processor"
    ],
    "sg:website":"www.lambweston.com",
    "wof:name":"Lamb-Weston Inc",
    "wof:placetype":"venue"
},
  "geometry": {"coordinates":[-116.35542100000001,43.688114],"type":"Point"}
}