{
  "type": "Feature",
  "properties": {
    "addr:full":"1008 S Division St Pinehurst ID 83850",
    "addr:housenumber":"1008",
    "addr:postcode":"83850",
    "addr:street":"S Division St",
    "iso:country":"US",
    "sg:address":"1008 S Division St",
    "sg:city":"Pinehurst",
    "sg:classifiers":[
        {
            "category":"Organizations",
            "subcategory":"Religious Organization",
            "type":"Services"
        }
    ],
    "sg:phone":"+1 208 682 2551",
    "sg:postcode":"83850",
    "sg:province":"ID",
    "sg:tags":[
        "church"
    ],
    "wof:name":"Assembly Of God New Hope",
    "wof:placetype":"venue"
},
  "geometry": {"coordinates":[-116.241759,47.529071],"type":"Point"}
}