{
  "type": "Feature",
  "properties": {
    "iso:country":"US",
    "sg:address":"1417 15th Ave",
    "sg:city":"Lewiston",
    "sg:classifiers":[
        {
            "category":"Farming",
            "subcategory":"Farm",
            "type":"Manufacturing & Wholesale Goods"
        }
    ],
    "sg:phone":"+1 208 743 0591",
    "sg:postcode":"83501",
    "sg:province":"ID",
    "sg:tags":[
        "crop",
        "general"
    ],
    "wof:name":"Etter Land Company LLC",
    "wof:placetype":"venue"
},
  "geometry": {"coordinates":[-117.01227299999999,46.405208],"type":"Point"}
}