{
  "type": "Feature",
  "properties": {
    "iso:country":"US",
    "sg:address":"26 W 1st S",
    "sg:city":"Rexburg",
    "sg:classifiers":[
        {
            "category":"Restaurant",
            "type":"Food & Drink"
        }
    ],
    "sg:menulink":"http://www.allmenus.com/id/thornton/87365-little-caesars-pizza/menu/",
    "sg:phone":"+1 208 359 0071",
    "sg:postcode":"83440",
    "sg:province":"ID",
    "sg:tags":[
        "american",
        "pizza"
    ],
    "wof:name":"Little Caesar's Pizza",
    "wof:placetype":"venue"
},
  "geometry": {"coordinates":[-111.78468700000001,43.824091],"type":"Point"}
}