{
  "type": "Feature",
  "properties": {
    "addr:full":"4648 Fenton St Boise ID 83714",
    "addr:housenumber":"4648",
    "addr:postcode":"83714",
    "addr:street":"Fenton St",
    "iso:country":"US",
    "sg:address":"4648 Fenton St",
    "sg:city":"Boise",
    "sg:classifiers":[
        {
            "category":"Real Estate",
            "subcategory":"Real Estate Agent",
            "type":"Services"
        }
    ],
    "sg:phone":"+1 208 375 2345",
    "sg:postcode":"83714",
    "sg:province":"ID",
    "sg:tags":[
        "appraiser"
    ],
    "wof:name":"Brent Smith Appraisal Svc",
    "wof:placetype":"venue"
},
  "geometry": {"coordinates":[-116.258562,43.637749],"type":"Point"}
}