{
  "type": "Feature",
  "properties": {
    "addr:full":"17 W Idaho St Weiser ID 83672",
    "addr:housenumber":"17",
    "addr:postcode":"83672",
    "addr:street":"W Idaho St",
    "iso:country":"US",
    "sg:address":"17 W Idaho St",
    "sg:city":"Weiser",
    "sg:classifiers":[
        {
            "category":"Restaurant",
            "type":"Food & Drink"
        }
    ],
    "sg:phone":"+1 208 414 1071",
    "sg:postcode":"83672",
    "sg:province":"ID",
    "wof:name":"Pizzamore",
    "wof:placetype":"venue"
},
  "geometry": {"coordinates":[-116.971497,44.245755],"type":"Point"}
}