{
  "type": "Feature",
  "properties": {
    "iso:country":"US",
    "sg:address":"2188 Addison Ave E",
    "sg:city":"Twin Falls",
    "sg:classifiers":[
        {
            "category":"Professional",
            "subcategory":"Accounting & Tax Preparation",
            "type":"Services"
        }
    ],
    "sg:phone":"+1 208 734 0598",
    "sg:postcode":"83301",
    "sg:province":"ID",
    "sg:tags":[
        "accountant"
    ],
    "wof:name":"Pollow & Moore",
    "wof:placetype":"venue"
},
  "geometry": {"coordinates":[-114.441216,42.563077],"type":"Point"}
}