{
  "type": "Feature",
  "properties": {
    "addr:full":"8414 W Thunder Mountain Dr Boise ID 83709",
    "addr:housenumber":"8414",
    "addr:postcode":"83709",
    "addr:street":"W Thunder Mountain Dr",
    "iso:country":"US",
    "sg:address":"8414 W Thunder Mountain Dr",
    "sg:city":"Boise",
    "sg:classifiers":[
        {
            "category":"Real Estate",
            "subcategory":"Real Estate Operator",
            "type":"Services"
        }
    ],
    "sg:phone":"+1 208 362 8990",
    "sg:postcode":"83709",
    "sg:province":"ID",
    "sg:tags":[
        "building",
        "nonresidential"
    ],
    "wof:name":"Lhb Investments Inc",
    "wof:placetype":"venue"
},
  "geometry": {"coordinates":[-116.285506,43.564273],"type":"Point"}
}