{
  "type": "Feature",
  "properties": {
    "addr:full":"3958 W 2000 S Rexburg ID 83440",
    "addr:housenumber":"3958",
    "addr:postcode":"83440",
    "addr:street":"W 2000 S",
    "iso:country":"US",
    "sg:address":"3958 W 2000 S",
    "sg:city":"Rexburg",
    "sg:classifiers":[
        {
            "category":"Organizations",
            "subcategory":"Religious Organization",
            "type":"Services"
        }
    ],
    "sg:phone":"+1 208 356 0094",
    "sg:postcode":"83440",
    "sg:province":"ID",
    "sg:tags":[
        "church"
    ],
    "wof:name":"Church Of Jesus Christ Of Lds",
    "wof:placetype":"venue"
},
  "geometry": {"coordinates":[-111.852476,43.797336],"type":"Point"}
}