{
  "type": "Feature",
  "properties": {
    "iso:country":"US",
    "sg:address":"106 E Liberty St",
    "sg:city":"Weiser",
    "sg:classifiers":[
        {
            "category":"Organizations",
            "subcategory":"Religious Organization",
            "type":"Services"
        }
    ],
    "sg:phone":"+1 208 549 1552",
    "sg:postcode":"83672",
    "sg:province":"ID",
    "sg:tags":[
        "place",
        "worship",
        "church"
    ],
    "wof:name":"Saint Lukes Church",
    "wof:placetype":"venue"
},
  "geometry": {"coordinates":[-116.968042,44.247849],"type":"Point"}
}