{
  "type": "Feature",
  "properties": {
    "iso:country":"US",
    "sg:address":"111 Broadway Ave",
    "sg:city":"Boise",
    "sg:classifiers":[
        {
            "category":"Professional",
            "subcategory":"Advertising",
            "type":"Services"
        }
    ],
    "sg:phone":"+1 208 336 1540",
    "sg:postcode":"83702",
    "sg:province":"ID",
    "sg:tags":[
        "mailing",
        "shipping"
    ],
    "wof:name":"Parcel Post",
    "wof:placetype":"venue"
},
  "geometry": {"coordinates":[-116.19322200000001,43.610604],"type":"Point"}
}