{
  "type": "Feature",
  "properties": {
    "iso:country":"US",
    "sg:address":"5525 Glenwood St",
    "sg:city":"Boise",
    "sg:classifiers":[
        {
            "category":"Retail",
            "subcategory":"Funeral Services",
            "type":"Services"
        }
    ],
    "sg:phone":"+1 208 853 3131",
    "sg:postcode":"83714",
    "sg:province":"ID",
    "sg:tags":[
        "director"
    ],
    "wof:name":"Bowman Funeral Svc",
    "wof:placetype":"venue"
},
  "geometry": {"coordinates":[-116.279824,43.650504],"type":"Point"}
}