{
  "type": "Feature",
  "properties": {
    "iso:country":"US",
    "sg:address":"1459 E 4300 N",
    "sg:city":"Buhl",
    "sg:classifiers":[
        {
            "category":"Personal",
            "subcategory":"Beauty Salon",
            "type":"Services"
        }
    ],
    "sg:phone":"+1 208 543 4776",
    "sg:postcode":"83316",
    "sg:province":"ID",
    "sg:tags":[
        "shop"
    ],
    "wof:name":"J BS Trendy Images",
    "wof:placetype":"venue"
},
  "geometry": {"coordinates":[-114.76027000000001,42.622467],"type":"Point"}
}