{
  "type": "Feature",
  "properties": {
    "addr:full":"4610 N Haroldsen Dr Idaho Falls ID 83401",
    "addr:housenumber":"4610",
    "addr:postcode":"83401",
    "addr:street":"N Haroldsen Dr",
    "iso:country":"US",
    "sg:address":"4610 N Haroldsen Dr",
    "sg:city":"Idaho Falls",
    "sg:classifiers":[
        {
            "category":"Home & Garden",
            "subcategory":"Building Materials",
            "type":"Retail Goods"
        }
    ],
    "sg:phone":"+1 208 552 5858",
    "sg:postcode":"83401",
    "sg:province":"ID",
    "sg:tags":[
        "roofing"
    ],
    "wof:name":"R & S Supply",
    "wof:placetype":"venue"
},
  "geometry": {"coordinates":[-112.00806300000001,43.536899],"type":"Point"}
}