{
  "type": "Feature",
  "properties": {
    "addr:full":"1978 Silvercreek Ln Boise ID 83706",
    "addr:housenumber":"1978",
    "addr:postcode":"83706",
    "addr:street":"Silvercreek Ln",
    "iso:country":"US",
    "sg:address":"1978 Silvercreek Ln",
    "sg:city":"Boise",
    "sg:classifiers":[
        {
            "category":"Professional",
            "subcategory":"Management & Consulting",
            "type":"Services"
        }
    ],
    "sg:phone":"+1 208 345 2720",
    "sg:postcode":"83706",
    "sg:province":"ID",
    "sg:tags":[
        "consultant",
        "business"
    ],
    "wof:name":"Smelek & Assoc",
    "wof:placetype":"venue"
},
  "geometry": {"coordinates":[-116.163151,43.586245],"type":"Point"}
}