{
  "type": "Feature",
  "properties": {
    "iso:country":"US",
    "sg:address":"5685 N Pioneer Dr",
    "sg:city":"Coeur D Alene",
    "sg:classifiers":[
        {
            "category":"Recreation",
            "type":"Entertainment"
        }
    ],
    "sg:phone":"+1 208 772 9507",
    "sg:postcode":"83815",
    "sg:province":"ID",
    "sg:tags":[
        "skating",
        "rink"
    ],
    "wof:name":"Skate Plaza",
    "wof:placetype":"venue"
},
  "geometry": {"coordinates":[-116.79292100000001,47.723744],"type":"Point"}
}