{
  "type": "Feature",
  "properties": {
    "iso:country":"US",
    "sg:address":"256 14th Ave N",
    "sg:city":"Payette",
    "sg:classifiers":[
        {
            "category":"Building & Trades",
            "subcategory":"Construction",
            "type":"Services"
        }
    ],
    "sg:phone":"+1 208 642 1540",
    "sg:postcode":"83661",
    "sg:province":"ID",
    "sg:tags":[
        "roofing",
        "contractor"
    ],
    "wof:name":"Three Angels Roofing",
    "wof:placetype":"venue"
},
  "geometry": {"coordinates":[-116.94248,44.089108],"type":"Point"}
}