{
  "type": "Feature",
  "properties": {
    "addr:full":"4065 S Cloudview Dr Coeur D Alene ID 83814",
    "addr:housenumber":"4065",
    "addr:postcode":"83814",
    "addr:street":"S Cloudview Dr",
    "iso:country":"US",
    "sg:address":"4065 S Cloudview Dr",
    "sg:city":"Coeur D Alene",
    "sg:classifiers":[
        {
            "category":"Professional",
            "type":"Services"
        }
    ],
    "sg:phone":"+1 208 651 0869",
    "sg:postcode":"83814",
    "sg:province":"ID",
    "wof:name":"Ideal Web Services LLC",
    "wof:placetype":"venue"
},
  "geometry": {"coordinates":[-116.79344,47.636334],"type":"Point"}
}