{
  "type": "Feature",
  "properties": {
    "iso:country":"US",
    "sg:address":"179 Jefferson Ave",
    "sg:city":"Pocatello",
    "sg:classifiers":[
        {
            "category":"Banks & Credit Unions",
            "subcategory":"Bank",
            "type":"Services"
        }
    ],
    "sg:phone":"+1 208 232 1542",
    "sg:postcode":"83201",
    "sg:province":"ID",
    "sg:tags":[
        "loan",
        "real estate"
    ],
    "wof:name":"Western Mortgage",
    "wof:placetype":"venue"
},
  "geometry": {"coordinates":[-112.441838,42.877301],"type":"Point"}
}