{
  "type": "Feature",
  "properties": {
    "addr:full":"3375 N 3300 E Kimberly ID 83341",
    "addr:housenumber":"3375;3300 e",
    "addr:postcode":"83341",
    "addr:street":"N",
    "iso:country":"US",
    "sg:address":"3375 N 3300 E",
    "sg:city":"Kimberly",
    "sg:classifiers":[
        {
            "category":"Professional",
            "subcategory":"Management & Consulting",
            "type":"Services"
        }
    ],
    "sg:phone":"+1 208 733 5711",
    "sg:postcode":"83341",
    "sg:province":"ID",
    "wof:name":"Safety Consultant",
    "wof:placetype":"venue"
},
  "geometry": {"coordinates":[-114.40149099999999,42.484738],"type":"Point"}
}