{
  "type": "Feature",
  "properties": {
    "addr:full":"7897 W Thunder Mountain Dr Boise ID 83709",
    "addr:housenumber":"7897",
    "addr:postcode":"83709",
    "addr:street":"W Thunder Mountain Dr",
    "iso:country":"US",
    "sg:address":"7897 W Thunder Mountain Dr",
    "sg:city":"Boise",
    "sg:classifiers":[
        {
            "category":"Shopping",
            "subcategory":"Bicycles & Sporting Goods",
            "type":"Retail Goods"
        }
    ],
    "sg:phone":"+1 208 362 5435",
    "sg:postcode":"83709",
    "sg:province":"ID",
    "sg:tags":[
        "equipment",
        "golf",
        "supply"
    ],
    "wof:name":"Golf Werks Idaho",
    "wof:placetype":"venue"
},
  "geometry": {"coordinates":[-116.28040300000001,43.563439],"type":"Point"}
}