{
  "type": "Feature",
  "properties": {
    "addr:full":"290 N Ash St Blackfoot ID 83221",
    "addr:housenumber":"290",
    "addr:postcode":"83221",
    "addr:street":"N Ash St",
    "iso:country":"US",
    "sg:address":"290 N Ash St",
    "sg:city":"Blackfoot",
    "sg:classifiers":[
        {
            "category":"Professional",
            "type":"Services"
        }
    ],
    "sg:phone":"+1 208 785 7405",
    "sg:postcode":"83221",
    "sg:province":"ID",
    "sg:tags":[
        "establishment"
    ],
    "wof:name":"Home Heakth Idaho",
    "wof:placetype":"venue"
},
  "geometry": {"coordinates":[-112.345247,43.191324],"type":"Point"}
}