{
  "type": "Feature",
  "properties": {
    "iso:country":"US",
    "sg:address":"301 Main St",
    "sg:city":"Lewiston",
    "sg:classifiers":[
        {
            "category":"Shopping",
            "type":"Retail Goods"
        }
    ],
    "sg:phone":"+1 208 746 4494",
    "sg:postcode":"83501",
    "sg:province":"ID",
    "sg:tags":[
        "merchandise"
    ],
    "wof:name":"Country House",
    "wof:placetype":"venue"
},
  "geometry": {"coordinates":[-117.027232,46.421515],"type":"Point"}
}