{
  "type": "Feature",
  "properties": {
    "iso:country":"US",
    "sg:address":"2305 S Main St",
    "sg:city":"Moscow",
    "sg:classifiers":[
        {
            "category":"Wholesale",
            "subcategory":"Farm Supplies",
            "type":"Manufacturing & Wholesale Goods"
        }
    ],
    "sg:phone":"+1 208 883 0615",
    "sg:postcode":"83843",
    "sg:province":"ID",
    "sg:tags":[
        "grain"
    ],
    "wof:name":"Latah County Grain Growers",
    "wof:placetype":"venue"
},
  "geometry": {"coordinates":[-117.004235,46.711996],"type":"Point"}
}