{
  "type": "Feature",
  "properties": {
    "iso:country":"US",
    "sg:address":"7905 Ustick Rd",
    "sg:city":"Boise",
    "sg:classifiers":[
        {
            "category":"Personal",
            "subcategory":"Beauty Salon",
            "type":"Services"
        }
    ],
    "sg:phone":"+1 208 322 7098",
    "sg:postcode":"83704",
    "sg:province":"ID",
    "wof:name":"Ustick Hair & Beauty Salon",
    "wof:placetype":"venue"
},
  "geometry": {"coordinates":[-116.279381,43.633846],"type":"Point"}
}