{
  "type": "Feature",
  "properties": {
    "addr:full":"3904 E Mullan Ave Post Falls ID 83854",
    "addr:housenumber":"3904",
    "addr:postcode":"83854",
    "addr:street":"E Mullan Ave",
    "iso:country":"US",
    "sg:address":"3904 E Mullan Ave",
    "sg:city":"Post Falls",
    "sg:classifiers":[
        {
            "category":"Restaurant",
            "type":"Food & Drink"
        }
    ],
    "sg:menulink":"http://www.allmenus.com/id/post-falls-rathdrum/68445-pizza-factory/menu/",
    "sg:phone":"+1 208 777 4373",
    "sg:postcode":"83854",
    "sg:province":"ID",
    "sg:tags":[
        "american",
        "pizza"
    ],
    "wof:name":"Pizza Factory",
    "wof:placetype":"venue"
},
  "geometry": {"coordinates":[-116.895518,47.715256],"type":"Point"}
}