{
  "type": "Feature",
  "properties": {
    "addr:full":"700 W State St Eagle ID 83616",
    "addr:housenumber":"700",
    "addr:postcode":"83616",
    "addr:street":"W State St",
    "iso:country":"US",
    "sg:address":"700 W State St",
    "sg:city":"Eagle",
    "sg:classifiers":[
        {
            "category":"Organizations",
            "subcategory":"Religious Organization",
            "type":"Services"
        }
    ],
    "sg:phone":"+1 208 939 5556",
    "sg:postcode":"83616",
    "sg:province":"ID",
    "sg:tags":[
        "church"
    ],
    "wof:name":"Church Of Jesus Christ Of Lds",
    "wof:placetype":"venue"
},
  "geometry": {"coordinates":[-116.36521,43.69558],"type":"Point"}
}