{
  "type": "Feature",
  "properties": {
    "addr:full":"1445 N Woodruff Ave Idaho Falls ID 83401",
    "addr:housenumber":"1445",
    "addr:postcode":"83401",
    "addr:street":"N Woodruff Ave",
    "iso:country":"US",
    "sg:address":"1445 N Woodruff Ave",
    "sg:city":"Idaho Falls",
    "sg:classifiers":[
        {
            "category":"Retail",
            "subcategory":"Auto Rental",
            "type":"Services"
        }
    ],
    "sg:phone":"+1 208 529 3970",
    "sg:postcode":"83401",
    "sg:province":"ID",
    "sg:tags":[
        "renting",
        "truck",
        "leasing"
    ],
    "wof:name":"U-Haul Co",
    "wof:placetype":"venue"
},
  "geometry": {"coordinates":[-112.000879,43.511185],"type":"Point"}
}