{
  "type": "Feature",
  "properties": {
    "addr:full":"104 E Fairview Ave 106 Meridian ID 83642",
    "addr:housenumber":"104;106",
    "addr:postcode":"83642",
    "addr:street":"E Fairview Ave;Meridian",
    "iso:country":"US",
    "sg:address":"104 E Fairview Ave 106",
    "sg:city":"Meridian",
    "sg:classifiers":[
        {
            "category":"Professional",
            "subcategory":"Business Services",
            "type":"Services"
        },
        {
            "category":"Professional",
            "subcategory":"Printing & Photocopies",
            "type":"Services"
        }
    ],
    "sg:phone":"+1 208 887 1590",
    "sg:postcode":"83642",
    "sg:province":"ID",
    "sg:tags":[
        "system",
        "form",
        "printers-business"
    ],
    "wof:name":"Professional Business Forms",
    "wof:placetype":"venue"
},
  "geometry": {"coordinates":[-116.39149,43.619272],"type":"Point"}
}