{
  "type": "Feature",
  "properties": {
    "iso:country":"US",
    "sg:address":"170 E Siphon Rd",
    "sg:city":"Pocatello",
    "sg:phone":"+1 208 238 3036",
    "sg:postcode":"83202",
    "sg:province":"ID",
    "sg:tags":[
        "wholesale",
        "good",
        "trade"
    ],
    "sg:website":"www.premiertechnology.cc",
    "wof:name":"Premier Technology Inc",
    "wof:placetype":"venue"
},
  "geometry": {"coordinates":[-112.466004,42.935069],"type":"Point"}
}