{
  "type": "Feature",
  "properties": {
    "iso:country":"US",
    "sg:address":"18125 N Ramsey Rd",
    "sg:city":"Rathdrum",
    "sg:classifiers":[
        {
            "category":"Manufacturing",
            "subcategory":"Tools & Machinery",
            "type":"Manufacturing & Wholesale Goods"
        }
    ],
    "sg:phone":"+1 208 687 1478",
    "sg:postcode":"83858",
    "sg:province":"ID",
    "sg:tags":[
        "equipment",
        "system",
        "automation"
    ],
    "sg:website":"www.pawtaw.com",
    "wof:name":"Paw-Taw-John Svc Inc",
    "wof:placetype":"venue"
},
  "geometry": {"coordinates":[-116.80815699999999,47.832963],"type":"Point"}
}