{
  "type": "Feature",
  "properties": {
    "iso:country":"US",
    "sg:address":"575 E Bower Ave",
    "sg:city":"Meridian",
    "sg:classifiers":[
        {
            "category":"Professional",
            "subcategory":"Business Services",
            "type":"Services"
        }
    ],
    "sg:phone":"+1 208 884 4930",
    "sg:postcode":"83642",
    "sg:province":"ID",
    "sg:tags":[
        "paper"
    ],
    "wof:name":"Shred Pro Inc",
    "wof:placetype":"venue"
},
  "geometry": {"coordinates":[-116.385225,43.60782],"type":"Point"}
}