{
  "type": "Feature",
  "properties": {
    "addr:full":"713 S Main St Bellevue ID 83333",
    "addr:housenumber":"713",
    "addr:postcode":"83333",
    "addr:street":"S Main St",
    "iso:country":"US",
    "sg:address":"713 S Main St",
    "sg:city":"Bellevue",
    "sg:classifiers":[
        {
            "category":"Home & Garden",
            "subcategory":"Building Materials",
            "type":"Retail Goods"
        }
    ],
    "sg:phone":"+1 208 578 9637",
    "sg:postcode":"83333",
    "sg:province":"ID",
    "wof:name":"Paradise Paint & Accessories",
    "wof:placetype":"venue"
},
  "geometry": {"coordinates":[-114.310716,43.513379],"type":"Point"}
}