{
  "type": "Feature",
  "properties": {
    "iso:country":"US",
    "sg:address":"848 Main St",
    "sg:city":"Lewiston",
    "sg:classifiers":[
        {
            "category":"Retail",
            "subcategory":"Repair Shop",
            "type":"Services"
        }
    ],
    "sg:phone":"+1 208 743 0921",
    "sg:postcode":"83501",
    "sg:province":"ID",
    "sg:tags":[
        "jewelry"
    ],
    "wof:name":"Time Shop",
    "wof:placetype":"venue"
},
  "geometry": {"coordinates":[-117.022336,46.419771],"type":"Point"}
}