{
  "type": "Feature",
  "properties": {
    "addr:full":"2025 12th Ave Rd Nampa ID 83686",
    "addr:housenumber":"2025",
    "addr:postcode":"83686",
    "addr:street":"12Th Ave Rd",
    "iso:country":"US",
    "sg:address":"2025 12th Ave Rd",
    "sg:city":"Nampa",
    "sg:classifiers":[
        {
            "category":"Banks & Credit Unions",
            "subcategory":"Bank",
            "type":"Services"
        }
    ],
    "sg:phone":"+1 208 467 9300",
    "sg:postcode":"83686",
    "sg:province":"ID",
    "sg:tags":[
        "loan"
    ],
    "wof:name":"Moneytree",
    "wof:placetype":"venue"
},
  "geometry": {"coordinates":[-116.572868,43.549765],"type":"Point"}
}