{
  "type": "Feature",
  "properties": {
    "addr:full":"861 N Idaho St Post Falls ID 83854",
    "addr:housenumber":"861",
    "addr:postcode":"83854",
    "addr:street":"N Idaho St",
    "iso:country":"US",
    "sg:address":"861 N Idaho St",
    "sg:city":"Post Falls",
    "sg:classifiers":[
        {
            "category":"Shopping",
            "subcategory":"Tobacco",
            "type":"Retail Goods"
        }
    ],
    "sg:phone":"+1 208 773 8691",
    "sg:postcode":"83854",
    "sg:province":"ID",
    "sg:tags":[
        "cigarette",
        "cigar",
        "dealer"
    ],
    "wof:name":"Cigarette Store",
    "wof:placetype":"venue"
},
  "geometry": {"coordinates":[-116.937324,47.716923],"type":"Point"}
}