{
  "type": "Feature",
  "properties": {
    "iso:country":"US",
    "sg:address":"598 N Capital Ave",
    "sg:city":"Idaho Falls",
    "sg:classifiers":[
        {
            "category":"Professional",
            "subcategory":"Lawyer & Legal Services",
            "type":"Services"
        }
    ],
    "sg:phone":"+1 208 542 6995",
    "sg:postcode":"83402",
    "sg:province":"ID",
    "sg:tags":[
        "attorney"
    ],
    "wof:name":"Curtis & Browning Law Offices",
    "wof:placetype":"venue"
},
  "geometry": {"coordinates":[-112.041219,43.493969],"type":"Point"}
}