{
  "type": "Feature",
  "properties": {
    "addr:full":"741 W Poleline Rd Rexburg ID 83440",
    "addr:housenumber":"741",
    "addr:postcode":"83440",
    "addr:street":"W Poleline Rd",
    "iso:country":"US",
    "sg:address":"741 W Poleline Rd",
    "sg:city":"Rexburg",
    "sg:classifiers":[
        {
            "category":"Professional",
            "subcategory":"Accounting & Tax Preparation",
            "type":"Services"
        }
    ],
    "sg:phone":"+1 208 359 1266",
    "sg:postcode":"83440",
    "sg:province":"ID",
    "sg:tags":[
        "accountant"
    ],
    "wof:name":"Padgett Business Svc",
    "wof:placetype":"venue"
},
  "geometry": {"coordinates":[-111.79004500000001,43.797103],"type":"Point"}
}