{
  "type": "Feature",
  "properties": {
    "iso:country":"US",
    "sg:address":"640 16th St",
    "sg:city":"Heyburn",
    "sg:classifiers":[
        {
            "category":"Wholesale",
            "subcategory":"Hardware",
            "type":"Manufacturing & Wholesale Goods"
        }
    ],
    "sg:phone":"+1 208 678 7102",
    "sg:postcode":"83336",
    "sg:province":"ID",
    "sg:tags":[
        "fastener"
    ],
    "wof:name":"Magic Valley Abrasives Inc",
    "wof:placetype":"venue"
},
  "geometry": {"coordinates":[-113.75234500000001,42.556378],"type":"Point"}
}