{
  "type": "Feature",
  "properties": {
    "iso:country":"US",
    "sg:address":"209 N 3rd St",
    "sg:city":"Mccall",
    "sg:classifiers":[
        {
            "category":"Restaurant",
            "type":"Food & Drink"
        }
    ],
    "sg:phone":"+1 208 634 5849",
    "sg:postcode":"83638",
    "sg:province":"ID",
    "wof:name":"Pancake House",
    "wof:placetype":"venue"
},
  "geometry": {"coordinates":[-116.09716299999999,44.89952],"type":"Point"}
}