{
  "type": "Feature",
  "properties": {
    "iso:country":"US",
    "sg:address":"617 N Orchard St",
    "sg:city":"Boise",
    "sg:classifiers":[
        {
            "category":"Personal",
            "subcategory":"Beauty Salon",
            "type":"Services"
        }
    ],
    "sg:phone":"+1 208 672 0593",
    "sg:postcode":"83706",
    "sg:province":"ID",
    "sg:tags":[
        "manicuring"
    ],
    "wof:name":"Exotic Nails",
    "wof:placetype":"venue"
},
  "geometry": {"coordinates":[-116.243529,43.610559],"type":"Point"}
}