{
  "type": "Feature",
  "properties": {
    "iso:country":"US",
    "sg:address":"304 N Main St",
    "sg:city":"Pocatello",
    "sg:classifiers":[
        {
            "category":"Bars & Pubs",
            "type":"Food & Drink"
        }
    ],
    "sg:phone":"+1 208 232 9347",
    "sg:postcode":"83204",
    "sg:province":"ID",
    "wof:name":"Oasis Sports Bar",
    "wof:placetype":"venue"
},
  "geometry": {"coordinates":[-112.453146,42.864384],"type":"Point"}
}