{
  "type": "Feature",
  "properties": {
    "iso:country":"US",
    "sg:address":"40 Superior St",
    "sg:city":"Cambridge",
    "sg:classifiers":[
        {
            "category":"Social Services",
            "type":"Services"
        }
    ],
    "sg:phone":"+1 208 257 3358",
    "sg:postcode":"83610",
    "sg:province":"ID",
    "sg:tags":[
        "senior",
        "citizen"
    ],
    "wof:name":"Cambridge Senior Citizens",
    "wof:placetype":"venue"
},
  "geometry": {"coordinates":[-116.67695399999999,44.571267],"type":"Point"}
}