{
  "type": "Feature",
  "properties": {
    "iso:country":"US",
    "sg:address":"401 S 9th St",
    "sg:city":"Boise",
    "sg:classifiers":[
        {
            "category":"Professional",
            "subcategory":"Accounting & Tax Preparation",
            "type":"Services"
        }
    ],
    "sg:phone":"+1 208 345 3426",
    "sg:postcode":"83702",
    "sg:province":"ID",
    "sg:tags":[
        "return",
        "filing"
    ],
    "wof:name":"Economical Tax Preperation",
    "wof:placetype":"venue"
},
  "geometry": {"coordinates":[-116.207594,43.613164],"type":"Point"}
}