{
  "type": "Feature",
  "properties": {
    "iso:country":"US",
    "sg:address":"205 W Ellis St",
    "sg:city":"Paul",
    "sg:classifiers":[
        {
            "category":"Autos & Motor Vehicles",
            "subcategory":"Auto Supplies",
            "type":"Retail Goods"
        }
    ],
    "sg:phone":"+1 208 438 5400",
    "sg:postcode":"83347",
    "sg:province":"ID",
    "sg:tags":[
        "automobile",
        "parts"
    ],
    "wof:name":"Snyder's Paul Automotive",
    "wof:placetype":"venue"
},
  "geometry": {"coordinates":[-113.786226,42.605099],"type":"Point"}
}