{
  "type": "Feature",
  "properties": {
    "iso:country":"US",
    "sg:address":"152 Park Ave",
    "sg:city":"Idaho Falls",
    "sg:classifiers":[
        {
            "category":"Home & Garden",
            "subcategory":"Garden Supply",
            "type":"Retail Goods"
        }
    ],
    "sg:phone":"+1 208 525 8183",
    "sg:postcode":"83402",
    "sg:province":"ID",
    "sg:tags":[
        "lawn",
        "mower"
    ],
    "wof:name":"Honda Power Products",
    "wof:placetype":"venue"
},
  "geometry": {"coordinates":[-112.04182900000001,43.491039],"type":"Point"}
}