{
  "type": "Feature",
  "properties": {
    "iso:country":"US",
    "sg:address":"131 N Milwaukee St",
    "sg:city":"Boise",
    "sg:classifiers":[
        {
            "category":"Shopping",
            "subcategory":"Hobbies, Toys, & Games",
            "type":"Retail Goods"
        }
    ],
    "sg:phone":"+1 208 322 4303",
    "sg:postcode":"83704",
    "sg:province":"ID",
    "wof:name":"Toys R Us",
    "wof:placetype":"venue"
},
  "geometry": {"coordinates":[-116.28166,43.606317],"type":"Point"}
}