{
  "type": "Feature",
  "properties": {
    "iso:country":"US",
    "sg:address":"29905 Golden Apple Ln",
    "sg:city":"Lapwai",
    "sg:phone":"+1 208 843 2507",
    "sg:postcode":"83540",
    "sg:province":"ID",
    "sg:tags":[
        "beef",
        "farm",
        "crop",
        "field",
        "cattle",
        "feedlot"
    ],
    "wof:name":"Lynn Lasswell",
    "wof:placetype":"venue"
},
  "geometry": {"coordinates":[-116.775205,46.357227],"type":"Point"}
}