{
  "type": "Feature",
  "properties": {
    "iso:country":"US",
    "sg:address":"1446 Sea Gull Ln",
    "sg:city":"Lewiston",
    "sg:classifiers":[
        {
            "category":"Shopping",
            "type":"Retail Goods"
        }
    ],
    "sg:phone":"+1 208 791 3660",
    "sg:postcode":"83501",
    "sg:province":"ID",
    "sg:tags":[
        "merchandise"
    ],
    "wof:name":"Super Auto Depot Inc.",
    "wof:placetype":"venue"
},
  "geometry": {"coordinates":[-116.97983,46.406644],"type":"Point"}
}