{
  "type": "Feature",
  "properties": {
    "iso:country":"US",
    "sg:address":"246 N 8th St",
    "sg:city":"Boise",
    "sg:classifiers":[
        {
            "category":"Restaurant",
            "type":"Food & Drink"
        }
    ],
    "sg:menulink":"http://www.allmenus.com/id/boise-city/26030-red-feather/menu/",
    "sg:phone":"+1 208 429 6240",
    "sg:postcode":"83702",
    "sg:province":"ID",
    "sg:tags":[
        "new",
        "american"
    ],
    "wof:name":"Red Feather",
    "wof:placetype":"venue"
},
  "geometry": {"coordinates":[-116.20238000000001,43.616753],"type":"Point"}
}