{
  "type": "Feature",
  "properties": {
    "iso:country":"US",
    "sg:address":"339 Main St",
    "sg:city":"Ririe",
    "sg:classifiers":[
        {
            "category":"Restaurant",
            "type":"Food & Drink"
        }
    ],
    "sg:phone":"+1 208 538 7226",
    "sg:postcode":"83443",
    "sg:province":"ID",
    "wof:name":"Sweet Surrender Breads",
    "wof:placetype":"venue"
},
  "geometry": {"coordinates":[-111.773658,43.630246],"type":"Point"}
}