{
  "type": "Feature",
  "properties": {
    "addr:full":"2934 N Mountain Rd Boise ID 83702",
    "addr:housenumber":"2934",
    "addr:postcode":"83702",
    "addr:street":"N Mountain Rd",
    "iso:country":"US",
    "sg:address":"2934 N Mountain Rd",
    "sg:city":"Boise",
    "sg:classifiers":[
        {
            "category":"Professional",
            "type":"Services"
        }
    ],
    "sg:phone":"+1 208 345 8317",
    "sg:postcode":"83702",
    "sg:province":"ID",
    "wof:name":"Showerworks LLC",
    "wof:placetype":"venue"
},
  "geometry": {"coordinates":[-116.216227,43.648217],"type":"Point"}
}