{
  "type": "Feature",
  "properties": {
    "addr:full":"517 S 9th St Payette ID 83661",
    "addr:housenumber":"517",
    "addr:postcode":"83661",
    "addr:street":"S 9Th St",
    "iso:country":"US",
    "sg:address":"517 S 9th St",
    "sg:city":"Payette",
    "sg:classifiers":[
        {
            "category":"Autos & Motor Vehicles",
            "subcategory":"Auto Supplies",
            "type":"Retail Goods"
        }
    ],
    "sg:phone":"+1 208 642 3586",
    "sg:postcode":"83661",
    "sg:province":"ID",
    "sg:tags":[
        "tire"
    ],
    "wof:name":"Rt's Commercial Tire",
    "wof:placetype":"venue"
},
  "geometry": {"coordinates":[-116.933367,44.06789],"type":"Point"}
}