{
  "type": "Feature",
  "properties": {
    "iso:country":"US",
    "sg:address":"919 E Park St",
    "sg:city":"Weiser",
    "sg:classifiers":[
        {
            "category":"Farming",
            "subcategory":"Farm",
            "type":"Manufacturing & Wholesale Goods"
        }
    ],
    "sg:phone":"+1 208 549 0303",
    "sg:postcode":"83672",
    "sg:province":"ID",
    "sg:tags":[
        "crop",
        "general"
    ],
    "wof:name":"Sara Torres Farm Labor Contrac",
    "wof:placetype":"venue"
},
  "geometry": {"coordinates":[-116.953157,44.249063],"type":"Point"}
}