{
  "type": "Feature",
  "properties": {
    "iso:country":"US",
    "sg:address":"23258 el Paso Rd",
    "sg:city":"Caldwell",
    "sg:classifiers":[
        {
            "category":"Farming",
            "subcategory":"Dairy Farm",
            "type":"Manufacturing & Wholesale Goods"
        }
    ],
    "sg:phone":"+1 208 454 1794",
    "sg:postcode":"83607",
    "sg:province":"ID",
    "wof:name":"Stan Bland",
    "wof:placetype":"venue"
},
  "geometry": {"coordinates":[-116.69278,43.710035],"type":"Point"}
}