{
  "type": "Feature",
  "properties": {
    "iso:country":"US",
    "sg:address":"791 Brundage St",
    "sg:city":"Pocatello",
    "sg:classifiers":[
        {
            "category":"Professional",
            "subcategory":"Management & Consulting",
            "type":"Services"
        }
    ],
    "sg:phone":"+1 208 244 1775",
    "sg:postcode":"83202",
    "sg:province":"ID",
    "wof:name":"Fred Flynn Consulting",
    "wof:placetype":"venue"
},
  "geometry": {"coordinates":[-112.449709,42.916251],"type":"Point"}
}