{
  "type": "Feature",
  "properties": {
    "iso:country":"US",
    "sg:address":"8990 Overland Rd",
    "sg:city":"Boise",
    "sg:classifiers":[
        {
            "category":"Food & Beverages",
            "subcategory":"Groceries & Convenience Stores",
            "type":"Retail Goods"
        }
    ],
    "sg:phone":"+1 208 376 9772",
    "sg:postcode":"83709",
    "sg:province":"ID",
    "wof:name":"Jackson's Food",
    "wof:placetype":"venue"
},
  "geometry": {"coordinates":[-116.29248699999999,43.590261],"type":"Point"}
}