{
  "type": "Feature",
  "properties": {
    "iso:country":"US",
    "sg:address":"2842 Pocatello Ave",
    "sg:city":"American Falls",
    "sg:classifiers":[
        {
            "category":"Health Services",
            "subcategory":"Chiropractor",
            "type":"Services"
        }
    ],
    "sg:phone":"+1 208 226 2338",
    "sg:postcode":"83211",
    "sg:province":"ID",
    "wof:name":"Hatt Chiropractic",
    "wof:placetype":"venue"
},
  "geometry": {"coordinates":[-112.83741999999999,42.790247],"type":"Point"}
}