{
  "type": "Feature",
  "properties": {
    "iso:country":"US",
    "sg:address":"1 E Owyhee Ave",
    "sg:city":"Homedale",
    "sg:classifiers":[
        {
            "category":"Home & Garden",
            "subcategory":"Hardware",
            "type":"Retail Goods"
        }
    ],
    "sg:phone":"+1 208 337 5006",
    "sg:postcode":"83624",
    "sg:province":"ID",
    "wof:name":"Tolmie's Ace Hardware",
    "wof:placetype":"venue"
},
  "geometry": {"coordinates":[-116.93428299999999,43.618722],"type":"Point"}
}