{
  "type": "Feature",
  "properties": {
    "iso:country":"US",
    "sg:address":"2085 Niagara St",
    "sg:city":"Idaho Falls",
    "sg:classifiers":[
        {
            "category":"Cinema",
            "subcategory":"Movie Theater",
            "type":"Entertainment"
        }
    ],
    "sg:phone":"+1 208 523 1142",
    "sg:postcode":"83404",
    "sg:province":"ID",
    "wof:name":"Paramount Theatre",
    "wof:placetype":"venue"
},
  "geometry": {"coordinates":[-111.99291700000001,43.480715],"type":"Point"}
}