{
  "type": "Feature",
  "properties": {
    "addr:full":"25736 N Clagstone Rd Athol ID 83801",
    "addr:housenumber":"25736",
    "addr:postcode":"83801",
    "addr:street":"N Clagstone Rd",
    "iso:country":"US",
    "sg:address":"25736 N Clagstone Rd",
    "sg:city":"Athol",
    "sg:classifiers":[
        {
            "category":"Building & Trades",
            "subcategory":"Construction",
            "type":"Services"
        }
    ],
    "sg:phone":"+1 208 683 0550",
    "sg:postcode":"83801",
    "sg:province":"ID",
    "sg:tags":[
        "home",
        "builder"
    ],
    "wof:name":"Maplewood Homes Inc",
    "wof:placetype":"venue"
},
  "geometry": {"coordinates":[-116.742141,47.907532],"type":"Point"}
}