{
  "type": "Feature",
  "properties": {
    "addr:full":"10009 Emerald St Boise ID 83704",
    "addr:housenumber":"10009",
    "addr:postcode":"83704",
    "addr:street":"Emerald St",
    "iso:country":"US",
    "sg:address":"10009 Emerald St",
    "sg:city":"Boise",
    "sg:classifiers":[
        {
            "category":"Wholesale",
            "subcategory":"Furniture",
            "type":"Manufacturing & Wholesale Goods"
        }
    ],
    "sg:phone":"+1 208 377 1010",
    "sg:postcode":"83704",
    "sg:province":"ID",
    "wof:name":"Corporate Express",
    "wof:placetype":"venue"
},
  "geometry": {"coordinates":[-116.305178,43.609537],"type":"Point"}
}