{
  "type": "Feature",
  "properties": {
    "iso:country":"US",
    "sg:address":"8010 E Ohio Match Rd",
    "sg:city":"Hayden Lake",
    "sg:classifiers":[
        {
            "category":"Retail",
            "subcategory":"Repair Shop",
            "type":"Services"
        }
    ],
    "sg:phone":"+1 208 762 7771",
    "sg:postcode":"83835",
    "sg:province":"ID",
    "sg:tags":[
        "plumbing",
        "drain",
        "cleaning",
        "sewer"
    ],
    "wof:name":"Ray's Plumbing & Heating",
    "wof:placetype":"venue"
},
  "geometry": {"coordinates":[-116.678727,47.828334],"type":"Point"}
}