{
  "type": "Feature",
  "properties": {
    "addr:full":"2680 Desert Dr Idaho Falls ID 83404",
    "addr:housenumber":"2680",
    "addr:postcode":"83404",
    "addr:street":"Desert Dr",
    "iso:country":"US",
    "sg:address":"2680 Desert Dr",
    "sg:city":"Idaho Falls",
    "sg:classifiers":[
        {
            "category":"Professional",
            "subcategory":"Management & Consulting",
            "type":"Services"
        }
    ],
    "sg:phone":"+1 208 520 7307",
    "sg:postcode":"83404",
    "sg:province":"ID",
    "sg:tags":[
        "business"
    ],
    "wof:name":"Strategic Partnering",
    "wof:placetype":"venue"
},
  "geometry": {"coordinates":[-112.017366,43.473421],"type":"Point"}
}