{
  "type": "Feature",
  "properties": {
    "iso:country":"US",
    "sg:address":"1308 E 17th St",
    "sg:city":"Idaho Falls",
    "sg:classifiers":[
        {
            "category":"Professional",
            "subcategory":"Accounting & Tax Preparation",
            "type":"Services"
        }
    ],
    "sg:phone":"+1 208 542 9467",
    "sg:postcode":"83404",
    "sg:province":"ID",
    "sg:tags":[
        "return",
        "filing"
    ],
    "wof:name":"Continental Loans",
    "wof:placetype":"venue"
},
  "geometry": {"coordinates":[-112.00786100000001,43.482297],"type":"Point"}
}