{
  "type": "Feature",
  "properties": {
    "addr:full":"970 Wilson Ave Pocatello ID 83201",
    "addr:housenumber":"970",
    "addr:postcode":"83201",
    "addr:street":"Wilson Ave",
    "iso:country":"US",
    "sg:address":"970 Wilson Ave",
    "sg:city":"Pocatello",
    "sg:classifiers":[
        {
            "category":"Restaurant",
            "type":"Food & Drink"
        }
    ],
    "sg:phone":"+1 208 233 4758",
    "sg:postcode":"83201",
    "sg:province":"ID",
    "sg:tags":[
        "eating"
    ],
    "wof:name":"Taco Bell",
    "wof:placetype":"venue"
},
  "geometry": {"coordinates":[-112.452856,42.892898],"type":"Point"}
}