{
  "type": "Feature",
  "properties": {
    "iso:country":"US",
    "sg:address":"5111 Alworth St",
    "sg:city":"Boise",
    "sg:classifiers":[
        {
            "category":"Building & Trades",
            "subcategory":"Construction",
            "type":"Services"
        }
    ],
    "sg:phone":"+1 208 321 4399",
    "sg:postcode":"83714",
    "sg:province":"ID",
    "sg:tags":[
        "contractor"
    ],
    "wof:name":"Creative Building Resources",
    "wof:placetype":"venue"
},
  "geometry": {"coordinates":[-116.267357,43.647342],"type":"Point"}
}