{
  "type": "Feature",
  "properties": {
    "iso:country":"US",
    "sg:address":"1766 Beaman Rd",
    "sg:city":"Mountain Home",
    "sg:classifiers":[
        {
            "category":"Building & Trades",
            "subcategory":"Construction",
            "type":"Services"
        }
    ],
    "sg:phone":"+1 208 587 5182",
    "sg:postcode":"83647",
    "sg:province":"ID",
    "sg:tags":[
        "house"
    ],
    "wof:name":"D&B Home Improvement",
    "wof:placetype":"venue"
},
  "geometry": {"coordinates":[-115.677763,43.1702],"type":"Point"}
}