{
  "type": "Feature",
  "properties": {
    "iso:country":"US",
    "sg:address":"1442 Monte Vista Dr",
    "sg:city":"Pocatello",
    "sg:classifiers":[
        {
            "category":"Manufacturing",
            "subcategory":"Wood Products",
            "type":"Manufacturing & Wholesale Goods"
        }
    ],
    "sg:phone":"+1 208 235 1825",
    "sg:postcode":"83201",
    "sg:province":"ID",
    "wof:name":"Wood Shop",
    "wof:placetype":"venue"
},
  "geometry": {"coordinates":[-112.436396,42.890067],"type":"Point"}
}