{
  "type": "Feature",
  "properties": {
    "addr:full":"817 W Ustick Rd Caldwell ID 83605",
    "addr:housenumber":"817",
    "addr:postcode":"83605",
    "addr:street":"W Ustick Rd",
    "iso:country":"US",
    "sg:address":"817 W Ustick Rd",
    "sg:city":"Caldwell",
    "sg:classifiers":[
        {
            "category":"Organizations",
            "subcategory":"Religious Organization",
            "type":"Services"
        }
    ],
    "sg:phone":"+1 208 459 2262",
    "sg:postcode":"83605",
    "sg:province":"ID",
    "sg:tags":[
        "church"
    ],
    "wof:name":"Ustick Road Church Of Nazarene",
    "wof:placetype":"venue"
},
  "geometry": {"coordinates":[-116.706817,43.633355],"type":"Point"}
}