{
  "type": "Feature",
  "properties": {
    "iso:country":"US",
    "sg:address":"670 1st St",
    "sg:city":"Idaho Falls",
    "sg:classifiers":[
        {
            "category":"Sports & Exercise",
            "subcategory":"Bowling",
            "type":"Entertainment"
        }
    ],
    "sg:phone":"+1 208 524 9900",
    "sg:postcode":"83401",
    "sg:province":"ID",
    "sg:tags":[
        "center"
    ],
    "wof:name":"Bowl Ero",
    "wof:placetype":"venue"
},
  "geometry": {"coordinates":[-112.020084,43.496837],"type":"Point"}
}