{
  "type": "Feature",
  "properties": {
    "iso:country":"US",
    "sg:address":"1022 E 8th St",
    "sg:city":"Moscow",
    "sg:classifiers":[
        {
            "category":"Professional",
            "subcategory":"Detective & Security Services",
            "type":"Services"
        }
    ],
    "sg:phone":"+1 208 883 8387",
    "sg:postcode":"83843",
    "sg:province":"ID",
    "sg:tags":[
        "guard"
    ],
    "wof:name":"Harry R Moran",
    "wof:placetype":"venue"
},
  "geometry": {"coordinates":[-116.985353,46.728144],"type":"Point"}
}