{
  "type": "Feature",
  "properties": {
    "iso:country":"US",
    "sg:address":"269 W Center St",
    "sg:city":"Shelley",
    "sg:classifiers":[
        {
            "category":"Manufacturing",
            "subcategory":"Jewelry",
            "type":"Manufacturing & Wholesale Goods"
        }
    ],
    "sg:phone":"+1 208 357 3348",
    "sg:postcode":"83274",
    "sg:province":"ID",
    "sg:tags":[
        "lapidary"
    ],
    "wof:name":"Anderson Rock Shop",
    "wof:placetype":"venue"
},
  "geometry": {"coordinates":[-112.126621,43.381435],"type":"Point"}
}