{
  "type": "Feature",
  "properties": {
    "iso:country":"US",
    "sg:address":"2421 Meridian Rd",
    "sg:city":"Eagle",
    "sg:classifiers":[
        {
            "category":"Building & Trades",
            "subcategory":"Construction",
            "type":"Services"
        }
    ],
    "sg:phone":"+1 208 938 0252",
    "sg:postcode":"83616",
    "sg:province":"ID",
    "sg:tags":[
        "house"
    ],
    "wof:name":"Shae Construction Inc",
    "wof:placetype":"venue"
},
  "geometry": {"coordinates":[-116.393574,43.719481],"type":"Point"}
}