{
  "type": "Feature",
  "properties": {
    "addr:full":"3563 Waldon St Boise ID 83709",
    "addr:housenumber":"3563",
    "addr:postcode":"83709",
    "addr:street":"Waldon St",
    "iso:country":"US",
    "sg:address":"3563 Waldon St",
    "sg:city":"Boise",
    "sg:classifiers":[
        {
            "category":"Manufacturing",
            "subcategory":"Retail Goods",
            "type":"Manufacturing & Wholesale Goods"
        }
    ],
    "sg:phone":"+1 208 562 0434",
    "sg:postcode":"83709",
    "sg:province":"ID",
    "sg:tags":[
        "manufacturer"
    ],
    "wof:name":"Dr Bobs Cowboy Crafts",
    "wof:placetype":"venue"
},
  "geometry": {"coordinates":[-116.272164,43.57031],"type":"Point"}
}