{
  "type": "Feature",
  "properties": {
    "addr:full":"250 S Skyline Dr Idaho Falls ID 83402",
    "addr:housenumber":"250",
    "addr:postcode":"83402",
    "addr:street":"S Skyline Dr",
    "iso:country":"US",
    "sg:address":"250 S Skyline Dr",
    "sg:city":"Idaho Falls",
    "sg:classifiers":[
        {
            "category":"Health Services",
            "subcategory":"Doctor",
            "type":"Services"
        }
    ],
    "sg:phone":"+1 208 529 9292",
    "sg:postcode":"83402",
    "sg:province":"ID",
    "sg:tags":[
        "physician",
        "surgeon"
    ],
    "wof:name":"Idaho Allergy & Asthma Clinic",
    "wof:placetype":"venue"
},
  "geometry": {"coordinates":[-112.063362,43.495518],"type":"Point"}
}