{
  "type": "Feature",
  "properties": {
    "addr:full":"1365 N Orchard St Boise ID 83706",
    "addr:housenumber":"1365",
    "addr:postcode":"83706",
    "addr:street":"N Orchard St",
    "iso:country":"US",
    "sg:address":"1365 N Orchard St",
    "sg:city":"Boise",
    "sg:classifiers":[
        {
            "category":"Autos & Motor Vehicles",
            "subcategory":"Recreational Vehicle Sales",
            "type":"Retail Goods"
        }
    ],
    "sg:phone":"+1 208 323 0652",
    "sg:postcode":"83706",
    "sg:province":"ID",
    "sg:tags":[
        "parts",
        "trailer"
    ],
    "wof:name":"Di-Pro Inc",
    "wof:placetype":"venue"
},
  "geometry": {"coordinates":[-116.243359,43.615806],"type":"Point"}
}