{
  "type": "Feature",
  "properties": {
    "addr:full":"73 N Center St Rexburg ID 83440",
    "addr:housenumber":"73",
    "addr:postcode":"83440",
    "addr:street":"N Center St",
    "iso:country":"US",
    "sg:address":"73 N Center St",
    "sg:city":"Rexburg",
    "sg:classifiers":[
        {
            "category":"Education",
            "subcategory":"Library",
            "type":"Public Place"
        }
    ],
    "sg:phone":"+1 208 356 3461",
    "sg:postcode":"83440",
    "sg:province":"ID",
    "wof:name":"Madison Library District",
    "wof:placetype":"venue"
},
  "geometry": {"coordinates":[-111.783889,43.826628],"type":"Point"}
}