{
  "type": "Feature",
  "properties": {
    "iso:country":"US",
    "sg:address":"819 US Hwy 2",
    "sg:city":"Sandpoint",
    "sg:classifiers":[
        {
            "category":"Social Services",
            "type":"Services"
        }
    ],
    "sg:phone":"+1 208 263 6141",
    "sg:postcode":"83864",
    "sg:province":"ID",
    "sg:tags":[
        "counseling"
    ],
    "wof:name":"Panhandle Behavioral Health",
    "wof:placetype":"venue"
},
  "geometry": {"coordinates":[-116.552952,48.281582],"type":"Point"}
}