{
  "type": "Feature",
  "properties": {
    "addr:full":"1162 Bone Rd Iona ID 83427",
    "addr:housenumber":"1162",
    "addr:postcode":"83427",
    "addr:street":"Bone Rd",
    "iso:country":"US",
    "sg:address":"1162 Bone Rd",
    "sg:city":"Iona",
    "sg:phone":"+1 208 529 4206",
    "sg:postcode":"83427",
    "sg:province":"ID",
    "sg:tags":[
        "farm",
        "corn"
    ],
    "wof:name":"Van Sandifer",
    "wof:placetype":"venue"
},
  "geometry": {"coordinates":[-111.806382,43.373841],"type":"Point"}
}