{
  "type": "Feature",
  "properties": {
    "iso:country":"US",
    "sg:address":"1749 E 400 S",
    "sg:city":"Jerome",
    "sg:classifiers":[
        {
            "category":"Farming",
            "subcategory":"Farm",
            "type":"Manufacturing & Wholesale Goods"
        }
    ],
    "sg:phone":"+1 208 825 5564",
    "sg:postcode":"83338",
    "sg:province":"ID",
    "wof:name":"J & K Farms Inc",
    "wof:placetype":"venue"
},
  "geometry": {"coordinates":[-114.169222,42.663329],"type":"Point"}
}