{
  "type": "Feature",
  "properties": {
    "addr:full":"4380 Stockman Rd Pocatello ID 83204",
    "addr:housenumber":"4380",
    "addr:postcode":"83204",
    "addr:street":"Stockman Rd",
    "iso:country":"US",
    "sg:address":"4380 Stockman Rd",
    "sg:city":"Pocatello",
    "sg:classifiers":[
        {
            "category":"Shopping",
            "subcategory":"Hobbies, Toys, & Games",
            "type":"Retail Goods"
        }
    ],
    "sg:phone":"+1 208 234 1167",
    "sg:postcode":"83204",
    "sg:province":"ID",
    "sg:tags":[
        "miniature",
        "collector",
        "for",
        "item"
    ],
    "wof:name":"Teddy's Treasures Miniature",
    "wof:placetype":"venue"
},
  "geometry": {"coordinates":[-112.40003400000001,42.83562],"type":"Point"}
}