{
  "type": "Feature",
  "properties": {
    "iso:country":"US",
    "sg:address":"2348 E 200 N",
    "sg:city":"St Anthony",
    "sg:classifiers":[
        {
            "category":"Farming",
            "subcategory":"Farm",
            "type":"Manufacturing & Wholesale Goods"
        }
    ],
    "sg:phone":"+1 208 458 4364",
    "sg:postcode":"83445",
    "sg:province":"ID",
    "wof:name":"T & S Farms",
    "wof:placetype":"venue"
},
  "geometry": {"coordinates":[-111.687476,43.91243],"type":"Point"}
}