{
  "type": "Feature",
  "properties": {
    "addr:full":"978 W Alameda Rd Pocatello ID 83201",
    "addr:housenumber":"978",
    "addr:postcode":"83201",
    "addr:street":"W Alameda Rd",
    "iso:country":"US",
    "sg:address":"978 W Alameda Rd",
    "sg:city":"Pocatello",
    "sg:classifiers":[
        {
            "category":"Real Estate",
            "subcategory":"Real Estate Agent",
            "type":"Services"
        }
    ],
    "sg:phone":"+1 208 237 2600",
    "sg:postcode":"83201",
    "sg:province":"ID",
    "sg:website":"www.pocatellorealtors.com",
    "wof:name":"Greater Pocatello Assoc",
    "wof:placetype":"venue"
},
  "geometry": {"coordinates":[-112.472796,42.891514],"type":"Point"}
}