{
  "type": "Feature",
  "properties": {
    "addr:full":"1515 Delphic Way Pocatello ID 83201",
    "addr:housenumber":"1515",
    "addr:postcode":"83201",
    "addr:street":"Delphic Way",
    "iso:country":"US",
    "sg:address":"1515 Delphic Way",
    "sg:city":"Pocatello",
    "sg:classifiers":[
        {
            "category":"Freight",
            "type":"Transportation"
        }
    ],
    "sg:phone":"+1 208 237 0891",
    "sg:postcode":"83201",
    "sg:province":"ID",
    "sg:tags":[
        "forwarder"
    ],
    "wof:name":"Elco Industries Ltd",
    "wof:placetype":"venue"
},
  "geometry": {"coordinates":[-112.433136,42.907339],"type":"Point"}
}