{
  "type": "Feature",
  "properties": {
    "iso:country":"US",
    "sg:address":"10145 N Government Way",
    "sg:city":"Hayden",
    "sg:classifiers":[
        {
            "category":"Home & Garden",
            "subcategory":"Building Materials",
            "type":"Retail Goods"
        }
    ],
    "sg:phone":"+1 208 772 4858",
    "sg:postcode":"83835",
    "sg:province":"ID",
    "sg:tags":[
        "roofing"
    ],
    "wof:name":"SRS-Systems Roofers Supply",
    "wof:placetype":"venue"
},
  "geometry": {"coordinates":[-116.786598,47.763983],"type":"Point"}
}