{
  "type": "Feature",
  "properties": {
    "addr:full":"11674 W Dallan Dr Boise ID 83713",
    "addr:housenumber":"11674",
    "addr:postcode":"83713",
    "addr:street":"W Dallan Dr",
    "iso:country":"US",
    "sg:address":"11674 W Dallan Dr",
    "sg:city":"Boise",
    "sg:classifiers":[
        {
            "category":"Retail",
            "subcategory":"Auto Repair",
            "type":"Services"
        }
    ],
    "sg:phone":"+1 208 376 6686",
    "sg:postcode":"83713",
    "sg:province":"ID",
    "sg:tags":[
        "body",
        "automobile",
        "painting"
    ],
    "wof:name":"Automedic Inc",
    "wof:placetype":"venue"
},
  "geometry": {"coordinates":[-116.33124100000001,43.649705],"type":"Point"}
}