{
  "type": "Feature",
  "properties": {
    "addr:full":"10312 N Bateman St Hayden ID 83835",
    "addr:housenumber":"10312",
    "addr:postcode":"83835",
    "addr:street":"N Bateman St",
    "iso:country":"US",
    "sg:address":"10312 N Bateman St",
    "sg:city":"Hayden",
    "sg:classifiers":[
        {
            "category":"Restaurant",
            "type":"Food & Drink"
        }
    ],
    "sg:phone":"+1 208 772 6486",
    "sg:postcode":"83835",
    "sg:province":"ID",
    "sg:tags":[
        "eating"
    ],
    "wof:name":"Dougs Dogs",
    "wof:placetype":"venue"
},
  "geometry": {"coordinates":[-116.768305,47.765953],"type":"Point"}
}