{
  "type": "Feature",
  "properties": {
    "addr:full":"934 10th Ave E Jerome ID 83338",
    "addr:housenumber":"934",
    "addr:postcode":"83338",
    "addr:street":"10Th Ave E",
    "iso:country":"US",
    "sg:address":"934 10th Ave E",
    "sg:city":"Jerome",
    "sg:classifiers":[
        {
            "category":"Education",
            "subcategory":"School",
            "type":"Public Place"
        }
    ],
    "sg:phone":"+1 208 324 4841",
    "sg:postcode":"83338",
    "sg:province":"ID",
    "wof:name":"Horizon Elementary School",
    "wof:placetype":"venue"
},
  "geometry": {"coordinates":[-114.502099,42.73317],"type":"Point"}
}