{
  "type": "Feature",
  "properties": {
    "iso:country":"US",
    "sg:address":"31 Old Crouch Rd",
    "sg:city":"Garden Valley",
    "sg:classifiers":[
        {
            "category":"Retail",
            "subcategory":"Auto Repair",
            "type":"Services"
        }
    ],
    "sg:phone":"+1 208 462 8022",
    "sg:postcode":"83622",
    "sg:province":"ID",
    "sg:tags":[
        "general"
    ],
    "wof:name":"Toms Car Care",
    "wof:placetype":"venue"
},
  "geometry": {"coordinates":[-115.969553,44.103496],"type":"Point"}
}