{
  "type": "Feature",
  "properties": {
    "iso:country":"US",
    "sg:address":"21259 US Hwy 30",
    "sg:city":"Filer",
    "sg:classifiers":[
        {
            "category":"Home & Garden",
            "subcategory":"Garden Supply",
            "type":"Retail Goods"
        }
    ],
    "sg:phone":"+1 208 734 1336",
    "sg:postcode":"83328",
    "sg:province":"ID",
    "sg:tags":[
        "lawn",
        "mower"
    ],
    "wof:name":"Magic Valley Rv & Mower",
    "wof:placetype":"venue"
},
  "geometry": {"coordinates":[-114.562568,42.563672],"type":"Point"}
}