{
  "type": "Feature",
  "properties": {
    "iso:country":"US",
    "sg:address":"2120 N 3rd St",
    "sg:city":"Coeur D Alene",
    "sg:classifiers":[
        {
            "category":"Real Estate",
            "subcategory":"Real Estate Agent",
            "type":"Services"
        }
    ],
    "sg:phone":"+1 208 667 6035",
    "sg:postcode":"83814",
    "sg:province":"ID",
    "sg:tags":[
        "rental",
        "vacation"
    ],
    "sg:website":"www.resortpropertiesidaho.com",
    "wof:name":"Resort Property Management",
    "wof:placetype":"venue"
},
  "geometry": {"coordinates":[-116.78227200000001,47.696345],"type":"Point"}
}