{
  "type": "Feature",
  "properties": {
    "iso:country":"US",
    "sg:address":"71 Freeman Ln",
    "sg:city":"Hope",
    "sg:classifiers":[
        {
            "category":"Health Services",
            "subcategory":"Nursing And Care Facility",
            "type":"Services"
        }
    ],
    "sg:phone":"+1 208 264 5688",
    "sg:postcode":"83836",
    "sg:province":"ID",
    "wof:name":"Trestle Creek Friendship Ctr",
    "wof:placetype":"venue"
},
  "geometry": {"coordinates":[-116.348571,48.282637],"type":"Point"}
}