{
  "type": "Feature",
  "properties": {
    "iso:country":"US",
    "sg:address":"4500 Chinden Blvd",
    "sg:city":"Boise",
    "sg:classifiers":[
        {
            "category":"Autos & Motor Vehicles",
            "subcategory":"Automobile Sales",
            "type":"Retail Goods"
        }
    ],
    "sg:phone":"+1 208 377 9777",
    "sg:postcode":"83714",
    "sg:province":"ID",
    "sg:tags":[
        "car",
        "used",
        "dealer"
    ],
    "wof:name":"A Car Sales",
    "wof:placetype":"venue"
},
  "geometry": {"coordinates":[-116.258449,43.63626],"type":"Point"}
}