{
  "type": "Feature",
  "properties": {
    "addr:full":"466 Mountain View Rd Clark Fork ID 83811",
    "addr:housenumber":"466",
    "addr:postcode":"83811",
    "addr:street":"Mountain View Rd",
    "iso:country":"US",
    "sg:address":"466 Mountain View Rd",
    "sg:city":"Clark Fork",
    "sg:classifiers":[
        {
            "category":"Manufacturing",
            "subcategory":"Metals",
            "type":"Manufacturing & Wholesale Goods"
        }
    ],
    "sg:phone":"+1 208 266 1394",
    "sg:postcode":"83811",
    "sg:province":"ID",
    "sg:tags":[
        "hardware",
        "mfg"
    ],
    "wof:name":"Broken Star Design",
    "wof:placetype":"venue"
},
  "geometry": {"coordinates":[-116.175258,48.182466],"type":"Point"}
}