{
  "type": "Feature",
  "properties": {
    "addr:full":"10251 Fairview Ave Boise ID 83704",
    "addr:housenumber":"10251",
    "addr:postcode":"83704",
    "addr:street":"Fairview Ave",
    "iso:country":"US",
    "sg:address":"10251 Fairview Ave",
    "sg:city":"Boise",
    "sg:classifiers":[
        {
            "category":"Shopping",
            "subcategory":"Gifts & Souvenirs",
            "type":"Retail Goods"
        }
    ],
    "sg:phone":"+1 208 321 9004",
    "sg:postcode":"83704",
    "sg:province":"ID",
    "sg:tags":[
        "shop"
    ],
    "wof:name":"El Sol Tienda Mexicana",
    "wof:placetype":"venue"
},
  "geometry": {"coordinates":[-116.310948,43.619377],"type":"Point"}
}