{
  "type": "Feature",
  "properties": {
    "addr:full":"20126 Hoskins Rd Caldwell ID 83607",
    "addr:housenumber":"20126",
    "addr:postcode":"83607",
    "addr:street":"Hoskins Rd",
    "iso:country":"US",
    "sg:address":"20126 Hoskins Rd",
    "sg:city":"Caldwell",
    "sg:classifiers":[
        {
            "category":"Building & Trades",
            "subcategory":"Construction",
            "type":"Services"
        }
    ],
    "sg:phone":"+1 208 454 8522",
    "sg:postcode":"83607",
    "sg:province":"ID",
    "sg:tags":[
        "carpentry",
        "finish",
        "contractor"
    ],
    "wof:name":"Custom Carpentry",
    "wof:placetype":"venue"
},
  "geometry": {"coordinates":[-116.794341,43.603112],"type":"Point"}
}