{
  "type": "Feature",
  "properties": {
    "iso:country":"US",
    "sg:address":"7609 Emerald St",
    "sg:city":"Boise",
    "sg:classifiers":[
        {
            "category":"Professional",
            "type":"Services"
        }
    ],
    "sg:phone":"+1 208 378 4703",
    "sg:postcode":"83704",
    "sg:province":"ID",
    "sg:tags":[
        "establishment"
    ],
    "wof:name":"Realnetnow",
    "wof:placetype":"venue"
},
  "geometry": {"coordinates":[-116.279042,43.612638],"type":"Point"}
}