{
  "type": "Feature",
  "properties": {
    "iso:country":"US",
    "sg:address":"5712 N Government Way",
    "sg:city":"Coeur D Alene",
    "sg:classifiers":[
        {
            "category":"Retail",
            "subcategory":"Auto Repair",
            "type":"Services"
        }
    ],
    "sg:phone":"+1 208 762 5522",
    "sg:postcode":"83815",
    "sg:province":"ID",
    "sg:tags":[
        "transmission",
        "general"
    ],
    "wof:name":"Affordable Transmissions",
    "wof:placetype":"venue"
},
  "geometry": {"coordinates":[-116.786697,47.722804],"type":"Point"}
}