{
  "type": "Feature",
  "properties": {
    "addr:full":"560 W Kathleen Ave Coeur D Alene ID 83815",
    "addr:housenumber":"560",
    "addr:postcode":"83815",
    "addr:street":"W Kathleen Ave",
    "iso:country":"US",
    "sg:address":"560 W Kathleen Ave",
    "sg:city":"Coeur D Alene",
    "sg:classifiers":[
        {
            "category":"Wholesale",
            "subcategory":"Electrical",
            "type":"Manufacturing & Wholesale Goods"
        }
    ],
    "sg:phone":"+1 208 676 0406",
    "sg:postcode":"83815",
    "sg:province":"ID",
    "sg:tags":[
        "control",
        "security",
        "system"
    ],
    "wof:name":"Atlas Security",
    "wof:placetype":"venue"
},
  "geometry": {"coordinates":[-116.795401,47.715379],"type":"Point"}
}