{
  "type": "Feature",
  "properties": {
    "iso:country":"US",
    "sg:address":"3165 E Iona Rd",
    "sg:city":"Idaho Falls",
    "sg:classifiers":[
        {
            "category":"Education",
            "subcategory":"School",
            "type":"Public Place"
        }
    ],
    "sg:phone":"+1 208 525 4406",
    "sg:postcode":"83401",
    "sg:province":"ID",
    "sg:website":"www.bonnevillebees.com",
    "wof:name":"Bonneville High School",
    "wof:placetype":"venue"
},
  "geometry": {"coordinates":[-111.972448,43.525888],"type":"Point"}
}