{
  "type": "Feature",
  "properties": {
    "iso:country":"US",
    "sg:address":"101 S Capitol Blvd",
    "sg:city":"Boise",
    "sg:classifiers":[
        {
            "category":"Banks & Credit Unions",
            "subcategory":"Financial Services",
            "type":"Services"
        }
    ],
    "sg:phone":"+1 208 342 7883",
    "sg:postcode":"83702",
    "sg:province":"ID",
    "sg:tags":[
        "company",
        "holding"
    ],
    "wof:name":"Brown's Industries Inc",
    "wof:placetype":"venue"
},
  "geometry": {"coordinates":[-116.203086,43.614215],"type":"Point"}
}