{
  "type": "Feature",
  "properties": {
    "iso:country":"US",
    "sg:address":"2037 Pandora Dr",
    "sg:city":"Boise",
    "sg:classifiers":[
        {
            "category":"Retail",
            "subcategory":"Portrait Studio",
            "type":"Services"
        }
    ],
    "sg:phone":"+1 208 429 8334",
    "sg:postcode":"83702",
    "sg:province":"ID",
    "sg:tags":[
        "photo"
    ],
    "wof:name":"Portraits Blue Moon",
    "wof:placetype":"venue"
},
  "geometry": {"coordinates":[-116.218974,43.639192],"type":"Point"}
}