{
  "type": "Feature",
  "properties": {
    "iso:country":"US",
    "sg:address":"310 2nd Ave E",
    "sg:city":"Twin Falls",
    "sg:classifiers":[
        {
            "category":"Home & Garden",
            "subcategory":"Home Furnishings",
            "type":"Retail Goods"
        }
    ],
    "sg:phone":"+1 208 733 0674",
    "sg:postcode":"83301",
    "sg:province":"ID",
    "wof:name":"Blind Store",
    "wof:placetype":"venue"
},
  "geometry": {"coordinates":[-114.466635,42.554615],"type":"Point"}
}