{
  "type": "Feature",
  "properties": {
    "iso:country":"US",
    "sg:address":"716 Diamond St",
    "sg:city":"Nampa",
    "sg:classifiers":[
        {
            "category":"Health Services",
            "subcategory":"Medical Lab",
            "type":"Services"
        }
    ],
    "sg:phone":"+1 208 466 1511",
    "sg:postcode":"83686",
    "sg:province":"ID",
    "sg:tags":[
        "laboratory"
    ],
    "wof:name":"Nampa Dental Laboratory",
    "wof:placetype":"venue"
},
  "geometry": {"coordinates":[-116.55852299999999,43.562211],"type":"Point"}
}