{
  "type": "Feature",
  "properties": {
    "iso:country":"US",
    "sg:address":"1818 W State St",
    "sg:city":"Boise",
    "sg:classifiers":[
        {
            "category":"Organizations",
            "subcategory":"Non-profit Organization",
            "type":"Services"
        }
    ],
    "sg:phone":"+1 208 344 5611",
    "sg:postcode":"83702",
    "sg:province":"ID",
    "sg:tags":[
        "info",
        "addiction",
        "abuse",
        "treatment",
        "drug"
    ],
    "wof:name":"First Step For Women/Men",
    "wof:placetype":"venue"
},
  "geometry": {"coordinates":[-116.213263,43.625187],"type":"Point"}
}