{
  "type": "Feature",
  "properties": {
    "addr:full":"9751 N Government Way Hayden Lake ID 83835",
    "addr:housenumber":"9751",
    "addr:postcode":"83835",
    "addr:street":"N Government Way",
    "iso:country":"US",
    "sg:address":"9751 N Government Way",
    "sg:city":"Hayden Lake",
    "sg:classifiers":[
        {
            "category":"Shopping",
            "type":"Retail Goods"
        }
    ],
    "sg:phone":"+1 208 772 0964",
    "sg:postcode":"83835",
    "sg:province":"ID",
    "sg:tags":[
        "hearing",
        "equipment",
        "supply",
        "impaired"
    ],
    "wof:name":"Miracle-Ear",
    "wof:placetype":"venue"
},
  "geometry": {"coordinates":[-116.786642,47.759429],"type":"Point"}
}