{
  "type": "Feature",
  "properties": {
    "addr:full":"4155 Yellowstone Ave Pocatello ID 83202",
    "addr:housenumber":"4155",
    "addr:postcode":"83202",
    "addr:street":"Yellowstone Ave",
    "iso:country":"US",
    "sg:address":"4155 Yellowstone Ave",
    "sg:city":"Pocatello",
    "sg:classifiers":[
        {
            "category":"Shopping",
            "subcategory":"Computers & Home Electronics",
            "type":"Retail Goods"
        }
    ],
    "sg:phone":"+1 208 237 4911",
    "sg:postcode":"83202",
    "sg:province":"ID",
    "sg:tags":[
        "equipment",
        "electronic",
        "supply"
    ],
    "sg:website":"www.radioshack.com",
    "wof:name":"Radio Shack",
    "wof:placetype":"venue"
},
  "geometry": {"coordinates":[-112.466407,42.908455],"type":"Point"}
}