{
  "type": "Feature",
  "properties": {
    "addr:full":"3315 Caldwell Blvd Nampa ID 83651",
    "addr:housenumber":"3315",
    "addr:postcode":"83651",
    "addr:street":"Caldwell Blvd",
    "iso:country":"US",
    "sg:address":"3315 Caldwell Blvd",
    "sg:city":"Nampa",
    "sg:classifiers":[
        {
            "category":"Wholesale",
            "subcategory":"Scrap",
            "type":"Manufacturing & Wholesale Goods"
        }
    ],
    "sg:phone":"+1 208 442 9391",
    "sg:postcode":"83651",
    "sg:province":"ID",
    "sg:tags":[
        "recycling",
        "center"
    ],
    "wof:name":"Grease Spot",
    "wof:placetype":"venue"
},
  "geometry": {"coordinates":[-116.621381,43.617204],"type":"Point"}
}