{
  "type": "Feature",
  "properties": {
    "iso:country":"US",
    "sg:address":"281 S School Ave",
    "sg:city":"Kuna",
    "sg:classifiers":[
        {
            "category":"Social Services",
            "subcategory":"Child Care",
            "type":"Services"
        }
    ],
    "sg:phone":"+1 208 322 5582",
    "sg:postcode":"83634",
    "sg:province":"ID",
    "sg:tags":[
        "day"
    ],
    "wof:name":"Panda Bear Daycare",
    "wof:placetype":"venue"
},
  "geometry": {"coordinates":[-116.423807,43.486797],"type":"Point"}
}