{
  "type": "Feature",
  "properties": {
    "iso:country":"US",
    "sg:address":"105 Prouse Ln",
    "sg:city":"Blackfoot",
    "sg:classifiers":[
        {
            "category":"Manufacturing",
            "subcategory":"Tools & Machinery",
            "type":"Manufacturing & Wholesale Goods"
        }
    ],
    "sg:phone":"+1 208 785 6653",
    "sg:postcode":"83221",
    "sg:province":"ID",
    "sg:tags":[
        "machine",
        "shop"
    ],
    "wof:name":"Blue Chip Machining",
    "wof:placetype":"venue"
},
  "geometry": {"coordinates":[-112.29640000000001,43.218091],"type":"Point"}
}