{
  "type": "Feature",
  "properties": {
    "addr:full":"4010 Yellowstone Ave Chubbuck ID 83202",
    "addr:housenumber":"4010",
    "addr:postcode":"83202",
    "addr:street":"Yellowstone Ave",
    "iso:country":"US",
    "sg:address":"4010 Yellowstone Ave",
    "sg:city":"Chubbuck",
    "sg:classifiers":[
        {
            "category":"Bars & Pubs",
            "type":"Food & Drink"
        }
    ],
    "sg:phone":"+1 208 237 0354",
    "sg:postcode":"83202",
    "sg:province":"ID",
    "sg:tags":[
        "club",
        "night"
    ],
    "wof:name":"Green Triangle Bar & Grill",
    "wof:placetype":"venue"
},
  "geometry": {"coordinates":[-112.46570800000001,42.906695],"type":"Point"}
}