{
  "type": "Feature",
  "properties": {
    "iso:country":"US",
    "sg:address":"2350 S Cloverdale Rd",
    "sg:city":"Boise",
    "sg:classifiers":[
        {
            "category":"Local Transit",
            "type":"Transportation"
        }
    ],
    "sg:phone":"+1 208 859 6869",
    "sg:postcode":"83709",
    "sg:province":"ID",
    "sg:tags":[
        "passenger"
    ],
    "wof:name":"Component Transport",
    "wof:placetype":"venue"
},
  "geometry": {"coordinates":[-116.3343,43.581935],"type":"Point"}
}