{
  "type": "Feature",
  "properties": {
    "iso:country":"US",
    "sg:address":"620 E Mullan Ave",
    "sg:city":"Osburn",
    "sg:classifiers":[
        {
            "category":"Insurance",
            "subcategory":"Insurance Agent",
            "type":"Services"
        }
    ],
    "sg:phone":"+1 208 556 1551",
    "sg:postcode":"83849",
    "sg:province":"ID",
    "wof:name":"State Farm Insurance",
    "wof:placetype":"venue"
},
  "geometry": {"coordinates":[-115.99560700000001,47.504438],"type":"Point"}
}