{
  "type": "Feature",
  "properties": {
    "iso:country":"US",
    "sg:address":"2955 Owen St",
    "sg:city":"Ammon",
    "sg:classifiers":[
        {
            "category":"Education",
            "subcategory":"School",
            "type":"Public Place"
        }
    ],
    "sg:phone":"+1 208 525 4416",
    "sg:postcode":"83406",
    "sg:province":"ID",
    "wof:name":"Sandcreek Middle School",
    "wof:placetype":"venue"
},
  "geometry": {"coordinates":[-111.974933,43.471941],"type":"Point"}
}