{
  "type": "Feature",
  "properties": {
    "iso:country":"US",
    "sg:address":"1524 W Hays St",
    "sg:city":"Boise",
    "sg:classifiers":[
        {
            "category":"Social Services",
            "type":"Services"
        }
    ],
    "sg:phone":"+1 208 343 7077",
    "sg:postcode":"83702",
    "sg:province":"ID",
    "sg:tags":[
        "counselor",
        "marriage",
        "family"
    ],
    "wof:name":"Olivia M Holly",
    "wof:placetype":"venue"
},
  "geometry": {"coordinates":[-116.207514,43.625661],"type":"Point"}
}