{
  "type": "Feature",
  "properties": {
    "iso:country":"US",
    "sg:address":"10120 Overland Rd",
    "sg:city":"Boise",
    "sg:classifiers":[
        {
            "category":"Autos & Motor Vehicles",
            "subcategory":"Auto Supplies",
            "type":"Retail Goods"
        }
    ],
    "sg:phone":"+1 208 321 1337",
    "sg:postcode":"83709",
    "sg:province":"ID",
    "sg:tags":[
        "automobile",
        "parts"
    ],
    "wof:name":"Schuck's Auto Supply",
    "wof:placetype":"venue"
},
  "geometry": {"coordinates":[-116.31343200000001,43.590215],"type":"Point"}
}