{
  "type": "Feature",
  "properties": {
    "iso:country":"US",
    "sg:address":"4710 Jennifer St",
    "sg:city":"Boise",
    "sg:classifiers":[
        {
            "category":"Shopping",
            "subcategory":"Hobbies, Toys, & Games",
            "type":"Retail Goods"
        }
    ],
    "sg:phone":"+1 208 322 2534",
    "sg:postcode":"83704",
    "sg:province":"ID",
    "wof:name":"Wayne Richey Enterprise",
    "wof:placetype":"venue"
},
  "geometry": {"coordinates":[-116.29852099999999,43.646878],"type":"Point"}
}