{
  "type": "Feature",
  "properties": {
    "addr:full":"2420 E 17th St Idaho Falls ID 83404",
    "addr:housenumber":"2420",
    "addr:postcode":"83404",
    "addr:street":"E 17Th St",
    "iso:country":"US",
    "sg:address":"2420 E 17th St",
    "sg:city":"Idaho Falls",
    "sg:classifiers":[
        {
            "category":"Shopping",
            "subcategory":"Department Store",
            "type":"Retail Goods"
        }
    ],
    "sg:phone":"+1 208 525 4000",
    "sg:postcode":"83404",
    "sg:province":"ID",
    "wof:name":"Dillard's",
    "wof:placetype":"venue"
},
  "geometry": {"coordinates":[-111.984754,43.481951],"type":"Point"}
}