{
  "type": "Feature",
  "properties": {
    "iso:country":"US",
    "sg:address":"7389 N 3000 W",
    "sg:city":"Preston",
    "sg:classifiers":[
        {
            "category":"Organizations",
            "subcategory":"Religious Organization",
            "type":"Services"
        }
    ],
    "sg:phone":"+1 208 852 2768",
    "sg:postcode":"83263",
    "sg:province":"ID",
    "sg:tags":[
        "church"
    ],
    "wof:name":"Church Of Jesus Christ Of Lds",
    "wof:placetype":"venue"
},
  "geometry": {"coordinates":[-111.95018899999999,42.230779],"type":"Point"}
}