{
  "type": "Feature",
  "properties": {
    "iso:country":"US",
    "sg:address":"725 Swan Falls Rd",
    "sg:city":"Kuna",
    "sg:classifiers":[
        {
            "category":"Professional",
            "subcategory":"Business Services",
            "type":"Services"
        }
    ],
    "sg:phone":"+1 208 922 5772",
    "sg:postcode":"83634",
    "sg:province":"ID",
    "sg:tags":[
        "school"
    ],
    "wof:name":"Blaine Astle Agency",
    "wof:placetype":"venue"
},
  "geometry": {"coordinates":[-116.413815,43.481202],"type":"Point"}
}