{
  "type": "Feature",
  "properties": {
    "iso:country":"US",
    "sg:address":"927 E Polston Ave",
    "sg:city":"Post Falls",
    "sg:classifiers":[
        {
            "category":"Wholesale",
            "subcategory":"Non-durable Goods",
            "type":"Manufacturing & Wholesale Goods"
        }
    ],
    "sg:phone":"+1 208 618 8000",
    "sg:postcode":"83854",
    "sg:province":"ID",
    "sg:tags":[
        "craft",
        "supply"
    ],
    "wof:name":"PSX",
    "wof:placetype":"venue"
},
  "geometry": {"coordinates":[-116.936615,47.714635],"type":"Point"}
}