{
  "type": "Feature",
  "properties": {
    "addr:full":"4304 Emerald St Boise ID 83706",
    "addr:housenumber":"4304",
    "addr:postcode":"83706",
    "addr:street":"Emerald St",
    "iso:country":"US",
    "sg:address":"4304 Emerald St",
    "sg:city":"Boise",
    "sg:classifiers":[
        {
            "category":"Social Services",
            "subcategory":"Job Training",
            "type":"Services"
        }
    ],
    "sg:phone":"+1 208 375 4477",
    "sg:postcode":"83706",
    "sg:province":"ID",
    "sg:tags":[
        "rehabilitation"
    ],
    "wof:name":"Aastum Vocational Svc Inc",
    "wof:placetype":"venue"
},
  "geometry": {"coordinates":[-116.235957,43.611671],"type":"Point"}
}