{
  "type": "Feature",
  "properties": {
    "iso:country":"US",
    "sg:address":"3427 N 1000 E",
    "sg:city":"Buhl",
    "sg:classifiers":[
        {
            "category":"Farming",
            "subcategory":"Dairy Farm",
            "type":"Manufacturing & Wholesale Goods"
        }
    ],
    "sg:phone":"+1 208 537 9165",
    "sg:postcode":"83316",
    "sg:province":"ID",
    "wof:name":"Vieira Al Dairies",
    "wof:placetype":"venue"
},
  "geometry": {"coordinates":[-114.849076,42.496263],"type":"Point"}
}