{
  "type": "Feature",
  "properties": {
    "addr:full":"343 Park Ave Idaho Falls ID 83402",
    "addr:housenumber":"343",
    "addr:postcode":"83402",
    "addr:street":"Park Ave",
    "iso:country":"US",
    "sg:address":"343 Park Ave",
    "sg:city":"Idaho Falls",
    "sg:classifiers":[
        {
            "category":"Personal",
            "subcategory":"Tattoo Parlor",
            "type":"Services"
        }
    ],
    "sg:phone":"+1 208 522 3301",
    "sg:postcode":"83402",
    "sg:province":"ID",
    "sg:tags":[
        "tattooing"
    ],
    "wof:name":"Underground Tattoo",
    "wof:placetype":"venue"
},
  "geometry": {"coordinates":[-112.04101799999999,43.492314],"type":"Point"}
}