{
  "type": "Feature",
  "properties": {
    "addr:full":"675 W Capstone Ct Hayden ID 83835",
    "addr:housenumber":"675",
    "addr:postcode":"83835",
    "addr:street":"W Capstone Ct",
    "iso:country":"US",
    "sg:address":"675 W Capstone Ct",
    "sg:city":"Hayden",
    "sg:classifiers":[
        {
            "category":"Manufacturing",
            "subcategory":"Rubber & Plastics",
            "type":"Manufacturing & Wholesale Goods"
        }
    ],
    "sg:phone":"+1 208 772 5199",
    "sg:postcode":"83835",
    "sg:province":"ID",
    "sg:website":"www.wolfpacgroup.com",
    "wof:name":"Wolfpac Group Inc",
    "wof:placetype":"venue"
},
  "geometry": {"coordinates":[-116.794498,47.747362],"type":"Point"}
}