{
  "type": "Feature",
  "properties": {
    "iso:country":"US",
    "sg:address":"6867 S 45th W",
    "sg:city":"Idaho Falls",
    "sg:classifiers":[
        {
            "category":"Autos & Motor Vehicles",
            "subcategory":"Fuel & Gas Station",
            "type":"Retail Goods"
        }
    ],
    "sg:phone":"+1 208 529 8000",
    "sg:postcode":"83402",
    "sg:province":"ID",
    "sg:tags":[
        "plaza",
        "truck",
        "stops"
    ],
    "wof:name":"Yellowstone Truck Stop",
    "wof:placetype":"venue"
},
  "geometry": {"coordinates":[-112.122569,43.436391],"type":"Point"}
}