{
  "type": "Feature",
  "properties": {
    "iso:country":"US",
    "sg:address":"2001 N Woodruff Ave",
    "sg:city":"Idaho Falls",
    "sg:classifiers":[
        {
            "category":"Building & Trades",
            "subcategory":"Equipment Rental",
            "type":"Services"
        }
    ],
    "sg:phone":"+1 208 524 7375",
    "sg:postcode":"83401",
    "sg:province":"ID",
    "sg:tags":[
        "yard"
    ],
    "wof:name":"Action Rental Ctr",
    "wof:placetype":"venue"
},
  "geometry": {"coordinates":[-112.00084200000001,43.516351],"type":"Point"}
}