{
  "type": "Feature",
  "properties": {
    "iso:country":"US",
    "sg:address":"46 N Borah St",
    "sg:city":"Nampa",
    "sg:classifiers":[
        {
            "category":"Building & Trades",
            "subcategory":"Construction",
            "type":"Services"
        }
    ],
    "sg:phone":"+1 208 461 4710",
    "sg:postcode":"83651",
    "sg:province":"ID",
    "sg:tags":[
        "hanging",
        "contractor"
    ],
    "wof:name":"Als Painting",
    "wof:placetype":"venue"
},
  "geometry": {"coordinates":[-116.583994,43.580348],"type":"Point"}
}