{
  "type": "Feature",
  "properties": {
    "addr:full":"9321 N Government Way Hayden ID 83835",
    "addr:housenumber":"9321",
    "addr:postcode":"83835",
    "addr:street":"N Government Way",
    "iso:country":"US",
    "sg:address":"9321 N Government Way",
    "sg:city":"Hayden",
    "sg:classifiers":[
        {
            "category":"Health Services",
            "subcategory":"Health Practitioner",
            "type":"Services"
        }
    ],
    "sg:phone":"+1 208 659 9697",
    "sg:postcode":"83835",
    "sg:province":"ID",
    "wof:name":"Barbara D Boss PHD License",
    "wof:placetype":"venue"
},
  "geometry": {"coordinates":[-116.786677,47.755837],"type":"Point"}
}