{
  "type": "Feature",
  "properties": {
    "iso:country":"US",
    "sg:address":"1424 Yellowstone Ave",
    "sg:city":"Pocatello",
    "sg:classifiers":[
        {
            "category":"Building & Trades",
            "subcategory":"Construction",
            "type":"Services"
        }
    ],
    "sg:phone":"+1 208 234 5726",
    "sg:postcode":"83201",
    "sg:province":"ID",
    "sg:tags":[
        "contractor"
    ],
    "wof:name":"Marinette Contracting",
    "wof:placetype":"venue"
},
  "geometry": {"coordinates":[-112.451273,42.900762],"type":"Point"}
}