{
  "type": "Feature",
  "properties": {
    "addr:full":"1990 Cherry Ln Emmett ID 83617",
    "addr:housenumber":"1990",
    "addr:postcode":"83617",
    "addr:street":"Cherry Ln",
    "iso:country":"US",
    "sg:address":"1990 Cherry Ln",
    "sg:city":"Emmett",
    "sg:classifiers":[
        {
            "category":"Building & Trades",
            "subcategory":"Cleaning & Sanitation",
            "type":"Services"
        }
    ],
    "sg:phone":"+1 208 398 8024",
    "sg:postcode":"83617",
    "sg:province":"ID",
    "sg:tags":[
        "maintenance"
    ],
    "wof:name":"Blue Sky Window Cleaning",
    "wof:placetype":"venue"
},
  "geometry": {"coordinates":[-116.47346400000001,43.85743],"type":"Point"}
}