{
  "type": "Feature",
  "properties": {
    "iso:country":"US",
    "sg:address":"1757 N Hampton Rd",
    "sg:city":"Boise",
    "sg:classifiers":[
        {
            "category":"Home & Garden",
            "subcategory":"Building Materials",
            "type":"Retail Goods"
        }
    ],
    "sg:phone":"+1 208 383 9696",
    "sg:postcode":"83704",
    "sg:province":"ID",
    "sg:tags":[
        "windows"
    ],
    "wof:name":"Boise Window Co",
    "wof:placetype":"venue"
},
  "geometry": {"coordinates":[-116.30932,43.621052],"type":"Point"}
}