{
  "type": "Feature",
  "properties": {
    "iso:country":"US",
    "sg:address":"150 S Arthur Ave",
    "sg:city":"Pocatello",
    "sg:classifiers":[
        {
            "category":"Professional",
            "subcategory":"Lawyer & Legal Services",
            "type":"Services"
        }
    ],
    "sg:phone":"+1 208 233 0079",
    "sg:postcode":"83204",
    "sg:province":"ID",
    "sg:tags":[
        "attorney"
    ],
    "wof:name":"Idaho Legal Aid Svc Inc",
    "wof:placetype":"venue"
},
  "geometry": {"coordinates":[-112.451037,42.861154],"type":"Point"}
}