{
  "type": "Feature",
  "properties": {
    "iso:country":"US",
    "sg:address":"7625 Hove Rd",
    "sg:city":"Melba",
    "sg:classifiers":[
        {
            "category":"Professional",
            "type":"Services"
        }
    ],
    "sg:phone":"+1 208 495 2876",
    "sg:postcode":"83641",
    "sg:province":"ID",
    "wof:name":"Robert Miller",
    "wof:placetype":"venue"
},
  "geometry": {"coordinates":[-116.545845,43.365365],"type":"Point"}
}