{
  "type": "Feature",
  "properties": {
    "addr:full":"2708 State Hwy 41 Post Falls ID 83854",
    "addr:housenumber":"2708",
    "addr:postcode":"83854",
    "addr:street":"State Hwy 41",
    "iso:country":"US",
    "sg:address":"2708 State Hwy 41",
    "sg:city":"Post Falls",
    "sg:classifiers":[
        {
            "category":"Wholesale",
            "subcategory":"Meat",
            "type":"Manufacturing & Wholesale Goods"
        }
    ],
    "sg:phone":"+1 208 773 2333",
    "sg:postcode":"83854",
    "sg:province":"ID",
    "sg:tags":[
        "butchering"
    ],
    "wof:name":"Prairie Custom Meats",
    "wof:placetype":"venue"
},
  "geometry": {"coordinates":[-116.894322,47.731322],"type":"Point"}
}