{
  "type": "Feature",
  "properties": {
    "iso:country":"US",
    "sg:address":"733 Laleene Dr",
    "sg:city":"Rexburg",
    "sg:classifiers":[
        {
            "category":"Building & Trades",
            "subcategory":"Cleaning & Sanitation",
            "type":"Services"
        }
    ],
    "sg:phone":"+1 208 356 8707",
    "sg:postcode":"83440",
    "sg:province":"ID",
    "sg:tags":[
        "maintenance"
    ],
    "wof:name":"Srmc LLC",
    "wof:placetype":"venue"
},
  "geometry": {"coordinates":[-111.764387,43.832756],"type":"Point"}
}