{
  "type": "Feature",
  "properties": {
    "iso:country":"US",
    "sg:address":"16 S 9th St",
    "sg:city":"Payette",
    "sg:classifiers":[
        {
            "category":"Government",
            "subcategory":"Office",
            "type":"Public Place"
        }
    ],
    "sg:phone":"+1 208 642 6022",
    "sg:postcode":"83661",
    "sg:province":"ID",
    "wof:name":"Payette County Agent",
    "wof:placetype":"venue"
},
  "geometry": {"coordinates":[-116.933581,44.074663],"type":"Point"}
}