{
  "type": "Feature",
  "properties": {
    "iso:country":"US",
    "sg:address":"2221 Madison Ave",
    "sg:city":"Pocatello",
    "sg:classifiers":[
        {
            "category":"Building & Trades",
            "subcategory":"Construction",
            "type":"Services"
        }
    ],
    "sg:phone":"+1 208 237 7021",
    "sg:postcode":"83201",
    "sg:province":"ID",
    "sg:tags":[
        "roofing",
        "contractor"
    ],
    "wof:name":"Pocatello Roofing Inc",
    "wof:placetype":"venue"
},
  "geometry": {"coordinates":[-112.466127,42.882432],"type":"Point"}
}