{
  "type": "Feature",
  "properties": {
    "iso:country":"US",
    "sg:address":"800 McGhee Rd",
    "sg:city":"Ponderay",
    "sg:classifiers":[
        {
            "category":"Social Services",
            "subcategory":"Child Care",
            "type":"Services"
        }
    ],
    "sg:phone":"+1 208 255 2245",
    "sg:postcode":"83864",
    "sg:province":"ID",
    "sg:website":"www.childrenscentersinc.com",
    "wof:name":"Kootenai Childrens Ctr",
    "wof:placetype":"venue"
},
  "geometry": {"coordinates":[-116.524469,48.30915],"type":"Point"}
}