{
  "type": "Feature",
  "properties": {
    "addr:full":"204 N 4th Ave Sandpoint ID 83864",
    "addr:housenumber":"204",
    "addr:postcode":"83864",
    "addr:street":"N 4Th Ave",
    "iso:country":"US",
    "sg:address":"204 N 4th Ave",
    "sg:city":"Sandpoint",
    "sg:classifiers":[
        {
            "category":"Government",
            "subcategory":"Post Office",
            "type":"Public Place"
        }
    ],
    "sg:phone":"+1 208 263 2716",
    "sg:postcode":"83864",
    "sg:province":"ID",
    "sg:website":"www.usps.com",
    "wof:name":"US Post Office",
    "wof:placetype":"venue"
},
  "geometry": {"coordinates":[-116.551761,48.27503],"type":"Point"}
}