{
  "type": "Feature",
  "properties": {
    "iso:country":"US",
    "sg:address":"727 Falls Ave",
    "sg:city":"American Falls",
    "sg:classifiers":[
        {
            "category":"Government",
            "subcategory":"Fire Station",
            "type":"Public Place"
        }
    ],
    "sg:phone":"+1 208 226 5494",
    "sg:postcode":"83211",
    "sg:province":"ID",
    "sg:tags":[
        "protection"
    ],
    "wof:name":"AM Falls Rural Fire District",
    "wof:placetype":"venue"
},
  "geometry": {"coordinates":[-112.852677,42.780315],"type":"Point"}
}