{
  "type": "Feature",
  "properties": {
    "iso:country":"US",
    "sg:address":"7009 Franklin Rd",
    "sg:city":"Boise",
    "sg:classifiers":[
        {
            "category":"Education",
            "subcategory":"School",
            "type":"Public Place"
        }
    ],
    "sg:phone":"+1 208 375 6010",
    "sg:postcode":"83709",
    "sg:province":"ID",
    "sg:website":"www.bk.org",
    "wof:name":"Bishop Kelly High School",
    "wof:placetype":"venue"
},
  "geometry": {"coordinates":[-116.269688,43.604192],"type":"Point"}
}