{
  "type": "Feature",
  "properties": {
    "iso:country":"US",
    "sg:address":"315 W Dalton Ave",
    "sg:city":"Coeur D Alene",
    "sg:classifiers":[
        {
            "category":"Real Estate",
            "subcategory":"Real Estate Agent",
            "type":"Services"
        }
    ],
    "sg:phone":"+1 208 762 2000",
    "sg:postcode":"83815",
    "sg:province":"ID",
    "wof:name":"Prudential",
    "wof:placetype":"venue"
},
  "geometry": {"coordinates":[-116.79209299999999,47.722696],"type":"Point"}
}