{
  "type": "Feature",
  "properties": {
    "iso:country":"US",
    "sg:address":"1686 E King Rd",
    "sg:city":"Kuna",
    "sg:classifiers":[
        {
            "category":"Manufacturing",
            "subcategory":"Food",
            "type":"Manufacturing & Wholesale Goods"
        }
    ],
    "sg:phone":"+1 208 922 2248",
    "sg:postcode":"83634",
    "sg:province":"ID",
    "sg:tags":[
        "desert",
        "ice",
        "mfg"
    ],
    "wof:name":"Blue Island Snow",
    "wof:placetype":"venue"
},
  "geometry": {"coordinates":[-116.392923,43.473858],"type":"Point"}
}