{
  "type": "Feature",
  "properties": {
    "iso:country":"US",
    "sg:address":"1059 W 200 S",
    "sg:city":"Blackfoot",
    "sg:classifiers":[
        {
            "category":"Food & Beverages",
            "subcategory":"Specialty",
            "type":"Retail Goods"
        }
    ],
    "sg:phone":"+1 208 684 5412",
    "sg:postcode":"83221",
    "sg:province":"ID",
    "sg:tags":[
        "water",
        "bulk",
        "company"
    ],
    "wof:name":"Water World",
    "wof:placetype":"venue"
},
  "geometry": {"coordinates":[-112.51341499999999,43.168062],"type":"Point"}
}