{
  "type": "Feature",
  "properties": {
    "iso:country":"US",
    "sg:address":"1562 Larsen Rd",
    "sg:city":"Soda Springs",
    "sg:classifiers":[
        {
            "category":"Building & Trades",
            "subcategory":"Construction",
            "type":"Services"
        }
    ],
    "sg:phone":"+1 208 547 2309",
    "sg:postcode":"83276",
    "sg:province":"ID",
    "sg:tags":[
        "painter"
    ],
    "wof:name":"Caribou Industrial Coating",
    "wof:placetype":"venue"
},
  "geometry": {"coordinates":[-111.623147,42.641861],"type":"Point"}
}