{
  "type": "Feature",
  "properties": {
    "iso:country":"US",
    "sg:address":"475 N Linder Rd",
    "sg:city":"Meridian",
    "sg:classifiers":[
        {
            "category":"Building & Trades",
            "subcategory":"Construction",
            "type":"Services"
        }
    ],
    "sg:phone":"+1 208 888 4790",
    "sg:postcode":"83642",
    "sg:province":"ID",
    "sg:tags":[
        "boring",
        "drilling",
        "contractor"
    ],
    "wof:name":"Haz-Tech Drilling Inc",
    "wof:placetype":"venue"
},
  "geometry": {"coordinates":[-116.413698,43.608997],"type":"Point"}
}