{
  "type": "Feature",
  "properties": {
    "iso:country":"US",
    "sg:address":"1200 1st St S",
    "sg:city":"Nampa",
    "sg:classifiers":[
        {
            "category":"Travel",
            "subcategory":"Travel Agent",
            "type":"Entertainment"
        }
    ],
    "sg:phone":"+1 208 467 7499",
    "sg:postcode":"83651",
    "sg:province":"ID",
    "sg:tags":[
        "agency",
        "bureau"
    ],
    "wof:name":"Uniglobe VIP Travel",
    "wof:placetype":"venue"
},
  "geometry": {"coordinates":[-116.559772,43.578838],"type":"Point"}
}