{
  "type": "Feature",
  "properties": {
    "iso:country":"US",
    "sg:address":"2716 N 36th St",
    "sg:city":"Boise",
    "sg:classifiers":[
        {
            "category":"Personal",
            "subcategory":"Beauty Salon",
            "type":"Services"
        }
    ],
    "sg:phone":"+1 208 385 0602",
    "sg:postcode":"83703",
    "sg:province":"ID",
    "sg:tags":[
        "shop"
    ],
    "wof:name":"Special Attntion For Hair Nils",
    "wof:placetype":"venue"
},
  "geometry": {"coordinates":[-116.233316,43.645389],"type":"Point"}
}