{
  "type": "Feature",
  "properties": {
    "iso:country":"US",
    "sg:address":"820 Sunny Ln",
    "sg:city":"Nampa",
    "sg:classifiers":[
        {
            "category":"Building & Trades",
            "subcategory":"Construction",
            "type":"Services"
        }
    ],
    "sg:phone":"+1 208 465 3565",
    "sg:postcode":"83651",
    "sg:province":"ID",
    "sg:tags":[
        "contractor"
    ],
    "wof:name":"Blackhawk Building Co",
    "wof:placetype":"venue"
},
  "geometry": {"coordinates":[-116.58929000000001,43.581484],"type":"Point"}
}