{
  "type": "Feature",
  "properties": {
    "iso:country":"US",
    "sg:address":"2010 Powers Dr",
    "sg:city":"Lewiston",
    "sg:classifiers":[
        {
            "category":"Professional",
            "subcategory":"Business Services",
            "type":"Services"
        }
    ],
    "sg:phone":"+1 208 746 2829",
    "sg:postcode":"83501",
    "sg:province":"ID",
    "wof:name":"Seasons Residential Care",
    "wof:placetype":"venue"
},
  "geometry": {"coordinates":[-116.926367,46.368661],"type":"Point"}
}