{
  "type": "Feature",
  "properties": {
    "addr:full":"1 11th Ave S Nampa ID 83651",
    "addr:housenumber":"1",
    "addr:postcode":"83651",
    "addr:street":"11Th Ave S",
    "iso:country":"US",
    "sg:address":"1 11th Ave S",
    "sg:city":"Nampa",
    "sg:classifiers":[
        {
            "category":"Social Services",
            "type":"Services"
        }
    ],
    "sg:phone":"+1 208 461 1651",
    "sg:postcode":"83651",
    "sg:province":"ID",
    "sg:tags":[
        "organization",
        "welfare"
    ],
    "wof:name":"Nampa Adventist Community Svc",
    "wof:placetype":"venue"
},
  "geometry": {"coordinates":[-116.55991,43.58027],"type":"Point"}
}