{
  "type": "Feature",
  "properties": {
    "iso:country":"US",
    "sg:address":"115 S 2nd St",
    "sg:city":"Coeur D Alene",
    "sg:classifiers":[
        {
            "category":"Shopping",
            "subcategory":"Gifts & Souvenirs",
            "type":"Retail Goods"
        }
    ],
    "sg:phone":"+1 208 666 9021",
    "sg:postcode":"83814",
    "sg:province":"ID",
    "sg:tags":[
        "shop"
    ],
    "wof:name":"Couer D'Alene Resort Logo Shop",
    "wof:placetype":"venue"
},
  "geometry": {"coordinates":[-116.78421299999999,47.673066],"type":"Point"}
}