{
  "type": "Feature",
  "properties": {
    "iso:country":"US",
    "sg:address":"1520 S 4th Ave",
    "sg:city":"Pocatello",
    "sg:classifiers":[
        {
            "category":"Real Estate",
            "subcategory":"Developer",
            "type":"Services"
        }
    ],
    "sg:phone":"+1 208 234 6195",
    "sg:postcode":"83201",
    "sg:province":"ID",
    "sg:tags":[
        "cemetery"
    ],
    "wof:name":"Mountain View Cemetery",
    "wof:placetype":"venue"
},
  "geometry": {"coordinates":[-112.431563,42.854826],"type":"Point"}
}