{
  "type": "Feature",
  "properties": {
    "iso:country":"US",
    "sg:address":"29560 N Lewellen Creek Rd",
    "sg:city":"Athol",
    "sg:classifiers":[
        {
            "category":"Retail",
            "subcategory":"Auto Repair",
            "type":"Services"
        }
    ],
    "sg:phone":"+1 208 683 3268",
    "sg:postcode":"83801",
    "sg:province":"ID",
    "sg:tags":[
        "automobile",
        "restoration",
        "classic"
    ],
    "wof:name":"Bellis Auto Restoration",
    "wof:placetype":"venue"
},
  "geometry": {"coordinates":[-116.633916,47.94628],"type":"Point"}
}