{
  "type": "Feature",
  "properties": {
    "iso:country":"US",
    "sg:address":"7129 Brentwood Dr",
    "sg:city":"Boise",
    "sg:classifiers":[
        {
            "category":"Banks & Credit Unions",
            "subcategory":"Bank",
            "type":"Services"
        }
    ],
    "sg:phone":"+1 208 322 8910",
    "sg:postcode":"83709",
    "sg:province":"ID",
    "sg:tags":[
        "financing"
    ],
    "wof:name":"Cit Group Inc",
    "wof:placetype":"venue"
},
  "geometry": {"coordinates":[-116.273079,43.594878],"type":"Point"}
}