{
  "type": "Feature",
  "properties": {
    "iso:country":"US",
    "sg:address":"185 N Woodruff Ave",
    "sg:city":"Idaho Falls",
    "sg:classifiers":[
        {
            "category":"Retail",
            "subcategory":"Auto Repair",
            "type":"Services"
        }
    ],
    "sg:phone":"+1 208 529 3232",
    "sg:postcode":"83401",
    "sg:province":"ID",
    "sg:tags":[
        "automobile",
        "lubrication"
    ],
    "sg:website":"www.jiffylube.com",
    "wof:name":"Jiffy Lube",
    "wof:placetype":"venue"
},
  "geometry": {"coordinates":[-111.999211,43.497294],"type":"Point"}
}