{
  "type": "Feature",
  "properties": {
    "iso:country":"US",
    "sg:address":"4696 N Tumbleweed Pl",
    "sg:city":"Boise",
    "sg:classifiers":[
        {
            "category":"Retail",
            "subcategory":"Veterinary Services",
            "type":"Services"
        }
    ],
    "sg:phone":"+1 208 888 2910",
    "sg:postcode":"83713",
    "sg:province":"ID",
    "sg:tags":[
        "veterinarian"
    ],
    "wof:name":"Family Pet Veterinary Clinic",
    "wof:placetype":"venue"
},
  "geometry": {"coordinates":[-116.326262,43.64771],"type":"Point"}
}