{
  "type": "Feature",
  "properties": {
    "iso:country":"US",
    "sg:address":"253 Davis Ave",
    "sg:city":"Nampa",
    "sg:classifiers":[
        {
            "category":"Freight",
            "type":"Transportation"
        }
    ],
    "sg:phone":"+1 208 467 5614",
    "sg:postcode":"83651",
    "sg:province":"ID",
    "sg:tags":[
        "trucking"
    ],
    "wof:name":"Christiancy Trucking Inc",
    "wof:placetype":"venue"
},
  "geometry": {"coordinates":[-116.58539399999999,43.584985],"type":"Point"}
}