{
  "type": "Feature",
  "properties": {
    "iso:country":"US",
    "sg:address":"159 E Commercial St",
    "sg:city":"Weiser",
    "sg:classifiers":[
        {
            "category":"Manufacturing",
            "subcategory":"Tools & Machinery",
            "type":"Manufacturing & Wholesale Goods"
        },
        {
            "category":"Wholesale",
            "subcategory":"Electrical",
            "type":"Manufacturing & Wholesale Goods"
        },
        {
            "category":"Building & Trades",
            "subcategory":"Electrical",
            "type":"Services"
        }
    ],
    "sg:phone":"+1 208 549 1135",
    "sg:postcode":"83672",
    "sg:province":"ID",
    "sg:tags":[
        "electrician",
        "electric",
        "supply",
        "equipment",
        "supplies-wholesale",
        "manufacturer"
    ],
    "wof:name":"R & D Auto Electric",
    "wof:placetype":"venue"
},
  "geometry": {"coordinates":[-116.968097,44.244515],"type":"Point"}
}