{
  "type": "Feature",
  "properties": {
    "iso:country":"US",
    "sg:address":"223 Roedel Ave",
    "sg:city":"Caldwell",
    "sg:classifiers":[
        {
            "category":"Wholesale",
            "subcategory":"Auto Parts",
            "type":"Manufacturing & Wholesale Goods"
        }
    ],
    "sg:phone":"+1 208 455 2707",
    "sg:postcode":"83605",
    "sg:province":"ID",
    "sg:tags":[
        "truck",
        "accessory"
    ],
    "sg:website":"www.extendobed.com",
    "wof:name":"Extend O Bed",
    "wof:placetype":"venue"
},
  "geometry": {"coordinates":[-116.708236,43.670269],"type":"Point"}
}