{
  "type": "Feature",
  "properties": {
    "iso:country":"US",
    "sg:address":"1051 Chaney Rd",
    "sg:city":"Viola",
    "sg:classifiers":[
        {
            "category":"Shopping",
            "subcategory":"Crafts & Fabrics",
            "type":"Retail Goods"
        }
    ],
    "sg:phone":"+1 208 883 9500",
    "sg:postcode":"83872",
    "sg:province":"ID",
    "sg:tags":[
        "shop"
    ],
    "wof:name":"Grammy G's Treasures & Notions",
    "wof:placetype":"venue"
},
  "geometry": {"coordinates":[-117.005705,46.846722],"type":"Point"}
}