{
  "type": "Feature",
  "properties": {
    "iso:country":"US",
    "sg:address":"1101 Elba Ave",
    "sg:city":"Burley",
    "sg:classifiers":[
        {
            "category":"Government",
            "subcategory":"Office",
            "type":"Public Place"
        }
    ],
    "sg:phone":"+1 208 678 9150",
    "sg:postcode":"83318",
    "sg:province":"ID",
    "wof:name":"Cassia Cnty Fair Board-Sec-Mgr",
    "wof:placetype":"venue"
},
  "geometry": {"coordinates":[-113.78671,42.539429],"type":"Point"}
}