{
  "type": "Feature",
  "properties": {
    "iso:country":"US",
    "sg:address":"810 E Bancroft Ave",
    "sg:city":"Coeur D Alene",
    "sg:classifiers":[
        {
            "category":"Real Estate",
            "subcategory":"Real Estate Agent",
            "type":"Services"
        }
    ],
    "sg:phone":"+1 208 664 1810",
    "sg:postcode":"83814",
    "sg:province":"ID",
    "wof:name":"Real Estate Office",
    "wof:placetype":"venue"
},
  "geometry": {"coordinates":[-116.77546100000001,47.670771],"type":"Point"}
}