{
  "type": "Feature",
  "properties": {
    "iso:country":"US",
    "sg:address":"1812 Madison Ave",
    "sg:city":"Nampa",
    "sg:classifiers":[
        {
            "category":"Wholesale",
            "subcategory":"Hardware",
            "type":"Manufacturing & Wholesale Goods"
        }
    ],
    "sg:phone":"+1 208 463 9909",
    "sg:postcode":"83687",
    "sg:province":"ID",
    "sg:tags":[
        "plumbing",
        "fixture",
        "supply"
    ],
    "wof:name":"Consolidated Supply Co",
    "wof:placetype":"venue"
},
  "geometry": {"coordinates":[-116.562989,43.599989],"type":"Point"}
}