{
  "type": "Feature",
  "properties": {
    "iso:country":"US",
    "sg:address":"900 N Cleveland Ave",
    "sg:city":"Kuna",
    "sg:classifiers":[
        {
            "category":"Building & Trades",
            "subcategory":"Construction",
            "type":"Services"
        }
    ],
    "sg:phone":"+1 208 922 9093",
    "sg:postcode":"83634",
    "sg:province":"ID",
    "sg:tags":[
        "general",
        "contractor"
    ],
    "wof:name":"MWT Inc",
    "wof:placetype":"venue"
},
  "geometry": {"coordinates":[-116.41222,43.497288],"type":"Point"}
}