{
  "type": "Feature",
  "properties": {
    "addr:full":"205 1st St W Ketchum ID 83340",
    "addr:housenumber":"205",
    "addr:postcode":"83340",
    "addr:street":"1St St W",
    "iso:country":"US",
    "sg:address":"205 1st St W",
    "sg:city":"Ketchum",
    "sg:classifiers":[
        {
            "category":"Banks & Credit Unions",
            "subcategory":"Investment Brokerage",
            "type":"Services"
        }
    ],
    "sg:phone":"+1 208 725 0300",
    "sg:postcode":"83340",
    "sg:province":"ID",
    "wof:name":"Wrigley Investments",
    "wof:placetype":"venue"
},
  "geometry": {"coordinates":[-114.365557,43.677637],"type":"Point"}
}