{
  "type": "Feature",
  "properties": {
    "iso:country":"US",
    "sg:address":"6901 E Sleepy Ln",
    "sg:city":"Coeur D Alene",
    "sg:classifiers":[
        {
            "category":"Building & Trades",
            "subcategory":"Construction",
            "type":"Services"
        }
    ],
    "sg:phone":"+1 208 664 3177",
    "sg:postcode":"83814",
    "sg:province":"ID",
    "sg:tags":[
        "general",
        "contractor"
    ],
    "wof:name":"O'Day Custom Construction Inc",
    "wof:placetype":"venue"
},
  "geometry": {"coordinates":[-116.70188,47.687588],"type":"Point"}
}