{
  "type": "Feature",
  "properties": {
    "iso:country":"US",
    "sg:address":"2133 Killebrew Dr",
    "sg:city":"Payette",
    "sg:classifiers":[
        {
            "category":"Freight",
            "type":"Transportation"
        }
    ],
    "sg:phone":"+1 208 642 5060",
    "sg:postcode":"83661",
    "sg:province":"ID",
    "sg:tags":[
        "trucking"
    ],
    "wof:name":"Blackburn Trucking",
    "wof:placetype":"venue"
},
  "geometry": {"coordinates":[-116.90921899999999,44.039635],"type":"Point"}
}