{
  "type": "Feature",
  "properties": {
    "iso:country":"US",
    "sg:address":"550 4th St",
    "sg:city":"Idaho Falls",
    "sg:classifiers":[
        {
            "category":"Professional",
            "subcategory":"Accounting & Tax Preparation",
            "type":"Services"
        }
    ],
    "sg:phone":"+1 208 529 8090",
    "sg:postcode":"83401",
    "sg:province":"ID",
    "sg:tags":[
        "return",
        "filing"
    ],
    "wof:name":"Data Tax Inc",
    "wof:placetype":"venue"
},
  "geometry": {"coordinates":[-112.022279,43.494159],"type":"Point"}
}