{
  "type": "Feature",
  "properties": {
    "iso:country":"US",
    "sg:address":"3340 S Denver Way",
    "sg:city":"Boise",
    "sg:classifiers":[
        {
            "category":"Freight",
            "type":"Transportation"
        }
    ],
    "sg:phone":"+1 208 345 3030",
    "sg:postcode":"83705",
    "sg:province":"ID",
    "sg:tags":[
        "mover"
    ],
    "wof:name":"North American Van Lines",
    "wof:placetype":"venue"
},
  "geometry": {"coordinates":[-116.19667,43.574749],"type":"Point"}
}