{
  "type": "Feature",
  "properties": {
    "addr:full":"1291 N Sandlin Ave Meridian ID 83642",
    "addr:housenumber":"1291",
    "addr:postcode":"83642",
    "addr:street":"N Sandlin Ave",
    "iso:country":"US",
    "sg:address":"1291 N Sandlin Ave",
    "sg:city":"Meridian",
    "sg:classifiers":[
        {
            "category":"Manufacturing",
            "subcategory":"Toys & Sporting Goods",
            "type":"Manufacturing & Wholesale Goods"
        }
    ],
    "sg:phone":"+1 208 898 9696",
    "sg:postcode":"83642",
    "sg:province":"ID",
    "sg:tags":[
        "mfg"
    ],
    "wof:name":"Young Scholars",
    "wof:placetype":"venue"
},
  "geometry": {"coordinates":[-116.380461,43.615054],"type":"Point"}
}