{
  "type": "Feature",
  "properties": {
    "iso:country":"US",
    "sg:address":"29777 US Hwy 95",
    "sg:city":"Athol",
    "sg:classifiers":[
        {
            "category":"Restaurant",
            "type":"Food & Drink"
        }
    ],
    "sg:phone":"+1 208 683 5049",
    "sg:postcode":"83801",
    "sg:province":"ID",
    "wof:name":"K K J's Pizza Place",
    "wof:placetype":"venue"
},
  "geometry": {"coordinates":[-116.698944,47.94067],"type":"Point"}
}