{
  "type": "Feature",
  "properties": {
    "addr:full":"4178 N 1000 E Buhl ID 83316",
    "addr:housenumber":"4178;1000 e",
    "addr:postcode":"83316",
    "addr:street":"N",
    "iso:country":"US",
    "sg:address":"4178 N 1000 E",
    "sg:city":"Buhl",
    "sg:classifiers":[
        {
            "category":"Building & Trades",
            "subcategory":"Landscaping Services",
            "type":"Services"
        }
    ],
    "sg:phone":"+1 208 543 2250",
    "sg:postcode":"83316",
    "sg:province":"ID",
    "sg:tags":[
        "landscape",
        "contractor"
    ],
    "wof:name":"Complete Landscaping Sprinkler",
    "wof:placetype":"venue"
},
  "geometry": {"coordinates":[-114.850897,42.608033],"type":"Point"}
}