{
  "type": "Feature",
  "properties": {
    "iso:country":"US",
    "sg:address":"160 N Main St",
    "sg:city":"Pocatello",
    "sg:classifiers":[
        {
            "category":"Building & Trades",
            "subcategory":"Construction",
            "type":"Services"
        }
    ],
    "sg:phone":"+1 208 238 1204",
    "sg:postcode":"83204",
    "sg:province":"ID",
    "sg:tags":[
        "home",
        "builder"
    ],
    "wof:name":"American Dream Home Builders",
    "wof:placetype":"venue"
},
  "geometry": {"coordinates":[-112.451053,42.862458],"type":"Point"}
}