{
  "type": "Feature",
  "properties": {
    "iso:country":"US",
    "sg:address":"13403 N Government Way",
    "sg:city":"Hayden Lake",
    "sg:classifiers":[
        {
            "category":"Manufacturing",
            "subcategory":"Lumber",
            "type":"Manufacturing & Wholesale Goods"
        }
    ],
    "sg:phone":"+1 208 772 4051",
    "sg:postcode":"83835",
    "sg:province":"ID",
    "sg:website":"www.lpcorp.com",
    "wof:name":"Louisiana-Pacific Corp",
    "wof:placetype":"venue"
},
  "geometry": {"coordinates":[-116.786632,47.800251],"type":"Point"}
}