{
  "type": "Feature",
  "properties": {
    "iso:country":"US",
    "sg:address":"797 E Anderson St",
    "sg:city":"Idaho Falls",
    "sg:classifiers":[
        {
            "category":"Organizations",
            "subcategory":"Religious Organization",
            "type":"Services"
        }
    ],
    "sg:phone":"+1 208 529 1079",
    "sg:postcode":"83401",
    "sg:province":"ID",
    "sg:tags":[
        "church"
    ],
    "wof:name":"Living Faith Christian Ctr",
    "wof:placetype":"venue"
},
  "geometry": {"coordinates":[-112.016092,43.51145],"type":"Point"}
}