{
  "type": "Feature",
  "properties": {
    "addr:full":"909 8th St Rupert ID 83350",
    "addr:housenumber":"909",
    "addr:postcode":"83350",
    "addr:street":"8Th St",
    "iso:country":"US",
    "sg:address":"909 8th St",
    "sg:city":"Rupert",
    "sg:classifiers":[
        {
            "category":"Organizations",
            "subcategory":"Religious Organization",
            "type":"Services"
        }
    ],
    "sg:phone":"+1 208 436 3413",
    "sg:postcode":"83350",
    "sg:province":"ID",
    "sg:tags":[
        "church"
    ],
    "wof:name":"Trinity Lutheran Church",
    "wof:placetype":"venue"
},
  "geometry": {"coordinates":[-113.680521,42.619552],"type":"Point"}
}