{
  "type": "Feature",
  "properties": {
    "iso:country":"US",
    "sg:address":"3293 N 10th Pl",
    "sg:city":"Coeur D Alene",
    "sg:classifiers":[
        {
            "category":"Wholesale",
            "subcategory":"Vending Machines",
            "type":"Manufacturing & Wholesale Goods"
        }
    ],
    "sg:phone":"+1 208 667 8146",
    "sg:postcode":"83815",
    "sg:province":"ID",
    "sg:tags":[
        "operator"
    ],
    "wof:name":"First Choice Vending",
    "wof:placetype":"venue"
},
  "geometry": {"coordinates":[-116.771035,47.707172],"type":"Point"}
}