{
  "type": "Feature",
  "properties": {
    "iso:country":"US",
    "sg:address":"16693 Oasis Rd",
    "sg:city":"Caldwell",
    "sg:classifiers":[
        {
            "category":"Home & Garden",
            "subcategory":"Furniture",
            "type":"Retail Goods"
        }
    ],
    "sg:phone":"+1 208 466 4586",
    "sg:postcode":"83607",
    "sg:province":"ID",
    "sg:tags":[
        "builder",
        "custom"
    ],
    "wof:name":"Mustache Flats",
    "wof:placetype":"venue"
},
  "geometry": {"coordinates":[-116.726249,43.807161],"type":"Point"}
}