{
  "type": "Feature",
  "properties": {
    "addr:full":"10706 W State St Star ID 83669",
    "addr:housenumber":"10706",
    "addr:postcode":"83669",
    "addr:street":"W State St",
    "iso:country":"US",
    "sg:address":"10706 W State St",
    "sg:city":"Star",
    "sg:classifiers":[
        {
            "category":"Restaurant",
            "type":"Food & Drink"
        }
    ],
    "sg:phone":"+1 208 286 7252",
    "sg:postcode":"83669",
    "sg:province":"ID",
    "sg:tags":[
        "shop",
        "coffee"
    ],
    "wof:name":"Lucky Star",
    "wof:placetype":"venue"
},
  "geometry": {"coordinates":[-116.48877299999999,43.692068],"type":"Point"}
}