{
  "type": "Feature",
  "properties": {
    "iso:country":"US",
    "sg:address":"202 W Seltice Way",
    "sg:city":"Post Falls",
    "sg:classifiers":[
        {
            "category":"Shopping",
            "subcategory":"Used Merchandise",
            "type":"Retail Goods"
        }
    ],
    "sg:phone":"+1 208 773 6836",
    "sg:postcode":"83854",
    "sg:province":"ID",
    "sg:tags":[
        "shop",
        "thrift"
    ],
    "wof:name":"St Vincent Books & More",
    "wof:placetype":"venue"
},
  "geometry": {"coordinates":[-116.950778,47.715221],"type":"Point"}
}