{
  "type": "Feature",
  "properties": {
    "iso:country":"US",
    "sg:address":"4101 Appaloosa Rd",
    "sg:city":"Coeur D Alene",
    "sg:classifiers":[
        {
            "category":"Retail",
            "subcategory":"Portrait Studio",
            "type":"Services"
        }
    ],
    "sg:phone":"+1 208 765 2795",
    "sg:postcode":"83815",
    "sg:province":"ID",
    "sg:tags":[
        "photo"
    ],
    "wof:name":"Tim Christie Photographer",
    "wof:placetype":"venue"
},
  "geometry": {"coordinates":[-116.83397600000001,47.708179],"type":"Point"}
}