{
  "type": "Feature",
  "properties": {
    "addr:full":"3616 E Rolling Green Pl Nampa ID 83687",
    "addr:housenumber":"3616",
    "addr:postcode":"83687",
    "addr:street":"E Rolling Green Pl",
    "iso:country":"US",
    "sg:address":"3616 E Rolling Green Pl",
    "sg:city":"Nampa",
    "sg:classifiers":[
        {
            "category":"Professional",
            "subcategory":"Detective & Security Services",
            "type":"Services"
        }
    ],
    "sg:phone":"+1 208 468 0044",
    "sg:postcode":"83687",
    "sg:province":"ID",
    "sg:tags":[
        "system"
    ],
    "wof:name":"One Stop Security",
    "wof:placetype":"venue"
},
  "geometry": {"coordinates":[-116.52681800000001,43.573862],"type":"Point"}
}