{
  "type": "Feature",
  "properties": {
    "iso:country":"US",
    "sg:address":"3703 Overland Rd",
    "sg:city":"Boise",
    "sg:classifiers":[
        {
            "category":"Personal",
            "subcategory":"Tattoo Parlor",
            "type":"Services"
        }
    ],
    "sg:phone":"+1 208 424 1465",
    "sg:postcode":"83705",
    "sg:province":"ID",
    "sg:tags":[
        "tattooing"
    ],
    "wof:name":"Krahnic Body Art",
    "wof:placetype":"venue"
},
  "geometry": {"coordinates":[-116.228585,43.589726],"type":"Point"}
}