{
  "type": "Feature",
  "properties": {
    "iso:country":"US",
    "sg:address":"200 E Carlton Ave",
    "sg:city":"Meridian",
    "sg:classifiers":[
        {
            "category":"Manufacturing",
            "subcategory":"Toys & Sporting Goods",
            "type":"Manufacturing & Wholesale Goods"
        }
    ],
    "sg:phone":"+1 208 288 5613",
    "sg:postcode":"83642",
    "sg:province":"ID",
    "sg:tags":[
        "athletic"
    ],
    "sg:website":"www.summitequipment.com",
    "wof:name":"Summit Equipment Co In",
    "wof:placetype":"venue"
},
  "geometry": {"coordinates":[-116.390137,43.613786],"type":"Point"}
}