{
  "type": "Feature",
  "properties": {
    "iso:country":"US",
    "sg:address":"102 S Plymouth Ave",
    "sg:city":"New Plymouth",
    "sg:classifiers":[
        {
            "category":"Food & Beverages",
            "subcategory":"Groceries & Convenience Stores",
            "type":"Retail Goods"
        }
    ],
    "sg:phone":"+1 208 278 3090",
    "sg:postcode":"83655",
    "sg:province":"ID",
    "sg:tags":[
        "grocer"
    ],
    "wof:name":"D J Pilgrim Market",
    "wof:placetype":"venue"
},
  "geometry": {"coordinates":[-116.819831,43.970203],"type":"Point"}
}