{
  "type": "Feature",
  "properties": {
    "iso:country":"US",
    "sg:address":"292 S 3rd St W",
    "sg:city":"Soda Springs",
    "sg:classifiers":[
        {
            "category":"Health Services",
            "subcategory":"Doctor",
            "type":"Services"
        }
    ],
    "sg:phone":"+1 208 547 3118",
    "sg:postcode":"83276",
    "sg:province":"ID",
    "sg:tags":[
        "clinic"
    ],
    "wof:name":"Lakeview Medical Clinic",
    "wof:placetype":"venue"
},
  "geometry": {"coordinates":[-111.613428,42.652672],"type":"Point"}
}