{
  "type": "Feature",
  "properties": {
    "iso:country":"US",
    "sg:address":"2700 Overland Ave",
    "sg:city":"Burley",
    "sg:classifiers":[
        {
            "category":"Government",
            "subcategory":"Office",
            "type":"Public Place"
        }
    ],
    "sg:phone":"+1 208 678 9492",
    "sg:postcode":"83318",
    "sg:province":"ID",
    "sg:tags":[
        "federal",
        "govt"
    ],
    "wof:name":"US Bonneville Power Adm",
    "wof:placetype":"venue"
},
  "geometry": {"coordinates":[-113.79323599999999,42.518506],"type":"Point"}
}