{
  "type": "Feature",
  "properties": {
    "iso:country":"US",
    "sg:address":"3350 W Americana Ter",
    "sg:city":"Boise",
    "sg:classifiers":[
        {
            "category":"Professional",
            "subcategory":"Management & Consulting",
            "type":"Services"
        }
    ],
    "sg:phone":"+1 208 336 3212",
    "sg:postcode":"83706",
    "sg:province":"ID",
    "wof:name":"Davis Wees Longwith",
    "wof:placetype":"venue"
},
  "geometry": {"coordinates":[-116.22666,43.616663],"type":"Point"}
}