{
  "type": "Feature",
  "properties": {
    "iso:country":"US",
    "sg:address":"213 11th Ave S",
    "sg:city":"Nampa",
    "sg:classifiers":[
        {
            "category":"Insurance",
            "subcategory":"Insurance Agent",
            "type":"Services"
        }
    ],
    "sg:phone":"+1 208 461 2202",
    "sg:postcode":"83651",
    "sg:province":"ID",
    "wof:name":"Allstate Insurance",
    "wof:placetype":"venue"
},
  "geometry": {"coordinates":[-116.561968,43.578774],"type":"Point"}
}