{
  "type": "Feature",
  "properties": {
    "addr:full":"213 11th Ave S Nampa ID 83651",
    "addr:housenumber":"213",
    "addr:postcode":"83651",
    "addr:street":"11Th Ave S",
    "iso:country":"US",
    "sg:address":"213 11th Ave S",
    "sg:city":"Nampa",
    "sg:classifiers":[
        {
            "category":"Insurance",
            "subcategory":"Insurance Agent",
            "type":"Services"
        }
    ],
    "sg:phone":"+1 208 461 2202",
    "sg:postcode":"83651",
    "sg:province":"ID",
    "wof:name":"Allstate Insurance",
    "wof:placetype":"venue"
},
  "geometry": {"coordinates":[-116.56196799999999,43.578774],"type":"Point"}
}