{
  "type": "Feature",
  "properties": {
    "iso:country":"US",
    "sg:address":"460 Cleveland St",
    "sg:city":"Idaho Falls",
    "sg:classifiers":[
        {
            "category":"Shopping",
            "subcategory":"Hobbies, Toys, & Games",
            "type":"Retail Goods"
        }
    ],
    "sg:phone":"+1 208 524 5552",
    "sg:postcode":"83401",
    "sg:province":"ID",
    "wof:name":"Sunrise Kites",
    "wof:placetype":"venue"
},
  "geometry": {"coordinates":[-112.024762,43.499537],"type":"Point"}
}