{
  "type": "Feature",
  "properties": {
    "addr:full":"740 Warm Springs Ave Boise ID 83712",
    "addr:housenumber":"740",
    "addr:postcode":"83712",
    "addr:street":"Warm Springs Ave",
    "iso:country":"US",
    "sg:address":"740 Warm Springs Ave",
    "sg:city":"Boise",
    "sg:classifiers":[
        {
            "category":"Organizations",
            "subcategory":"Non-profit Organization",
            "type":"Services"
        }
    ],
    "sg:phone":"+1 208 343 7813",
    "sg:postcode":"83712",
    "sg:province":"ID",
    "sg:website":"www.childrenshomesociety.com",
    "wof:name":"Childrens Home Society-Idaho",
    "wof:placetype":"venue"
},
  "geometry": {"coordinates":[-116.186792,43.609006],"type":"Point"}
}