{
  "type": "Feature",
  "properties": {
    "addr:full":"418 S River St Hailey ID 83333",
    "addr:housenumber":"418",
    "addr:postcode":"83333",
    "addr:street":"S River St",
    "iso:country":"US",
    "sg:address":"418 S River St",
    "sg:city":"Hailey",
    "sg:classifiers":[
        {
            "category":"Professional",
            "type":"Services"
        }
    ],
    "sg:phone":"+1 208 788 9097",
    "sg:postcode":"83333",
    "sg:province":"ID",
    "sg:tags":[
        "establishment"
    ],
    "wof:name":"Marketing Success",
    "wof:placetype":"venue"
},
  "geometry": {"coordinates":[-114.31368000000001,43.515315],"type":"Point"}
}