{
  "type": "Feature",
  "properties": {
    "iso:country":"US",
    "sg:address":"517 S 14th St",
    "sg:city":"Boise",
    "sg:classifiers":[
        {
            "category":"Professional",
            "subcategory":"Management & Consulting",
            "type":"Services"
        }
    ],
    "sg:phone":"+1 208 336 6918",
    "sg:postcode":"83702",
    "sg:province":"ID",
    "sg:tags":[
        "business"
    ],
    "wof:name":"John Wennstrom Consulting",
    "wof:placetype":"venue"
},
  "geometry": {"coordinates":[-116.215328,43.616217],"type":"Point"}
}