{
  "type": "Feature",
  "properties": {
    "iso:country":"US",
    "sg:address":"102 Sunnyside Dr",
    "sg:city":"Caldwell",
    "sg:classifiers":[
        {
            "category":"Building & Trades",
            "subcategory":"Construction",
            "type":"Services"
        }
    ],
    "sg:phone":"+1 208 459 1764",
    "sg:postcode":"83605",
    "sg:province":"ID",
    "sg:tags":[
        "well",
        "drilling"
    ],
    "wof:name":"Ransom Rod",
    "wof:placetype":"venue"
},
  "geometry": {"coordinates":[-116.698204,43.661811],"type":"Point"}
}