{
  "type": "Feature",
  "properties": {
    "iso:country":"US",
    "sg:address":"1413 Rand St",
    "sg:city":"Boise",
    "sg:classifiers":[
        {
            "category":"Professional",
            "subcategory":"Management & Consulting",
            "type":"Services"
        }
    ],
    "sg:phone":"+1 208 377 1440",
    "sg:postcode":"83709",
    "sg:province":"ID",
    "sg:tags":[
        "business"
    ],
    "wof:name":"Greg Kaltenecker",
    "wof:placetype":"venue"
},
  "geometry": {"coordinates":[-116.258059,43.591004],"type":"Point"}
}