{
  "type": "Feature",
  "properties": {
    "addr:full":"720 Park Blvd Boise ID 83712",
    "addr:housenumber":"720",
    "addr:postcode":"83712",
    "addr:street":"Park Blvd",
    "iso:country":"US",
    "sg:address":"720 Park Blvd",
    "sg:city":"Boise",
    "sg:classifiers":[
        {
            "category":"Professional",
            "type":"Services"
        }
    ],
    "sg:phone":"+1 208 338 9984",
    "sg:postcode":"83712",
    "sg:province":"ID",
    "sg:tags":[
        "establishment"
    ],
    "wof:name":"LCA",
    "wof:placetype":"venue"
},
  "geometry": {"coordinates":[-116.19045800000001,43.604073],"type":"Point"}
}