{
  "type": "Feature",
  "properties": {
    "addr:full":"20478 N Main St Carey ID 83320",
    "addr:housenumber":"20478",
    "addr:postcode":"83320",
    "addr:street":"N Main St",
    "iso:country":"US",
    "sg:address":"20478 N Main St",
    "sg:city":"Carey",
    "sg:phone":"+1 208 823 4014",
    "sg:postcode":"83320",
    "sg:province":"ID",
    "sg:tags":[
        "irrigation",
        "company"
    ],
    "wof:name":"Little Wood River Irrigation",
    "wof:placetype":"venue"
},
  "geometry": {"coordinates":[-113.94586200000001,43.309276],"type":"Point"}
}