{
  "type": "Feature",
  "properties": {
    "iso:country":"US",
    "sg:address":"1216 Broadway Ave",
    "sg:city":"Boise",
    "sg:classifiers":[
        {
            "category":"Retail",
            "subcategory":"Veterinary Services",
            "type":"Services"
        }
    ],
    "sg:phone":"+1 208 344 5592",
    "sg:postcode":"83706",
    "sg:province":"ID",
    "sg:tags":[
        "veterinarian"
    ],
    "wof:name":"Broadway Veterinary Hospital",
    "wof:placetype":"venue"
},
  "geometry": {"coordinates":[-116.193522,43.597347],"type":"Point"}
}