{
  "type": "Feature",
  "properties": {
    "iso:country":"US",
    "sg:address":"90 S 9th St",
    "sg:city":"Payette",
    "sg:classifiers":[
        {
            "category":"Recreation",
            "type":"Entertainment"
        }
    ],
    "sg:phone":"+1 208 642 4883",
    "sg:postcode":"83661",
    "sg:province":"ID",
    "sg:tags":[
        "historical"
    ],
    "wof:name":"Payette County Historical Soc",
    "wof:placetype":"venue"
},
  "geometry": {"coordinates":[-116.93358000000001,44.073836],"type":"Point"}
}