{
  "type": "Feature",
  "properties": {
    "iso:country":"US",
    "sg:address":"700 Yakima St",
    "sg:city":"Filer",
    "sg:classifiers":[
        {
            "category":"Food & Beverages",
            "subcategory":"Specialty",
            "type":"Retail Goods"
        }
    ],
    "sg:phone":"+1 208 326 4093",
    "sg:postcode":"83321",
    "sg:province":"ID",
    "wof:name":"Haertfelt Treasures",
    "wof:placetype":"venue"
},
  "geometry": {"coordinates":[-114.60769000000001,42.564766],"type":"Point"}
}