{
  "type": "Feature",
  "properties": {
    "addr:full":"1453 W Hays St Boise ID 83702",
    "addr:housenumber":"1453",
    "addr:postcode":"83702",
    "addr:street":"W Hays St",
    "iso:country":"US",
    "sg:address":"1453 W Hays St",
    "sg:city":"Boise",
    "sg:classifiers":[
        {
            "category":"Health Services",
            "subcategory":"Doctor",
            "type":"Services"
        }
    ],
    "sg:phone":"+1 208 345 6287",
    "sg:postcode":"83702",
    "sg:province":"ID",
    "sg:tags":[
        "dentist"
    ],
    "wof:name":"Eagle Orthodontics",
    "wof:placetype":"venue"
},
  "geometry": {"coordinates":[-116.206166,43.624778],"type":"Point"}
}