{
  "type": "Feature",
  "properties": {
    "iso:country":"US",
    "sg:address":"126 E Main St",
    "sg:city":"Grangeville",
    "sg:classifiers":[
        {
            "category":"Shopping",
            "type":"Retail Goods"
        }
    ],
    "sg:phone":"+1 208 983 3095",
    "sg:postcode":"83530",
    "sg:province":"ID",
    "sg:tags":[
        "pet",
        "food",
        "supply"
    ],
    "wof:name":"Selwae Shoppe",
    "wof:placetype":"venue"
},
  "geometry": {"coordinates":[-116.119664,45.925605],"type":"Point"}
}