{
  "type": "Feature",
  "properties": {
    "addr:full":"650 E 900 N Rupert ID 83350",
    "addr:housenumber":"650",
    "addr:postcode":"83350",
    "addr:street":"E 900 N",
    "iso:country":"US",
    "sg:address":"650 E 900 N",
    "sg:city":"Rupert",
    "sg:classifiers":[
        {
            "category":"Farming",
            "subcategory":"Dairy Farm",
            "type":"Manufacturing & Wholesale Goods"
        }
    ],
    "sg:phone":"+1 208 531 5691",
    "sg:postcode":"83350",
    "sg:province":"ID",
    "wof:name":"Brent Wilson",
    "wof:placetype":"venue"
},
  "geometry": {"coordinates":[-113.54046200000001,42.749472],"type":"Point"}
}