{
  "type": "Feature",
  "properties": {
    "iso:country":"US",
    "sg:address":"2007 N Monaco Way",
    "sg:city":"Meridian",
    "sg:classifiers":[
        {
            "category":"Building & Trades",
            "subcategory":"Construction",
            "type":"Services"
        }
    ],
    "sg:phone":"+1 208 377 4455",
    "sg:postcode":"83646",
    "sg:province":"ID",
    "sg:tags":[
        "contractor"
    ],
    "wof:name":"Valley Drywall Systems",
    "wof:placetype":"venue"
},
  "geometry": {"coordinates":[-116.41868100000001,43.623042],"type":"Point"}
}