{
  "type": "Feature",
  "properties": {
    "addr:full":"599 E 44th St Boise ID 83714",
    "addr:housenumber":"599",
    "addr:postcode":"83714",
    "addr:street":"E 44Th St",
    "iso:country":"US",
    "sg:address":"599 E 44th St",
    "sg:city":"Boise",
    "sg:classifiers":[
        {
            "category":"Wholesale",
            "subcategory":"Hardware",
            "type":"Manufacturing & Wholesale Goods"
        }
    ],
    "sg:phone":"+1 208 375 3644",
    "sg:postcode":"83714",
    "sg:province":"ID",
    "sg:tags":[
        "equipment",
        "energy",
        "solar"
    ],
    "wof:name":"Solar Cascade",
    "wof:placetype":"venue"
},
  "geometry": {"coordinates":[-116.248003,43.638373],"type":"Point"}
}