{
  "type": "Feature",
  "properties": {
    "iso:country":"US",
    "sg:address":"1200 W Ironwood Dr",
    "sg:city":"Coeur D Alene",
    "sg:classifiers":[
        {
            "category":"Health Services",
            "subcategory":"Doctor",
            "type":"Services"
        }
    ],
    "sg:phone":"+1 208 666 1481",
    "sg:postcode":"83814",
    "sg:province":"ID",
    "sg:tags":[
        "physician",
        "surgeon"
    ],
    "wof:name":"North Idaho Allergy Asthma",
    "wof:placetype":"venue"
},
  "geometry": {"coordinates":[-116.800514,47.696507],"type":"Point"}
}