{
  "type": "Feature",
  "properties": {
    "iso:country":"US",
    "sg:address":"913 S Latah St",
    "sg:city":"Boise",
    "sg:classifiers":[
        {
            "category":"Professional",
            "subcategory":"Advertising",
            "type":"Services"
        }
    ],
    "sg:phone":"+1 208 336 6526",
    "sg:postcode":"83705",
    "sg:province":"ID",
    "wof:name":"Auto Shopper",
    "wof:placetype":"venue"
},
  "geometry": {"coordinates":[-116.228653,43.595339],"type":"Point"}
}